Workbook

Sheet ESTRATÈGIA
C3: ESQUEMA CONCEPTUAL PER A LA ELABORACIÓ DEL PLA ESTRATÈGIC EN EL MARC
C4: DELS ESTÀNDARDS OBERTS PER A LA GESTIÓ ADAPTATIVA A CATALUNYA

Sheet INSTRUCCIONS
A1: PESTANYA DE PRIORITZACIÓ
A2: Llistat elements: | B2: Tasca 1: Revisar el llistat d'elements prioritzats per tal d'avaluar si cal afegir-ne algun o treure'n algun. A la columna comentaris cal argumentar, breument, el perquè de la decisió.
A4: Llistat amenaces: | B4: Tasca 2: A partir de la taxonomia d'amenaces que es troba a la pestanya final, cal omplir les tres columnes (E, F i G) amb les tres principals amenaces per a la conservació de l'element. S'afegeixi una darrera columna per si hi ha amenaces que no es troben incloses a la taxonomia.
A6: PESTANYA DEL PLA
A7: Explicacions:
B8: 7 Eixos temàtics: NATURA, CULTURA, CONEIXEMENT, DESENVOLUPAMENT LOCAL, ÚS PÚBLIC I SOCIAL, EDUCACIÓ, VOLUNTARIAT I COMUNICACIÓ, GESTIÓ I ADMINISTRACIÓ
B9: Els objectius generals estan directament associats als objectius generals dels Plans de Protecció del medi natural i del paisatge. NO ES PODEN RETOCAR
B10: Objectius estratègics: definits en un grup de treball intern de serveis Centrals i dels Parcs durant l'any 2023. NO ES PODEN RETOCAR
B11: Objectius operacionals: definits en un grup de treball intern de serveis Centrals i dels Parcs durant l'any 2023
A14: Tasques a realitzar:
A15: Objectius operacionals: | B15: El llistat d'objectius operacionals té una columna al costat (columna I) on s'indica si l'objectiu és obligatori de mantenir al Pla estratègic o no.
B16: Tasca 1: Columna I. Revisar els que es posa com a obligatoris per veure si són realment aplicables a l'espai o no.
B17: Tasca 2: Columna I. Revisar els que posa "Optatiu" per identificar els que són aplicables o no a l'espai. O, també, determinar si algun d'ells seria aplicable o es pot concretar millor el redactat de l'objectiu.
B18: Tasca 3: Columna J. En ambdós casos, cal posar a la columna J, el redactat final de l'objectiu concretat a l'espai. En el cas de que l'objectiu s'elimina, posar "NA". Ara es reprodueix el redactat dels objectius operacionals derivats del grup de treball esmentat
B19: Tasca 4: Columna K. Per tots els casos en que hi ha modificació respecte al redactat original de l'objectiu operatiu -i, també, en el cas que es consideri que s'ha d'eliminar-, a la columna K cal redactar molt breument el motiu pel qual es prèn la decisió.
B20: Tasca 5: Columna L. Incloure un Si/No avaluant si l'objectiu operatiu podria tenir mesures a incorporar a la programació d'actuacions de l'espai (Si) o, per altra banda, el seu assoliment depèn d'altres òrgans, com l'ACA o altres serveis dins la DGPAMN (No).
B21: Tasca 6: Columna M. Definir la prioritat que hauria de tenir l'assoliment de l'objectiu (màxima, si cal assolir en els propers 4 anys, o altrament alta, mitja o baixa). També hi ha l'opció de prioritat a assolir a més llarg termini.
A22: Propostes genèriques d'accions: | B22: Tasca 7: Columna N. En aquesta columna cal introduir les accions, de manera genèrica, que caldria aplicar a l'espai per tal d'assolir l'objectiu operatiu. No es tracta d'un llistat d'accions concretes si no, més aviat, accions generals que acabarien concretant-se en la programació anual. PER A INICIAR AMB LA TAULA US PODEU BASAR MOLT EN LA FEINA JA FETA DE PRIORITZACIÓ DE MESURES PEL MAP
B23: En el cas dels objectius operatius que s'ha considerat que no són aplicables a l'espai, cal avaluar si podrien tenir alguna acció que sí tindria sentit d'incloure al Pla estratègic tot i que l'objectiu de manera global no hi seria d'aplicació.
A24: Indicadors: | B24: Tasca 8: Columna Q. Posar un indicador SMART per avaluar el compliment de la mesura proposada a la columna N | C24: Qualitatius o quantitatius
A25: Fites a assolir en 4 anys: | B25: Tasca 9: Posar un valor de l'indicador a assolir: valor mínim necessari (columna R) o valor desitjable (columna S).
A26: Hores de dedicació: | B26: Tasca 10: Columna T. Realitzar una aproximació el més acurada que es pugui de les hores del personal de gestió de l'espai que cal destinar per a la realització de l'acció.
A27: Àrea responsable: | B27: Tasca 11: Columna U. Indicar quina àrea de l'equip de gestió és responsable de coordinar l'execució de l'acció.
A28: Persona responsable: | B28: Tasca 12: Columna V. Indicar quina persona dins l'àrea seria l'encarregada.
A30: PESTANYA DEL VINCLE
A31: Definir vincle amenaça vs. Obj. Operatiu | B31: Tasca 1: Establir / Revisar el vincle entre les amenaces identificades a la pestanya de priorització i els objectius operatius definits a la columna J de la pestanya Pla. La columna B conté el llistat dels objectius operatius tal i com quedaran definits després de la vostra revisió.
B32: Tasca 2: En cas que es pugui, definir l'amenaça / factor / causa concret a la que atén l'objectiu definit al Pla. Poden ser més d'una.
B33: És important que es visualitzi a quina amenaça es dirigeix l'objectiu operatiu que es proposa al Pla, tot i que, no sempre hi ha d'haver un vincle clar. Pot haver-hi algun objectiu sense amenaça vinculada.

Sheet PRIORITZACIÓ
A1: Element prioritzat a la proposta inicial | B1: canvi a no | C1: Element prioritzat | D1: Hàbitat no present al PNIN/Ni surt a la nostra llista
B2: manté o afegim a sí | D2: No surt prioritzat amb els nostres criteris
B3: Dubtós | D3: Ens surt prioritzat amb els nostres criteris
A4: Llistats corresponent a l'espai de Natura 2000 ES5120014"L'Albera"
A5: LLISTAT D'ELEMENTS PRESENT A L'ESPAI | E5: AMENACES PER A CADA ELEMENT
A6: Hàbitats d'interès comunitari | B6: Prioritzat | C6: Puntuació índex rellevància | D6: Comentaris en cas de canvi en la priorització | E6: Amenaça 1 segons taxonomia | F6: Amenaça 2 segons taxonomia | G6: Amenaça 3 segons taxonomia | H6: Altres amenaces
A7: 1120p - Alguers de posidònia | B7: No | D7: Hàbitat no present al PNIN | J7: Nota: La priorització d'elements actual inclou els Elements Clau que es van determinar en l'instrument de gestió aprovat amb l'Acord de Govern 150/2014 (Annex 6)
A8: 1170 - Fons marins rocosos i concrecions biogèniques sublitorals | B8: No | D8: Hàbitat no present al PNIN | J8: Aquest Acord era per les Zones Especials de Conservació, no per les ZEPA i, per tant, no es va fer l'exercici de priorització de les aus.
A9: 1240 - Penya-segats de les costes mediterrànies colonitzats per vegetació, amb ensopegueres (Limonium spp.) endèmiques | B9: No | C9: 4.125 | D9: Hàbitat no present al PNIN | J9: També inclou el primer quartil de l'exercici de la UIC per prioritzar els elements present a cada espai de Natura 2000, és a dir, el 25% dels
A10: 2110 - Dunes movents embrionàries | B10: No | D10: Hàbitat no present al PNIN | J10: elements amb major índex de rellevància a l'espai. Veure document metodològic aquí:
A11: 2120 - Dunes movents del cordó litoral, amb borró (Ammophila arenaria) | B11: No | D11: Hàbitat no present al PNIN | J11: https://gencat.sharepoint.com/sites/Informaciiconeixementpatrimoninatural2/Documents%20compartits/Forms/AllItems.aspx?csf=1&web=1&e=3x4ZkK&ovuser=3b9427dc%2Dd30e%2D43bc%2D8c06%2Dff7253676fec%2Cjordiparpal%40gencat%2Ecat&OR=Teams%2DHL&CT=1713942253212&clic
A12: 3170p - Basses i tolls temporers mediterranis | B12: Si | E12: Ramaderia | F12: Activitat agrícola | G12: Impactes del canvi climàtic relatius a l'alteració del règim de precipitació i sequera | H12: Producció d'energia renovable | J12: El llistat original d'elements prové de les taules del MAP que heu estat treballant amb el SENP
A13: 3250 - Rius mediterranis amb vegetació del Glaucion flavi | B13: No
A14: 3260 - Rius de terra baixa i de la muntanya mitjana amb vegetació submersa o parcialment flotant (Ranunculion fluitantis i Callitricho-Batrachion) | B14: No
A15: 3270 - Rius amb vores llotoses colonitzades per herbassars nitròfils del Chenopodion rubri (p.p.) i del Bidention (p.p.) | B15: No
A16: 3290 - Rius mediterranis intermitents, amb gespes nitròfiles del Paspalo-Agrostidion | B16: No | D16: No surt prioritzat amb els nostres criteris
A17: 6420 - Jonqueres i herbassars graminoides humits, mediterranis, del Molinio-Holoschoenion | B17: No | C17: 3.625 | D17: No surt prioritzat amb els nostres criteris
A18: 6510 - Prats de dall de terra baixa i de la muntanya mitjana (Arrhenatherion) | B18: No | C18: 3.375 | D18: No surt prioritzat amb els nostres criteris, ni és present al PNIN.
A19: 8130 - Tarteres de l'Europa meridional amb vegetació poc o molt termòfila | B19: No
A20: 8220 - Costers rocosos silicis amb vegetació rupícola | B20: No | C20: 2.875 | D20: Hàbitat no present al PNIN
A21: 9120 - Fagedes acidòfiles | B21: No | C21: 3.875 | D21: No surt prioritzat amb els nostres criteris
A22: 91E0p - Vernedes i altres boscos de ribera afins (Alno-Padion) | B22: Si | C22: 3.625 | E22: Impactes del canvi climàtic relatius a l'alteració del règim de precipitació i sequera | F22: Gestió de l'aigua | G22: Treballs forestals
A23: 9260 - Castanyedes | B23: No
A24: 92A0 - Alberedes, salzedes i altres boscos de ribera | B24: No
A25: 92D0 - Bosquines i matollars meridionals de rambles, rieres i llocs humits (Nerio-Tamaricetea) | B25: No | C25: 4.75 | D25: No surt prioritzat amb els nostres criteris
A26: 9330 - Suredes | B26: Si | C26: 3.875 | E26: Impactes del canvi climàtic relatius a l'alteració del règim de precipitació i sequera | F26: Ramaderia | G26: Treballs forestals | H26: Incendis
A27: 9340 - Alzinars i carrascars | B27: No | C27: 4 | D27: No surt prioritzat amb els nostres criteris
A28: 9380 - Grevoledes | B28: Si | E28: Impactes del canvi climàtic relatius a l'alteració del règim de precipitació i sequera | F28: Impactes del canvi climàtic relatius a l'alteració del règim de temperatures | G28: Recol·lecció de vegetals | H28: Treballs forestals
A29: 9540 - Pinedes mediterrànies | B29: No
A30: Espècies presents a l'espai | B30: Prioritzat | C30: Puntuació índex rellevància | D30: Comentaris en cas de canvi en la priorització | E30: Amenaça 1 segons taxonomia | F30: Amenaça 2 segons taxonomia | G30: Amenaça 3 segons taxonomia | H30: Altres amenaces
A31: Accipiter gentilis gentilis | B31: No
A32: Alcedo atthis | B32: No
A33: Alectoris rufa | B33: Dubtós | C33: 2 | D33: No surt prioritzat amb els nostres criteris
A34: Alytes obstetricans | B34: No
A35: Anas platyrhynchos | B35: No
A36: Anthus campestris | B36: No
A37: Aquila chrysaetos | B37: Si | D37: Ens surt prioritzat amb els nostres criteris | E37: Molèsties per activitats recreatives | F37: Producció d'energia renovable
A38: Aquila fasciata | B38: Si | C38: 2.111 | E38: Molèsties per activitats recreatives | F38: Producció d'energia renovable
A39: Austropotamobius pallipes | B39: Si | C39: 1.833 | E39: Impactes del canvi climàtic relatius a l'alteració del règim de precipitació i sequera | F39: Gestió de l'aigua | G39: Espècies invasores
A40: Barbastella barbastellus | B40: Si | D40: Ens surt prioritzat amb els nostres criteris | E40: Producció d'energia renovable
A41: Barbus meridionalis | B41: Si | C41: 1.5 | E41: Impactes del canvi climàtic relatius a l'alteració del règim de precipitació i sequera | F41: Gestió de l'aigua
A42: Bubo bubo | B42: No
A43: Buteo buteo | B43: No
A44: Calandrella brachydactyla | B44: No | C44: 2.333 | D44: No surt prioritzat amb els nostres criteris, i fora de PNIN
A45: Canis lupus | B45: Si | D45: Ens surt prioritzat amb els nostres criteris | E45: Ramaderia | F45: Caça i recol·lecció d'animals
A46: Caprimulgus europaeus | B46: No
A47: Cerambyx cerdo | B47: Si | E47: Impactes del canvi climàtic relatius a l'alteració del règim de precipitació i sequera | F47: Gestió d'hàbitats
A48: Certhia brachydactyla all others | B48: No
A49: Cinclus cinclus | B49: Si | E49: Gestió de l'aigua
A50: Circaetus gallicus | B50: No
A51: Circus cyaneus | B51: No
A52: Circus pygargus | B52: No
A53: Columba palumbus palumbus | B53: No
A54: Coracias garrulus | B54: No
A55: Coturnix coturnix | B55: No
A56: Dryocopus martius | B56: No
A57: Emberiza hortulana | B57: No | I57: No es coneixen cites d'aquesta espècie a l'espai
A58: Euphydryas aurinia | B58: No
A59: Falco columbarius | B59: No
A60: Falco naumanni | B60: No
A61: Falco peregrinus | B61: No
A62: Falco subbuteo | B62: No
A63: Falco tinnunculus | B63: No
A64: Felis silvestris | B64: Si | D64: Ens surt prioritzat amb els nostres criteris | E64: Introducció de genotips aliens
A65: Fringilla coelebs all others | B65: No
A66: Fulica atra | B66: No
A67: Galerida cristata | B67: No
A68: Galerida theklae | B68: No | C68: 1.556 | D68: No surt prioritzat amb els nostres criteris
A69: Gallinula chloropus | B69: No
A70: Glis glis | B70: No | D70: No surt prioritzat, però en fem seguiment
A71: Hericium erinaceus | B71: Si | D71: Ens surt prioritzat amb els nostres criteris | E71: Recol·lecció de vegetals | F71: Gestió d'hàbitats
A72: Hieraaetus pennatus | B72: No
A73: Hippolais polyglotta | B73: No | C73: 1.5 | D73: No surt prioritzat amb els nostres criteris
A74: Hoplia coerulea | B74: Si | D74: Ens surt prioritzat amb els nostres criteris | E74: Gestió d'hàbitats
A75: Hydrocotyle vulgaris | B75: No | D75: No surt prioritzat amb els nostres criteris
A76: Isoetes durieui | B76: Si | D76: Ens surt prioritzat amb els nostres criteris | E76: Impactes del canvi climàtic relatius a l'alteració del règim de precipitació i sequera | F76: Ramaderia | G76: Activitat agrícola | H76: Gestió de l'aigua
A77: Jynx torquilla | B77: No | C77: 1.5 | D77: No surt prioritzat amb els nostres criteris
A78: Kurzia sylvatica | B78: No | D78: No surt prioritzat amb els nostres criteris
A79: Lacerta bilineata | B79: Si | C79: 1.667 | E79: No especificada
A80: Lanius collurio | B80: No
A81: Lanius excubitor meridionalis | B81: No
A82: Lanius senator | B82: No | C82: 2 | D82: No surt prioritzat amb els nostres criteris
A83: Larus michahellis | B83: No
A84: Larus ridibundus | B84: No
A85: Linaria cannabina | B85: No | C85: 1.667 | D85: No surt prioritzat amb els nostres criteris
A86: Lucanus cervus | B86: Si | D86: Ens surt prioritzat amb els nostres criteris | E86: Impactes del canvi climàtic relatius a l'alteració del règim de precipitació i sequera | F86: Gestió d'hàbitats
A87: Lullula arborea | B87: No | C87: 1.5 | D87: No surt prioritzat amb els nostres criteris
A88: Lutra lutra | B88: No
A89: Marsilea strigosa | B89: Si | D89: Ens surt prioritzat amb els nostres criteris | E89: Impactes del canvi climàtic relatius a l'alteració del règim de precipitació i sequera | F89: Ramaderia | G89: Activitat agrícola
A90: Mauremys leprosa | B90: Si | E90: Impactes del canvi climàtic relatius a l'alteració del règim de precipitació i sequera | F90: Gestió de l'aigua
A91: Melanargia occitanica | B91: Si | D91: Ens surt prioritzat amb els nostres criteris | E91: No especificada
A92: Merops apiaster | B92: No
A93: Miniopterus schreibersii | B93: Si | C93: 1.5 | E93: Producció d'energia renovable
A94: Muscicapa striata | B94: No | C94: 1.833 | D94: No surt prioritzat amb els nostres criteris
A95: Mustela putorius | B95: Si | C95: 2 | D95: No surt prioritzat amb els nostres criteris | E95: Vials de transport | F95: Espècies invasores
A96: Myotis alcathoe | B96: Si | C96: 2.167 | D96: No surt prioritzat amb els nostres criteris | E96: Producció d'energia renovable | F96: Impactes del canvi climàtic relatius a l'alteració del règim de precipitació i sequera | G96: Impactes del canvi climàtic relatius a l'alteració del règim de temperatures | H96: Treballs forestals
A97: Myotis bechsteinii | B97: Si | C97: 1.667 | E97: Producció d'energia renovable
A98: Myotis blythii | B98: Si | C98: 2.167 | E98: Producció d'energia renovable
A99: Myotis daubentonii | B99: No | C99: 1.5 | D99: No surt prioritzat amb els nostres criteris
A100: Myotis emarginatus | B100: Si | C100: 2.167 | E100: Producció d'energia renovable
...

Sheet Full2
A3: Hàbitats d'interès comunitari | B3: Amenaça 1 | C3: Amenaça 2 | D3: Amenaça 3 | E3: Altres amenaces
A4: 3170p - Basses i tolls temporers mediterranis | B4: Ramaderia | C4: Activitat agrícola | D4: Impactes del canvi climàtic relatius a l'alteració del règim de precipitació i sequera
A5: 91E0p - Vernedes i altres boscos de ribera afins (Alno-Padion) | B5: Impactes del canvi climàtic relatius a l'alteració del règim de precipitació i sequera | C5: Gestió de l'aigua | D5: Treballs forestals
A6: 9330 - Suredes | B6: Impactes del canvi climàtic relatius a l'alteració del règim de precipitació i sequera | C6: Ramaderia | D6: Treballs forestals | E6: Incendis
A7: 9380 - Grevoledes | B7: Impactes del canvi climàtic relatius a l'alteració del règim de precipitació i sequera | C7: Impactes del canvi climàtic relatius a l'alteració del règim de temperatures | D7: Recol·lecció de vegetals | E7: Treballs forestals
A8: Espècies presents a l'espai | B8: Amenaça 1 | C8: Amenaça 2 | D8: Amenaça 3 | E8: Altres amenaces
A9: Aquila chrysaetos | B9: Molèsties per activitats recreatives | C9: Producció d'energia renovable
A10: Aquila fasciata | B10: Molèsties per activitats recreatives | C10: Producció d'energia renovable
A11: Austropotamobius pallipes | B11: Impactes del canvi climàtic relatius a l'alteració del règim de precipitació i sequera | C11: Gestió de l'aigua | D11: Espècies invasores
A12: Barbastella barbastellus | B12: Producció d'energia renovable
A13: Barbus meridionalis | B13: Impactes del canvi climàtic relatius a l'alteració del règim de precipitació i sequera | C13: Gestió de l'aigua
A14: Canis lupus | B14: Ramaderia | C14: Caça i recol·lecció d'animals
A15: Cerambyx cerdo | B15: Impactes del canvi climàtic relatius a l'alteració del règim de precipitació i sequera | C15: Gestió d'hàbitats
A16: Cinclus cinclus | B16: Gestió de l'aigua
A17: Felis silvestris | B17: Introducció de genotips aliens
A18: Hericium erinaceus | B18: Recol·lecció de vegetals | C18: Gestió d'hàbitats
A19: Hoplia coerulea | B19: Gestió d'hàbitats
A20: Isoetes durieui | B20: Impactes del canvi climàtic relatius a l'alteració del règim de precipitació i sequera | C20: Ramaderia | D20: Activitat agrícola | E20: Gestió de l'aigua
A21: Lacerta bilineata | B21: No especificada
A22: Lucanus cervus | B22: Impactes del canvi climàtic relatius a l'alteració del règim de precipitació i sequera | C22: Gestió d'hàbitats
A23: Marsilea strigosa | B23: Impactes del canvi climàtic relatius a l'alteració del règim de precipitació i sequera | C23: Ramaderia | D23: Activitat agrícola
A24: Mauremys leprosa | B24: Impactes del canvi climàtic relatius a l'alteració del règim de precipitació i sequera | C24: Gestió de l'aigua
A25: Melanargia occitanica | B25: No especificada
A26: Miniopterus schreibersii | B26: Producció d'energia renovable
A27: Mustela putorius | B27: Vials de transport | C27: Espècies invasores
A28: Myotis alcathoe | B28: Producció d'energia renovable | C28: Impactes del canvi climàtic relatius a l'alteració del règim de precipitació i sequera | D28: Impactes del canvi climàtic relatius a l'alteració del règim de temperatures | E28: Treballs forestals
A29: Myotis bechsteinii | B29: Producció d'energia renovable
A30: Myotis blythii | B30: Producció d'energia renovable
A31: Myotis emarginatus | B31: Producció d'energia renovable
A32: Nyctalus leisleri | B32: Producció d'energia renovable
A33: Osmoderma eremita | B33: No especificada
A34: Osmunda regalis | B34: Impactes del canvi climàtic relatius a l'alteració del règim de precipitació i sequera | C34: Gestió de l'aigua | D34: Foc
A35: Osphya aeneipennis | B35: No especificada
A36: Pedicularis comosa sp. Asparagoides | B36: No especificada
A37: Rana temporaria | B37: Impactes del canvi climàtic relatius a l'alteració del règim de precipitació i sequera | C37: Impactes del canvi climàtic relatius a l'alteració del règim de temperatures | D37: Ramaderia
A38: Ranunculus nodiflorus | B38: Impactes del canvi climàtic relatius a l'alteració del règim de precipitació i sequera | C38: Ramaderia
A39: Rhinolophus euryale | B39: Producció d'energia renovable
A40: Rhinolophus ferrumequinum | B40: Producció d'energia renovable
A41: Rosalia alpina | B41: Impactes del canvi climàtic relatius a l'alteració del règim de precipitació i sequera | C41: Gestió d'hàbitats
A42: Saxifraga fragosoi | B42: Impactes del canvi climàtic relatius a l'alteració del règim de precipitació i sequera | C42: Foc
A43: Synchita undata | B43: No especificada
A44: Testudo hermanni | B44: Activitat agrícola | C44: Treballs forestals | D44: Caça i recol·lecció d'animals | E44: Foc
A45: Triturus marmoratus | B45: Impactes del canvi climàtic relatius a l'alteració del règim de precipitació i sequera | C45: Gestió de l'aigua | D45: Ramaderia
A46: Tyto alba | B46: Activitat agrícola | C46: Desaparició d'activitats tradicionals

Sheet Analisi_Prioritat_Grup
A2: Grups | B2: Espècie | C2: Normatives | D2: Feina Feta | E2: AVALUACIÓ
A3: Amfibis | B3: Alytes obstetricans | C3: 10 | D3: 2 | E3: 8 | I3: 33 elements prioritaris
A4: Aus | B4: Aquila chrysaetos | C4: 8 | D4: 1 | E4: 7 | I4: Invertebrats | J4: =COUNTIF($A$3:$A$35,I4) -> 5
A5: Aus | B5: Aquila fasciata | C5: 13 | D5: 6 | E5: 7 | F5: EN | I5: Peixos | J5: =COUNTIF($A$3:$A$35,I5) -> 1
A6: Invertebrats | B6: Austropotamobius pallipes | C6: 7 | D6: 5 | E6: 2 | F6: EN | I6: Amfibis | J6: =COUNTIF($A$3:$A$35,I6) -> 3
A7: Mamífers | B7: Barbastella barbastellus | C7: 10 | D7: 2 | E7: 8 | F7: VU | I7: Rèptils | J7: =COUNTIF($A$3:$A$35,I7) -> 3
A8: Peixos | B8: Barbus meridionalis | C8: 6 | D8: 0 | E8: 6 | I8: Mamífers | J8: =COUNTIF($A$3:$A$35,I8) -> 12
A9: Mamífers | B9: Canis lupus | C9: 11 | D9: 4 | E9: 7 | I9: Plantes vasculars | J9: =COUNTIF($A$3:$A$35,I9) -> 4
A10: Invertebrats | B10: Cerambyx cerdo | C10: 11 | D10: 2 | E10: 9 | F10: VU | I10: Aus | J10: =COUNTIF($A$3:$A$35,I10) -> 2
A11: Mamífers | B11: Felis silvestris | C11: 10 | D11: 4 | E11: 6 | I11: Pteridòfits | J11: =COUNTIF($A$3:$A$35,I11) -> 3
A12: Mamífers | B12: Glis glis | C12: 5 | D12: 3 | E12: 2 | J12: =SUM(J4:J11) -> 33
A13: Amfibis | B13: Hyla meridionalis | C13: 11 | D13: 2 | E13: 9
A14: Pteridòfits | B14: Isoetes durieui | C14: 8 | D14: 1 | E14: 7 | F14: VU
A15: Rèptils | B15: Lacerta bilineata (ex viridis) | C15: 10 | D15: 0 | E15: 10
A16: Plantes vasculars | B16: Limonium geronense | C16: 7 | D16: 1 | E16: 6 | F16: VU
A17: Invertebrats | B17: Lucanus cervus | C17: 10 | D17: 2 | E17: 8 | F17: VU
A18: Pteridòfits | B18: Marsilea strigosa | C18: 8 | D18: 2 | E18: 6 | F18: EN
A19: Rèptils | B19: Mauremys leprosa | C19: 11 | D19: 0 | E19: 11
A20: Mamífers | B20: Miniopterus schreibersii | C20: 12 | D20: 4 | E20: 8 | F20: VU
A21: Mamífers | B21: Mustela putorius | C21: 9 | D21: 4 | E21: 5 | F21: EN
A22: Mamífers | B22: Myotis bechsteini | C22: 12 | D22: 4 | E22: 8 | F22: EN
A23: Mamífers | B23: Myotis blythii | C23: 12 | D23: 2 | E23: 10 | F23: VU
A24: Mamífers | B24: Myotis emarginatus | C24: 12 | D24: 2 | E24: 10 | F24: VU
A25: Mamífers | B25: Neomys milleri | C25: 7 | D25: 1 | E25: 6 | F25: VU
A26: Invertebrats | B26: Osmoderma eremita | C26: 15 | D26: 4 | E26: 11 | F26: EN
A27: Pteridòfits | B27: Osmunda regalis | C27: 5 | D27: 0 | E27: 5
A28: Plantes vasculars | B28: Pedicularis comosa ssp asparagoides | C28: 10 | D28: 1 | E28: 9 | F28: VU
A29: Mamífers | B29: Rhinolophus eurylae | C29: 13 | D29: 4 | E29: 9 | F29: EN
A30: Mamífers | B30: Rhinolophus ferrumequinum | C30: 12 | D30: 4 | E30: 8 | F30: VU
A31: Invertebrats | B31: Rosalia alpina | C31: 13 | D31: 2 | E31: 11 | F31: EN
A32: Plantes vasculars | B32: Saxifraga fragosoi | C32: 7 | D32: 2 | E32: 5 | F32: VU | I32: EN | J32: =COUNTIF($F$3:$F$35,"EN") -> 9
A33: Plantes vasculars | B33: Spiranthes aestivalis | C33: 8 | D33: 1 | E33: 7 | F33: VU | I33: VU | J33: =COUNTIF($F$3:$F$35,"VU") -> 13
A34: Rèptils | B34: Testudo hermanni | C34: 17 | D34: 5 | E34: 12 | F34: EN | I34: No amenaçades Cat/Es | J34: =COUNTIF($F$3:$F$35,"") -> 11
A35: Amfibis | B35: Triturus marmoratus | C35: 10 | D35: 2 | E35: 8

Sheet PLA
A1: MODEL DE PLA ESTRATÈGIC PELS ENP | I1: canviat optatiu-obligatori | J1: text modificat
B2: Espai natural protegit: | C2: L'Albera | J2: No aplicable (NA)
S3: Fita a assolir en 4 anys | U3: Gestió interna | Y3: Anualitat
A4: EIXOS | C4: OBJECTIUS Generals (PP) | E4: OBJECTIUS Estratègics | G4: OBJECTIUS operatius | H4: Comú / Específic | I4: Obligatori / Optatiu | J4: Objectiu operatiu concret a l'espai | K4: Explicació de la decisió presa en el cas de canvis respecte al llistat inicial (columna G) | L4: Objectiu amb mesures incorporables a la planificació anual de la gestió de l'espai? | M4: Prioritat | N4: Propostes genèriques d'accions | O4: Marc de referència | P4: Resultats derivats | Q4: Accions (afegit Albera) | R4: indicadors | S4: Mínima | T4: Màxim (Desitjable) | U4: Hores de dedicació (hores/setmana) | V4: Total hores període (hores) | W4: Àrea responsable | X4: Persona responsable | Y4: 2025 | Z4: 2026 | AA4: 2027 | AB4: 2028
A5: NATURA | B5: 1 | C5: CONSERVAR LA NATURA i restaurar els ecosistemes, els processos naturals i seminaturals, la biodiversitat i la geodiversitat associada. | D5: 01.1 | E5: Adequar i fer eficient la conservació dels elements objecte de gestió prioritària marcats per la DG a l'ENP | F5: 01.1.1 | G5: Implementar i executar plans de gestió específics per a hàbitats i espècies de conservació prioritària dins l'ENP | H5: Comú | I5: Obligatori | J5: =G5 -> Implementar i executar plans de gestió específics per a hàbitats i espècies de conservació prioritària dins l'ENP | M5: MÀXIMA | N5: *Realització d'accions per a la millora dels elements prioritzats a l'espai *Elaboració de plans de gestió per elements prioritzats a l'espai | O5: MAP | P5: SFF: Elaboració de plans de gestió específics per a espècies de conservació prioritària i directrius de gestió d'hàbitats. SFF/SENP: Definir a nivell de cluster quins son els que es poden elaborar conjuntament. | Q5: Millora del coneixement de la distribució i població (o superfície) dels elements priorizats. | R5: % d'elements prioritzats dels quals s'ha millorat el coneixent en base a les aproximacions següents: (1) Increment anual del 25% de N elements amb informació/N total elements prioritzats a l'espai (any 2029 -> Inexistència de cap element prioritzat sense 'feina feta' ). 2) Distribució: Tots els quadrats 1x1 de l'ENP tenen informació de la distribució dels elements prioritzats. 3) Es coneixen densitats poblacionals/estimes per totes les sp catalogades 'En Perill' i s'estableix periodicitat seguiment/sp. 4) Es prospecta el 50% d'hàbitat no prospectat per a una sp 5) Almenys 1 vegada es fa una anàlisi poblacional per a sp que no es coneix la distribució (òliba) | S5: 0.5 | T5: 1 | U5: 15 | V5: =PLA!U5*Llistes!$L$11*Llistes!$L$12 -> 2000 | W5: Patrimoni natural | X5: =IF(W5=Llistes!$K$2,Llistes!$L$2,IF(W5=Llistes!$K$3,Llistes!$L$3,IF(W5=Llistes!$K$4,Llistes!$L$4,IF(W5=Llistes!$K$5,Llistes!$L$5,IF(W5=Llistes!$K$6,Llistes!$L$6,IF(W5=Llistes!$K$7,Llistes!$L$7,"")))))) -> Pau Federico | Y5: X | Z5: X | AA5: X | AB5: X
A6: NATURA | F6: 01.1.1 | G6: Implementar i executar plans de gestió específics per a hàbitats i espècies de conservació prioritària dins l'ENP | H6: Comú | I6: Obligatori | J6: =G6 -> Implementar i executar plans de gestió específics per a hàbitats i espècies de conservació prioritària dins l'ENP | M6: MÀXIMA | Q6: Desplegament del MAP a l'espai XN2000 Basses Albera | R6: Nombre d'accions del MAP que s'han començat a desenvolupar | S6: 0.3 | T6: 0.6 | U6: 7.8 | V6: =PLA!U6*Llistes!$L$11*Llistes!$L$12 -> 1040 | W6: XN2000 | X6: =IF(W6=Llistes!$K$2,Llistes!$L$2,IF(W6=Llistes!$K$3,Llistes!$L$3,IF(W6=Llistes!$K$4,Llistes!$L$4,IF(W6=Llistes!$K$5,Llistes!$L$5,IF(W6=Llistes!$K$6,Llistes!$L$6,IF(W6=Llistes!$K$7,Llistes!$L$7,"")))))) -> Montse Pascual | Y6: X | Z6: X | AA6: X | AB6: X
A7: NATURA | F7: 01.1.1 | G7: Implementar i executar plans de gestió específics per a hàbitats i espècies de conservació prioritària dins l'ENP | H7: Comú | I7: Obligatori | J7: =G7 -> Implementar i executar plans de gestió específics per a hàbitats i espècies de conservació prioritària dins l'ENP | M7: MÀXIMA | Q7: Redacció del projecte de restauració de depressions. | R7: S'ha redactat el projecte | T7: Sí | U7: 0.15 | V7: =PLA!U7*Llistes!$L$11*Llistes!$L$12 -> 20 | W7: XN2000 | X7: =IF(W7=Llistes!$K$2,Llistes!$L$2,IF(W7=Llistes!$K$3,Llistes!$L$3,IF(W7=Llistes!$K$4,Llistes!$L$4,IF(W7=Llistes!$K$5,Llistes!$L$5,IF(W7=Llistes!$K$6,Llistes!$L$6,IF(W7=Llistes!$K$7,Llistes!$L$7,"")))))) -> Montse Pascual | Y7: X | Z7: X | AA7: X | AB7: X
A8: NATURA | F8: 01.1.1 | G8: Implementar i executar plans de gestió específics per a hàbitats i espècies de conservació prioritària dins l'ENP | H8: Comú | I8: Obligatori | J8: =G8 -> Implementar i executar plans de gestió específics per a hàbitats i espècies de conservació prioritària dins l'ENP | M8: MÀXIMA | Q8: Execució del projecte de restauració de depressions | R8: S'ha executat el projecte | T8: Sí | U8: 0.15 | V8: =PLA!U8*Llistes!$L$11*Llistes!$L$12 -> 20 | W8: XN2000 | X8: =IF(W8=Llistes!$K$2,Llistes!$L$2,IF(W8=Llistes!$K$3,Llistes!$L$3,IF(W8=Llistes!$K$4,Llistes!$L$4,IF(W8=Llistes!$K$5,Llistes!$L$5,IF(W8=Llistes!$K$6,Llistes!$L$6,IF(W8=Llistes!$K$7,Llistes!$L$7,"")))))) -> Montse Pascual | Y8: X | Z8: X | AA8: X | AB8: X
A9: NATURA | F9: 01.1.1 | G9: Implementar i executar plans de gestió específics per a hàbitats i espècies de conservació prioritària dins l'ENP | H9: Comú | I9: Obligatori | J9: =G9 -> Implementar i executar plans de gestió específics per a hàbitats i espècies de conservació prioritària dins l'ENP | M9: MÀXIMA | Q9: Redacció del projecte executiu de restauració de Garbet | R9: S'ha redactat el projecte executiu | T9: Sí | U9: 0.15 | V9: =PLA!U9*Llistes!$L$11*Llistes!$L$12 -> 20 | W9: XN2000 | X9: =IF(W9=Llistes!$K$2,Llistes!$L$2,IF(W9=Llistes!$K$3,Llistes!$L$3,IF(W9=Llistes!$K$4,Llistes!$L$4,IF(W9=Llistes!$K$5,Llistes!$L$5,IF(W9=Llistes!$K$6,Llistes!$L$6,IF(W9=Llistes!$K$7,Llistes!$L$7,"")))))) -> Montse Pascual | Y9: X | Z9: X | AA9: X | AB9: X
A10: NATURA | F10: 01.1.1 | G10: Implementar i executar plans de gestió específics per a hàbitats i espècies de conservació prioritària dins l'ENP | H10: Comú | I10: Obligatori | J10: =G10 -> Implementar i executar plans de gestió específics per a hàbitats i espècies de conservació prioritària dins l'ENP | M10: MÀXIMA | Q10: Execució del projecte de restauració de Garbet | R10: S'ha executat el projecte | T10: Sí | U10: 0.15 | V10: =PLA!U10*Llistes!$L$11*Llistes!$L$12 -> 20 | W10: XN2000 | X10: =IF(W10=Llistes!$K$2,Llistes!$L$2,IF(W10=Llistes!$K$3,Llistes!$L$3,IF(W10=Llistes!$K$4,Llistes!$L$4,IF(W10=Llistes!$K$5,Llistes!$L$5,IF(W10=Llistes!$K$6,Llistes!$L$6,IF(W10=Llistes!$K$7,Llistes!$L$7,"")))))) -> Montse Pascual | Y10: X | Z10: X | AA10: X | AB10: X
A11: NATURA | F11: 01.1.1 | G11: Implementar i executar plans de gestió específics per a hàbitats i espècies de conservació prioritària dins l'ENP | H11: Comú | I11: Obligatori | J11: =G11 -> Implementar i executar plans de gestió específics per a hàbitats i espècies de conservació prioritària dins l'ENP | M11: MÀXIMA | N11: *Realització d'accions per a la millora dels elements prioritzats a l'espai *Elaboració de plans de gestió per elements prioritzats a l'espai | Q11: Realització d'accions per a la millora dels elements prioritzats a l'espai | R11: S'ha realitzat com a mínim 1 acció/sp | S11: 1 acció/ 50% sp prioritzades | T11: 1 acció/ 100% sp prioritzades | U11: 7.02 | V11: =PLA!U11*Llistes!$L$11*Llistes!$L$12 -> 936 | W11: Patrimoni natural | X11: =IF(W11=Llistes!$K$2,Llistes!$L$2,IF(W11=Llistes!$K$3,Llistes!$L$3,IF(W11=Llistes!$K$4,Llistes!$L$4,IF(W11=Llistes!$K$5,Llistes!$L$5,IF(W11=Llistes!$K$6,Llistes!$L$6,IF(W11=Llistes!$K$7,Llistes!$L$7,"")))))) -> Pau Federico | Y11: X | Z11: X | AA11: X | AB11: X
A12: NATURA | F12: 01.1.1 | G12: Implementar i executar plans de gestió específics per a hàbitats i espècies de conservació prioritària dins l'ENP | H12: Comú | I12: Obligatori | J12: =G12 -> Implementar i executar plans de gestió específics per a hàbitats i espècies de conservació prioritària dins l'ENP | M12: ALTA | Q12: Seguiment rompudes i efectes dels treballs forestals sobre tortuga mediterrània en XN2000 | R12: Nombre d'expedients | S12: Al 50% dels expedients se'ls fa un seguiment | T12: Al 100% dels expedients se'ls fa un seguiment | U12: 0.15 | V12: =PLA!U12*Llistes!$L$11*Llistes!$L$12 -> 20 | W12: XN2000 | X12: =IF(W12=Llistes!$K$2,Llistes!$L$2,IF(W12=Llistes!$K$3,Llistes!$L$3,IF(W12=Llistes!$K$4,Llistes!$L$4,IF(W12=Llistes!$K$5,Llistes!$L$5,IF(W12=Llistes!$K$6,Llistes!$L$6,IF(W12=Llistes!$K$7,Llistes!$L$7,"")))))) -> Montse Pascual
A13: NATURA | F13: 01.1.2 | G13: Adaptar i executar plans de gestió específics per a elements geològics de conservació prioritària dins l'ENP | H13: Comú | I13: Obligatori
A14: NATURA | D14: 01.2 | E14: Executar les mesures de gestió directa previstes en els intruments de planificació per la conservació i la gestió adaptativa dels elements clau de l'ENP | F14: 01.2.1 | G14: Implementar la metodologia de gestió adaptativa (Estàndards Oberts de Gestió Adaptativa a Catalunya) en tots els processos de l'ENP | H14: Comú | I14: Obligatori | J14: =G14 -> Implementar la metodologia de gestió adaptativa (Estàndards Oberts de Gestió Adaptativa a Catalunya) en tots els processos de l'ENP | M14: ALTA | N14: *Definició d'un protocol per tal d'incorporar la metodologia dels Estàndards Oberts pels processos més rellevants per a la conservació a l'espai | O14: ESNATURA | P14: SENP: Elaboració d'un manual per la implementació dels OSAM | Q14: Aplicació de la metodologia dels Estàndards Oberts pels processos més rellevants per a la conservació a l'espai | R14: 1) S'analitzen els resultats a través dels indicadors 2) La planificació s'adapta en funció dels resultats. 3) S'avalua el grau de millora de les amenaces/factors de canvi | S14: Per al 50% de les accions | T14: Per al 100% de les accions | U14: 0.15 | V14: =PLA!U14*Llistes!$L$11*Llistes!$L$12 -> 20 | W14: Direcció | X14: =IF(W14=Llistes!$K$2,Llistes!$L$2,IF(W14=Llistes!$K$3,Llistes!$L$3,IF(W14=Llistes!$K$4,Llistes!$L$4,IF(W14=Llistes!$K$5,Llistes!$L$5,IF(W14=Llistes!$K$6,Llistes!$L$6,IF(W14=Llistes!$K$7,Llistes!$L$7,"")))))) -> Gerard Carrion | Y14: X | Z14: X | AA14: X | AB14: X
A15: NATURA | F15: 01.2.1 | G15: Implementar la metodologia de gestió adaptativa (Estàndards Oberts de Gestió Adaptativa a Catalunya) en tots els processos de l'ENP | H15: Comú | I15: Obligatori | J15: =G15 -> Implementar la metodologia de gestió adaptativa (Estàndards Oberts de Gestió Adaptativa a Catalunya) en tots els processos de l'ENP | M15: ALTA | Q15: Aplicació de la metodologia dels Estàndards Oberts pels processos més rellevants per a la conservació a l'espai de XN2000 Basses de l'Albera | R15: S'aplica la metodologia dels estàndars oberts | T15: Sí | U15: 0.15 | V15: =PLA!U15*Llistes!$L$11*Llistes!$L$12 -> 20 | W15: XN2000 | X15: =IF(W15=Llistes!$K$2,Llistes!$L$2,IF(W15=Llistes!$K$3,Llistes!$L$3,IF(W15=Llistes!$K$4,Llistes!$L$4,IF(W15=Llistes!$K$5,Llistes!$L$5,IF(W15=Llistes!$K$6,Llistes!$L$6,IF(W15=Llistes!$K$7,Llistes!$L$7,"")))))) -> Montse Pascual | Y15: X | Z15: X | AA15: X | AB15: X
A16: NATURA | F16: 01.2.2 | G16: Executar les mesures previstes en els plans de conservació o recuperació d'espècies amenaçades de forma coordinada amb el Servei de Flora i Fauna en l'àmbit de l'ENP | H16: Comú | I16: Obligatori | J16: =G16 -> Executar les mesures previstes en els plans de conservació o recuperació d'espècies amenaçades de forma coordinada amb el Servei de Flora i Fauna en l'àmbit de l'ENP | M16: MÀXIMA | N16: * Implicació i participació en la redacció dels plans de conservació /recuperació d'espècies amenaçades | Q16: Implicació i participació en la redacció dels plans de conservació /recuperació d'espècies amenaçades | R16: 1) Nombre de plans de conservació/recuperació en els que l'ENP hi participa | S16: 1) Participació en el 50% dels plans d'sp amenaçades (EN i VU), 11 | T16: 1) Participació en el 100% dels plans d'sp amenaçades (EN i VU),22 | U16: 3 | V16: =PLA!U16*Llistes!$L$11*Llistes!$L$12 -> 400 | W16: Patrimoni natural | X16: =IF(W16=Llistes!$K$2,Llistes!$L$2,IF(W16=Llistes!$K$3,Llistes!$L$3,IF(W16=Llistes!$K$4,Llistes!$L$4,IF(W16=Llistes!$K$5,Llistes!$L$5,IF(W16=Llistes!$K$6,Llistes!$L$6,IF(W16=Llistes!$K$7,Llistes!$L$7,"")))))) -> Pau Federico | Y16: X | Z16: X | AA16: X | AB16: X
A17: NATURA | F17: 01.2.2 | G17: Executar les mesures previstes en els plans de conservació o recuperació d'espècies amenaçades de forma coordinada amb el Servei de Flora i Fauna en l'àmbit de l'ENP | H17: Comú | I17: Obligatori | J17: =G17 -> Executar les mesures previstes en els plans de conservació o recuperació d'espècies amenaçades de forma coordinada amb el Servei de Flora i Fauna en l'àmbit de l'ENP | M17: MÀXIMA | N17: * Execució de les accions dins els plans que pertoquin a cada espai (incorporar totes les mesures que surten als plans ja aprovats que tenen incidència a l'espai) | Q17: Execució de les accions dins els plans que pertoquin a cada espai (incorporar totes les mesures que surten als plans ja aprovats que tenen incidència a l'espai) | R17: Nombre d'accions que provenen de l'aplicació de plans de conservació/recuperació | S17: 5 accions | T17: 10 accions | U17: 3 | V17: =PLA!U17*Llistes!$L$11*Llistes!$L$12 -> 400 | W17: Patrimoni natural | X17: =IF(W17=Llistes!$K$2,Llistes!$L$2,IF(W17=Llistes!$K$3,Llistes!$L$3,IF(W17=Llistes!$K$4,Llistes!$L$4,IF(W17=Llistes!$K$5,Llistes!$L$5,IF(W17=Llistes!$K$6,Llistes!$L$6,IF(W17=Llistes!$K$7,Llistes!$L$7,"")))))) -> Pau Federico | Y17: X | Z17: X | AA17: X | AB17: X
A18: NATURA | F18: 01.2.2 | G18: Executar les mesures previstes en els plans de conservació o recuperació d'espècies amenaçades de forma coordinada amb el Servei de Flora i Fauna en l'àmbit de l'ENP | H18: Comú | I18: Obligatori | J18: =G18 -> Executar les mesures previstes en els plans de conservació o recuperació d'espècies amenaçades de forma coordinada amb el Servei de Flora i Fauna en l'àmbit de l'ENP | M18: MÀXIMA | N18: * Col.laboració en l'obtenció de la informació necessària dins els espais per al desenvolupament dels Plans | O18: MAP Catàlegs | P18: SFF: Elaboració de plans de conservació o recuperació d'espècies protegides | Q18: Col·laboració en l'obtenció de la informació necessària dins els espais per al desenvolupament dels Plans | R18: Nombre d'sp amenaçades prioritzades amb les quals treballa l'ENP | S18: 50% sp amenaçades prioritzades | T18: 100% sp amenaçades prioritzades | U18: 3 | V18: =PLA!U18*Llistes!$L$11*Llistes!$L$12 -> 400 | W18: Patrimoni natural | X18: =IF(W18=Llistes!$K$2,Llistes!$L$2,IF(W18=Llistes!$K$3,Llistes!$L$3,IF(W18=Llistes!$K$4,Llistes!$L$4,IF(W18=Llistes!$K$5,Llistes!$L$5,IF(W18=Llistes!$K$6,Llistes!$L$6,IF(W18=Llistes!$K$7,Llistes!$L$7,"")))))) -> Pau Federico | Y18: X | Z18: X | AA18: X | AB18: X
A19: NATURA | F19: 01.2.3 | G19: Executar les mesures de gestió previstes en els plans de control i erradicació d'espècies exòtiques de forma coordinada amb el Servei de Flora i Fauna en l'àmbit de l'ENP | H19: Comú | I19: Obligatori | J19: =G19 -> Executar les mesures de gestió previstes en els plans de control i erradicació d'espècies exòtiques de forma coordinada amb el Servei de Flora i Fauna en l'àmbit de l'ENP | M19: MÀXIMA | N19: * Implicació i participació en la redacció (cal identificar els plans que estan ja en marxa o previstos i posar les mesures concretes) * Execució de les accions dins els plans que pertoquin a cada espai * Col.laboració en l'obtenció de la informació necessària dins els espais per al desenvolupament dels Plans | Q19: Col·laboració amb el Servei de Fauna i Flora en les actuacions de gestió de les espècies exòtiques invasores dins de l'ENP. (Opuntia, bambú, estramoni, Solanum sisymbriifolium, coipú, visó americà, ailant, cortaderia i robínia) (XN2000) | R19: Nombre d'EEI prioritzades en l'ENP que es gestionen | S19: 3 EEI | T19: 6 EEI | U19: 1.02 | V19: =PLA!U19*Llistes!$L$11*Llistes!$L$12 -> 136 | W19: Patrimoni natural | X19: =IF(W19=Llistes!$K$2,Llistes!$L$2,IF(W19=Llistes!$K$3,Llistes!$L$3,IF(W19=Llistes!$K$4,Llistes!$L$4,IF(W19=Llistes!$K$5,Llistes!$L$5,IF(W19=Llistes!$K$6,Llistes!$L$6,IF(W19=Llistes!$K$7,Llistes!$L$7,"")))))) -> Pau Federico | Y19: X | Z19: X | AA19: X | AB19: X
A20: NATURA | F20: 01.2.3 | G20: Executar les mesures de gestió previstes en els plans de control i erradicació d'espècies exòtiques de forma coordinada amb el Servei de Flora i Fauna en l'àmbit de l'ENP | H20: Comú | I20: Obligatori | J20: =G20 -> Executar les mesures de gestió previstes en els plans de control i erradicació d'espècies exòtiques de forma coordinada amb el Servei de Flora i Fauna en l'àmbit de l'ENP | M20: MÀXIMA | N20: * Implicació i participació en la redacció (cal identificar els plans que estan ja en marxa o previstos i posar les mesures concretes) * Execució de les accions dins els plans que pertoquin a cada espai * Col.laboració en l'obtenció de la informació necessària dins els espais per al desenvolupament dels Plans | O20: ESNATURA MAP | P20: SFF: Elaboració de plans de control i erradicació d'espècies exòtiques | Q20: Coordinació i realització d'accions de gestió d'espècies exòtiques invasores dins de l'ENP (Opuntia, bambú, estramoni, Solanum sisymbriifolium, coipú) (XN2000). | R20: Nombre de reunions/any vinculades a EEI en què l'ENP participa o impulsades pel ENP | S20: 1 reunions/any | T20: 3 reunions/any | U20: 0.15 | V20: =PLA!U20*Llistes!$L$11*Llistes!$L$12 -> 20 | W20: Patrimoni natural | X20: =IF(W20=Llistes!$K$2,Llistes!$L$2,IF(W20=Llistes!$K$3,Llistes!$L$3,IF(W20=Llistes!$K$4,Llistes!$L$4,IF(W20=Llistes!$K$5,Llistes!$L$5,IF(W20=Llistes!$K$6,Llistes!$L$6,IF(W20=Llistes!$K$7,Llistes!$L$7,"")))))) -> Pau Federico | Y20: X | Z20: X | AA20: X | AB20: X
A21: NATURA | F21: 01.2.4 | G21: Desplegar els objectius i tasques recollits en els instruments de referència i compromisos internacionals | H21: Específic | I21: Optatiu | J21: =G21 -> Desplegar els objectius i tasques recollits en els instruments de referència i compromisos internacionals | M21: MITJANA | N21: * Desplegament dels objectius recollits en l'Estratègia de la Xarxa d'àrees marines protegides del Mediterrani (MedPAN network) * Col·laboració en el compliment dels objectius i tasques derivats de la Mediterranean Climate Action Partnership en matèria de biodiversitat i canvi climàtic i els seus impactes sobre la sequera, calor i incendis * Col·laboració en la implementació pràctica de projectes de l'àrea internacional i dels compromisos amb les entitats membres UICN, Euroregió Pirineus Mediterrània | Q21: Col·laboració amb altres unitats per a l'assoliment d'objectius i compromisos internacionals, quan aquestes ho demanin. | R21: Nombre de reunions i/o accions vinculades a compromisos internacionals | S21: 1 reunions/any | T21: 3 reunions/any | U21: 0.15 | V21: =PLA!U21*Llistes!$L$11*Llistes!$L$12 -> 20 | W21: Direcció | X21: =IF(W21=Llistes!$K$2,Llistes!$L$2,IF(W21=Llistes!$K$3,Llistes!$L$3,IF(W21=Llistes!$K$4,Llistes!$L$4,IF(W21=Llistes!$K$5,Llistes!$L$5,IF(W21=Llistes!$K$6,Llistes!$L$6,IF(W21=Llistes!$K$7,Llistes!$L$7,"")))))) -> Gerard Carrion | Y21: X | Z21: X | AA21: X | AB21: X
A22: NATURA | F22: 01.2.4 | G22: Desplegar els objectius i tasques recollits en els instruments de referència i compromisos internacionals | H22: Específic | I22: Optatiu | J22: =G22 -> Desplegar els objectius i tasques recollits en els instruments de referència i compromisos internacionals | M22: MITJANA | Q22: Seguiment dels ajuts d’espais naturals i d’actuacions en espais de la XN2000. | R22: Percentatge d’ajuts sobre els que es fa seguiment | S22: 0.5 | T22: 1 | U22: 0.15 | V22: =PLA!U22*Llistes!$L$11*Llistes!$L$12 -> 20 | W22: XN2000 | X22: =IF(W22=Llistes!$K$2,Llistes!$L$2,IF(W22=Llistes!$K$3,Llistes!$L$3,IF(W22=Llistes!$K$4,Llistes!$L$4,IF(W22=Llistes!$K$5,Llistes!$L$5,IF(W22=Llistes!$K$6,Llistes!$L$6,IF(W22=Llistes!$K$7,Llistes!$L$7,"")))))) -> Montse Pascual
D23: 01.3 | E23: Crear ecosistemes complexes, resilients, i d'alta biodiversitat per garantir la recuperació dels processos ecosistèmics | F23: 01.3.1 | G23: Identificar espais pel foment de la dinàmica natural i l'aprofitament no extractiu | H23: Comú | I23: Obligatori | J23: Identificar espais pel foment de la dinàmica natural i l'aprofitament no extractiu | M23: ALTA | N23: *Afavorir la creació d'hàbitats per a la conservació d'espècies | Q23: Afavorir la creació d'hàbitats per a la conservació d'espècies | R23: Nombre d'hectàrees creades per a la conservació | S23: 2 ha | T23: 5 ha | U23: 0.3 | V23: =PLA!U23*Llistes!$L$11*Llistes!$L$12 -> 40 | W23: Patrimoni natural | X23: =IF(W23=Llistes!$K$2,Llistes!$L$2,IF(W23=Llistes!$K$3,Llistes!$L$3,IF(W23=Llistes!$K$4,Llistes!$L$4,IF(W23=Llistes!$K$5,Llistes!$L$5,IF(W23=Llistes!$K$6,Llistes!$L$6,IF(W23=Llistes!$K$7,Llistes!$L$7,"")))))) -> Pau Federico
A24: NATURA | F24: 01.3.1 | G24: Identificar espais pel foment de la dinàmica natural i l'aprofitament no extractiu | H24: Comú | I24: Obligatori | J24: =G23 -> Identificar espais pel foment de la dinàmica natural i l'aprofitament no extractiu | M24: ALTA | N24: *Participar en la identificació d'espais pel foment de la dinàmica natural i l'aprofitament no extractiu dins l'ENP en base a uns criteris metodològics predefinits | O24: ESNATURA | P24: SENP/SFF: Definir criteris metodològics | Q24: Participació en la identificació d'espais pel foment de la dinàmica natural i l'aprofitament no extractiu dins l'ENP en base a uns criteris metodològics predefinits | R24: Nombre d'hores dedicades a la identificació d'espais per a dinàmica natural | S24: 1 hora/any | T24: 3 hores/any | U24: 0.045 | V24: =PLA!U24*Llistes!$L$11*Llistes!$L$12 -> 6 | W24: Patrimoni natural | X24: =IF(W24=Llistes!$K$2,Llistes!$L$2,IF(W24=Llistes!$K$3,Llistes!$L$3,IF(W24=Llistes!$K$4,Llistes!$L$4,IF(W24=Llistes!$K$5,Llistes!$L$5,IF(W24=Llistes!$K$6,Llistes!$L$6,IF(W24=Llistes!$K$7,Llistes!$L$7,"")))))) -> Pau Federico | Y24: X | Z24: X | AA24: X | AB24: X
A25: NATURA | F25: 01.3.2 | G25: Afavorir la maduresa dels sistemes forestals | H25: Específic | I25: Obligatori | J25: =G25 -> Afavorir la maduresa dels sistemes forestals | M25: ALTA | N25: *Participar i impulsar la planificació i execució d'accions d'acceleració de la maduresa forestal en zones boscoses dins l'ENP en base als criteris metodològics predefinits | O25: MAP | P25: SENP/SFF: Definir criteris metodològics | Q25: Execució d'accions d'acceleració de la maduresa forestal en zones boscoses dins l'ENP en base als criteris metodològics predefinits | R25: Nombre d'hectàrees destinades a a maduresa forestal contemplades en els PTGiMF. | S25: 25% de les actuacions previstes als PTGiMF | T25: 50% de les actuacions previstes als PTGiMF | U25: 0.045 | V25: =PLA!U25*Llistes!$L$11*Llistes!$L$12 -> 6 | W25: Direcció | X25: =IF(W25=Llistes!$K$2,Llistes!$L$2,IF(W25=Llistes!$K$3,Llistes!$L$3,IF(W25=Llistes!$K$4,Llistes!$L$4,IF(W25=Llistes!$K$5,Llistes!$L$5,IF(W25=Llistes!$K$6,Llistes!$L$6,IF(W25=Llistes!$K$7,Llistes!$L$7,"")))))) -> Gerard Carrion | Y25: X | AA25: X
A26: NATURA | F26: 01.3.3 | G26: Generar pertorbacions controlades | H26: Específic | I26: Optatiu | J26: =G26 -> Generar pertorbacions controlades | K26: No hi ha zones compatibles amb cremes controlades dins del PNIN, ara mateix. Sí que es fan en zones de XN2000 | M26: MITJANA | N26: *Elaboració d'una planificació d'actuacions de simulació d'incendis forestals naturals (cremes controlades) dins l'espai en base als criteris metodològics predefinits. *Realització dels estudis necessaris i participació en la reintroducció de grans herbívors, carnívors o carronyaires dins l'ENP en base als criteris metodològics predefinits. | O26: MAP | P26: SENP/SFF: Definir criteris metodològics | Q26: Col·laboració amb Bombers i GEPIF per a la realització de cremes controlades en àmbits compatibles | R26: Nombre d'hectàrees destinades a cremes controlades | S26: 0,5 ha | T26: 1,5 ha | U26: 0.045 | V26: =PLA!U26*Llistes!$L$11*Llistes!$L$12 -> 6 | W26: Direcció | X26: =IF(W26=Llistes!$K$2,Llistes!$L$2,IF(W26=Llistes!$K$3,Llistes!$L$3,IF(W26=Llistes!$K$4,Llistes!$L$4,IF(W26=Llistes!$K$5,Llistes!$L$5,IF(W26=Llistes!$K$6,Llistes!$L$6,IF(W26=Llistes!$K$7,Llistes!$L$7,"")))))) -> Gerard Carrion | Y26: X | Z26: X | AA26: X | AB26: X
A27: NATURA | F27: 01.3.4 | G27: Restaurar la dinàmica natural dels rius | H27: Específic | I27: Optatiu
A28: NATURA | F28: 01.3.5 | G28: Fomentar el paisatge en mosaïc | H28: Específic | I28: Obligatori | J28: =G28 -> Fomentar el paisatge en mosaïc | M28: ALTA | N28: *Realització d'accions per gestionar l'herbivoria domèstica associada a la ramaderia extensiva *Aplicació dels criteris metodològics predefinits en un manual tècnic de bones pràctiques en ramaderia extensiva i recuperació i manteniment de pastures aplicat a l'ENP. *Coordinació i gestió dels ramats locals en actuacions de restauració de pastures i desembosc. | O28: ESNATURA | P28: SENP/SFF: Definir criteris metodològics | Q28: Col·laboració amb el sector ramader per mantenir i millorar les pastures, especialment en zones culminals d'interès per a la prevenció d'incendis. | R28: Nombre hectàrees desbrossades per mantenir les pastures per a la prevenció d'incendis | S28: 0,5 ha | T28: 1 ha | U28: 0.045 | V28: =PLA!U28*Llistes!$L$11*Llistes!$L$12 -> 6 | W28: Direcció | X28: =IF(W28=Llistes!$K$2,Llistes!$L$2,IF(W28=Llistes!$K$3,Llistes!$L$3,IF(W28=Llistes!$K$4,Llistes!$L$4,IF(W28=Llistes!$K$5,Llistes!$L$5,IF(W28=Llistes!$K$6,Llistes!$L$6,IF(W28=Llistes!$K$7,Llistes!$L$7,"")))))) -> Gerard Carrion | Y28: X | Z28: X | AA28: X | AB28: X
A29: NATURA | F29: 01.3.6 | G29: Gestionar i intervenir en la dinàmica de poblacions de fauna que no tenen depredador natural | H29: Específic | I29: Optatiu
A30: NATURA | F30: 01.3.7 | G30: Afavorir la connectivitat ecològica del territori | H30: Comú | I30: Obligatori
A31: NATURA | D31: 01.4 | E31: Alinear l'activitat de propietaris i gestors del territori amb la conservació, millora i restauració dels valors de l'ENP | F31: 01.4.1 | G31: Fomentar acords de custòdia en espais d'alt valor dins l'ENP per a la gestió dels elements prioritaris | H31: Comú | I31: Obligatori | J31: =G31 -> Fomentar acords de custòdia en espais d'alt valor dins l'ENP per a la gestió dels elements prioritaris | M31: MÀXIMA | N31: *Realització d'acords de custòdia aplicant el model d'acord elaborat per Serveis Centrals | O31: MAP | P31: SENP/SENP: Dissenyar el protocol i elaborar un model d'acord | Q31: Exploració de la via dels acords de custòdia en espais d'alt valor dins l'ENP. | R31: Establiment d'acords de custòdia en alguna de les finques privades | S31: 1 | T31: 2 | U31: 0.045 | V31: =PLA!U31*Llistes!$L$11*Llistes!$L$12 -> 6 | W31: Direcció | X31: =IF(W31=Llistes!$K$2,Llistes!$L$2,IF(W31=Llistes!$K$3,Llistes!$L$3,IF(W31=Llistes!$K$4,Llistes!$L$4,IF(W31=Llistes!$K$5,Llistes!$L$5,IF(W31=Llistes!$K$6,Llistes!$L$6,IF(W31=Llistes!$K$7,Llistes!$L$7,"")))))) -> Gerard Carrion
A32: NATURA | F32: 01.4.1 | G32: Fomentar acords de custòdia en espais d'alt valor dins l'ENP per a la gestió dels elements prioritaris | H32: Comú | I32: Obligatori | J32: =G32 -> Fomentar acords de custòdia en espais d'alt valor dins l'ENP per a la gestió dels elements prioritaris | M32: MÀXIMA | N32: *Realització d'acords de custòdia aplicant el model d'acord elaborat per Serveis Centrals | O32: MAP | P32: SENP/SENP: Dissenyar el protocol i elaborar un model d'acord | Q32: Redacció dels plans de gestió de les 3 finques privades incloses al PNIN, de forma consensuada amb la propietat. | R32: Nombre plans de gestió de les finques privades aprovats | S32: 1 | T32: 3 | U32: 0.045 | V32: =PLA!U32*Llistes!$L$11*Llistes!$L$12 -> 6 | W32: Direcció | X32: =IF(W32=Llistes!$K$2,Llistes!$L$2,IF(W32=Llistes!$K$3,Llistes!$L$3,IF(W32=Llistes!$K$4,Llistes!$L$4,IF(W32=Llistes!$K$5,Llistes!$L$5,IF(W32=Llistes!$K$6,Llistes!$L$6,IF(W32=Llistes!$K$7,Llistes!$L$7,"")))))) -> Gerard Carrion | Y32: X | Z32: X
A33: NATURA | F33: 01.4.2 | G33: Fomentar bones pràctiques entre els col·lectius de propietaris i gestors del territori | H33: Comú | I33: Obligatori | J33: =G33 -> Fomentar bones pràctiques entre els col·lectius de propietaris i gestors del territori | M33: ALTA | N33: *Realització d'actuacions demostratives en finques pròpies per al foment de bones pràctiques | Q33: Realització d'actuacions demostratives que permetin millorar la gestió d'hàbitats i espècies en altres llocs de l'espai, o zones semblants. | R33: Nombre actuacions destinades a accions demostratives | S33: 1 | T33: 2 | U33: 0.15 | V33: =PLA!U33*Llistes!$L$11*Llistes!$L$12 -> 20 | W33: Patrimoni natural | X33: =IF(W33=Llistes!$K$2,Llistes!$L$2,IF(W33=Llistes!$K$3,Llistes!$L$3,IF(W33=Llistes!$K$4,Llistes!$L$4,IF(W33=Llistes!$K$5,Llistes!$L$5,IF(W33=Llistes!$K$6,Llistes!$L$6,IF(W33=Llistes!$K$7,Llistes!$L$7,"")))))) -> Pau Federico | Y33: X | AA33: X
A34: NATURA
F35: 01.4.3 | G35: Impulsar la coordinació amb els ens locals en la gestió finques públiques situades dins d’ENP | H35: Específic | I35: Optatiu
A36: NATURA | B36: 2 | C36: ADAPTAR ELS ECOSISTEMES AL CANVI CLIMÀTIC i millorar-ne la resiliència en front dels riscos associats. | D36: 02.1 | E36: Planificar l'adaptació dels sistemes naturals al canvi climàtic | F36: 02.1.1 | G36: Adaptar i implementar el Pla d'adaptació de l'ENP al canvi climàtic | H36: Comú | I36: Obligatori | J36: Redactar i implementar el Pla d'adaptació de l'ENP al canvi climàtic | K36: No disposem de cap Pla d'adaptació de l'ENP al canvi climàtic, de manera que primer caldrà redactar-lo. | M36: ALTA | N36: *Planificació del sistema d'espais oberts *Creació de zones de laminació per defensa de inundacions *Creació i manteniment d'espais dunars de protecció de temporals | Q36: Redacció del Pla d'adaptació del PNIN al canvi climàtic. | R36: S'ha redactat el Pla d'adaptació del PNIN al canvi climàtic | T36: Sí | U36: 0.51 | V36: =PLA!U36*Llistes!$L$11*Llistes!$L$12 -> 68 | W36: Direcció | X36: =IF(W36=Llistes!$K$2,Llistes!$L$2,IF(W36=Llistes!$K$3,Llistes!$L$3,IF(W36=Llistes!$K$4,Llistes!$L$4,IF(W36=Llistes!$K$5,Llistes!$L$5,IF(W36=Llistes!$K$6,Llistes!$L$6,IF(W36=Llistes!$K$7,Llistes!$L$7,"")))))) -> Gerard Carrion | Y36: X | Z36: X
A37: NATURA | F37: 02.1.1 | G37: Adaptar i implementar el Pla d'adaptació de l'ENP al canvi climàtic | H37: Comú | I37: Obligatori | J37: Redactar i implementar el Pla d'adaptació de l'ENP al canvi climàtic | K37: No disposem de cap Pla d'adaptació de l'ENP al canvi climàtic, de manera que primer caldrà redactar-lo. | M37: ALTA | N37: *Planificació del sistema d'espais oberts *Creació de zones de laminació per defensa de inundacions *Creació i manteniment d'espais dunars de protecció de temporals | Q37: Donar a conèixer el Pla entre els propietaris perquè puguin integrar les mesures proposades a la gestió de les seves finques. | R37: Nombre de propietats informades sobre el Pla d'adaptació al canvi climàtic | S37: 1 | T37: 3 (les que tinguin Pla de Gestió) | U37: 0.045 | V37: =PLA!U37*Llistes!$L$11*Llistes!$L$12 -> 6 | W37: Direcció | X37: =IF(W37=Llistes!$K$2,Llistes!$L$2,IF(W37=Llistes!$K$3,Llistes!$L$3,IF(W37=Llistes!$K$4,Llistes!$L$4,IF(W37=Llistes!$K$5,Llistes!$L$5,IF(W37=Llistes!$K$6,Llistes!$L$6,IF(W37=Llistes!$K$7,Llistes!$L$7,"")))))) -> Gerard Carrion | AA37: X
A38: NATURA | F38: 02.1.1 | G38: Adaptar i implementar el Pla d'adaptació de l'ENP al canvi climàtic | H38: Comú | I38: Obligatori | J38: Redactar i implementar el Pla d'adaptació de l'ENP al canvi climàtic | K38: No disposem de cap Pla d'adaptació de l'ENP al canvi climàtic, de manera que primer caldrà redactar-lo. | M38: ALTA | N38: *Planificació del sistema d'espais oberts *Creació de zones de laminació per defensa de inundacions *Creació i manteniment d'espais dunars de protecció de temporals | P38: OCCC/SENP: Elaboració del model de Pla d'adaptació dels ENP al canvi climàtic | Q38: Implementació de les mesures d'adaptació del PNIN al canvi climàtic | R38: Nombre de mesures implementades relacionades amb l'adaptació al canvi climàtic | S38: 1 | T38: 4 | U38: 0.045 | V38: =PLA!U38*Llistes!$L$11*Llistes!$L$12 -> 6 | W38: Direcció | X38: =IF(W38=Llistes!$K$2,Llistes!$L$2,IF(W38=Llistes!$K$3,Llistes!$L$3,IF(W38=Llistes!$K$4,Llistes!$L$4,IF(W38=Llistes!$K$5,Llistes!$L$5,IF(W38=Llistes!$K$6,Llistes!$L$6,IF(W38=Llistes!$K$7,Llistes!$L$7,"")))))) -> Gerard Carrion | AA38: X | AB38: X
A39: NATURA | F39: 02.1.2 | G39: Gestionar i planificar els recursos hídrics de l'ENP | H39: Comú | I39: Obligatori | J39: =G39 -> Gestionar i planificar els recursos hídrics de l'ENP | K39: Gestió i manteniment de les fonts i punts d'aigua del PNIN perquè els recursos hídrics estiguin disponibles tant per als hàbitats i les espècies, com per als usos humans (ramaderia, aigua de boca...). | M39: MÀXIMA | Q39: Revisió de les fonts i punts d'aigua per assegurar el seu manteniment (XN2000) | R39: Nombre de fonts i punts d'aigua revisats | S39: 5 | T39: 10 | U39: 1.02 | V39: =PLA!U39*Llistes!$L$11*Llistes!$L$12 -> 136 | W39: Manteniment | X39: =IF(W39=Llistes!$K$2,Llistes!$L$2,IF(W39=Llistes!$K$3,Llistes!$L$3,IF(W39=Llistes!$K$4,Llistes!$L$4,IF(W39=Llistes!$K$5,Llistes!$L$5,IF(W39=Llistes!$K$6,Llistes!$L$6,IF(W39=Llistes!$K$7,Llistes!$L$7,"")))))) -> Sergi Roura | Y39: X | Z39: X | AA39: X | AB39: X
A40: NATURA | F40: 02.1.2 | G40: Gestionar i planificar els recursos hídrics de l'ENP | H40: Comú | I40: Obligatori | J40: =G40 -> Gestionar i planificar els recursos hídrics de l'ENP | K40: Gestió i manteniment de les fonts i punts d'aigua del PNIN perquè els recursos hídrics estiguin disponibles tant per als hàbitats i les espècies, com per als usos humans (ramaderia, aigua de boca...). | M40: MÀXIMA | Q40: Manteniment de GR, itineraris, camins d’accés a dòlmens i menhirs (XN2000) | R40: Nombre de camins, dòlmens i menhirs revisats | U40: 1.02 | V40: =PLA!U40*Llistes!$L$11*Llistes!$L$12 -> 136 | W40: Manteniment | X40: =IF(W40=Llistes!$K$2,Llistes!$L$2,IF(W40=Llistes!$K$3,Llistes!$L$3,IF(W40=Llistes!$K$4,Llistes!$L$4,IF(W40=Llistes!$K$5,Llistes!$L$5,IF(W40=Llistes!$K$6,Llistes!$L$6,IF(W40=Llistes!$K$7,Llistes!$L$7,"")))))) -> Sergi Roura
A41: NATURA | F41: 02.1.2 | G41: Gestionar i planificar els recursos hídrics de l'ENP | H41: Comú | I41: Obligatori | J41: =G41 -> Gestionar i planificar els recursos hídrics de l'ENP | K41: Gestió i manteniment de les fonts i punts d'aigua del PNIN perquè els recursos hídrics estiguin disponibles tant per als hàbitats i les espècies, com per als usos humans (ramaderia, aigua de boca...). | M41: MÀXIMA | Q41: Manteniment de la captació de la font de la Verna per compatibilitzar els usos agroramaders i els cabals naturals. | R41: Recurs hídric disponible i en funcionament | T41: Sí | U41: 1.02 | V41: =PLA!U41*Llistes!$L$11*Llistes!$L$12 -> 136 | W41: Manteniment | X41: =IF(W41=Llistes!$K$2,Llistes!$L$2,IF(W41=Llistes!$K$3,Llistes!$L$3,IF(W41=Llistes!$K$4,Llistes!$L$4,IF(W41=Llistes!$K$5,Llistes!$L$5,IF(W41=Llistes!$K$6,Llistes!$L$6,IF(W41=Llistes!$K$7,Llistes!$L$7,"")))))) -> Sergi Roura | Y41: X | Z41: X | AA41: X | AB41: X
A42: NATURA | F42: 02.1.3 | G42: Participar en la redacció i execució dels instruments d'ordenació forestal sostenible i per la conservació en finques públiques | H42: Específic | I42: Optatiu
A43: NATURA | F43: 02.1.4 | G43: Promoure la redacció d'instruments d'ordenació forestal per reduir la sensibilitat i vulnerabilitat dels boscos al canvi climàtic en finques privades | H43: Específic | I43: Optatiu
A44: NATURA | D44: 02.2 | E44: Planificar la prevenció i extinció d’incendis forestals i la gestió del foc de forma coordinada amb els diferents agents del territori | F44: 02.2.1 | G44: Redactar i implementar el Pla de Prevenció d'Incendis | H44: Comú | I44: Obligatori | J44: Col·laborar en la implementació del Pla de Prevenció d'Incendis | K44: El Pla de Prevenció d'Incendis ja està redactat i vigent des de fa anys per a tot el massís de l'Albera | M44: ALTA | N44: *Elaboració del Pla de Prevenció d'Incendis *Definició de: xarxa estratègica i complementària de vials forestals, xarxa estratègica i complementària de punts d’aigua, tractaments de vegetació, punts estratègics de gestió | Q44: Coordinació de les accions incloses en el Pla de prevenció d'incendis al PNIN. | R44: Nombre de reunions de coordinació de prevenció d'incendis | S44: 2 | T44: 4 | U44: 0.045 | V44: =PLA!U44*Llistes!$L$11*Llistes!$L$12 -> 6 | W44: Direcció | X44: =IF(W44=Llistes!$K$2,Llistes!$L$2,IF(W44=Llistes!$K$3,Llistes!$L$3,IF(W44=Llistes!$K$4,Llistes!$L$4,IF(W44=Llistes!$K$5,Llistes!$L$5,IF(W44=Llistes!$K$6,Llistes!$L$6,IF(W44=Llistes!$K$7,Llistes!$L$7,"")))))) -> Gerard Carrion | Y44: X | Z44: X | AA44: X | AB44: X
A45: NATURA | F45: 02.2.1 | G45: Redactar i implementar el Pla de Prevenció d'Incendis | H45: Comú | I45: Obligatori | J45: Col·laborar en la implementació del Pla de Prevenció d'Incendis | K45: El Pla de Prevenció d'Incendis ja està redactat i vigent des de fa anys per a tot el massís de l'Albera | M45: ALTA | N45: *Elaboració del Pla de Prevenció d'Incendis *Definició de: xarxa estratègica i complementària de vials forestals, xarxa estratègica i complementària de punts d’aigua, tractaments de vegetació, punts estratègics de gestió | O45: ESNATURA | P45: Equip de PPI: Disseny del protocol de treball | Q45: Col·laboració en l'execució d'actuacions de prevenció d'incendis com el manteniment de franges a la carretera d'accés al monestir de Sant Quirze de Colera. | R45: Nombres d'hores dedicades a la col·laboració | S45: 1 | T45: 2 | U45: 0.045 | V45: =PLA!U45*Llistes!$L$11*Llistes!$L$12 -> 6 | W45: Direcció | X45: =IF(W45=Llistes!$K$2,Llistes!$L$2,IF(W45=Llistes!$K$3,Llistes!$L$3,IF(W45=Llistes!$K$4,Llistes!$L$4,IF(W45=Llistes!$K$5,Llistes!$L$5,IF(W45=Llistes!$K$6,Llistes!$L$6,IF(W45=Llistes!$K$7,Llistes!$L$7,"")))))) -> Gerard Carrion | Y45: X | Z45: X | AA45: X | AB45: X
A46: NATURA | F46: 02.2.2 | G46: Definir i planificar la gestió del foc per a la millora de l'ENP | H46: Específic | I46: Obligatori | J46: Participar en la definició i planificació de la gestió del foc per a la millora de l'ENP | K46: La Taula de Foc, coordinada per Bombers i a la qual participem, és el marc on es prenen aquestes decisions. | M46: ALTA | N46: *Pla de gestió de foc *Pla de gestió de cremes | P46: SPEN: Elaboració d'un model de pla de gestió | Q46: Participació a la Taula de Foc de l'Albera i Cap de Creus | R46: Assistència i participació a les reunions de la Taula del Foc | T46: 1 | U46: 0.045 | V46: =PLA!U46*Llistes!$L$11*Llistes!$L$12 -> 6 | W46: Direcció | X46: =IF(W46=Llistes!$K$2,Llistes!$L$2,IF(W46=Llistes!$K$3,Llistes!$L$3,IF(W46=Llistes!$K$4,Llistes!$L$4,IF(W46=Llistes!$K$5,Llistes!$L$5,IF(W46=Llistes!$K$6,Llistes!$L$6,IF(W46=Llistes!$K$7,Llistes!$L$7,"")))))) -> Gerard Carrion | Y46: X | Z46: X | AA46: X | AB46: X
A47: NATURA | F47: 02.2.3 | G47: Treballar per a la prevenció d'incendis juntament amb els propietaris, ajuntaments, protecció civil, ADF i bombers. | H47: Comú | I47: Obligatori | J47: Treballar per a la prevenció d'incendis juntament amb el CAR, propietaris, ajuntaments, protecció civil, ADF, DARPA i bombers. | K47: petita modificació del redactat, afegint el CAR i el DARPA (per petició d'aquest Departament) | M47: MITJANA | Q47: Organització de reunions de coordinació del dispositiu de prevenció d'incendis en cas de tancament del massís, conjuntament amb el CAR. | R47: Nombre de reunions organitzades | S47: 1 reunió/any | T47: 4 reunions/any | U47: 0.045 | V47: =PLA!U47*Llistes!$L$11*Llistes!$L$12 -> 6 | W47: Direcció | X47: =IF(W47=Llistes!$K$2,Llistes!$L$2,IF(W47=Llistes!$K$3,Llistes!$L$3,IF(W47=Llistes!$K$4,Llistes!$L$4,IF(W47=Llistes!$K$5,Llistes!$L$5,IF(W47=Llistes!$K$6,Llistes!$L$6,IF(W47=Llistes!$K$7,Llistes!$L$7,"")))))) -> Gerard Carrion | Y47: X | Z47: X | AA47: X | AB47: X
A48: NATURA | B48: 3 | C48: PROTEGIR LA BIODIVERSITAT, i especialment els elements fràgils i amenaçats, d’interès comunitari o de major interès natural. | D48: 03.1 | E48: Prevenir, minimitzar i compensar els impactes ambientals dels usos i activitats que es desenvolupin en l'àmbit de l'ENP | F48: 03.1.1 | G48: Participar en les consultes dels procesos d'Avaluació Ambiental que afectin directament o indirectament l’espai del ENP | H48: Comú | I48: Obligatori | J48: Participar en les consultes dels processos d'Avaluació Ambiental que afectin directament o indirectament l’ENP | K48: petita modificació del redactat | M48: MITJANA | Q48: Redacció dels informes preceptius sobre avaluació ambiental de projectes o plans que puguin afectar l'ENP. | R48: Nombre d'informes d'AIA | S48: 1 informe/ any | T48: 2 informe/any | U48: 0.045 | V48: =PLA!U48*Llistes!$L$11*Llistes!$L$12 -> 6 | W48: Direcció | X48: =IF(W48=Llistes!$K$2,Llistes!$L$2,IF(W48=Llistes!$K$3,Llistes!$L$3,IF(W48=Llistes!$K$4,Llistes!$L$4,IF(W48=Llistes!$K$5,Llistes!$L$5,IF(W48=Llistes!$K$6,Llistes!$L$6,IF(W48=Llistes!$K$7,Llistes!$L$7,"")))))) -> Gerard Carrion | Y48: X | Z48: X | AA48: X | AB48: X
A49: NATURA | F49: 03.1.2 | G49: Exercir un seguiment efectiu de les obres al Parc juntament amb les Oficines Territorials d'Acció i Avaluació Ambiental als efectes d'assegurar la correcta translació de la tutela administrativa. | H49: Comú | I49: Obligatori | J49: Exercir un seguiment efectiu dels treballs informats a l'ENP per assegurar l'acompliment de les condicions establertes. | K49: modificació del redactat | M49: MITJANA | Q49: Fer visites als treballs informats per l'òrgan de gestió, en coordinació amb l'OTAAA. | R49: Nombre visites camp relacionades amb informes | S49: 1 | T49: 4 | U49: 0.51 | V49: =PLA!U49*Llistes!$L$11*Llistes!$L$12 -> 68 | W49: Direcció | X49: =IF(W49=Llistes!$K$2,Llistes!$L$2,IF(W49=Llistes!$K$3,Llistes!$L$3,IF(W49=Llistes!$K$4,Llistes!$L$4,IF(W49=Llistes!$K$5,Llistes!$L$5,IF(W49=Llistes!$K$6,Llistes!$L$6,IF(W49=Llistes!$K$7,Llistes!$L$7,"")))))) -> Gerard Carrion | Y49: X | Z49: X | AA49: X | AB49: X
A50: NATURA | F50: 03.1.3 | G50: Participar en la compensació d'impactes residuals durant els processos d'avaluació ambiental mitjançant la identificació de necessitats d'actuació prioritària dins i fora dels límits de l’ENP | H50: Comú | I50: Obligatori | J50: =G50 -> Participar en la compensació d'impactes residuals durant els processos d'avaluació ambiental mitjançant la identificació de necessitats d'actuació prioritària dins i fora dels límits de l’ENP | M50: MITJANA | N50: *Catàleg de possibles actuacions compensatories *Catàleg de sectors amb necessitats d'intervenció (incloent també zones fora dels límits de l'ENP que es considerin importants per al manteniment de la connectivitat ecològica dels espais) | Q50: Identificació de possibles actuacions que es poguessin incloure en el marc de mesures compensatòries derivades de l'avaluació ambiental de projectes. | R50: Redacció del catàleg | T50: Sí | U50: 0.045 | V50: =PLA!U50*Llistes!$L$11*Llistes!$L$12 -> 6 | W50: Direcció | X50: =IF(W50=Llistes!$K$2,Llistes!$L$2,IF(W50=Llistes!$K$3,Llistes!$L$3,IF(W50=Llistes!$K$4,Llistes!$L$4,IF(W50=Llistes!$K$5,Llistes!$L$5,IF(W50=Llistes!$K$6,Llistes!$L$6,IF(W50=Llistes!$K$7,Llistes!$L$7,"")))))) -> Gerard Carrion | AB50: X
A51: NATURA | D51: 03.2 | E51: Garantir el compliment dels objectius de conservació dotant l'ENP de la planificació adequada segons estableix la normativa vigent (Pla de Protecció, PRUG, plans específics...) | F51: 03.2.1 | G51: Participar en l'elaboració dels instruments de planificació de l'ENP | H51: Comú | I51: Obligatori | J51: =G51 -> Participar en l'elaboració dels instruments de planificació de l'ENP | K51: Estaríem parlant concretament del pla de protecció, en el nostre cas. | M51: MÀXIMA | N51: *Participació en l'elaboració del Pla de Protecció (PP) juntament amb l'SPEN. *Participació en l'elaboració del Pla Rector d'usos i Gestió (PRUG) juntament amb l'SPEN. *Participació en l'elaboració d'altres instruments de planificació juntament amb l'SPEN. | P51: SPEN: Elaboració del Pla rector d'usos i gestió. SPEN: Elaboració del Pla rector d'usos i gestió | Q51: Participació en l'elaboració del Pla de Protecció (PP) juntament amb el SPEN. | R51: Participació en l'elaboració del Pla de Protecció | T51: Sí | U51: 0.45 | V51: =PLA!U51*Llistes!$L$11*Llistes!$L$12 -> 60 | W51: Direcció | X51: =IF(W51=Llistes!$K$2,Llistes!$L$2,IF(W51=Llistes!$K$3,Llistes!$L$3,IF(W51=Llistes!$K$4,Llistes!$L$4,IF(W51=Llistes!$K$5,Llistes!$L$5,IF(W51=Llistes!$K$6,Llistes!$L$6,IF(W51=Llistes!$K$7,Llistes!$L$7,"")))))) -> Gerard Carrion | Y51: X | Z51: X | AA51: X | AB51: X
A52: NATURA | F52: 03.2.1 | G52: Participar en l'elaboració dels instruments de planificació de l'ENP | H52: Comú | I52: Obligatori | J52: =G52 -> Participar en l'elaboració dels instruments de planificació de l'ENP | M52: ALTA | Q52: Col·laboració amb servei de planificació amb els nous estudis a l'espai XN2000 Basses de l’Albera | R52: Col·laboració en la planificació dels estudis | T52: Sí | U52: 0.3 | V52: =PLA!U52*Llistes!$L$11*Llistes!$L$12 -> 40 | W52: XN2000 | X52: =IF(W52=Llistes!$K$2,Llistes!$L$2,IF(W52=Llistes!$K$3,Llistes!$L$3,IF(W52=Llistes!$K$4,Llistes!$L$4,IF(W52=Llistes!$K$5,Llistes!$L$5,IF(W52=Llistes!$K$6,Llistes!$L$6,IF(W52=Llistes!$K$7,Llistes!$L$7,"")))))) -> Montse Pascual | Y52: X | Z52: X | AA52: X | AB52: X
A53: NATURA | F53: 03.2.1 | G53: Participar en l'elaboració dels instruments de planificació de l'ENP | H53: Comú | I53: Obligatori | J53: =G53 -> Participar en l'elaboració dels instruments de planificació de l'ENP | M53: ALTA | Q53: Participació en l’òrgan de governança de XN2000 Basses de l’Albera | R53: Participació en l'òrgan de governança Basses Albera | T53: Sí | U53: 0.15 | V53: =PLA!U53*Llistes!$L$11*Llistes!$L$12 -> 20 | W53: XN2000 | X53: =IF(W53=Llistes!$K$2,Llistes!$L$2,IF(W53=Llistes!$K$3,Llistes!$L$3,IF(W53=Llistes!$K$4,Llistes!$L$4,IF(W53=Llistes!$K$5,Llistes!$L$5,IF(W53=Llistes!$K$6,Llistes!$L$6,IF(W53=Llistes!$K$7,Llistes!$L$7,"")))))) -> Montse Pascual | Y53: X | Z53: X | AA53: X | AB53: X
A54: NATURA | F54: 03.2.1 | G54: Participar en l'elaboració dels instruments de planificació de l'ENP | H54: Comú | I54: Obligatori | J54: =G54 -> Participar en l'elaboració dels instruments de planificació de l'ENP | M54: ALTA | Q54: Execució del projecte d’ordenació de Cap Ras (XN2000) | R54: S'ha redactat el projecte d'ordenació | T54: Sí | U54: 0.45 | V54: =PLA!U54*Llistes!$L$11*Llistes!$L$12 -> 60 | W54: Direcció | X54: =IF(W54=Llistes!$K$2,Llistes!$L$2,IF(W54=Llistes!$K$3,Llistes!$L$3,IF(W54=Llistes!$K$4,Llistes!$L$4,IF(W54=Llistes!$K$5,Llistes!$L$5,IF(W54=Llistes!$K$6,Llistes!$L$6,IF(W54=Llistes!$K$7,Llistes!$L$7,"")))))) -> Gerard Carrion | Y54: X | Z54: X | AA54: X | AB54: X
A55: NATURA | D55: 03.3 | E55: Vetllar pel manteniment dels cabals ecològics i la bona qualitat dels cursos fluvials de l'ENP de forma coordinada amb l'administració competent | F55: 03.3.1 | G55: Avaluar i controlar les actuacions que produeixin drenatges, captacions o que puguin impedir l’arribada d’aigua tant superficial com freàtica | H55: Específic | I55: Obligatori | J55: =G55 -> Avaluar i controlar les actuacions que produeixin drenatges, captacions o que puguin impedir l’arribada d’aigua tant superficial com freàtica | M55: ALTA | N55: *Participació, de forma coordinada amb l'administració competent, en l'avaluació i control d'actuacions dins els límits de l'ENP. *Impuls del control per incompliment de la normativa i el seu trasllat cap a l'administració competent *Participació en les comunitats d'usuaris de les conques | Q55: Participació, de forma coordinada amb l'administració competent, en l'avaluació i control d'actuacions dins els límits de l'ENP. | R55: Nombre de captacions il·legals identificades | T55: 0 | U55: 0.015 | V55: =PLA!U55*Llistes!$L$11*Llistes!$L$12 -> 2 | W55: Direcció | X55: =IF(W55=Llistes!$K$2,Llistes!$L$2,IF(W55=Llistes!$K$3,Llistes!$L$3,IF(W55=Llistes!$K$4,Llistes!$L$4,IF(W55=Llistes!$K$5,Llistes!$L$5,IF(W55=Llistes!$K$6,Llistes!$L$6,IF(W55=Llistes!$K$7,Llistes!$L$7,"")))))) -> Gerard Carrion | Y55: X | Z55: X | AA55: X | AB55: X
A56: NATURA | F56: 03.3.2 | G56: Vetllar per la regulació dels dragatges, canalitzacions o implantació d'activitats extractives que puguin modificar la llera i el cabal dels rius | H56: Específic | I56: Optatiu
A57: NATURA | F57: 03.3.3 | G57: Avaluar i controlar les actuacions que produeixin drenatges, captacions o que puguin impedir l’arribada d’aigua tant superficial com freàtica | H57: Específic | I57: Optatiu
A58: NATURA | F58: 03.3.4 | G58: Vetllar pel compliment de la normativa de depuració dels efluents agroramaders, urbans i industrials que s'aboquen als cursos fluvials | H58: Específic | I58: Optatiu
A59: NATURA | F59: 03.3.5 | G59: Colaborar amb l'òrgan competent per la conservació del domini públic d'acord amb les delimitacions i la normativa d'usos vigent | H59: Comú | I59: Optatiu
A60: NATURA | D60: 03.4 | E60: Incrementar el patrimoni públic destinat a la conservació i millora del patrimoni natural | F60: 03.4.1 | G60: Identificar espais prioritaris per a la compra de terrenys de més valor dins l'ENP | H60: Comú | I60: Obligatori | J60: =G60 -> Identificar espais prioritaris per a la compra de terrenys de més valor dins l'ENP | M60: ALTA | N60: *Participació en la identificació de finques prioritàries en base als criteris indicats | P60: SENP/SPEN: Facilitar els criteris a seguir | Q60: Participació en la identificació de finques prioritàries de compra en base als criteris indicats | R60: Nombre de finques identificades com a prioritàries per a la compra de terrenys (XN2000) | S60: 1 | T60: 5 | U60: 0.045 | V60: =PLA!U60*Llistes!$L$11*Llistes!$L$12 -> 6 | W60: Direcció | X60: =IF(W60=Llistes!$K$2,Llistes!$L$2,IF(W60=Llistes!$K$3,Llistes!$L$3,IF(W60=Llistes!$K$4,Llistes!$L$4,IF(W60=Llistes!$K$5,Llistes!$L$5,IF(W60=Llistes!$K$6,Llistes!$L$6,IF(W60=Llistes!$K$7,Llistes!$L$7,"")))))) -> Gerard Carrion | Y60: X | Z60: X | AA60: X | AB60: X
F61: 03.4.2 | G61: Identificar espais prioritaris per a la gestió directa | H61: Comú | I61: Optatiu
A62: CULTURA | B62: 4 | C62: CONSERVAR ELS ELEMENTS CULTURALS materials i immaterials vinculats a la natura | D62: 04.1 | E62: Millorar el coneixement disponible sobre el patrimoni arquitectònic i cultural (material i immaterial) vinculat al patrimoni natural, el seu estat de conservació i els estils propis dels territoris de l'ENP | F62: 04.1.1 | G62: Elaborar l'inventari i cartografia de patrimoni cultural de l'ENP, que també inclogui el patrimoni etnològic i immaterial | H62: Comú | I62: Obligatori | J62: Elaborar l'inventari i cartografia de patrimoni cultural de l'ENP, que també inclogui el patrimoni etnològic i immaterial | M62: MITJANA | N62: *Recopilació de la informació dels catàlegs dels ajuntaments de l'ENP i fer diagnosi *Inventari de patrimoni cultural material *Inventari de patrimoni cultural immaterial (metodologia de l'inventari de la unesco) *Elaboració d'un mapa de tranquil·litat. | Q62: Recopilació de la informació dels catàlegs d'altres admnistracions, buidat bibliogràfic, i fer diagnosi | R62: S'ha realitzat la recopilació d'informació dels diversos catàlegs existents | S62: 2 | T62: 5 | U62: 0.045 | V62: =PLA!U62*Llistes!$L$11*Llistes!$L$12 -> 6 | W62: Ús públic i educació ambiental | X62: =IF(W62=Llistes!$K$2,Llistes!$L$2,IF(W62=Llistes!$K$3,Llistes!$L$3,IF(W62=Llistes!$K$4,Llistes!$L$4,IF(W62=Llistes!$K$5,Llistes!$L$5,IF(W62=Llistes!$K$6,Llistes!$L$6,IF(W62=Llistes!$K$7,Llistes!$L$7,"")))))) -> Ivan Bustamante | Y62: X | Z62: X
A63: CULTURA | F63: 04.1.1 | G63: Elaborar l'inventari i cartografia de patrimoni cultural de l'ENP, que també inclogui el patrimoni etnològic i immaterial | H63: Comú | I63: Obligatori | J63: =J64 -> Elaborar l'inventari i cartografia de patrimoni cultural de l'ENP, que també inclogui el patrimoni etnològic i immaterial | M63: MITJANA | N63: *Recopilació de la informació dels catàlegs dels ajuntaments de l'ENP i fer diagnosi *Inventari de patrimoni cultural material *Inventari de patrimoni cultural immaterial (metodologia de l'inventari de la unesco) *Elaboració d'un mapa de tranquil·litat. | Q63: Redacció de l'inventari de patrimoni cultural material | R63: Es disposa de l'inventari de patrimoni cultural material | T63: Sí | U63: 0.045 | V63: =PLA!U63*Llistes!$L$11*Llistes!$L$12 -> 6 | W63: Direcció | X63: =IF(W63=Llistes!$K$2,Llistes!$L$2,IF(W63=Llistes!$K$3,Llistes!$L$3,IF(W63=Llistes!$K$4,Llistes!$L$4,IF(W63=Llistes!$K$5,Llistes!$L$5,IF(W63=Llistes!$K$6,Llistes!$L$6,IF(W63=Llistes!$K$7,Llistes!$L$7,"")))))) -> Gerard Carrion | AA63: X
A64: CULTURA | F64: 04.1.1 | G64: Elaborar l'inventari i cartografia de patrimoni cultural de l'ENP, que també inclogui el patrimoni etnològic i immaterial | H64: Comú | I64: Obligatori | J64: =G64 -> Elaborar l'inventari i cartografia de patrimoni cultural de l'ENP, que també inclogui el patrimoni etnològic i immaterial | M64: MITJANA | N64: *Recopilació de la informació dels catàlegs dels ajuntaments de l'ENP i fer diagnosi *Inventari de patrimoni cultural material *Inventari de patrimoni cultural immaterial (metodologia de l'inventari de la unesco) *Elaboració d'un mapa de tranquil·litat. | Q64: Redacció de l'inventari de patrimoni cultural immaterial (metodologia de l'inventari de la UNESCO) | R64: Es disposa de l'inventari de patrimoni cultural immaterial | T64: Sí | U64: 0.045 | V64: =PLA!U64*Llistes!$L$11*Llistes!$L$12 -> 6 | W64: Direcció | X64: =IF(W64=Llistes!$K$2,Llistes!$L$2,IF(W64=Llistes!$K$3,Llistes!$L$3,IF(W64=Llistes!$K$4,Llistes!$L$4,IF(W64=Llistes!$K$5,Llistes!$L$5,IF(W64=Llistes!$K$6,Llistes!$L$6,IF(W64=Llistes!$K$7,Llistes!$L$7,"")))))) -> Gerard Carrion | AA64: X
A65: CULTURA | F65: 04.1.2 | G65: Elaborar el catàleg lingüístic (localismes) de patrimoni natural, geografia popular, festes i activitats tradicionals de l'ENP | H65: Comú | I65: Obligatori | J65: =G65 -> Elaborar el catàleg lingüístic (localismes) de patrimoni natural, geografia popular, festes i activitats tradicionals de l'ENP | M65: ALTA | Q65: Redacció de l'inventari de patrimoni lingüístic | R65: Es disposa de l'inventari de patrimoni cultural lingüístic | T65: Sí | U65: 0.045 | V65: =PLA!U65*Llistes!$L$11*Llistes!$L$12 -> 6 | W65: Direcció | X65: =IF(W65=Llistes!$K$2,Llistes!$L$2,IF(W65=Llistes!$K$3,Llistes!$L$3,IF(W65=Llistes!$K$4,Llistes!$L$4,IF(W65=Llistes!$K$5,Llistes!$L$5,IF(W65=Llistes!$K$6,Llistes!$L$6,IF(W65=Llistes!$K$7,Llistes!$L$7,"")))))) -> Gerard Carrion | AB65: X
A66: CULTURA | F66: 04.1.3 | G66: Elaborar la cartografia de la xarxa de camins ramaders i senders tradicionals de l'ENP | H66: Comú | I66: Obligatori | J66: Elaborar l'inventari i cartografia de la xarxa de camins ramaders i altres vies públiques de l'ENP | K66: Recollir la informació en forma d'inventari. Fixar-nos en la propietat pública, i no tant en si és tradicional o no, molt més difícil de saber de forma objectiva i històrica. | M66: MITJANA | Q66: Redacció de l'inventari de camins ramaders o públics | R66: Es disposa de l'inventari de camins ramaders o públics | T66: Sí | U66: 0.045 | V66: =PLA!U66*Llistes!$L$11*Llistes!$L$12 -> 6 | W66: Direcció | X66: =IF(W66=Llistes!$K$2,Llistes!$L$2,IF(W66=Llistes!$K$3,Llistes!$L$3,IF(W66=Llistes!$K$4,Llistes!$L$4,IF(W66=Llistes!$K$5,Llistes!$L$5,IF(W66=Llistes!$K$6,Llistes!$L$6,IF(W66=Llistes!$K$7,Llistes!$L$7,"")))))) -> Gerard Carrion | Z66: X
A67: CULTURA | D67: 04.2 | E67: Conservar i gestionar el patrimoni cultural de l'ENP de forma coordinada amb els agents responsables i entitats de referència | F67: 04.2.1 | G67: Identificar els ens de referència en patrimoni cultural (entitats, associacions, museus i ecomuseus, etc.) en l'àmbit de l'ENP | H67: Comú | I67: Obligatori | J67: =G67 -> Identificar els ens de referència en patrimoni cultural (entitats, associacions, museus i ecomuseus, etc.) en l'àmbit de l'ENP | K67: Diria que ja està fet, però s'hauria de revisar. | M67: MITJANA | N67: *Elaboració d'un mapa d'entitats, associacions, museus, ecomuseus, OPEI (Observatori del Patrimoni Etnològic i Immaterial), etc. | Q67: Elaboració d'un mapa d'entitats, associacions, museus, ecomuseus, OPEI (Observatori del Patrimoni Etnològic i Immaterial), etc. | R67: Es disposa d'un mapa d'entitats, associacions, museus, ecomuseus, OPEI, etc | T67: Sí | U67: 0.045 | V67: =PLA!U67*Llistes!$L$11*Llistes!$L$12 -> 6 | W67: Ús públic i educació ambiental | X67: =IF(W67=Llistes!$K$2,Llistes!$L$2,IF(W67=Llistes!$K$3,Llistes!$L$3,IF(W67=Llistes!$K$4,Llistes!$L$4,IF(W67=Llistes!$K$5,Llistes!$L$5,IF(W67=Llistes!$K$6,Llistes!$L$6,IF(W67=Llistes!$K$7,Llistes!$L$7,"")))))) -> Ivan Bustamante | Y67: X
A68: CULTURA | F68: 04.2.1 | G68: Identificar els ens de referència en patrimoni cultural (entitats, associacions, museus i ecomuseus, etc.) en l'àmbit de l'ENP | H68: Comú | I68: Obligatori | J68: =G68 -> Identificar els ens de referència en patrimoni cultural (entitats, associacions, museus i ecomuseus, etc.) en l'àmbit de l'ENP | K68: Diria que ja està fet, però s'hauria de revisar. | M68: MITJANA | N68: *Elaboració d'un mapa d'entitats, associacions, museus, ecomuseus, OPEI (Observatori del Patrimoni Etnològic i Immaterial), etc. | Q68: Impuls de col·laboració amb la xarxa de museus i altres equipaments i entitats de referència | R68: Nombre d'activitats en col·laboració amb la xarxa de museus i altres equipaments i entitats de referència | S68: 2 | T68: 4 | U68: 0.015 | V68: =PLA!U68*Llistes!$L$11*Llistes!$L$12 -> 2 | W68: Ús públic i educació ambiental | X68: =IF(W68=Llistes!$K$2,Llistes!$L$2,IF(W68=Llistes!$K$3,Llistes!$L$3,IF(W68=Llistes!$K$4,Llistes!$L$4,IF(W68=Llistes!$K$5,Llistes!$L$5,IF(W68=Llistes!$K$6,Llistes!$L$6,IF(W68=Llistes!$K$7,Llistes!$L$7,"")))))) -> Ivan Bustamante | Y68: X | Z68: X | AA68: X | AB68: X
A69: CULTURA | F69: 04.2.2 | G69: Articular treballs conjunts entre l'ENP i representants, gestors o custodis del patrimoni cultural per a la seva protecció i millora | H69: Comú | I69: Obligatori | J69: =G69 -> Articular treballs conjunts entre l'ENP i representants, gestors o custodis del patrimoni cultural per a la seva protecció i millora | K69: Els convenis són una forma jurídica difícil de portar a la pràctica. Val més parlar de col·laboració o acords. | M69: MITJANA | N69: *Projecte parcs i museus *Impuls dels convenis de col·laboració amb la xarxa de museus i altres equipaments i entitats de referència *Foment de la cooperació tècnica dels gestors de l'ENP amb els representants o custodis del patrimoni cultural, i coordinar-ne l'ús compartit dels recursos | Q69: Foment de la cooperació tècnica dels gestors de l'ENP amb els representants o custodis del patrimoni cultural, per a un ús compartit dels recursos | R69: Nombre de reunions relacionades amb la cooperació tècnica dels gestors de l'ENP amb els representants del patrimoni cultural | S69: 2 | T69: 4 | U69: 0.015 | V69: =PLA!U69*Llistes!$L$11*Llistes!$L$12 -> 2 | W69: Ús públic i educació ambiental | X69: =IF(W69=Llistes!$K$2,Llistes!$L$2,IF(W69=Llistes!$K$3,Llistes!$L$3,IF(W69=Llistes!$K$4,Llistes!$L$4,IF(W69=Llistes!$K$5,Llistes!$L$5,IF(W69=Llistes!$K$6,Llistes!$L$6,IF(W69=Llistes!$K$7,Llistes!$L$7,"")))))) -> Ivan Bustamante | Y69: X | Z69: X | AA69: X | AB69: X
A70: CULTURA | F70: 04.2.2 | G70: Articular treballs conjunts entre l'ENP i representants, gestors o custodis del patrimoni cultural per a la seva protecció i millora | H70: Comú | I70: Obligatori | J70: =G70 -> Articular treballs conjunts entre l'ENP i representants, gestors o custodis del patrimoni cultural per a la seva protecció i millora | K70: Els convenis són una forma jurídica difícil de portar a la pràctica. Val més parlar de col·laboració o acords. | M70: MITJANA | N70: *Projecte parcs i museus *Impuls dels convenis de col·laboració amb la xarxa de museus i altres equipaments i entitats de referència *Foment de la cooperació tècnica dels gestors de l'ENP amb els representants o custodis del patrimoni cultural, i coordinar-ne l'ús compartit dels recursos | Q70: Coordinació de l'equip tècnic (propi) amb els responsables dels treballs de restauració arquitectònica i del patrimoni cultural | R70: Nombre de reunions amb els responsables dels treballs de restauració arquitectònica i del patrimoni cultural | S70: 2 | T70: 4 | U70: 0.015 | V70: =PLA!U70*Llistes!$L$11*Llistes!$L$12 -> 2 | W70: Direcció | X70: =IF(W70=Llistes!$K$2,Llistes!$L$2,IF(W70=Llistes!$K$3,Llistes!$L$3,IF(W70=Llistes!$K$4,Llistes!$L$4,IF(W70=Llistes!$K$5,Llistes!$L$5,IF(W70=Llistes!$K$6,Llistes!$L$6,IF(W70=Llistes!$K$7,Llistes!$L$7,"")))))) -> Gerard Carrion | Y70: X | Z70: X | AA70: X | AB70: X
A71: CULTURA | F71: 04.2.3 | G71: Impulsar i/o participar dels treballs de restauració arquitectònica, arqueològica i del patrimoni cultural | H71: Comú | I71: Obligatori | J71: =G71 -> Impulsar i/o participar dels treballs de restauració arquitectònica, arqueològica i del patrimoni cultural | M71: MITJANA | N71: *Coordinació de l'equip tècnic (propi) amb els responsables dels treballs de restauració arquitectònica i del patrimoni cultural *Participació quan els treballs estan vinculats a l’àrea d’ús públic de l’ENP | Q71: Participació en els treballs de restauració arquitectònica i del patrimoni cultural quan estan vinculats a l’àrea d’ús públic de l’ENP | R71: Nombre de treballs en què s'ha participat | S71: 1 | T71: 2 | U71: 0.015 | V71: =PLA!U71*Llistes!$L$11*Llistes!$L$12 -> 2 | W71: Direcció | X71: =IF(W71=Llistes!$K$2,Llistes!$L$2,IF(W71=Llistes!$K$3,Llistes!$L$3,IF(W71=Llistes!$K$4,Llistes!$L$4,IF(W71=Llistes!$K$5,Llistes!$L$5,IF(W71=Llistes!$K$6,Llistes!$L$6,IF(W71=Llistes!$K$7,Llistes!$L$7,"")))))) -> Gerard Carrion | Y71: X | Z71: X | AA71: X | AB71: X
F72: 04.2.4 | G72: Disposar de personal especialitzat en patrimoni cultural | H72: Comú | I72: Obligatori
A73: CULTURA | D73: 04.3 | E73: Potenciar la conservació i recuperació del patrimoni cultural material i immaterial de l'ENP | F73: 04.3.1 | G73: Recuperar i conservar el patrimoni cultural immaterial (associat a les activitats i aprofitaments rurals tradicionals) i els valors espirituals | H73: Específic | I73: Obligatori | J73: =G73 -> Recuperar i conservar el patrimoni cultural immaterial (associat a les activitats i aprofitaments rurals tradicionals) i els valors espirituals | M73: MITJANA | O73: MAP | Q73: Col·laborar en mantenir el patrimoni cultural immaterial. | R73: Nombre d'actuacions de col·laboració per mantenir el patrimoni cultural immaterial | S73: 4 | T73: 8 | U73: 0.015 | V73: 2 | W73: Manteniment | X73: =IF(W73=Llistes!$K$2,Llistes!$L$2,IF(W73=Llistes!$K$3,Llistes!$L$3,IF(W73=Llistes!$K$4,Llistes!$L$4,IF(W73=Llistes!$K$5,Llistes!$L$5,IF(W73=Llistes!$K$6,Llistes!$L$6,IF(W73=Llistes!$K$7,Llistes!$L$7,"")))))) -> Sergi Roura | Y73: X | Z73: X | AA73: X | AB73: X
A74: CULTURA | F74: 04.3.2 | G74: Recuperar i conservar el patrimoni cultural rural vinculat específicament a construccions de pedra en sec | H74: Comú | I74: Obligatori | J74: =G74 -> Recuperar i conservar el patrimoni cultural rural vinculat específicament a construccions de pedra en sec | M74: MITJANA | Q74: Conservació de construccions de pedra seca | R74: Nombre d'actuacions amb pedra seca | S74: 2 | T74: 4 | U74: 0.045 | V74: =PLA!U74*Llistes!$L$11*Llistes!$L$12 -> 6 | W74: Manteniment | X74: =IF(W74=Llistes!$K$2,Llistes!$L$2,IF(W74=Llistes!$K$3,Llistes!$L$3,IF(W74=Llistes!$K$4,Llistes!$L$4,IF(W74=Llistes!$K$5,Llistes!$L$5,IF(W74=Llistes!$K$6,Llistes!$L$6,IF(W74=Llistes!$K$7,Llistes!$L$7,"")))))) -> Sergi Roura | Y74: X | Z74: X | AA74: X | AB74: X
A75: CULTURA | F75: 04.3.3 | G75: Fomentar la recuperació i conservació de l'arquitectura tradicional d'interès de les edificacions i construccions | H75: Comú | I75: Obligatori | J75: =G75 -> Fomentar la recuperació i conservació de l'arquitectura tradicional d'interès de les edificacions i construccions | M75: MITJANA | Q75: Foment de la recuperació i conservació de l'arquitectura tradicional d'interès de les edificacions i construccions | R75: Nombre d'actuacions vinculades amb la recuperació i conservació de l'arquitectura tradicional d'interès de les edificacions i construccions | S75: 2 | T75: 4 | U75: 0.015 | V75: =PLA!U75*Llistes!$L$11*Llistes!$L$12 -> 2 | W75: Manteniment | X75: =IF(W75=Llistes!$K$2,Llistes!$L$2,IF(W75=Llistes!$K$3,Llistes!$L$3,IF(W75=Llistes!$K$4,Llistes!$L$4,IF(W75=Llistes!$K$5,Llistes!$L$5,IF(W75=Llistes!$K$6,Llistes!$L$6,IF(W75=Llistes!$K$7,Llistes!$L$7,"")))))) -> Sergi Roura | Y75: X | Z75: X | AA75: X | AB75: X
A76: CULTURA | F76: 04.3.4 | G76: Identificar i conservar la diversitat domesticada de varietats agrícoles i ramaderes locals | H76: Comú | I76: Obligatori | J76: =G76 -> Identificar i conservar la diversitat domesticada de varietats agrícoles i ramaderes locals | K76: Ja s'està fent per a la vaca de l'Albera sense la nostra participació, i és que tampoc hi arribem | M76: BAIXA | N76: *Banc de llavors *Convenis ramaders per la cria de races locals | O76: ESNATURA | Q76: Conservar les varietats locals en planters (de llavor o esqueix). | R76: Nombre de varietats locals que s'han col·laborat a mantenir | S76: 3 | T76: 6 | U76: 0.015 | V76: =PLA!U76*Llistes!$L$11*Llistes!$L$12 -> 2 | W76: Direcció | X76: =IF(W76=Llistes!$K$2,Llistes!$L$2,IF(W76=Llistes!$K$3,Llistes!$L$3,IF(W76=Llistes!$K$4,Llistes!$L$4,IF(W76=Llistes!$K$5,Llistes!$L$5,IF(W76=Llistes!$K$6,Llistes!$L$6,IF(W76=Llistes!$K$7,Llistes!$L$7,"")))))) -> Gerard Carrion | Y76: X | Z76: X | AA76: X | AB76: X
Q77: Col·laborar en mantenir arbres fruiters de varietats locals situats al costat dels masos del massís. | R77: Nombre d'arbres fruiters de varietats locals que s'han col·laborat a mantenir | S77: 5 | T77: 8 | U77: 0.015 | V77: =PLA!U77*Llistes!$L$11*Llistes!$L$12 -> 2 | W77: Direcció | X77: =IF(W77=Llistes!$K$2,Llistes!$L$2,IF(W77=Llistes!$K$3,Llistes!$L$3,IF(W77=Llistes!$K$4,Llistes!$L$4,IF(W77=Llistes!$K$5,Llistes!$L$5,IF(W77=Llistes!$K$6,Llistes!$L$6,IF(W77=Llistes!$K$7,Llistes!$L$7,"")))))) -> Gerard Carrion | Y77: X | Z77: X | AA77: X | AB77: X
A78: CULTURA | D78: 04.4 | E78: Donar a conèixer els elements culturals com a valors del paisatge de l'ENP en les activitats d'ús públic | F78: 04.4.1 | G78: Integrar el patrimoni cultural als itineraris i cartelleria de l'ENP. | H78: Comú | I78: Obligatori | J78: =G78 -> Integrar el patrimoni cultural als itineraris i cartelleria de l'ENP. | K78: Ja es té en compte, però així es visualitza. | M78: ALTA | Q78: Integració del patrimoni cultural als itineraris i cartelleria de l'ENP. | R78: Nombre de cartells de patrimoni cultural que s'han integrat en la cartelleria de l'ENP (nous o manteniment) | S78: 4 | T78: 10 | U78: 0.015 | V78: =PLA!U78*Llistes!$L$11*Llistes!$L$12 -> 2 | W78: Ús públic i educació ambiental | X78: =IF(W78=Llistes!$K$2,Llistes!$L$2,IF(W78=Llistes!$K$3,Llistes!$L$3,IF(W78=Llistes!$K$4,Llistes!$L$4,IF(W78=Llistes!$K$5,Llistes!$L$5,IF(W78=Llistes!$K$6,Llistes!$L$6,IF(W78=Llistes!$K$7,Llistes!$L$7,"")))))) -> Ivan Bustamante | Y78: X | Z78: X | AA78: X | AB78: X
A79: CULTURA | F79: 04.4.2 | G79: Incorporar el patrimoni cultural en els plans d’ús públic i educació ambiental per fomentar-ne la seva conservació i divulgació. | H79: Comú | I79: Obligatori | J79: =G79 -> Incorporar el patrimoni cultural en els plans d’ús públic i educació ambiental per fomentar-ne la seva conservació i divulgació. | K79: Ja es té en compte, però així es visualitza. | M79: ALTA | Q79: Incorporació del patrimoni cultural en els plans d’ús públic i educació ambiental | R79: S'incorpora el patrimoni cultural en els plans d’ús públic i educació ambiental | T79: Sí | U79: 0.015 | V79: =PLA!U79*Llistes!$L$11*Llistes!$L$12 -> 2 | W79: Ús públic i educació ambiental | X79: =IF(W79=Llistes!$K$2,Llistes!$L$2,IF(W79=Llistes!$K$3,Llistes!$L$3,IF(W79=Llistes!$K$4,Llistes!$L$4,IF(W79=Llistes!$K$5,Llistes!$L$5,IF(W79=Llistes!$K$6,Llistes!$L$6,IF(W79=Llistes!$K$7,Llistes!$L$7,"")))))) -> Ivan Bustamante | Y79: X | Z79: X | AA79: X | AB79: X
A80: CULTURA | F80: 04.4.3 | G80: Formar el personal dels punts d’informació en els valors culturals de l'ENP | H80: Comú | I80: Obligatori | J80: =G80 -> Formar el personal dels punts d’informació en els valors culturals de l'ENP | M80: MÀXIMA | Q80: Formació del personal dels punts d'informació (propi o aliè) en els valors culturals de l'ENP. | R80: Hores de formació sobre els valors culturals | S80: 2 | T80: 4 | U80: 0.015 | V80: =PLA!U80*Llistes!$L$11*Llistes!$L$12 -> 2 | W80: Ús públic i educació ambiental | X80: =IF(W80=Llistes!$K$2,Llistes!$L$2,IF(W80=Llistes!$K$3,Llistes!$L$3,IF(W80=Llistes!$K$4,Llistes!$L$4,IF(W80=Llistes!$K$5,Llistes!$L$5,IF(W80=Llistes!$K$6,Llistes!$L$6,IF(W80=Llistes!$K$7,Llistes!$L$7,"")))))) -> Ivan Bustamante | Y80: X | Z80: X | AA80: X | AB80: X
A81: CULTURA | B81: 5 | C81: PROTEGIR EL PAISATGE i la qualitat de l'ambient visual, sonor i lumínic. | D81: 05.1 | E81: Identificar els elements d'interès paisatgístic de l'espai | F81: 05.1.1 | G81: Elaborar un inventari d'elements d'interès paisatgístic de l'ENP d'acord amb el Catàleg de paisatge de la zona | H81: Comú | I81: Obligatori | J81: =G81 -> Elaborar un inventari d'elements d'interès paisatgístic de l'ENP d'acord amb el Catàleg de paisatge de la zona | M81: MITJANA | Q81: Redacció de l'inventari d'elements d'interès paisatgístic de l'ENP d'acord amb el Catàleg de paisatge de la zona | R81: S'ha redactat l'inventari d'elements d'interès paisatgístic de l'ENP d'acord amb el Catàleg de paisatge de la zona | T81: Sí | U81: 0.015 | V81: =PLA!U81*Llistes!$L$11*Llistes!$L$12 -> 2 | W81: Ús públic i educació ambiental | X81: =IF(W81=Llistes!$K$2,Llistes!$L$2,IF(W81=Llistes!$K$3,Llistes!$L$3,IF(W81=Llistes!$K$4,Llistes!$L$4,IF(W81=Llistes!$K$5,Llistes!$L$5,IF(W81=Llistes!$K$6,Llistes!$L$6,IF(W81=Llistes!$K$7,Llistes!$L$7,"")))))) -> Ivan Bustamante | Y81: X | Z81: X | AA81: X | AB81: X
A82: CULTURA | D82: 05.2 | E82: Millorar la qualitat paisatgística | F82: 05.2.1 | G82: Minimitzar la brutícia, deixalles, vandalisme i males praxis dins l'ENP | H82: Comú | I82: Obligatori | J82: Minimitzar la brutícia, deixalles, vandalisme i males praxis dins l'ENP | M82: MITJANA | Q82: Identificació dels punts on s'acumulen més deixalles. | R82: Nombre de zones d'acumulació de deixalles | S82: 0 | T82: 0 | U82: 0.015 | V82: =PLA!U82*Llistes!$L$11*Llistes!$L$12 -> 2 | W82: Manteniment | X82: =IF(W82=Llistes!$K$2,Llistes!$L$2,IF(W82=Llistes!$K$3,Llistes!$L$3,IF(W82=Llistes!$K$4,Llistes!$L$4,IF(W82=Llistes!$K$5,Llistes!$L$5,IF(W82=Llistes!$K$6,Llistes!$L$6,IF(W82=Llistes!$K$7,Llistes!$L$7,"")))))) -> Sergi Roura | Y82: X | Z82: X | AA82: X | AB82: X
A83: CULTURA | F83: 05.2.1 | G83: Minimitzar la brutícia, deixalles, vandalisme i males praxis dins l'ENP | H83: Comú | I83: Obligatori | J83: Minimitzar la brutícia, deixalles, vandalisme i males praxis dins l'ENP | M83: MITJANA | Q83: Reforç de la vigilància en els punts on s'acumulen més deixalles. | R83: S'ha realitzat algun tipus de vigilància | T83: Sí | U83: 0.015 | V83: =PLA!U83*Llistes!$L$11*Llistes!$L$12 -> 2 | W83: Direcció | X83: =IF(W83=Llistes!$K$2,Llistes!$L$2,IF(W83=Llistes!$K$3,Llistes!$L$3,IF(W83=Llistes!$K$4,Llistes!$L$4,IF(W83=Llistes!$K$5,Llistes!$L$5,IF(W83=Llistes!$K$6,Llistes!$L$6,IF(W83=Llistes!$K$7,Llistes!$L$7,"")))))) -> Gerard Carrion | Y83: X | Z83: X | AA83: X | AB83: X
A84: CULTURA | F84: 05.2.1 | G84: Minimitzar la brutícia, deixalles, vandalisme i males praxis dins l'ENP | H84: Comú | I84: Obligatori | J84: =G84 -> Minimitzar la brutícia, deixalles, vandalisme i males praxis dins l'ENP | M84: MITJANA | Q84: Reforç de la senyalització, si es considera oportú. | R84: S'ha instal·lat cartelleria a les zones conflictives | T84: Sí | U84: 0.015 | V84: =PLA!U84*Llistes!$L$11*Llistes!$L$12 -> 2 | W84: Manteniment | X84: =IF(W84=Llistes!$K$2,Llistes!$L$2,IF(W84=Llistes!$K$3,Llistes!$L$3,IF(W84=Llistes!$K$4,Llistes!$L$4,IF(W84=Llistes!$K$5,Llistes!$L$5,IF(W84=Llistes!$K$6,Llistes!$L$6,IF(W84=Llistes!$K$7,Llistes!$L$7,"")))))) -> Sergi Roura | Y84: X | Z84: X | AA84: X | AB84: X
A85: CULTURA | D85: 05.3 | E85: Protegir la qualitat acústica i lumínica de l'ENP | F85: 05.3.1 | G85: Promoure la certificació de zones d'especial protecció de la qualitat acústica | H85: Específic | I85: Obligatori | J85: Promoure la declaració de zones d'especial protecció de la qualitat acústica, d'acord amb els ajuntaments | K85: Els ajuntaments hi han d'estar interessats (ho han d'incloure al seu mapa de capacitat acústica en 6 mesos), i la declaració és de la DGQA | M85: MITJANA | O85: ESNATURA | Q85: Coordinació per a la declaració de l'ENP com a ZEPQA, d'acord amb els ajuntaments. | R85: S'ha iniciat la tramitació d'alguna ZEPQA | T85: Sí | U85: 0.015 | V85: =PLA!U85*Llistes!$L$11*Llistes!$L$12 -> 2 | W85: Direcció | X85: =IF(W85=Llistes!$K$2,Llistes!$L$2,IF(W85=Llistes!$K$3,Llistes!$L$3,IF(W85=Llistes!$K$4,Llistes!$L$4,IF(W85=Llistes!$K$5,Llistes!$L$5,IF(W85=Llistes!$K$6,Llistes!$L$6,IF(W85=Llistes!$K$7,Llistes!$L$7,"")))))) -> Gerard Carrion | AB85: X
A86: CULTURA | F86: 05.3.2 | G86: Promoure la certificació de zones d'especial protecció de la qualitat acústica | H86: Específic | I86: Optatiu
A87: CONEIXEMENT | B87: 6 | C87: MILLORAR EL CONEIXEMENT DE L'ENTORN, del patrimoni natural, cultural i social. | D87: 06.1 | E87: Identificar els objectes de gestió prioritària de l'ENP en el marc dels objectius de govern | F87: 06.1.1 | G87: Identificar i prioritzar els elements clau i d'interès per a la gestió de la biodiversitat i geodiversitat de Catalunya que es troben dins l'ENP (espècies amenaçades, espècies exòtiques invasores,.. ) | H87: Comú | I87: Obligatori | J87: =G87 -> Identificar i prioritzar els elements clau i d'interès per a la gestió de la biodiversitat i geodiversitat de Catalunya que es troben dins l'ENP (espècies amenaçades, espècies exòtiques invasores,.. ) | M87: MÀXIMA | N87: *Participació en la definició dels objectes de conservació clau (hàbitats, espècies, processos i elements d’interès geològic) comuns a nivell de Xarxa d'ENP o clúster territorial | O87: Directriva Habitats Carta emplaçament ESNATURA Catàlegs | P87: UIC/SFF/SPEN: Definir criteris d'identificació d'elements interès. UIC/SFF/SPEN: Definició dels objectes de conservació clau comuns a nivell de Xarxa d'ENP o clúster territorial | Q87: Participació en la definició dels objectes de conservació clau (hàbitats, espècies, processos i elements d’interès geològic) comuns a nivell de Xarxa d'ENP o clúster territorial | R87: Nombre de reunions en què s'ha participat en la definició dels objectes de conservació. | S87: 2 | T87: 5 | U87: 0.015 | V87: =PLA!U87*Llistes!$L$11*Llistes!$L$12 -> 2 | W87: Patrimoni natural | X87: =IF(W87=Llistes!$K$2,Llistes!$L$2,IF(W87=Llistes!$K$3,Llistes!$L$3,IF(W87=Llistes!$K$4,Llistes!$L$4,IF(W87=Llistes!$K$5,Llistes!$L$5,IF(W87=Llistes!$K$6,Llistes!$L$6,IF(W87=Llistes!$K$7,Llistes!$L$7,"")))))) -> Pau Federico | Y87: X | Z87: X | AA87: X | AB87: X
A88: CONEIXEMENT | F88: 06.1.2 | G88: Definir espais fràgils i zones d'especial atenció | H88: Comú | I88: Obligatori | J88: =G88 -> Definir espais fràgils i zones d'especial atenció | M88: MÀXIMA | N88: *Generació d'informació per a l'inventari i cartografia d'espais fràgils *Realització o actualització de l'inventari de ZH, espais interès geològic, etc. | P88: SPEN: Inventari i cartografia d'espais fràgils i zones d'especial atenció | Q88: S'ha participat en la realització o actualització de l'inventari de ZH, espais interès geològic, etc. | R88: Nombre de reunions en què s'ha participat per l'actualització de l'inventari de ZH, espais d'interès geològic | S88: 2 | T88: 5 | U88: 0.015 | V88: =PLA!U88*Llistes!$L$11*Llistes!$L$12 -> 2 | W88: Direcció | X88: =IF(W88=Llistes!$K$2,Llistes!$L$2,IF(W88=Llistes!$K$3,Llistes!$L$3,IF(W88=Llistes!$K$4,Llistes!$L$4,IF(W88=Llistes!$K$5,Llistes!$L$5,IF(W88=Llistes!$K$6,Llistes!$L$6,IF(W88=Llistes!$K$7,Llistes!$L$7,"")))))) -> Gerard Carrion | Y88: X | Z88: X | AA88: X | AB88: X
A89: CONEIXEMENT | F89: 06.1.2 | G89: Definir espais fràgils i zones d'especial atenció | H89: Comú | I89: Obligatori | J89: =G89 -> Definir espais fràgils i zones d'especial atenció | M89: MÀXIMA | N89: *Generació d'informació per a l'inventari i cartografia d'espais fràgils *Realització o actualització de l'inventari de ZH, espais interès geològic, etc. | Q89: Redacció del treball tècnic sobre els hàbitats presents a les basses | R89: S'ha redactat el treball | T89: Sí | U89: 0.15 | V89: =PLA!U89*Llistes!$L$11*Llistes!$L$12 -> 20 | W89: XN2000 | X89: =IF(W89=Llistes!$K$2,Llistes!$L$2,IF(W89=Llistes!$K$3,Llistes!$L$3,IF(W89=Llistes!$K$4,Llistes!$L$4,IF(W89=Llistes!$K$5,Llistes!$L$5,IF(W89=Llistes!$K$6,Llistes!$L$6,IF(W89=Llistes!$K$7,Llistes!$L$7,"")))))) -> Montse Pascual | Y89: X
A90: CONEIXEMENT | D90: 06.2 | E90: Conèixer l'estat de conservació i la seva tendència dels hàbitats, les espècies els elements de la gea i els processos ecològics com a eina per avaluar i optimitzar la gestió | F90: 06.2.1 | G90: Participar en l'elaboració de la cartografia que elabora la UIC | H90: Comú | I90: Obligatori | J90: =G90 -> Participar en l'elaboració de la cartografia que elabora la UIC | M90: ALTA | N90: *Participació en la programació de la realització de la cartografia d'hàbitats en el contracte plurienal que existeix amb GeoVeg-UB | O90: ESNATURA | P90: UIC: Coordinar i contractar l'elaboració de la cartografia | Q90: Participació en la programació de la realització de la cartografia d'hàbitats en el contracte pluriennal que existeix amb GeoVeg-UB | R90: Nombre de reunions en què s'ha participat en la programació de la cartografia d'hàbitats | S90: 1 | T90: 3 | U90: 0.015 | V90: =PLA!U90*Llistes!$L$11*Llistes!$L$12 -> 2 | W90: Direcció | X90: =IF(W90=Llistes!$K$2,Llistes!$L$2,IF(W90=Llistes!$K$3,Llistes!$L$3,IF(W90=Llistes!$K$4,Llistes!$L$4,IF(W90=Llistes!$K$5,Llistes!$L$5,IF(W90=Llistes!$K$6,Llistes!$L$6,IF(W90=Llistes!$K$7,Llistes!$L$7,"")))))) -> Gerard Carrion | Y90: X | Z90: X | AA90: X | AB90: X
A91: CONEIXEMENT | F91: 06.2.2 | G91: Conèixer i estudiar els processos naturals propis de l’espai, la seva funcionalitat, i ecologia en referència als ecosistemes | H91: Comú | I91: Obligatori | J91: =G91 -> Conèixer i estudiar els processos naturals propis de l’espai, la seva funcionalitat, i ecologia en referència als ecosistemes | M91: MITJANA | N91: *Foment i coordinació dels estudis d'ecologia del foc, el règim hidrològic, la pol·linització, la tipificació i funcionament de les cadenes tròfiques pròpies de l’espai, la dinàmica de la neu i les allaus, dinàmica litoral, dinàmica geomorfològica i morfodinàmica de les roques, etc. *Millora del coneixement de la geoconservació (escala més detallada de 1:50.000) *Implementació del protocol de fluxos d'informació i coneixement de biodiversitat | Q91: Foment i coordinació dels estudis d'ecologia del foc, el règim hidrològic, la pol·linització, la tipificació i funcionament de les cadenes tròfiques pròpies de l’espai, la dinàmica geomorfològica i morfodinàmica de les roques, etc. | R91: Nombre de reunions per fomentar i coordinar estudis diversos relacionats amb els processos naturals de l'ENP | S91: 1 | T91: 3 | U91: 0.015 | V91: =PLA!U91*Llistes!$L$11*Llistes!$L$12 -> 2 | W91: Direcció | X91: =IF(W91=Llistes!$K$2,Llistes!$L$2,IF(W91=Llistes!$K$3,Llistes!$L$3,IF(W91=Llistes!$K$4,Llistes!$L$4,IF(W91=Llistes!$K$5,Llistes!$L$5,IF(W91=Llistes!$K$6,Llistes!$L$6,IF(W91=Llistes!$K$7,Llistes!$L$7,"")))))) -> Gerard Carrion | Y91: X | Z91: X | AA91: X | AB91: X
A92: CONEIXEMENT | F92: 06.2.2 | G92: Conèixer i estudiar els processos naturals propis de l’espai, la seva funcionalitat, i ecologia en referència als ecosistemes | H92: Comú | I92: Obligatori | J92: =G92 -> Conèixer i estudiar els processos naturals propis de l’espai, la seva funcionalitat, i ecologia en referència als ecosistemes | M92: MITJANA | N92: *Foment i coordinació dels estudis d'ecologia del foc, el règim hidrològic, la pol·linització, la tipificació i funcionament de les cadenes tròfiques pròpies de l’espai, la dinàmica de la neu i les allaus, dinàmica litoral, dinàmica geomorfològica i morfodinàmica de les roques, etc. *Millora del coneixement de la geoconservació (escala més detallada de 1:50.000) *Implementació del protocol de fluxos d'informació i coneixement de biodiversitat | Q92: Millora del coneixement de la geoconservació (escala més detallada de 1:50.000) | R92: Nombre d'estudis sobre geoconservació | S92: 0 | T92: 1 | U92: 0.015 | V92: =PLA!U92*Llistes!$L$11*Llistes!$L$12 -> 2 | W92: Direcció | X92: =IF(W92=Llistes!$K$2,Llistes!$L$2,IF(W92=Llistes!$K$3,Llistes!$L$3,IF(W92=Llistes!$K$4,Llistes!$L$4,IF(W92=Llistes!$K$5,Llistes!$L$5,IF(W92=Llistes!$K$6,Llistes!$L$6,IF(W92=Llistes!$K$7,Llistes!$L$7,"")))))) -> Gerard Carrion | Y92: X | Z92: X | AA92: X | AB92: X
A93: CONEIXEMENT | F93: 06.2.2 | G93: Conèixer i estudiar els processos naturals propis de l’espai, la seva funcionalitat, i ecologia en referència als ecosistemes | H93: Comú | I93: Obligatori | J93: =G93 -> Conèixer i estudiar els processos naturals propis de l’espai, la seva funcionalitat, i ecologia en referència als ecosistemes | M93: MITJANA | N93: *Foment i coordinació dels estudis d'ecologia del foc, el règim hidrològic, la pol·linització, la tipificació i funcionament de les cadenes tròfiques pròpies de l’espai, la dinàmica de la neu i les allaus, dinàmica litoral, dinàmica geomorfològica i morfodinàmica de les roques, etc. *Millora del coneixement de la geoconservació (escala més detallada de 1:50.000) *Implementació del protocol de fluxos d'informació i coneixement de biodiversitat | Q93: Implementació del protocol de fluxos d'informació i coneixement de biodiversitat | R93: S'han implementat fluxos d'informació i coneixement de la biodiversitat | T93: Sí | U93: 0.015 | V93: =PLA!U93*Llistes!$L$11*Llistes!$L$12 -> 2 | W93: Patrimoni natural | X93: =IF(W93=Llistes!$K$2,Llistes!$L$2,IF(W93=Llistes!$K$3,Llistes!$L$3,IF(W93=Llistes!$K$4,Llistes!$L$4,IF(W93=Llistes!$K$5,Llistes!$L$5,IF(W93=Llistes!$K$6,Llistes!$L$6,IF(W93=Llistes!$K$7,Llistes!$L$7,"")))))) -> Pau Federico | Y93: X | Z93: X | AA93: X | AB93: X
A94: CONEIXEMENT | F94: 06.2.2 | G94: Conèixer i estudiar els processos naturals propis de l’espai, la seva funcionalitat, i ecologia en referència als ecosistemes | H94: Comú | I94: Obligatori | J94: =G94 -> Conèixer i estudiar els processos naturals propis de l’espai, la seva funcionalitat, i ecologia en referència als ecosistemes | M94: MÀXIMA | N94: *Foment de l'estudi de l'afectació de determinats processos naturals o activitats antròpiques (contaminació, fragmentació d'hàbitats, atropellaments, noves arts de pesca o pràctiques agrícoles de muntanya, etc.) en l’ENP (amenaces i impacte ambiental). *Avaluació de l'impacte del canvi climàtic en l'ENP i la seva capacitat d'adaptació i resiliència. *Avaluació dels resultats de les estratègies de gestió aplicades en l'ENP *Col.laboració amb l?Observatori per aportar els coneixements generats a l'ENP. | Q94: Foment de l'estudi de l'afectació de determinats processos naturals o activitats antròpiques en l’ENP (amenaces i impacte ambiental). | R94: Nombre d'estudis sobre processos naturals o activitats antròpiques que afecten l'ENP. | S94: 1 | T94: 2 | U94: 0.015 | V94: =PLA!U94*Llistes!$L$11*Llistes!$L$12 -> 2 | W94: Patrimoni natural | X94: =IF(W94=Llistes!$K$2,Llistes!$L$2,IF(W94=Llistes!$K$3,Llistes!$L$3,IF(W94=Llistes!$K$4,Llistes!$L$4,IF(W94=Llistes!$K$5,Llistes!$L$5,IF(W94=Llistes!$K$6,Llistes!$L$6,IF(W94=Llistes!$K$7,Llistes!$L$7,"")))))) -> Pau Federico | Y94: X | Z94: X | AA94: X | AB94: X
A95: CONEIXEMENT | F95: 06.2.2 | G95: Conèixer i estudiar els processos naturals propis de l’espai, la seva funcionalitat, i ecologia en referència als ecosistemes | H95: Comú | I95: Obligatori | J95: =G95 -> Conèixer i estudiar els processos naturals propis de l’espai, la seva funcionalitat, i ecologia en referència als ecosistemes | M95: ALTA | N95: *Foment de l'estudi de l'afectació de determinats processos naturals o activitats antròpiques (contaminació, fragmentació d'hàbitats, atropellaments, noves arts de pesca o pràctiques agrícoles de muntanya, etc.) en l’ENP (amenaces i impacte ambiental). *Avaluació de l'impacte del canvi climàtic en l'ENP i la seva capacitat d'adaptació i resiliència. *Avaluació dels resultats de les estratègies de gestió aplicades en l'ENP *Col.laboració amb l?Observatori per aportar els coneixements generats a l'ENP. | Q95: Avaluació de l'impacte del canvi climàtic en l'ENP i la seva capacitat d'adaptació i resiliència. | R95: S'ha avaluat l'impacte del canvi climàtic en l'ENP i la seva capacitat d'adaptació i resiliència | T95: Sí | U95: 0.015 | V95: =PLA!U95*Llistes!$L$11*Llistes!$L$12 -> 2 | W95: Direcció | X95: =IF(W95=Llistes!$K$2,Llistes!$L$2,IF(W95=Llistes!$K$3,Llistes!$L$3,IF(W95=Llistes!$K$4,Llistes!$L$4,IF(W95=Llistes!$K$5,Llistes!$L$5,IF(W95=Llistes!$K$6,Llistes!$L$6,IF(W95=Llistes!$K$7,Llistes!$L$7,"")))))) -> Gerard Carrion | Z95: X
A96: CONEIXEMENT | F96: 06.2.2 | G96: Conèixer i estudiar els processos naturals propis de l’espai, la seva funcionalitat, i ecologia en referència als ecosistemes | H96: Comú | I96: Obligatori | J96: =G96 -> Conèixer i estudiar els processos naturals propis de l’espai, la seva funcionalitat, i ecologia en referència als ecosistemes | M96: ALTA | N96: *Foment de l'estudi de l'afectació de determinats processos naturals o activitats antròpiques (contaminació, fragmentació d'hàbitats, atropellaments, noves arts de pesca o pràctiques agrícoles de muntanya, etc.) en l’ENP (amenaces i impacte ambiental). *Avaluació de l'impacte del canvi climàtic en l'ENP i la seva capacitat d'adaptació i resiliència. *Avaluació dels resultats de les estratègies de gestió aplicades en l'ENP *Col.laboració amb l?Observatori per aportar els coneixements generats a l'ENP. | Q96: Avaluació dels resultats de les estratègies de gestió aplicades en l'ENP. | R96: S'han avaluat els resultat de les estratègies de gestió de l'ENP | T96: Sí | U96: 0.015 | V96: =PLA!U96*Llistes!$L$11*Llistes!$L$12 -> 2 | W96: Direcció | X96: =IF(W96=Llistes!$K$2,Llistes!$L$2,IF(W96=Llistes!$K$3,Llistes!$L$3,IF(W96=Llistes!$K$4,Llistes!$L$4,IF(W96=Llistes!$K$5,Llistes!$L$5,IF(W96=Llistes!$K$6,Llistes!$L$6,IF(W96=Llistes!$K$7,Llistes!$L$7,"")))))) -> Gerard Carrion | AB96: X
A97: CONEIXEMENT | F97: 06.2.2 | G97: Conèixer els usos i factors de canvi rellevants en l'evolució dels elements de conservació, i avaluar els efectes que generen en l’espai (pressions i amenaces) | H97: Comú | I97: Obligatori | J97: =G97 -> Conèixer els usos i factors de canvi rellevants en l'evolució dels elements de conservació, i avaluar els efectes que generen en l’espai (pressions i amenaces) | M97: ALTA | N97: *Foment de l'estudi de l'afectació de determinats processos naturals o activitats antròpiques (contaminació, fragmentació d'hàbitats, atropellaments, noves arts de pesca o pràctiques agrícoles de muntanya, etc.) en l’ENP (amenaces i impacte ambiental). *Avaluació de l'impacte del canvi climàtic en l'ENP i la seva capacitat d'adaptació i resiliència. *Avaluació dels resultats de les estratègies de gestió aplicades en l'ENP *Col.laboració amb l?Observatori per aportar els coneixements generats a l'ENP. | O97: ESNATURA | P97: SENP/UIC: Elaborar la classificació i cartografia de les pressions o factors de canvi sobre el medi natural | Q97: Col.laboració amb l'Observatori per aportar els coneixements generats a l'ENP. | R97: S'han compartit els treballs/coneixements generats amb l'Observatori | T97: Sí | U97: 0.015 | V97: =PLA!U97*Llistes!$L$11*Llistes!$L$12 -> 2 | W97: Patrimoni natural | X97: =IF(W97=Llistes!$K$2,Llistes!$L$2,IF(W97=Llistes!$K$3,Llistes!$L$3,IF(W97=Llistes!$K$4,Llistes!$L$4,IF(W97=Llistes!$K$5,Llistes!$L$5,IF(W97=Llistes!$K$6,Llistes!$L$6,IF(W97=Llistes!$K$7,Llistes!$L$7,"")))))) -> Pau Federico | Y97: X | Z97: X | AA97: X | AB97: X
A98: CONEIXEMENT | F98: 06.2.3 | G98: Conèixer els usos i factors de canvi rellevants en l'evolució dels elements de conservació, i avaluar els efectes que generen en l’espai (pressions i amenaces) | H98: Comú | I98: Obligatori
A99: CONEIXEMENT | F99: 06.2.4 | G99: Conèixer l'impacte de les gestió de l'aigua, sobre la biodiversitat | H99: Comú | I99: Obligatori | J99: =G99 -> Conèixer l'impacte de les gestió de l'aigua, sobre la biodiversitat | M99: MITJANA | N99: *Programa de seguiment de l’estat hidrològic de les masses d’aigua *Establiment d’una xarxa automatitzada de control (sensors, inventaris, models hidrològics, etc.). | Q99: Programa de seguiment de l’estat hidrològic dels cursos d'aigua | R99: Nombre d'anys amb seguiment de l'estat hidrològic dels cursos d'aigua | S99: 1 | T99: 2 | U99: 0.015 | V99: =PLA!U99*Llistes!$L$11*Llistes!$L$12 -> 2 | W99: Direcció | X99: =IF(W99=Llistes!$K$2,Llistes!$L$2,IF(W99=Llistes!$K$3,Llistes!$L$3,IF(W99=Llistes!$K$4,Llistes!$L$4,IF(W99=Llistes!$K$5,Llistes!$L$5,IF(W99=Llistes!$K$6,Llistes!$L$6,IF(W99=Llistes!$K$7,Llistes!$L$7,"")))))) -> Gerard Carrion | Y99: X | Z99: X | AA99: X | AB99: X
A100: CONEIXEMENT | F100: 06.2.5 | G100: Participar en el coneixement de la tendència d'espècies plaga amb afectacions sobre ecosistemes o activitats econòmiques dins l'ENP | H100: Comú | I100: Obligatori | J100: =G100 -> Participar en el coneixement de la tendència d'espècies plaga amb afectacions sobre ecosistemes o activitats econòmiques dins l'ENP | M100: MITJANA | N100: *Participació en els estudis de les autoritats competents | Q100: Participació en els estudis d'espècies plaga amb afectacions sobre ecosistemes o activitats econòmiques dins l'ENP de les autoritats competents. | R100: Nombre d'autoritzacions relacionades amb el coneixement de la tendència d'espècies plaga amb afectacions sobre ecosistemes o activitats econòmiques dins l'ENP | S100: 1 | T100: 2 | U100: 0.015 | V100: =PLA!U100*Llistes!$L$11*Llistes!$L$12 -> 2 | W100: Direcció | X100: =IF(W100=Llistes!$K$2,Llistes!$L$2,IF(W100=Llistes!$K$3,Llistes!$L$3,IF(W100=Llistes!$K$4,Llistes!$L$4,IF(W100=Llistes!$K$5,Llistes!$L$5,IF(W100=Llistes!$K$6,Llistes!$L$6,IF(W100=Llistes!$K$7,Llistes!$L$7,"")))))) -> Gerard Carrion | Y100: X | Z100: X | AA100: X | AB100: X
...

Sheet Transposicio_Pla_Doc
A1: EIXOS | C1: OBJECTIUS Generals (PP) | E1: Objectiu Estratègic | F1: Codi | G1: Objectiu operatiu | H1: Accions (afegit Albera) | I1: Indicadors | J1: Valor mínim | K1: Valor objectiu | L1: Objectiu operatiu | M1: Comú / Específic | N1: Obligatori / Optatiu | O1: Explicació de la decisió presa en el cas de canvis respecte al llistat inicial (columna G) | P1: Objectiu amb mesures incorporables a la planificació anual de la gestió de l'espai? | Q1: Prioritat | R1: Propostes genèriques d'accions | S1: Marc de referència | T1: Resultats derivats | U1: Hores de dedicació (hores/setmana) | V1: Total hores període (hores) | W1: Àrea responsable | X1: Persona responsable | Y1: 2025 | Z1: 2026 | AA1: 2027 | AB1: 2028
A2: NATURA | B2: 1 | C2: CONSERVAR LA NATURA i restaurar els ecosistemes, els processos naturals i seminaturals, la biodiversitat i la geodiversitat associada. | D2: 01.1 | E2: Adequar i fer eficient la conservació dels elements objecte de gestió prioritària marcats per la DG a l'ENP | F2: 01.1.1 | G2: =L2 -> Implementar i executar plans de gestió específics per a hàbitats i espècies de conservació prioritària dins l'ENP | H2: Millora del coneixement de la distribució i població (o superfície) dels elements priorizats. | I2: % d'elements prioritzats dels quals s'ha millorat el coneixent en base a les aproximacions següents: (1) Increment anual del 25% de N elements amb informació/N total elements prioritzats a l'espai (any 2029 -> Inexistència de cap element prioritzat sense 'feina feta' ). 2) Distribució: Tots els quadrats 1x1 de l'ENP tenen informació de la distribució dels elements prioritzats. 3) Es coneixen densitats poblacionals/estimes per totes les sp catalogades 'En Perill' i s'estableix periodicitat seguiment/sp. 4) Es prospecta el 50% d'hàbitat no prospectat per a una sp 5) Almenys 1 vegada es fa una anàlisi poblacional per a sp que no es coneix la distribució (òliba) | J2: 0.5 | K2: 1 | L2: Implementar i executar plans de gestió específics per a hàbitats i espècies de conservació prioritària dins l'ENP | M2: Comú | N2: Obligatori | Q2: MÀXIMA | R2: *Realització d'accions per a la millora dels elements prioritzats a l'espai *Elaboració de plans de gestió per elements prioritzats a l'espai | S2: MAP | T2: SFF: Elaboració de plans de gestió específics per a espècies de conservació prioritària i directrius de gestió d'hàbitats. SFF/SENP: Definir a nivell de cluster quins son els que es poden elaborar conjuntament. | U2: 15 | V2: =PLA!U5*Llistes!$L$11*Llistes!$L$12 -> 2000 | W2: Patrimoni natural | X2: =IF(W2=Llistes!$K$2,Llistes!$L$2,IF(W2=Llistes!$K$3,Llistes!$L$3,IF(W2=Llistes!$K$4,Llistes!$L$4,IF(W2=Llistes!$K$5,Llistes!$L$5,IF(W2=Llistes!$K$6,Llistes!$L$6,IF(W2=Llistes!$K$7,Llistes!$L$7,"")))))) -> Pau Federico | Y2: X | Z2: X | AA2: X | AB2: X
A3: NATURA | F3: 01.1.1 | G3: =L3 -> Implementar i executar plans de gestió específics per a hàbitats i espècies de conservació prioritària dins l'ENP | H3: Desplegament del MAP a l'espai XN2000 Basses Albera | I3: Nombre d'accions del MAP que s'han començat a desenvolupar | J3: 0.3 | K3: 0.6 | L3: Implementar i executar plans de gestió específics per a hàbitats i espècies de conservació prioritària dins l'ENP | M3: Comú | N3: Obligatori | Q3: MÀXIMA | U3: 7.8 | V3: =PLA!U6*Llistes!$L$11*Llistes!$L$12 -> 1040 | W3: XN2000 | X3: =IF(W3=Llistes!$K$2,Llistes!$L$2,IF(W3=Llistes!$K$3,Llistes!$L$3,IF(W3=Llistes!$K$4,Llistes!$L$4,IF(W3=Llistes!$K$5,Llistes!$L$5,IF(W3=Llistes!$K$6,Llistes!$L$6,IF(W3=Llistes!$K$7,Llistes!$L$7,"")))))) -> Montse Pascual | Y3: X | Z3: X | AA3: X | AB3: X
A4: NATURA | F4: 01.1.1 | G4: =L4 -> Implementar i executar plans de gestió específics per a hàbitats i espècies de conservació prioritària dins l'ENP | H4: Redacció del projecte de restauració de depressions. | I4: S'ha redactat el projecte | K4: Sí | L4: Implementar i executar plans de gestió específics per a hàbitats i espècies de conservació prioritària dins l'ENP | M4: Comú | N4: Obligatori | Q4: MÀXIMA | U4: 0.15 | V4: =PLA!U7*Llistes!$L$11*Llistes!$L$12 -> 20 | W4: XN2000 | X4: =IF(W4=Llistes!$K$2,Llistes!$L$2,IF(W4=Llistes!$K$3,Llistes!$L$3,IF(W4=Llistes!$K$4,Llistes!$L$4,IF(W4=Llistes!$K$5,Llistes!$L$5,IF(W4=Llistes!$K$6,Llistes!$L$6,IF(W4=Llistes!$K$7,Llistes!$L$7,"")))))) -> Montse Pascual | Y4: X | Z4: X | AA4: X | AB4: X
A5: NATURA | F5: 01.1.1 | G5: =L5 -> Implementar i executar plans de gestió específics per a hàbitats i espècies de conservació prioritària dins l'ENP | H5: Execució del projecte de restauració de depressions | I5: S'ha executat el projecte | K5: Sí | L5: Implementar i executar plans de gestió específics per a hàbitats i espècies de conservació prioritària dins l'ENP | M5: Comú | N5: Obligatori | Q5: MÀXIMA | U5: 0.15 | V5: =PLA!U8*Llistes!$L$11*Llistes!$L$12 -> 20 | W5: XN2000 | X5: =IF(W5=Llistes!$K$2,Llistes!$L$2,IF(W5=Llistes!$K$3,Llistes!$L$3,IF(W5=Llistes!$K$4,Llistes!$L$4,IF(W5=Llistes!$K$5,Llistes!$L$5,IF(W5=Llistes!$K$6,Llistes!$L$6,IF(W5=Llistes!$K$7,Llistes!$L$7,"")))))) -> Montse Pascual | Y5: X | Z5: X | AA5: X | AB5: X
A6: NATURA | F6: 01.1.1 | G6: =L6 -> Implementar i executar plans de gestió específics per a hàbitats i espècies de conservació prioritària dins l'ENP | H6: Redacció del projecte executiu de restauració de Garbet | I6: S'ha redactat el projecte executiu | K6: Sí | L6: Implementar i executar plans de gestió específics per a hàbitats i espècies de conservació prioritària dins l'ENP | M6: Comú | N6: Obligatori | Q6: MÀXIMA | U6: 0.15 | V6: =PLA!U9*Llistes!$L$11*Llistes!$L$12 -> 20 | W6: XN2000 | X6: =IF(W6=Llistes!$K$2,Llistes!$L$2,IF(W6=Llistes!$K$3,Llistes!$L$3,IF(W6=Llistes!$K$4,Llistes!$L$4,IF(W6=Llistes!$K$5,Llistes!$L$5,IF(W6=Llistes!$K$6,Llistes!$L$6,IF(W6=Llistes!$K$7,Llistes!$L$7,"")))))) -> Montse Pascual | Y6: X | Z6: X | AA6: X | AB6: X
A7: NATURA | F7: 01.1.1 | G7: =L7 -> Implementar i executar plans de gestió específics per a hàbitats i espècies de conservació prioritària dins l'ENP | H7: Execució del projecte de restauració de Garbet | I7: S'ha executat el projecte | K7: Sí | L7: Implementar i executar plans de gestió específics per a hàbitats i espècies de conservació prioritària dins l'ENP | M7: Comú | N7: Obligatori | Q7: MÀXIMA | U7: 0.15 | V7: =PLA!U10*Llistes!$L$11*Llistes!$L$12 -> 20 | W7: XN2000 | X7: =IF(W7=Llistes!$K$2,Llistes!$L$2,IF(W7=Llistes!$K$3,Llistes!$L$3,IF(W7=Llistes!$K$4,Llistes!$L$4,IF(W7=Llistes!$K$5,Llistes!$L$5,IF(W7=Llistes!$K$6,Llistes!$L$6,IF(W7=Llistes!$K$7,Llistes!$L$7,"")))))) -> Montse Pascual | Y7: X | Z7: X | AA7: X | AB7: X
A8: NATURA | F8: 01.1.1 | G8: =L8 -> Implementar i executar plans de gestió específics per a hàbitats i espècies de conservació prioritària dins l'ENP | H8: Realització d'accions per a la millora dels elements prioritzats a l'espai | I8: S'ha realitzat com a mínim 1 acció/sp | J8: 1 acció/ 50% sp prioritzades | K8: 1 acció/ 100% sp prioritzades | L8: Implementar i executar plans de gestió específics per a hàbitats i espècies de conservació prioritària dins l'ENP | M8: Comú | N8: Obligatori | Q8: MÀXIMA | R8: *Realització d'accions per a la millora dels elements prioritzats a l'espai *Elaboració de plans de gestió per elements prioritzats a l'espai | U8: 7.02 | V8: =PLA!U11*Llistes!$L$11*Llistes!$L$12 -> 936 | W8: Patrimoni natural | X8: =IF(W8=Llistes!$K$2,Llistes!$L$2,IF(W8=Llistes!$K$3,Llistes!$L$3,IF(W8=Llistes!$K$4,Llistes!$L$4,IF(W8=Llistes!$K$5,Llistes!$L$5,IF(W8=Llistes!$K$6,Llistes!$L$6,IF(W8=Llistes!$K$7,Llistes!$L$7,"")))))) -> Pau Federico | Y8: X | Z8: X | AA8: X | AB8: X
A9: NATURA | F9: 01.1.1 | G9: =L9 -> Implementar i executar plans de gestió específics per a hàbitats i espècies de conservació prioritària dins l'ENP | H9: Seguiment rompudes i efectes dels treballs forestals sobre tortuga mediterrània en XN2000 | I9: Nombre d'expedients | J9: Al 50% dels expedients se'ls fa un seguiment | K9: Al 100% dels expedients se'ls fa un seguiment | L9: Implementar i executar plans de gestió específics per a hàbitats i espècies de conservació prioritària dins l'ENP | M9: Comú | N9: Obligatori | Q9: ALTA | U9: 0.15 | V9: =PLA!U12*Llistes!$L$11*Llistes!$L$12 -> 20 | W9: XN2000 | X9: =IF(W9=Llistes!$K$2,Llistes!$L$2,IF(W9=Llistes!$K$3,Llistes!$L$3,IF(W9=Llistes!$K$4,Llistes!$L$4,IF(W9=Llistes!$K$5,Llistes!$L$5,IF(W9=Llistes!$K$6,Llistes!$L$6,IF(W9=Llistes!$K$7,Llistes!$L$7,"")))))) -> Montse Pascual
A10: NATURA | F10: 01.1.2 | L10: Adaptar i executar plans de gestió específics per a elements geològics de conservació prioritària dins l'ENP | M10: Comú | N10: Obligatori
A11: NATURA | D11: 01.2 | E11: Executar les mesures de gestió directa previstes en els instruments de planificació per la conservació i la gestió adaptativa dels elements clau de l'ENP | F11: 01.2.1 | G11: =L11 -> Implementar la metodologia de gestió adaptativa (Estàndards Oberts de Gestió Adaptativa a Catalunya) en tots els processos de l'ENP | H11: Aplicació de la metodologia dels Estàndards Oberts pels processos més rellevants per a la conservació a l'espai | I11: 1) S'analitzen els resultats a través dels indicadors 2) La planificació s'adapta en funció dels resultats. 3) S'avalua el grau de millora de les amenaces/factors de canvi | J11: Per al 50% de les accions | K11: Per al 100% de les accions | L11: Implementar la metodologia de gestió adaptativa (Estàndards Oberts de Gestió Adaptativa a Catalunya) en tots els processos de l'ENP | M11: Comú | N11: Obligatori | Q11: ALTA | R11: *Definició d'un protocol per tal d'incorporar la metodologia dels Estàndards Oberts pels processos més rellevants per a la conservació a l'espai | S11: ESNATURA | T11: SENP: Elaboració d'un manual per la implementació dels OSAM | U11: 0.15 | V11: =PLA!U14*Llistes!$L$11*Llistes!$L$12 -> 20 | W11: Direcció | X11: =IF(W11=Llistes!$K$2,Llistes!$L$2,IF(W11=Llistes!$K$3,Llistes!$L$3,IF(W11=Llistes!$K$4,Llistes!$L$4,IF(W11=Llistes!$K$5,Llistes!$L$5,IF(W11=Llistes!$K$6,Llistes!$L$6,IF(W11=Llistes!$K$7,Llistes!$L$7,"")))))) -> Gerard Carrion | Y11: X | Z11: X | AA11: X | AB11: X
A12: NATURA | F12: 01.2.1 | G12: =L12 -> Implementar la metodologia de gestió adaptativa (Estàndards Oberts de Gestió Adaptativa a Catalunya) en tots els processos de l'ENP | H12: Aplicació de la metodologia dels Estàndards Oberts pels processos més rellevants per a la conservació a l'espai de XN2000 Basses de l'Albera | I12: S'aplica la metodologia dels estàndars oberts | K12: Sí | L12: Implementar la metodologia de gestió adaptativa (Estàndards Oberts de Gestió Adaptativa a Catalunya) en tots els processos de l'ENP | M12: Comú | N12: Obligatori | Q12: ALTA | U12: 0.15 | V12: =PLA!U15*Llistes!$L$11*Llistes!$L$12 -> 20 | W12: XN2000 | X12: =IF(W12=Llistes!$K$2,Llistes!$L$2,IF(W12=Llistes!$K$3,Llistes!$L$3,IF(W12=Llistes!$K$4,Llistes!$L$4,IF(W12=Llistes!$K$5,Llistes!$L$5,IF(W12=Llistes!$K$6,Llistes!$L$6,IF(W12=Llistes!$K$7,Llistes!$L$7,"")))))) -> Montse Pascual | Y12: X | Z12: X | AA12: X | AB12: X
A13: NATURA | F13: 01.2.2 | G13: =L13 -> Executar les mesures previstes en els plans de conservació o recuperació d'espècies amenaçades de forma coordinada amb el Servei de Flora i Fauna en l'àmbit de l'ENP | H13: Implicació i participació en la redacció dels plans de conservació /recuperació d'espècies amenaçades | I13: 1) Nombre de plans de conservació/recuperació en els que l'ENP hi participa | J13: 1) Participació en el 50% dels plans d'sp amenaçades (EN i VU), 11 | K13: 1) Participació en el 100% dels plans d'sp amenaçades (EN i VU),22 | L13: Executar les mesures previstes en els plans de conservació o recuperació d'espècies amenaçades de forma coordinada amb el Servei de Flora i Fauna en l'àmbit de l'ENP | M13: Comú | N13: Obligatori | Q13: MÀXIMA | R13: * Implicació i participació en la redacció dels plans de conservació /recuperació d'espècies amenaçades | U13: 3 | V13: =PLA!U16*Llistes!$L$11*Llistes!$L$12 -> 400 | W13: Patrimoni natural | X13: =IF(W13=Llistes!$K$2,Llistes!$L$2,IF(W13=Llistes!$K$3,Llistes!$L$3,IF(W13=Llistes!$K$4,Llistes!$L$4,IF(W13=Llistes!$K$5,Llistes!$L$5,IF(W13=Llistes!$K$6,Llistes!$L$6,IF(W13=Llistes!$K$7,Llistes!$L$7,"")))))) -> Pau Federico | Y13: X | Z13: X | AA13: X | AB13: X
A14: NATURA | F14: 01.2.2 | G14: =L14 -> Executar les mesures previstes en els plans de conservació o recuperació d'espècies amenaçades de forma coordinada amb el Servei de Flora i Fauna en l'àmbit de l'ENP | H14: Execució de les accions dins els plans que pertoquin a cada espai (incorporar totes les mesures que surten als plans ja aprovats que tenen incidència a l'espai) | I14: Nombre d'accions que provenen de l'aplicació de plans de conservació/recuperació | J14: 5 accions | K14: 10 accions | L14: Executar les mesures previstes en els plans de conservació o recuperació d'espècies amenaçades de forma coordinada amb el Servei de Flora i Fauna en l'àmbit de l'ENP | M14: Comú | N14: Obligatori | Q14: MÀXIMA | R14: * Execució de les accions dins els plans que pertoquin a cada espai (incorporar totes les mesures que surten als plans ja aprovats que tenen incidència a l'espai) | U14: 3 | V14: =PLA!U17*Llistes!$L$11*Llistes!$L$12 -> 400 | W14: Patrimoni natural | X14: =IF(W14=Llistes!$K$2,Llistes!$L$2,IF(W14=Llistes!$K$3,Llistes!$L$3,IF(W14=Llistes!$K$4,Llistes!$L$4,IF(W14=Llistes!$K$5,Llistes!$L$5,IF(W14=Llistes!$K$6,Llistes!$L$6,IF(W14=Llistes!$K$7,Llistes!$L$7,"")))))) -> Pau Federico | Y14: X | Z14: X | AA14: X | AB14: X
A15: NATURA | F15: 01.2.2 | G15: =L15 -> Executar les mesures previstes en els plans de conservació o recuperació d'espècies amenaçades de forma coordinada amb el Servei de Flora i Fauna en l'àmbit de l'ENP | H15: Col·laboració en l'obtenció de la informació necessària dins els espais per al desenvolupament dels Plans | I15: Nombre d'sp amenaçades prioritzades amb les quals treballa l'ENP | J15: 50% sp amenaçades prioritzades | K15: 100% sp amenaçades prioritzades | L15: Executar les mesures previstes en els plans de conservació o recuperació d'espècies amenaçades de forma coordinada amb el Servei de Flora i Fauna en l'àmbit de l'ENP | M15: Comú | N15: Obligatori | Q15: MÀXIMA | R15: * Col.laboració en l'obtenció de la informació necessària dins els espais per al desenvolupament dels Plans | S15: MAP Catàlegs | T15: SFF: Elaboració de plans de conservació o recuperació d'espècies protegides | U15: 3 | V15: =PLA!U18*Llistes!$L$11*Llistes!$L$12 -> 400 | W15: Patrimoni natural | X15: =IF(W15=Llistes!$K$2,Llistes!$L$2,IF(W15=Llistes!$K$3,Llistes!$L$3,IF(W15=Llistes!$K$4,Llistes!$L$4,IF(W15=Llistes!$K$5,Llistes!$L$5,IF(W15=Llistes!$K$6,Llistes!$L$6,IF(W15=Llistes!$K$7,Llistes!$L$7,"")))))) -> Pau Federico | Y15: X | Z15: X | AA15: X | AB15: X
A16: NATURA | F16: 01.2.3 | G16: =L16 -> Executar les mesures de gestió previstes en els plans de control i erradicació d'espècies exòtiques de forma coordinada amb el Servei de Flora i Fauna en l'àmbit de l'ENP | H16: Col·laboració amb el Servei de Fauna i Flora en les actuacions de gestió de les espècies exòtiques invasores dins de l'ENP. (Opuntia, bambú, estramoni, Solanum sisymbriifolium, coipú, visó americà, ailant, cortaderia i robínia) (XN2000) | I16: Nombre d'EEI prioritzades en l'ENP que es gestionen | J16: 3 EEI | K16: 6 EEI | L16: Executar les mesures de gestió previstes en els plans de control i erradicació d'espècies exòtiques de forma coordinada amb el Servei de Flora i Fauna en l'àmbit de l'ENP | M16: Comú | N16: Obligatori | Q16: MÀXIMA | R16: * Implicació i participació en la redacció (cal identificar els plans que estan ja en marxa o previstos i posar les mesures concretes) * Execució de les accions dins els plans que pertoquin a cada espai * Col.laboració en l'obtenció de la informació necessària dins els espais per al desenvolupament dels Plans | U16: 1.02 | V16: =PLA!U19*Llistes!$L$11*Llistes!$L$12 -> 136 | W16: Patrimoni natural | X16: =IF(W16=Llistes!$K$2,Llistes!$L$2,IF(W16=Llistes!$K$3,Llistes!$L$3,IF(W16=Llistes!$K$4,Llistes!$L$4,IF(W16=Llistes!$K$5,Llistes!$L$5,IF(W16=Llistes!$K$6,Llistes!$L$6,IF(W16=Llistes!$K$7,Llistes!$L$7,"")))))) -> Pau Federico | Y16: X | Z16: X | AA16: X | AB16: X
A17: NATURA | F17: 01.2.3 | G17: =L17 -> Executar les mesures de gestió previstes en els plans de control i erradicació d'espècies exòtiques de forma coordinada amb el Servei de Flora i Fauna en l'àmbit de l'ENP | H17: Coordinació i realització d'accions de gestió d'espècies exòtiques invasores dins de l'ENP (Opuntia, bambú, estramoni, Solanum sisymbriifolium, coipú) (XN2000). | I17: Nombre de reunions/any vinculades a EEI en què l'ENP participa o impulsades pel ENP | J17: 1 reunions/any | K17: 3 reunions/any | L17: Executar les mesures de gestió previstes en els plans de control i erradicació d'espècies exòtiques de forma coordinada amb el Servei de Flora i Fauna en l'àmbit de l'ENP | M17: Comú | N17: Obligatori | Q17: MÀXIMA | R17: * Implicació i participació en la redacció (cal identificar els plans que estan ja en marxa o previstos i posar les mesures concretes) * Execució de les accions dins els plans que pertoquin a cada espai * Col.laboració en l'obtenció de la informació necessària dins els espais per al desenvolupament dels Plans | S17: ESNATURA MAP | T17: SFF: Elaboració de plans de control i erradicació d'espècies exòtiques | U17: 0.15 | V17: =PLA!U20*Llistes!$L$11*Llistes!$L$12 -> 20 | W17: Patrimoni natural | X17: =IF(W17=Llistes!$K$2,Llistes!$L$2,IF(W17=Llistes!$K$3,Llistes!$L$3,IF(W17=Llistes!$K$4,Llistes!$L$4,IF(W17=Llistes!$K$5,Llistes!$L$5,IF(W17=Llistes!$K$6,Llistes!$L$6,IF(W17=Llistes!$K$7,Llistes!$L$7,"")))))) -> Pau Federico | Y17: X | Z17: X | AA17: X | AB17: X
A18: NATURA | F18: 01.2.4 | G18: =L18 -> Desplegar els objectius i tasques recollits en els instruments de referència i compromisos internacionals | H18: Col·laboració amb altres unitats per a l'assoliment d'objectius i compromisos internacionals, quan aquestes ho demanin. | I18: Nombre de reunions i/o accions vinculades a compromisos internacionals | J18: 1 reunions/any | K18: 3 reunions/any | L18: Desplegar els objectius i tasques recollits en els instruments de referència i compromisos internacionals | M18: Específic | N18: Optatiu | Q18: MITJANA | R18: * Desplegament dels objectius recollits en l'Estratègia de la Xarxa d'àrees marines protegides del Mediterrani (MedPAN network) * Col·laboració en el compliment dels objectius i tasques derivats de la Mediterranean Climate Action Partnership en matèria de biodiversitat i canvi climàtic i els seus impactes sobre la sequera, calor i incendis * Col·laboració en la implementació pràctica de projectes de l'àrea internacional i dels compromisos amb les entitats membres UICN, Euroregió Pirineus Mediterrània | U18: 0.15 | V18: =PLA!U21*Llistes!$L$11*Llistes!$L$12 -> 20 | W18: Direcció | X18: =IF(W18=Llistes!$K$2,Llistes!$L$2,IF(W18=Llistes!$K$3,Llistes!$L$3,IF(W18=Llistes!$K$4,Llistes!$L$4,IF(W18=Llistes!$K$5,Llistes!$L$5,IF(W18=Llistes!$K$6,Llistes!$L$6,IF(W18=Llistes!$K$7,Llistes!$L$7,"")))))) -> Gerard Carrion | Y18: X | Z18: X | AA18: X | AB18: X
A19: NATURA | F19: 01.2.4 | G19: =L19 -> Desplegar els objectius i tasques recollits en els instruments de referència i compromisos internacionals | H19: Seguiment dels ajuts d’espais naturals i d’actuacions en espais de la XN2000. | I19: Percentatge d’ajuts sobre els que es fa seguiment | J19: 0.5 | K19: 1 | L19: Desplegar els objectius i tasques recollits en els instruments de referència i compromisos internacionals | M19: Específic | N19: Optatiu | Q19: MITJANA | U19: 0.15 | V19: =PLA!U22*Llistes!$L$11*Llistes!$L$12 -> 20 | W19: XN2000 | X19: =IF(W19=Llistes!$K$2,Llistes!$L$2,IF(W19=Llistes!$K$3,Llistes!$L$3,IF(W19=Llistes!$K$4,Llistes!$L$4,IF(W19=Llistes!$K$5,Llistes!$L$5,IF(W19=Llistes!$K$6,Llistes!$L$6,IF(W19=Llistes!$K$7,Llistes!$L$7,"")))))) -> Montse Pascual
D20: 01.3 | E20: Crear ecosistemes complexes, resilients, i d'alta biodiversitat per garantir la recuperació dels processos ecosistèmics | F20: 01.3.1 | G20: Identificar espais pel foment de la dinàmica natural i l'aprofitament no extractiu | H20: Afavorir la creació d'hàbitats per a la conservació d'espècies | I20: Nombre d'hectàrees creades per a la conservació | J20: 2 ha | K20: 5 ha | L20: Identificar espais pel foment de la dinàmica natural i l'aprofitament no extractiu | M20: Comú | N20: Obligatori | Q20: ALTA | R20: *Afavorir la creació d'hàbitats per a la conservació d'espècies | U20: 0.3 | V20: =PLA!U23*Llistes!$L$11*Llistes!$L$12 -> 40 | W20: Patrimoni natural | X20: =IF(W20=Llistes!$K$2,Llistes!$L$2,IF(W20=Llistes!$K$3,Llistes!$L$3,IF(W20=Llistes!$K$4,Llistes!$L$4,IF(W20=Llistes!$K$5,Llistes!$L$5,IF(W20=Llistes!$K$6,Llistes!$L$6,IF(W20=Llistes!$K$7,Llistes!$L$7,"")))))) -> Pau Federico
A21: NATURA | F21: 01.3.1 | G21: =L20 -> Identificar espais pel foment de la dinàmica natural i l'aprofitament no extractiu | H21: Participació en la identificació d'espais pel foment de la dinàmica natural i l'aprofitament no extractiu dins l'ENP en base a uns criteris metodològics predefinits | I21: Nombre d'hores dedicades a la identificació d'espais per a dinàmica natural | J21: 1 hora/any | K21: 3 hores/any | L21: Identificar espais pel foment de la dinàmica natural i l'aprofitament no extractiu | M21: Comú | N21: Obligatori | Q21: ALTA | R21: *Participar en la identificació d'espais pel foment de la dinàmica natural i l'aprofitament no extractiu dins l'ENP en base a uns criteris metodològics predefinits | S21: ESNATURA | T21: SENP/SFF: Definir criteris metodològics | U21: 0.045 | V21: =PLA!U24*Llistes!$L$11*Llistes!$L$12 -> 6 | W21: Patrimoni natural | X21: =IF(W21=Llistes!$K$2,Llistes!$L$2,IF(W21=Llistes!$K$3,Llistes!$L$3,IF(W21=Llistes!$K$4,Llistes!$L$4,IF(W21=Llistes!$K$5,Llistes!$L$5,IF(W21=Llistes!$K$6,Llistes!$L$6,IF(W21=Llistes!$K$7,Llistes!$L$7,"")))))) -> Pau Federico | Y21: X | Z21: X | AA21: X | AB21: X
A22: NATURA | F22: 01.3.2 | G22: =L22 -> Afavorir la maduresa dels sistemes forestals | H22: Execució d'accions d'acceleració de la maduresa forestal en zones boscoses dins l'ENP en base als criteris metodològics predefinits | I22: Nombre d'hectàrees destinades a a maduresa forestal contemplades en els PTGiMF. | J22: 25% de les actuacions previstes als PTGiMF | K22: 50% de les actuacions previstes als PTGiMF | L22: Afavorir la maduresa dels sistemes forestals | M22: Específic | N22: Obligatori | Q22: ALTA | R22: *Participar i impulsar la planificació i execució d'accions d'acceleració de la maduresa forestal en zones boscoses dins l'ENP en base als criteris metodològics predefinits | S22: MAP | T22: SENP/SFF: Definir criteris metodològics | U22: 0.045 | V22: =PLA!U25*Llistes!$L$11*Llistes!$L$12 -> 6 | W22: Direcció | X22: =IF(W22=Llistes!$K$2,Llistes!$L$2,IF(W22=Llistes!$K$3,Llistes!$L$3,IF(W22=Llistes!$K$4,Llistes!$L$4,IF(W22=Llistes!$K$5,Llistes!$L$5,IF(W22=Llistes!$K$6,Llistes!$L$6,IF(W22=Llistes!$K$7,Llistes!$L$7,"")))))) -> Gerard Carrion | Y22: X | AA22: X
A23: NATURA | F23: 01.3.3 | G23: =L23 -> Generar pertorbacions controlades | H23: Col·laboració amb Bombers i GEPIF per a la realització de cremes controlades en àmbits compatibles | I23: Nombre d'hectàrees destinades a cremes controlades | J23: 0,5 ha | K23: 1,5 ha | L23: Generar pertorbacions controlades | M23: Específic | N23: Optatiu | O23: No hi ha zones compatibles amb cremes controlades dins del PNIN, ara mateix. Sí que es fan en zones de XN2000 | Q23: MITJANA | R23: *Elaboració d'una planificació d'actuacions de simulació d'incendis forestals naturals (cremes controlades) dins l'espai en base als criteris metodològics predefinits. *Realització dels estudis necessaris i participació en la reintroducció de grans herbívors, carnívors o carronyaires dins l'ENP en base als criteris metodològics predefinits. | S23: MAP | T23: SENP/SFF: Definir criteris metodològics | U23: 0.045 | V23: =PLA!U26*Llistes!$L$11*Llistes!$L$12 -> 6 | W23: Direcció | X23: =IF(W23=Llistes!$K$2,Llistes!$L$2,IF(W23=Llistes!$K$3,Llistes!$L$3,IF(W23=Llistes!$K$4,Llistes!$L$4,IF(W23=Llistes!$K$5,Llistes!$L$5,IF(W23=Llistes!$K$6,Llistes!$L$6,IF(W23=Llistes!$K$7,Llistes!$L$7,"")))))) -> Gerard Carrion | Y23: X | Z23: X | AA23: X | AB23: X
A24: NATURA | F24: 01.3.4 | L24: Restaurar la dinàmica natural dels rius | M24: Específic | N24: Optatiu
A25: NATURA | F25: 01.3.5 | G25: =L25 -> Fomentar el paisatge en mosaïc | H25: Col·laboració amb el sector ramader per mantenir i millorar les pastures, especialment en zones culminals d'interès per a la prevenció d'incendis. | I25: Nombre hectàrees desbrossades per mantenir les pastures per a la prevenció d'incendis | J25: 0,5 ha | K25: 1 ha | L25: Fomentar el paisatge en mosaïc | M25: Específic | N25: Obligatori | Q25: ALTA | R25: *Realització d'accions per gestionar l'herbivoria domèstica associada a la ramaderia extensiva *Aplicació dels criteris metodològics predefinits en un manual tècnic de bones pràctiques en ramaderia extensiva i recuperació i manteniment de pastures aplicat a l'ENP. *Coordinació i gestió dels ramats locals en actuacions de restauració de pastures i desembosc. | S25: ESNATURA | T25: SENP/SFF: Definir criteris metodològics | U25: 0.045 | V25: =PLA!U28*Llistes!$L$11*Llistes!$L$12 -> 6 | W25: Direcció | X25: =IF(W25=Llistes!$K$2,Llistes!$L$2,IF(W25=Llistes!$K$3,Llistes!$L$3,IF(W25=Llistes!$K$4,Llistes!$L$4,IF(W25=Llistes!$K$5,Llistes!$L$5,IF(W25=Llistes!$K$6,Llistes!$L$6,IF(W25=Llistes!$K$7,Llistes!$L$7,"")))))) -> Gerard Carrion | Y25: X | Z25: X | AA25: X | AB25: X
A26: NATURA | F26: 01.3.6 | L26: Gestionar i intervenir en la dinàmica de poblacions de fauna que no tenen depredador natural | M26: Específic | N26: Optatiu
A27: NATURA | F27: 01.3.7 | L27: Afavorir la connectivitat ecològica del territori | M27: Comú | N27: Obligatori
A28: NATURA | D28: 01.4 | E28: Alinear l'activitat de propietaris i gestors del territori amb la conservació, millora i restauració dels valors de l'ENP | F28: 01.4.1 | G28: =L28 -> Fomentar acords de custòdia en espais d'alt valor dins l'ENP per a la gestió dels elements prioritaris | H28: Exploració de la via dels acords de custòdia en espais d'alt valor dins l'ENP. | I28: Establiment d'acords de custòdia en alguna de les finques privades | J28: 1 | K28: 2 | L28: Fomentar acords de custòdia en espais d'alt valor dins l'ENP per a la gestió dels elements prioritaris | M28: Comú | N28: Obligatori | Q28: MÀXIMA | R28: *Realització d'acords de custòdia aplicant el model d'acord elaborat per Serveis Centrals | S28: MAP | T28: SENP/SENP: Dissenyar el protocol i elaborar un model d'acord | U28: 0.045 | V28: =PLA!U31*Llistes!$L$11*Llistes!$L$12 -> 6 | W28: Direcció | X28: =IF(W28=Llistes!$K$2,Llistes!$L$2,IF(W28=Llistes!$K$3,Llistes!$L$3,IF(W28=Llistes!$K$4,Llistes!$L$4,IF(W28=Llistes!$K$5,Llistes!$L$5,IF(W28=Llistes!$K$6,Llistes!$L$6,IF(W28=Llistes!$K$7,Llistes!$L$7,"")))))) -> Gerard Carrion
A29: NATURA | F29: 01.4.1 | G29: =L29 -> Fomentar acords de custòdia en espais d'alt valor dins l'ENP per a la gestió dels elements prioritaris | H29: Redacció dels plans de gestió de les 3 finques privades incloses al PNIN, de forma consensuada amb la propietat. | I29: Nombre plans de gestió de les finques privades aprovats | J29: 1 | K29: 3 | L29: Fomentar acords de custòdia en espais d'alt valor dins l'ENP per a la gestió dels elements prioritaris | M29: Comú | N29: Obligatori | Q29: MÀXIMA | R29: *Realització d'acords de custòdia aplicant el model d'acord elaborat per Serveis Centrals | S29: MAP | T29: SENP/SENP: Dissenyar el protocol i elaborar un model d'acord | U29: 0.045 | V29: =PLA!U32*Llistes!$L$11*Llistes!$L$12 -> 6 | W29: Direcció | X29: =IF(W29=Llistes!$K$2,Llistes!$L$2,IF(W29=Llistes!$K$3,Llistes!$L$3,IF(W29=Llistes!$K$4,Llistes!$L$4,IF(W29=Llistes!$K$5,Llistes!$L$5,IF(W29=Llistes!$K$6,Llistes!$L$6,IF(W29=Llistes!$K$7,Llistes!$L$7,"")))))) -> Gerard Carrion | Y29: X | Z29: X
A30: NATURA | F30: 01.4.2 | G30: =L30 -> Fomentar bones pràctiques entre els col·lectius de propietaris i gestors del territori | H30: Realització d'actuacions demostratives que permetin millorar la gestió d'hàbitats i espècies en altres llocs de l'espai, o zones semblants. | I30: Nombre actuacions destinades a accions demostratives | J30: 1 | K30: 2 | L30: Fomentar bones pràctiques entre els col·lectius de propietaris i gestors del territori | M30: Comú | N30: Obligatori | Q30: ALTA | R30: *Realització d'actuacions demostratives en finques pròpies per al foment de bones pràctiques | U30: 0.15 | V30: =PLA!U33*Llistes!$L$11*Llistes!$L$12 -> 20 | W30: Patrimoni natural | X30: =IF(W30=Llistes!$K$2,Llistes!$L$2,IF(W30=Llistes!$K$3,Llistes!$L$3,IF(W30=Llistes!$K$4,Llistes!$L$4,IF(W30=Llistes!$K$5,Llistes!$L$5,IF(W30=Llistes!$K$6,Llistes!$L$6,IF(W30=Llistes!$K$7,Llistes!$L$7,"")))))) -> Pau Federico | Y30: X | AA30: X
A31: NATURA | F31: 01.4.2 | H31: Coordinació amb oficina comarcal d’agricultura (SIGPAC) i la interacció basses temporals de l’Albera | I31: Existeix una coordinació amb l'oficina comarcal | K31: Sí | L31: Fomentar bones pràctiques entre els col·lectius de propietaris i gestors del territori | M31: Comú | N31: Obligatori | Q31: ALTA | U31: 0.15 | V31: =PLA!U34*Llistes!$L$11*Llistes!$L$12 -> 0 | W31: XN2000 | X31: =IF(W31=Llistes!$K$2,Llistes!$L$2,IF(W31=Llistes!$K$3,Llistes!$L$3,IF(W31=Llistes!$K$4,Llistes!$L$4,IF(W31=Llistes!$K$5,Llistes!$L$5,IF(W31=Llistes!$K$6,Llistes!$L$6,IF(W31=Llistes!$K$7,Llistes!$L$7,"")))))) -> Montse Pascual
F32: 01.4.3 | L32: Impulsar la coordinació amb els ens locals en la gestió finques públiques situades dins d’ENP | M32: Específic | N32: Optatiu
A33: NATURA | B33: 2 | C33: ADAPTAR ELS ECOSISTEMES AL CANVI CLIMÀTIC i millorar-ne la resiliència en front dels riscos associats. | D33: 02.1 | E33: Planificar l'adaptació dels sistemes naturals al canvi climàtic | F33: 02.1.1 | G33: Redactar i implementar el Pla d'adaptació de l'ENP al canvi climàtic | H33: Redacció del Pla d'adaptació del PNIN al canvi climàtic. | I33: S'ha redactat el Pla d'adaptació del PNIN al canvi climàtic | K33: Sí | L33: Adaptar i implementar el Pla d'adaptació de l'ENP al canvi climàtic | M33: Comú | N33: Obligatori | O33: No disposem de cap Pla d'adaptació de l'ENP al canvi climàtic, de manera que primer caldrà redactar-lo. | Q33: ALTA | R33: *Planificació del sistema d'espais oberts *Creació de zones de laminació per defensa de inundacions *Creació i manteniment d'espais dunars de protecció de temporals | U33: 0.51 | V33: =PLA!U36*Llistes!$L$11*Llistes!$L$12 -> 68 | W33: Direcció | X33: =IF(W33=Llistes!$K$2,Llistes!$L$2,IF(W33=Llistes!$K$3,Llistes!$L$3,IF(W33=Llistes!$K$4,Llistes!$L$4,IF(W33=Llistes!$K$5,Llistes!$L$5,IF(W33=Llistes!$K$6,Llistes!$L$6,IF(W33=Llistes!$K$7,Llistes!$L$7,"")))))) -> Gerard Carrion | Y33: X | Z33: X
A34: NATURA | F34: 02.1.1 | G34: Redactar i implementar el Pla d'adaptació de l'ENP al canvi climàtic | H34: Donar a conèixer el Pla entre els propietaris perquè puguin integrar les mesures proposades a la gestió de les seves finques. | I34: Nombre de propietats informades sobre el Pla d'adaptació al canvi climàtic | J34: 1 | K34: 3 (les que tinguin Pla de Gestió) | L34: Adaptar i implementar el Pla d'adaptació de l'ENP al canvi climàtic | M34: Comú | N34: Obligatori | O34: No disposem de cap Pla d'adaptació de l'ENP al canvi climàtic, de manera que primer caldrà redactar-lo. | Q34: ALTA | R34: *Planificació del sistema d'espais oberts *Creació de zones de laminació per defensa de inundacions *Creació i manteniment d'espais dunars de protecció de temporals | U34: 0.045 | V34: =PLA!U37*Llistes!$L$11*Llistes!$L$12 -> 6 | W34: Direcció | X34: =IF(W34=Llistes!$K$2,Llistes!$L$2,IF(W34=Llistes!$K$3,Llistes!$L$3,IF(W34=Llistes!$K$4,Llistes!$L$4,IF(W34=Llistes!$K$5,Llistes!$L$5,IF(W34=Llistes!$K$6,Llistes!$L$6,IF(W34=Llistes!$K$7,Llistes!$L$7,"")))))) -> Gerard Carrion | AA34: X
A35: NATURA | F35: 02.1.1 | G35: Redactar i implementar el Pla d'adaptació de l'ENP al canvi climàtic | H35: Implementació de les mesures d'adaptació del PNIN al canvi climàtic | I35: Nombre de mesures implementades relacionades amb l'adaptació al canvi climàtic | J35: 1 | K35: 4 | L35: Adaptar i implementar el Pla d'adaptació de l'ENP al canvi climàtic | M35: Comú | N35: Obligatori | O35: No disposem de cap Pla d'adaptació de l'ENP al canvi climàtic, de manera que primer caldrà redactar-lo. | Q35: ALTA | R35: *Planificació del sistema d'espais oberts *Creació de zones de laminació per defensa de inundacions *Creació i manteniment d'espais dunars de protecció de temporals | T35: OCCC/SENP: Elaboració del model de Pla d'adaptació dels ENP al canvi climàtic | U35: 0.045 | V35: =PLA!U38*Llistes!$L$11*Llistes!$L$12 -> 6 | W35: Direcció | X35: =IF(W35=Llistes!$K$2,Llistes!$L$2,IF(W35=Llistes!$K$3,Llistes!$L$3,IF(W35=Llistes!$K$4,Llistes!$L$4,IF(W35=Llistes!$K$5,Llistes!$L$5,IF(W35=Llistes!$K$6,Llistes!$L$6,IF(W35=Llistes!$K$7,Llistes!$L$7,"")))))) -> Gerard Carrion | AA35: X | AB35: X
A36: NATURA | F36: 02.1.2 | G36: =L36 -> Gestionar i planificar els recursos hídrics de l'ENP | H36: Revisió de les fonts i punts d'aigua per assegurar el seu manteniment (XN2000) | I36: Nombre de fonts i punts d'aigua revisats | J36: 5 | K36: 10 | L36: Gestionar i planificar els recursos hídrics de l'ENP | M36: Comú | N36: Obligatori | O36: Gestió i manteniment de les fonts i punts d'aigua del PNIN perquè els recursos hídrics estiguin disponibles tant per als hàbitats i les espècies, com per als usos humans (ramaderia, aigua de boca...). | Q36: MÀXIMA | U36: 1.02 | V36: =PLA!U39*Llistes!$L$11*Llistes!$L$12 -> 136 | W36: Manteniment | X36: =IF(W36=Llistes!$K$2,Llistes!$L$2,IF(W36=Llistes!$K$3,Llistes!$L$3,IF(W36=Llistes!$K$4,Llistes!$L$4,IF(W36=Llistes!$K$5,Llistes!$L$5,IF(W36=Llistes!$K$6,Llistes!$L$6,IF(W36=Llistes!$K$7,Llistes!$L$7,"")))))) -> Sergi Roura | Y36: X | Z36: X | AA36: X | AB36: X
A37: NATURA | F37: 02.1.2 | G37: =L37 -> Gestionar i planificar els recursos hídrics de l'ENP | H37: Manteniment de GR, itineraris, camins d’accés a dòlmens i menhirs (XN2000) | I37: Nombre de camins, dòlmens i menhirs revisats | L37: Gestionar i planificar els recursos hídrics de l'ENP | M37: Comú | N37: Obligatori | O37: Gestió i manteniment de les fonts i punts d'aigua del PNIN perquè els recursos hídrics estiguin disponibles tant per als hàbitats i les espècies, com per als usos humans (ramaderia, aigua de boca...). | Q37: MÀXIMA | U37: 1.02 | V37: =PLA!U40*Llistes!$L$11*Llistes!$L$12 -> 136 | W37: Manteniment | X37: =IF(W37=Llistes!$K$2,Llistes!$L$2,IF(W37=Llistes!$K$3,Llistes!$L$3,IF(W37=Llistes!$K$4,Llistes!$L$4,IF(W37=Llistes!$K$5,Llistes!$L$5,IF(W37=Llistes!$K$6,Llistes!$L$6,IF(W37=Llistes!$K$7,Llistes!$L$7,"")))))) -> Sergi Roura
A38: NATURA | F38: 02.1.2 | G38: =L38 -> Gestionar i planificar els recursos hídrics de l'ENP | H38: Manteniment de la captació de la font de la Verna per compatibilitzar els usos agroramaders i els cabals naturals. | I38: Recurs hídric disponible i en funcionament | K38: Sí | L38: Gestionar i planificar els recursos hídrics de l'ENP | M38: Comú | N38: Obligatori | O38: Gestió i manteniment de les fonts i punts d'aigua del PNIN perquè els recursos hídrics estiguin disponibles tant per als hàbitats i les espècies, com per als usos humans (ramaderia, aigua de boca...). | Q38: MÀXIMA | U38: 1.02 | V38: =PLA!U41*Llistes!$L$11*Llistes!$L$12 -> 136 | W38: Manteniment | X38: =IF(W38=Llistes!$K$2,Llistes!$L$2,IF(W38=Llistes!$K$3,Llistes!$L$3,IF(W38=Llistes!$K$4,Llistes!$L$4,IF(W38=Llistes!$K$5,Llistes!$L$5,IF(W38=Llistes!$K$6,Llistes!$L$6,IF(W38=Llistes!$K$7,Llistes!$L$7,"")))))) -> Sergi Roura | Y38: X | Z38: X | AA38: X | AB38: X
A39: NATURA | F39: 02.1.3 | L39: Participar en la redacció i execució dels instruments d'ordenació forestal sostenible i per la conservació en finques públiques | M39: Específic | N39: Optatiu
A40: NATURA | F40: 02.1.4 | L40: Promoure la redacció d'instruments d'ordenació forestal per reduir la sensibilitat i vulnerabilitat dels boscos al canvi climàtic en finques privades | M40: Específic | N40: Optatiu
A41: NATURA | D41: 02.2 | E41: Planificar la prevenció i extinció d’incendis forestals i la gestió del foc de forma coordinada amb els diferents agents del territori | F41: 02.2.1 | G41: Col·laborar en la implementació del Pla de Prevenció d'Incendis | H41: Coordinació de les accions incloses en el Pla de prevencio d'incendis al PNIN. | I41: Nombre de reunions de coordinació de prevenció d'incendis | J41: 2 | K41: 4 | L41: Redactar i implementar el Pla de Prevenció d'Incendis | M41: Comú | N41: Obligatori | O41: El Pla de Prevenció d'Incendis ja està redactat i vigent des de fa anys per a tot el massís de l'Albera | Q41: ALTA | R41: *Elaboració del Pla de Prevenció d'Incendis *Definició de: xarxa estratègica i complementària de vials forestals, xarxa estratègica i complementària de punts d’aigua, tractaments de vegetació, punts estratègics de gestió | U41: 0.045 | V41: =PLA!U44*Llistes!$L$11*Llistes!$L$12 -> 6 | W41: Direcció | X41: =IF(W41=Llistes!$K$2,Llistes!$L$2,IF(W41=Llistes!$K$3,Llistes!$L$3,IF(W41=Llistes!$K$4,Llistes!$L$4,IF(W41=Llistes!$K$5,Llistes!$L$5,IF(W41=Llistes!$K$6,Llistes!$L$6,IF(W41=Llistes!$K$7,Llistes!$L$7,"")))))) -> Gerard Carrion | Y41: X | Z41: X | AA41: X | AB41: X
A42: NATURA | F42: 02.2.1 | G42: Col·laborar en la implementació del Pla de Prevenció d'Incendis | H42: Col·laboració en l'execució d'actuacions de prevenció d'incendis com el manteniment de franges a la carretera d'accés al monestir de Sant Quirze de Colera. | I42: Nombres d'hores dedicades a la col·laboració | J42: 1 | K42: 2 | L42: Redactar i implementar el Pla de Prevenció d'Incendis | M42: Comú | N42: Obligatori | O42: El Pla de Prevenció d'Incendis ja està redactat i vigent des de fa anys per a tot el massís de l'Albera | Q42: ALTA | R42: *Elaboració del Pla de Prevenció d'Incendis *Definició de: xarxa estratègica i complementària de vials forestals, xarxa estratègica i complementària de punts d’aigua, tractaments de vegetació, punts estratègics de gestió | S42: ESNATURA | T42: Equip de PPI: Disseny del protocol de treball | U42: 0.045 | V42: =PLA!U45*Llistes!$L$11*Llistes!$L$12 -> 6 | W42: Direcció | X42: =IF(W42=Llistes!$K$2,Llistes!$L$2,IF(W42=Llistes!$K$3,Llistes!$L$3,IF(W42=Llistes!$K$4,Llistes!$L$4,IF(W42=Llistes!$K$5,Llistes!$L$5,IF(W42=Llistes!$K$6,Llistes!$L$6,IF(W42=Llistes!$K$7,Llistes!$L$7,"")))))) -> Gerard Carrion | Y42: X | Z42: X | AA42: X | AB42: X
A43: NATURA | F43: 02.2.2 | G43: Participar en la definició i planificació de la gestió del foc per a la millora de l'ENP | H43: Participació a la Taula de Foc de l'Albera i Cap de Creus | I43: Assistència i participació a les reunions de la Taula del Foc | K43: 1 | L43: Definir i planificar la gestió del foc per a la millora de l'ENP | M43: Específic | N43: Obligatori | O43: La Taula de Foc, coordinada per Bombers i a la qual participem, és el marc on es prenen aquestes decisions. | Q43: ALTA | R43: *Pla de gestió de foc *Pla de gestió de cremes | T43: SPEN: Elaboració d'un model de pla de gestió | U43: 0.045 | V43: =PLA!U46*Llistes!$L$11*Llistes!$L$12 -> 6 | W43: Direcció | X43: =IF(W43=Llistes!$K$2,Llistes!$L$2,IF(W43=Llistes!$K$3,Llistes!$L$3,IF(W43=Llistes!$K$4,Llistes!$L$4,IF(W43=Llistes!$K$5,Llistes!$L$5,IF(W43=Llistes!$K$6,Llistes!$L$6,IF(W43=Llistes!$K$7,Llistes!$L$7,"")))))) -> Gerard Carrion | Y43: X | Z43: X | AA43: X | AB43: X
A44: NATURA | F44: 02.2.3 | G44: Treballar per a la prevenció d'incendis juntament amb el CAR, propietaris, ajuntaments, protecció civil, ADF, DARPA i bombers. | H44: Organització de reunions de coordinació de prevenció d'incendis en col·laboració amb el CAR, especialment en el cas de tancament del massís. | I44: Nombre de reunions organitzades | J44: 1 reunió/any | K44: 4 reunions/any | L44: Treballar per a la prevenció d'incendis juntament amb els propietaris, ajuntaments, protecció civil, ADF i bombers. | M44: Comú | N44: Obligatori | O44: petita modificació del redactat, afegint el CAR i el DARPA (per petició d'aquest Departament) | Q44: MITJANA | U44: 0.045 | V44: =PLA!U47*Llistes!$L$11*Llistes!$L$12 -> 6 | W44: Direcció | X44: =IF(W44=Llistes!$K$2,Llistes!$L$2,IF(W44=Llistes!$K$3,Llistes!$L$3,IF(W44=Llistes!$K$4,Llistes!$L$4,IF(W44=Llistes!$K$5,Llistes!$L$5,IF(W44=Llistes!$K$6,Llistes!$L$6,IF(W44=Llistes!$K$7,Llistes!$L$7,"")))))) -> Gerard Carrion | Y44: X | Z44: X | AA44: X | AB44: X
A45: NATURA | B45: 3 | C45: PROTEGIR LA BIODIVERSITAT, i especialment els elements fràgils i amenaçats, d’interès comunitari o de major interès natural. | D45: 03.1 | E45: Prevenir, minimitzar i compensar els impactes ambientals dels usos i activitats que es desenvolupin en l'àmbit de l'ENP | F45: 03.1.1 | G45: Participar en les consultes dels processos d'Avaluació Ambiental que afectin directament o indirectament l’ENP | H45: Redacció dels informes preceptius sobre avaluació ambiental de projectes o plans que puguin afectar l'ENP. | I45: Nombre d'informes d'AIA | J45: 1 informe/ any | K45: 2 informe/any | L45: Participar en les consultes dels procesos d'Avaluació Ambiental que afectin directament o indirectament l’espai del ENP | M45: Comú | N45: Obligatori | O45: petita modificació del redactat | Q45: MITJANA | U45: 0.045 | V45: =PLA!U48*Llistes!$L$11*Llistes!$L$12 -> 6 | W45: Direcció | X45: =IF(W45=Llistes!$K$2,Llistes!$L$2,IF(W45=Llistes!$K$3,Llistes!$L$3,IF(W45=Llistes!$K$4,Llistes!$L$4,IF(W45=Llistes!$K$5,Llistes!$L$5,IF(W45=Llistes!$K$6,Llistes!$L$6,IF(W45=Llistes!$K$7,Llistes!$L$7,"")))))) -> Gerard Carrion | Y45: X | Z45: X | AA45: X | AB45: X
A46: NATURA | F46: 03.1.2 | G46: Exercir un seguiment efectiu dels treballs informats a l'ENP per assegurar l'acompliment de les condicions establertes. | H46: Fer visites als treballs informats per l'òrgan de gestió, en coordinació amb l'OTAAA. | I46: Nombre visites camp relacionades amb informes | J46: 1 | K46: 4 | L46: Exercir un seguiment efectiu de les obres al Parc juntament amb les Oficines Territorials d'Acció i Avaluació Ambiental als efectes d'assegurar la correcta translació de la tutela administrativa. | M46: Comú | N46: Obligatori | O46: modificació del redactat | Q46: MITJANA | U46: 0.51 | V46: =PLA!U49*Llistes!$L$11*Llistes!$L$12 -> 68 | W46: Direcció | X46: =IF(W46=Llistes!$K$2,Llistes!$L$2,IF(W46=Llistes!$K$3,Llistes!$L$3,IF(W46=Llistes!$K$4,Llistes!$L$4,IF(W46=Llistes!$K$5,Llistes!$L$5,IF(W46=Llistes!$K$6,Llistes!$L$6,IF(W46=Llistes!$K$7,Llistes!$L$7,"")))))) -> Gerard Carrion | Y46: X | Z46: X | AA46: X | AB46: X
A47: NATURA | F47: 03.1.3 | G47: =L47 -> Participar en la compensació d'impactes residuals durant els processos d'avaluació ambiental mitjançant la identificació de necessitats d'actuació prioritària dins i fora dels límits de l’ENP | H47: Identificació de possibles actuacions que es poguessin incloure en el marc de mesures compensatòries derivades de l'avaluació ambiental de projectes. | I47: Redacció del catàleg | K47: Sí | L47: Participar en la compensació d'impactes residuals durant els processos d'avaluació ambiental mitjançant la identificació de necessitats d'actuació prioritària dins i fora dels límits de l’ENP | M47: Comú | N47: Obligatori | Q47: MITJANA | R47: *Catàleg de possibles actuacions compensatories *Catàleg de sectors amb necessitats d'intervenció (incloent també zones fora dels límits de l'ENP que es considerin importants per al manteniment de la connectivitat ecològica dels espais) | U47: 0.045 | V47: =PLA!U50*Llistes!$L$11*Llistes!$L$12 -> 6 | W47: Direcció | X47: =IF(W47=Llistes!$K$2,Llistes!$L$2,IF(W47=Llistes!$K$3,Llistes!$L$3,IF(W47=Llistes!$K$4,Llistes!$L$4,IF(W47=Llistes!$K$5,Llistes!$L$5,IF(W47=Llistes!$K$6,Llistes!$L$6,IF(W47=Llistes!$K$7,Llistes!$L$7,"")))))) -> Gerard Carrion | AB47: X
A48: NATURA | D48: 03.2 | E48: Garantir el compliment dels objectius de conservació dotant l'ENP de la planificació adequada segons estableix la normativa vigent (Pla de Protecció, PRUG, plans específics...) | F48: 03.2.1 | G48: =L48 -> Participar en l'elaboració dels instruments de planificació de l'ENP | H48: Participació en l'elaboració del Pla de Protecció (PP) juntament amb el SPEN. | I48: Participació en l'elaboració del Pla de Protecció | K48: Sí | L48: Participar en l'elaboració dels instruments de planificació de l'ENP | M48: Comú | N48: Obligatori | O48: Estaríem parlant concretament del pla de protecció, en el nostre cas. | Q48: MÀXIMA | R48: *Participació en l'elaboració del Pla de Protecció (PP) juntament amb l'SPEN. *Participació en l'elaboració del Pla Rector d'usos i Gestió (PRUG) juntament amb l'SPEN. *Participació en l'elaboració d'altres instruments de planificació juntament amb l'SPEN. | T48: SPEN: Elaboració del Pla rector d'usos i gestió. SPEN: Elaboració del Pla rector d'usos i gestió | U48: 0.45 | V48: =PLA!U51*Llistes!$L$11*Llistes!$L$12 -> 60 | W48: Direcció | X48: =IF(W48=Llistes!$K$2,Llistes!$L$2,IF(W48=Llistes!$K$3,Llistes!$L$3,IF(W48=Llistes!$K$4,Llistes!$L$4,IF(W48=Llistes!$K$5,Llistes!$L$5,IF(W48=Llistes!$K$6,Llistes!$L$6,IF(W48=Llistes!$K$7,Llistes!$L$7,"")))))) -> Gerard Carrion | Y48: X | Z48: X | AA48: X | AB48: X
A49: NATURA | F49: 03.2.1 | G49: =L49 -> Participar en l'elaboració dels instruments de planificació de l'ENP | H49: Col·laboració amb servei de planificació amb els nous estudis a l'espai XN2000 Basses de l’Albera | I49: Col·laboració en la planificació dels estudis | K49: Sí | L49: Participar en l'elaboració dels instruments de planificació de l'ENP | M49: Comú | N49: Obligatori | Q49: ALTA | U49: 0.3 | V49: =PLA!U52*Llistes!$L$11*Llistes!$L$12 -> 40 | W49: XN2000 | X49: =IF(W49=Llistes!$K$2,Llistes!$L$2,IF(W49=Llistes!$K$3,Llistes!$L$3,IF(W49=Llistes!$K$4,Llistes!$L$4,IF(W49=Llistes!$K$5,Llistes!$L$5,IF(W49=Llistes!$K$6,Llistes!$L$6,IF(W49=Llistes!$K$7,Llistes!$L$7,"")))))) -> Montse Pascual | Y49: X | Z49: X | AA49: X | AB49: X
A50: NATURA | F50: 03.2.1 | G50: =L50 -> Participar en l'elaboració dels instruments de planificació de l'ENP | H50: Participació en l’òrgan de governança de XN2000 Basses de l’Albera | I50: Participació en l'òrgan de governança Basses Albera | K50: Sí | L50: Participar en l'elaboració dels instruments de planificació de l'ENP | M50: Comú | N50: Obligatori | Q50: ALTA | U50: 0.15 | V50: =PLA!U53*Llistes!$L$11*Llistes!$L$12 -> 20 | W50: XN2000 | X50: =IF(W50=Llistes!$K$2,Llistes!$L$2,IF(W50=Llistes!$K$3,Llistes!$L$3,IF(W50=Llistes!$K$4,Llistes!$L$4,IF(W50=Llistes!$K$5,Llistes!$L$5,IF(W50=Llistes!$K$6,Llistes!$L$6,IF(W50=Llistes!$K$7,Llistes!$L$7,"")))))) -> Montse Pascual | Y50: X | Z50: X | AA50: X | AB50: X
A51: NATURA | F51: 03.2.1 | G51: =L51 -> Participar en l'elaboració dels instruments de planificació de l'ENP | H51: Execució del projecte d’ordenació de Cap Ras (XN2000) | I51: S'ha redactat el projecte d'ordenació | K51: Sí | L51: Participar en l'elaboració dels instruments de planificació de l'ENP | M51: Comú | N51: Obligatori | Q51: ALTA | U51: 0.45 | V51: =PLA!U54*Llistes!$L$11*Llistes!$L$12 -> 60 | W51: Direcció | X51: =IF(W51=Llistes!$K$2,Llistes!$L$2,IF(W51=Llistes!$K$3,Llistes!$L$3,IF(W51=Llistes!$K$4,Llistes!$L$4,IF(W51=Llistes!$K$5,Llistes!$L$5,IF(W51=Llistes!$K$6,Llistes!$L$6,IF(W51=Llistes!$K$7,Llistes!$L$7,"")))))) -> Gerard Carrion | Y51: X | Z51: X | AA51: X | AB51: X
A52: NATURA | D52: 03.3 | E52: Vetllar pel manteniment dels cabals ecològics i la bona qualitat dels cursos fluvials de l'ENP de forma coordinada amb l'administració competent | F52: 03.3.1 | G52: =L52 -> Avaluar i controlar les actuacions que produeixin drenatges, captacions o que puguin impedir l’arribada d’aigua tant superficial com freàtica | H52: Participació, de forma coordinada amb l'administració competent, en l'avaluació i control d'actuacions dins els límits de l'ENP. | I52: Nombre de captacions il·legals identificades | K52: 0 | L52: Avaluar i controlar les actuacions que produeixin drenatges, captacions o que puguin impedir l’arribada d’aigua tant superficial com freàtica | M52: Específic | N52: Obligatori | Q52: ALTA | R52: *Participació, de forma coordinada amb l'administració competent, en l'avaluació i control d'actuacions dins els límits de l'ENP. *Impuls del control per incompliment de la normativa i el seu trasllat cap a l'administració competent *Participació en les comunitats d'usuaris de les conques | U52: 0.015 | V52: =PLA!U55*Llistes!$L$11*Llistes!$L$12 -> 2 | W52: Direcció | X52: =IF(W52=Llistes!$K$2,Llistes!$L$2,IF(W52=Llistes!$K$3,Llistes!$L$3,IF(W52=Llistes!$K$4,Llistes!$L$4,IF(W52=Llistes!$K$5,Llistes!$L$5,IF(W52=Llistes!$K$6,Llistes!$L$6,IF(W52=Llistes!$K$7,Llistes!$L$7,"")))))) -> Gerard Carrion | Y52: X | Z52: X | AA52: X | AB52: X
A53: NATURA | F53: 03.3.2 | L53: Vetllar per la regulació dels dragatges, canalitzacions o implantació d'activitats extractives que puguin modificar la llera i el cabal dels rius | M53: Específic | N53: Optatiu
A54: NATURA | F54: 03.3.3 | L54: Avaluar i controlar les actuacions que produeixin drenatges, captacions o que puguin impedir l’arribada d’aigua tant superficial com freàtica | M54: Específic | N54: Optatiu
A55: NATURA | F55: 03.3.4 | L55: Vetllar pel compliment de la normativa de depuració dels efluents agroramaders, urbans i industrials que s'aboquen als cursos fluvials | M55: Específic | N55: Optatiu
A56: NATURA | F56: 03.3.5 | L56: Colaborar amb l'òrgan competent per la conservació del domini públic d'acord amb les delimitacions i la normativa d'usos vigent | M56: Comú | N56: Optatiu
A57: NATURA | D57: 03.4 | E57: Incrementar el patrimoni públic destinat a la conservació i millora del patrimoni natural | F57: 03.4.1 | G57: =L57 -> Identificar espais prioritaris per a la compra de terrenys de més valor dins l'ENP | H57: Participació en la identificació de finques prioritàries de compra en base als criteris indicats | I57: Nombre de finques identificades com a prioritàries per a la compra de terrenys (XN2000) | J57: 1 | K57: 5 | L57: Identificar espais prioritaris per a la compra de terrenys de més valor dins l'ENP | M57: Comú | N57: Obligatori | Q57: ALTA | R57: *Participació en la identificació de finques prioritàries en base als criteris indicats | T57: SENP/SPEN: Facilitar els criteris a seguir | U57: 0.045 | V57: =PLA!U60*Llistes!$L$11*Llistes!$L$12 -> 6 | W57: Direcció | X57: =IF(W57=Llistes!$K$2,Llistes!$L$2,IF(W57=Llistes!$K$3,Llistes!$L$3,IF(W57=Llistes!$K$4,Llistes!$L$4,IF(W57=Llistes!$K$5,Llistes!$L$5,IF(W57=Llistes!$K$6,Llistes!$L$6,IF(W57=Llistes!$K$7,Llistes!$L$7,"")))))) -> Gerard Carrion | Y57: X | Z57: X | AA57: X | AB57: X
F58: 03.4.2 | L58: Identificar espais prioritaris per a la gestió directa | M58: Comú | N58: Optatiu
A59: CULTURA | B59: 4 | C59: CONSERVAR ELS ELEMENTS CULTURALS materials i immaterials vinculats a la natura | D59: 04.1 | E59: Millorar el coneixement disponible sobre el patrimoni arquitectònic i cultural (material i immaterial) vinculat al patrimoni natural, el seu estat de conservació i els estils propis dels territoris de l'ENP | F59: 04.1.1 | G59: Elaborar l'inventari i cartografia de patrimoni cultural de l'ENP, que també inclogui el patrimoni etnològic i immaterial | H59: Recopilació de la informació dels catàlegs d'altres admnistracions, buidat bibliogràfic, i fer diagnosi | I59: S'ha realitzat la recopilació d'informació dels diversos catàlegs existents | J59: 2 | K59: 5 | L59: Elaborar l'inventari i cartografia de patrimoni cultural de l'ENP, que també inclogui el patrimoni etnològic i immaterial | M59: Comú | N59: Obligatori | Q59: MITJANA | R59: *Recopilació de la informació dels catàlegs dels ajuntaments de l'ENP i fer diagnosi *Inventari de patrimoni cultural material *Inventari de patrimoni cultural immaterial (metodologia de l'inventari de la unesco) *Elaboració d'un mapa de tranquil·litat. | U59: 0.045 | V59: =PLA!U62*Llistes!$L$11*Llistes!$L$12 -> 6 | W59: Ús públic i educació ambiental | X59: =IF(W59=Llistes!$K$2,Llistes!$L$2,IF(W59=Llistes!$K$3,Llistes!$L$3,IF(W59=Llistes!$K$4,Llistes!$L$4,IF(W59=Llistes!$K$5,Llistes!$L$5,IF(W59=Llistes!$K$6,Llistes!$L$6,IF(W59=Llistes!$K$7,Llistes!$L$7,"")))))) -> Ivan Bustamante | Y59: X | Z59: X
A60: CULTURA | F60: 04.1.1 | G60: =G61 -> Elaborar l'inventari i cartografia de patrimoni cultural de l'ENP, que també inclogui el patrimoni etnològic i immaterial | H60: Redacció de l'inventari de patrimoni cultural material | I60: Es disposa de l'inventari de patrimoni cultural material | K60: Sí | L60: Elaborar l'inventari i cartografia de patrimoni cultural de l'ENP, que també inclogui el patrimoni etnològic i immaterial | M60: Comú | N60: Obligatori | Q60: MITJANA | R60: *Recopilació de la informació dels catàlegs dels ajuntaments de l'ENP i fer diagnosi *Inventari de patrimoni cultural material *Inventari de patrimoni cultural immaterial (metodologia de l'inventari de la unesco) *Elaboració d'un mapa de tranquil·litat. | U60: 0.045 | V60: =PLA!U63*Llistes!$L$11*Llistes!$L$12 -> 6 | W60: Direcció | X60: =IF(W60=Llistes!$K$2,Llistes!$L$2,IF(W60=Llistes!$K$3,Llistes!$L$3,IF(W60=Llistes!$K$4,Llistes!$L$4,IF(W60=Llistes!$K$5,Llistes!$L$5,IF(W60=Llistes!$K$6,Llistes!$L$6,IF(W60=Llistes!$K$7,Llistes!$L$7,"")))))) -> Gerard Carrion | AA60: X
A61: CULTURA | F61: 04.1.1 | G61: =L61 -> Elaborar l'inventari i cartografia de patrimoni cultural de l'ENP, que també inclogui el patrimoni etnològic i immaterial | H61: Redacció de l'inventari de patrimoni cultural immaterial (metodologia de l'inventari de la UNESCO) | I61: Es disposa de l'inventari de patrimoni cultural immaterial | K61: Sí | L61: Elaborar l'inventari i cartografia de patrimoni cultural de l'ENP, que també inclogui el patrimoni etnològic i immaterial | M61: Comú | N61: Obligatori | Q61: MITJANA | R61: *Recopilació de la informació dels catàlegs dels ajuntaments de l'ENP i fer diagnosi *Inventari de patrimoni cultural material *Inventari de patrimoni cultural immaterial (metodologia de l'inventari de la unesco) *Elaboració d'un mapa de tranquil·litat. | U61: 0.045 | V61: =PLA!U64*Llistes!$L$11*Llistes!$L$12 -> 6 | W61: Direcció | X61: =IF(W61=Llistes!$K$2,Llistes!$L$2,IF(W61=Llistes!$K$3,Llistes!$L$3,IF(W61=Llistes!$K$4,Llistes!$L$4,IF(W61=Llistes!$K$5,Llistes!$L$5,IF(W61=Llistes!$K$6,Llistes!$L$6,IF(W61=Llistes!$K$7,Llistes!$L$7,"")))))) -> Gerard Carrion | AA61: X
A62: CULTURA | F62: 04.1.2 | G62: =L62 -> Elaborar el catàleg lingüístic (localismes) de patrimoni natural, geografia popular, festes i activitats tradicionals de l'ENP | H62: Redacció de l'inventari de patrimoni lingüístic | I62: Es disposa de l'inventari de patrimoni cultural lingüístic | K62: Sí | L62: Elaborar el catàleg lingüístic (localismes) de patrimoni natural, geografia popular, festes i activitats tradicionals de l'ENP | M62: Comú | N62: Obligatori | Q62: ALTA | U62: 0.045 | V62: =PLA!U65*Llistes!$L$11*Llistes!$L$12 -> 6 | W62: Direcció | X62: =IF(W62=Llistes!$K$2,Llistes!$L$2,IF(W62=Llistes!$K$3,Llistes!$L$3,IF(W62=Llistes!$K$4,Llistes!$L$4,IF(W62=Llistes!$K$5,Llistes!$L$5,IF(W62=Llistes!$K$6,Llistes!$L$6,IF(W62=Llistes!$K$7,Llistes!$L$7,"")))))) -> Gerard Carrion | AB62: X
A63: CULTURA | F63: 04.1.3 | G63: Elaborar l'inventari i cartografia de la xarxa de camins ramaders i altres vies públiques de l'ENP | H63: Redacció de l'inventari de camins ramaders o públics | I63: Es disposa de l'inventari de camins ramaders o públics | K63: Sí | L63: Elaborar la cartografia de la xarxa de camins ramaders i senders tradicionals de l'ENP | M63: Comú | N63: Obligatori | O63: Recollir la informació en forma d'inventari. Fixar-nos en la propietat pública, i no tant en si és tradicional o no, molt més difícil de saber de forma objectiva i històrica. | Q63: MITJANA | U63: 0.045 | V63: =PLA!U66*Llistes!$L$11*Llistes!$L$12 -> 6 | W63: Direcció | X63: =IF(W63=Llistes!$K$2,Llistes!$L$2,IF(W63=Llistes!$K$3,Llistes!$L$3,IF(W63=Llistes!$K$4,Llistes!$L$4,IF(W63=Llistes!$K$5,Llistes!$L$5,IF(W63=Llistes!$K$6,Llistes!$L$6,IF(W63=Llistes!$K$7,Llistes!$L$7,"")))))) -> Gerard Carrion | Z63: X
A64: CULTURA | D64: 04.2 | E64: Conservar i gestionar el patrimoni cultural de l'ENP de forma coordinada amb els agents responsables i entitats de referència | F64: 04.2.1 | G64: =L64 -> Identificar els ens de referència en patrimoni cultural (entitats, associacions, museus i ecomuseus, etc.) en l'àmbit de l'ENP | H64: Elaboració d'un mapa d'entitats, associacions, museus, ecomuseus, OPEI (Observatori del Patrimoni Etnològic i Immaterial), etc. | I64: Es disposa d'un mapa d'entitats, associacions, museus, ecomuseus, OPEI, etc | K64: Sí | L64: Identificar els ens de referència en patrimoni cultural (entitats, associacions, museus i ecomuseus, etc.) en l'àmbit de l'ENP | M64: Comú | N64: Obligatori | O64: Diria que ja està fet, però s'hauria de revisar. | Q64: MITJANA | R64: *Elaboració d'un mapa d'entitats, associacions, museus, ecomuseus, OPEI (Observatori del Patrimoni Etnològic i Immaterial), etc. | U64: 0.045 | V64: =PLA!U67*Llistes!$L$11*Llistes!$L$12 -> 6 | W64: Ús públic i educació ambiental | X64: =IF(W64=Llistes!$K$2,Llistes!$L$2,IF(W64=Llistes!$K$3,Llistes!$L$3,IF(W64=Llistes!$K$4,Llistes!$L$4,IF(W64=Llistes!$K$5,Llistes!$L$5,IF(W64=Llistes!$K$6,Llistes!$L$6,IF(W64=Llistes!$K$7,Llistes!$L$7,"")))))) -> Ivan Bustamante | Y64: X
A65: CULTURA | F65: 04.2.1 | G65: =L65 -> Identificar els ens de referència en patrimoni cultural (entitats, associacions, museus i ecomuseus, etc.) en l'àmbit de l'ENP | H65: Impuls de col·laboració amb la xarxa de museus i altres equipaments i entitats de referència | I65: Nombre d'activitats en col·laboració amb la xarxa de museus i altres equipaments i entitats de referència | J65: 2 | K65: 4 | L65: Identificar els ens de referència en patrimoni cultural (entitats, associacions, museus i ecomuseus, etc.) en l'àmbit de l'ENP | M65: Comú | N65: Obligatori | O65: Diria que ja està fet, però s'hauria de revisar. | Q65: MITJANA | R65: *Elaboració d'un mapa d'entitats, associacions, museus, ecomuseus, OPEI (Observatori del Patrimoni Etnològic i Immaterial), etc. | U65: 0.015 | V65: =PLA!U68*Llistes!$L$11*Llistes!$L$12 -> 2 | W65: Ús públic i educació ambiental | X65: =IF(W65=Llistes!$K$2,Llistes!$L$2,IF(W65=Llistes!$K$3,Llistes!$L$3,IF(W65=Llistes!$K$4,Llistes!$L$4,IF(W65=Llistes!$K$5,Llistes!$L$5,IF(W65=Llistes!$K$6,Llistes!$L$6,IF(W65=Llistes!$K$7,Llistes!$L$7,"")))))) -> Ivan Bustamante | Y65: X | Z65: X | AA65: X | AB65: X
A66: CULTURA | F66: 04.2.2 | G66: =L66 -> Articular treballs conjunts entre l'ENP i representants, gestors o custodis del patrimoni cultural per a la seva protecció i millora | H66: Foment de la cooperació tècnica dels gestors de l'ENP amb els representants o custodis del patrimoni cultural, per a un ús compartit dels recursos | I66: Nombre de reunions relacionades amb la cooperació tècnica dels gestors de l'ENP amb els representants del patrimoni cultural | J66: 2 | K66: 4 | L66: Articular treballs conjunts entre l'ENP i representants, gestors o custodis del patrimoni cultural per a la seva protecció i millora | M66: Comú | N66: Obligatori | O66: Els convenis són una forma jurídica difícil de portar a la pràctica. Val més parlar de col·laboració o acords. | Q66: MITJANA | R66: *Projecte parcs i museus *Impuls dels convenis de col·laboració amb la xarxa de museus i altres equipaments i entitats de referència *Foment de la cooperació tècnica dels gestors de l'ENP amb els representants o custodis del patrimoni cultural, i coordinar-ne l'ús compartit dels recursos | U66: 0.015 | V66: =PLA!U69*Llistes!$L$11*Llistes!$L$12 -> 2 | W66: Ús públic i educació ambiental | X66: =IF(W66=Llistes!$K$2,Llistes!$L$2,IF(W66=Llistes!$K$3,Llistes!$L$3,IF(W66=Llistes!$K$4,Llistes!$L$4,IF(W66=Llistes!$K$5,Llistes!$L$5,IF(W66=Llistes!$K$6,Llistes!$L$6,IF(W66=Llistes!$K$7,Llistes!$L$7,"")))))) -> Ivan Bustamante | Y66: X | Z66: X | AA66: X | AB66: X
A67: CULTURA | F67: 04.2.2 | G67: =L67 -> Articular treballs conjunts entre l'ENP i representants, gestors o custodis del patrimoni cultural per a la seva protecció i millora | H67: Coordinació de l'equip tècnic (propi) amb els responsables dels treballs de restauració arquitectònica i del patrimoni cultural | I67: Nombre de reunions amb els responsables dels treballs de restauració arquitectònica i del patrimoni cultural | J67: 2 | K67: 4 | L67: Articular treballs conjunts entre l'ENP i representants, gestors o custodis del patrimoni cultural per a la seva protecció i millora | M67: Comú | N67: Obligatori | O67: Els convenis són una forma jurídica difícil de portar a la pràctica. Val més parlar de col·laboració o acords. | Q67: MITJANA | R67: *Projecte parcs i museus *Impuls dels convenis de col·laboració amb la xarxa de museus i altres equipaments i entitats de referència *Foment de la cooperació tècnica dels gestors de l'ENP amb els representants o custodis del patrimoni cultural, i coordinar-ne l'ús compartit dels recursos | U67: 0.015 | V67: =PLA!U70*Llistes!$L$11*Llistes!$L$12 -> 2 | W67: Direcció | X67: =IF(W67=Llistes!$K$2,Llistes!$L$2,IF(W67=Llistes!$K$3,Llistes!$L$3,IF(W67=Llistes!$K$4,Llistes!$L$4,IF(W67=Llistes!$K$5,Llistes!$L$5,IF(W67=Llistes!$K$6,Llistes!$L$6,IF(W67=Llistes!$K$7,Llistes!$L$7,"")))))) -> Gerard Carrion | Y67: X | Z67: X | AA67: X | AB67: X
A68: CULTURA | F68: 04.2.3 | G68: =L68 -> Impulsar i/o participar dels treballs de restauració arquitectònica, arqueològica i del patrimoni cultural | H68: Participació en els treballs de restauració arquitectònica i del patrimoni cultural quan estan vinculats a l’àrea d’ús públic de l’ENP | I68: Nombre de treballs en què s'ha participat | J68: 1 | K68: 2 | L68: Impulsar i/o participar dels treballs de restauració arquitectònica, arqueològica i del patrimoni cultural | M68: Comú | N68: Obligatori | Q68: MITJANA | R68: *Coordinació de l'equip tècnic (propi) amb els responsables dels treballs de restauració arquitectònica i del patrimoni cultural *Participació quan els treballs estan vinculats a l’àrea d’ús públic de l’ENP | U68: 0.015 | V68: =PLA!U71*Llistes!$L$11*Llistes!$L$12 -> 2 | W68: Direcció | X68: =IF(W68=Llistes!$K$2,Llistes!$L$2,IF(W68=Llistes!$K$3,Llistes!$L$3,IF(W68=Llistes!$K$4,Llistes!$L$4,IF(W68=Llistes!$K$5,Llistes!$L$5,IF(W68=Llistes!$K$6,Llistes!$L$6,IF(W68=Llistes!$K$7,Llistes!$L$7,"")))))) -> Gerard Carrion | Y68: X | Z68: X | AA68: X | AB68: X
F69: 04.2.4 | L69: Disposar de personal especialitzat en patrimoni cultural | M69: Comú | N69: Obligatori
A70: CULTURA | D70: 04.3 | E70: Potenciar la conservació i recuperació del patrimoni cultural material i immaterial de l'ENP | F70: 04.3.1 | G70: =L70 -> Recuperar i conservar el patrimoni cultural immaterial (associat a les activitats i aprofitaments rurals tradicionals) i els valors espirituals | H70: Col·laborar en mantenir el patrimoni cultural immaterial. | I70: Nombre d'actuacions de col·laboració per mantenir el patrimoni cultural immaterial | J70: 4 | K70: 8 | L70: Recuperar i conservar el patrimoni cultural immaterial (associat a les activitats i aprofitaments rurals tradicionals) i els valors espirituals | M70: Específic | N70: Obligatori | Q70: MITJANA | S70: MAP | U70: 0.015 | V70: 2 | W70: Manteniment | X70: =IF(W70=Llistes!$K$2,Llistes!$L$2,IF(W70=Llistes!$K$3,Llistes!$L$3,IF(W70=Llistes!$K$4,Llistes!$L$4,IF(W70=Llistes!$K$5,Llistes!$L$5,IF(W70=Llistes!$K$6,Llistes!$L$6,IF(W70=Llistes!$K$7,Llistes!$L$7,"")))))) -> Sergi Roura | Y70: X | Z70: X | AA70: X | AB70: X
A71: CULTURA | F71: 04.3.2 | G71: =L71 -> Recuperar i conservar el patrimoni cultural rural vinculat específicament a construccions de pedra en sec | H71: Conservació de construccions de pedra seca | I71: Nombre d'actuacions amb pedra seca | J71: 2 | K71: 4 | L71: Recuperar i conservar el patrimoni cultural rural vinculat específicament a construccions de pedra en sec | M71: Comú | N71: Obligatori | Q71: MITJANA | U71: 0.045 | V71: =PLA!U74*Llistes!$L$11*Llistes!$L$12 -> 6 | W71: Manteniment | X71: =IF(W71=Llistes!$K$2,Llistes!$L$2,IF(W71=Llistes!$K$3,Llistes!$L$3,IF(W71=Llistes!$K$4,Llistes!$L$4,IF(W71=Llistes!$K$5,Llistes!$L$5,IF(W71=Llistes!$K$6,Llistes!$L$6,IF(W71=Llistes!$K$7,Llistes!$L$7,"")))))) -> Sergi Roura | Y71: X | Z71: X | AA71: X | AB71: X
A72: CULTURA | F72: 04.3.3 | G72: =L72 -> Fomentar la recuperació i conservació de l'arquitectura tradicional d'interès de les edificacions i construccions | H72: Foment de la recuperació i conservació de l'arquitectura tradicional d'interès de les edificacions i construccions | I72: Nombre d'actuacions vinculades amb la recuperació i conservació de l'arquitectura tradicional d'interès de les edificacions i construccions | J72: 2 | K72: 4 | L72: Fomentar la recuperació i conservació de l'arquitectura tradicional d'interès de les edificacions i construccions | M72: Comú | N72: Obligatori | Q72: MITJANA | U72: 0.015 | V72: =PLA!U75*Llistes!$L$11*Llistes!$L$12 -> 2 | W72: Manteniment | X72: =IF(W72=Llistes!$K$2,Llistes!$L$2,IF(W72=Llistes!$K$3,Llistes!$L$3,IF(W72=Llistes!$K$4,Llistes!$L$4,IF(W72=Llistes!$K$5,Llistes!$L$5,IF(W72=Llistes!$K$6,Llistes!$L$6,IF(W72=Llistes!$K$7,Llistes!$L$7,"")))))) -> Sergi Roura | Y72: X | Z72: X | AA72: X | AB72: X
A73: CULTURA | F73: 04.3.4 | G73: =L73 -> Identificar i conservar la diversitat domesticada de varietats agrícoles i ramaderes locals | H73: Conservar les varietats locals en planters (de llavor o esqueix). | I73: Nombre de varietats locals que s'han col·laborat a mantenir | J73: 3 | K73: 6 | L73: Identificar i conservar la diversitat domesticada de varietats agrícoles i ramaderes locals | M73: Comú | N73: Obligatori | O73: Ja s'està fent per a la vaca de l'Albera sense la nostra participació, i és que tampoc hi arribem | Q73: BAIXA | R73: *Banc de llavors *Convenis ramaders per la cria de races locals | S73: ESNATURA | U73: 0.015 | V73: =PLA!U76*Llistes!$L$11*Llistes!$L$12 -> 2 | W73: Direcció | X73: =IF(W73=Llistes!$K$2,Llistes!$L$2,IF(W73=Llistes!$K$3,Llistes!$L$3,IF(W73=Llistes!$K$4,Llistes!$L$4,IF(W73=Llistes!$K$5,Llistes!$L$5,IF(W73=Llistes!$K$6,Llistes!$L$6,IF(W73=Llistes!$K$7,Llistes!$L$7,"")))))) -> Gerard Carrion | Y73: X | Z73: X | AA73: X | AB73: X
H74: Col·laborar en mantenir arbres fruiters de varietats locals situats al costat dels masos del massís. | I74: Nombre d'arbres fruiters de varietats locals que s'han col·laborat a mantenir | J74: 5 | K74: 8 | U74: 0.015 | V74: =PLA!U77*Llistes!$L$11*Llistes!$L$12 -> 2 | W74: Direcció | X74: =IF(W74=Llistes!$K$2,Llistes!$L$2,IF(W74=Llistes!$K$3,Llistes!$L$3,IF(W74=Llistes!$K$4,Llistes!$L$4,IF(W74=Llistes!$K$5,Llistes!$L$5,IF(W74=Llistes!$K$6,Llistes!$L$6,IF(W74=Llistes!$K$7,Llistes!$L$7,"")))))) -> Gerard Carrion | Y74: X | Z74: X | AA74: X | AB74: X
A75: CULTURA | D75: 04.4 | E75: Donar a conèixer els elements culturals com a valors del paisatge de l'ENP en les activitats d'ús públic | F75: 04.4.1 | G75: =L75 -> Integrar el patrimoni cultural als itineraris i cartelleria de l'ENP. | H75: Integració del patrimoni cultural als itineraris i cartelleria de l'ENP. | I75: Nombre de cartells de patrimoni cultural que s'han integrat en la cartelleria de l'ENP (nous o manteniment) | J75: 4 | K75: 10 | L75: Integrar el patrimoni cultural als itineraris i cartelleria de l'ENP. | M75: Comú | N75: Obligatori | O75: Ja es té en compte, però així es visualitza. | Q75: ALTA | U75: 0.015 | V75: =PLA!U78*Llistes!$L$11*Llistes!$L$12 -> 2 | W75: Ús públic i educació ambiental | X75: =IF(W75=Llistes!$K$2,Llistes!$L$2,IF(W75=Llistes!$K$3,Llistes!$L$3,IF(W75=Llistes!$K$4,Llistes!$L$4,IF(W75=Llistes!$K$5,Llistes!$L$5,IF(W75=Llistes!$K$6,Llistes!$L$6,IF(W75=Llistes!$K$7,Llistes!$L$7,"")))))) -> Ivan Bustamante | Y75: X | Z75: X | AA75: X | AB75: X
A76: CULTURA | F76: 04.4.2 | G76: =L76 -> Incorporar el patrimoni cultural en els plans d’ús públic i educació ambiental per fomentar-ne la seva conservació i divulgació. | H76: Incorporació del patrimoni cultural en els plans d’ús públic i educació ambiental | I76: S'incorpora el patrimoni cultural en els plans d’ús públic i educació ambiental | K76: Sí | L76: Incorporar el patrimoni cultural en els plans d’ús públic i educació ambiental per fomentar-ne la seva conservació i divulgació. | M76: Comú | N76: Obligatori | O76: Ja es té en compte, però així es visualitza. | Q76: ALTA | U76: 0.015 | V76: =PLA!U79*Llistes!$L$11*Llistes!$L$12 -> 2 | W76: Ús públic i educació ambiental | X76: =IF(W76=Llistes!$K$2,Llistes!$L$2,IF(W76=Llistes!$K$3,Llistes!$L$3,IF(W76=Llistes!$K$4,Llistes!$L$4,IF(W76=Llistes!$K$5,Llistes!$L$5,IF(W76=Llistes!$K$6,Llistes!$L$6,IF(W76=Llistes!$K$7,Llistes!$L$7,"")))))) -> Ivan Bustamante | Y76: X | Z76: X | AA76: X | AB76: X
A77: CULTURA | F77: 04.4.3 | G77: =L77 -> Formar el personal dels punts d’informació en els valors culturals de l'ENP | H77: Formació del personal dels punts d'informació (propi o aliè) en els valors culturals de l'ENP. | I77: Hores de formació sobre els valors culturals | J77: 2 | K77: 4 | L77: Formar el personal dels punts d’informació en els valors culturals de l'ENP | M77: Comú | N77: Obligatori | Q77: MÀXIMA | U77: 0.015 | V77: =PLA!U80*Llistes!$L$11*Llistes!$L$12 -> 2 | W77: Ús públic i educació ambiental | X77: =IF(W77=Llistes!$K$2,Llistes!$L$2,IF(W77=Llistes!$K$3,Llistes!$L$3,IF(W77=Llistes!$K$4,Llistes!$L$4,IF(W77=Llistes!$K$5,Llistes!$L$5,IF(W77=Llistes!$K$6,Llistes!$L$6,IF(W77=Llistes!$K$7,Llistes!$L$7,"")))))) -> Ivan Bustamante | Y77: X | Z77: X | AA77: X | AB77: X
A78: CULTURA | B78: 5 | C78: PROTEGIR EL PAISATGE i la qualitat de l'ambient visual, sonor i lumínic. | D78: 05.1 | E78: Identificar els elements d'interès paisatgístic de l'espai | F78: 05.1.1 | G78: =L78 -> Elaborar un inventari d'elements d'interès paisatgístic de l'ENP d'acord amb el Catàleg de paisatge de la zona | H78: Redacció de l'inventari d'elements d'interès paisatgístic de l'ENP d'acord amb el Catàleg de paisatge de la zona | I78: S'ha redactat l'inventari d'elements d'interès paisatgístic de l'ENP d'acord amb el Catàleg de paisatge de la zona | K78: Sí | L78: Elaborar un inventari d'elements d'interès paisatgístic de l'ENP d'acord amb el Catàleg de paisatge de la zona | M78: Comú | N78: Obligatori | Q78: MITJANA | U78: 0.015 | V78: =PLA!U81*Llistes!$L$11*Llistes!$L$12 -> 2 | W78: Ús públic i educació ambiental | X78: =IF(W78=Llistes!$K$2,Llistes!$L$2,IF(W78=Llistes!$K$3,Llistes!$L$3,IF(W78=Llistes!$K$4,Llistes!$L$4,IF(W78=Llistes!$K$5,Llistes!$L$5,IF(W78=Llistes!$K$6,Llistes!$L$6,IF(W78=Llistes!$K$7,Llistes!$L$7,"")))))) -> Ivan Bustamante | Y78: X | Z78: X | AA78: X | AB78: X
A79: CULTURA | D79: 05.2 | E79: Millorar la qualitat paisatgística | F79: 05.2.1 | G79: Minimitzar la brutícia, deixalles, vandalisme i males praxis dins l'ENP | H79: Identificació dels punts on s'acumulen més deixalles. | I79: Nombre de zones d'acumulació de deixalles | J79: 0 | K79: 0 | L79: Minimitzar la brutícia, deixalles, vandalisme i males praxis dins l'ENP | M79: Comú | N79: Obligatori | Q79: MITJANA | U79: 0.015 | V79: =PLA!U82*Llistes!$L$11*Llistes!$L$12 -> 2 | W79: Manteniment | X79: =IF(W79=Llistes!$K$2,Llistes!$L$2,IF(W79=Llistes!$K$3,Llistes!$L$3,IF(W79=Llistes!$K$4,Llistes!$L$4,IF(W79=Llistes!$K$5,Llistes!$L$5,IF(W79=Llistes!$K$6,Llistes!$L$6,IF(W79=Llistes!$K$7,Llistes!$L$7,"")))))) -> Sergi Roura | Y79: X | Z79: X | AA79: X | AB79: X
A80: CULTURA | F80: 05.2.1 | G80: Minimitzar la brutícia, deixalles, vandalisme i males praxis dins l'ENP | H80: Reforç de la vigilància en els punts on s'acumulen més deixalles. | I80: S'ha realitzat algun tipus de vigilància | K80: Sí | L80: Minimitzar la brutícia, deixalles, vandalisme i males praxis dins l'ENP | M80: Comú | N80: Obligatori | Q80: MITJANA | U80: 0.015 | V80: =PLA!U83*Llistes!$L$11*Llistes!$L$12 -> 2 | W80: Direcció | X80: =IF(W80=Llistes!$K$2,Llistes!$L$2,IF(W80=Llistes!$K$3,Llistes!$L$3,IF(W80=Llistes!$K$4,Llistes!$L$4,IF(W80=Llistes!$K$5,Llistes!$L$5,IF(W80=Llistes!$K$6,Llistes!$L$6,IF(W80=Llistes!$K$7,Llistes!$L$7,"")))))) -> Gerard Carrion | Y80: X | Z80: X | AA80: X | AB80: X
A81: CULTURA | F81: 05.2.1 | G81: =L81 -> Minimitzar la brutícia, deixalles, vandalisme i males praxis dins l'ENP | H81: Reforç de la senyalització, si es considera oportú. | I81: S'ha instal·lat cartelleria a les zones conflictives | K81: Sí | L81: Minimitzar la brutícia, deixalles, vandalisme i males praxis dins l'ENP | M81: Comú | N81: Obligatori | Q81: MITJANA | U81: 0.015 | V81: =PLA!U84*Llistes!$L$11*Llistes!$L$12 -> 2 | W81: Manteniment | X81: =IF(W81=Llistes!$K$2,Llistes!$L$2,IF(W81=Llistes!$K$3,Llistes!$L$3,IF(W81=Llistes!$K$4,Llistes!$L$4,IF(W81=Llistes!$K$5,Llistes!$L$5,IF(W81=Llistes!$K$6,Llistes!$L$6,IF(W81=Llistes!$K$7,Llistes!$L$7,"")))))) -> Sergi Roura | Y81: X | Z81: X | AA81: X | AB81: X
A82: CULTURA | D82: 05.3 | E82: Protegir la qualitat acústica i lumínica de l'ENP | F82: 05.3.1 | G82: Promoure la declaració de zones d'especial protecció de la qualitat acústica, d'acord amb els ajuntaments | H82: Coordinació per a la declaració de l'ENP com a ZEPQA, d'acord amb els ajuntaments. | I82: S'ha iniciat la tramitació d'alguna ZEPQA | K82: Sí | L82: Promoure la certificació de zones d'especial protecció de la qualitat acústica | M82: Específic | N82: Obligatori | O82: Els ajuntaments hi han d'estar interessats (ho han d'incloure al seu mapa de capacitat acústica en 6 mesos), i la declaració és de la DGQA | Q82: MITJANA | S82: ESNATURA | U82: 0.015 | V82: =PLA!U85*Llistes!$L$11*Llistes!$L$12 -> 2 | W82: Direcció | X82: =IF(W82=Llistes!$K$2,Llistes!$L$2,IF(W82=Llistes!$K$3,Llistes!$L$3,IF(W82=Llistes!$K$4,Llistes!$L$4,IF(W82=Llistes!$K$5,Llistes!$L$5,IF(W82=Llistes!$K$6,Llistes!$L$6,IF(W82=Llistes!$K$7,Llistes!$L$7,"")))))) -> Gerard Carrion | AB82: X
A83: CULTURA | F83: 05.3.2 | L83: Promoure la certificació de zones d'especial protecció de la qualitat acústica | M83: Específic | N83: Optatiu
A84: CONEIXEMENT | B84: 6 | C84: MILLORAR EL CONEIXEMENT DE L'ENTORN, del patrimoni natural, cultural i social. | D84: 06.1 | E84: Identificar els objectes de gestió prioritària de l'ENP en el marc dels objectius de govern | F84: 06.1.1 | G84: =L84 -> Identificar i prioritzar els elements clau i d'interès per a la gestió de la biodiversitat i geodiversitat de Catalunya que es troben dins l'ENP (espècies amenaçades, espècies exòtiques invasores,.. ) | H84: Participació en la definició dels objectes de conservació clau (hàbitats, espècies, processos i elements d’interès geològic) comuns a nivell de Xarxa d'ENP o clúster territorial | I84: Nombre de reunions en què s'ha participat en la definició dels objectes de conservació. | J84: 2 | K84: 5 | L84: Identificar i prioritzar els elements clau i d'interès per a la gestió de la biodiversitat i geodiversitat de Catalunya que es troben dins l'ENP (espècies amenaçades, espècies exòtiques invasores,.. ) | M84: Comú | N84: Obligatori | Q84: MÀXIMA | R84: *Participació en la definició dels objectes de conservació clau (hàbitats, espècies, processos i elements d’interès geològic) comuns a nivell de Xarxa d'ENP o clúster territorial | S84: Directriva Habitats Carta emplaçament ESNATURA Catàlegs | T84: UIC/SFF/SPEN: Definir criteris d'identificació d'elements interès. UIC/SFF/SPEN: Definició dels objectes de conservació clau comuns a nivell de Xarxa d'ENP o clúster territorial | U84: 0.015 | V84: =PLA!U87*Llistes!$L$11*Llistes!$L$12 -> 2 | W84: Patrimoni natural | X84: =IF(W84=Llistes!$K$2,Llistes!$L$2,IF(W84=Llistes!$K$3,Llistes!$L$3,IF(W84=Llistes!$K$4,Llistes!$L$4,IF(W84=Llistes!$K$5,Llistes!$L$5,IF(W84=Llistes!$K$6,Llistes!$L$6,IF(W84=Llistes!$K$7,Llistes!$L$7,"")))))) -> Pau Federico | Y84: X | Z84: X | AA84: X | AB84: X
A85: CONEIXEMENT | F85: 06.1.2 | G85: =L85 -> Definir espais fràgils i zones d'especial atenció | H85: S'ha participat en la realització o actualització de l'inventari de ZH, espais interès geològic, etc. | I85: Nombre de reunions en què s'ha participat per l'actualització de l'inventari de ZH, espais d'interès geològic | J85: 2 | K85: 5 | L85: Definir espais fràgils i zones d'especial atenció | M85: Comú | N85: Obligatori | Q85: MÀXIMA | R85: *Generació d'informació per a l'inventari i cartografia d'espais fràgils *Realització o actualització de l'inventari de ZH, espais interès geològic, etc. | T85: SPEN: Inventari i cartografia d'espais fràgils i zones d'especial atenció | U85: 0.015 | V85: =PLA!U88*Llistes!$L$11*Llistes!$L$12 -> 2 | W85: Direcció | X85: =IF(W85=Llistes!$K$2,Llistes!$L$2,IF(W85=Llistes!$K$3,Llistes!$L$3,IF(W85=Llistes!$K$4,Llistes!$L$4,IF(W85=Llistes!$K$5,Llistes!$L$5,IF(W85=Llistes!$K$6,Llistes!$L$6,IF(W85=Llistes!$K$7,Llistes!$L$7,"")))))) -> Gerard Carrion | Y85: X | Z85: X | AA85: X | AB85: X
A86: CONEIXEMENT | F86: 06.1.2 | G86: =L86 -> Definir espais fràgils i zones d'especial atenció | H86: Redacció del treball tècnic sobre els hàbitats presents a les basses | I86: S'ha redactat el treball | K86: Sí | L86: Definir espais fràgils i zones d'especial atenció | M86: Comú | N86: Obligatori | Q86: MÀXIMA | R86: *Generació d'informació per a l'inventari i cartografia d'espais fràgils *Realització o actualització de l'inventari de ZH, espais interès geològic, etc. | U86: 0.15 | V86: =PLA!U89*Llistes!$L$11*Llistes!$L$12 -> 20 | W86: XN2000 | X86: =IF(W86=Llistes!$K$2,Llistes!$L$2,IF(W86=Llistes!$K$3,Llistes!$L$3,IF(W86=Llistes!$K$4,Llistes!$L$4,IF(W86=Llistes!$K$5,Llistes!$L$5,IF(W86=Llistes!$K$6,Llistes!$L$6,IF(W86=Llistes!$K$7,Llistes!$L$7,"")))))) -> Montse Pascual | Y86: X
A87: CONEIXEMENT | D87: 06.2 | E87: Conèixer l'estat de conservació i la seva tendència dels hàbitats, les espècies els elements de la gea i els processos ecològics com a eina per avaluar i optimitzar la gestió | F87: 06.2.1 | G87: =L87 -> Participar en l'elaboració de la cartografia que elabora la UIC | H87: Participació en la programació de la realització de la cartografia d'hàbitats en el contracte pluriennal que existeix amb GeoVeg-UB | I87: Nombre de reunions en què s'ha participat en la programació de la cartografia d'hàbitats | J87: 1 | K87: 3 | L87: Participar en l'elaboració de la cartografia que elabora la UIC | M87: Comú | N87: Obligatori | Q87: ALTA | R87: *Participació en la programació de la realització de la cartografia d'hàbitats en el contracte plurienal que existeix amb GeoVeg-UB | S87: ESNATURA | T87: UIC: Coordinar i contractar l'elaboració de la cartografia | U87: 0.015 | V87: =PLA!U90*Llistes!$L$11*Llistes!$L$12 -> 2 | W87: Direcció | X87: =IF(W87=Llistes!$K$2,Llistes!$L$2,IF(W87=Llistes!$K$3,Llistes!$L$3,IF(W87=Llistes!$K$4,Llistes!$L$4,IF(W87=Llistes!$K$5,Llistes!$L$5,IF(W87=Llistes!$K$6,Llistes!$L$6,IF(W87=Llistes!$K$7,Llistes!$L$7,"")))))) -> Gerard Carrion | Y87: X | Z87: X | AA87: X | AB87: X
A88: CONEIXEMENT | F88: 06.2.2 | G88: =L88 -> Conèixer i estudiar els processos naturals propis de l’espai, la seva funcionalitat, i ecologia en referència als ecosistemes | H88: Foment i coordinació dels estudis d'ecologia del foc, el règim hidrològic, la pol·linització, la tipificació i funcionament de les cadenes tròfiques pròpies de l’espai, la dinàmica geomorfològica i morfodinàmica de les roques, etc. | I88: Nombre de reunions per fomentar i coordinar estudis diversos relacionats amb els processos naturals de l'ENP | J88: 1 | K88: 3 | L88: Conèixer i estudiar els processos naturals propis de l’espai, la seva funcionalitat, i ecologia en referència als ecosistemes | M88: Comú | N88: Obligatori | Q88: MITJANA | R88: *Foment i coordinació dels estudis d'ecologia del foc, el règim hidrològic, la pol·linització, la tipificació i funcionament de les cadenes tròfiques pròpies de l’espai, la dinàmica de la neu i les allaus, dinàmica litoral, dinàmica geomorfològica i morfodinàmica de les roques, etc. *Millora del coneixement de la geoconservació (escala més detallada de 1:50.000) *Implementació del protocol de fluxos d'informació i coneixement de biodiversitat | U88: 0.015 | V88: =PLA!U91*Llistes!$L$11*Llistes!$L$12 -> 2 | W88: Direcció | X88: =IF(W88=Llistes!$K$2,Llistes!$L$2,IF(W88=Llistes!$K$3,Llistes!$L$3,IF(W88=Llistes!$K$4,Llistes!$L$4,IF(W88=Llistes!$K$5,Llistes!$L$5,IF(W88=Llistes!$K$6,Llistes!$L$6,IF(W88=Llistes!$K$7,Llistes!$L$7,"")))))) -> Gerard Carrion | Y88: X | Z88: X | AA88: X | AB88: X
A89: CONEIXEMENT | F89: 06.2.2 | G89: =L89 -> Conèixer i estudiar els processos naturals propis de l’espai, la seva funcionalitat, i ecologia en referència als ecosistemes | H89: Millora del coneixement de la geoconservació (escala més detallada de 1:50.000) | I89: Nombre d'estudis sobre geoconservació | J89: 0 | K89: 1 | L89: Conèixer i estudiar els processos naturals propis de l’espai, la seva funcionalitat, i ecologia en referència als ecosistemes | M89: Comú | N89: Obligatori | Q89: MITJANA | R89: *Foment i coordinació dels estudis d'ecologia del foc, el règim hidrològic, la pol·linització, la tipificació i funcionament de les cadenes tròfiques pròpies de l’espai, la dinàmica de la neu i les allaus, dinàmica litoral, dinàmica geomorfològica i morfodinàmica de les roques, etc. *Millora del coneixement de la geoconservació (escala més detallada de 1:50.000) *Implementació del protocol de fluxos d'informació i coneixement de biodiversitat | U89: 0.015 | V89: =PLA!U92*Llistes!$L$11*Llistes!$L$12 -> 2 | W89: Direcció | X89: =IF(W89=Llistes!$K$2,Llistes!$L$2,IF(W89=Llistes!$K$3,Llistes!$L$3,IF(W89=Llistes!$K$4,Llistes!$L$4,IF(W89=Llistes!$K$5,Llistes!$L$5,IF(W89=Llistes!$K$6,Llistes!$L$6,IF(W89=Llistes!$K$7,Llistes!$L$7,"")))))) -> Gerard Carrion | Y89: X | Z89: X | AA89: X | AB89: X
A90: CONEIXEMENT | F90: 06.2.2 | G90: =L90 -> Conèixer i estudiar els processos naturals propis de l’espai, la seva funcionalitat, i ecologia en referència als ecosistemes | H90: Implementació del protocol de fluxos d'informació i coneixement de biodiversitat | I90: S'han implementat fluxos d'informació i coneixement de la biodiversitat | K90: Sí | L90: Conèixer i estudiar els processos naturals propis de l’espai, la seva funcionalitat, i ecologia en referència als ecosistemes | M90: Comú | N90: Obligatori | Q90: MITJANA | R90: *Foment i coordinació dels estudis d'ecologia del foc, el règim hidrològic, la pol·linització, la tipificació i funcionament de les cadenes tròfiques pròpies de l’espai, la dinàmica de la neu i les allaus, dinàmica litoral, dinàmica geomorfològica i morfodinàmica de les roques, etc. *Millora del coneixement de la geoconservació (escala més detallada de 1:50.000) *Implementació del protocol de fluxos d'informació i coneixement de biodiversitat | U90: 0.015 | V90: =PLA!U93*Llistes!$L$11*Llistes!$L$12 -> 2 | W90: Patrimoni natural | X90: =IF(W90=Llistes!$K$2,Llistes!$L$2,IF(W90=Llistes!$K$3,Llistes!$L$3,IF(W90=Llistes!$K$4,Llistes!$L$4,IF(W90=Llistes!$K$5,Llistes!$L$5,IF(W90=Llistes!$K$6,Llistes!$L$6,IF(W90=Llistes!$K$7,Llistes!$L$7,"")))))) -> Pau Federico | Y90: X | Z90: X | AA90: X | AB90: X
A91: CONEIXEMENT | F91: 06.2.2 | G91: =L91 -> Conèixer i estudiar els processos naturals propis de l’espai, la seva funcionalitat, i ecologia en referència als ecosistemes | H91: Foment de l'estudi de l'afectació de determinats processos naturals o activitats antròpiques en l’ENP (amenaces i impacte ambiental). | I91: Nombre d'estudis sobre processos naturals o activitats antròpiques que afecten l'ENP. | J91: 1 | K91: 2 | L91: Conèixer i estudiar els processos naturals propis de l’espai, la seva funcionalitat, i ecologia en referència als ecosistemes | M91: Comú | N91: Obligatori | Q91: MÀXIMA | R91: *Foment de l'estudi de l'afectació de determinats processos naturals o activitats antròpiques (contaminació, fragmentació d'hàbitats, atropellaments, noves arts de pesca o pràctiques agrícoles de muntanya, etc.) en l’ENP (amenaces i impacte ambiental). *Avaluació de l'impacte del canvi climàtic en l'ENP i la seva capacitat d'adaptació i resiliència. *Avaluació dels resultats de les estratègies de gestió aplicades en l'ENP *Col.laboració amb l?Observatori per aportar els coneixements generats a l'ENP. | U91: 0.015 | V91: =PLA!U94*Llistes!$L$11*Llistes!$L$12 -> 2 | W91: Patrimoni natural | X91: =IF(W91=Llistes!$K$2,Llistes!$L$2,IF(W91=Llistes!$K$3,Llistes!$L$3,IF(W91=Llistes!$K$4,Llistes!$L$4,IF(W91=Llistes!$K$5,Llistes!$L$5,IF(W91=Llistes!$K$6,Llistes!$L$6,IF(W91=Llistes!$K$7,Llistes!$L$7,"")))))) -> Pau Federico | Y91: X | Z91: X | AA91: X | AB91: X
