Workbook

Sheet ESTRATÈGIA
C3: ESQUEMA CONCEPTUAL PER A LA ELABORACIÓ DEL PLA ESTRATÈGIC EN EL MARC
C4: DELS ESTÀNDARDS OBERTS PER A LA GESTIÓ ADAPTATIVA A CATALUNYA

Sheet INSTRUCCIONS
A1: PESTANYA DE PRIORITZACIÓ
A2: Llistat elements: | B2: Tasca 1: Revisar el llistat d'elements prioritzats per tal d'avaluar si cal afegir-ne algun o treure'n algun. A la columna comentaris cal argumentar, breument, el perquè de la decisió.
A4: Llistat amenaces: | B4: Tasca 2: A partir de la taxonomia d'amenaces que es troba a la pestanya final, cal omplir les tres columnes (E, F i G) amb les tres principals amenaces per a la conservació de l'element. S'afegeixi una darrera columna per si hi ha amenaces que no es troben incloses a la taxonomia.
A6: PESTANYA DEL PLA
A7: Explicacions:
B8: 7 Eixos temàtics
B9: Els objectius generals estan directament associats als objectius generals dels Plans de Protecció del medi naatural i del paisatge. NO ES PODEN RETOCAR
B10: Objectius estratègics: definits en un grup de treball intern de serveis Centrals i dels Parcs durant l'any 2023. NO ES PODEN RETOCAR
B11: Objectius operacionals: definits en un grup de treball intern de serveis Centrals i dels Parcs durant l'any 2023
A14: Tasques a realitzar:
A15: Objectius operacionals: | B15: El llistat d'objectius operacionals té una columna al costa (columna I) on s'indica si l'objectiu és obligatori de mantenir al Pla estratègic o no.
B16: Tasca 1: Columna I. Revisar els que es posa com a obligatoris per veure si són realment aplicables a l'espai o no.
B17: Tasca 2: Columna I. Revisar els que posa "Opcional" per identificar els que són aplicables o no a l'espai. O, també, determinar si algun d'ells seria aplicable o es pot concretar millor el redactat de l'objectiu.
B18: Tasca 3: Columna J. En ambdós casos, cal posar a la columna J, el redactat final de l'objectiu concretat a l'espai. En el cas de que l'objectiu s'elimina, posar "NA". Ara es reprodueix el redactat dels objectius operacionals derivats del grup de treball esmentat
B19: Tasca 4: Columna K. Per tots els casos en que hi ha modificació respecte al redactat original de l'objectiu operatiu -i, també, en el cas que es consideri que s'ha d'eliminar-, a la columna K cal redactar molt breument el motiu pel qual es prèn la decisió.
B20: Tasca 5: Columna L. Incloure un Si/No avaluant si l'objectiu operatiu podria tenir mesures a incorporar a la programació d'actuacions de l'espai (Si) o, per altra banda, el seu assoliment depèn d'altres òrgans, com l'ACA o altres serveis dins la DGPAMN (No).
B21: Tasca 6: Columna M. Definir la prioritat que hauria de tenir l'assoliment de l'objectiu (màxima, si cal assolir en els propers 4 anys, o altrament alta, mitja o baixa). També hi ha l'opció de prioritat a assolir a més llarg termini.
A22: Propostes genèriques d'accions: | B22: Tasca 7: Columna N. En aquest columna cal introduir les accions, de manera genèrica, que caldria aplicar a l'espai per tal d'assolir l'objectiu operatiu. No es tracta d'un llistat d'accions concretes si no, més aviat, accions generals que acabarien concretant-se en la programació anual. PER A INICIAR AMB LA TAULA US PODEU BASAR MOLT EN LA FEINA JA FETA DE PRIORITZACIÓ DE MESURES PEL MAP
B23: En el cas dels objectius operatius que s'ha considerat que no són aplicables a l'espai, cal avaluar si podrien tenir alguna acció que sí tindria sentit d'incloure al Pla estratègic tot i que l'objectiu de manera global no hi ´seria d'aplicació.
A24: Indicadors: | B24: Tasca 8: Columna Q. Posar un indicar SMART per avaluar el compliment de la mesura proposada a la columna N
A25: Fites a assolir en 4 anys: | B25: Tasca 9: Posar un valor de l'indicador a asolir: valor mínim necessari (columna R) o valor desitjable (columna S).
A26: Hores de dedicació: | B26: Tasca 10: Columna T. Realitzar una aproximació el més acurada que es pugui de les hores del personal de gestió de l'espai que cal destinar per a la realització de l'acció.
A27: Àrea responsable: | B27: Tasca 11: Columna U. Indicar quina àrea de l'equip de gestió és responsable de coordinar l'execució de l'acció.
A28: Persona responsable: | B28: Tasca 12: Columna V. Indicar quina persona dins l'àrea seria l'encarregada.
A30: PESTANYA DEL VINCLE
A31: Definir vincle amenaça vs. Obj. Operatiu | B31: Tasca 1: Establir / Revisar el vincle entre les amenaces identificades a la pestanya de priorització i els objectius operatius definits a la columna J de la pestanya Pla. La columna B conté el llistat dels objectius operatius tal i com quedaran definits després de la vostra revisió.
B32: Tasca 2: En cas que es pugui, definir l'amenaça / factor / causa concret a la que atén l'objectiu definit al Pla. Poden ser més d'una.
B33: És important que es visualitzi a quina amenaça es dirigeix l'objectiu operatiu que es proposa al Pla, tot i que, no sempre hi ha d'haver un vincle clar. Pot haver algun objectiu sense amenaça vinculada.

Sheet PRIORITZACIÓ
A2: Llistats corresponent a l'espai de Natura 2000 ES5120001 "Alta Garrotxa-Massís de les Salines"
A3: LLISTAT D'ELEMENTS PRESENT A L'ESPAI | I3: AMENACES PER A CADA ELEMENT
A4: Hàbitats d'interès comunitari | B4: PP 6.2 i 6.3 | C4: PP A8 | D4: MAP | E4: 25% IdR | F4: Puntuació IdR | G4: PRIORITARI PE | H4: Comentaris en cas de canvi en la priorització | I4: Amenaça 1 segons taxonomia | J4: Amenaça 2 segons taxonomia | K4: Amenaça 3 segons taxonomia | L4: Altres amenaces | N4: Nota: La priorització d'elements actual inclou els Elements Clau que es van determinar en l'instrument de gestió aprovat amb l'Acord de Govern 150/2014 (Annex 6)
A5: 3130 - Aigües estagnants oligotròfiques o mesotròfiques amb vegetació de Littorelletea uniflorae i/o Isoëto-nanojuncetea | C5: Si | D5: Si | G5: Sí | I5: Desaparició d'activitats tradicionals | J5: Gestió de l'aigua | K5: Ramaderia | N5: Aquest Acord era per les Zones Especials de Conservació, no per les ZEPA i, per tant, no es va fer l'exercici de priorització de les aus.
A6: 3140 - Aigües oligomesotròfiques calcàries amb vegetació bèntica de Chara spp. | C6: Si | D6: Si | G6: Sí | I6: Desaparició d'activitats tradicionals | J6: Gestió de l'aigua | K6: Ramaderia | N6: També inclou el primer quartil de l'exercici de la UIC per prioritzar els elements present a cada espai de Natura 2000, és a dir, el 25% dels
A7: 3240 - Rius de tipus alpí amb bosquines de muntanya | B7: Si | C7: Si | D7: Si | G7: Sí | I7: Impactes del canvi climàtic relatius a l'alteració del règim de precipitació i sequera | J7: Molèsties per activitats recreatives | K7: Gestió de l'aigua | N7: elements amb major índex de rellevància a l'espai. Veure document metodològic aquí:
A8: 3250 - Rius mediterranis amb vegetació del Glaucion flavi | C8: Si | D8: Si | G8: Sí | I8: Impactes del canvi climàtic relatius a l'alteració del règim de precipitació i sequera | J8: Molèsties per activitats recreatives | K8: Gestió de l'aigua
A9: 3260 - Rius de terra baixa i de la muntanya mitjana amb vegetació submersa o parcialment flotant (Ranunculion fluitantis i Callitricho-Batrachion) | C9: Si | D9: Si | G9: Sí | I9: Impactes del canvi climàtic relatius a l'alteració del règim de precipitació i sequera | J9: Molèsties per activitats recreatives | K9: Gestió de l'aigua | N9: https://gencat.sharepoint.com/sites/Informaciiconeixementpatrimoninatural2/Documents%20compartits/Forms/AllItems.aspx?csf=1&web=1&e=3x4ZkK&ovuser=3b9427dc%2Dd30e%2D43bc%2D8c06%2Dff7253676fec%2Cjordiparpal%40gencat%2Ecat&OR=Teams%2DHL&CT=1713942253212&clic
A10: 3270 - Rius amb vores llotoses colonitzades per herbassars nitròfils del Chenopodion rubri (p.p.) i del Bidention (p.p.) | C10: Si | D10: Si | G10: Sí | I10: Impactes del canvi climàtic relatius a l'alteració del règim de precipitació i sequera | J10: Molèsties per activitats recreatives | K10: Gestió de l'aigua
A11: 4030 - Landes atlàntiques i subatlàntiques seques | B11: Si | C11: Si | D11: Si | E11: Si | G11: Sí | I11: Desaparició d'activitats tradicionals | J11: Espècies invasores | K11: Impactes del canvi climàtic relatius a l'alteració del règim de precipitació i sequera
A12: 4090 - Matollars xerocàntics endèmics oromediterranis | C12: Si | D12: Si | E12: Si | G12: Dubtós | H12: Molt poc representatiu per superfície
A13: 5110 - Boixedes xerotermòfiles permanents, dels vessants rocosos | C13: Si | D13: Si | G13: Sí | I13: Desaparició d'activitats tradicionals | J13: Espècies invasores | K13: Plagues i patògens
A14: 5130 - Formacions de Juniperus communis colonitzadores de landes o de pastures calcícoles | C14: Si | D14: Si | E14: Si | G14: No | H14: Espècie colonitzadora d'espais oberts molt abundant
A15: 5210 - Màquies i garrigues amb Juniperus spp. arborescents, no dunars | C15: Si | D15: Si | G15: No | H15: Espècie colonitzadora d'espais oberts molt abundant
A16: 6110p - Prats calcàris o basòfils d'Alysso-Sedion albi (*) | C16: Si | D16: Si | G16: Sí | I16: Desaparició d'activitats tradicionals | J16: Espècies invasores | K16: Impactes del canvi climàtic relatius a l'alteració del règim de precipitació i sequera
A17: 6210 - Prats -i fàcies emmatades- medioeuropeus, seminaturals, sobre substrat calcari (Festuco-Brometea) | B17: Si | C17: Si | D17: Si | E17: Si | G17: Sí | I17: Desaparició d'activitats tradicionals | J17: Espècies invasores | K17: Impactes del canvi climàtic relatius a l'alteració del règim de precipitació i sequera
A18: 6410 - Herbassars de Molinia coerulea en sòls calcaris torbosos o argil·lollimosos (Molinion caeruleae) | C18: Si | D18: Si | G18: Sí | I18: Desaparició d'activitats tradicionals | J18: Espècies invasores | K18: Impactes del canvi climàtic relatius a l'alteració del règim de precipitació i sequera
A19: 6420 - Jonqueres i herbassars graminoides humits, mediterranis, del Molinio-Holoschoenion | C19: Si | D19: Si | G19: Sí | I19: Gestió de l'aigua | J19: Desaparició d'activitats tradicionals
A20: 6430 - Herbassars higròfils, tant de marges i vorades com de l'alta muntanya | C20: Si | D20: Si | G20: No | H20: Fitxa ZEC posa 0 ha. No surt a la memòria hàbitats de la AG | I20: Desaparició d'activitats tradicionals | J20: Gestió de l'aigua | K20: Impactes del canvi climàtic relatius a l'alteració del règim de precipitació i sequera
A21: 6510 - Prats de dall de terra baixa i de la muntanya mitjana (Arrhenatherion) | C21: Si | D21: Si | E21: Si | G21: No | H21: Index de rellevància molt elevat però no hi ha a l'espai | I21: Desaparició d'activitats tradicionals | J21: Ramaderia
A22: 7220p - Fonts petrificants amb formació de travertí (Cratoneurion commutati) | C22: Si | D22: Si | G22: Sí | I22: Gestió de l'aigua | J22: Àrees recretives i turístiques | K22: Impactes del canvi climàtic relatius a l'alteració del règim de precipitació i sequera
A23: 8130 - Tarteres de l'Europa meridional amb vegetació poc o molt termòfila | B23: Si | C23: Si | D23: Si | E23: Si | G23: Dubtós | H23: element clau però sense accions associades | I23: Àrees recretives i turístiques | J23: Espècies desestabilitzades
A24: 8210 - Costers rocosos calcaris amb vegetació rupícola | C24: Si | D24: Si | G24: Sí | I24: Molèsties per activitats recreatives
A25: 8220 - Costers rocosos silicis amb vegetació rupícola | C25: Si | D25: Si | G25: No | H25: No és representatiu a l'espai
A26: 8310 - Coves no explotades pel turisme | C26: Si | D26: Si | E26: Si | G26: Sí | I26: Molèsties per activitats recreatives
A27: 9120 - Fagedes acidòfiles | B27: Si | C27: Si | D27: Si | G27: Sí | I27: Treballs forestals | J27: Impactes del canvi climàtic relatius a l'alteració del règim de precipitació i sequera | K27: Impactes del canvi climàtic relatius a l'alteració del règim de temperatures
A28: 9130 - Fagedes neutròfiles | B28: Si | C28: Si | D28: Si | G28: Sí | I28: Treballs forestals | J28: Impactes del canvi climàtic relatius a l'alteració del règim de precipitació i sequera | K28: Impactes del canvi climàtic relatius a l'alteració del règim de temperatures
A29: 9150 - Fagedes calcícoles xerotermòfiles | B29: Si | C29: Si | D29: Si | E29: Si | G29: Sí | I29: Treballs forestals | J29: Impactes del canvi climàtic relatius a l'alteració del règim de precipitació i sequera | K29: Impactes del canvi climàtic relatius a l'alteració del règim de temperatures
A30: 9160 - Rouredes de roure pènol i boscos mixtos del Carpinion betuli | B30: Si | C30: Si | D30: Si | E30: Si | G30: Sí | I30: Treballs forestals | J30: Impactes del canvi climàtic relatius a l'alteració del règim de precipitació i sequera | K30: Impactes del canvi climàtic relatius a l'alteració del règim de temperatures
A31: 9180p - Boscos de vessants rostos, tarteres o barrancs, del Tilio-Acerion | D31: Si | E31: Si | G31: No | H31: NO present a l'espai | I31: Treballs forestals | J31: Impactes del canvi climàtic relatius a l'alteració del règim de precipitació i sequera | K31: Impactes del canvi climàtic relatius a l'alteració del règim de temperatures
A32: 91E0p - Vernedes i altres boscos de ribera afins (Alno-Padion) | B32: Si | C32: Si | D32: Si | E32: Si | G32: Sí | I32: Gestió de l'aigua | J32: Espècies invasores | K32: Àrees recretives i turístiques
A33: 9240 - Rouredes ibèriques de roure valencià (Quercus faginea) i roure africà (Quercus canariensis) | B33: Si | C33: Si | D33: Si | E33: Si | G33: Sí | I33: Treballs forestals | J33: Impactes del canvi climàtic relatius a l'alteració del règim de precipitació i sequera | K33: Impactes del canvi climàtic relatius a l'alteració del règim de temperatures
A34: 9260 - Castanyedes | B34: Si | C34: Si | D34: Si | E34: Si | G34: No | H34: Poc representatiu a l'espai | I34: Treballs forestals | J34: Impactes del canvi climàtic relatius a l'alteració del règim de precipitació i sequera | K34: Impactes del canvi climàtic relatius a l'alteració del règim de temperatures
A35: 9330 - Suredes | C35: Si | D35: Si | E35: Si | G35: No | H35: NO present a l'espai
A36: 9340 - Alzinars i carrascars | B36: Si | C36: Si | D36: Si | E36: Si | G36: Sí | I36: Desaparició d'activitats tradicionals | J36: Impactes del canvi climàtic relatius a l'alteració del règim de precipitació i sequera | K36: Impactes del canvi climàtic relatius a l'alteració del règim de temperatures
A37: 9530p - Pinedes submediterrànies de pinassa (Pinus nigra subsp. salzmannii) | B37: Si | C37: Si | D37: Si | E37: Si | G37: No | H37: Poca superfície a l'espai | I37: Treballs forestals | J37: Impactes del canvi climàtic relatius a l'alteració del règim de precipitació i sequera | K37: Impactes del canvi climàtic relatius a l'alteració del règim de temperatures
A38: 9540 - Pinedes mediterrànies | C38: Si | D38: Si | E38: Si | G38: Dubtós | H38: rellevant per gestió risc d'incendis | I38: Treballs forestals | J38: Impactes del canvi climàtic relatius a l'alteració del règim de precipitació i sequera | K38: Impactes del canvi climàtic relatius a l'alteració del règim de temperatures
A39: 9580p - Boscs mediterranis de Taxus baccata (*) | B39: Si | C39: Si | D39: Si | E39: Si | G39: Sí | I39: Treballs forestals | J39: Impactes del canvi climàtic relatius a l'alteració del règim de precipitació i sequera | K39: Impactes del canvi climàtic relatius a l'alteració del règim de temperatures
A40: Espècies presents a l'espai | B40: PP 6.2 i 6.3 | C40: PP A8 | D40: MAP | E40: 25% IdR | F40: Puntuació IdR | G40: PRIORITARI PE | H40: Comentaris en cas de canvi en la priorització | I40: Gestió de l'aigua | J40: Espècies invasores | K40: Àrees recretives i turístiques | L40: Altres amenaces
A41: Abida gittenbergeri | B41: Si | G41: Sí | I41: Treballs forestals | J41: Impactes del canvi climàtic relatius a l'alteració del règim de precipitació i sequera
A42: Abida secale affinis | B42: Si | G42: Sí | I42: Treballs forestals | J42: Impactes del canvi climàtic relatius a l'alteració del règim de precipitació i sequera
A43: Acanthocreagris granulata | B43: Si | G43: Sí | I43: Molèsties per activitats recreatives
A44: Accipiter gentilis gentilis | D44: Si | G44: Dubtós | H44: Espècie forestal no amenaçada
A45: Actitis hypoleucos | D45: Si | G45: No | H45: no present a l'Alta Garrotxa (deu ser a Salines?)
A46: Alcedo atthis | D46: Si | E46: Si | F46: 1.667 | G46: Dubtós | H46: Poc representatiu perquè hi ha pocs rius de cabal permanent, però surt a Directiva aus | I46: Molèsties per activitats recreatives | J46: Impactes del canvi climàtic relatius a l'alteració del règim de precipitació i sequera | K46: Polució aquàtica
A47: Allium pyrenaicum | B47: Si | G47: Sí | I47: Ramaderia
A48: Alytes obstetricans | D48: Si | G48: Sí | I48: Impactes del canvi climàtic relatius a l'alteració del règim de precipitació i sequera | J48: Plagues i patògens
A49: Anas platyrhynchos | D49: Si | G49: No | H49: Molt abundant arreu i gens representatiu de l'espai
A50: Anthus campestris | D50: Si | G50: No | H50: No present a l'espai
A51: Aquila chrysaetos | D51: Si | G51: Sí | I51: Molèsties per activitats recreatives | J51: Desaparició d'activitats tradicionals | K51: Caça i recol·lecció d'animals
A52: Arvicola sapidus | B52: Si | G52: Sí | I52: Molèsties per activitats recreatives | J52: Espècies invasores | K52: Gestió de l'aigua
A53: Austropotamobius pallipes | B53: Si | C53: Si | D53: Si | E53: Si | G53: Sí | I53: Espècies invasores | J53: Caça i recol·lecció d'animals | K53: Impactes del canvi climàtic relatius a l'alteració del règim de precipitació i sequera
A54: Barbastella barbastellus | B54: Si | C54: Si | D54: Si | E54: Si | G54: Sí | I54: Treballs forestals | J54: Modificació del clima
A55: Barbus meridionalis | B55: Si | C55: Si | D55: Si | E55: Si | G55: Sí | I55: Impactes del canvi climàtic relatius a l'alteració del règim de precipitació i sequera | J55: Pesca i semblants | K55: Espècies invasores
A56: Belisarius xambeui | B56: Si | G56: Sí | I56: Molèsties per activitats recreatives
A57: Bofilliella subarcuata | B57: Si | G57: Sí | I57: Modificació del clima | J57: Impactes del canvi climàtic relatius a l'alteració del règim de precipitació i sequera | K57: Foc
A58: Bubo bubo | D58: Si | G58: Sí | I58: Molèsties per activitats recreatives | J58: Desaparició d'activitats tradicionals | K58: Plagues i patògens
A59: Buteo buteo | D59: Si | G59: No | H59: Poc representatiu de l'espai, està més associat a planes agrícoles
A60: Callimorpha quadripunctaria | B60: Si | C60: Si | G60: Sí | I60: Modificació del clima
A61: Calotriton asper | B61: Si | G61: Sí | I61: Impactes del canvi climàtic relatius a l'alteració del règim de precipitació i sequera | J61: Plagues i patògens | K61: Espècies invasores
A62: Canis lupus | D62: Si | G62: Dubtós | H62: No està establert com a reproductor
A63: Caprimulgus europaeus | D63: Si | G63: Dubtós | H63: No està amenaçat i no tenim dades
A64: Cerambyx cerdo | B64: Si | C64: Si | D64: Si | G64: Sí | I64: Modificació del clima | J64: Treballs forestals
A65: Certhia brachydactyla all others | D65: Si | G65: No | H65: Abundant
A66: Cinclus cinclus | B66: Si | D66: Si | E66: Si | F66: 1.944 | G66: Sí | I66: Molèsties per activitats recreatives | J66: Impactes del canvi climàtic relatius a l'alteració del règim de precipitació i sequera | K66: Polució aquàtica
A67: Circaetus gallicus | D67: Si | G67: Sí | I67: Molèsties per activitats recreatives
A68: Circus cyaneus | B68: Si | D68: Si | G68: No | H68: No present a l'Alta Garrotxa
A69: Coenagrion mercuriale | B69: Si | C69: Si | D69: Si | G69: Sí | I69: Polució aquàtica | J69: Desaparició d'activitats tradicionals
A70: Columba palumbus palumbus | D70: Si | G70: No | H70: Molt abundant
A71: Coronella austriaca | B71: Si | G71: Sí | I71: Modificació del clima | J71: Foc
A72: Coturnix coturnix | D72: Si | G72: Sí | I72: Caça i recol·lecció d'animals
A73: Dichoropetalum schottii | B73: Si | G73: Sí | I73: Ramaderia | J73: Impactes del canvi climàtic relatius a l'alteració del règim de precipitació i sequera
A74: Dryocopus martius | B74: Si | D74: Si | G74: Sí | I74: Molèsties per activitats recreatives | J74: Modificació del clima | K74: Treballs forestals
A75: Dryopteris remota | B75: Si | G75: Sí | I75: Ramaderia
A76: Emberiza martius | B76: Si | G76: No | H76: ERROR. Si es refereix al repicatalons Emberiza shoeniclus, no està present a l'Alta Garrotxa
A77: Eriogaster catax | B77: Si | C77: Si | D77: Si | E77: Si | G77: Sí | I77: No especificada
A78: Euphorbia duvalii | B78: Si | G78: Sí
A79: Euphydryas aurinia | B79: Si | C79: Si | D79: Si | G79: Sí | I79: Modificació del clima | J79: Desaparició d'activitats tradicionals
A80: Euplagia quadripunctaria | D80: Si | G80: Dubtós | H80: Espècie dublicada degut a canvi de gènere
A81: Falco peregrinus | D81: Si | G81: Sí | I81: Molèsties per activitats recreatives
A82: Falco subbuteo | D82: Si | G82: Sí | I82: Molèsties per activitats recreatives
A83: Falco tinnunculus | D83: Si | G83: Sí | I83: Molèsties per activitats recreatives
A84: Fringilla coelebs all others | D84: Si | G84: No | H84: Molt abundant
A85: Galerida cristata | D85: Si | G85: No | H85: Molt abundant
A86: Glandora oleifolia | B86: Si | G86: Sí | I86: Àrees recretives i turístiques | J86: Espècies invasores
A87: Graellsia isabellae | B87: Si | C87: Si | D87: Si | G87: Sí | I87: Caça i recol·lecció d'animals | J87: Modificació del clima
A88: Gypaetus barbatus | B88: Si | D88: Si | G88: Sí | I88: Molèsties per activitats recreatives | J88: Desaparició d'activitats tradicionals
A89: Gyps fulvus | D89: Si | G89: No | H89: Molt abundant
A90: Hieraaetus fasciatus | B90: Si | G90: Dubtós | H90: Cuabarrada no nidificant, només cites puntuals
A91: Hieraaetus pennatus | D91: Si | G91: Sí | I91: Desaparició d'activitats tradicionals | J91: Treballs forestals
A92: Hierophis viridiflavus | B92: Si | G92: Sí | I92: No especificada
A93: Islamia globulus = Neohoratia globulus globulus | B93: Si | G93: Sí | I93: Gestió de l'aigua
A94: Jynx torquilla | D94: Si | G94: No | H94: Abundant
A95: Lanius collurio | B95: Si | D95: Si | E95: Si | F95: 1.944 | G95: Sí | I95: Modificació del clima | J95: Desaparició d'activitats tradicionals
A96: Larus michahellis | D96: Si | G96: No | H96: No present
A97: Limax cinereoniger | B97: Si | G97: Sí | I97: Modificació del clima
A98: Lithobius allothyphlus | B98: Si | G98: Sí | I98: Molèsties per activitats recreatives
A99: Loxia curvirostra | D99: Si | G99: No | H99: Escàs
A100: Lucanus cervus | B100: Si | C100: Si | D100: Si | G100: Sí | I100: Caça i recol·lecció d'animals
A101: Lullula arborea | D101: Si | G101: Sí | I101: Desaparició d'activitats tradicionals
...

Sheet PLA
A1: MODEL DE PLA ESTRATÈGIC PELS ENP
B2: Espai natural protegit: | C2: Alta Garrotxa
W3: Fita a assolir en 4 anys | Y3: Calendarització interna | AD3: Gestió interna
A4: EIXOS | C4: Objectius generals (PP) | E4: Objectius estratègics | G4: OBJECTIUS operatius | H4: Comú / Específic | I4: Obligatori / Optatiu | J4: Marc de referència | K4: Resultats derivats | L4: Objectius operatius Alta Garrotxa | M4: Justificació del canvi o no inclusió d'un OP | N4: Objectiu aplicable amb accions que depenen de l'AG | O4: Objectiu aplicable amb accions que depenen de la Direcció General de PAMN | P4: Prioritat | Q4: Proposta d'accions | R4: Proposta concreta d'accions | S4: Mesures MAP Traslladar observacions en vermell al MAP de l'Alta Garrotxa | T4: Mesures PPAG | U4: Mesures d'altres plans | V4: Indicadors | W4: Valor mínim | X4: Valor objectiu (desitjable) | Y4: Executat/ en curs | Z4: 2026/27 | AA4: 2027/28 | AB4: 2028/29 | AC4: 2029/30 | AD4: Hores de dedicació | AE4: Àrea responsable | AF4: Persona responsable
A5: NATURA | B5: 1 | C5: CONSERVAR LA NATURA i restaurar els ecosistemes, els processos naturals i seminaturals, la biodiversitat i la geodiversitat associada. | D5: 01.1 | E5: Adequar i fer eficient la conservació dels elements objecte de gestió prioritària marcats per la DG a l'ENP | F5: 01.1.1 | G5: Implementar i executar plans de gestió específics per a hàbitats i espècies de conservació prioritària dins l'ENP | H5: Comú | I5: Obligatori | J5: MAP | K5: SFF: Elaboració de plans de gestió específics per a espècies de conservació prioritària i directrius de gestió d'hàbitats. SFF/SENP: Definir a nivell de cluster quins son els que es poden elaborar conjuntament. | L5: Implementar i executar plans i mesures de gestió específiques per a hàbitats i espècies de conservació prioritària dins l'ENP | M5: Canvi de redactat OP. Implementació d'accions no emmarcades en un Pla de gestió específic | N5: Sí | O5: Si | P5: ALTA | Q5: Implementació del PIRE i de millores en el maneig de les activitats agràries_CAG, FPC i DGPA Millora d'hàbitats i espècies de conservació prioritària (espais oberts, fluvials, basses, boscos, etc) d'acord el PPAG_CAG Disseny del pla de seguiment de la biodiversitat de l'Alta Garrotxa_CAG i DGPA Gestió de l'ús públic per protegir hàbitats i espècies de conservació prioritària d'acord amb PPAG i el PUP (escalada, bany, barrancs, etc)_CAG | R5: REVISAR EL MAP I DISTRIBUIR ACCIONS A LA RESTA DE PLA ESTRATÈGIC *Recuperació d'hàbitat6210 i espècies associades a espais oberts (ratpenats, papallones, aus, insectes pol·linitzadors (relacionar amb espècies concretes) *Cartografia i proposta gestió hàbitats fluvials 91E0p, 3250, 3260, 3270 amb perspectiva canvi climàtic *Millora de basses i punts d'aigua * Gestió ús públic gorgues (fonts petrificants 7221) (gestió barrancs i restauració hàbitat) * Seguiment de la regulació de l'escalada per afectació als costers rocosos 8210 i de l'imapcte sobre fauna i flora rupícoles * Seguiment de les comunicacions d'espeleologia per les coves no explotades pel turisme 8310 * Estudi fauna cavernícola i ratpenats 8310 (invertebrats) * Dissenyar Pla de Seguiment de la biodiversitat de l'ALta Garrotxa (identifcar grups de fauna i flora protegida) Cerambix cerdo, Cinclus cinclus, rèptils i tot el que estigui al llistat i no es fa cap seguiment concret, Distribució escarbats saproxilics, guatlla i becada, tortora i ungulats salvatges, escorxador , cotoliu, turó, mustela, gat salvatge * 9120, 9130, 9150, 9160, 9340, 9240 treballs forestals adaptació al canvi climàtic i lliure evolució tendència a la maduresa * Estudi preliminar presència i distribució gasteròpodes amenaçats (prioritat baixa) * Cartografia distribució amfibis * Seguiment amfibis (mig termini) * Seguiment rupícoles en zones escalada * Seguiment àguila daurada * Estudi rata d'aigua Arvicola sapidus (priorita baixa) * Cranc de riu ho fa la Gene (impuls) * Promoure recerca duc (rapis nocturns) * Gestió de la convivència amb el llop (impuls) * Seguiment SEGRE, SOCC, trencalòs * Seguiment flora amenaçada i accions de conservació (6 taxons) *Redacció del projecte executiu d’intervenció forestal per a la millora de l’hàbitat de Polygala vayredae *Seguiment de l'estat ecològic dels prats a l'Alta Garrotxa * Coordinació amb Caça per sp aus cinegetiques i ungulats * restauració bosc ribera * seguiment aufrany * Suport a la FPC en l'elaboració de plans de maneig per la gesitó de pastures i seguiment en les zones on s'han realitzat cremes prescrites (proiecte Foc i Biodiversitat i Projecte Forwards_CAG (en algun cas pot afectar especies i hàbitats interès comunitari. * Millora de la senyalització dels itineraris (zona del Comanegra) per evitar els impactes del senderisme dispers per accedir al cim i l'afectació al 6210. * Coordinació amb els cossos de seguretat i CAR en cas d'incidències sobre habitats forestals protegits (ex. teixedes)_CAG | S5: *Control sanitari de la població de cranc de riu. Ho fa la generalitat *Consolidació del programa de cria en captivitat del cranc de riu autòcton.Ho fa la generalitat *Actuacions de conservació de les zones conegudes de posta regular de les especies de peixos d'interès comunitari.Ho podem parlar amb en Quim Pou. El primer pas és identificar això com una part de l'estudi de seguiment de peixos. *Actuacions de millora d'hàbitat en boscos subalpins amb presència espècies amenaçades. No en tenim. Traslladar al MAP original *Actuacions de manteniment dels matollars d’arç blanc i aranyoner, principals plantes nutrícies d'Eriogaster catax. Es pot dir que ho fem quan fem espais oberts en deixar zona de més baixa intensitat i creant zones ecotons en el perímetre. INtegrar en els criteris d'EEOO aquestes espècies especificament. Integrar en el MAP original aquest aclariment. *Actuacions de manteniment de les masses de lligabosc (Lonicera sp) com a principal planta nutrícia d'Euphydryas aurinia.Es pot dir que ho fem quan fem espais oberts en deixar zona de més baixa intensitat i creant zones ecotons en el perímetre. INtegrar en els criteris d'EEOO aquestes espècies especificament. Integrar en el MAP original aquest aclariment. *Actuacions de manteniment de les masses de Pinus sylvestris i Pinus nigra en les principals àrees de distribució de Graellsia isabelae. Establiment de rodals amb gestió adaptativa pel manteniment dels processos ecològics. *Actuacions de millora de l'habitat de Lutra lutra. L'espècie està en expansió. No es prioritari en aquest Pla estratègic. *Actuacions de restauració de zones de cria d'Emys orbicularis i Mauremys leprosa.No aplica a AG *Actuacions per mantenir una estructura vegetal adequada en zones properes a l'entrada de coves/refugis amb presència de rats-penats. Es va fer alguna actuació a la cova de polí. Si fem un seguiment de ratpenats valorar si és necessari. *Col·locació de caixes refugi per a ratpenats com a mesura transitòria fins que s’aconsegueixi el grau de maduresa i l’abundància de cavitats suficient en el bosc. Ja s'ha fet. Si fem de nou un seguiment de ratpenats valorar l'estat de les caixes existents i valorar si és necessari. Contrastar amb XPuig si aquesta actuació és necessària. *Els instruments de planificació i ordenació dels espais naturals protegits estableixen mesures de protecció específica dels refugis i colònies de rat-penats.El PPAG no ho preveu però es te constància de les coves amb més valors i en base a això es fan les autortizacions. *Execució de mesures de tractaments específics a petita escala en fagedes destinats a incrementar la disponibilitat de microhàbitats potencialment adequats per a Rosalia alpina. Cal un projecte executiu en aquest sentit. *Incorporació de la tórtora europea en els instruments i plans de gestió dels espais de Natura 2000 en què l'espècie estigui considerada. La tenim com a tàxon prioritzat *Creació de zones d'alimentació riques en llavors per a la tórtora europea i altres espècies mitjançant la implantació de zones lliures de sembra i/o sembres específiques per a la fauna. No entenc bén bé que cal fer? *Recuperació de la qualitat de les pastures d'interès comunitari i les espècies associades (10% de la superfície total de 6170, 6210 i 6230). Integrat. *Actuacions de restauració dels indrets més degradats dels hàbitats o les àrees amb presència d'espècies d'interès comunitari en zones de roquissars, dunes o àrees de vegetació esparsa en base a una identificació i valoració de l'estat de conservació. No es una prioritat. NO tenim espècies d'interès comunitari amb hàbitats degradats. No prioritari. *Incorporació de criteris de conservació de l'hàbitat (p.ex. accions de control biològic) en les accions per la prevenció de les malalties del castanyes (xancre i tinta) o plagues (vespeta del castanyer). Es pot fer un estudi de millora hàbitat del xancre a Hortmoier. Parlar amb en QUim Avellà- *Aplicació de mesures físiques per minimitzar el risc d'erosió a les àrees amb presència de l'hàbitat. Millora de la senyalització al Comanegra. Seguiment de l'actuació i implementació de mesures, Algun lloc més? *Redacció del projecte executiu d’intervenció forestal per a la millora de l’hàbitat de Polygala vayredae Ho he afegit | T5: *Altres actuacions de conservació del patrimoni natural i del paisatge. Es contempla de forma transversal a totes les accions planificades *Mesures de foment d’actuacions per la gestió de teixedes, castanyedes i deveses S'ha fet un projecte europeu per millorar les teixedes i es va descartar la possibilitat de fer millores en les castanyedes (es va fer amb Galanthus, demanar a en Quim avellà) | U5: *Accions de conservació de tàxons de flora En curs amb el SFF *Millora d’hàbitats i control de flora invasora | V5: 1) Nombre de plans de gestió específics per a elements prioritaris redactats i implementats 2) Nombre de mesures/actuacions específiques per a elements prioritaris redactades i implementades | W5: 1) 1 2) 5 | X5: 1) 3 2) 7 | Y5: x | Z5: x | AA5: x | AB5: x | AC5: x | AD5: 1550 | AE5: No tenim àrees | AF5: En no tenir àrees no hi ha una unica persona responsable. Per les dimensions de l'entitat i sense quadre de substitució es fa de forma conjunta
D6: 01.1 | E6: Adequar i fer eficient la conservació dels elements objecte de gestió prioritària marcats per la DG a l'ENP | F6: 01.1.2 | G6: Adaptar i executar plans de gestió específics per a elements geològics de conservació prioritària dins l'ENP | H6: Comú | I6: Obligatori | L6: =G6 -> Adaptar i executar plans de gestió específics per a elements geològics de conservació prioritària dins l'ENP | N6: Sí | O6: Si | P6: MITJANA | Q6: Desenvolupament de la Geoestratègia de l'ENPAG_CAG | R6: *Desenvolupament de la Geoestratègia de l'ENPAG_CAG * Estudi hidrpgeològic de l' ENPAG_Contracte Programa entre la DGPA i ICGC | S6: *Redacció d'un pla d'accés públic a les coves d'alt valor natural i geològic_ En el PPAG es va resoldre amb la necessitat de comunicació a les coves i es va descartar cap limitaicó. Traslladar el MAP original. *Actuacions de restauració de les coves degradades. Què hi ha degradat? No en tenim constància. Es descarta per aquest pla estratègic. | U6: *Planificació i execució de les accions de conservació dels elements d’interès geològic inventariats. Es fa amb al seuiment de la geoestratègia. | V6: 1) Nombre d'actuacions/mesures incloses a la geoestratègia | W6: 1) 2 | X6: 1) 6 | Y6: x | Z6: x | AA6: x | AB6: x | AC6: x | AD6: 35
D7: 01.2 | E7: Executar les mesures de gestió directa previstes en els intruments de planificació per la conservació i la gestió adaptativa dels elements clau de l'ENP | F7: 01.2.1 | G7: Implementar la metodologia de gestió adaptativa (Estàndards Oberts de Gestió Adaptativa a Catalunya) en tots els processos de l'ENP | H7: Comú | I7: Obligatori | J7: ESNATURA | K7: SENP: Elaboració d'un manual per la implementació dels OSAM | L7: =G7 -> Implementar la metodologia de gestió adaptativa (Estàndards Oberts de Gestió Adaptativa a Catalunya) en tots els processos de l'ENP | N7: Sí | O7: Si | P7: MITJANA | Q7: Formació específica al personal del CAG sobre els open estàndards _DGPA Implementar els open estàndards a la gestió de l'espai _CAG | R7: *Formació específica al personal del CAG sobre els open estàndards- DGPA | T7: *Programa de seguiment del Pla. Crec que no aplica aquí. HO posaria a la linia 31 *Avaluació de l’efectivitat i actualització del Pla. Crec que no aplica aquí. Ho posaria a la linia 31. | U7: *Reunió taller un cop l’any per fer el seguiment i avaluar l’estratègia de geoconservació., Crec que no aplica aquí. Ho posaria al 01,01,2- | V7: 1) Formació realitzada 2) % de proejectes/accions que incorporen open estandards | W7: 1) 1 2) 50 | X7: 1) 1 2) 75 | AA7: x | AD7: 30
F8: 01.2.2 | G8: Executar les mesures previstes en els plans de conservació o recuperació d'espècies amenaçades de forma coordinada amb el Servei de Flora i Fauna en l'àmbit de l'ENP | H8: Comú | I8: Obligatori | J8: MAP Catàlegs | K8: SFF: Elaboració de plans de conservació o recuperació d'espècies protegides | L8: =G8 -> Executar les mesures previstes en els plans de conservació o recuperació d'espècies amenaçades de forma coordinada amb el Servei de Flora i Fauna en l'àmbit de l'ENP | N8: Sí | O8: Si | P8: ALTA | Q8: Implicació i participació en la redacció dels plans de conservació/recuperació d'epècies amenaçades_DGPA i CAG Execució de les accions contemplades en els plans de conservació/recuperació aprovats dins l'àmbit de l'ENP_CAG | R8: *Execució de les accions pactades amb el SFF per espècies de flora vascular amenaçada (nombrar totes les de la llista) * Participació en el seguiment del SEGRE (aus rapinyaires) i el cens simultari de Gypaetus barbatus valorar si va a coneixement o si ho repetim QUINS MËS PLANS HI HA APROVATA PER ESPÈCIES? | S8: *Aprovació dels Plans de Conservació i/o Recuperació de les espècies de fauna d'interès comunitari. *Realització d'altres mesures vinculades als Plans de Conservació i/o Recuperació de les espècies aquàtiques d'interès comunitari amenaçades.Hi ha plans de conservació associats a espècies aquàtiques. *Execució d'altres mesures incloses als plans de conservació de Callimorpha quadripunctaria i Euphydryas aurinia. *Execució de mesures de desenvolupament del pla de recuperació de rapinyaires. | V8: 1) Nombre de plans de conservació o recuperació en els que s'ha participat 2) Nombre de mesures executades en els plans de conservació o recuperació vigents | W8: 1) 2 2) 2 | X8: 1) 4 2) 4 | Y8: x | Z8: x | AA8: x | AB8: x | AC8: x | AD8: 60
F9: 01.2.3 | G9: Executar les mesures de gestió previstes en els plans de control i erradicació d'espècies exòtiques de forma coordinada amb el Servei de Flora i Fauna en l'àmbit de l'ENP | H9: Comú | I9: Obligatori | J9: ESNATURA MAP | K9: SFF: Elaboració de plans de control i erradicació d'espècies exòtiques | L9: =G9 -> Executar les mesures de gestió previstes en els plans de control i erradicació d'espècies exòtiques de forma coordinada amb el Servei de Flora i Fauna en l'àmbit de l'ENP | N9: Sí | O9: Si | P9: ALTA | Q9: Implicació en la redacció de plans de control i erradicació d'EEI i protocols per la gestió preventiva de vies d'entrada vinculades a sectors d'activitat_DGPA i CAG Execució d'accions de control d'EEI_CAG Suport a una prova pilot per al control de Seneci inaquidens en zones amb presència d'hàbitat i espècies d'interès comunitari o amb impacte sobre l'activitat agroramadera_DGPA i CAG | R9: *Actuacions de manteniment i control d'Ailanthus altissina_CAG *Disseny d'una prova pilot per al control de Seneci inaquidens en zones amb presència d'hàbitat i espècies d'interès comunitari o amb impacte sobre l'activitat agroramadera_CAG i SFF *Protocol comú per als ENPs de protocols per a la gestió preventiva de vies d'entrada vinculada a sectors d'activitat (per exemple, jardineria, aqüicultura, distribució comercial), inclosos codis de conducta i manuals de bones pràctiques_SFF *Plans de control de crancs invasors_DGPA | S9: *Elaboració i execució de plans de control d'espècies exòtiques i prevenció del seu ús en activitats productives en zones fluvials. No és el cas de l'AG *Redacció de protocols per a la gestió preventiva de vies d'entrada vinculada a sectors d'activitat (per exemple, jardineria, aqüicultura, distribució comercial), inclosos codis de conducta i manuals de bones pràctiques. Això ho podria fer la DG? *Execució de plans de control de crancs invasors (Procambarus clarki, Pacifastacus leniusculus i Orconectes limosus). *Elaboració i execució de plans de control d'espècies exòtiques i prevenció del seu ús en activitats productives. CPf?? demanar a en Quim Avellà *Elaboració i execució de plans globals de control d'altres espècies exòtiques i prevenció del seu ús en activitats productives.DGPA. valorar si tot el que es globar ho volem posar o no cal fer referència. | V9: 1) Nombre de plans/ protocols de control d'espècies exòtiques en els que s'ha participat 2) Nombre de mesures executades en els plans de gestió d'espècies exòtiques 3)Execució prova pilot | W9: 1) 2 2) 2 3) 0 | X9: 1) 4 2) 4 3) 1 | Y9: x | Z9: x | AA9: x | AB9: x | AC9: x | AD9: 160
F10: 01.2.4 | G10: Desplegar els objectius i tasques recollits en els instruments de referència i compromisos internacionals | H10: Específic | I10: Optatiu | L10: =G10 -> Desplegar els objectius i tasques recollits en els instruments de referència i compromisos internacionals | N10: Impuls-Suport | O10: Si | P10: MITJANA | Q10: Col·laboració en la implementació pràctica de projectes de l'àrea internacional a petició de la DGPA | R10: *Seguiment dels avenços de la Generalitat en aquest desplegament unitari en territori català. | V10: 1) Nombre de col·laboracions | W10: 1) 1 | X10: 1) 2 | Y10: x | Z10: x | AA10: x | AB10: x | AC10: x | AD10: 30
D11: 01.3 | E11: Crear ecosistemes complexes, resilients, i d'alta biodiversitat per garantir la recuperació dels processos ecosistèmics | F11: 01.3.1 | G11: Identificar espais pel foment de la dinàmica natural i l'aprofitament no extractiu | H11: Comú | I11: Obligatori | J11: ESNATURA | K11: SENP/SFF: Definir criteris metodològics | L11: =G11 -> Identificar espais pel foment de la dinàmica natural i l'aprofitament no extractiu | N11: Realitzat | O11: Si | P11: MITJANA | Q11: Objectiu operatiu assolit, sense mesures continuïstes en el termini del present Pla estratègic | R11: * Projecte de renaturalització_DGPA (PPAG) *Realitzar la signatura de convenis de dinàmica natural amb propietaris_DGPA (PPAG) | S11: *Signatura de convenis de dinàmica naturals Competència de la generalitat en tant que competent. *Identificació efectiva dels rodals madurs que tendeixen a evolució natural en tots els Plans d'Ordenació Forestal. Hi ha estudi de galanthus que identifica els rodals clau de l'espai. No es té una cartografia/buidat de tots els plans però no es considera necessària sino més prioritari el projecte de renaturalització i els convenis de dinàmica natural pròpiament. | T11: *Projecte de renaturalització i valorització en la zona de foment de la dinàmica natural *Mesures de foment de la gestió de finques en règim de dinàmica natural i aprofitament no extractiu | AD11: 0
F12: 01.3.2 | G12: Afavorir la maduresa dels sistemes forestals | H12: Específic | I12: Optatiu | J12: MAP | K12: SENP/SFF: Definir criteris metodològics | L12: =G12 -> Afavorir la maduresa dels sistemes forestals | N12: Impuls-Suport | O12: Si | P12: MITJANA | Q12: Redacció del Projecte de renaturalització i adaptació al canvi climàtic_DGPA (PPAG) Execució del Projecte de renaturalització i adaptació al canvi climàtic_DGPA (PPAG) Signatura de convenis de dinàmica natural amb propietaris_DGPA (PPAG) Incorporació dels criteris del PPAG als IOF_DGPA | R12: * Projecte de renaturalització_DGPA (PPAG) *Signatura de convenis de dinàmica natural amb propietaris_DGPA (PPAG) * Compliment dels informes de SSTT i el compliment de criteris_CPF Demanar Quim Avellà com revisen el compliment dels criteris i si ho fan. | S12: TOTES AQUETES ACCIONS /CRITERIS ES PODEN INTEGRAR A LES DUES ACCIONS DETERMINADES A LA COLUMNA ANTERIOR. *Actuacions per al foment de la maduresa i naturalitat dels boscos_ *Actuacions de gestió forestal dirigida al manteniment de la maduresa i naturalitat de la massa en boscos públics. *Actuacions de manteniment de grans peus de planifolis i altres arbres vells caducifolis per afavorir el manteniment d'espècies forestals d'interès comunitari (Rosalia alpina, Lucanus cervus i Osmoderma eremita). *Actuacions per fomentar la presència de fusta morta en peu o a terra i d'arbres vells o decrèpits en boscos públics. *Actuacions de gestió per augmentar la densitat de cavitats fomentant la presència d’arbres decrèpits o morts. *Actuacions de millora de la maduresa dels boscos dels hàbitats 9160, 9240 i 9540. *Mesures d'adaptació de boscos de 9340 al canvi climàtic i per a l'increment de la maduresa o l'entrada d'espècies de futur (Phyllirea sp, Pistacia sp....). *Realització de tractaments silvícoles en boscos premadurs, tot buscant estructures amb edats irregulars, que garanteixin un equilibri entre les diferents classes d'edat, amb grans diàmetres, amb separació vertical de les copes dels arbres amb els estrats. | T12: *Mesures de foment d’actuacions d’acceleració o millora de la maduresa del bosc | V12: 1) Redacció del projecte 2) Nombre d'actuacions executades del projecte 3) Nombre de convenis signats 4) Incorporació dels criteris als IOF | W12: 1) 1 2) 2 3) 3 4) 1 | X12: 1) 1 2) 4 3) 5 4) 1 (a tots) | Z12: x | AA12: x | AB12: x | AC12: x | AD12: 300
F13: 01.3.3 | G13: Generar pertorbacions controlades | H13: Específic | I13: Optatiu | J13: MAP | K13: SENP/SFF: Definir criteris metodològics | L13: =G13 -> Generar pertorbacions controlades | N13: Impuls-Suport | O13: Si | P13: MITJANA | Q13: Execució d'accions per generar pertorbacions controlades (incloses al PPAG, Pla de cremes prescrites, Projecte de Renaturalització, PIRE, etc)_DGPA i CAG | R13: *Projecte de renaturalització_DGPA (PPAG) * Pla de cremes prescrites_FPC (Ajut entitats) | S13: *Redacció d’un projecte de renaturalització a l’Alta Garrotxa | U13: *Comissió per la coexistència amb cànids i resta de fauna | V13: 1) Nombre d'accions executades a l'ENP | W13: 1) 3 | X13: 2) 6 | Y13: x | Z13: x | AA13: x | AB13: x | AC13: x | AD13: 150
F14: 01.3.4 | G14: Restaurar la dinàmica natural dels rius | H14: Específic | I14: Optatiu | J14: MAP | K14: SENP/SFF: Definir criteris metodològics | L14: Restaurar i conservar la dinàmica i estructura natural dels rius, les zones humides, i altres hàbitats d'aigua dolça | M14: Canvi de redactat OP. Adaptar el redactat per a tot tipus de masses d'aigua | N14: Impuls-Suport | O14: Si | P14: MITJANA | Q14: Suport tècnic en l'execució d'accions de millora de connectivitat fluvial_CAG Foment de la custòdia fluvial_CAG | R14: *Elaboració d'una cartografia d'hàbitats fluvials i un programa d'actuacions per a la millora dels hàbitats (anomenar els hàbitats)_CAG *Seguiment dels treballs de construcció del connector fluvial del Gomarell (riera de Sant Aniol) que realitza l'Ajuntament de Montagut i Oix_CAG * Acord de custòdia fluvial a la conca de la Muga_CAG | S14: *Recuperació de basses. Projecte ponderful. No aplica aquí. Aplica al primer objectiu *Restauració de la morfologia, la connectivitat i les riberes de les masses d'aigua rius del DCFC. Connector fluvial del Gomarelli acord de custòdia fluvial al sector de la Muga *Actuacions de millora de la vegetació ripària a partir de l'aplicació del Programa de Manteniment i conservació de lleres de l'ACA, especialment en àrees que requereixen recuperació de cobertura arbòria. Primer farem la cartografia el programa d'actuacions, a posteriori redacció de projectes executius. *Actuacions pel manteniment de la dinàmica hidrològica pròpia de l'hàbitat 6420, evitant drenatges o inundacions permanents. On en tenim? Seria el qu hi ha a Palomeres?si no ho sabem li podem demanar a en Lluis Benejam. Però seria a l'objectiu 1. Valorar si és el cas d'aques hàbitat específicament. | V14: 1) Nombre d'actuacions executades 2) Nombre d'acords | W14: 1) 1 2) 1 | X14: 1) 2 2) 2 | Y14: x | Z14: x | AA14: x | AB14: x | AC14: x | AD14: 200
F15: 01.3.5 | G15: Fomentar el paisatge en mosaïc | H15: Específic | I15: Optatiu | J15: ESNATURA | K15: SENP/SFF: Definir criteris metodològics | L15: =G15 -> Fomentar el paisatge en mosaïc | N15: Sí | O15: Si | P15: ALTA | Q15: Recuperació d'espais oberts segons PIRE_CAG Execució del Programa de compensacions per afavorir ramaderia extensiva segons PIRE_DGPA | R15: * Projecte de recuperació d'espais oberts_CAG *Desenvolupament del PIRE i del Programa de Compensacions a l'activitat ramadera_CAG i DGPA * Seguiment de l'estat ecològic dels prats de l'Alta Garrotxa_CAG * Anàlisi d'oportunitats per la recuperació de prats de dall_CAG valorar si es factible a ENPAG | S15: *Recuperació de pastures i espais oberts En curs des de 2009. *Manteniment dels espais oberts (conreus i pastures), els prats de dall i un paisatge en mosaic en les zones amb presència destacada d'espècies d'interès comunitariEn curs des de 2009. *Potenciar la ramaderia extensiva per conservar els hàbitats agroforestals i prevenir incendis forestals.En curs des de 2009. *Realització de desbrossades selectives en zones de matollar per a afavorir l'hàbitat de la tórtora europea.Es fa amb els criteris de recuperació EEOO (ecotons, conservació espècies nutrícies, i reducció de la intensitat als marges de l'actuació, períemtres irregulars) *Mesures de conservació de la vegetació arbustiva i de la bardissa en fons de valls mantenint un mosaic de vegetació. Es un hàbitat no en regressió per s'apliquen els criteris abans descrits quan es fa recuperació d'espais oberts. *Els instruments de planificació i ordenació dels espais naturals protegits eviten l'aforestació en nuclis rellevants dels matollars i prats d'interès comunitari.Si, el PPAG preveu àrees atenció condicionada associades a espais oberts. *Recuperació de prats de dall (5% de la superfície actual). Què podriem fer per encara aquesta actuació? | T15: *Mesures de foment d’actuacions de recuperació i manteniment de pastures. | U15: *Recuperació de pastures i d'hàbitsts d'espais oberts *Redacció de Plans de Pastura prescrita *Ampliació i recuperació de pastures | V15: 1) Nombre d'actuacions executades 2) Nombre d'explotacions ramaderes afavorides | W15: 1) 3 2) 2 | X15: 1) 6 2) 4 | Y15: x | Z15: x | AA15: x | AB15: x | AC15: x | AD15: 500
F16: 01.3.6 | G16: Gestionar i intervenir en la dinàmica de poblacions de fauna que no tenen depredador natural | H16: Específic | I16: Optatiu | K16: SENP/SFF: Definir criteris metodològics | L16: =G16 -> Gestionar i intervenir en la dinàmica de poblacions de fauna que no tenen depredador natural | N16: No | O16: Si | P16: BAIXA | Q16: Participació i impuls del control directe de poblacions de fauna d'acord amb l'organisme competent en matèria de gestió cinegètica_CAG i DGPA | V16: 1) Nombre d'accions de control impulsades | W16: 1) 0 | X16: 1) 1 (segons necessitats) | AB16: x | AC16: x | AD16: 25
D17: 01.4 | E17: Alinear l'activitat de propietaris i gestors del territori amb la conservació, millora i restauració dels valors de l'ENP | F17: 01.4.1 | G17: Fomentar acords de custòdia en espais d'alt valor dins l'ENP per a la gestió dels elements prioritaris | H17: Comú | I17: Optatiu | J17: MAP | K17: SENP/SENP: Dissenyar el protocol i elaborar un model d'acord | L17: =G17 -> Fomentar acords de custòdia en espais d'alt valor dins l'ENP per a la gestió dels elements prioritaris | N17: Sí | O17: Si | P17: ALTA | Q17: Foment i signatura d'acords de custòdia amb entitats o el CAG_CAG Signatura de convenis de dinàmica natural amb propietaris_DGPA | R17: * Signatura d'acords de custòdia per realitzar accions de millora d'hàbitat dins ENPAG_CAG * Signatura d'un acord de cusòdia fluvial amb l'ACA per a sector de la Muga_CAG *Signatura de convenis de dinàmica natural amb propietaris_DGPA (PPAG) | T17: *Promoure acords de custòdia del territori | U17: *Diagnosi i proposta d’accions-custodia fluvial a la Muga *Acord de custòdia fluvial per la Reserva Natural Parcial de la Muga | V17: 1) Nombre d'acords de custòdia aconseguits 2) Nombre de convenis de dinàmica natural signats | W17: 1) 3 2) 3 | X17: 1) 6 2) 5 | Y17: x | Z17: x | AA17: x | AB17: x | AC17: x | AD17: 150
F18: 01.4.2 | G18: Fomentar bones pràctiques entre els col·lectius de propietaris i gestors del territori | H18: Comú | I18: Optatiu | L18: =G18 -> Fomentar bones pràctiques entre els col·lectius de propietaris i gestors del territori | N18: Impuls-Suport | O18: Si | P18: MITJANA | Q18: Divulgació de bones pràctiques per la gestió d'hàbitats i espècies (estudi canvi climàtic, maneig de pastures) | R18: * Trasllat als propietaris dels resultats de l'estudi del CREAF sobre l'impacte del canvi climàtic a les masses forestals de l'ENPAG_CAG * Creació una taula de treball per consensuar BBPP de gestió forestal al'ENPAG ¿??? * Creació d'un manual de BBPP de gestió forestal vinculat a l'adaptació del canvi climàtic_CAG * Suport a la FPC en la redacció de Plans de maneig per a la gestió del pastoreig (Projecte Forwards)_CAG | S18: INCLOURE COM A CRITERIS DE BBPP O BÉ FORA DE L'ABAST DAQUEST PLA ESTRATÈGIC*Actuacions per disminuir i substituir els productes fitosanitaris per altres de més selectius i de baixa toxicitat (AAA) tant per a la fauna terrestre com aquàtica. *Actuacions de foment de l'ús de permetrines enlloc d'organoclorats pel tractament de la fusta d'edificacions amb presència de rat-penats. *Actuacions de manteniment dels sistemes tradicionals de gestió de les pastures. Es realitza a trvés del projecte d'EEOO perquè la recuperació espais permet la transhumància dins de l'espai, i s'articula a través del PIRE. | U18: *Implicació de la pagesia en el manteniment d’espais oberts i recuperació d’elements d’interès que acompanyen el patrimoni geològic HO fem en el desenvolupament de l'estratègia | V18: 1) Nombre de sessions de divulgació 2) Elaboració de material divulgatiu | W18: 1) 2 2) 1 | X18: 1) 4 2) 2 | AB18: x | AC18: x | AD18: 64
F19: 01.4.3 | G19: Impulsar la coordinació amb els ens locals en la gestió finques públiques situades dins d’ENP | H19: Específic | I19: Optatiu | J19: ESNATURA | L19: =G19 -> Impulsar la coordinació amb els ens locals en la gestió finques públiques situades dins d’ENP | M19: No aplica, finca pública de la Generalitat | O19: No | Q19: Objectiu no aplicable a l'espai | R19: *Consens en el marc del CP del CAG les accions impulades per l'ens en finca pública. | AD19: 0
B20: 2 | C20: ADAPTAR ELS ECOSISTEMES AL CANVI CLIMÀTIC i millorar-ne la resiliència en front dels riscos associats. | D20: 02.1 | E20: Planificar l'adaptació dels sistemes naturals al canvi climàtic | F20: 02.1.1 | G20: Adaptar i implementar el Pla d'adaptació de l'ENP al canvi climàtic | H20: Comú | I20: Obligatori | K20: OCCC/SENP: Elaboració del model de Pla d'adaptació dels ENP al canvi climàtic | L20: Implementar els resultats de l'estudi d'adaptació dels boscos de l'Alta Garrotxa | M20: Es té una estudi-prova pilot a específic per l'ENPAG | N20: Impuls-Suport | O20: Si | P20: ALTA | Q20: Redacció del Pla d'adaptació al canvi climàtic de l'ENP_DGPA i CAG Foment d'actuacions per a la creació de refugis climàtics_DGPA i CAG Divulgació dels criteris de gestió d'adaptació al canvi climàtic a l'ENP_DGPA i CAG | R20: * Signatura d'acords de custòdia per realitzar accions de millora d'hàbitat dins ENPAG_CAG *Signatura de convenis de dinàmica natural amb propietaris_DGPA (PPAG) *Suport a DGBoscos (SSTT) en la definció i seguiment del projecte de refugis climàtics del MITECO_CAG i DGPA (SSTT) *Integració dels criteris de la prova pilot sobre canvi climàtic en els informes dels SSTT respecte a actuacions forestals_DGPA (SSTT) * Creació d'un manual de BBPP de gestió forestal vinculat a l'adaptació del canvi climàtic_CAG | V20: 1) Redacció del Pla 2) Nombre d'actuacions 3) Nombre de sessions divulgatives CC | W20: 1) 1 2) 3 3) 1 | X20: 1) 1 2) 6 3) 2 | Y20: x | Z20: x | AA20: x | AB20: x | AC20: x | AD20: 120
F21: 02.1.2 | G21: Gestionar i planificar els recursos hídrics de l'ENP | H21: Comú | I21: Obligatori | L21: =G21 -> Gestionar i planificar els recursos hídrics de l'ENP | N21: Impuls-Suport | O21: Si | P21: ALTA | Q21: Redacció del Pla de gestió dels recursos hídrics d'acord amb l'estudi hidrogeològic de l'ENP_DGPA Suport a la regulació de les captacions per ús domèstic_CAG | R21: Podem fer alguna cosa per evitar els impactes del canvi climàtic sobre els recursos hídrics. Què podem fer? HO podem integrar en l'estudi de gestió dels hàbitats de ribera?? Mirar què han fet altres espais. | V21: 1) Redacciódel Pla | W21: 1) 1 | X21: 1) 1 | AB21: x | AC21: x | AD21: 50
F22: 02.1.3 | G22: Participar en la redacció i execució dels instruments d'ordenació forestal sostenible i per la conservació en finques públiques | H22: Específic | I22: Optatiu | K22: DGEFMN: Redacció d'IOF en finques públiques | L22: Promoure la redacció d'instruments d'ordenació forestal sostenible i l'execució d'accions per la conservació i millora dels boscos i els elements d'interès | M22: Canvi de redactat OP. Inclusió d'accions forestals per a la millora de la biodiversitat sense detallar la propietat de la finca | N22: Impuls-Suport | O22: Si | P22: MITJANA | Q22: Suport a la implementació dels IOF en finca pública_CAG i SSTT | R22: *Suport a DGBoscos (SSTT) en la definció i seguiment del projecte de refugis climàtics del MITECO_CAG i DGPA (SSTT) | S22: *Redacció del projecte executiu d’intervenció forestal per a la millora de l’hàbitat de Polygala vayredae Això no aplica en aquest objecitu, va en el primer. Ho he posat al primer objectiu. *Els Plans d’Ordenació Forestal de finques públiques inclouen criteris orientats a la conservació de les millors àrees amb presència d'hàbitats o espècies d'interès comunitari.Hem donat suport amb la info de la que disposem sobre patirmoni natural. *Els instruments de planificació forestal han de tenir en compte la realització de les estassades de forma més selectiva per tal d'evitar la tala d'espècies d'interès especial als boscos d'interès comunitari.Ja està integrat. contrastat amb la Miriam. *Establiment de mesures de gestió per a la conservació en els models de gestió ORGEST. Per exemple, el manteniment d'un mínim de 5 a 10 arbres/ha de més de 40 dn, respecte a Hedera, peus morts, arbres amb cavitats sense tallar, etc.Ja està integrat. contrastat amb la Miriam. *Els instruments de planificació forestal han d’establir una freqüència de nou anys entre estassades en les rouredes d'interès comunitari (9160,9230,9240).Ja està integrat. contrastat amb la Miriam. *Mesures i actuacions d'us de la ramaderia extensiva o d'aclarides selectives per controlar l'excés de sotabosc a pinedes i alzinars.Ja està integrat. contrastat amb la Miriam. *Recuperació de tècniques tradicionals d'aclarida al voltant dels arbres més productius per minimitzar la pertorbació que suposen les estassades generals de l'estrat arbustiu.Ja està integrat. contrastat amb la Miriam. *Actuacions per augmentar la presència d'espècies arbòries i arbustives productores de fruits susceptibles de ser font d'aliment per a la fauna.Ja està integrat. contrastat amb la Miriam. *Realització de les estassades de forma més selectives per tal d'evitar la tala d'espècies d'interès especial.Ja està integrat. contrastat amb la Miriam. *Actuacions de gestió forestal específica per conservació dels rodals de 9580 dins la massa mitjançant tallades selectives.Hi ha teixeda en finca pública? Crec que no aplica. Contrastat amb la Miriam. | V22: 1) Percentatge d'actuacions forestal amb IOF redactat en que s'ha participat a petició de la DGB | W22: 1) 25 | X22: 2) 50 | AD22: 20
F23: 02.1.4 | G23: Promoure la redacció d'instruments d'ordenació forestal per reduir la sensibilitat i vulnerabilitat dels boscos al canvi climàtic en finques privades | H23: Específic | I23: Optatiu | L23: =G23 -> Promoure la redacció d'instruments d'ordenació forestal per reduir la sensibilitat i vulnerabilitat dels boscos al canvi climàtic en finques privades | N23: Impuls-Suport | O23: Si | P23: MITJANA | Q23: Col·laboració amb el CPF per al foment dels IOF per reduir la sensibilitat i vulnerabilitat al canvi climàtic en finca privada_CAG Foment i revisió de les mesures compensatòries i condicions d'execució dels dels IOF perquè no siguin agressius amb l'hàbitat forestal_CAG Foment de la implementació crèdits climàtics forestals_CAG | R23: * Trasllat als propietaris dels resultats de l'estudi del CREAF sobre l'impacte del canvi climàtic a les masses forestals de l'ENPAG_CAG * Sigantura d'acords de custòdia per realitzar accions de millora d'hàbitat dins ENPAG_CAG * Signatura de convenis de dinàmica natural amb propietaris_DGPA (PPAG) *Integració dels criteris de la prova pilot sobre canvi climàtic en els informes dels SSTT respecte a actuacions forestals_DGPA (SSTT) * Creació d' una taula de treball per consensuar BBPP de gestió forestal a l' ENPAG ¿??? * Creació d'un manual de BBPP de gestió forestal vinculat a l'adaptació del canvi climàtic_CAG | V23: 1) Nombre d'accions conjuntes de divulgació | W23: 1) 1 | X23: 1) 3 | Z23: x | AA23: x | AB23: x | AC23: x | AD23: 80
D24: 02.2 | E24: Planificar la prevenció i extinció d’incendis forestals i la gestió del foc de forma coordinada amb els diferents agents del territori | F24: 02.2.1 | G24: Redactar i implementar el Pla de Prevenció d'Incendis | H24: Comú | I24: Obligatori | J24: ESNATURA | K24: Equip de PPI: Disseny del protocol de treball | L24: =G24 -> Redactar i implementar el Pla de Prevenció d'Incendis | N24: Impuls-Suport | O24: Si | P24: MÀXIMA | Q24: Redacció dels PEGs inclosos al PIE_CAG Implementació d'accions del PIE (xarxa viària, espais oberts)_CAG Manteniment i adequació de la xarxa viària per a la prevenció d'incendis_CAG | R24: * Suport a la FPC i la DGPA en el projecte Foc i Biodiversitat a l'Alta Garrotxa_CAG * Redacció dels projectes executius dels PEGs definits pel Cos de Bombers_CAG * Establiment de lligams amb el GPIF (Forestal Catalana) per a l'execució del PIE de l'ENPAG_CAG i DGPA * Impuls de l'aprovació de l'Annex del PIE vinculat als PEGs redefinits_CAG * Millora de la xarxa viària establerta al PIE_CAG * Pagament per serveis ambientals als ramaders_DGPA * Priorització de la recuperació d'EEOO en PEGs i sectors prioritzats al PIE_CAG * Manteniment dels punts d'aigua segons incidències_CAG/Ajuntaments | S24: *Actuacions de prevenció i extinció de grans incendis forestals. | U24: *Construcció i manteniment de vials forestals per a la prevenció d'incendis *Actuacions en punts crítics associats a la xarxa viària per a la prevenció d'incendis *Construcció i manteniment de punts d'aigua de la xarxa bàsica per a la prevenció d'incendis *Protecció, adequació i senyalització de punts d'aigua de la xarxa bàsica per a l'extinció d'incendis *Actuacions sobre la vegetació per a l'obertura de franges auxiliars de trànsit (FAT) i tractament de restes vegetals *Actuacions sobre la vegetació per a la creació d'àrees estratègiques de baixa càrrega de combustible per a la prevenció d'incendis *Implementació d'intraestructures o serveis per als ramats de manteniment de les àrees estratègiques *Manteniment d'àrees estratègiques de baixa càrrega de combustible per a la prevenció d'incendis mitjançant pasturatge amb ramaderia extenisva *Actuacions sobre la vegetació per l'obertura d'àrees de seguretat amb eliminació de restes in situ *Actuacions sobre la vegetació a l'entorn dels punts d'aigua d'extinció d'incendis *Actuacions sobre la vegetació en Zones de Foment de la Gestió (ZFG) | V24: 1) Nombre de PEGs redactats 2) Nombre d'accions implementades | W24: 1) 3 2) 4 | X24: 1) 6 2) 8 | Y24: x | Z24: x | AA24: x | AB24: x | AC24: x | AD24: 450
F25: 02.2.2 | G25: Definir i planificar la gestió del foc per a la millora de l'ENP | H25: Específic | I25: Optatiu | K25: SPEN: Elaboració d'un model de pla de gestió | L25: =G25 -> Definir i planificar la gestió del foc per a la millora de l'ENP | N25: Sí | P25: ALTA | Q25: Suport a la FPC en el seguiment de les zones on s'han realitzat cremes prescrites (proiecte Foc i Biodiversitat i Projecte Forwards_CAG Participació i dinamització de la Taula de foc de l'Alta Garrotxa_CAG Suport a la sensibilització sobre el foc com a eina de gestió_CAG | R25: * Suport a la FPC i la DGPA en el projecte Foc i Biodiversitat a l'Alta Garrotxa (pla de cremes prescrites i execució de treballs forestals en PEGs_CAG * Suport a la FPC en l'elaboració de plans de maneig per la gesitó de pastures i seguiment en les zones on s'han realitzat cremes prescrites (proiecte Foc i Biodiversitat i Projecte Forwards_CAG * Participació i dinamització de la Taula de foc de l'Alta Garrotxa_CAG * Suport a la FPC i participació en les sessions de sensibilització sobre el foc com a eina de gestió_CAG | S25: *Regulació de pràctiques de gestió de pastures (cremes controlades i ramaderia intensiva) que poden comportar una simplificació de l'ecosistema o la desaparició dels hàbitats 4060 i 6420. Plans de maneig del pastoreig que construirem amb la FPC en el projecte Forwards. (si és l'hàbitat ho tindrem en compte). | T25: *Planificació per la prevenció i extinció d’incendis forestals i per la gestió del foc. En curs- | U25: *Constitució d'una Taula de foc i elaboració dels projectes executius dels punts estratègics de gestió per incendis | V25: 1) Nombre d'espais objecte de seguiment 2) Nombre de sessions de la taula de foc 3) Nombre d'accions de sensibilització | W25: 1) 2 2) 4 3) 1 | X25: 1) 4 2) 6 3) 2 | AD25: 180
F26: 02.2.3 | G26: Treballar per a la prevenció d'incendis juntament amb els propietaris, ajuntaments, protecció civil, ADF i bombers. | H26: Comú | I26: Obligatori | L26: =G26 -> Treballar per a la prevenció d'incendis juntament amb els propietaris, ajuntaments, protecció civil, ADF i bombers. | N26: Sí | O26: Si | P26: ALTA | Q26: Participació i dinamització de la Taula de foc de l'Alta Garrotxa_CAG Suport a la sensibilització sobre el foc com a eina de gestió_CAG | R26: * Participació i dinamització de la Taula de foc de l'Alta Garrotxa_CAG * Suport a la FPC i participació en les sessions de sensibilització sobre el foc com a eina de gestió_CAG | V26: 1) Nombre de sessions de la taula de foc 2) Nombre d'accions de sensibilització | W26: 1) 4 2) 1 | X26: 1) 6 2) 2
B27: 3 | C27: PROTEGIR LA BIODIVERSITAT, i especialment els elements fràgils i amenaçats, d’interès comunitari o de major interès natural. | D27: 03.1 | E27: Prevenir, minimitzar i compensar els impactes ambientals dels usos i activitats que es desenvolupin en l'àmbit de l'ENP | F27: 03.1.1 | G27: Participar en les consultes dels procesos d'Avaluació Ambiental que afectin directament o indirectament l’espai del ENP | H27: Comú | I27: Obligatori | L27: =G27 -> Participar en les consultes dels procesos d'Avaluació Ambiental que afectin directament o indirectament l’espai del ENP | N27: Impuls-Suport | O27: Si | P27: ALTA | Q27: Suport i assessorament als SSTT en l'emissió d'informes dins al tramitació de l'AIA de projectes i activitats dins ENPAG_CAG i SSTT | R27: * Tramitació dels DAE necessaris en el desenvolupament de projectes promoguts pel Consorci_CAG * Suport als SSTT en l'emissió d'informes dins al tramitació de l'AIA_CAG i SSTT * Assessorament i interlocució en l'àmbit de l'AIA en el marc de la implementació de planificació /projectes impulsats per tercers_CAG | S27: *L'avaluació ambiental de la creació de nous vials i infraestructures en àrees amb presència d'hàbitats o espècies d'interès comunitari ha de minimitzar la seva afectació evitant l'afectació de les àrees més ben conservades. Es realitza sempre prèvia consulta amb SSTT i OTAA | V27: 1) Percentatge de suport i assessorament realitzat a petició dels SSTT | W27: 1) 65% | X27: 1) 100% | Y27: x | Z27: x | AA27: x | AB27: x | AC27: x | AD27: 25
F28: 03.1.2 | G28: Exercir un seguiment efectiu de les obres al Parc juntament amb les Oficines Territorials d'Acció i Avaluació Ambiental als efectes d'assegurar la correcta translació de la tutela administrativa. | H28: Comú | I28: Obligatori | L28: =G28 -> Exercir un seguiment efectiu de les obres al Parc juntament amb les Oficines Territorials d'Acció i Avaluació Ambiental als efectes d'assegurar la correcta translació de la tutela administrativa. | M28: No tenim capacitat ni som competents | O28: Si | Q28: Objectiu descartat per falta de capacitat o competències | AD28: 0
F29: 03.1.3 | G29: Participar en la compensació d'impactes residuals durant els processos d'avaluació ambiental mitjançant la identificació de necessitats d'actuació prioritària dins i fora dels límits de l’ENP | H29: Comú | I29: Optatiu | L29: =G29 -> Participar en la compensació d'impactes residuals durant els processos d'avaluació ambiental mitjançant la identificació de necessitats d'actuació prioritària dins i fora dels límits de l’ENP | M29: No tenim capacitat | Q29: Objectiu descartat per falta de capacitat o competències | R29: *Identificació de punts d'atropellament d'amfibis_CAG (com es fa això, ho podem demanar en el marc del SACC) | S29: *Identificació de punts d'atropellament d'amfibis i construcció de passos de fauna. Intentar fer a través de l'estudi del SACCi si no de forma complementària. *Actuacions de correcció dels suports de línies elèctriques on es detectin noves electrocucions o amb risc potencial d'electrocució i senyalització amb salvaocells de les línies perilloses per col·lisió. No es un problema greu a AG per poca circulació rodada. contrstar Dani. *Actuacions de correcció de punts negres d'atropellament de L. lutra i Mustela lutreola. No és una problema greu a AG per poca circulació rodada. Contrastar Dani. | AD29: 0
D30: 03.2 | E30: Garantir el compliment dels objectius de conservació dotant l'ENP de la planificació adequada segons estableix la normativa vigent (Pla de Protecció, PRUG, plans específics...) | F30: 03.2.1 | G30: Participar en l'elaboració dels instruments de planificació de l'ENP | H30: Comú | I30: Obligatori | K30: SPEN: Elaboració del Pla rector d'usos i gestió. SPEN: Elaboració del Pla rector d'usos i gestió | L30: Revisar el PPAG | N30: Impuls-Suport | O30: Si | P30: MITJANA | Q30: Suport a la revisió i seguiment del PPAG segons el que estableix apartat 12 de la memòria del mateix Pla, a instàncies del SPENP_CAG | R30: * Suport a la revisió i seguiment del PPAG segons el que estableix apartat 12 de la memòria del mateix Pla, a instàncies del SPENP. | V30: 1) Revisió del PPAG | W30: 1) 1 | X30: 1) 1 | AB30: x | AC30: x | AD30: 180
D31: 03.3 | E31: Vetllar pel manteniment dels cabals ecològics i la bona qualitat dels cursos fluvials de l'ENP de forma coordinada amb l'administració competent | F31: 03.3.1 | G31: Vetllar pel manteniment del cabal ecològic dels rius definit al Pla sectorial corresponent | H31: Específic | I31: Optatiu | J31: ESNATURA | K31: ACA/CHE: Determinar els cabals ecològics en espais naturals protegits | L31: =G31 -> Vetllar pel manteniment del cabal ecològic dels rius definit al Pla sectorial corresponent | N31: Impuls-Suport | O31: Si | P31: ALTA | Q31: Suport a la materialització de l'estudi hidrogeològic i els seguiments associats en el marc del CP entre la DGPA i ICGC_CAG Foment, a través de l'organisme competent (ACA), de major nombre de punts de control de cabal a la xarxa fluvial_ACA i CAG Signatura d'acords de custòdia fluvial a l'ENPAG_ACA i CAG | R31: * Impulsar la materialització de l'estudi hidrogeològic i els seguiments associats en el marc del CP entre la DGPA i ICGC_CAG * Acord de custòdia fluvial a la conca de la Muga_CAG * Neteja del futur connector fluvial del Gomarell a la riera de Sant Aniol_CAG Podem fer alguna cosa per evitar els impactes del canvi climàtic sobre els recursos hídrics. Què podem fer? HO podem integrar en l'estudi de gestió dels hàbitats de ribera?? Mirar què han fet altres espais. | S31: *Concertació amb els titulars de concessions d'aigua per a la implantació de cabals ecològics. ACA *Implementació dels cabals ecològics segons marc normatiu del Pla de gestió de l'Aigua (2016-2021) i aplicació de les mesures del capítol A1.Cabals manteniment.aCA | V31: 1) Realització estudi hidrogeològic 2) Establiment de punts de control 3) Signatura acords de custòdia | W31: 1) 1 2) 1 3) 1 | X31: 1) 1 2) 2 3) 1 | Y31: x | Z31: x | AA31: x | AB31: x | AC31: x | AD31: 40
F32: 03.3.2 | G32: Vetllar per la regulació dels dragatges, canalitzacions o implantació d'activitats extractives que puguin modificar la llera i el cabal dels rius | H32: Específic | I32: Optatiu | L32: =G32 -> Vetllar per la regulació dels dragatges, canalitzacions o implantació d'activitats extractives que puguin modificar la llera i el cabal dels rius | M32: No tenim capacitat ni som competents | Q32: Objectiu descartat per falta de capacitat o competències | S32: *Els instruments de planificació i ordenació dels espais naturals protegits no admeten la realització de canvis en la morfologia de les lleres on l'hàbitat 6430 és present. Contrastar amb en Guifré *Els instruments de planificació i ordenació dels espais naturals protegits regulen aquelles activitats que puguin generar una alteració del sistema exo-endocàrstic (extracció o alteració del curs d'aigua subterrània, etc.).Contrastar amb en Guifré. | AD32: 0
F33: 03.3.3 | G33: Avaluar i controlar les actuacions que produeixin drenatges, captacions o que puguin impedir l’arribada d’aigua tant superficial com freàtica | H33: Específic | I33: Optatiu | L33: =G33 -> Avaluar i controlar les actuacions que produeixin drenatges, captacions o que puguin impedir l’arribada d’aigua tant superficial com freàtica | M33: No tenim capacitat ni som competents | Q33: Objectiu descartat per falta de capacitat o competències | S33: *Els instruments de planificació i ordenació dels espais naturals protegits regulen les actuacions que requereixen drenatges, captacions i altres usos de les masses d'aigua o que puguin impedir l’arribada d’aigua tant superficial com freàtica afectant a la conservació d'hàbitats i espècies d'interès comunitari aquàtics o litorals.si *Establiment de procediments de concertació amb els titulars de concessions d'aigua per determinar els drets d'ús i els efectes sobre la conservació del patrimoni natural de les mateixes.ACA ho te establerts. *Avaluació de les actuacions que requereixen drenatges, captacions i altres usos de les masses d'aigua o que puguin impedir l’arribada d’aigua tant superficial com freàtica afectant a la conservació dels elements d'interès comunitari.ACA en fa seguiment, | AD33: 0
F34: 03.3.4 | G34: Vetllar pel compliment de la normativa de depuració dels efluents agroramaders, urbans i industrials que s'aboquen als cursos fluvials | H34: Específic | I34: Optatiu | L34: =G34 -> Vetllar pel compliment de la normativa de depuració dels efluents agroramaders, urbans i industrials que s'aboquen als cursos fluvials | N34: Impuls-Suport | O34: Si | P34: ALTA | Q34: Suport als Ajuntaments per agilitzar la construcció dels sistemes de depuració de nuclis urbans (Beget, Albanyà i Sant Llorenç de la Muga)_CAG | R34: * Suport als Ajuntaments per agilitzar la construcció dels sistemes de depuració de nuclis urbans (Beget, Albanyà i Sant Llorenç de la Muga_CAG * Acord de custòdia fluvial a la conca de la Muga_CAG | S34: *Augment dels sistemes de depuració i tractament d'aigües per garantir les condicions fisicoquímiques de l'aigua a través de l'aplicació de les mesures dels capítols C1 i C2 del Programa de Mesures del Pla de gestió de l'Aigua de l'ACA. Es fa donant suport als AJuntaments. | V34: 1) Redacció del projecte executiu per part de l'organisme competent | W34: 1) 1 | X34: 1) 1 | Y34: x | Z34: x | AA34: x | AD34: 32
D35: 03.4 | E35: Incrementar el patrimoni públic destinat a la conservació i millora del patrimoni natural | F35: 03.4.1 | G35: Identificar espais prioritaris per a la compra de terrenys de més valor dins l'ENP | H35: Comú | I35: Optatiu | K35: SENP/SPEN: Facilitar els criteris a seguir | L35: =G35 -> Identificar espais prioritaris per a la compra de terrenys de més valor dins l'ENP | N35: Realitzat | O35: Si | P35: ALTA | Q35: Objectiu operatiu assolit, sense mesures continuïstes en el termini del present Pla estratègic | R35: Realitzat juntament amb la DGPA | S35: *Compra (o adquisició de drets de tala) de rodals madurs, premadurs, o amb agrupacions d’arbres grans, vells, morts en peu, amb abundància de cavitats. També s'hi inclouen boscos singulars per raons biogeogràfiques o d'escassetat. Pendent de la DG, està previst al PPAG | Y35: x | AD35: 0
F36: 03.4.2 | G36: Identificar espais prioritaris per a la gestió directa | H36: Comú | I36: Optatiu | K36: SENP/SPEN: Facilitar els criteris a seguir | L36: =G36 -> Identificar espais prioritaris per a la gestió directa | N36: Realitzat | O36: Si | P36: BAIXA | Q36: Objectiu operatiu assolit, sense mesures continuïstes en el termini del present Pla estratègic | R36: * Millores en l'adequació del campanar de Santa Cecília com a punt de refugi d'espècies de quiròpters_CAG (demanara en Xevi si considera necessari extendre a altres punts amb algun mètode) Realitzat juntament amb la DGPA | S36: *Adequació d'alguna edificació de propietat pública com a refugi de Rhinolophus ferrumequinun, preferiblement propers a llacunes. Es va fer a sant cecilia. Valorar si cal extendre a altres punts. *Actuacions de restauració dels indrets més degradats dels hàbitats o les àrees amb presència d'espècies d'interès comunitari en zones de prats i pastures en base a una identificació i valoració de l'estat de conservació. Estudi estat ecològic de prats. No l'aplicaria en aquest obkectiu propiament, hi ha més adients. *Actuacions de restauració dels indrets més degradats dels hàbitats o les àrees amb presència d'espècies d'interès comunitari en zones forestals en base a una identificació i valoració de l'estat de conservació. Millora de la senyalitzacio de l' l'itinerari de MOnars per evitar el senderimse dispers. *Delimitació de zones de protecció al voltant de les àrees forestals més ben conservades de determinats hàbitats d'interès comunitari per l'esmorteïment de possibles impactes. les zones forestals benconservades son poc freqüentades. Actuar en cas d'incidències recurrents. | Y36: x | AD36: 0
A37: CULTURA | B37: 4 | C37: CONSERVAR ELS ELEMENTS CULTURALS materials i immaterials vinculats a la natura | D37: 04.1 | E37: Millorar el coneixement disponible sobre el patrimoni arquitectònic i cultural (material i immaterial) vinculat al patrimoni natural, el seu estat de conservació i els estils propis dels territoris de l'ENP | F37: 04.1.1 | G37: Elaborar l'inventari i cartografia de patrimoni cultural de l'ENP, que també inclogui el patrimoni etnològic i immaterial | H37: Comú | I37: Optatiu | L37: =G37 -> Elaborar l'inventari i cartografia de patrimoni cultural de l'ENP, que també inclogui el patrimoni etnològic i immaterial | N37: Sí | O37: Si | P37: MITJANA | Q37: Recull del patrimoni etnològic i cultural immaterial més rellevant a l'ENPAG_CAG | R37: * Inventari de patrimoni cultural immaterial (metodologia de la UNESCO)_CAG (en cas de disposar de POCTEFA) (el material ja està realitzat) - llegendes, rondalles i vocabulari específic i patrimoni musical- * Identificació de les fórmules de maneig tradicional del bestiar en el context del projecte de la FPC de Foc i Biodivesitat_CAG | U37: *Inventari de les mines, els forns de calç, les teuleries, les antigues pedreres, les fargues, etc. En curs | V37: 1) Realitzacio del recull de patrimoni etnològic i cultural immaterial | W37: 1) 1 | X37: 1) 1 | AA37: x | AD37: 200
F38: 04.1.2 | G38: Elaborar el catàleg lingüístic (localismes) de patrimoni natural, geografia popular, festes i activitats tradicionals de l'ENP | H38: Comú | I38: Optatiu | L38: =G38 -> Elaborar el catàleg lingüístic (localismes) de patrimoni natural, geografia popular, festes i activitats tradicionals de l'ENP | M38: Inclòs a l'anterior | P38: MITJANA | Q38: Accions recollides en altres objectius operatius | R38: Valorar si es pot posar en l'anterior | AD38: 0
F39: 04.1.3 | G39: Elaborar la cartografia de la xarxa de camins ramaders i senders tradicionals de l'ENP | H39: Comú | I39: Optatiu | L39: =G39 -> Elaborar la cartografia de la xarxa de camins ramaders i senders tradicionals de l'ENP | N39: Realitzat | O39: Si | P39: BAIXA | Q39: Actualització de la xarxa de camins tradicionals de l'ENP_CAG | R39: * Instar els Ajuntaments a que facin els corresponents catàlegs de camins públics. | U39: *Manteniment de la ruta transhumant | V39: 1) Cartografia de la xarxa de camins 2) Kms amb manteniment per part del CAG | W39: 1) 1 2) 100 | X39: 1) 1 2) 200 | Y39: x | AD39: 60
D40: 04.2 | E40: Conservar i gestionar el patrimoni cultural de l'ENP de forma coordinada amb els agents responsables i entitats de referència | F40: 04.2.1 | G40: Identificar els ens de referència en patrimoni cultural (entitats, associacions, museus i ecomuseus, etc.) en l'àmbit de l'ENP | H40: Comú | I40: Obligatori | L40: =G40 -> Identificar els ens de referència en patrimoni cultural (entitats, associacions, museus i ecomuseus, etc.) en l'àmbit de l'ENP | N40: Sí | P40: BAIXA | Q40: Revisió periòdica de la llista d'ens de referència en patrimoni cultural_CAG | V40: 1) Nombre de revisions realitzades | W40: 1) 1 | X40: 1) 2 | Y40: x | AB40: x | AD40: 20
F41: 04.2.2 | G41: Articular treballs conjunts entre l'ENP i representants, gestors o custodis del patrimoni cultural per a la seva protecció i millora | H41: Comú | I41: Optatiu | L41: =G41 -> Articular treballs conjunts entre l'ENP i representants, gestors o custodis del patrimoni cultural per a la seva protecció i millora | N41: Sí | O41: Si | P41: ALTA | Q41: Signatura de convenis amb entitats de conservació del patrimoni cultural_CAG Impulsar formació en matèria de pedra seca_CAG | R41: * Signatura d'un conveni amb els Amics de Sant Aniol_CAG * Formació en matèria de pedra seca en el marc de la TVAPO i paral·lelament amb la FES i IES Garrotxa_CAG | V41: 1) Signatura de convenis 2) Edicions de formació en mat de pedra seca | W41: 1) 1 2) 1 | X41: 1) 2 2) 2 | Y41: x | Z41: x | AA41: x | AD41: 160
F42: 04.2.3 | G42: Coordinar i participar dels treballs de restauració arquitectònica i del patrimoni cultural | H42: Comú | I42: Optatiu | L42: =G42 -> Coordinar i participar dels treballs de restauració arquitectònica i del patrimoni cultural | N42: Sí | O42: No | P42: ALTA | Q42: Neteja d'elements de patrimoni cultural_CAG Accions de manteniment i recuperació de camins tradicionals_CAG Accions de conservació de parets i estructures de pedra seca_CAG | R42: * Accions per a la conservació de parets i estructures de pedra seca_CAG | U42: *Adequació de la rectoria de Sant Aniol | V42: 1) Accions de neteja d'elements de patrimoni cultural 2) Trams recuperats o restaurats 3) Millores sobre estructures de pedra seca | W42: 1) 5 2) 1 3) 1 | X42: 1) 10 2) 2 3) 2 | Y42: x | Z42: x | AA42: x | AB42: x | AC42: x | AD42: 120
F43: 04.2.4 | G43: Disposar de personal especialitzat en patrimoni cultural | H43: Comú | I43: Obligatori | L43: =G43 -> Disposar de personal especialitzat en patrimoni cultural | N43: No | O43: Si | P43: MÀXIMA | Q43: Dotació al CAG de personal especialitzat en patrimoni cultural_DGPA | R43: * Dotar el Consorci de personal especialitzat_DGPA | V43: 1) Personal especialitzat en patrimoni cultural | W43: 1) 1 | X43: 1) 2 | Z43: x | AA43: x | AB43: x | AC43: x | AD43: 0
D44: 04.3 | E44: Potenciar la conservació i recuperació del patrimoni cultural material i immaterial de l'ENP | F44: 04.3.1 | G44: Recuperar i conservar el patrimoni cultural rural immaterial associat a les activitats i aprofitaments tradicionals | H44: Comú | I44: Obligatori | J44: MAP | L44: =G44 -> Recuperar i conservar el patrimoni cultural rural immaterial associat a les activitats i aprofitaments tradicionals | N44: Sí | P44: MITJANA | Q44: Celebració d'una jornada d'activitats tradicionals de la Garrotxa_CAG i PNZVG | R44: Aplec de Sant Aniol | V44: 1) Jornades | W44: 1) 1 | X44: 1) 2 | AB44: x | AD44: 50
F45: 04.3.2 | G45: Recuperar i conservar el patrimoni cultural rural vinculat específicament a construccions de pedra en sec | H45: Específic | I45: Obligatori | J45: MAP | L45: =G45 -> Recuperar i conservar el patrimoni cultural rural vinculat específicament a construccions de pedra en sec | N45: Sí | P45: MITJANA | Q45: Accions de conservació de parets i estructures de pedra seca_CAG | R45: * Accions per a la conservació de parets i estructures de pedra seca_CAG Millores específiques a Lliurona | S45: *Actuacions de conservació i recuperació dels murs de pedra seca. | V45: 1) Millores sobre estructures de pedra seca | W45: 1) 1 | X45: 1) 2 | Y45: x | Z45: x | AA45: x | AB45: x | AC45: x
F46: 04.3.3 | G46: Fomentar la recuperació i conservació de l'arquitectura tradicional d'intrès de les edificacions i construccions | H46: Comú | I46: Optatiu | L46: =G46 -> Fomentar la recuperació i conservació de l'arquitectura tradicional d'intrès de les edificacions i construccions | M46: No tenim capacitat ni som competents | Q46: Objectiu descartat per falta de capacitat o competències | AD46: 0
F47: 04.3.4 | G47: Identificar i conservar la diversitat domesticada de varietats agrícoles i ramaderes locals | H47: Comú | I47: Obligatori | J47: ESNATURA | L47: =G47 -> Identificar i conservar la diversitat domesticada de varietats agrícoles i ramaderes locals | N47: Impuls-Suport | O47: Si | P47: MÀXIMA | Q47: Dotació al CAG de personal especialitzat en l'àmbit agrari_DGPA | R47: * Suport al pagament per serveis ambientals que està articulant la DGPA, fomentant espècies de pota petita_CAG | V47: 1) Personal especialitzat en patrimoni cultural | W47: 1) 1 | X47: 1) 2 | Z47: x | AA47: x | AB47: x | AC47: x | AD47: 0
D48: 04.4 | E48: Donar a conèixer els elements culturals com a valors del paisatge de l'ENP en les activitats d'ús públic | F48: 04.4.1 | G48: Integrar el patrimoni cultural als itineraris i cartelleria de l'ENP. | H48: Comú | I48: Obligatori | L48: =G48 -> Integrar el patrimoni cultural als itineraris i cartelleria de l'ENP. | N48: Sí | O48: Si | P48: MITJANA | Q48: Integració progressiva dels elements de patrimoni cultural als fulletons d'itineraris_CAG Recuperació de camins transfronterers_CAG Foment i manteniment d'una xarxa d'itineraris amb la Catalunya Nord_CAG | R48: * Integració d'aquests elements en els nous itineraris_CAG Integració del patrimoni cultural a l'exposició de la Rectoria_CAG | V48: 1) Nombre de fulletons amb referència al patrimoni cultural | W48: 1) 2 | X48: 1) 4 | Y48: x | Z48: x | AD48: 60
F49: 04.4.2 | G49: Incorporar el patrimoni cultural en els plans d’ús públic i educació ambiental per fomentar-ne la seva conservació i divulgació. | H49: Comú | I49: Obligatori | L49: =G49 -> Incorporar el patrimoni cultural en els plans d’ús públic i educació ambiental per fomentar-ne la seva conservació i divulgació. | N49: Sí | O49: Si | P49: MÀXIMA | Q49: Integració del patrimoni cultural en el PUP G i AG, en el disseny d'activitats i en els centres d'informació de l'ENPAG_CAG | R49: * Conveni amb els Amics de Sant Aniol (Rectoria de Sant Aniol) i l'Ajuntament de Sales de Llierca (Rectoria de Sant Grau) per donar usos amb caràcter d'ús públic a aquestes edificacions_CAG * Adquisició de la Rectoria de Sadernes com a centre interpretació i acollida de l'ENPAG_CAG | U49: *Potenciar els valors naturals i culturals de la comarca i de l'espai com a oferta per als visitants fet | V49: 1) Integració de l'eix cultural en aquestes iniciatives | W49: 1) 1 | X49: 1) 3 | Y49: x | Z49: x | AA49: x | AB49: x | AC49: x | AD49: 100
F50: 04.4.3 | G50: Formar el personal dels punts d’informació en els valors culturals de l'ENP | H50: Comú | I50: Obligatori | L50: =G50 -> Formar el personal dels punts d’informació en els valors culturals de l'ENP | N50: Sí | O50: Si | P50: ALTA | Q50: Integració del patrimoni cultural en el Curs per al bon coneixement de la Garrotxa i en la formació continua que es fa amb la FES en el marc del desplegament de la Carta Europea de Turismse Sostenible_CAG | R50: * Integració del patrimini cultural en el Curs per al bon coneixement de la Garrotxa i en la formació continua que es fa amb la FES en el marc del desplegament de la Carta Europea de Turismse Sostenible_CAG | V50: 1) Sessions formatives sobre patrimoni cultural | W50: 1) 1 | X50: 1) 4 | Y50: x | Z50: x | AA50: x | AB50: x | AC50: x | AD50: 50
B51: 5 | C51: PROTEGIR EL PAISATGE i la qualitat de l'ambient visual, sonor i lumínic. | D51: 05.1 | E51: Identificar els elements d'interès paisatgístic de l'espai | F51: 05.1.1 | G51: Elaborar un inventari d'elements d'interès paisatgístic de l'ENP d'acord amb el Catàleg de paisatge de la zona | H51: Comú | I51: Optatiu | L51: =G51 -> Elaborar un inventari d'elements d'interès paisatgístic de l'ENP d'acord amb el Catàleg de paisatge de la zona | M51: Realitzat, existeix la Carta del Paisatge de l'Alta Garrotxa (Observatori del Paisatge) | N51: Realitzat | O51: Si | P51: MITJANA | Q51: Objectiu operatiu assolit, sense mesures continuïstes en el termini del present Pla estratègic | R51: * En el Catàleg del Paisatge de les Comarques Gironines es defineix la Unitat paisatgística de l’Alta Garrotxa, per la que presenta uns objectius de qualitat paisatgística i una proposta de mesures (criteris) i accions específiques, identificant els elements clau. De la mateixa manera el PPAG estableix cartogràficament les zones de fragilitat paisatgística i a l'Annex 3 de la memòria estableix els Elements d’interès paisatgístic i cultural de l’espai. | Y51: x | AD51: 0
D52: 05.2 | E52: Millorar la qualitat paisatgística | F52: 05.2.1 | G52: Desplegar actuacions de restauració dels elements d'interès paisatgístic degradats | H52: Comú | I52: Optatiu | L52: =G52 -> Desplegar actuacions de restauració dels elements d'interès paisatgístic degradats | N52: Sí | P52: MITJANA | Q52: Seguiment amb l'organisme competent i el SPENP de l'estat de les restauracions de les explotacions extractives_CAG | V52: 1) Identificació de les explotacions amb data de caducitat propera i estat | W52: 1) 1 | X52: 1) 1 | AA52: x | AD52: 20
F53: 05.2.2 | G53: Gestionar l'abandonament d'infraestructures i instal·lacions amb impactes sobre els valors de l'espai | L53: =G53 -> Gestionar l'abandonament d'infraestructures i instal·lacions amb impactes sobre els valors de l'espai | M53: No tenim capacitat ni som competents | Q53: Objectiu descartat per falta de capacitat o competències | AD53: 0
F54: 05.2.3 | G54: Minimitzar la brutícia, deixalles, vandalisme i males praxis dins l'ENP | H54: Comú | I54: Obligatori | L54: =G54 -> Minimitzar la brutícia, deixalles, vandalisme i males praxis dins l'ENP | N54: Sí | O54: Si | P54: MÀXIMA | Q54: Servei de neteja i manteniment d'infraestructures de l'ENPAG_CAG Difusió de Bones pràctiques a través de diferents mitjans_CAG | R54: Servei de neteja i manteniment d'infraestructures de l'ENPAG_CAG | V54: 1) Hores destinades a manteniment i neteja 2) Integració de BBPP en material de difusió, cartelleria, etc. | W54: 1) 150 2) 2 | X54: 1)300€ 2) 4 | Y54: x | Z54: x | AA54: x | AB54: x | AC54: x | AD54: 110
D55: 05.3 | E55: Protegir la qualitat acústica i lumínica de l'ENP | F55: 05.3.1 | G55: Promoure la certificació de qualitat del cel nocturn | H55: Específic | I55: Optatiu | J55: ESNATURA | L55: =G55 -> Promoure la certificació de qualitat del cel nocturn | N55: Sí | O55: Si | P55: MITJANA | Q55: Integració de la certificació de qualitat del cel nocturn a la CETS Garrotxa durant la renovació prevista per al 2025_CAG | R55: * Integració de la certificació de qualitat del cel nocturn a la CETS Garrotxa durant la renovació prevista per al 2025_CAG Realitzat al nucli Albanyà. | T55: *Promoció de les declaracions de cel nocturn en curs | V55: 1) Accions realitzades per promoure la certificació de qualitat del cel nocturn | W55: 1) 1 | X55: 1) 3 | AB55: x | AC55: x | AD55: 80
F56: 05.3.2 | G56: Promoure la certificació de zones d'especial protecció de la qualitat acústica | H56: Específic | I56: Optatiu | J56: ESNATURA | L56: =G56 -> Promoure la certificació de zones d'especial protecció de la qualitat acústica | N56: Sí | P56: MITJANA | Q56: Integració de la certificació de zones d'especial protecció dela qualitat acústica a la CETS Garrotxa durant la renovació prevista per al 2025_CAG | R56: * Integració de la certificació de zones d'especial protecció dela qualitat acústica a la CETS Garrotxa durant la renovació prevista per al 2025_CAG | T56: *Promoció de les zones d’especial protecció de la qualitat acústica en curs | V56: 1) Accions realitzades per promoure la certificació de qualitat acústica | W56: 1) 1 | X56: 1) 3 | AB56: x | AC56: x | AD56: 70
A57: CONEIXEMENT | B57: 6 | C57: MILLORAR EL CONEIXEMENT DE L'ENTORN, del patrimoni natural, cultural i social. | D57: 06.1 | E57: Identificar els objectes de gestió prioritària de l'ENP en el marc dels objectius de govern | F57: 06.1.1 | G57: Identificar i prioritzar els elements clau i d'interès per la gestió de la biodiversitat i geodiversitat de Catalunya es troben dins l'ENP (especies amenaçades, espècies exòtiques invasores,.. ) | H57: Comú | I57: Obligatori | J57: Directriva Habitats Carta emplaçament ESNATURA Catàlegs | K57: UIC/SFF/SPEN: Definir criteris d'identificació d'elements interès. UIC/SFF/SPEN: Definició dels objectes de conservació clau comuns a nivell de Xarxa d'ENP o clúster territorial | L57: =G57 -> Identificar i prioritzar els elements clau i d'interès per la gestió de la biodiversitat i geodiversitat de Catalunya es troben dins l'ENP (especies amenaçades, espècies exòtiques invasores,.. ) | M57: Realitzat durant la confecció del PPAG, la geoestratègia i revisat amb el MAP i el Pla Estratègic (pestanya "Priorització"). | N57: Realitzat | O57: Si | P57: MÀXIMA | Q57: Objectiu operatiu assolit, sense mesures continuïstes en el termini del present Pla estratègic | R57: Realitzat durant la confecció del PPAG i revisat amb el MAP i el Pla Estratègic. | S57: *Realització d'un inventari i catàleg de coves que diagnostiqui i analitzi el seu estat de conservació. Inventari realtizat. Parlar amb enllorenç si cal un estudi exhausitiu de l'estat de consevaicó. Què diu l'estratègia al respecte? | U57: *Inventari-catàleg actualitzat de les coves, avencs, gorges i congostos en curs *Elaboració de fitxes dels punts i les zones per l’inventari d'elements geològics fet | Y57: x | AD57: 0
F58: 06.1.2 | G58: Definir espais fràgils i zones d'especial atenció | H58: Comú | I58: Obligatori | K58: SPEN: Inventari i cartografia d'espais fràgils i zones d'especial atenció | L58: =G58 -> Definir espais fràgils i zones d'especial atenció | M58: Realitzat durant la confecció del PPAG | N58: Realitzat | O58: Si | P58: MÀXIMA | Q58: Objectiu operatiu assolit, sense mesures continuïstes en el termini del present Pla estratègic | R58: Realitzat durant la confecció del PPAG. | S58: *Identificació dels indrets més representatius dels hàbitats i espècies d'interès comunitari, millora de la cartografia i valoració del seu estat de conservació. Revisió de la cartgografia amb els estudis que es facin. *Actualització de les Reserves Naturals Fluvials. Just ho està fent l'ACA i estem ajudant les empreses adjudicatàries amb la informació i coneixement del que disposem. *Estudi sobre l'interès relatiu per a la biodiversitat de les representacions locals dels prats d'interès comunitari, en particular 6420, amb l'objectiu de prioritzar la gestió dels indrets més rellevants. Tenim estudi hàbitats, revisar si identifica espècies. | Y58: x | AD58: 0
D59: 06.2 | E59: Conèixer l'estat de conservació i la seva tendència dels hàbitats, les espècies els elements de la gea i els processos ecològics com a eina per avaluar i optimitzar la gestió | F59: 06.2.1 | G59: Participar en l'elaboració de la cartografia que elabora la UIC | H59: Comú | I59: Obligatori | J59: ESNATURA | K59: UIC: Coordinar i contractar l'elaboració de la cartografia | L59: =G59 -> Participar en l'elaboració de la cartografia que elabora la UIC | N59: Impuls-Suport | O59: Si | P59: ALTA | Q59: Trasllat de la cartografia de l'ENPAG a la UIC segons protocol que defineixi la Unitat (actualment en elaboració)_CAG | R59: Traslladat de la cartografia de l'ENPAG a la UIC segons protocol que defineixi la Unitat (actualment en elaboració)_CAG | S59: *Adaptació i integració de la cartografia dels hàbitats fluvials. Cartografia dels hàbitats fluvials de les Reserves Naturals Fluvials. Ho farem a través estudi de cartografia xarxa fluvial. *Inventaris i cartografia fina dels hàbitats 81XX i impulsar estudis sobre la dinàmica geomorfològica i morfodinàmica de les roques. Ja els tenim cartografiats. Valorar que diu estratègia sobre l'estudi de tarteres, es prioritari fer seguiment de la seva evolucó,. cal posar específicament o ho posem en el marc del seguiment de l'estratègia. *Cartografia de detall de les torberes i comunitats fontinals dins espai de la xarxa Natura 2000 (7110,7140,7220, 7230, 7240). realitzat estudi hàbitat. *Millora de la cartografia a petita escala de les àrees de presència d'hàbitats d'interès comunitari. La tenim ja a escala 1:10,000 | U59: *Cartografia i caracterització de les formacions de travertí de la Vall de Sant Aniol fet *Cartografia de punts d’interès geològic del sector de Lliurona, Albanyà i Bac Grillera fet *Cartografia a 1:10.000 de les tarteres | V59: 1) Nombre de capes integrades al SIG corporatiu, a instàncies de la UIC | W59: 1) 4 | X59: 1) 6 | Z59: x | AA59: x | AB59: x | AC59: x | AD59: 150
F60: 06.2.2 | G60: Conèixer i estudiar els processos naturals propis de l’espai, la seva funcionalitat, i ecologia en referència als ecosistemes | H60: Comú | I60: Obligatori | L60: Conèixer i estudiar els elements i processos naturals propis de l’espai, la seva tendència, funcionalitat, i ecologia, per al desenvolupament d'accions de gestió i conservació | N60: Sí | O60: Si | P60: MITJANA | Q60: Foment i coordinació estudis sobre la polinització, el funcionament de les xarxes tròfiques (l'herbivoria, depredadors, etc. ), i la hidrogeologia de l'ENPAG_CAG i DGPA | R60: * Suport al desenvolupament del projecte de renaturalització del PPAG_CAG * Seguiment de l'estat ecològic dels prats en el marc de les accions del projecte de FPC sobre foc i biodiversitat_CAG * Suport a la UdG en el seguiment de grups de fauna en el marc del projecte de FPC sobre foc i biodiversitat_CAG * Segona fase de l'estudi de polinització_CAG * Seguiment sobre l'evolució de l'hàbitat 8130 (tarteres). contrastar al'estratègia de geoconservació si és prioritari._CAG * Inspecció visual dels itineraris i el seu entorn per valorar processos erosius per hiperfreqüentació_CAG | S60: TOT INTEGRAT AL PLA DE SEGUIMENT DE LA BIODIVERSITAT DE L'ALTA GARROTXA. no crec que correspongui específicament amb aquest objectiu *Estudis sobre l'estatus i l'ecologia dels ocells d'interès comunitari. *Estudis sobre l’estatus i ecologia dels rats-penats. *Estudis sobre l’estatus i ecologia de les espècies de fauna d'interès comunitari. *Estudis sobre l’estatus, distribució i biologia de les espècies d'invertebrats d'interès comunitari. *Estudis per a la millora del coneixement de la especificitat alimentícia de l'eruga d'Euphydryas aurinia i de selecció de l'hàbitat. *Estudi sobre l’ecologia dels hàbitats dels quals no es té prou informació i el seu estat de conservació. *Seguiment del grau de regeneració i fertilitat de les comunitats de 4090, 5130 i 5210 per detectar possibles canvis deguts al canvi climàtic. | T60: *Millora del coneixement sobre els valors de l’espai i el sistema de seguiment d’aquests | U60: *Estudi de l’origen dels granits *Descripció de l’estratigrafia del Cambroordovicià *Caracterització geològica de les mineralitzacions *Estudi sobre pol·linitzadors de l'Alta Garrotxa | V60: 1) Nombre d'estudis/seguiments de processos realitzats | W60: 1) 1 | X60: 1) 2 | AD60: 100
F61: 06.2.3 | G61: Conèixer els usos i factors de canvi rellevants en l'evolució dels elements de conservació, i avaluar els efectes que generen en l’espai (pressions i amenaces) | H61: Comú | I61: Obligatori | J61: ESNATURA | K61: SENP/UIC: Elaborar la classificació i cartografia de les pressions o factors de canvi sobre el medi natural | L61: =G61 -> Conèixer els usos i factors de canvi rellevants en l'evolució dels elements de conservació, i avaluar els efectes que generen en l’espai (pressions i amenaces) | N61: Impuls-Suport | O61: Si | P61: MITJANA | Q61: Estudi sobre l'impacte del canvi climàtic als boscos de l'ENPAG en el marc del CP entre la DGPA i CREAF_DGPA Identificació dels impactes de l'ús públic sobre els valors de l'ENPAG_CAG Seguiment de l'estat ecològic dels prats en el marc de les accions del projecte de FPC sobre foc i biodiversitat_CAG | R61: Aquest bloc i anterior els confonc. Contrastar Guifré si la classififació es bona. * Estudi sobre la hidrogeologia de l'ENPAG en el marc del CP entre la DGPA i l'ICGC_DGPA * Estudi sobre l'impacte del canvi climàtic als boscos de l'ENPAG en el marc del CP entre la DGPA i CREAF_DGPA * Col·laboració amb la UIC per al trasllat de la informació sobre factors de canvi_CAG | S61: *Estudi de l’efecte de la pastura i els incendis en els matollars d'interès comunitari. Estudi de seguiment de flora i fauna en el marc dle projecte de FPC. *Avaluació de l'afectació de les furgades dels porcs senglars en relació amb la fertilitat del sòl i la composició florística. No prioritari en HIC, però si en flora. Quan es fan els estudis ja es té en compte. *Seguiment dels nivells d'erosió d'hàbitats d'interès comunitari a causa de la freqüentació humana. Inspeccions visuals al COmanegra per l'itinerari. | T61: *Millora del coneixement sobre els factors de canvi que es donen a l’espai i els efectes que generen, i sistema de seguiment d’aquests. | U61: *Recull de la memòria històrica dels hidrocarburs (conceptes de canvi climàtic) *Cartografia del perill de despreniments i esllavissades de les zones més freqüentades (població local o visitant) *Alteració i erosió d’unitats geològiques | V61: 1) Realització de l'estudi de CC 2) Identificació impactes clau 3) Prats amb seguiment | W61: 1) 1 1) 4 3) 5 | X61: 1) 1 2) 6 3) 8 | Y61: x | Z61: x | AA61: x | AB61: x | AC61: x | AD61: 100
F62: 06.2.4 | G62: Conèixer l'impacte de les gestió de l'aigua, sobre la biodiversitat. | H62: Comú | I62: Optatiu | L62: =G62 -> Conèixer l'impacte de les gestió de l'aigua, sobre la biodiversitat. | N62: Impuls-Suport | O62: Si | P62: ALTA | Q62: Estudi i seguiment sobre la hidrogeologia de l'ENPAG en el marc del CP entre la DGPA i l'ICGC_DGPA | R62: * Estudi i seguiment sobre la hidrogeologia de l'ENPAG en el marc del CP entre la DGPA i l'ICGC_DGPA El primer model hidrogeològic de l'espai ja ha estat realitzat per part del CAG. | U62: *Seguiment de les surgències d’aigua | V62: 1) Realització estudi hidrogeològic | W62: 1)1 | X62: 1) 1 | Z62: x | AA62: x
F63: 06.2.5 | G63: Participar en el coneixement de la tendència d'espècies plaga amb afectacions sobre ecosistemes o activitats econòmiques dins l'ENP | H63: Comú | I63: Optatiu | L63: =G63 -> Participar en el coneixement de la tendència d'espècies plaga amb afectacions sobre ecosistemes o activitats econòmiques dins l'ENP | N63: Impuls-Suport | O63: Si | P63: BAIXA | Q63: Participació en dels estudis de les autoritats competents_CAG | R63: *Participació en dels estudis de les autoritats competents | S63: *Foment de la investigació per trobar noves mesures de lluita biològica contra la processionària del pi que no afectin a altres lepidòpters, com Graellsia isabelae. Competència Agents Rurals. | V63: 1) Participació a petició de l'òrgan competent | W63: 1) 1 | X63: 1) 1 | AB63: x | AC63: x | AD63: 10
F64: 06.2.6 | G64: Conèixer la tendència d'espècies exòtiques invasores amb afectacions sobre ecosistemes o activitats econòmiques dins l'ENP | H64: Comú | I64: Obligatori | J64: ESNATURA | L64: =G64 -> Conèixer la tendència d'espècies exòtiques invasores amb afectacions sobre ecosistemes o activitats econòmiques dins l'ENP | N64: Sí | O64: Si | P64: ALTA | Q64: Treball de camp pel seguiment i cerca de nous rodals d'Ailanthus altissima_CAG Participació en el disseny d'una prova pilot per la control de seneci a l'Alta Garrotxa_SFF i CAG | R64: * Control de les poblacions d'Ailanthus altissima_CAG * Disseny d'una prova pilot per la control de seneci a l'Alta Garrotxa_SFF i CAG | V64: 1) Intervenció en punts/rodals de l'espai | W64: 1) 2 | X64: 1) 4 | Y64: x | Z64: x | AA64: x | AB64: x | AC64: x | AD64: 50
F65: 06.2.7 | G65: Coneixer com millorar la connectivitat de forma coordinada amb altres ENP | H65: Comú | I65: Optatiu | J65: ESNATURA | L65: =G65 -> Coneixer com millorar la connectivitat de forma coordinada amb altres ENP | M65: Es descarta perquè tenim espais contigus sense grans barreres/infraestructures artificials | O65: No | P65: FORA DEL TERMINI DEL PLA | Q65: Objectiu fora de termini del present Pla estratègic | R65: Decidir amb capceleres i zona volcànica si volem fer alguna actuació en aquest sentit. | AD65: 0
D66: 06.3 | E66: Estandaritzar els seguiments periòdics dels grups clau | F66: 06.3.1 | G66: Participar en la definició del sistema estàndard de seguiment de flora, fauna i hàbitats de la DG | H66: Comú | I66: Obligatori | J66: ESNATURA | K66: UIC/SFF/SENP: Crear espais de participació UIC/SFF: Definir el sistema estàndard de seguiment i el protocol d'aplicació | L66: =G66 -> Participar en la definició del sistema estàndard de seguiment de flora, fauna i hàbitats de la DG | N66: Sí | O66: Si | P66: ALTA | Q66: Participació en el sistema de definció d'estàndards de seguiment per part de la UIC_CAG i DGPA | R66: * Participació en el sistema de definció d'estàndards de seguiment per part de la UIC_CAG Nuria, contactar amb UIC per veure en quin punt està. | V66: 1) Participació a petició de l'òrgan competent | W66: 1) 1 | X66: 1) 1 | AA66: x | AB66: x | AC66: x | AD66: 100
F67: 06.3.2 | G67: Adequar i executar el sistema de seguiment periòdic dels grups clau de l'ENP al sistema estàndard de seguiment | H67: Comú | I67: Obligatori | J67: ESNATURA | K67: UIC/SFF: Definir el sistema estàndard de seguiment i el protocol d'aplicació UIC: Elaborar el protocol d'informació i coneixement | L67: =G67 -> Adequar i executar el sistema de seguiment periòdic dels grups clau de l'ENP al sistema estàndard de seguiment | N67: Sí | O67: Si | P67: MÀXIMA | Q67: Seguiment de la població d'Aquila chrysaetos_CAG Participació en el SOCC, SEGRE, cens simultani de trencalòs_CAG Seguiment de les poblacions d'amfibis_CAG Realització de nous estudis de base o actualització dels existents de grups de fauna, flora amenaçada i hàbitats necessaris per dissenyar el Pla de seguiment de la biodiversitat de l'ENPAG_CAG i DGPA Disseny d'un Pla de seguiment de la biodiversitat específic per ENPAG (Pendent de l'estandarització de la DGPA_UIC patrimoni) | R67: * Disseny d'un Pla de seguiment de la biodiversitat específic per ENPAG prioritzant el que es detalla a continuació (detallar i eliminar del primer objecitu i l'excel de correspondència de la susana)_CAG | S67: TOT INTEGRAT AL PLA DE SEGUIMENT DE LA BIODIVERSITAT DE L'ALTA GARROTXA. *Establiment de programes de seguiment de les poblacions d'aus d'interès comunitari. *Establiment de programes de seguiment de les poblacions d'A. pallipes. *Seguiment de ropalòcers i quiròpters en el marc del SISEBIO. *Establiment de programes de seguiment de les espècies d'invertebrats d'interès comunitari. *Establiment de programes de seguiment de les poblacions de Macromia splendens, Oxygastra curtisii i Coenagrion mercuriale. *Establiment de programes de seguiment dels hàbitats d'interès comunitari. | U67: *Seguiment cada cinc anys de les tarteres (Bassegoda, Guitarriu, Montmajor, etc.) *Seguiment Dichoropetalum schottii i estudi demogràfic *Seguiment de Dryopteris remota i conservació de l'hàbitat *Seguiment de l’àliga daurada (Aquila chrysaetos) *Seguiment de les espècies presa de grans rapinyaires *Seguiment del trencalòs (Gypaetus barbatus) *Seguiment de rapinyaires a l’ENP (SEGRE) *Participació al Seguiment dels Ocells Comuns de Catalunya (SOCC) | V67: 1) Nombre d'espècies i hàbitats clau estudiats i incorporats al seguiment | W67: 1) 3 | X67: 1) 15 | Y67: x | Z67: x | AA67: x | AB67: x | AC67: x | AD67: 1100
F68: 06.3.3 | G68: Mantenir una base de dades de seguiment de patrimoni natural de l'ENP actualitzada i ordenada | H68: Comú | I68: Obligatori | L68: =G68 -> Mantenir una base de dades de seguiment de patrimoni natural de l'ENP actualitzada i ordenada | N68: Impuls-Suport | O68: Si | P68: MITJANA | Q68: Manteniment i actualització de la base de dades de l'ENP corresponent al Pla de seguiment de la Biodiversitat_CAG Aportació de dades a l'Observatori de Pnat (segons indicacions UIC)_CAG | R68: això ho ha de fer la UIC i nosaltres nodrir? | V68: 1) Nombre d'espècies i hàbitats clau estudiats i incorporats a la base de dades SINATCAT | W68: 1) 3 | X68: 1) 10 | AD68: 200
F69: 06.3.4 | G69: Participar en el grups de treball per a la definició i organització del SINATCAT | H69: Comú | I69: Obligatori | K69: UIC/SENP: Crear i coordinar una metodologia participativa per a la definició del SINATCAT | L69: Participar en el grups de treball per a la definició i organització del SINATCAT | N69: Sí | O69: Si | P69: ALTA | Q69: Participació en els grups de treball en el marc de la definició del SINATCAT a petició de la DGPA_CAG | R69: * Participació en els grups de treball en el marc de la definició del SINATCAT a petició de la DGPA_CAG | V69: 1) Percentatge de participació en els grups de treball i formacions | W69: 1) 50 | X69: 1) 80 | Z69: x | AA69: x | AB69: x | AC69: x | AD69: 200
D70: 06.4 | E70: Incrementar el coneixement de qualitat mitjançant l’establiment de marcs de col·laboració, assessorament i suport amb centres de recerca, museus i entitats naturalistes per al desenvolupament de part de la seva activitat en l’ENP | F70: 06.4.1 | G70: Crear sinèrgies i col·laborar amb museus i equipaments de referència per definir línies d'actuació conjunta entre patrimoni cultural i natural | H70: Comú | I70: Optatiu | K70: SENP: Elaborar un mapa d'agents de referència | L70: =G70 -> Crear sinèrgies i col·laborar amb museus i equipaments de referència per definir línies d'actuació conjunta entre patrimoni cultural i natural | N70: Sí | O70: Si | P70: MITJANA | Q70: Detecció d'organismes amb qui traçar linies de col·laboració per definir actuacions conjuntes entre patrimoni natural i cultural_CAGi DGPA | R70: * Identificació del centres museístics propers territorialment o per temàtiques per poder generar sinèrgies en revalorització del patrimoni natural i cultural (terra, Museu etnogràfic Ripoll, Espai Crater)_CAG i DGPA | U70: *Continuar treballant amb el "Pla d'Espais Museístics, d'espais d'interès natural i cultural" iniciat pel Parc Natural de la Zona Volcànica de la Garrotxa per a una millor interpretació del patrimoni. | V70: 1) Nombre de col·laboracions amb museus | W70: 1) 1 | X70: 1) 3 | AB70: x | AC70: x | AD70: 50
F71: 06.4.2 | G71: Establir acords amb les institucions de recerca i naturalistes per al desenvolupament d'estudis i inventaris dins l'ENP en el marc de les seves línies de recerca | H71: Comú | I71: Optatiu | K71: SENP: Elaborar un mapa d'agents de referècia | L71: =G71 -> Establir acords amb les institucions de recerca i naturalistes per al desenvolupament d'estudis i inventaris dins l'ENP en el marc de les seves línies de recerca | N71: Sí | O71: Si | P71: MITJANA | Q71: Elaboració d'un mapa d'institucions per col·laborar en l'àmbit de recerca i coneixement del territori_CAG Col·laboració amb UNiversitats per a la confecció de projectes i treballs de final de graus i màster_CAG Renovació/signatura de convenis amb institucions/centres de recerca amb objectius comuns_CAG | R71: * Elaboració d'un mapa d'institucions per col·laborar en l'àmbit de recerca i coneixement del territori_CAG * Col·laboració amb la UdG per a la confecció d'un projecte POCTEFA per revaloritzar el patrimoni cultural en ENPs_CAG * Renovació del conveni amb la Fundació Bionexus i amb en Centre Sostenibilitat Territorial_CAG | T71: *Col·laboracions amb centres de recerca i entitats naturalistes. | V71: 1) Nombre de col·laboracions amb institucions de recerca | W71: 1) 1 | X71: 1) 3 | Y71: x | Z71: x | AA71: x | AB71: x | AC71: x | AD71: 300
F72: 06.4.3 | G72: Potenciar la ciència ciutadana en l’ENP com a eina per generar coneixement | H72: Comú | I72: Optatiu | L72: =G72 -> Potenciar la ciència ciutadana en l’ENP com a eina per generar coneixement | N72: Sí | O72: Si | P72: BAIXA | Q72: Dinamització del voluntariat per a la realització de seguiments de biodiversitat_CAG | R72: * Col·laboració amb les iniciatives de ciència ciutadana en el projecte de Foc i biodiversitat de la FPC_CAG | V72: 1) Inciatives de voluntariat vinculades a la conservació i/o seguiment de la biodiversitat | W72: 1) 1 | X72: 1) 3 | AB72: x | AC72: x | AD72: 50
F73: 06.4.4 | G73: Crear i desenvolupar jornades de recerca de l'ENP de forma anual on els diferents centres mostrin els estudis realizats en l'ENP | H73: Comú | I73: Optatiu | K73: SENP: Suport en l'organització de les jornades | L73: =G73 -> Crear i desenvolupar jornades de recerca de l'ENP de forma anual on els diferents centres mostrin els estudis realizats en l'ENP | M73: No tenim capacitat | O73: Si | P73: FORA DEL TERMINI DEL PLA | Q73: Objectiu fora de termini del present Pla estratègic | R73: Proper pla estratègic si aconseguim pressupost minim per recerca- | AD73: 0
F74: 06.4.5 | G74: Posar a disposició de la recerca, equipaments i serveis de l'ENP | H74: Comú | I74: Optatiu | J74: ESNATURA | L74: =G74 -> Posar a disposició de la recerca, equipaments i serveis de l'ENP | N74: Sí | O74: No | P74: MITJANA | Q74: Gestió d'autoritzacions de pas, cessió puntual d'espais, etc._CAG | R74: * Adequació de la Rectoria de Sadernes i establiment de preus públics per l'acollida de personal de recerca_CAG | V74: 1) Nombre d'autoritzacions o cessions puntuals realitzades | W74: 1) 1 | X74: 1) 3 | Y74: x | Z74: x | AA74: x | AB74: x | AC74: x | AD74: 0
F75: 06.4.6 | G75: Crear l'Observatori de recerca de l'ENP vinculat a l'Observatori del Patrimoni natural i la biodiversitat | H75: Comú | I75: Optatiu | K75: UIC: Suport en la creació de l'Observatori de reserca | L75: =G75 -> Crear l'Observatori de recerca de l'ENP vinculat a l'Observatori del Patrimoni natural i la biodiversitat | N75: Impuls-Suport | O75: Si | P75: BAIXA | Q75: Participació en l'Observatori del Patrimoni Natural de la Generalitat_CAG | R75: Proper pla estratègic si aconseguim pressupost minim per recerca- | V75: 1) Participació en les iniciatives a petició de l'Observatori | W75: 1) 50% | X75: 1) 80% | Z75: x | AA75: x | AB75: x | AC75: x | AD75: 200
D76: 06.5 | E76: Millorar el coneixement global de les dinàmiques d'usos antròpics de l’ENP | F76: 06.5.1 | G76: Participar en la definició del sistema estándard de seguiment de l'ús públic amb el SENP | H76: Comú | I76: Obligatori | K76: SENP: Crear espais de participació. Definició del sistema estándard de seguiment de l'ús públic | L76: =G76 -> Participar en la definició del sistema estándard de seguiment de l'ús públic amb el SENP | N76: Sí | O76: Si | P76: MITJANA | Q76: Participació en el procés d'estandarització de la DGPA de la presa de dades vinculades a ús públic _CAG | R76: * Participació en el procés d'estandarització de la DGPA de la presa de dades vinculades a ús públic _CAG | V76: 1) Participació en el procés estandarització a petició de la DGPA | W76: 1) 50% | X76: 1) 80% | Z76: x | AC76: x | AD76: 20
F77: 06.5.2 | G77: Disposar de dades de freqüentació i perfil d'usuari en l'ENP i en especial en equipaments i en zones d'alta freqüentació segons el model de DG | H77: Comú | I77: Obligatori | K77: SENP: Disseny i elaboració del sistema estandaritzat de presa de dades i seguiment de la freqüentació en ENP | L77: =G77 -> Disposar de dades de freqüentació i perfil d'usuari en l'ENP i en especial en equipaments i en zones d'alta freqüentació segons el model de DG | N77: Sí | O77: Si | P77: MÀXIMA | Q77: Seguiment de les dades de freqüentació a través dels punts d'informació, l'ecocomptador, els sensors aforament i les autoritzacions vinculades a les reserves d'aparcament i pràctica del descens de barrancs a l'ENP_CAG | R77: * Seguiment de les dades de freqüentació a través dels punts d'informació, l'ecocomptador, els sensors aforament i les autoritzacions vinculades a les reserves d'aparcament i pràctica del descens de barrancs a l'ENP_CAG | T77: *Estudi, i proposta de mesures d’ordenació i gestió, pels sectors més freqüentats de l’espai | U77: *Recollir les dades dels visitants a través de l’aplicatiu que estableixi el responsable de l’espai natural (a través d’un suport electrònic tipus tauleta tàctil o ordinador amb connexió a internet). *Dissenyar i realitzar enquestes adreçades als visitants de l’espai natural. | V77: 1) Punts de recollida de dades de freqüentació i de perfil d'usuari | W77: 1) 1 | X77: 1) 3 | Y77: x | Z77: x | AA77: x | AB77: x | AC77: x | AD77: 200
F78: 06.5.3 | G78: Identificar les activitats i actors de l’espai. | H78: Comú | I78: Obligatori | L78: =G78 -> Identificar les activitats i actors de l’espai. | N78: Sí | O78: No | P78: MITJANA | Q78: Identificació de nous actors i activitats durant el desenvolupament del PUP (l'anàlisi està realitzat i contemplat a la memòria del PPAG)_CAG | R78: * Identificació de nous actors i activitats durant el desenvolupament del PUP (l'anàlisi està realitzat i contemplat a la memòria del PPAG)_CAG | V78: 1) Redacció del PUP amb identificació dels actors | W78: 1) 1 | X78: 1) 1 | Y78: x | AC78: x | AD78: 50
F79: 06.5.4 | G79: Identificar en cartografia les males praxis i punts de massificació | L79: =G79 -> Identificar en cartografia les males praxis i punts de massificació | N79: Sí | O79: No | P79: MITJANA | Q79: Identificació, si s'escau, de noves zones de massificació a mida que es vagin identificat (l'anàlisi està realitzat i contemplat a la memòria del PIE)_CAG | R79: * Identificació, si s'escau, de noves zones de massificació a mida que es vagin identificat (l'anàlisi està realitzat i contemplat a la memòria del PIE)_CAG | V79: 1) Redacció del PUP amb identificació dels sectors | W79: 1) 1 | X79: 1) 1 | Y79: x | AC79: x | AD79: 50
F80: 06.5.5 | G80: Adaptar i mantenir un registre d'activitats, actors i inciències en ús públic (curses, conflictes, queixes, etc) | H80: Comú | I80: Obligatori | K80: UIC: Disseny d'un model de registre d'activitats, actors i inciències en ús públic | L80: =G80 -> Adaptar i mantenir un registre d'activitats, actors i inciències en ús públic (curses, conflictes, queixes, etc) | N80: Sí | O80: No | P80: MITJANA | Q80: Registre de les dades segons el protocol d'incidències elaborat per part del DGPA_CAG i DGPA Recollida de suggeriments i reclamació dels usuaris_CAG i informació | R80: * Integració de dades en el registre un cop estigui sistematitzat_CAG | V80: 1) Disposar d'un registre sistematitzat | W80: 1) 1 | X80: 1) 1 | Y80: x | Z80: x | AA80: x | AB80: x | AC80: x | AD80: 20
F81: 06.5.6 | G81: Identificar els impactes (positius i negatius) que generen les activitats d'ús públic dins l'ENP | H81: Comú | I81: Obligatori | J81: ESNATURA | L81: =G81 -> Identificar els impactes (positius i negatius) que generen les activitats d'ús públic dins l'ENP | N81: Sí | O81: No | P81: MITJANA | Q81: Indentificació, si s'escau, dels impactes derivats de noves activitats d'us públic (l'anàlisi ja està realitzat a diferents documents:PPAG, Model de gestió de zones fluvials DdGi, etc.) | R81: * Indentificació, si s'escau, dels impactes derivats de noves activitats d'us públic (l'anàlisi ja està realitzat a diferents documents:PPAG, Model de gestió de zones fluvials DdGi, etc.) | U81: *Estudi dels serveis ecosistèmics de la comarca per la salut i el benestar de les persones | V81: 1) Redacció del PUP amb identificació de noves activitats i impactes | W81: 1) 1 | X81: 1) 1 | Y81: x | AA81: x | AC81: x | AD81: 50
A82: DESENVOLUPAMENT LOCAL | B82: 7 | C82: FIXAR LA POBLACIÓ AL TERRITORI d'acord amb les oportunitats que generen els objectius de l'espai. | D82: 07.1 | E82: Fomentar i donar suport tècnic als Plans de desenvolupament socioecòmonic local sostenible dels municipis | F82: 07.1.1 | G82: Promoure i col·laborar en l'aplicació de Plans de Desenvolupament Local Sostenible | H82: Comú | I82: Obligatori | L82: =G82 -> Promoure i col·laborar en l'aplicació de Plans de Desenvolupament Local Sostenible | N82: Impuls-Suport | O82: No | P82: MITJANA | Q82: Participació en l'aplicació dels Plans de desenvolupament local sostenible_CAG | R82: * Identificació dels consistoris que tenen un Pla de desenvolupament local_CAG | U82: *Grup motor per al relleu agrari. Cens de cedents | V82: 1) Nombre de reunions en què el personal participa a petició dels mateixos ajuntaments | W82: 1) 50% | X82: 1) 80% | Z82: x | AB82: x | AD82: 20
B83: 8 | C83: APROFITAR ELS RECURSOS NATURALS DE FORMA SOSTENIBLE mitjançant desenvolupament dels aprofitaments tradicionals de forma compatible amb la conservació de l'espai | D83: 08.1 | E83: Impulsar models productius agraris i forestals per tal d'afavorir la conservació dels hàbitats i els paisatges modelats per aquestes, i contribuir a la millora socioeconòmica de les persones que la fan possible | F83: 08.1.1 | G83: Acompanyar i assessorar els productors agraris per millorar les tècniques productives agràries i afavorir la conservació dels hàbitats i paisatges | H83: Comú | I83: Obligatori | L83: Assessorar i donar suport als productors agropecuaris en l'aplicació de bones pràctiques per la conservació dels hàbitats i les espècies presents | M83: Canvi de redactat OP. Inclusió de la ramaderia | N83: Impuls-Suport | O83: Si | P83: ALTA | Q83: Suport a la FPC en la redacció de Plans de maneig per a la gestió del pastoreig (Projecte Forwards i altres)_CAG Identificació de les BBPP per a una gestió de la pastura orientada a la conservació del patrimoni natural_CAG Anàlisi de les potencialitats del maneig de bestiar amb les noves tecnologies_CAG Revisió dels IOF perquè no siguin agressius amb l'hàbitat forestal (i incloure mesures compensatòries i condicions d'execució)_CAG Reforçar la vigilància en l'exeució dels IOF_CAR, CPF i CAG | R83: * Suport a la FPC en la redacció de Plans de maneig per a la gestió del pastoreig (Projecte Forwards i altres)_CAG * Identificació de les BBPP per a una gestió de la pastura orientada a la conservació del patrimoni natural_CAG | S83: *Realització de campanya de foment de la disminució i substitució dels productes fitosanitaris per altres de més selectius i de baixa toxicitat (AAA) tant per a la fauna terrestre com aquàtica. No es un problema greu a l'espai, activitat agrícola minima. *Incorporació de mesures en les pràctiques agrícoles per tal de fer compatibles la producció agrícola i la conservació de les mulleres. No es un problema greu a l'espai, activitat agrícola minima. *Divulgació i valorització de les espècies pròpies d'ambients agrícoles entre els agents locals, incidint en la importància de l'aplicació de pràctiques de gestió encaminades a la seva conservació. No es un problema greu a l'espai, activitat agrícola minima. | U83: *Estudi i innovació en mètodes de recuperació i manteniment de pastures *Implementació d’eines digitals per al control i seguiment del bestiar *Preparació i protecció envers atacs de cànids i altra fauna | V83: 1) Actuacions realitzades per millorar la gestió agrària | W83: 1) 1 | X83: 1) 2 | Y83: x | Z83: x | AA83: x | AB83: x | AC83: x | AD83: 650
F84: 08.1.2 | G84: Oferir formació als productors agraris per millorar el seu coneixement sobre tècniques eficients i respectuoses amb la conservació del patrimoni natural i cultural | H84: Comú | I84: Obligatori | L84: =G84 -> Oferir formació als productors agraris per millorar el seu coneixement sobre tècniques eficients i respectuoses amb la conservació del patrimoni natural i cultural | N84: Impuls-Suport | O84: Si | P84: MITJANA | Q84: Suport a l'organització de jornades dirigides al sector primari per divulgar informació útil per al maneig de pastures_CAG, FPC PNZVG | R84: * Suport a la FPC en la formació dels ramaders en la gestió del pastoreig orientat a la conservació (Projecte Forwards i altres)_CAG | U84: *Organització de formacions | V84: 1) Nombre de jornades realitzades | W84: 1) 1 | X84: 1) 3 | AA84: x | AC84: x | AD84: 20
F85: 08.1.3 | G85: Promoure la recuperació i conservació de marges i punts d'aigua associats a la ramaderia i l'agricultura i d'interès per la biodiversitat | H85: Específic | I85: Optatiu | L85: Promoure l'adequació d'edificacions, la recuperació de marges i la conservació de punts d'aigua associats a la ramaderia i l'agricultura d'interès per la biodiversitat | M85: Canvi de redactat OP. Inclusió d'edificacions rurals | N85: Sí | O85: Si | P85: MITJANA | Q85: Dinamització d'accions per al manteniment, millora o recuperació de punts d'aigua, ja sigui directament o a través d'altres institucions_CAG Formació en matèria de pedra seca_CAG | R85: * Desenvolupament dels acords del Conveni i els Acords signats amb la Fundació Bionexus per a la millora de punts d'aigua_CAG+ font de lliurona+PIE * Formació en matèria de pedra seca en el marc de la TVAPO i paral·lelament amb la FES i IES Garrotxa_CAG | S85: Aquestes accions no encaixen ben bé amb l'objectiu. *Manteniment de marges i tanques arbustives i arbrades entre prats i pastures, llindars i clarianes de bosc. Es fa amb la creació ecotons en EEOO. *Potenciació de franges de ribera entre cultius i la llera (DPH) a través, per exemple, de les mesures incloses al PDR de Catalunya. No tenim cultius a l'entorn del bosc de ribera. *Conservació de punts d'aigua propers a zones forestals com a llocs d'alimentació preferent. *Actuacions per instal·lar abeuradors i evitar instal·lacions de suport a la ramaderia properes als ecosistemes lèntics (basses permanents, estanys i llacunes) per tal de protegir els hàbitats 3110, 3140, 3150 i 3170 associats a ells. COnveni fundacio bionexus. *Els instruments de planificació i ordenació de l'espai han d'evitar la substitució total o parcial de 6420 per basses i abeuradors per bestiar. *Manteniment dels punts d’aigua, basses o entollaments temporals presents com a zones importants per a la flora i fauna aquàtica i terrestre amb una secció sense accés al bestiar. A través dels informes. *Construcció d’abeuradors propers per evitar la pressió sobre la torbera en cas de falta d’aigua a la zona. En tenim en els llocs identificats (Bestrecà) i ho farem a Palomeres. | U85: *Manteniment de punts d'aigua *Infraestructures per a l’abastiment d’aigua | V85: 1) Nombre d'actuacions executades | W85: 1) 1 | X85: 1) 3 | Y85: x | Z85: x | AA85: x | AB85: x | AC85: x | AD85: 400
F86: 08.1.4 | R86: Crec que no cal un específic, està inclòs tot el que fem en altres | S86: Ja està establert en altres objectius (compensacions a ramaderia i convenis dinàmica natural). *Establiment del Programa de compensacions a la ramaderia extensiva associada a la conservació *Compensació per danys a la ramaderia i l’apicultura (Ursus arctos, Gyps fulvus, Canis lupus,…). *Consolidació i agilització de compensacions –flora i fauna- (estudis per determinar mètodes eficaços de valoració del dany o la limitació, estudis per identificar mètodes efectius de prevenció de danys,…). *Compensació per limitacions en la gestió forestal planificada en PTGMF, o que forma part d'algun dret adquirit d'aprofitament forestal, (drets de tala, sistemes d'extracció de fusta més costosos, rodals d'exclusió, etc...) derivades de la presència d'hàbitats o espècies d'interès comunitari. | T86: *Mesures de foment per a la instal·lació d’infraestructura ramadera i per la protecció de conreus i instal·lacions agràries | U86: *Elaboració d’un Programa de compensació pels serveis ambientals de la pastura *Pagament pel servei ambiental de manteniment de pastures *Infraestructures de suport al maneig del bestiar *Impuls d’obradors compartits *Creació d’una borsa de pastures i ramades: finques, pastors/es i explotacions ramaderes
D87: 08.2 | E87: Promoure la coordinació amb els agents socioeconòmics del territori pel foment del desenvolupament sostenible de l'espai (sector primari i secundari) | F87: 08.2.1 | G87: Establir una relació contínua amb agents socioeconòmics del territori, i si s'escau, crear una Taula de desenvolupament local | J87: ESNATURA | L87: =G87 -> Establir una relació contínua amb agents socioeconòmics del territori, i si s'escau, crear una Taula de desenvolupament local | N87: Sí | O87: Si | P87: MÀXIMA | Q87: Establiment de marcs de treball amb diferents agents del territori en el marc d'accions i projectes desenvolupats a l'ENPAG_CAG | R87: * Establiment de marcs de treball amb diferents agents del territori en el marc d'accions i projectes desenvolupats a l'ENPAG (ordenació de l'ús públic a la vall de Sant Aniol, TVAPO, CETS, Relleu agrari, custòdia del territori, contacte directe amb propietaris i ramaders, etc.) | U87: *Creació d’una associació de ramaders/es de l’Alta Garrotxa *Establir complicitats amb altres entitats, associacions locals i sectors econòmics | V87: 1) Nombre d'iniciatives per establir sinèrgies amb els agents del territori | W87: 1) 1 | X87: 1) 3 | Y87: x | Z87: x | AA87: x | AB87: x | AC87: x
D88: 08.3 | E88: Millorar la valorització i comercialització dels productes generats a l'ENP que contribueixen al desenvolupament socioeconòmic i la conservació del patrimoni de l'ENP | F88: 08.3.1 | G88: Implantar un distintiu de qualitat i compatibilitat amb la conservació dels productes de la Xarxa d'ENP o criteris de qualitat propis de l'ENP | H88: Comú | I88: Optatiu | J88: ESNATURA | K88: SENP: Crear una marca que identifiqui els productes agroalimentaris generats en els ENP | L88: =G88 -> Implantar un distintiu de qualitat i compatibilitat amb la conservació dels productes de la Xarxa d'ENP o criteris de qualitat propis de l'ENP | N88: Impuls-Suport | O88: Si | P88: BAIXA | Q88: Participació en les reunions amb la DGPA per la generació d'un segell comú_DGPA i CAG | R88: * Accions per a la implementació a l'ENPAG de la marca de qualitat de productes agroalimentaris creada per part del SENP_CAG i DGPA | V88: 1) Creació d'un nou segell comú per part de la DGPA | W88: 1) 1 | X88: 1) 1 | AB88: x | AC88: x | AD88: 60
F89: 08.3.2 | G89: Integrar els productes i activitats locals de qualitat en l'oferta d'activitats d'informació i turístiques de l'ENP | H89: Comú | I89: Obligatori | J89: ESNATURA CETS | L89: =G89 -> Integrar els productes i activitats locals de qualitat en l'oferta d'activitats d'informació i turístiques de l'ENP | N89: Sí | O89: Si | P89: MITJANA | Q89: Revisió del sistema d'acreditació de les empreses CETS per integrar productes i activitats locals_CAG Cerca d'alternatives per incloure i acreditar entitats i ajuntaments (o concessions dels mateixos) a la CETS_CAG Particiapció en el Programa Visites en Valors_CAG | R89: * Integració dels procuctes locals en les activitats d'EA que es desenvolupin en el marc del Contracte del Servei d'EA de la Generalitat_CAG i DGPA | U89: *Fer que la població local se senti involucrada en activitats turístiques *Crear i involucrar entitats no turístiques en esdeveniments turístics | V89: 1) Integració dels productes locals com a element de valoració de l'acreditació CETS 2) Anys en els que es desenvolupa el Programa visites en valors o similar | W89: 1) 1 2) 1 | X89: 1) 1 2) 2 | Y89: x | Z89: x | AA89: x | AB89: x | AC89: x | AD89: 100
F90: 08.3.3 | G90: Promoure fires d'artesania i productes locals de l'ENP | H90: Comú | I90: Optatiu | L90: =G90 -> Promoure fires d'artesania i productes locals de l'ENP | N90: No | O90: No | P90: FORA DEL TERMINI DEL PLA | Q90: Objectiu fora de termini del present Pla estratègic | S90: *Accions de promoció dels productes agrícoles vinculats a la conservació dels valors naturals dels espais Natura 2000. | U90: *Dinamització d’un punt de venta de producte local | AD90: 0
F91: 08.3.4 | G91: Generar aliances entre el sector primari, el turisme, la restauració i altres per fomentar la gastronomia local | H91: Comú | I91: Optatiu | J91: ESNATURA CETS | L91: =G91 -> Generar aliances entre el sector primari, el turisme, la restauració i altres per fomentar la gastronomia local | N91: Impuls-Suport | O91: No | P91: MITJANA | Q91: Col·laboració amb Turisme Garrotxa i Garrotxa Hostalatge per desenvolupar accions vinculades a gastronomia de la CETS_CAG | U91: *Acollir en zones rurals *Donar a conèixer l'oferta i els recursos turístics entre la població local *Evidenciar els beneficis del sector turístic a la destinació – Visitor Payback | V91: 1) Nombre d'actuacions de la CETS vinculades a Gastronomia | W91: 1)2 | X91: 1) 3 | Y91: x | Z91: x | AA91: x | AB91: x | AC91: x
F92: 08.3.5 | G92: Elaborar una diagnòsi del teixit productiu local i un pla d’acció amb línies de treball i actuacions concretes per donar-li suport | H92: Comú | I92: Optatiu | J92: ESNATURA | L92: =G92 -> Elaborar una diagnòsi del teixit productiu local i un pla d’acció amb línies de treball i actuacions concretes per donar-li suport | M92: Realitzat, contemplat al Pla d'impuls de la Ramaderia Extensiva | N92: Realitzat | O92: Si | P92: ALTA | Q92: Objectiu operatiu assolit, sense mesures continuïstes en el termini del present Pla estratègic | R92: *Desenvolupament del PIRE i del Programa de Compensacions a l'activitat ramadera_CAG i DGPA | Y92: x | AD92: 1000
F93: 08.3.6 | G93: Promoure els agents del territori que potencien i difonen els productes alimentaris locals i de qualitat (allotjaments, restaurants, cellers, establiments, elaboradors i productors) | H93: Comú | I93: Optatiu | L93: =G93 -> Promoure els agents del territori que potencien i difonen els productes alimentaris locals i de qualitat (allotjaments, restaurants, cellers, establiments, elaboradors i productors) | N93: Sí | O93: No | P93: ALTA | Q93: Revisió del sistema d'acreditació de les empreses CETS per integrar productes i activitats locals_CAG | R93: * Identificació dels establiments que hi ha dins dels municipis que formen part de l'ENPAG i determinar en quina mesura promocionen producte local i especificament de l'ENPAG_CAG | V93: 1) Integració dels productes locals com a element de valoració de l'acreditació CETS | W93: 1) 1 | X93: 1) 1 | Y93: x | Z93: x | AA93: x | AB93: x | AC93: x
D94: 08.4 | E94: Contribuir a una correcta planificació i gestió dels recursos cinegètics i piscícoles de forma compatible amb els valors de l'ENP | F94: 08.4.1 | G94: Treballar amb l'autoritat competent per garantir objectius de conservació d’espècies i hàbitats en la revisió dels Plans de Gestió Cinegètica | H94: Comú | I94: Obligatori | J94: MAP | L94: =G94 -> Treballar amb l'autoritat competent per garantir objectius de conservació d’espècies i hàbitats en la revisió dels Plans de Gestió Cinegètica | N94: Impuls-Suport | O94: Si | P94: MITJANA | Q94: Suport al Servei de Gestió cinegètica, segons demandes, per establiment de mesures per la conservació d'espècies i hàbitats objectes de conservació i millorar les poblacions presa (conill i perdiu) en la revisió de Plans de gestió cinegètica | R94: * Suport al Servei de Gestió cinegètica, segons demandes, per establiment de mesures per la conservació d'espècies i hàbitats objectes de conservació i millorar les poblacions presa (conill i perdiu) en la revisió de Plans de gestió cinegètica. | S94: *Acords amb les Societats de Caçadors per a incorporar objectius de conservació d’espècies, com la tórtora comú, i hàbitats en la revisió dels Plans de Gestió Cinegètica. | V94: 1) Plans de Gestió Cinegètica en els que s'ha participat a petició de l'organisme competents | W94: 1) 1 | X94: 1) 2 | AA94: x | AC94: x | AD94: 20
F95: 08.4.2 | G95: Col·laborar en la regulació i ordenació de la caça i la pesca en zones sensibles o amb risc d'afectació d'elements clau objecte de conservació | H95: Comú | I95: Obligatori | J95: MAP | L95: =G95 -> Col·laborar en la regulació i ordenació de la caça i la pesca en zones sensibles o amb risc d'afectació d'elements clau objecte de conservació | M95: No tenim capacitat ni som competents | O95: Si | Q95: Objectiu descartat per falta de capacitat o competències | R95: * Suport al servei de Gestió cinegètica, en funció de les demandes i la capacitat interna del CAG_CAG | S95: *Foment dels acords amb les societats de caçadors per millorar la gestió de les poblacions de conills i perdius en àrees amb presència d'Aquila fasciata. *Actuacions de potenciació del conill i perdiu com a preses *Declaració de refugis de pesca a les capçaleres dels rius on és present Barbus meridionalis. *Establir acords amb societats de pescadors per tal de crear zones de refugi de pesca en zones particularment estratègiques. fet,. *Els instruments de planificació i ordenació dels espais naturals protegits regulen la pesca recreativa en àrees amb presència de peixos d'interès comunitari evitant l'ús d'esquer viu. | AD95: 0
F96: 08.4.3 | G96: Donar suport en la gestió de poblacions que generen danys a les activitats econòmiques de l'ENP | H96: Comú | I96: Obligatori | L96: =G96 -> Donar suport en la gestió de poblacions que generen danys a les activitats econòmiques de l'ENP | N96: Impuls-Suport | O96: Si | P96: MITJANA | Q96: Suport al servei de Gestió cinegètica, en funció de les demandes i la capacitat interna del CAG_CAG | R96: * Suport al servei de Gestió cinegètica, en funció de les demandes i la capacitat interna del CAG_CAG | V96: 1) Col·laboracions realitzades segons petició de l'organisme competent | W96: 1) 1 | X96: 1) 2 | AA96: x | AC96: x | AD96: 20
B97: 9 | C97: FOMENTAR UN TURISME SOSTENIBLE compatible amb la conservació de l'espai | D97: 09.1 | E97: Fomentar un model de turisme que promogui els valors dels espais naturals protegits d'acord amb els agents turístics del territori | F97: 09.1.1 | G97: Desplegar la Carta Europea de Turisme Sostenible (CETS) | H97: Comú | I97: Optatiu | J97: ESNATURA | L97: =G97 -> Desplegar la Carta Europea de Turisme Sostenible (CETS) | N97: Sí | O97: Si | P97: MÀXIMA | Q97: Impuls per l'acreditació de l'ENPAG (paral·lela a la del PNZVG) en el marc de la CETS de la Garrotxa, en el seu procés de renovació 26-30_CAG Coordinació de la CETS_CAG Implementació de la metodologia AGILE i gestió OKR_CAG | R97: * Implementació de la CETS Garrotxa_CAG * Impuls per l'acreditació de l'ENPAG (paral·lela a la del PNZVG) en el marc de la CETS de la Garrotxa, en el seu procés de renovació 26-30_CAG | T97: *Carta Europea de Turisme Sostenible de la Federació EUROPARC | U97: *Participació activa a la carta europea de turisme sostenible *Realitzar un treball de benchmark nacional i internacional de models de governança *Organitzar sessions de participació amb experts per analitzar diferents models de governança *Organitzar activitats participatives amb els agents implicats per a la co-creació del model *Dissenyar un model sostenible de governança integrador i vertebrador *Testejar el prototip del model de governança *Concretar i implementar el model de governança *Avaluar i millorar contínuament el model de governança *Dur a terme accions de promoció local, nacional i internacional del turisme sostenible a la Garrotxa donant importància a la visualització de la CETS | V97: 1) Dossier de renovació 2) Reunions realitzades 3) Participació en Grups OKR de treball | W97: 1) 1 2) 10 3) 1 | X97: 1) 1 2) 25 3) 2 | Y97: x | Z97: x | AA97: x | AB97: x | AC97: x | AD97: 1200
F98: 09.1.2 | G98: Tramitar la certificació Biosphere | H98: Comú | I98: Optatiu | L98: =G98 -> Tramitar la certificació Biosphere | N98: No | O98: Si | P98: FORA DEL TERMINI DEL PLA | Q98: Objectiu fora de termini del present Pla estratègic | AD98: 0
D99: 09.2 | E99: Promoure la coordinació amb els agents turístics del territori (empreses, industries, administració). | F99: 09.2.1 | G99: Treballar amb les empreses turístiques per trobar eines de canvi cap a un model de turisme sostenible i de qualitat | H99: Comú | I99: Optatiu | J99: ESNATURA | L99: =G99 -> Treballar amb les empreses turístiques per trobar eines de canvi cap a un model de turisme sostenible i de qualitat | N99: Sí | O99: Si | P99: ALTA | Q99: Revisió del sistema d'acreditació de la CETS per augmentar els criteris de sostenibilitat_CAG | R99: * Mapa de les principals empreses que operen a l'ENPAG_CAG | U99: *Promoure una oferta turística sostenible de qualitat *Incrementar el nombre d'empreses i paquets turístics a partir de la Fase II i III de la CETS *Redactar un Pla de mobilitat sostenible i eco mobilitat turística *Desplegar el Pla de mobilitat sostenible i eco mobilitat turística i contribuir a la implementació del Pla a través d'inversions *Incorporar els Objectius de Desenvolupament Sostenible (ODS) en tots els productes *Mantenir i millorar la xarxa d'indicadors turístics i ambientals de la Garrotxa *Realitzar accions orientades a un model de Smart Destination | V99: 1) revisió del sistema d'acreditació de les empreses cets | W99: 1) 1 | X99: 1) 1 | Y99: x | Z99: x | AA99: x | AB99: x | AC99: x
F100: 09.2.2 | G100: Crear productes i paquets turístics amb associacions d’empreses turístiques i operadors turístics | H100: Comú | I100: Optatiu | J100: ESNATURA | L100: =G100 -> Crear productes i paquets turístics amb associacions d’empreses turístiques i operadors turístics | N100: Sí | O100: Si | P100: ALTA | Q100: Suport al Programa de Visites amb valors_CAG | R100: * Programa Visites amb Valors juntament amb Turisme Garrotxa i PNZVG_CAG * Col·laboració amb Turisme Garrotxa en la creació de nous productes turístics_CAG | U100: *La Garrotxa Soft & Smart County. Destinació turística sostenible i intel·ligent *Crear una oferta que inclogui la mobilitat com a experiència turística per al visitant *Crear nous productes 4D *Promoció de nous productes 4D *Consolidar el "Servei d'Innovació i Producte turístic" dirigit a empreses turístiques del territori CETS | V100: 1) Anys en que es dona suport al Programa de visites amb valors o similar | W100: 1) 1 | X100: 1) 3 | Y100: x | Z100: x | AA100: x | AB100: x | AC100: x
...

Sheet Hores per blocs
A1: Proposta de distribució d'hores
A3: Prèvia | B3: Gestió | C3: Sara 35% hores | D3: 2222
C4: Marta 85% | D4: 5397
A6: Ens queden | B6: 22010 hores
A8: Distribució aprox per blocs | E8: Hores computades a l'excel del Pla | F8: Diferència | H8: 50 hores són 1,5 dies per any
A9: Natura | C9: 20 | D9: =C9*22010/100 -> 4402 | E9: =SUM(PLA!AD5:AD36) -> 4431 | F9: =D9-E9 -> -29 | H9: 200 són 6,25 dies any
A10: Cultura | C10: 5 | D10: =C10*22010/100 -> 1100.5 | E10: =SUM(PLA!AD37:AD56) -> 1100 | F10: =D10-E10 -> 0.5
A11: Coneixement | C11: 14 | D11: =C11*22010/100 -> 3081.4 | E11: =SUM(PLA!AD57:AD81) -> 3000 | F11: =D11-E11 -> 81.4 | H11: =D12/18 -> 195.64444
A12: Desenvolupament local | C12: 16 | D12: =C12*22010/100 -> 3521.6 | E12: =SUM(PLA!AD82:AD100) -> 3490 | F12: =D12-E12 -> 31.6 | H12: =D13/35 -> 176.08
A13: Us public | C13: 28 | D13: =C13*22010/100 -> 6162.8 | E13: =SUM(PLA!AD101:AD137) -> 6215 | F13: =D13-E13 -> -52.2
A14: EiVA | C14: 17 | D14: =C14*22010/100 -> 3741.7 | E14: =SUM(PLA!AD138:AD170) -> 3800 | F14: =D14-E14 -> -58.3
A15: Total | C15: =SUM(C9:C14) -> 100 | D15: =SUM(D9:D14) -> 22010
A17: Hem comptat les hores dels 4 pax de Consorci i 1/3 de la Nuria i la Susanna.
A18: La de coneixement-us públic s'integra en el funcionament habitual dels serveis d'us públic
D19: Gestió
D20: 7620 | E20: =SUM(PLA!AD171:AD188) -> 7400 | F20: =D20-E20 -> 220
F22: =SUM(F9:F21) -> 194
A24: Total hores | D24: =D15+D20 -> 29630 | E24: 100
D25: 7620 | E25: =D25*E24/D24 -> 25.717179

Sheet VINCLE AMENAÇA_OBJ. OPERATIU
A1: TAULA DE VINCLE ENTRE LES AMENACES I ELS OBJECTIUS OPERATIUS DE L'EIX DEL PATRIMONI NATURAL
A3: Eix 1. Natura
A4: Codi | B4: Objectius operatius | C4: Tipologia amenaça | D4: Amenaça concreta
A5: 01.1.1 | B5: =PLA!L5 -> Implementar i executar plans i mesures de gestió específiques per a hàbitats i espècies de conservació prioritària dins l'ENP | C5: No especificada
A6: 01.1.2 | B6: =PLA!L6 -> Adaptar i executar plans de gestió específics per a elements geològics de conservació prioritària dins l'ENP | C6: No especificada
A7: 01.2.1 | B7: =PLA!L7 -> Implementar la metodologia de gestió adaptativa (Estàndards Oberts de Gestió Adaptativa a Catalunya) en tots els processos de l'ENP | C7: Activitat agrícola
A8: 01.2.2 | B8: =PLA!L8 -> Executar les mesures previstes en els plans de conservació o recuperació d'espècies amenaçades de forma coordinada amb el Servei de Flora i Fauna en l'àmbit de l'ENP | C8: No especificada
A9: 01.2.3 | B9: =PLA!L9 -> Executar les mesures de gestió previstes en els plans de control i erradicació d'espècies exòtiques de forma coordinada amb el Servei de Flora i Fauna en l'àmbit de l'ENP | C9: Espècies invasores i patògens
A10: 01.2.4 | B10: =PLA!L10 -> Desplegar els objectius i tasques recollits en els instruments de referència i compromisos internacionals | C10: No especificada
A11: 01.3.1 | B11: =PLA!L11 -> Identificar espais pel foment de la dinàmica natural i l'aprofitament no extractiu | C11: Gestió i modificació de sistemes naturals
A12: 01.3.2 | B12: =PLA!L12 -> Afavorir la maduresa dels sistemes forestals | C12: Gestió i modificació de sistemes naturals
A13: 01.3.3 | B13: =PLA!L13 -> Generar pertorbacions controlades | C13: Gestió i modificació de sistemes naturals
A14: 01.3.4 | B14: =PLA!L14 -> Restaurar i conservar la dinàmica i estructura natural dels rius, les zones humides, i altres hàbitats d'aigua dolça | C14: Gestió i modificació de sistemes naturals
A15: 01.3.5 | B15: =PLA!L15 -> Fomentar el paisatge en mosaïc | C15: Gestió i modificació de sistemes naturals
A16: 01.3.6 | B16: =PLA!L16 -> Gestionar i intervenir en la dinàmica de poblacions de fauna que no tenen depredador natural | C16: Gestió i modificació de sistemes naturals
... A36: 03.4.2 | B36: =PLA!L36 -> Identificar espais prioritaris per a la gestió directa | C36: No especificada
B37: AFEGIR LES FILES QUE S'HAGIN INCORPORAT A LA TAULA DEL PLA

Sheet Taxonomia Amenaces
A1: Taxonomia d'Amenaces - Xarxa d'ENP Catalunya
A2: Versió 1_revisada pels equips del PNAT Cap de Creus, PNAT Montgrí-Medes, PNAT els Ports, PNIN Poblet, PNAT Delta de l'Ebre, PNAT Alt Pirineu i PNAT Capçaleres del Ter i Freser
A3: Font de dades 1: List of pressures and threats for reporting 2019-2024 v1.1 (Comissió Europea)
A4: Font de dades 2: Llistat de pressions i amenaces del Pla de Protecció del Cadí-Moixeró, inspirat en el llistat de la Comissió Europea
A5: Font de dades 3: IUCN/CMP Threats Classification v 3.3 (2016) i v4.0 draft (2023)
A8: Codi Amenaça | B8: Tipologia d'amenaça | C8: Codi Amenaça | D8: Nom Amenaça | E8: Exemples i descripció del grup
A9: 1 | B9: Urbanització i edificació | C9: 1.1 | D9: Urbanització residencial | E9: Construccions relacionades amb àrees residencials. Tot i que la normativa no permet noves construccions, existeixen edificacions fóra d'ordenació. També casos de remodelacions, reconstruccions o ampliacions d'edificis rurals per usos agrícoles, forestals, ramaders, recreatius, residencials, etc). Restauracions de cabanes i bordes que no deixen forats per ratpenats. cases forestals. Bordes que es canvien d'ús per hosteleria
C10: 1.2 | D10: Urbanització comercial o industrial
C11: 1.3 | D11: Àrees recretives i turístiques | E11: Refugis de muntanya que es remodelen, impacten etc
A12: 2 | B12: Producció primària | C12: 2.1 | D12: Activitat agrícola | E12: Cultius annuals i perennes. Canvis de tipus de cultiu, secà a regadiu o al revés. Canvi d'usos del sòl com cultius de vinya a muntanya, Inclosos el cultiu de l'arròs amb substàncies biocides. Inclòs el cultiu de marihuana
C13: 2.2 | D13: Plantacions forestals
C14: 2.3 | D14: Ramaderia | E14: Ramaderia tan intensiva com extensiva i semi-intensiva (pastura de dia i nit en corral)
C15: 2.4 | D15: Aqüicultura | E15: Aquicultura marina i d'aigua dolça, a l'interior o als voltants del parc
A16: 3 | B16: Producció d'energia i mineria | C16: 3.1 | D16: Activitats de la mineria | E16: Mineria de qualsevol tipus (a cel obert, marina, al·luvial com extracció d'àrids i còdols, subterrània), a l'interior o als voltants del parc. Extracció de torba i salines. Si aplica, extracció d'hidrocarburs terrestres o marins
C17: 3.2 | D17: Producció d'energia renovable | E17: Centrals de producció d'energia renovable (molins eòlics terrestres o marins, instal·lacions solars, hidroelèctriques, geotèrmia inclosos els impactes de fauna contra les instal·lacions). A dins del parc o afectant connectors entre parcs
A18: 4 | B18: Infrastructures de transport i serveis | C18: 4.1 | D18: Vials de transport | E18: Carreteres, pistes forestals, línies fèrries i cremalleres
C19: 4.2 | D19: Conduccions | E19: Conduccions elèctriques, aqueductes, canals de rec, estacions de bombament, conduccions d'aigua o gas
C20: 4.3 | D20: Infrastructures marines | E20: Rutes marines, canals, impactes de vaixells sobre balenes i infrastructura associada. Ports, pantalans, etc
C21: 4.4 | D21: Tancaments i vallats | E21: Tancaments, valles perimetrals i parets de tota mena, en carreteres, per bestiar, estètiques, etc
A22: 5 | B22: Extracció de recursos naturals | C22: 5.1 | D22: Caça i recol·lecció d'animals | E22: Caça i recolecció d'animals, ous, mel silvestre, etc ja sigui per subsistència, esport, tradició, comerç o de forma accidental
C23: 5.2 | D23: Recol·lecció de vegetals | E23: Recolecció de plantes, bolets, resines, líquens, etc
C24: 5.3 | D24: Treballs forestals | E24: Treball forestals de tota mena (arreu, selectiva, carboneig, aclarides, etc)
C25: 5.4 | D25: Pesca i semblants | E25: Pesca i recollida de recursos aquàtics de tota mena i amb qualsevol tècnica (artesanal, xarxa, marisqueig, recollida de corall, pesca accidental, recreativa, etc)
A26: 6 | B26: Molèsties | C26: 6.1 | D26: Molèsties per activitats recreatives | E26: Per activitats recreatives al medi natural de qualsevol tipus (excursionisme, bicicleta, cavall, vehicles a motor, escalada, esquí de muntanya, acampada temporal, pernoctació, ornitòlegs, fotografs, esports nàutics, pesca turisme, àrees recreatives, drons, globus, parapents, buggy-kite, sobrevol amb helicòpters, amb ultralleugers, motos de neu, etc) i tan sigui esporàdica com recurrent
C27: 6.2 | D27: Molèsties per activitats militars | E27: Activitats militars de qualsevol mena (camps militars, assajos amb artilleria, etc)
C28: 6.3 | D28: Altres tipus de molèsties | E28: Qualsevol altra molèstia (per bany en rius i tolles, passeig de gossos, peregrinatges, aplecs, recerca sobre espècies, extraccions arqueològiques, vandalisme, tràfic de drogues, etc)
C29: 6.4 | D29: Molèsties per activitats multitudinàries | E29: Activitats organitzades i multitudinàries, per exemple curses de muntanya, festivals, esdeveniments, filmacions, fins i tot enterraments
A30: 7 | B30: Gestió i modificació de sistemes naturals | C30: 7.1 | D30: Foc | E30: Foc, grans incendis forestals i supressió del foc, incloses activitats de restauració post-foc
C31: 7.2 | D31: Gestió de l'aigua | E31: Construcció i utilització de preses, canals, captacions, pous, dics, etc de qualsevol mena. Extracció / captacions d'aigua per rec, etc. Construcció de basses per fer neu artificial. Dessaladores, potabilitzadores, depuradores, conduccions, trasvassaments, emissaris de salmorres, alteració de cabals, gestió de cabals en rius
C32: 7.3 | D32: Moviments de terres i sediments | E32: Gestió i estabilització de terrenys i sediments (estabilització de dunes, construccions en litorals, remediació de sòls, restauració de mines, dragatges, moviments de sorres, etc)
C33: 7.4 | D33: Modificació del clima | E33: Activitats per modificar el clima o processos naturals (prevenció de gelades, fertilització amb ferro a l'oceà, captura de carboni, etc)
C34: 7.5 | D34: Gestió d'hàbitats | E34: Gestió d'hàbitats: gestió d'aigua dolça de rec i arrossars (que pot afectar a llacunes, etc), retirada de fustes en rius, desbrossades, creació d'esculls artificials, alimentació d'ocells, tancament de coves, barreres elèctriques
C35: 7.6 | D35: Desaparició d'activitats tradicionals | E35: Desaparició de pràctiques tradicionals com pastura extensiva, canvi en el maneig de la pastura, la tipologia de bestiar, caça per control de predadors, etc
A36: 8 | B36: Espècies invasores i patògens | C36: 8.1 | D36: Espècies invasores | E36: Espècies invasores com rates en illes, animals domèstics assilvestrats, musclo zebra, bambú, peixos introduïts com Phoxinus en estanys d'alta muntanya, etc
C37: 8.2 | D37: Espècies desestabilitzades | E37: Espècies natives desestabilitzades com superpoblació de cèrvids, porcs senglars, manca de carnívors, blooms d'algues, plagues d'insectes, o amb impactes puntuals com predadors sobre espècies sensibles com colònies d'ocells, gall fer, etc
C38: 8.3 | D38: Introducció de genotips aliens | E38: Material genètic introduït com cultius resistents a plagues, creuament de gat domèstic amb gat fer, restauracions d'hàbitats fetes amb varietats alienes, arbres o instectes modificats genèticament, aquicultura amb espècies no natives, etc
C39: 8.4 | D39: Plagues i patògens | E39: Malalties que afecten conills, grip aviar, botulisme, castanyers, oliveres, cítrics, amfibis, etc
A40: 9 | B40: Polució | C40: 9.1 | D40: Polució aquàtica | E40: Polució dissolta en aigua (aigües sèptiques, efluents industrials, pesticides, fertilitzants, efluents de la mineria, excès de nutrients en activitats de l'aquicultura, purins, potasses per desfer la neu en pistes i carreteres, etc
C41: 9.2 | D41: Residus sòlids | E41: Residus sòlids de qualsevol orígen i en medi terrestre o marí, inclosos de la caça, pesca, agricultura, aqüicultura, del turisme, construcció, transport, xarxes fantasma i elements abandonats al medi
C42: 9.3 | D42: Polució aèria | E42: Residus en medi aeri com partícules, gasos, o partícules radioactives
C43: 9.4 | D43: Contaminació acústica, llumínica o per radiació | E43: Contaminació lumínica, tèrmica com efluents de centrals elèctriques en rius, acústica com soroll en aeroports o zones industrials o per escoles de formació de pilots d'helicòpters al Pirineu, camps electromagnètics en cables, sonars submarins, soroll i onades causades per embarcacions recreatives, llums de les maquinàries a pistes d'esquí, il·luminació nocturna en estacions d'esquí, il·luminació de monuments, etc
A44: 10 | B44: Grans pertorbacions naturals | C44: 10.1 | D44: Pertorbacions d'origen geològic | E44: De tipus geològic com terratrèmols, esllavissades, allaus, erupcions volcàniques
C45: 10.2 | D45: Pertorbacions d'origen metereològic | E45: Per fenòmens extrems com inundacions, temporals, pedregades, etc
A46: 11 | B46: Canvi global i/o climàtic | C46: 11.1 | D46: Impactes del canvi climàtic en sistemes físics i químics | E46: Canvis en sistemes físics i químics com acidificació d'oceans, augment del CO2 atmosfèric, pèrdua de sediments, colmatació de basses i llacunes, canvis en corrents marins, regressió de la línia de costa, subsidència del Delta, canvis en la cobertura de núvols, etc
C47: 11.2 | D47: Impactes del canvi climàtic relatius a l'alteració del règim de temperatures | E47: Canvis en règims de temperatures: onades de calor o de fred, canvis en la temperatura del mar, fusió de glaceres, etc
C48: 11.3 | D48: Impactes del canvi climàtic relatius a l'alteració del règim de precipitació i sequera | E48: Canvis en règims de precipitació i règims hidrològics com patrons de pluja, d'innivació, generant sequeres, increment de la severitat d'inundacions, reducció de la superfície de llacs i estanys, etc
C49: 11.4 | D49: Pujada del nivell del mar

Sheet Llistes
A1: Llista d'amenaces OS | D1: Si/No | F1: Codi Amenaça | G1: Nom Amenaça
A2: 0 | B2: No especificada | D2: Si | G2: No especificada
A3: 1 | B3: Urbanització i edificació | D3: No | F3: 1.1 | G3: Urbanització residencial
A4: 2 | B4: Producció primària | D4: Dubtós | F4: 1.2 | G4: Urbanització comercial o industrial
A5: 3 | B5: Producció d'energia i mineria | F5: 1.3 | G5: Àrees recretives i turístiques
A6: 4 | B6: Infrastructures de transport i serveis | F6: 2.1 | G6: Activitat agrícola
A7: 5 | B7: Extracció de recursos naturals | F7: 2.2 | G7: Plantacions forestals
A8: 6 | B8: Molèsties | F8: 2.3 | G8: Ramaderia
A9: 7 | B9: Gestió i modificació de sistemes naturals | F9: 2.4 | G9: Aqüicultura
A10: 8 | B10: Espècies invasores i patògens | F10: 3.1 | G10: Activitats de la mineria
A11: 9 | B11: Polució | F11: 3.2 | G11: Producció d'energia renovable
A12: 10 | B12: Grans pertorbacions naturals | F12: 4.1 | G12: Vials de transport
A13: 11 | B13: Canvi global i/o climàtic | F13: 4.2 | G13: Conduccions
F14: 4.3 | G14: Infrastructures marines
F15: 4.4 | G15: Tancaments i vallats
F16: 5.1 | G16: Caça i recol·lecció d'animals
F17: 5.2 | G17: Recol·lecció de vegetals
F18: 5.3 | G18: Treballs forestals
F19: 5.4 | G19: Pesca i semblants
F20: 6.1 | G20: Molèsties per activitats recreatives
F21: 6.2 | G21: Molèsties per activitats militars
F22: 6.3 | G22: Altres tipus de molèsties
F23: 6.4 | G23: Molèsties per activitats multitudinàries
F24: 7.1 | G24: Foc
F25: 7.2 | G25: Gestió de l'aigua
... F43: 11.4 | G43: Pujada del nivell del mar

Sheet BUIDAT_ACCIONS_vDec
A1: ORDRE | B1: DOCUMENT | C1: CODI OBJECTIU | D1: OBJECTIU | E1: CODI ACCIÓ | F1: ACCIÓ | G1: Executat/ planificat | H1: NO APLICA | I1: Comentaris ENP | J1: CODI OP | K1: OP | L1: OP MODIFICAT | M1: CODI NOU | N1: OP PROPOSTA | O1: Repetides
A2: 1 | B2: Estratègia de geoconservació | D2: Coneixement i seguiment | F2: Cartografia i caracterització de les formacions de travertí de la Vall de Sant Aniol | G2: Executat | J2: 06.2.1 | K2: Participar en l'elaboració de la cartografia que elabora la UIC
A3: 2 | B3: Estratègia de geoconservació | D3: Coneixement i seguiment | F3: Inventari-catàleg actualitzat de les coves, avencs, gorges i congostos | G3: Executat en part/en curs | I3: juntament amb el centre de la sostenibilitat territorial | J3: 06.1.1 | K3: Identificar i prioritzar els elements clau i d'interès per la gestió de la biodiversitat i geodiversitat de Catalunya es troben dins l'ENP (especies amenaçades, espècies exòtiques invasores,.. ) | O3: Similar a l'acció 16, 34 i 329
A4: 3 | B4: Estratègia de geoconservació | D4: Coneixement i seguiment | F4: Cartografia de punts d’interès geològic del sector de Lliurona, Albanyà i Bac Grillera | G4: Executat | J4: 06.2.1 | K4: Participar en l'elaboració de la cartografia que elabora la UIC
A5: 4 | B5: Estratègia de geoconservació | D5: Coneixement i seguiment | F5: Cartografia a 1:10.000 de les tarteres | J5: 06.2.1 | K5: Participar en l'elaboració de la cartografia que elabora la UIC
A6: 5 | B6: Estratègia de geoconservació | D6: Coneixement i seguiment | F6: Estudi de l’origen dels granits | G6: Executat en part/en curs | J6: 06.2.2 | K6: Conèixer i estudiar els processos naturals propis de l’espai, la seva funcionalitat, i ecologia en referència als ecosistemes | L6: Conèixer i estudiar els elements i processos naturals propis de l’espai, la seva tendència, funcionalitat, i ecologia, per al desenvolupament d'accions de gestió i conservació
A7: 6 | B7: Estratègia de geoconservació | D7: Coneixement i seguiment | F7: Descripció de l’estratigrafia del Cambroordovicià | G7: Executat en part/en curs | J7: 06.2.2 | K7: Conèixer i estudiar els processos naturals propis de l’espai, la seva funcionalitat, i ecologia en referència als ecosistemes | L7: Conèixer i estudiar els elements i processos naturals propis de l’espai, la seva tendència, funcionalitat, i ecologia, per al desenvolupament d'accions de gestió i conservació
A8: 7 | B8: Estratègia de geoconservació | D8: Coneixement i seguiment | F8: Beca per realitzar treballs de fi de grau, màster, etc. | J8: 13.2.4 | K8: Oferir projectes de recerca vinculats a l'espai natural per a l'alumnat universitari i de la XEEN
A9: 8 | B9: Estratègia de geoconservació | D9: Coneixement i seguiment | F9: Inventari de les mines, els forns de calç, les teuleries, les antigues pedreres, les fargues, etc. | J9: 04.1.1 | K9: Elaborar l'inventari i cartografia de patrimoni cultural de l'ENP, que també inclogui el patrimoni etnològic i immaterial
A10: 9 | B10: Estratègia de geoconservació | D10: Coneixement i seguiment | F10: Caracterització geològica de les mineralitzacions | J10: 06.2.2 | K10: Conèixer i estudiar els processos naturals propis de l’espai, la seva funcionalitat, i ecologia en referència als ecosistemes | L10: Conèixer i estudiar els elements i processos naturals propis de l’espai, la seva tendència, funcionalitat, i ecologia, per al desenvolupament d'accions de gestió i conservació
A11: 10 | B11: Estratègia de geoconservació | D11: Coneixement i seguiment | F11: Recull de la memòria històrica dels hidrocarburs (conceptes de canvi climàtic) | J11: 06.2.3 | K11: Conèixer els usos i factors de canvi rellevants en l'evolució dels elements de conservació, i avaluar els efectes que generen en l’espai (pressions i amenaces)
A12: 11 | B12: Estratègia de geoconservació | D12: Coneixement i seguiment | F12: Inventari de basses en la formació Bellmunt | H12: NA | I12: descartada, no n'hi ha | J12: 06.1.2 | K12: Definir espais fràgils i zones d'especial atenció
A13: 12 | B13: Estratègia de geoconservació | D13: Coneixement i seguiment | F13: Cartografia del perill de despreniments i esllavissades de les zones més freqüentades (població local o visitant) | J13: 06.2.3 | K13: Conèixer els usos i factors de canvi rellevants en l'evolució dels elements de conservació, i avaluar els efectes que generen en l’espai (pressions i amenaces)
A14: 13 | B14: Estratègia de geoconservació | D14: Coneixement i seguiment | F14: Anàlisi de l’evolució de les surgències del Gorg Blau, el Pont de Valentí, el Borró, Ormoier, etc. | H14: NA | I14: pendent estudi hidrogeològic ICGC (nosaltres fem de precursors) | J14: 06.2.2 | K14: Conèixer i estudiar els processos naturals propis de l’espai, la seva funcionalitat, i ecologia en referència als ecosistemes | L14: Conèixer i estudiar els elements i processos naturals propis de l’espai, la seva tendència, funcionalitat, i ecologia, per al desenvolupament d'accions de gestió i conservació
A15: 14 | B15: Estratègia de geoconservació | D15: Coneixement i seguiment | F15: Seguiment de l’erosió antròpica dels travertins vora les surgències (Sant Aniol, Pont del Llierca, etc. | H15: NA | I15: no de forma estructural, som conscient de les incidències pel treball de camp | J15: 06.2.3 | K15: Conèixer els usos i factors de canvi rellevants en l'evolució dels elements de conservació, i avaluar els efectes que generen en l’espai (pressions i amenaces)
A16: 15 | B16: Estratègia de geoconservació | D16: Coneixement i seguiment | F16: Seguiment cada cinc anys de les tarteres (Bassegoda, Guitarriu, Montmajor, etc.) | J16: 06.3.2 | K16: Adequar i executar el sistema de seguiment periòdic dels grups clau de l'ENP al sistema estàndard de seguiment
A17: 16 | B17: Estratègia de geoconservació | D17: Conservació dels elements del patrimoni geològic | F17: Elaboració de fitxes dels punts i les zones per l’inventari d'elements geològics | G17: Executat | J17: 06.1.1 | K17: Identificar i prioritzar els elements clau i d'interès per la gestió de la biodiversitat i geodiversitat de Catalunya es troben dins l'ENP (especies amenaçades, espècies exòtiques invasores,.. ) | O17: Similar a l'acció 16, 34 i 329
A18: 17 | B18: Estratègia de geoconservació | D18: Conservació dels elements del patrimoni geològic | F18: Acords de custòdia geològica amb els propietaris | H18: NA | I18: s'ha intentat però no ha prosperat, de moment es descarta | J18: 01.4.1 | K18: Fomentar acords de custòdia en espais d'alt valor dins l'ENP per a la gestió dels elements prioritaris
A19: 18 | B19: Estratègia de geoconservació | D19: Conservació dels elements del patrimoni geològic | F19: Planificació i execució de les accions de conservació dels elements d’interès geològic inventariats | G19: Executat | J19: 01.1.2 | K19: Adaptar i executar plans de gestió específics per a elements geològics de conservació prioritària dins l'ENP
A20: 19 | B20: Estratègia de geoconservació | D20: Conservació dels elements del patrimoni geològic | F20: Implicació de la pagesia en el manteniment d’espais oberts i recuperació d’elements d’interès que acompanyen el patrimoni geològic | G20: Executat en part/en curs | J20: 01.4.2 | K20: Fomentar bones pràctiques entre els col·lectius de propietaris i gestors del territori
A21: 20 | B21: Estratègia de geoconservació | D21: Conservació dels elements del patrimoni geològic | F21: Neteja i senyalització mínima dels punts i zones d’interès geològic de l’inventari | G21: En curs indefinidament | J21: 11.5.2 | K21: Implantar el programa de senyalització i manteniment
A22: 21 | B22: Estratègia de geoconservació | D22: Divulgació, educació i implicació de la societat | F22: Geoitinerari en format de custòdia geològica d’Ormoier, Sant Aniol i Riu | I22: a Hortmoier descartat, a Sant Aniol i riu ho treballem | J22: 14.2.1 | K22: Sensibilitzar als diferents agents sobre els valors de l'ENP
A23: 22 | B23: Estratègia de geoconservació | D23: Divulgació, educació i implicació de la societat | F23: Web, xarxes socials i Viquipèdia | I23: web i xxss publiquem si fem alguna acció, però no a viquipedia | J23: 14.3.1 | K23: Optimitzar els canals de comunicació | O23: Similar a les accions 67 i 377
A24: 23 | B24: Estratègia de geoconservació | D24: Divulgació, educació i implicació de la societat | F24: Incorporació de la geologia a les guies sensibilitzadores per als usuaris de l’espai | G24: Executat en part/en curs | I24: Creació de material específic | J24: 14.2.1 | K24: Sensibilitzar als diferents agents sobre els valors de l'ENP | O24: Similar a l'acció 24
A25: 24 | B25: Estratègia de geoconservació | D25: Divulgació, educació i implicació de la societat | F25: Mapes guies de diferents elements del patrimoni geològic de l’espai (parcel·les de coneixement) | G25: Executat en part/en curs | I25: Creació de material específic | J25: 14.2.1 | K25: Sensibilitzar als diferents agents sobre els valors de l'ENP | O25: Similar a l'acció 23
A26: 25 | B26: Estratègia de geoconservació | D26: Divulgació, educació i implicació de la societat | F26: Recurs pedagògic del paisatge i carst. *Itinerari Borró o Llierca | G26: Executat en part/en curs | I26: es descarten itineraris però s'estan creant materials especifics per temàtiques | J26: 13.2.3 | K26: Elaborar recursos educatius sobre l’espai (que tinguin en compte les problemàtiques singulars del seu espai) i posar-los a disposició dels centres educatius
A27: 26 | B27: Estratègia de geoconservació | D27: Divulgació, educació i implicació de la societat | F27: Activitat sobre la relació roques i homes *Itinerari Burró o Llierca | G27: Executat en part/en curs | I27: es descarten itineraris però s'estan creant materials especifics per temàtiques | J27: 13.2.3 | K27: Elaborar recursos educatius sobre l’espai (que tinguin en compte les problemàtiques singulars del seu espai) i posar-los a disposició dels centres educatius
A28: 27 | B28: Estratègia de geoconservació | D28: Divulgació, educació i implicació de la societat | F28: Activitat sobre la relació roques i homes *Itinerari Sant Feliu de Riu | G28: Executat en part/en curs | I28: es descarten itineraris però s'estan creant materials especifics per temàtiques | J28: 13.2.3 | K28: Elaborar recursos educatius sobre l’espai (que tinguin en compte les problemàtiques singulars del seu espai) i posar-los a disposició dels centres educatius
A29: 28 | B29: Estratègia de geoconservació | D29: Divulgació, educació i implicació de la societat | F29: Recurs pedagògic sobre l’aigua i el canvi climàtic *Itinerari Ormoier o Sant Aniol | G29: Executat en part/en curs | I29: es descarten itineraris però s'estan creant materials especifics per temàtiques | J29: 13.2.3 | K29: Elaborar recursos educatius sobre l’espai (que tinguin en compte les problemàtiques singulars del seu espai) i posar-los a disposició dels centres educatius
A30: 29 | B30: Estratègia de geoconservació | D30: Divulgació, educació i implicació de la societat | F30: Sortides, xerrades, etc. Anuals | G30: Executat en part/en curs | I30: es contempa al curs de bon coneixedor de la Garrotxa i s'ha fet alguna xerrada, es podries fer més | J30: 14.2.1 | K30: Sensibilitzar als diferents agents sobre els valors de l'ENP
A31: 30 | B31: Estratègia de geoconservació | D31: Divulgació, educació i implicació de la societat | F31: Curs d’introducció a la geologia de l’Alta Garrotxa (paisatge, relació amb l’home, etc.) | G31: Executat en part/en curs | I31: en curs, es contempa al curs de bon coneixedor de la Garrotxa | J31: 14.2.1 | K31: Sensibilitzar als diferents agents sobre els valors de l'ENP
A32: 31 | B32: Estratègia de geoconservació | D32: Divulgació, educació i implicació de la societat | F32: Llista de persones locals interessades a participar en la conservació (whatsapp, correu electrònic, etc.) | J32: 13.5.1 | K32: Identificar col·lectius estratègics implicats en la gestió i l'ús del territori | O32: Similar a l'acció 160
A33: 32 | B33: Estratègia de geoconservació | D33: Divulgació, educació i implicació de la societat | F33: Seguiment de les surgències d’aigua | I33: pendent estudi hidrogeològic ICGC | J33: 06.2.4 | K33: Conèixer l'impacte de les gestió de l'aigua, sobre la biodiversitat.
A34: 33 | B34: Estratègia de geoconservació | D34: Divulgació, educació i implicació de la societat | F34: Alteració i erosió d’unitats geològiques | J34: 06.2.3 | K34: Conèixer els usos i factors de canvi rellevants en l'evolució dels elements de conservació, i avaluar els efectes que generen en l’espai (pressions i amenaces)
A35: 34 | B35: Estratègia de geoconservació | D35: Divulgació, educació i implicació de la societat | F35: Realització d’un inventari de totes les coves i avencs de l’espai | G35: Executat en part/en curs | I35: creació de material específic | J35: 06.1.1 | K35: Identificar i prioritzar els elements clau i d'interès per la gestió de la biodiversitat i geodiversitat de Catalunya es troben dins l'ENP (especies amenaçades, espècies exòtiques invasores,.. ) | O35: Similar a l'acció 2
A36: 35 | B36: Estratègia de geoconservació | D36: Marc legal i governança | F36: Reunió taller un cop l’any per fer el seguiment i avaluar l’estratègia de geoconservació | G36: Executat en part/en curs | J36: 01.2.1 | K36: Implementar la metodologia de gestió adaptativa (Estàndards Oberts de Gestió Adaptativa a Catalunya) en tots els processos de l'ENP
A37: 36 | B37: Programa anual d'actuacions | D37: Natura | F37: Seguiment Dichoropetalum schottii i estudi demogràfic | G37: Executat en part/en curs | I37: es pot fer de nou un cop acabi el floralab, revisar notes de la darrera reunió amb la Sonia Herrando | J37: 06.3.2 | K37: Adequar i executar el sistema de seguiment periòdic dels grups clau de l'ENP al sistema estàndard de seguiment
A38: 37 | B38: Programa anual d'actuacions | D38: Natura | F38: Seguiment de Dryopteris remota i conservació de l'hàbitat | G38: Executat en part/en curs | J38: 06.3.2 | K38: Adequar i executar el sistema de seguiment periòdic dels grups clau de l'ENP al sistema estàndard de seguiment
A39: 38 | B39: Programa anual d'actuacions | D39: Natura | F39: Accions de conservació de tàxons de flora | G39: Executat en part/en curs | J39: 01.1.1 | K39: Implementar i executar plans de gestió específics per a hàbitats i espècies de conservació prioritària dins l'ENP | L39: Implementar i executar plans i mesures de gestió específiques per a hàbitats i espècies de conservació prioritària dins l'ENP | O39: Similar a l'acció 44
A40: 39 | B40: Programa anual d'actuacions | D40: Natura | F40: Seguiment de l’àliga daurada (Aquila chrysaetos) | G40: Executat en part/en curs | J40: 06.3.2 | K40: Adequar i executar el sistema de seguiment periòdic dels grups clau de l'ENP al sistema estàndard de seguiment
A41: 40 | B41: Programa anual d'actuacions | D41: Natura | F41: Seguiment de les espècies presa de grans rapinyaires | G41: Executat | J41: 06.3.2 | K41: Adequar i executar el sistema de seguiment periòdic dels grups clau de l'ENP al sistema estàndard de seguiment
A42: 41 | B42: Programa anual d'actuacions | D42: Natura | F42: Seguiment del trencalòs (Gypaetus barbatus) | G42: Executat en part/en curs | J42: 06.3.2 | K42: Adequar i executar el sistema de seguiment periòdic dels grups clau de l'ENP al sistema estàndard de seguiment
A43: 42 | B43: Programa anual d'actuacions | D43: Natura | F43: Seguiment de rapinyaires a l’ENP (SEGRE) | G43: Executat en part/en curs | J43: 06.3.2 | K43: Adequar i executar el sistema de seguiment periòdic dels grups clau de l'ENP al sistema estàndard de seguiment
A44: 43 | B44: Programa anual d'actuacions | D44: Natura | F44: Participació al Seguiment dels Ocells Comuns de Catalunya (SOCC) | G44: Executat en part/en curs | J44: 06.3.2 | K44: Adequar i executar el sistema de seguiment periòdic dels grups clau de l'ENP al sistema estàndard de seguiment
A45: 44 | B45: Programa anual d'actuacions | D45: Natura | F45: Millora d’hàbitats i control de flora invasora | G45: Executat en part/en curs | J45: 01.1.1 | K45: Implementar i executar plans de gestió específics per a hàbitats i espècies de conservació prioritària dins l'ENP | L45: Implementar i executar plans i mesures de gestió específiques per a hàbitats i espècies de conservació prioritària dins l'ENP | O45: Similar a l'acció 38
A46: 45 | B46: Programa anual d'actuacions | D46: Natura | F46: Projecte constructiu i document ambiental del connector fluvial al Gomarell | G46: Suport/Impuls | I46: Donem suport als ajuntaments en el desenvolupament | K46: NOU OP | M46: 01.3.7 | N46: Afavorir la connectivitat ecològica del territori
A47: 46 | B47: Programa anual d'actuacions | D47: Natura | F47: Diagnosi i proposta d’accions-custodia fluvial a la Muga | G47: Executat en part/en curs | J47: 01.4.1 | K47: Fomentar acords de custòdia en espais d'alt valor dins l'ENP per a la gestió dels elements prioritaris
A48: 47 | B48: Programa anual d'actuacions | D48: Natura | F48: Constitució d'una Taula de foc i elaboració dels projectes executius dels punts estratègics de gestió per incendis | G48: En curs indefinidament | I48: la taula funciona indefinidament. estem ara mateix elaborant els projectes executius dels primers pegs delimitats per Bombers, la resta els encarregarem més endavant. Posteriorment cal buscar finançament per al seva execució. Tenim un projecte amb FPC en el que som collaboradors, i preveiem executar les accions previstes ena quest projectes executius | J48: 02.2.2 | K48: Definir i planificar la gestió del foc per a la millora de l'ENP
A49: 48 | B49: Programa anual d'actuacions | D49: Natura | F49: Recuperació de pastures i d'hàbitsts d'espais oberts | G49: En curs indefinidament | J49: 01.3.5 | K49: Fomentar el paisatge en mosaïc | O49: Similar a les accions 117, 185 i 234
A50: 49 | B50: Programa anual d'actuacions | D50: Natura | F50: Acord de custòdia fluvial per la Reserva Natural Parcial de la Muga | G50: Executat en part/en curs | J50: 01.4.1 | K50: Fomentar acords de custòdia en espais d'alt valor dins l'ENP per a la gestió dels elements prioritaris | O50: Similar a l'acció 120
A51: 50 | B51: Programa anual d'actuacions | D51: Cultura | F51: Adequació de la rectoria de Sant Aniol | G51: Executat en part/en curs | I51: anirem fent millores progressivament | J51: 04.2.3 | K51: Coordinar i participar dels treballs de restauració arquitectònica i del patrimoni cultural
A52: 51 | B52: Programa anual d'actuacions | D52: Desenvolupament local | F52: Grup motor per al relleu agrari. Cens de cedents | G52: En curs indefinidament | J52: 07.1.1 | K52: Promoure i col·laborar en l'aplicació de Plans de Desenvolupament Local Sostenible
A53: 52 | B53: Programa anual d'actuacions | D53: Desenvolupament local | F53: Manteniment de punts d'aigua | G53: En curs indefinidament | I53: Aquí tenim un projecte amb FUndació Bionexus 2025-2026 | J53: 08.1.3 | K53: Promoure la recuperació i conservació de marges i punts d'aigua associats a la ramaderia i l'agricultura i d'interès per la biodiversitat | L53: Promoure l'adequació d'edificacions, la recuperació de marges i la conservació de punts d'aigua associats a la ramaderia i l'agricultura d'interès per la biodiversitat | O53: Similar a l'acció 77
A54: 53 | B54: Programa anual d'actuacions | D54: Desenvolupament local | F54: Manteniment de xarxa viària | G54: En curs indefinidament | J54: 11.2.1 | K54: Identificar i classificar la xarxa viària bàsica, secundària, senders i itineraris senyalitzats d'acord amb els ajuntaments | O54: Similar a l'acció 60
A55: 54 | B55: Programa anual d'actuacions | D55: Desenvolupament local | F55: Adequació i manteniment d'infraestructures de suport en nuclis | G55: En curs indefinidament | J55: 11.7.2 | K55: Disposar dels equipaments i infraestructures necessàries i accessibles per acollir, informar, facilitar la visita i garantir la seguretat dels visitants i la protecció de l'entorn
A56: 55 | B56: Programa anual d'actuacions | D56: Desenvolupament local | F56: Participació activa a la carta europea de turisme sostenible | G56: En curs indefinidament | I56: Estem treballant amb europarc perquè acreditin ENPAG pròpiament amb la CETS de la Garrotxa (1 procés,2 ENP acreditats) | J56: 09.1.1 | K56: Desplegar la Carta Europea de Turisme Sostenible (CETS)
A57: 56 | B57: Programa anual d'actuacions | D57: Coneixement | F57: Estudi sobre pol·linitzadors de l'Alta Garrotxa | G57: Executat en part/en curs | I57: Hem de valorar si podem fer seguiment de polinitzadors al 2027, per exemple | J57: 06.2.2 | K57: Conèixer i estudiar els processos naturals propis de l’espai, la seva funcionalitat, i ecologia en referència als ecosistemes | L57: Conèixer i estudiar els elements i processos naturals propis de l’espai, la seva tendència, funcionalitat, i ecologia, per al desenvolupament d'accions de gestió i conservació
A58: 57 | B58: Programa anual d'actuacions | D58: Ús Públic i Social | F58: Servei d'informació i sensibilització ambiental de l'espai natural protegit | G58: En curs indefinidament | J58: 14.2.1 | K58: Sensibilitzar als diferents agents sobre els valors de l'ENP
A59: 58 | B59: Programa anual d'actuacions | D59: Ús Públic i Social | F59: Projecte executiu associat al Pla Especial Urbanístic Autònom de l'Eix Central de l'ENP | G59: En curs indefinidament | I59: 2025 preveu el seguiment de la tramitació urbanística i si es pot encarregar la redacció del projecte executiu. Enguany no ha estat possible. 2027 en funció finançment, obres de millora dels aparcament | J59: 11.7.2 | K59: Disposar dels equipaments i infraestructures necessàries i accessibles per acollir, informar, facilitar la visita i garantir la seguretat dels visitants i la protecció de l'entorn
A60: 59 | B60: Programa anual d'actuacions | D60: Ús Públic i Social | F60: Manteniment d'itineraris, GRs i altres | G60: En curs indefinidament | I60: tenim un conveni amb el CCG i fem directament millores segons necessitats | J60: 11.5.2 | K60: Implantar el programa de senyalització i manteniment | O60: Similar a l'acció 78
A61: 60 | B61: Programa anual d'actuacions | D61: Ús Públic i Social | F61: Compte de Wikiloc per ENP de l'Alta Garrotxa | G61: En curs indefinidament | I61: El 2025 es posarà a punt (estem gairebé) i caldrà fer mantenimetn indefinidament | J61: 11.2.2 | K61: Treballar conjuntament amb els principals canals d’informació de rutes per prioritzar itineraris oficials dins l’ENP | O61: Similar a l'acció 53
A62: 61 | B62: Programa anual d'actuacions | D62: Ús Públic i Social | F62: Regulació de l'escalada | G62: En curs indefinidament | I62: Cal fer seguimetn incidències, tenim una comissió escalada, temes de BBPP, gestió de reequipaments. HO fem juntament amb SSTT i DG | J62: 11.1.3 | K62: Regular l'escalada i alpinisme, barranquisme, i espeleologia en base al model de Pla de protecció | O62: Similar a l'acció 200
A63: 62 | B63: Programa anual d'actuacions | D63: Ús Públic i Social | F63: Regulació del descens de barrancs | G63: En curs indefinidament | I63: Tramiten la sol·licitud de 6000 participants anual | J63: 11.1.3 | K63: Regular l'escalada i alpinisme, barranquisme, i espeleologia en base al model de Pla de protecció
A64: 63 | B64: Programa anual d'actuacions | D64: Ús Públic i Social | F64: Regulació de l'accés motoritzat | G64: En curs indefinidament | I64: Senyalitzacio, emissió autoritzacions de pas, aprovacions ajuntaments per prevenció incemdis, etc. | J64: 11.3.1 | K64: Regular l'accés i la circulació
A65: 64 | B65: Programa anual d'actuacions | D65: Ús Públic i Social | F65: Adequació i manteniment d'altres infraestructures i senyalització | G65: En curs indefinidament | J65: 11.5.2 | K65: Implantar el programa de senyalització i manteniment
A66: 65 | B66: Programa anual d'actuacions | D66: Ús Públic i Social | F66: Servei de guardes rurals | G66: En curs indefinidament | J66: 11.8.2 | K66: Millorar la coordinació amb els cossos de seguretat per efectuar accions de control i vigilància
A67: 66 | B67: Programa anual d'actuacions | D67: Ús Públic i Social | F67: La Garrotxa Soft & Smart County. Destinació turística sostenible i intel·ligent | G67: En curs, fins a finals de 2027 | J67: 09.2.2 | K67: Crear productes i paquets turístics amb associacions d’empreses turístiques i operadors turístics
A68: 67 | B68: Programa anual d'actuacions | D68: Educació i Voluntariat | F68: Pàgina web, xarxes socials i bulletí@ | G68: En curs indefinidament | J68: 14.3.1 | K68: Optimitzar els canals de comunicació | O68: Similar a les accions 22 i 377
A69: 68 | B69: Programa anual d'actuacions | D69: Educació i Voluntariat | F69: Elaboració i edició de material interpretatiu del territori | G69: En curs indefinidament | J69: 14.1.2 | K69: Garantir l'accessibilitat i gestió del coneixement disponible sobre l'ENP | O69: Similar a l'acció 123
A70: 69 | B70: Programa anual d'actuacions | D70: Educació i Voluntariat | F70: Projecte socioeducatiu | G70: EN PROCÉS 2024_executat | J70: 13.2.3 | K70: Elaborar recursos educatius sobre l’espai (que tinguin en compte les problemàtiques singulars del seu espai) i posar-los a disposició dels centres educatius
A71: 70 | B71: Programa anual d'actuacions | D71: Educació i Voluntariat | F71: Programa estratègic d'educació i voluntariat ambiental de l'ENP | G71: EN PROCÉS 2024_en desenvolupament i millora segons els PLecs | J71: 13.6.2 | K71: Establir un model de coordinació territorial amb agents clau del voluntariat ambiental
A72: 71 | B72: Programa anual d'actuacions | D72: Educació i Voluntariat | F72: Adequació del centre d'acollida i interpretació de l'ENP de l'Alta Garrotxa | G72: EN PROCÉS 2024_2025 especialment i indefinidament millores | J72: 11.7.2 | K72: Disposar dels equipaments i infraestructures necessàries i accessibles per acollir, informar, facilitar la visita i garantir la seguretat dels visitants i la protecció de l'entorn
A73: 72 | B73: Pla d'impuls a la ramaderia extensiva | D73: Contractació d'un/a tècnic/a de desenvolupament ramader i agrari | F73: Contractació d'un/a tècnic/a de desenvolupament ramader i agrari | J73: 16.6.2 | K73: Gestió de personal
A74: 73 | B74: Pla d'impuls a la ramaderia extensiva | D74: Compensació per la prestació de serveis ambientals de la ramaderia extensiva | F74: Elaboració d’un Programa de compensació pels serveis ambientals de la pastura | G74: Executat | I74: Fem de precursors i busquem fórmules de finançament propis i a través d'altres institucions | K74: NOU OP | M74: 08.1.4 | N74: Suport tècnic, material i/o econòmic per a la fixació d'aprofitaments i usos benificiosos per a l'espai | O74: Similar a l'acció 76
A75: 74 | B75: Pla d'impuls a la ramaderia extensiva | D75: Compensació per la prestació de serveis ambientals de la ramaderia extensiva | F75: Redacció de Plans de Pastura prescrita | G75: 2025 en col·labroació amb la FPC | J75: 01.3.5 | K75: Fomentar el paisatge en mosaïc
A76: 75 | B76: Pla d'impuls a la ramaderia extensiva | D76: Compensació per la prestació de serveis ambientals de la ramaderia extensiva | F76: Ampliació i recuperació de pastures | G76: En curs indefinidament | I76: HO fem anualment | J76: 01.3.5 | K76: Fomentar el paisatge en mosaïc
A77: 76 | B77: Pla d'impuls a la ramaderia extensiva | D77: Compensació per la prestació de serveis ambientals de la ramaderia extensiva | F77: Pagament pel servei ambiental de manteniment de pastures | I77: s'estan buscant fórmules amb la FPC, DG i LIfeECO ADAPT. FEm de percursors però no tenim capacitat ara mateix | K77: NOU OP | M77: 08.1.4 | N77: Suport tècnic, material i/o econòmic per a la fixació d'aprofitaments i usos benificiosos per a l'espai | O77: Similar a l'acció 73
A78: 77 | B78: Pla d'impuls a la ramaderia extensiva | D78: Adequació d'intraestructures per a la pastura | F78: Infraestructures per a l’abastiment d’aigua | G78: 2025 i indefinidament | I78: Tenim un conveni amb la FUndació bionexus per a la millora d epunts d'aigua i tenim partida per al manteniment de punts d'aigua de l'espai | J78: 08.1.3 | K78: Promoure la recuperació i conservació de marges i punts d'aigua associats a la ramaderia i l'agricultura i d'interès per la biodiversitat | L78: Promoure l'adequació d'edificacions, la recuperació de marges i la conservació de punts d'aigua associats a la ramaderia i l'agricultura d'interès per la biodiversitat | O78: Similar a l'acció 52
A79: 78 | B79: Pla d'impuls a la ramaderia extensiva | D79: Adequació d'intraestructures per a la pastura | F79: Millora de la xarxa de camins | G79: 2025 i indefinits | I79: veure conveni que tenim amb el CCG | J79: 11.7.2 | K79: Disposar dels equipaments i infraestructures necessàries i accessibles per acollir, informar, facilitar la visita i garantir la seguretat dels visitants i la protecció de l'entorn | O79: Similar a l'acció 59
A80: 79 | B80: Pla d'impuls a la ramaderia extensiva | D80: Adequació d'intraestructures per a la pastura | F80: Infraestructures de suport al maneig del bestiar | G80: puntual | K80: NOU OP | M80: 08.1.4 | N80: Suport tècnic, material i/o econòmic per a la fixació d'aprofitaments i usos benificiosos per a l'espai
A81: 80 | B81: Pla d'impuls a la ramaderia extensiva | D81: Adequació d'intraestructures per a la pastura | F81: Cabanes per als pastors | H81: NA | I81: nosaltres no ho fem. hem donat suport a boscos per posar una cabana a monars | J81: 04.3.2 | K81: Recuperar i conservar el patrimoni cultural rural vinculat específicament a construccions de pedra en sec
A82: 81 | B82: Pla d'impuls a la ramaderia extensiva | D82: Implementació d'eines d'innovació en el maneig de la pastura | F82: Estudi i innovació en mètodes de recuperació i manteniment de pastures | G82: Suport/Impuls | I82: col·laborem amb FPC, cremes prescrites | J82: 08.1.1 | K82: Acompanyar i assessorar els productors agraris per millorar les tècniques productives agràries i afavorir la conservació dels hàbitats i paisatges | L82: Assessorar i donar suport als productors agropecuaris per l'aplicació de bones pràctiques argopecuàries en la conservació dels hàbitats i les espècies presents | O82: Similar a l'acció 82
A83: 82 | B83: Pla d'impuls a la ramaderia extensiva | D83: Implementació d'eines d'innovació en el maneig de la pastura | F83: Implementació d’eines digitals per al control i seguiment del bestiar | G83: Prova pilot de seguiment de collars | I83: Els hem comprat el 2024 però farem seguiment juntamnet amb la FPC per veure la seva viabilitat i si és el cas ho impulsarem a l'ENP | J83: 08.1.1 | K83: Acompanyar i assessorar els productors agraris per millorar les tècniques productives agràries i afavorir la conservació dels hàbitats i paisatges | L83: Assessorar i donar suport als productors agropecuaris per l'aplicació de bones pràctiques argopecuàries en la conservació dels hàbitats i les espècies presents | O83: Similar a l'acció 81
A84: 83 | B84: Pla d'impuls a la ramaderia extensiva | D84: Suport a la transhumància | F84: Manteniment de la ruta transhumant | G84: Executat | I84: ho hem fet segons sol·licituds, ho podem fer si ens ho demana algun pastor, però no està previst. | J84: 04.1.3 | K84: Elaborar la cartografia de la xarxa de camins ramaders i senders tradicionals de l'ENP
A85: 84 | B85: Pla d'impuls a la ramaderia extensiva | D85: Suport a l'activitat ramadera mitjançant el control de malalties | F85: Creació d’un programa de suport sanitari a la ramaderia (PSSR) | H85: NA | I85: no som competeents | J85: 08.1.1 | K85: Acompanyar i assessorar els productors agraris per millorar les tècniques productives agràries i afavorir la conservació dels hàbitats i paisatges | L85: Assessorar i donar suport als productors agropecuaris per l'aplicació de bones pràctiques argopecuàries en la conservació dels hàbitats i les espècies presents
A86: 85 | B86: Pla d'impuls a la ramaderia extensiva | D86: Dinamització del producte local | F86: Dinamització d’un punt de venta de producte local | G86: Suport/Impuls | I86: adrinoc | J86: 08.3.3 | K86: Promoure fires d'artesania i productes locals de l'ENP | L86: Promoure els productes locals de l'ENP
A87: 86 | B87: Pla d'impuls a la ramaderia extensiva | D87: Dinamització del producte local | F87: Impuls d’obradors compartits | K87: NOU OP | M87: 08.1.4 | N87: Suport tècnic, material i/o econòmic per a la fixació d'aprofitaments i usos benificiosos per a l'espai
A88: 87 | B88: Pla d'impuls a la ramaderia extensiva | D88: Coexistència amb fauna | F88: Comissió per la coexistència amb cànids i resta de fauna | I88: HO porta el servei de fauna i el CAR. De moment no ho toquem però suposem que en algun moment ho haurem de fer. de moment indefinit. | J88: 01.3.3 | K88: Generar pertorbacions controlades
A89: 88 | B89: Pla d'impuls a la ramaderia extensiva | D89: Coexistència amb fauna | F89: Preparació i protecció envers atacs de cànids i altra fauna | I89: HO porta el servei de fauna i el CAR. De moment no ho toquem però suposem que en algun moment ho haurem de fer. de moment indefinit. | J89: 08.1.1 | K89: Acompanyar i assessorar els productors agraris per millorar les tècniques productives agràries i afavorir la conservació dels hàbitats i paisatges | L89: Assessorar i donar suport als productors agropecuaris per l'aplicació de bones pràctiques argopecuàries en la conservació dels hàbitats i les espècies presents
A90: 89 | B90: Pla d'impuls a la ramaderia extensiva | D90: Governança i gestió | F90: Convivència de la ramaderia amb visitants per oci o per altres Activitats | G90: Executat en part/en curs | I90: segons incidències (senuyalitzacio, tanques, etc) | J90: 13.4.1 | K90: Desplegar en el territori les campanyes de sensibilització i bones pràctiques que s'impulsin des de la DG
A91: 90 | B91: Pla d'impuls a la ramaderia extensiva | D91: Governança i gestió | F91: Creació d’una borsa de pastures i ramades: finques, pastors/es i explotacions ramaderes | G91: Executat en part/en curs | I91: en col·laboracióa mb ADRINOC, vinculat al grup de relleu agrari | K91: NOU OP | M91: 08.1.4 | N91: Suport tècnic, material i/o econòmic per a la fixació d'aprofitaments i usos benificiosos per a l'espai
A92: 91 | B92: Pla d'impuls a la ramaderia extensiva | D92: Governança i gestió | F92: Organització de formacions | J92: 08.1.2 | K92: Oferir formació als productors agraris per millorar el seu coneixement sobre tècniques eficients i respectuoses amb la conservació del patrimoni natural i cultural
A93: 92 | B93: Pla d'impuls a la ramaderia extensiva | D93: Governança i gestió | F93: Creació d’una associació de ramaders/es de l’Alta Garrotxa | I93: es una cosa que entenem que han de dinamitzar ells mateixos, si bé tenim molt de contacte, valorar si el treball conjunt es considera. POdem fer referència a establir llaços amb el sector ramader | J93: 08.2.1 | K93: Establir una relació contínua amb agents socioeconòmics del territori, i si s'escau, crear una Taula de desenvolupament local
A94: 93 | B94: Pla d'impuls a la ramaderia extensiva | D94: Governança i gestió | F94: Taula de treball transfronterera | G94: Executat en part/en curs | I94: La tenim però només amb els Acaldes, surten molts temes. FOrmem part del Pais art i història. | J94: 15.1.1 | K94: Crear una taula de treball amb els agents prioritaris per a la gestió de l'ENP i els grups de treball temàtics necessaris
A95: 94 | B95: Pla d'educació ambiental i voluntariat | D95: Activitats i programes d'educació ambiental i entitats i accions de voluntariat ambiental | F95: Redacció del projecte socioeducatiu de l'ENP de l'Alta Garrotxa | G95: Executat | J95: 13.1.1 | K95: Definir el model de Xarxa d'Escoles de l'Espai Natural (XEEN) a l'ENP amb els agents educatius del territori
A96: 95 | B96: Pla d'educació ambiental i voluntariat | D96: Activitats i programes d'educació ambiental i entitats i accions de voluntariat ambiental | F96: Elaboració de programes de formació i sensibilització a l'ENP de l'Alta Garrotxa. | G96: en curs segons els plecs, 2025 en endavant | J96: 13.3.1 | K96: Establir un model de coordinació territorial amb agents clau de l'educació ambiental
A97: 96 | B97: Pla d'educació ambiental i voluntariat | D97: Activitats i programes d'educació ambiental i entitats i accions de voluntariat ambiental | F97: Implementació de programes de formació i sensibilització a l'ENP de l'Alta Garrotxa | G97: en curs segons els plecs, 2025 en endavant | J97: 13.5.2 | K97: Executar els projectes de sensibilització i formació dirigits al sector turístic, esportiu i de lleure
A98: 97 | B98: Pla d'educació ambiental i voluntariat | D98: Activitats i programes d'educació ambiental i entitats i accions de voluntariat ambiental | F98: Creació de l'oferta pedagògica i recursos didàctics per a l'educació formal. | G98: en curs segons els plecs, 2025 en endavant | J98: 13.2.3 | K98: Elaborar recursos educatius sobre l’espai (que tinguin en compte les problemàtiques singulars del seu espai) i posar-los a disposició dels centres educatius | O98: Similar a l'acció 98
A99: 98 | B99: Pla d'educació ambiental i voluntariat | D99: Activitats i programes d'educació ambiental i entitats i accions de voluntariat ambiental | F99: Implementació de l'oferta pedagògica i recursos didàctics per a l'educació formal | G99: en curs segons els plecs, 2025 en endavant | J99: 13.2.3 | K99: Elaborar recursos educatius sobre l’espai (que tinguin en compte les problemàtiques singulars del seu espai) i posar-los a disposició dels centres educatius | O99: Similar a l'acció 97
A100: 99 | B100: Pla d'educació ambiental i voluntariat | D100: Activitats i programes d'educació ambiental i entitats i accions de voluntariat ambiental | F100: Creació d'un programa d'activitats per a l'educació no formal | G100: en curs segons els plecs, 2025 en endavant | J100: 13.4.4 | K100: Adaptar el programa de divulgació i sensibilització de l'ENP perquè incorpori una oferta d’activitats dirigida al lleure educatiu
...

Sheet BUIDAT_ACCIONS_vNov
A1: DOCUMENT | B1: OBJECTIU | C1: ACCIÓ | D1: EXECUTADA | E1: COMENTARIS AG
A2: Estratègia de geoconservació | B2: Coneixement i seguiment | C2: Cartografia i caracterització de les formacions de travertí de la Vall de Sant Aniol | D2: si
A3: Estratègia de geoconservació | B3: Coneixement i seguiment | C3: Inventari-catàleg actualitzat de les coves, avencs, gorges i congostos | D3: en curs | E3: juntament amb el centre de la sostenibilitat territorial
A4: Estratègia de geoconservació | B4: Coneixement i seguiment | C4: Cartografia de punts d’interès geològic del sector de Lliurona, Albanyà i Bac Grillera | D4: si
A5: Estratègia de geoconservació | B5: Coneixement i seguiment | C5: Cartografia a 1:10.000 de les tarteres | D5: no
A6: Estratègia de geoconservació | B6: Coneixement i seguiment | C6: Estudi de l’origen dels granits | D6: en curs
A7: Estratègia de geoconservació | B7: Coneixement i seguiment | C7: Descripció de l’estratigrafia del Cambroordovicià | D7: en curs
A8: Estratègia de geoconservació | B8: Coneixement i seguiment | C8: Beca per realitzar treballs de fi de grau, màster, etc. | D8: no
A9: Estratègia de geoconservació | B9: Coneixement i seguiment | C9: Inventari de les mines, els forns de calç, les teuleries, les antigues pedreres, les fargues, etc. | D9: no
A10: Estratègia de geoconservació | B10: Coneixement i seguiment | C10: Caracterització geològica de les mineralitzacions | D10: no
A11: Estratègia de geoconservació | B11: Coneixement i seguiment | C11: Recull de la memòria històrica dels hidrocarburs (conceptes de canvi climàtic) | D11: no
A12: Estratègia de geoconservació | B12: Coneixement i seguiment | C12: Inventari de basses en la formació Bellmunt | D12: descartada, no n'hi ha
A13: Estratègia de geoconservació | B13: Coneixement i seguiment | C13: Cartografia del perill de despreniments i esllavissades de les zones més freqüentades (població local o visitant) | D13: no
A14: Estratègia de geoconservació | B14: Coneixement i seguiment | C14: Anàlisi de l’evolució de les surgències del Gorg Blau, el Pont de Valentí, el Borró, Ormoier, etc. | D14: no, pendent estudi hidrogeològic ICGC (nosaltres fem de precursors)
A15: Estratègia de geoconservació | B15: Coneixement i seguiment | C15: Seguiment de l’erosió antròpica dels travertins vora les surgències (Sant Aniol, Pont del Llierca, etc. | D15: no de forma estructural, som conscient de les incidències pel treball de camp
... A38: Estratègia de geoconservació | B38: Marc legal i governança | C38: Reunió taller un cop l’any per fer el seguiment i avaluar l’estratègia | D38: en curs
A39: Programa anual d'actuacions | B39: Natura | C39: Seguiment Dichoropetalum schottii i estudi demogràfic | D39: 2022, 2023, 2024-2028 | E39: es pot fer de nou un cop acabi el floralab, revisar notes de la darrera reunió amb la Sonia Herrando
A40: Programa anual d'actuacions | B40: Natura | C40: Seguiment de Dryopteris remota i conservació de l'hàbitat | D40: 2022, en curs
A41: Programa anual d'actuacions | B41: Natura | C41: Accions de conservació de tàxons de flora | D41: 2023, 2024, en curs
A42: Programa anual d'actuacions | B42: Natura | C42: Seguiment de poblacions de preses a Comanegra | D42: 2022
A43: Programa anual d'actuacions | B43: Natura | C43: Seguiment de l’àliga daurada (Aquila chrysaetos) | D43: 2022, 2023, en curs
A44: Programa anual d'actuacions | B44: Natura | C44: Altres seguiments d'avifauna | D44: 2022, en curs
A45: Programa anual d'actuacions | B45: Natura | C45: Seguiment de les espècies presa de grans rapinyaires | D45: 2023
A46: Programa anual d'actuacions | B46: Natura | C46: Seguiment del trencalòs (Gypaetus barbatus) | D46: 2023, en curs
A47: Programa anual d'actuacions | B47: Natura | C47: Seguiment de rapinyaires a l’ENP (SEGRE) | D47: 2023, en curs
A48: Programa anual d'actuacions | B48: Natura | C48: Participació al Seguiment dels Ocells Comuns de Catalunya (SOCC) | D48: 2023, en curs
A49: Programa anual d'actuacions | B49: Natura | C49: Millora d’hàbitats i control de flora invasora | D49: 2022, 2023, 2024, en curs
A50: Programa anual d'actuacions | B50: Natura | C50: Projecte constructiu i document ambiental del connector fluvial al Gomarell | D50: 2022, 2023, 2025 | E50: Donem suport als ajuntaments en el desenvolupament
A51: Programa anual d'actuacions | B51: Natura | C51: Diagnosi i proposta d’accions-custodia fluvial a la Muga | D51: 2023, en curs
A52: Programa anual d'actuacions | B52: Natura | C52: Recuperació d'hàbitsts d'espais oberts | D52: EN PROCÉS 2024 i 2025
A53: Programa anual d'actuacions | B53: Natura | C53: Acord de custòdia fluvial per la Reserva Natural Parcial de la Muga | D53: EN PROCÉS 2024 2025-2028
A54: Programa anual d'actuacions | B54: Cultura | C54: Adequació de la rectoria de Sant Aniol | D54: EN PROCÉS 2024 i 2025 i futur | E54: anirem fent millores progressivament
A55: Programa anual d'actuacions | B55: Desenvolupament local | C55: Grup motor per al relleu agrari. Cens de cedents | D55: EN PROCÉS 2024 en curs indefinidament
A56: Programa anual d'actuacions | B56: Desenvolupament local | C56: Recuperació de pastures | D56: EN PROCÉS 2024en curs indefinidament
A57: Programa anual d'actuacions | B57: Desenvolupament local | C57: Manteniment de punts d'aigua | D57: EN PROCÉS 2024-en curs indefinidament | E57: Aquí tenim un projecte amb FUndació Bionexus 2025-2026
A58: Programa anual d'actuacions | B58: Desenvolupament local | C58: Manteniment de xarxa viària | D58: EN PROCÉS 2024en curs indefinidament
