Workbook

Sheet ESTRATÈGIA
C3: ESQUEMA CONCEPTUAL PER A LA ELABORACIÓ DEL PLA ESTRATÈGIC EN EL MARC
C4: DELS ESTÀNDARDS OBERTS PER A LA GESTIÓ ADAPTATIVA A CATALUNYA

Sheet INSTRUCCIONS
A1: PESTANYA DE PRIORITZACIÓ
A2: Llistat elements: | B2: Tasca 1: Revisar el llistat d'elements prioritzats per tal d'avaluar si cal afegir-ne algun o treure'n algun. A la columna comentaris cal argumentar, breument, el perquè de la decisió.
A4: Llistat amenaces: | B4: Tasca 2: A partir de la taxonomia d'amenaces que es troba a la pestanya final, cal omplir les tres columnes (E, F i G) amb les tres principals amenaces per a la conservació de l'element. S'afegeixi una darrera columna per si hi ha amenaces que no es troben incloses a la taxonomia.
A6: PESTANYA DEL PLA
A7: Explicacions:
B8: 7 Eixos temàtics
B9: Els objectius generals estan directament associats als objectius generals dels Plans de Protecció del medi naatural i del paisatge. NO ES PODEN RETOCAR
B10: Objectius estratègics: definits en un grup de treball intern de serveis Centrals i dels Parcs durant l'any 2023. NO ES PODEN RETOCAR
B11: Objectius operacionals: definits en un grup de treball intern de serveis Centrals i dels Parcs durant l'any 2023
A14: Tasques a realitzar:
A15: Objectius operacionals: | B15: El llistat d'objectius operacionals té una columna al costa (columna I) on s'indica si l'objectiu és obligatori de mantenir al Pla estratègic o no.
B16: Tasca 1: Columna I. Revisar els que es posa com a obligatoris per veure si són realment aplicables a l'espai o no.
B17: Tasca 2: Columna I. Revisar els que posa "Opcional" per identificar els que són aplicables o no a l'espai. O, també, determinar si algun d'ells seria aplicable o es pot concretar millor el redactat de l'objectiu.
B18: Tasca 3: Columna J. En ambdós casos, cal posar a la columna J, el redactat final de l'objectiu concretat a l'espai. En el cas de que l'objectiu s'elimina, posar "NA". Ara es reprodueix el redactat dels objectius operacionals derivats del grup de treball esmentat
B19: Tasca 4: Columna K. Per tots els casos en que hi ha modificació respecte al redactat original de l'objectiu operatiu -i, també, en el cas que es consideri que s'ha d'eliminar-, a la columna K cal redactar molt breument el motiu pel qual es prèn la decisió.
B20: Tasca 5: Columna L. Incloure un Si/No avaluant si l'objectiu operatiu podria tenir mesures a incorporar a la programació d'actuacions de l'espai (Si) o, per altra banda, el seu assoliment depèn d'altres òrgans, com l'ACA o altres serveis dins la DGPAMN (No).
B21: Tasca 6: Columna M. Definir la prioritat que hauria de tenir l'assoliment de l'objectiu (màxima, si cal assolir en els propers 4 anys, o altrament alta, mitja o baixa). També hi ha l'opció de prioritat a assolir a més llarg termini.
A22: Propostes genèriques d'accions: | B22: Tasca 7: Columna N. En aquest columna cal introduir les accions, de manera genèrica, que caldria aplicar a l'espai per tal d'assolir l'objectiu operatiu. No es tracta d'un llistat d'accions concretes si no, més aviat, accions generals que acabarien concretant-se en la programació anual. PER A INICIAR AMB LA TAULA US PODEU BASAR MOLT EN LA FEINA JA FETA DE PRIORITZACIÓ DE MESURES PEL MAP
B23: En el cas dels objectius operatius que s'ha considerat que no són aplicables a l'espai, cal avaluar si podrien tenir alguna acció que sí tindria sentit d'incloure al Pla estratègic tot i que l'objectiu de manera global no hi ´seria d'aplicació.
A24: Indicadors: | B24: Tasca 8: Columna Q. Posar un indicar SMART per avaluar el compliment de la mesura proposada a la columna N
A25: Fites a assolir en 4 anys: | B25: Tasca 9: Posar un valor de l'indicador a asolir: valor mínim necessari (columna R) o valor desitjable (columna S).
A26: Hores de dedicació: | B26: Tasca 10: Columna T. Realitzar una aproximació el més acurada que es pugui de les hores del personal de gestió de l'espai que cal destinar per a la realització de l'acció.
A27: Àrea responsable: | B27: Tasca 11: Columna U. Indicar quina àrea de l'equip de gestió és responsable de coordinar l'execució de l'acció.
A28: Persona responsable: | B28: Tasca 12: Columna V. Indicar quina persona dins l'àrea seria l'encarregada.
A30: PESTANYA DEL VINCLE
A31: Definir vincle amenaça vs. Obj. Operatiu | B31: Tasca 1: Establir / Revisar el vincle entre les amenaces identificades a la pestanya de priorització i els objectius operatius definits a la columna J de la pestanya Pla. La columna B conté el llistat dels objectius operatius tal i com quedaran definits després de la vostra revisió.
B32: Tasca 2: En cas que es pugui, definir l'amenaça / factor / causa concret a la que atén l'objectiu definit al Pla. Poden ser més d'una.
B33: És important que es visualitzi a quina amenaça es dirigeix l'objectiu operatiu que es proposa al Pla, tot i que, no sempre hi ha d'haver un vincle clar. Pot haver algun objectiu sense amenaça vinculada.

Sheet PRIORITZACIÓ
A2: Llistats corresponent a l'espai de Natura 2000 ES5120002"Capçaleres del Ter i del Freser"
A3: LLISTAT D'ELEMENTS PRESENT A L'ESPAI | E3: AMENACES PER A CADA ELEMENT
A4: Hàbitats d'interès comunitari | B4: Prioritzat | C4: Puntuació índex rellevància | D4: Comentaris en cas de canvi en la priorització | E4: Amenaça 1 segons taxonomia | F4: Amenaça 2 segons taxonomia | G4: Amenaça 3 segons taxonomia | H4: Altres amenaces
A5: 3110 - Aigües estagnants oligotròfiques, molt poc mineralitzades (Littorelletalia uniflorae) | J5: Nota: La priorització d'elements actual inclou els Elements Clau que es van determinar en l'instrument de gestió aprovat amb l'Acord de Govern 150/2014 (Annex 6)
A6: 3130 - Aigües estagnants oligotròfiques o mesotròfiques amb vegetació de Littorelletea uniflorae i/o Isoëto-nanojuncetea | J6: Aquest Acord era per les Zones Especials de Conservació, no per les ZEPA i, per tant, no es va fer l'exercici de priorització de les aus.
A7: 3240 - Rius de tipus alpí amb bosquines de muntanya | J7: També inclou el primer quartil de l'exercici de la UIC per prioritzar els elements present a cada espai de Natura 2000, és a dir, el 25% dels
A8: 4030 - Landes atlàntiques i subatlàntiques seques | J8: elements amb major índex de rellevància a l'espai. Veure document metodològic aquí:
A9: 4060 - Matollars alpins i boreals | B9: Si | C9: 2.625 | E9: Impactes del canvi climàtic relatius a l'alteració del règim de precipitació i sequera | F9: Impactes del canvi climàtic relatius a l'alteració del règim de temperatures | J9: https://gencat.sharepoint.com/sites/Informaciiconeixementpatrimoninatural2/Documents%20compartits/Forms/AllItems.aspx?csf=1&web=1&e=3x4ZkK&ovuser=3b9427dc%2Dd30e%2D43bc%2D8c06%2Dff7253676fec%2Cjordiparpal%40gencat%2Ecat&OR=Teams%2DHL&CT=1713942253212&clic
A10: 4090 - Matollars xerocàntics endèmics oromediterranis | B10: No | D10: Hàbitat molt poc present al parc | J10: El llistat original d'elements prové de les taules del MAP que heu estat treballant amb el SENP
A11: 5110 - Boixedes xerotermòfiles permanents, dels vessants rocosos
A12: 5120 - Formacions muntanyenques de bàlec (Genista balansae subsp. europaea = Cytisus purgans)
A13: 5130 - Formacions de Juniperus communis colonitzadores de landes o de pastures calcícoles | B13: No | C13: 3.625 | D13: Hàbitat en expansió en deteriorament d'altres hàbitats que si que es consideren prioritaris
A14: 6110p - Prats calcàris o basòfils d'Alysso-Sedion albi (*)
A15: 6140 - Gespets tancats, silicícoles, dels Pirineus
A16: 6170 - Prats calcícoles alpins i subalpins | B16: Si | C16: 2.625 | E16: Impactes del canvi climàtic relatius a l'alteració del règim de precipitació i sequera | F16: Impactes del canvi climàtic relatius a l'alteració del règim de temperatures | G16: Ramaderia
A17: 6210 - Prats -i fàcies emmatades- medioeuropeus, seminaturals, sobre substrat calcari (Festuco-Brometea)
A18: 6230p - Prats de pèl caní (Nardus stricta), rics florísticament, dels terrenys silicis de la muntanya mitjana atlàntica o subatlàntica | B18: Si | E18: Desaparició d'activitats tradicionals | F18: Impactes del canvi climàtic relatius a l'alteració del règim de precipitació i sequera | G18: Impactes del canvi climàtic relatius a l'alteració del règim de temperatures | H18: Maneig ramader
A19: 6410 - Herbassars de Molinia coerulea en sòls calcaris torbosos o argil·lollimosos (Molinion caeruleae) | B19: No | C19: 2.625 | D19: Hàbitat molt poc present al parc
A20: 6420 - Jonqueres i herbassars graminoides humits, mediterranis, del Molinio-Holoschoenion
A21: 6430 - Herbassars higròfils, tant de marges i vorades com de l'alta muntanya | B21: Si | C21: 5.125 | E21: Impactes del canvi climàtic relatius a l'alteració del règim de precipitació i sequera | F21: Impactes del canvi climàtic relatius a l'alteració del règim de temperatures | G21: Desaparició d'activitats tradicionals
A22: 6510 - Prats de dall de terra baixa i de la muntanya mitjana (Arrhenatherion) | B22: Si | D22: Tot i ser un hàbitat poc present al Parc, es troba en regressió arreu i a més a més és possible conservar-lo amb mesures de gestió activa. | E22: Desaparició d'activitats tradicionals
A23: 6520 - Prats de dall altimontans i subalpins (Triseto-Polygonion bistortae) | B23: Si | C23: 2.625 | E23: Desaparició d'activitats tradicionals
A24: 7110p - Torberes altes actives
A25: 7220p - Fonts petrificants amb formació de travertí (Cratoneurion commutati) | B25: No | C25: 2.75 | D25: Hàbitat molt poc present al parc
A26: 7230 - Molleres alcalines | B26: Si | C26: 2.875 | E26: Ramaderia | F26: Impactes del canvi climàtic relatius a l'alteració del règim de precipitació i sequera | G26: Impactes del canvi climàtic relatius a l'alteració del règim de temperatures
A27: 7240p - Formacions pioneres alpines del Caricion bicoloris-atrofuscae
A28: 8110 - Tarteres silícies medioeuropees i dels indrets freds i humits de l'alta muntanya (Galeopsietalia ladani i Androsacetalia alpinae)
A29: 8130 - Tarteres de l'Europa meridional amb vegetació poc o molt termòfila | B29: Si | E29: Molèsties per activitats recreatives
A30: 8210 - Costers rocosos calcaris amb vegetació rupícola | B30: Dubtós | D30: Hàbitat interessant dins el Parc ja que tan sols es troba en alguns sectors específics i acull espècies de flora d'interès. Tot i així, no presenta amenaces clares
A31: 8220 - Costers rocosos silicis amb vegetació rupícola
A32: 8230 - Terraprims silicis amb vegetació pionera (Sedo-Scleranthion)
A33: 8310 - Coves no explotades pel turisme | B33: Si | E33: Molèsties per activitats recreatives
A34: 8340 - Glaceres permanents | B34: Dubtós | D34: Hàbitat rar a Catalunya, i especialment vulnerable a causa del canvi climàtic. Al Parc el trobem representat per una forma atípica: glaceres rocalloses
A35: 9120 - Fagedes acidòfiles
A36: 9130 - Fagedes neutròfiles
A37: 9180p - Boscos de vessants rostos, tarteres o barrancs, del Tilio-Acerion | B37: Dubtós | D37: Hàbitat molt poc present al parc
A38: 91E0p - Vernedes i altres boscos de ribera afins (Alno-Padion)
A39: 9430 - Boscos de pi negre (Pinus uncinata) sobre substrat silici
A40: 9430p - Boscos de pi negre (Pinus uncinata) sobre substrat calcari | B40: Dubtós | C40: 2.875 | D40: És un hàbitat escàs al Parc i no es coneixen amenaces clares que puguin condicionar la seva persistència.
A42: Espècies d'interès comunitari | B42: Prioritzat | C42: Puntuació índex rellevància | D42: Comentaris en cas de canvi en la priorització | E42: Amenaça 1 segons taxonomia | F42: Amenaça 2 segons taxonomia | G42: Amenaça 3 segons taxonomia | H42: Altres amenaces
A43: Accipiter gentilis gentilis | B43: No
A44: Accipiter nisus | B44: No
A45: Aegithalos caudatus | B45: No
A46: Aegolius funereus | B46: Si | C46: 1.944 | E46: Impactes del canvi climàtic relatius a l'alteració del règim de precipitació i sequera | F46: Treballs forestals | G46: Molèsties per activitats recreatives
A47: Alauda arvensis | B47: No
A48: Alytes obstetricans | B48: No
A49: Anas platyrhynchos | B49: No
A50: Anthus campestris | B50: No
A51: Anthus spinoletta | B51: Dubtós | C51: 1.556 | D51: Espècie abundant i ben distribuïda al Parc.
A52: Anthus trivialis | B52: No
A53: Aquila chrysaetos | B53: Dubtós | D53: Malgrat ser una espècie en expansió es tracta d'una espècie clau a l'espai, únic gran depredador present actualment. | E53: Molèsties per activitats recreatives | F53: Conduccions | G53: Residus sòlids
A54: Arnica montana | B54: Dubtós | D54: Espècie que era abundant i que actualment s'està rarificant | E54: Recol·lecció de vegetals | F54: Ramaderia
A55: Arvicola sapidus | B55: Si | D55: Espècie amb presència confirmada dins el Parc que es troba amenaçada i en regressió. | E55: Espècies invasores | F55: Gestió de l'aigua
A56: Asio otus | B56: No
A57: Barbastella barbastellus | B57: Si | D57: Espècie catalogada com a vulnerable, present a l'espai | E57: Treballs forestals | F57: Molèsties per activitats recreatives | G57: Gestió d'hàbitats | H57: Desaparició d'activitats tradicionals
A58: Bubo bubo | B58: No
A59: Buxbaumia viridis | B59: Si | C59: 1.833 | E59: Treballs forestals | F59: Impactes del canvi climàtic relatius a l'alteració del règim de precipitació i sequera | G59: Impactes del canvi climàtic relatius a l'alteració del règim de temperatures
A60: Calotriton asper | B60: Si | D60: Espècie endèmica del Pirineu i relativament escassa. Al Parc es troba present només en alguns torrents determinats | E60: Impactes del canvi climàtic relatius a l'alteració del règim de precipitació i sequera | F60: Gestió de l'aigua | G60: Espècies invasores | H60: Polució aquàtica
A61: Canis lupus | B61: Si | C61: 2.167 | E61: Caça i recol·lecció d'animals
A62: Caprimulgus europaeus | B62: No
A63: Carduelis citrinella | B63: No
A64: Certhia brachydactyla all others | B64: No
A65: Charadrius morinellus | B65: Dubtós | D65: Espècie amenaçada. S'han constatat diversos intents de nidificació al Pirineu, alguns dels quals a les proximitats del Parc. Aquests individus nidificants es desconeix si són ocasionals o si realment es tracta d'una població desconectada de la resta d'Europa. A més a més, el Pirineu oriental té un paper rellevant durant la migració. | E65: Impactes del canvi climàtic relatius a l'alteració del règim de precipitació i sequera | F65: Molèsties per activitats recreatives | G65: Ramaderia
A66: Cinclus cinclus | B66: No
A67: Circaetus gallicus | B67: No
A68: Columba palumbus palumbus | B68: No
A69: Corallorhiza trifida | B69: Si | E69: Treballs forestals | F69: Impactes del canvi climàtic relatius a l'alteració del règim de precipitació i sequera | G69: Impactes del canvi climàtic relatius a l'alteració del règim de temperatures
A70: Coronella austriaca | B70: Si | C70: 1.667 | E70: Impactes del canvi climàtic relatius a l'alteració del règim de temperatures | F70: Espècies desestabilitzades | G70: Vials de transport
A71: Corvus corax | B71: No
A72: Corvus corone | B72: No
A73: Coturnix coturnix | B73: No
A74: Cuculus canorus | B74: No
A75: Cyanistes caeruleus | B75: No
A76: Daphne alpina | B76: No | D76: Es desconeix la seva presència a l'espai
A77: Delichon urbicum | B77: No
A78: Delphinium montanum | B78: Si | D78: Espècie que s'ha afegit a la llista ja que es considera una espècie prioritària a l'espai, malgrat no ser d'interès comunitari. És una espècie endèmica del Pirineu Oriental, amb un nombre baix de localitats. | E78: Impactes del canvi climàtic relatius a l'alteració del règim de precipitació i sequera | F78: Impactes del canvi climàtic relatius a l'alteració del règim de temperatures | G78: Ramaderia | H78: Molèsties per activitats recreatives
A79: Dendrocopos major | B79: No
A80: Dryocopus martius | B80: No
A81: Emberiza cia | B81: No | C81: 1.833 | D81: Malgrat estar en regressió a Catalunya és una espècie poc present al Parc Natural, i la gestió que es faci poc podrà incidir en la conservació d'aquesta espècie. A més a més, al ripollès és una espècie abundant i ben distribuïda a cotes baixes
A82: Emberiza citrinella | B82: Dubtós | D82: Espècie que s'ha afegit a la llista per estar catalogada com a vulnerable al catàleg de fauna amenaçada de Catalunya, i perquè la seva conservació es veu afectada per a la gestió que es dugui a terme. | E82: Desaparició d'activitats tradicionals | F82: Ramaderia | G82: Impactes del canvi climàtic relatius a l'alteració del règim de temperatures
A83: Emberiza hortulana | B83: Dubtós | D83: Podria considerar-se prioritari però al Parc Natural l'hàbitat potencial és escàs i es coneix tan sols un sol punt confirmat de nidificació. La gestió poc incidirà en l'espècie | E83: Desaparició d'activitats tradicionals | F83: Ramaderia
A84: Epidalea calamita | B84: No
A85: Eptesicus serotinus | B85: No
A86: Eriogaster catax | B86: Dubtós | D86: Es desconeix la seva presència a l'espai.
A87: Erithacus rubecula | B87: No
A88: Euphydryas aurinia | B88: Dubtós | D88: D'entrada no es considera prioritaria però podria tenir interès la presència de la subespècie pyrenesdebilis. | E88: Ramaderia
A89: Falco peregrinus | B89: No
A90: Falco tinnunculus | B90: No
A91: Felis silvestris | B91: No
A92: Fringilla coelebs all others | B92: No
A93: Galemys pyrenaicus | B93: Si | E93: Gestió de l'aigua | F93: Espècies invasores
A94: Garrulus glandarius | B94: No
A95: Gentiana lutea | B95: No
A96: Graellsia isabellae | B96: No
A97: Gypaetus barbatus | B97: Si | D97: Espècie amenaçada amb presència recurrent dins l'espai, on ha fet diversos intents de nidificació. El Parc es troba pròxim al límit de distribució actual de la població nidificant, i a més és un espai inclòs dins el pla de recuperació de l'espècie. | E97: Desaparició d'activitats tradicionals | F97: Espècies desestabilitzades | G97: Molèsties per activitats recreatives
A98: Gyps fulvus | B98: No
A99: Hieraaetus pennatus | B99: No
A100: Hierophis viridiflavus | B100: Dubtós | D100: Espècie segurament en regressió, que es veu perjudicada per l'expansió de la serp verda, més termòfila i abundant. | E100: Desaparició d'activitats tradicionals | F100: Impactes del canvi climàtic relatius a l'alteració del règim de temperatures | G100: Espècies desestabilitzades | H100: Vials de transport
A101: Hypsugo savii | B101: No
A102: Lacerta agilis | B102: Si | C102: 2.167 | E102: Desaparició d'activitats tradicionals | F102: Ramaderia | G102: Impactes del canvi climàtic relatius a l'alteració del règim de precipitació i sequera | H102: Impactes del canvi climàtic relatius a l'alteració del règim de temperatures
...

Sheet PLA
A1: MODEL DE PLA ESTRATÈGIC PELS ENP
B2: Espai natural protegit: | C2: Capçaleres del Ter i del Freser
T3: Fita a assolir en 4 anys | V3: Gestió interna
A4: EIXOS | C4: OBJECTIUS Generals (PP) | E4: OBJECTIUS Estratègics | G4: OBJECTIUS operatius / Línia estratègica | H4: Comú / Específic | I4: Obligatori / Optatiu | J4: Objectiu operatiu concret a l'espai | K4: Explicació de la decisió presa en el cas de canvis respecte al llistat inicial (columna G) | L4: Objectiu amb mesures incorporables a la planificació anual de la gestió de l'espai? | M4: Prioritat | N4: Propostes genèriques d'accions | O4: Vincles amb d'altres accions | P4: MODIFICACIONS PENDENTS | Q4: Marc de referència | R4: Resultats derivats | S4: indicadors | T4: Mínima | U4: Màxim (Desitjable) | V4: Hores de dedicació | W4: Àrea responsable | X4: Persona responsable / Persona a implicar | Y4: Documentació vinculada | Z4: 2025 | AA4: 2026 | AB4: 2027 | AC4: 2028 | AD4: Comentaris
A5: NATURA | B5: 1 | C5: CONSERVAR LA NATURA i restaurar els ecosistemes, els processos naturals i seminaturals, la biodiversitat i la geodiversitat associada. | D5: 01.1 | E5: Adequar i fer eficient la conservació dels elements objecte de gestió prioritària marcats per la DG a l'ENP | F5: 01.1.1 | G5: Implementar i executar plans de gestió específics per a hàbitats i espècies de conservació prioritària dins l'ENP | H5: Comú | I5: Obligatori | J5: =G5 -> Implementar i executar plans de gestió específics per a hàbitats i espècies de conservació prioritària dins l'ENP | L5: Si | M5: MÀXIMA | N5: 1) Realització d'accions per a la millora dels elements prioritzats a l'espai: - Actuacions de millora d'hàbitat per el gall fer - Recuperació de sistemes de mollera - Reducció de l'impacte de la freqüentació en zones d'alta muntanya | Q5: MAP | R5: SFF: Elaboració de plans de gestió específics per a espècies de conservació prioritària i directrius de gestió d'hàbitats. SFF/SENP: Definir a nivell de cluster quins son els que es poden elaborar conjuntament. | S5: 1) Projectes de gestió activa i/o adaptatiu lligat a l'objectiu 1.2.1 duts a terme per a la millora dels elements de conservació prioritària 2) Nombre de seguiments efectuats per diferents tipologies (sòls, espècies herbàcies, interès farratger i invertebrats) en les 23 parcel·les de seguiment establertes 3) classificació de l'estat eològic de pastures altimontanes i subalpines amb elemètode del transsecte (percentage de bon estat, regular i dolent) | T5: 1) 5 2) 4 3) avaluar-ne 30 (>50% bon estat) | U5: 1) 5 2) 8 3) avaluar-ne 50 (> 80% bon estat) | V5: =200+200 -> 400 | W5: Patrimoni natural/Sistemes agropastorals | X5: Anna Planella/Bernat Perramon | Y5: Posar només projectes de seguiment (POCTEFA Redbio) i recuperació espais oberts??? | AD5: Fusionar-lo amb el 6.1.1.
F6: 01.1.2 | G6: Adaptar i executar plans de gestió específics per a elements geològics de conservació prioritària dins l'ENP | H6: Comú | I6: Obligatori | J6: =G6 -> Adaptar i executar plans de gestió específics per a elements geològics de conservació prioritària dins l'ENP | L6: Si | M6: ALTA | N6: 1) Accions de conservació i protecció dels elements geològics: - Retirada d'elements que afecten el patrimoni geològic (creus, làpides...) - Retirada de les construccions de pedres (tipus vivac) i accions de difusió per limitar-les. - Protecció d'elements considerats d'interès (per exemple, protecció del dipòsit morrènic de Queralbs) - Dur a terme una gestió preventiva sobre els usos i activitats que poden afectar la conservació del patrimoni geològic - Divulgació i sensibilització del patrimoni geològic | S6: 1) Percentatge d'elements geològics detectats en mal estat de conservació durant l'inventariat geològic, en els que s'ha actuat 2) Percentatge d'elements geològics que presenten un risc, que disposen d'elements de senyalització. 3) Nombre d'elements que afecten el patrimoni geològic retirats | T6: 1) 75% 2) 50% 3) 10 | U6: 1) 100% 2) 100% 3) 20 | V6: 160 | W6: Patrimoni natural | X6: Anna Planella
D7: 01.2 | E7: Executar les mesures de gestió directa previstes en els intruments de planificació per la conservació i la gestió adaptativa dels elements clau de l'ENP | F7: 01.2.1 | G7: Implementar la metodologia de gestió adaptativa (Estàndards Oberts de Gestió Adaptativa a Catalunya) en tots els processos de l'ENP | H7: Comú | I7: Obligatori | J7: =G7 -> Implementar la metodologia de gestió adaptativa (Estàndards Oberts de Gestió Adaptativa a Catalunya) en tots els processos de l'ENP | L7: Si | M7: ALTA | N7: 1) Definició d'un protocol per tal d'incorporar la metodologia dels Estàndards Oberts pels processos més rellevants per a la conservació a l'espai 2) Creació d'un sistema de seguiment de les accions de gestió de l'espai i un adequat mecanisme de gestió adaptativa de les mateixes | Q7: ESNATURA | R7: SENP: Elaboració d'un manual per la implementació dels OSAM | S7: 1) Percentatge de projectes transversals que incorporin la metodologia d'Estàndards Oberts 2) Percentatge d'accions dutes a terme a l'espai que disposen d'un sistema de seguiment i un adequat mecanisme de gestió adaptativa | T7: 0.75 | U7: 1 | V7: =50*6+100 -> 400 | W7: Transversal | X7: Tots/es
F8: 01.2.2 | G8: Executar les mesures previstes en els plans de conservació o recuperació d'espècies amenaçades de forma coordinada amb el Servei de Flora i Fauna en l'àmbit de l'ENP | H8: Comú | I8: Obligatori | J8: =G8 -> Executar les mesures previstes en els plans de conservació o recuperació d'espècies amenaçades de forma coordinada amb el Servei de Flora i Fauna en l'àmbit de l'ENP | L8: Si | M8: MÀXIMA | N8: 1) Execució de les accions dins els plans que pertoquin a cada espai (incorporar totes les mesures que surten als plans ja aprovats que tenen incidència a l'espai) 2) Implicació i participació en la redacció dels plans de conservació /recuperació d'espècies amenaçades 3) Col.laboració en l'obtenció de la informació necessària dins els espais per al desenvolupament dels Plans | Q8: MAP Catàlegs | R8: SFF: Elaboració de plans de conservació o recuperació d'espècies protegides | S8: 1) Percentatge d'accions executades incloses dins de plans de recuperació/conservació d'espècies amenaçades presents a l'espai 2) Nombre de plans de recuperació/conservació d'espècies amenaçades presents a l'espai en els que s'ha participat de forma activa en la seva redacció | T8: 1) 25% 2) 2 | U8: 1) 50% 2) 4 | V8: 150 | W8: Patrimoni natural | X8: Anna Planella
F9: 01.2.3 | G9: Executar les mesures de gestió previstes en els plans de control i erradicació d'espècies exòtiques de forma coordinada amb el Servei de Flora i Fauna en l'àmbit de l'ENP | H9: Comú | I9: Obligatori | J9: =G9 -> Executar les mesures de gestió previstes en els plans de control i erradicació d'espècies exòtiques de forma coordinada amb el Servei de Flora i Fauna en l'àmbit de l'ENP | L9: Si | M9: MÀXIMA | N9: 1) Implementació anual dels plans de control i erradicació d'espècies de fauna exòtiques invasores. 2) Implementació anual dels plans de control i erradicació d'espècies de flora exòtiques invasores. 3) Establir seguiment de col·lonització del seneci en diferents escencaris com en les zones de recuperació de pastures 4) Elaborar pautes de maneig ramader per reduir la col·lonització de seneci en prats de manera preventiva 5) eliminació flora exòtica invasora de zones sensibles | Q9: ESNATURA MAP | R9: SFF: Elaboració de plans de control i erradicació d'espècies exòtiques | S9: 1) Campanyes de control de fauna exòtica invasora fluvial dutes a terme 2) Nombre d'espècies de fauna exòtica invasora (visó americà, coipú,...) detectada dins el Parc Natural. 3) Seguiments específics per estudiar comportament espècies exòtiques invasores 4) Elaboració d'un pla de control del seneci del cap, orientat a la identificació de zones conflictives per la seva presència (zones amb espècies sensibles, zones d'especial interés per a la ramaderia, etc.) 5) actuacions elliminació flora exòtica invasora | T9: 1) 4 (1/any) 2) 0 3) 1 4) pautes generals 5) suport en actuacions PNCTF (exemple_recuperació espais oberts) | U9: 1) 8 (2/any) 2) 0 3) 2 4) pautes desglossades per hàbitats i gestió associada 5)actuacions específiques d'eliminació | V9: 1 i 2) 30h + equip exòtiques SFF 3) 100h + serveis externs 4) 50h 5) brigades + voluntariat (no es comptabilitzen les h) | W9: Patrimoni natural / Sistemes agropastorals | X9: Anna Planella / Bernat Parramon
F10: 01.2.4 | G10: Desplegar els objectius i tasques recollits en els instruments de referència i compromisos internacionals | H10: Específic | I10: Optatiu | J10: =G10 -> Desplegar els objectius i tasques recollits en els instruments de referència i compromisos internacionals | L10: Si | M10: MITJANA | N10: 1) Participació en l'execució de projectes transfronterers 2) Establir mecanismes de col·laboració transfronterera en diferents formats (jornades de treball, jornades de divulgació, reunions conjuntes, etc.). Article 3 punts 2b i 2c del Decret 211/2015 | S10: 1)Nombre de projectes transfronterers en els que s'ha participat (POCTEFA Red-BIO, POCTEFA Floralab+ i POCTEFA Transmuntanya) 2) Nombre de reunions, activitats, etc/any | T10: 3 | U10: 6 | V10: 460 | W10: Patrimoni natural/Sistemes agropastorals/Millora rural/Direcció/Administració | X10: Anna Planella/Bernat Perramon/Gerard Vila/Santi Farriol/Fàtima
D11: 01.3 | E11: Crear ecosistemes complexes, resilients, i d'alta biodiversitat per garantir la recuperació dels processos ecosistèmics | F11: 01.3.1 | G11: Identificar espais pel foment de la dinàmica natural i l'aprofitament no extractiu | H11: Comú | I11: Obligatori | J11: =G11 -> Identificar espais pel foment de la dinàmica natural i l'aprofitament no extractiu | L11: Si | M11: ALTA | N11: Afavorir la creació d'hàbitats per a la conservació d'espècies | Q11: ESNATURA | R11: SENP/SFF: Definir criteris metodològics | S11: 1) Nombre d'hectàrees gestionades per a la conservació d'espècies (recuperació d'espais oberts, millores forestals, etc.) | T11: 1) 20 | U11: 1) 50 | V11: =(80*2)+50 -> 210 | W11: Patrimoni natural, Sistemes agropastorals, Millora rural | X11: Anna, Bernat, Gerard
F12: 01.3.2 | G12: Afavorir la maduresa dels sistemes forestals | H12: Específic | I12: Optatiu | J12: =G12 -> Afavorir la maduresa dels sistemes forestals | L12: Si | M12: ALTA | N12: Definir criteris per classificació dels boscos madurs Creació d'un catàleg dels rodals amb bosc madur dins del PN Participació projecte Life Uncinata Participació projecte Redbio | Q12: MAP | R12: SENP/SFF: Definir criteris metodològics | S12: Número d'actuacions o projectes destinats afavorir la maduresa forestal | T12: 2 | U12: 4 | V12: 240 | W12: Millora rural | X12: Gerard Vila
F13: 01.3.3 | G13: Generar pertorbacions controlades | H13: Específic | I13: Optatiu | J13: NA | K13: No aplica. No es preveu com a mètode per assolir aquests ecosistemes complexes | Q13: MAP | R13: SENP/SFF: Definir criteris metodològics
F14: 01.3.4 | G14: Restaurar la dinàmica natural dels rius | H14: Específic | I14: Optatiu | J14: NA | K14: No seria una mesura prioritaria dins l'espai natural. Poca superfície de bosc de ribera, de laminació... | M14: FORA DEL TERMINI DEL PLA | N14: Realització i impuls de la renaturalització de lleres i creació de zones de laminació dins l'ENP en base als criteris metodològics predefinits | Q14: MAP | R14: SENP/SFF: Definir criteris metodològics | S14: Superfície (ha) on s'han realitzat actuacions de millora (aclarides, plantacions...) | T14: 20 | U14: 80 | V14: =80*2*4 -> 640 | W14: Patrimoni Natural + Millora rural | X14: Gerard Vila / Anna Planella
F15: 01.3.5 | G15: Fomentar el paisatge en mosaïc | H15: Específic | I15: Optatiu | J15: =G15 -> Fomentar el paisatge en mosaïc | L15: Si | M15: ALTA | N15: Recuperació i manteniment dels espais oberts identificats com a prioritaris segons els estudis previs realitzats des del PN | Q15: ESNATURA | R15: SENP/SFF: Definir criteris metodològics | S15: 1) Actuacions de recuperació en zones identificades com a prioritaries a mantenir obertes o en en zones que es consideren prioritàries a recuperar (estudi Minuàrtia) 2) Ajuts per manteniment d'hàbitats amb pasturatge | T15: 1) 1 2) 10 | U15: 1) 12 2) 30 | V15: =60+60 -> 120 | W15: Sistemes agropastorals / Millora Rural | X15: Bernat Perramon / Gerard Vila
F16: 01.3.6 | G16: Gestionar i intervenir en la dinàmica de poblacions de fauna que no tenen depredador natural | H16: Específic | I16: Optatiu | J16: =G16 -> Gestionar i intervenir en la dinàmica de poblacions de fauna que no tenen depredador natural | L16: Si | M16: ALTA | N16: 1) Participació i impuls en el control directe de poblacions de fauna, en fase a criteris metodològics predefinits, que suposin una amenaça per a la ramaderia, hàbitats o espècies amenaçats | R16: SENP/SFF: Definir criteris metodològics | S16: 1) Hectàrees en les que s'ha dut a terme un control anual de depredadors per a la millora de l'estat de conservació del gall fer o altres espècies amenaçades, segons metodologia predefinida | T16: 0 a 1000 | U16: 4000 | V16: 180 | W16: Patrimoni natural | X16: Anna Planella
D17: 01.4 | E17: Alinear l'activitat de propietaris i gestors del territori amb la conservació, millora i restauració dels valors de l'ENP | F17: 01.4.1 | G17: Fomentar acords de custòdia en espais d'alt valor dins l'ENP per a la gestió dels elements prioritaris | H17: Comú | I17: Optatiu | J17: =G17 -> Fomentar acords de custòdia en espais d'alt valor dins l'ENP per a la gestió dels elements prioritaris | L17: Si | M17: BAIXA | N17: Realització d'acords de custòdia aplicant el model d'acord elaborat per Serveis Centrals | Q17: MAP | R17: SENP/SENP: Dissenyar el protocol i elaborar un model d'acord | S17: Número d'acords de custòdia duts a terme | T17: 1 | U17: 2 | V17: 60 | W17: Patrimoni Natural | X17: Anna Planella
F18: 01.4.2 | G18: Fomentar bones pràctiques entre els col·lectius de propietaris i gestors del territori | H18: Comú | I18: Optatiu | J18: =G18 -> Fomentar bones pràctiques entre els col·lectius de propietaris i gestors del territori | L18: Si | M18: ALTA | N18: Elaboració bones pràctiques de maneig ramader i fauna cinegètica pel desenvolupament actuacions així com participació en projectes conjunts | S18: 1) Treballs sobre bones pràctiques 2) actuacions per fomentar bones pràctiques 3) Coordinació en la gestió 4) Organització de jornades conjuntes 5) Participacií en projectes conjunts | T18: 1) 1 2) 2 3) 2 4) 1 5) 1 | U18: 1) 2 2) 4 3) 4 4) 2 5) 2 | V18: 60 | W18: Sistemes agropastorals | X18: Bernat Perramon
F19: 01.4.3 | G19: Impulsar la coordinació amb els ens locals en la gestió finques públiques situades dins d’ENP | H19: Específic | I19: Optatiu | J19: =G19 -> Impulsar la coordinació amb els ens locals en la gestió finques públiques situades dins d’ENP | L19: Si | M19: MÀXIMA | N19: Realització de projectes de forma col·laborativa amb els ens locals per a la gestió de boscos comunals i lleres i boscos de ribera | Q19: ESNATURA | S19: Nombre de projectes col·laboratius CEINR X PNCTF X GENCAT | T19: 3 | U19: 6 | V19: =20+40+100+100 -> 260 | W19: Transversal | X19: Gerard Vila / Anna Planella/Bernat Perramon/Santi Farriol
B20: 2 | C20: ADAPTAR ELS ECOSISTEMES AL CANVI CLIMÀTIC i millorar-ne la resiliència en front dels riscos associats. | D20: 02.1 | E20: Planificar l'adaptació dels sistemes naturals al canvi climàtic | F20: 02.1.1 | G20: Adaptar i implementar el Pla d'adaptació de l'ENP al canvi climàtic | H20: Comú | I20: Obligatori | J20: =G20 -> Adaptar i implementar el Pla d'adaptació de l'ENP al canvi climàtic | K20: No hi ha perspectiva de fer un pla específic per temes de canvi climàtic. Les actuacions ja estan recollides dins dels objectius de fomentar el paisatge en mosaic i l'objectiu de prevenció d'incendis | M20: FORA DEL TERMINI DEL PLA | R20: OCCC/SENP: Elaboració del model de Pla d'adaptació dels ENP al canvi climàtic
F21: 02.1.2 | G21: Gestionar i planificar els recursos hídrics de l'ENP | H21: Comú | I21: Obligatori | J21: =G21 -> Gestionar i planificar els recursos hídrics de l'ENP | L21: Si | M21: ALTA | N21: Creació de la cartografia dels recursos hídrics de l'ENP i les seves amenaces (per exemple captacions d'aigua) | S21: Cartografia creada que cobreixi tot l'ENP sobre els recursos hídrics existents i les seves amenaces | T21: 1 (cartografia) | U21: 1 (cartografia) | V21: =40+40 -> 80 | W21: Millora rural | X21: Gerard Vila / Anna Planella
F22: 02.1.3 | G22: Participar en la redacció i execució dels instruments d'ordenació forestal sostenible i per la conservació en finques públiques | H22: Específic | I22: Optatiu | J22: =G22 -> Participar en la redacció i execució dels instruments d'ordenació forestal sostenible i per la conservació en finques públiques | K22: Aportació ramaders i proietaris així combsector conservacionista | L22: Si | M22: MITJANA | N22: Participació en la redacció d'IOF de finques públiques Realització de tractaments silvícoles i tallades selectives Promoció de boscos mixtes i de la biodiversitat Foment de la fusta de baixa qualitat per a l'aprofitamet de biomassa Incloure conceptes d'evolució lliure i del manual 11 d'Europarc | R22: DGEFMN: Redacció d'IOF en finques públiques | S22: % d'actuacions forestals (finca pública i dins PN) en les que s'ha participat de forma activa des del PN | T22: 50 | U22: 100 | V22: =20+200+200 -> 420 | W22: Millora rural | X22: Gerard Vila/Anna Planella/Bernat Perramon
F23: 02.1.4 | G23: Promoure la redacció d'instruments d'ordenació forestal per reduir la sensibilitat i vulnerabilitat dels boscos al canvi climàtic en finques privades | H23: Específic | I23: Optatiu | J23: =G23 -> Promoure la redacció d'instruments d'ordenació forestal per reduir la sensibilitat i vulnerabilitat dels boscos al canvi climàtic en finques privades | L23: Si | M23: MITJANA | N23: * Realització d'accions per donar a conèixer subvencions entre propietaris | S23: % de superfície de finques privades amb IOF dins del PN | T23: 60 | U23: 100 | V23: 200 | W23: Millora rural | X23: Gerard Vila
D24: 02.2 | E24: Planificar la prevenció i extinció d’incendis forestals i la gestió del foc de forma coordinada amb els diferents agents del territori | F24: 02.2.1 | G24: Redactar i implementar el Pla de Prevenció d'Incendis | H24: Comú | I24: Obligatori | J24: =G24 -> Redactar i implementar el Pla de Prevenció d'Incendis | L24: Si | M24: MÀXIMA | N24: *Elaboració del Pla de Prevenció d'Incendis *Definició de: xarxa estratègica i complementària de vials forestals, xarxa estratègica i complementària de punts d’aigua, tractaments de vegetació, punts estratègics de gestió | Q24: ESNATURA | R24: Equip de PPI: Disseny del protocol de treball | S24: Aprovació del PPIFF del PNCTF | T24: 1 | U24: 1 | V24: =80*4 -> 320 | W24: Millora rural | X24: Gerard Vila
F25: 02.2.2 | G25: Definir i planificar la gestió del foc per a la millora de l'ENP | H25: Específic | I25: Optatiu | J25: =G25 -> Definir i planificar la gestió del foc per a la millora de l'ENP | L25: Si | M25: ALTA | N25: Integració de criteris sobre zones sensibles al foc i zones no sensibles pels valors naturals que hi alberguen | R25: SPEN: Elaboració d'un model de pla de gestió | S25: % de cartografia compartida amb els diferents departaments per tal de determinar en quines zones cal actuar si hi ha un incendi i en quines no | T25: 60 | U25: 100 | V25: 200 | W25: Millora rural | X25: Gerard Vila
F26: 02.2.3 | G26: Treballar per a la prevenció d'incendis juntament amb els propietaris, ajuntaments, protecció civil, ADF i bombers. | H26: Comú | I26: Obligatori | J26: Treballar per a la prevenció d'incendis juntament amb els propietaris, ajuntaments, protecció civil, ADF i bombers. També amb ramaders i empreses del sector forestal | K26: Aportació sector ranmader i propietat privada | L26: Si | M26: MITJANA | N26: Execució de les actuacions recollides dins del PNCTF / Integrar la variable prevenció d'incendis en la recuperació i manteniment d'espais oberts | S26: Número d'actuacions d'interès per la prevenció IIFF | T26: 2 | U26: 8 | V26: 200 | W26: Millora rural | X26: Gerard Vila
B27: 3 | C27: PROTEGIR LA BIODIVERSITAT, i especialment els elements fràgils i amenaçats, d’interès comunitari o de major interès natural. | D27: 03.1 | E27: Prevenir, minimitzar i compensar els impactes ambientals dels usos i activitats que es desenvolupin en l'àmbit de l'ENP | F27: 03.1.1 | G27: Participar en les consultes dels procesos d'Avaluació Ambiental que afectin directament o indirectament l’espai del ENP | H27: Comú | I27: Obligatori | J27: =G27 -> Participar en les consultes dels procesos d'Avaluació Ambiental que afectin directament o indirectament l’espai del ENP | L27: Si | M27: MITJANA | N27: Participació a les taules d'avaluació | S27: % de participació sobre els processos d'avaluació ambiental | T27: 50 | U27: 100 | V27: =30*4 -> 120 | W27: Millora rural | X27: Gerard Vila/ Anna Planella
F28: 03.1.2 | G28: Exercir un seguiment efectiu de les obres al Parc juntament amb les Oficines Territorials d'Acció i Avaluació Ambiental als efectes d'assegurar la correcta translació de la tutela administrativa. | H28: Comú | I28: Obligatori | J28: =G28 -> Exercir un seguiment efectiu de les obres al Parc juntament amb les Oficines Territorials d'Acció i Avaluació Ambiental als efectes d'assegurar la correcta translació de la tutela administrativa. | L28: Si | M28: MITJANA | N28: Seguiment amb les obres que afectent i es realitzen dins dels límits del PNCTF | S28: % de participació sobre les obres executades | T28: 50 | U28: 100 | V28: 300 | W28: Millora rural | X28: Gerard Vila
F29: 03.1.3 | G29: Participar en la compensació d'impactes residuals durant els processos d'avaluació ambiental mitjançant la identificació de necessitats d'actuació prioritària dins i fora dels límits de l’ENP | H29: Comú | I29: Optatiu | J29: =G29 -> Participar en la compensació d'impactes residuals durant els processos d'avaluació ambiental mitjançant la identificació de necessitats d'actuació prioritària dins i fora dels límits de l’ENP | L29: Si | M29: MITJANA | N29: *Catàleg de possibles actuacions compensatories *Catàleg de sectors amb necessitats d'intervenció (incloent també zones fora dels límits de l'ENP que es considerin importants per al manteniment de la connectivitat ecològica dels espais) | S29: 1) Creació d'un catàleg d'actuacions futures i compensatòries 2) Nombre d'actuacions compensatories realitzades dins del PN | T29: 1) 1 2) 2 | U29: 1) 1 2) 4 | V29: =50+50+(80*4) -> 420 | W29: Transversal | X29: Anna Planella / Tbernat Perramon/Gerard Vila
D30: 03.2 | E30: Garantir el compliment dels objectius de conservació dotant l'ENP de la planificació adequada segons estableix la normativa vigent (Pla de Protecció, PRUG, plans específics...) | F30: 03.2.1 | G30: Participar en l'elaboració dels instruments de planificació de l'ENP | H30: Comú | I30: Obligatori | J30: =G30 -> Participar en l'elaboració dels instruments de planificació de l'ENP | K30: Que s'implementi l'actuació no depèn directament de l'espai | L30: No | R30: SPEN: Elaboració del Pla rector d'usos i gestió. SPEN: Elaboració del Pla rector d'usos i gestió | W30: Transversal | X30: Tots/es
D31: 03.3 | E31: Vetllar pel manteniment dels cabals ecològics i la bona qualitat dels cursos fluvials de l'ENP de forma coordinada amb l'administració competent | F31: 03.3.1 | G31: Vetllar pel manteniment del cabal ecològic dels rius definit al Pla sectorial corresponent | H31: Específic | I31: Optatiu | J31: =G31 -> Vetllar pel manteniment del cabal ecològic dels rius definit al Pla sectorial corresponent | L31: Si | M31: ALTA | N31: 1) Establiment d'una xarxa de control del cabal en els trams de riu dins del Parc 2) Realització d'un inventari de les activitats que poden modificar la llera i el cabal 3) Revisió de les concessions actuals | P31: Revisar les actuacions. L'establiment de punts de control depèn de l'ACA. Es pot incloure la revisió de les concessions, les reunions amb l'ACA,... Afegir indicadors i fites | Q31: ESNATURA | R31: ACA/CHE: Determinar els cabals ecològics en espais naturals protegits | S31: 1) Nombre d'estacions de control de cabal 2) Reunions anuals amb l'ACA 3) Inventari de les activitats que modifiquen la llera i el cabal dels principals rius de l'espai i pla de millora | T31: 1) 2 2) 1 3) 1 | U31: 1) 4 2) 2 3) 1 | V31: =20*4 -> 80 | W31: Patrimoni natural | X31: Anna Planella
F32: 03.3.2 | G32: Vetllar per la regulació dels dragatges, canalitzacions o implantació d'activitats extractives que puguin modificar la llera i el cabal dels rius | H32: Específic | I32: Optatiu | J32: =G32 -> Vetllar per la regulació dels dragatges, canalitzacions o implantació d'activitats extractives que puguin modificar la llera i el cabal dels rius | L32: Si | M32: ALTA | N32: Actuacions incloses en l'objectiu 3.3.1
F33: 03.3.3 | G33: Avaluar i controlar les actuacions que produeixin drenatges, captacions o que puguin impedir l’arribada d’aigua tant superficial com freàtica | H33: Específic | I33: Optatiu | J33: =G33 -> Avaluar i controlar les actuacions que produeixin drenatges, captacions o que puguin impedir l’arribada d’aigua tant superficial com freàtica | L33: Si | M33: ALTA | N33: Actuacions incloses en l'objectiu 3.3.1
F34: 03.3.4 | G34: Vetllar pel compliment de la normativa de depuració dels efluents agroramaders, urbans i industrials que s'aboquen als cursos fluvials | H34: Específic | I34: Optatiu | J34: =G34 -> Vetllar pel compliment de la normativa de depuració dels efluents agroramaders, urbans i industrials que s'aboquen als cursos fluvials | L34: Si | M34: ALTA | N34: 1) Establiment d'una xarxa de control de qualitat de l'aigua | P34: Revisar. Igual que l'anterior potser és competència de l'ACA? | S34: 1) Nombre d'estacions de control de la qualitat | T34: 2 | U34: 4 | V34: =10*4 -> 40 | W34: Patrimoni natural | X34: Anna Planella
D35: 03.4 | E35: Incrementar el patrimoni públic destinat a la conservació i millora del patrimoni natural | F35: 03.4.1 | G35: Identificar espais prioritaris per a la compra de terrenys de més valor dins l'ENP | H35: Comú | I35: Optatiu | J35: =G35 -> Identificar espais prioritaris per a la compra de terrenys de més valor dins l'ENP | L35: Si | M35: ALTA | N35: Vetllar per l'adquisició des del PN o d'altres òrgans públics de finques privades d'interès | R35: SENP/SPEN: Facilitar els criteris a seguir | S35: 1) Llistat de finques potencials classificades per interes 2) Adquisicó de finques d'alt interès | T35: 1) 1 2) 1 | U35: 1) 1 2) 2 | V35: 140 | W35: Transversal | X35: Anna Planella/Gerard Vila/Santi Farriol
F36: 03.4.2 | G36: Identificar espais prioritaris per a la gestió directa | H36: Comú | I36: Optatiu | J36: =G36 -> Identificar espais prioritaris per a la gestió directa | L36: Si | M36: ALTA | N36: Identificació d'espais prioritaris per a la gestió activa | R36: SENP/SPEN: Facilitar els criteris a seguir | S36: 1) Llistat d'espais prioritaris per a gestió activa, ordenats per l'interès 2) Nombre d'actuacions executades | T36: 1) 1 2) 2 | U36: 1) 1 2) 5 | V36: =(50*4)*2 -> 400 | W36: Patrimoni natural / Millora rural | X36: Anna Planella i Gerard Vila
A37: CULTURA | B37: 4 | C37: CONSERVAR ELS ELEMENTS CULTURALS materials i immaterials vinculats a la natura | D37: 04.1 | E37: Millorar el coneixement disponible sobre el patrimoni arquitectònic i cultural (material i immaterial) vinculat al patrimoni natural, el seu estat de conservació i els estils propis dels territoris de l'ENP | F37: 04.1.1 | G37: Elaborar l'inventari i cartografia de patrimoni cultural de l'ENP, que també inclogui el patrimoni etnològic i immaterial | H37: Comú | I37: Optatiu | J37: =G37 -> Elaborar l'inventari i cartografia de patrimoni cultural de l'ENP, que també inclogui el patrimoni etnològic i immaterial | L37: Si | M37: MITJANA | N37: *Redacció d'un full de ruta conjunt amb el Museu Etnogràfic de Ripoll per al desenvolupament d'aquest inventari *Recopilació de la informació dels catàlegs dels ajuntaments de l'ENP i fer diagnosi *Inventari de patrimoni cultural material (arquitectònic /arqueològic / ramader...) *Inventari de patrimoni cultural immaterial (etnològic / espiritual...) (metodologia de l'inventari de la unesco) *Elaboració d'un mapa de tranquil·litat. *Creuar dades amb altres inventaris ja existents (Carta del paisatge, etc.) | S37: Nombre d'inventaris o mapes desenvolupats, juntament amb la cartografia de patrimoni cultural del PNCTF, que també incloguin el patrimoni etnològic i immaterial | T37: 1 | U37: 3 | V37: 50 | W37: Us public | X37: Xavier Grivé
F38: 04.1.2 | G38: Elaborar el catàleg lingüístic (localismes) de patrimoni natural, geografia popular, festes i activitats tradicionals de l'ENP | H38: Comú | I38: Optatiu | J38: =G38 -> Elaborar el catàleg lingüístic (localismes) de patrimoni natural, geografia popular, festes i activitats tradicionals de l'ENP | L38: Si | M38: MITJANA | N38: *Redacció d'un full de ruta conjunt amb el Museu Etnogràfic de Ripoll per al desenvolupament d'aquest inventari *Detecció de les persones i entitats locals de referència en la matèria *Catàleg lingüístic (localismes) de patrimoni natural del PNCTF *Catàleg lingüístic (localismes) de geografia popular, festes i activitats tradicionals del PNCTF *Creuar dades amb altres inventaris ja existents (Carta del paisatge, etc.) | S38: Nombre de catàlegs lingüístics (localismes) desenvolupats de patrimoni natural i de geografia popular, festes i activitats tradicionals del PNCTF | T38: 1 | U38: 2 | V38: 50 | W38: Us public / Patrimoni natural | X38: Xavier Grivé / Anna Planella
F39: 04.1.3 | G39: Elaborar la cartografia de la xarxa de camins ramaders i senders tradicionals de l'ENP | H39: Comú | I39: Optatiu | J39: =G39 -> Elaborar la cartografia de la xarxa de camins ramaders i senders tradicionals de l'ENP | L39: Si | M39: MITJANA | N39: *Redacció d'un full de ruta conjunt amb el Museu Etnogràfic de Ripoll i la xarxa de senders Itinerànnia per al desenvolupament d'aquesta cartografia. *Cartografia de la xarxa de camins ramaders i senders tradicionals de l'ENP * Consensuar amb la propietat (pública o privada) quins senders s'inclouran i, si escau, signatura de convenis | S39: Nombre de mapes desenvolupats de camins ramaders i senders tradicionals | T39: 1 | U39: 1 | V39: 50 | W39: Ús públic / Sistemes agropastorals | X39: Xavier Grivé / Bernat Perramon
D40: 04.2 | E40: Conservar i gestionar el patrimoni cultural de l'ENP de forma coordinada amb els agents responsables i entitats de referència | F40: 04.2.1 | G40: Identificar els ens de referència en patrimoni cultural (entitats, associacions, museus i ecomuseus, etc.) en l'àmbit de l'ENP | H40: Comú | I40: Obligatori | J40: =G40 -> Identificar els ens de referència en patrimoni cultural (entitats, associacions, museus i ecomuseus, etc.) en l'àmbit de l'ENP | L40: Si | M40: MITJANA | N40: *Elaboració d'un mapa d'entitats, associacions, museus, ecomuseus, OPEI (Observatori del Patrimoni Etnològic i Immaterial), etc. *Creuar dades amb altres inventaris ja existents (Carta del paisatge, etc.) | S40: Nombre de mapes desenvolupats d'entitats, associacions, museus, ecomuseus, OPEI (Observatori del Patrimoni Etnològic i Immaterial), etc. | T40: 1 | U40: 1 | V40: 24 | W40: Ús públic | X40: Xavier Grivé i Rai
F41: 04.2.2 | G41: Articular treballs conjunts entre l'ENP i representants, gestors o custodis del patrimoni cultural per a la seva protecció i millora | H41: Comú | I41: Optatiu | J41: =G41 -> Articular treballs conjunts entre l'ENP i representants, gestors o custodis del patrimoni cultural per a la seva protecció i millora | L41: Si | M41: MITJANA | N41: *Projecte parcs i museus *Impuls dels convenis de col·laboració amb la xarxa de museus i altres equipaments i entitats de referència *Foment de la cooperació tècnica dels gestors de l'ENP amb els representants o custodis del patrimoni cultural, i coordinar-ne l'ús compartit dels recursos | S41: Nombre de convenis de col·laboració posats en marxa entre el PNCTF i altres entitats culturals de referència del territori | T41: 1 | U41: 1 | V41: 50 | W41: Ús públic | X41: Xavier Grivé i Rai
F42: 04.2.3 | G42: Coordinar i participar dels treballs de restauració arquitectònica i del patrimoni cultural | H42: Comú | I42: Optatiu | J42: Impulsar i/o participar dels treballs de restauració arquitectònica, arqueològica i del patrimoni cultural | K42: CANVI DE REDACTAT OP DE LA DG | L42: Si | M42: MITJANA | N42: *Coordinació de l'equip tècnic (propi) amb els responsables dels treballs de restauració arquitectònica i del patrimoni cultural Participació quan els treballs estan vinculats a l’àrea d’ús públic de l’ENP *Creuar dades amb altres inventaris ja existents (Carta del paisatge, etc.) | S42: Nombre d'elements de patrimoni arquitectònic o cultural restaurats | T42: 1 | U42: 4 | V42: 50 | W42: Ús públic | X42: Xavier Grivé i Rai
F43: 04.2.4 | G43: Disposar de personal que tingui coneixements tècnics sobre patrimoni natural | H43: Comú | I43: Obligatori | J43: =G43 -> Disposar de personal que tingui coneixements tècnics sobre patrimoni natural | L43: Si | M43: MITJANA | N43: *Formació del personal tècnic de l'ENP en la gestió i conservació dels valors culturals de l'ENP | S43: Nombre de formacions rebudes per part del personal tècnic de l'ENP en la gestió i conservació dels valors culturals de l'ENP | T43: 1 | U43: 4 | V43: 25 | W43: Ús públic | X43: Xavier Grivé i Rai
D44: 04.3 | E44: Potenciar la conservació i recuperació del patrimoni cultural material i immaterial de l'ENP | F44: 04.3.1 | G44: Recuperar i conservar el patrimoni cultural rural immaterial associat a les activitats i aprofitaments tradicionals | H44: Comú | I44: Obligatori | J44: Recuperar i conservar el patrimoni cultural immaterial (associat a les activitats i aprofitaments rurals tradicionals) i els valors espirituals | K44: CANVI DE REDACTAT OP DE LA DG | L44: Si | M44: MITJANA | N44: *Redacció d'un full de ruta conjunt amb el Museu Etnogràfic de Ripoll per a la recuperació i conservació del patrimoni cultural rural immaterial associat a les activitats i aprofitaments tradicionals *Inventariar els elements concrets del patrimoni rural immaterial associat a les activitats i aprofitaments tradicionals. *Desenvolupament d'accions de conservació d'elements concrets del patrimoni rural immaterial associat a les activitats i aprofitaments tradicionals. | Q44: MAP | S44: Nombre d'accions de conservació desenvolupades d'elements concrets del patrimoni rural immaterial associat a les activitats i aprofitaments tradicionals. | T44: 1 | U44: 4 | V44: 25 | W44: Ús públic | X44: Xavier Grivé i Rai
B45: 4 | C45: CONSERVAR EL PATRIMONI CULTURAL material i immaterial | F45: 04.3.2 | G45: Recuperar i conservar el patrimoni cultural rural vinculat específicament a construccions de pedra en sec | H45: Específic | I45: Obligatori | J45: =G45 -> Recuperar i conservar el patrimoni cultural rural vinculat específicament a construccions de pedra en sec | L45: Si | M45: MITJANA | N45: * Redacció d'un pla de recuperació dels murs de pedra seca i barraques de pastor dins del PNCTF * Implicar la taula de Voluntariat Ambiental del Pirineu Oriental *Creuar dades amb altres inventaris ja existents (Carta del paisatge, etc.) | Q45: MAP | S45: 1) Número d'actuacions de restauració de pedra seca 2) Actuacions de voluntariat | T45: 1) 3 2) 1 | U45: 1) 6 2) 2 | V45: 225 | W45: Millora rural | X45: Gerard Vila / Xavier Grivé
F46: 04.3.3 | G46: Fomentar la recuperació i conservació de l'arquitectura tradicional d'interès de les edificacions i construccions | H46: Comú | I46: Optatiu | J46: =G46 -> Fomentar la recuperació i conservació de l'arquitectura tradicional d'interès de les edificacions i construccions | L46: Si | M46: ALTA | N46: Redacció del catàleg d'elements d'arquitectura dins del PNCTF | S46: Redacció del Pla d'elements arquitectònics de l'Alt Ripollès. | T46: 1 | U46: 1 | V46: 250 | W46: Millora rural | X46: Gerard Vila
F47: 04.3.4 | G47: Identificar i conservar la diversitat domesticada de varietats agrícoles i ramaderes locals | H47: Comú | I47: Obligatori | J47: =G47 -> Identificar i conservar la diversitat domesticada de varietats agrícoles i ramaderes locals | L47: Si | M47: MITJANA | N47: Diversitat espècies hàbitats de pastura | Q47: ESNATURA | S47: 1) Seguiment dels principals hàbitats de pastura per assegurar que no hi ha una pèrdua de diversitat associada (número de seguiments portats a terme) | T47: 1) 1 | U47: 1) 4 | V47: =10*4 -> 40 | W47: Sistemes agropastorals | X47: Bernat Perramon
D48: 04.4 | E48: Donar a conèixer els elements culturals com a valors del paisatge de l'ENP en les activitats d'ús públic | F48: 04.4.1 | G48: Integrar el patrimoni cultural als itineraris i cartelleria de l'ENP. | H48: Comú | I48: Obligatori | J48: =G48 -> Integrar el patrimoni cultural als itineraris i cartelleria de l'ENP. | L48: Si | M48: MITJANA | N48: *Redacció d'un full de ruta conjunt amb el Museu Etnogràfic de Ripoll i la xarxa de senders Itinerànnia per a la integració del patrimoni cultural als itineraris i cartelleria del PNCTF *Elaborar un projecte que incorpori els elements de patrimoni cultural a les banderoles de senderisme del PNCTF així com a les altres eines de comunicació del senderisme al PNCTF *Incorporar els elements de patrimoni cultural a les banderoles de senderisme així com a les altres eines de comunicació del senderisme al PNCTF | S48: Nombre d'elements de patrimoni cultural incorporats a les banderoles de senderisme així com a les altres eines de comunicació del senderisme al PNCTF | T48: 4 | U48: 20 | V48: =10*4 -> 40 | W48: Ús públic | X48: Xavier Grivé i Rai
F49: 04.4.2 | G49: Incorporar el patrimoni cultural en els plans d’ús públic i educació ambiental per fomentar-ne la seva conservació i divulgació. | H49: Comú | I49: Obligatori | J49: =G49 -> Incorporar el patrimoni cultural en els plans d’ús públic i educació ambiental per fomentar-ne la seva conservació i divulgació. | L49: Si | M49: MITJANA | N49: * Incorporar el patrimoni cultural en el Pla Estratègic d'Educació i Voluntariat Ambiental del PNCTF desenvolupat a partir de processos participatius al Ripollès * Incorporar el patrimoni cultural en el Projecte Pedagògic del PNCTF desenvolupat conjuntament amb les escoles del Ripollès *Executar una formació anual | S49: Nombre de plans d'ús públic i educació ambiental en què s'ha incorporat el patrimoni cultural | T49: 1 | U49: 2 | V49: =10+5+5+5 -> 25 | W49: Ús públic | X49: Xavier Grivé i Rai
F50: 04.4.3 | G50: Formar el personal dels punts d’informació en els valors culturals de l'ENP | H50: Comú | I50: Obligatori | J50: =G50 -> Formar el personal dels punts d’informació en els valors culturals de l'ENP | L50: Si | M50: MITJANA | N50: *Incorporar els valors culturals del PNCTF als documents formatius adreçats als treballadors dels centres d'Informació *Incorporar els valors culturals del PNCTF al programa del Curs d'Informadors del PNCTF adreçat a establiments turístics *Fer una formació específica a les empreses acreditades a la CETS sobre aquests valors. | S50: Nombre de documents formatius / programes en què s'ha incorporat els valors culturals del PNCTF | T50: 1 | U50: 2 | V50: 25 | W50: Ús públic | X50: Xavier Grivé i Rai
B51: 5 | C51: PROTEGIR EL PAISATGE i la qualitat de l'ambient visual, sonor i lumínic. | D51: 05.1 | E51: Identificar els elements d'interès paisatgístic de l'espai | F51: 05.1.1 | G51: Elaborar un inventari d'elements d'interès paisatgístic de l'ENP d'acord amb el Catàleg de paisatge de la zona | H51: Comú | I51: Optatiu | J51: =G51 -> Elaborar un inventari d'elements d'interès paisatgístic de l'ENP d'acord amb el Catàleg de paisatge de la zona | L51: Si | M51: MITJANA | N51: Creació del catàleg de paisatge del PN | S51: Elaboració del catàleg i caracterització dels paisatges del PN | T51: 1 | U51: 1 | V51: 150 | W51: Millora rural | X51: Gerard Vila
D52: 05.2 | E52: Millorar la qualitat paisatgística | F52: 05.2.1 | G52: Desplegar actuacions de restauració dels elements d'interès paisatgístic degradats | H52: Comú | I52: Optatiu | J52: NA | K52: De moment no aplica a l'espai, no hi ha elements d'interès paisatgístics degradats importants
F53: 05.2.2 | G53: Gestionar l'abandonament d'infraestructures i instal·lacions amb impactes sobre els valors de l'espai | J53: =G53 -> Gestionar l'abandonament d'infraestructures i instal·lacions amb impactes sobre els valors de l'espai | L53: Si | M53: MÀXIMA | N53: Pla d'identificació i retirada d'elements abandonats o en mal estat (per exemple elements dels cims, pistes d'esquí en desús...) | S53: 1) % de superficie prospectada pel mapeig de totes les infraestructures abandonades dins del PN. 2) Percentatge d'elements extrets sobre els elements identificats | T53: 1) 50 2) 10 | U53: 1) 100 2) 15 | V53: 150 | W53: Millora rural | X53: Gerard Vila
F54: 05.2.3 | G54: Minimitzar la brutícia, deixalles, vandalisme i males praxis dins l'ENP | H54: Comú | I54: Obligatori | J54: =G54 -> Minimitzar la brutícia, deixalles, vandalisme i males praxis dins l'ENP | L54: Si | M54: MITJANA | N54: *Control gràfic i inventari dels punts amb més deixalles *Impulsar campanya comunicativa amb informadors i altres mitjans *Implicació de la Taula de Voluntariat Ambiental del Pirineu Oriental | S54: 1) Nombre de punts identificats. 2) % de punts tractats. | T54: 1) 10 2) 50 | U54: 1) tots els existents 2) 100 | V54: =20*6 -> 120 | W54: Ús públic | X54: Xavier Grivé i Rai | AD54: Eliminem indicador 3 (nombre de punts amb més deixalles)
D55: 05.3 | E55: Protegir la qualitat acústica i lumínica de l'ENP | F55: 05.3.1 | G55: Promoure la certificació de qualitat del cel nocturn | H55: Específic | I55: Optatiu | J55: =G55 -> Promoure la certificació de qualitat del cel nocturn | L55: Si | M55: BAIXA | N55: Dotar l'espai d'una figura de protecció del cel nocturn | Q55: ESNATURA | S55: Figures de protecció otorgades al Parc en relació a la qualitat del cel nocturn | T55: 1 | U55: 1 | V55: 150 | W55: Transversal | X55: Tots
F56: 05.3.2 | G56: Promoure la certificació de zones d'especial protecció de la qualitat acústica | H56: Específic | I56: Optatiu | J56: =G56 -> Promoure la certificació de zones d'especial protecció de la qualitat acústica | L56: Si | M56: BAIXA | N56: Dotar l'espai d'una figura de protecció de la qualitat acústica | Q56: ESNATURA | S56: Figures de protecció otorgades al Parc en relació a la qualitat acústica | T56: 1 | U56: 1 | V56: 150 | W56: Transversal | X56: Tots
A57: CONEIXEMENT | B57: 6 | C57: MILLORAR EL CONEIXEMENT DE L'ENTORN, del patrimoni natural, cultural i social. | D57: 06.1 | E57: Identificar els objectes de gestió prioritària de l'ENP en el marc dels objectius de govern | F57: 06.1.1 | G57: Identificar i prioritzar els elements clau i d'interès per la gestió de la biodiversitat i geodiversitat de Catalunya es troben dins l'ENP (especies amenaçades, espècies exòtiques invasores,.. ) | H57: Comú | I57: Obligatori | J57: Identificar i prioritzar els elements clau i d'interès per la gestió de la biodiversitat i geodiversitat de Catalunya es troben dins l'ENP (especies amenaçades, espècies exòtiques invasores,.. ) i obtenció de coneixement sobre pràctiques de maneig ramader sobre l'estat de conservació i interès farratger dels prats | K57: un 60% de la superfície del PN es ramadera i cal incrementar el coneixement sobre aquests espais en concret tal i com diu el decret 211/2015 de creació del Parc natural. El Decret conclou que hi ha d'haver un tècnic específic en ramaderia, per tant no estem parlant d'un tema menor. | L57: Si | M57: MÀXIMA | N57: 1) Elaboració d'una base de dades amb els objectes de conservació prioritaris dins l'espai i de la cartografia de les seves localitats 2) Elaboració de l'inventari d'espais d'interès geològic i prioritzar geosites i geomorfosites i quin poder ser o no visitables 3) Seguiments associats a diferents casuístiques de maneig agrari i ramader per definir sistemes de maneig interessants 4) Seguiments associats a la recuperació d'espais oberts per definir sistemes de maneig interessants i determinar possibles impactes associats 5) Seguiments transversals en els principals hàbitats de prats del PN per seguir-ne l'evolució i conèixer el grau de conservació a mig-llarg termini | Q57: Directriva Habitats Carta emplaçament ESNATURA Catàlegs | R57: UIC/SFF/SPEN: Definir criteris d'identificació d'elements interès. UIC/SFF/SPEN: Definició dels objectes de conservació clau comuns a nivell de Xarxa d'ENP o clúster territorial | S57: 1) Base de dades dels objectes de conservació (hàbitats, espècies, processos i elements d'interès geològic) claus dins l'espai i cartografia de les seves localitats lligat al SINATCAT 2) Nombre d'elements d'interès geològics identificats 3) Percentatge d'elements d'interès cartografiats entrats a la BDD 4) Seguiments implementats per a la millora de la gestió ramadera 5) seguiments implementats per a la recuperació d'espais oberts | T57: 1) 1 2) 30 3) 75% 4) 2 5) 2 | U57: 1) 1 2) 50 3) 100% 4) 4 5) 4 | V57: =50+200 -> 250 | W57: Patrimoni natural/Sistemes agropastorals | X57: Anna Planella / Bernat Perramon
F58: 06.1.2 | G58: Definir espais fràgils i zones d'especial atenció | H58: Comú | I58: Obligatori | J58: =G58 -> Definir espais fràgils i zones d'especial atenció | L58: Si | M58: MÀXIMA | N58: 1) Creació de zones d'especial atenció: "zones de prioritat per la conservació" 2) Creació de "zones de tranquil·litat" per a la conservació de fauna amenaçada en època hivernal (també a la part d'ús públic) | R58: SPEN: Inventari i cartografia d'espais fràgils i zones d'especial atenció | S58: 1) Nombre de zones de Prioritat per la Conservació creades 2) Nombre de zones de tranquil·litat creades 3) Superfície (ha) de zones de tranquil·litat | T58: 1) 1 2) 1 3) 30 | U58: 1) 4 2) 4 3) 150 | V58: 180 | W58: Patrimoni natural | X58: Anna Planella
D59: 06.2 | E59: Conèixer l'estat de conservació i la seva tendència dels hàbitats, les espècies els elements de la gea i els processos ecològics com a eina per avaluar i optimitzar la gestió | F59: 06.2.1 | G59: Participar en l'elaboració de la cartografia que elabora la UIC | H59: Comú | I59: Obligatori | J59: =G59 -> Participar en l'elaboració de la cartografia que elabora la UIC | L59: Si | M59: ALTA | N59: Elaboració de la cartografia de la distribució dels elements d'interès del Parc (hàbitats, flora, fauna, geologia...) i aportació a la UIC | Q59: ESNATURA | R59: UIC: Coordinar i contractar l'elaboració de la cartografia | S59: 1) Percentatge d'aportació de la informació sol·licitada des de la UIC 2) Percentatge d'elements d'interès identificats que disposen de cartografia | T59: 1) 100% 2) 75% | U59: 1) 100% 2) 100% | V59: 400 | W59: Patrimoni natural | X59: Anna Planella
F60: 06.2.2 | G60: Conèixer i estudiar els processos naturals propis de l’espai, la seva funcionalitat, i ecologia en referència als ecosistemes | H60: Comú | I60: Obligatori | J60: =G60 -> Conèixer i estudiar els processos naturals propis de l’espai, la seva funcionalitat, i ecologia en referència als ecosistemes | L60: Si | M60: MITJANA | N60: 1) Implementació del protocol de fluxos d'informació i coneixement de biodiversitat 2) Foment i coordinació dels estudis sobre el règim hidrològic, la pol·linització, la tipificació i funcionament de les cadenes tròfiques pròpies de l’espai, la dinàmica de la neu i les allaus | S60: 1) Percentatge d'estudis elaborats des del Parc aportats anualment a la UIC 2) Nombre d'estudis potenciats des del Parc relacionats amb els processos naturals que es donen a l'espai | T60: 1) 80 2) 4 | U60: 1) 100 2) 6 | V60: 400 | W60: Patrimoni natural | X60: Anna Planella
F61: 06.2.3 | G61: Conèixer els usos i factors de canvi rellevants en l'evolució dels elements de conservació, i avaluar els efectes que generen en l’espai (pressions i amenaces) | H61: Comú | I61: Obligatori | J61: =G61 -> Conèixer els usos i factors de canvi rellevants en l'evolució dels elements de conservació, i avaluar els efectes que generen en l’espai (pressions i amenaces) | L61: Si | M61: ALTA | N61: 1) Avaluació de l'impacte del canvi climàtic en l'ENP i la seva capacitat d'adaptació i resiliència. 2) Avaluació dels resultats de les estratègies de gestió aplicades en l'ENP 3) Foment de l'estudi de l'afectació de determinats processos naturals o activitats antròpiques en l'ENP (per exemple conèixer l'impacte de l'activitat ramadera sobre la biodiversitat - diferents pautes de maneig i tractaments com l'ivermectina - , la freqüentació humana sobre algunes espècies prioritàries com la perdiu blanca, etc.) | Q61: ESNATURA | R61: SENP/UIC: Elaborar la classificació i cartografia de les pressions o factors de canvi sobre el medi natural | S61: 1) Nombre d'estudis o projectes relacionats amb l'impacte del canvi climàtic en l'ENP (per exemple, impacte sobre els hàbitats de congestera, molleres, espècies prioritaries com perdiu blanca...) 2) Percentatges d'actuacions de gestió directe en les quals es du a terme un seguiment i avaluació per tal de mesurar l'eficàcia de les intervencions 3) Projectes duts a terme que avaluin l'afectació de processos i activitats sobre l'ENP | T61: 1) 3 2) 75 3) 2 | U61: 1) 6 2) 100 3) 4 | V61: =40*5 -> 200 | W61: Transversal | X61: Tots
F62: 06.2.4 | G62: Conèixer l'impacte de les gestió de l'aigua, sobre la biodiversitat. | H62: Comú | I62: Optatiu | J62: =G62 -> Conèixer l'impacte de les gestió de l'aigua, sobre la biodiversitat. | L62: Si | M62: ALTA | N62: Implementació d'un programa de seguiment de l’estat hidrològic de les masses d’aigua | O62: Accions vinculades als OP 3.3.1 i OP 3.3.4 | S62: 1) Instal·lació de punts de control automàtics | T62: 2 | U62: 4 | V62: 80 | W62: Patrimoni natural | X62: Anna Planella
F63: 06.2.5 | G63: Participar en el coneixement de la tendència d'espècies plaga amb afectacions sobre ecosistemes o activitats econòmiques dins l'ENP | H63: Comú | I63: Optatiu | J63: =G63 -> Participar en el coneixement de la tendència d'espècies plaga amb afectacions sobre ecosistemes o activitats econòmiques dins l'ENP | L63: Si | M63: BAIXA | N63: Participació en dels estudis de les autoritats competents | S63: Nombre d'estudis sobre espècies plaga en els que s'ha participat des del Parc | T63: 1 | U63: 1 | V63: 80 | W63: Patrimoni natural | X63: Anna Planella
F64: 06.2.6 | G64: Conèixer la tendència d'espècies exòtiques invasores amb afectacions sobre ecosistemes o activitats econòmiques dins l'ENP | H64: Comú | I64: Obligatori | J64: =G64 -> Conèixer la tendència d'espècies exòtiques invasores amb afectacions sobre ecosistemes o activitats econòmiques dins l'ENP | L64: Si | M64: ALTA | N64: Realització i foment d'estudis de forma coordinada amb el SFF: avaluació de la tendència del seneci del cap dins del Parc, xarxa de seguiment d'espècies aquàtiques de fauna exòtica com el coipú o el visó americà | Q64: ESNATURA | S64: Estudis relacionats amb l'estat de les espècies exòtiques invasores (principalment seneci del cap, visó americà i coipú) | T64: 1 | U64: 3 | V64: 180 | W64: Patrimoni natural | X64: Anna Planella
F65: 06.2.7 | G65: Coneixer com millorar la connectivitat de forma coordinada amb altres ENP | H65: Comú | I65: Optatiu | J65: =G65 -> Coneixer com millorar la connectivitat de forma coordinada amb altres ENP | L65: Si | M65: MITJANA | N65: Elaboració d'una cartografia detallada i actualitzada de connectors ecològics | Q65: ESNATURA | S65: Cartografia elaborada que cobreixi tot l'espai | T65: 1 | U65: 1 | V65: =20*4 -> 80 | W65: Patrimoni natural | X65: Anna Planella
D66: 06.3 | E66: Estandaritzar els seguiments periòdics dels grups clau | F66: 06.3.1 | G66: Participar en la definició del sistema estàndard de seguiment de flora, fauna i hàbitats de la DG | H66: Comú | I66: Obligatori | J66: =G66 -> Participar en la definició del sistema estàndard de seguiment de flora, fauna i hàbitats de la DG | L66: Si | M66: ALTA | N66: Suport a la UIC en la definició dels sistemes de seguiment | Q66: ESNATURA | R66: UIC/SFF/SENP: Crear espais de participació UIC/SFF: Definir el sistema estàndard de seguiment i el protocol d'aplicació | S66: 1) % d'assistència a les convocatories de la UIC per la definició d'un sistema estandard de seguiment dels elements dels ENP 2)% de metodologies de seguiments estandaritzats que apliquen a l'espai | T66: 80 | U66: 100 | V66: 180 | W66: Patrimoni natural | X66: Anna Planella
F67: 06.3.2 | G67: Adequar i executar el sistema de seguiment periòdic dels grups clau de l'ENP al sistema estàndard de seguiment | H67: Comú | I67: Obligatori | J67: =G67 -> Adequar i executar el sistema de seguiment periòdic dels grups clau de l'ENP al sistema estàndard de seguiment | L67: Si | M67: ALTA | N67: 1) Contractació d’especialistes per dur a terme el seguiment periòdic dels grups clau de l'ENP 2) Col.laboració amb l'Observatori per aportar els coneixements generats a l'ENP. 3) Seguiment de les directius del sistema de seguiment establerts segons la versió més recent aportada per la UIC 4) Aplicació del protocol establert de compartir informació per al seguiment global d’indicadors de l’estat de la natura, el seguiment dels pol·linitzadors silvestres, o el seguiment dels pol·linitzadors silvestres . | Q67: ESNATURA | R67: UIC/SFF: Definir el sistema estàndard de seguiment i el protocol d'aplicació UIC: Elaborar el protocol d'informació i coneixement | S67: 1) Nombre d'encarrecs anuals a especialistes per dur a terme el seguiment dels grups clau de l'espai. Nombre d'encarrecs per grup: coleopters, ortopters, pol·linitzadors, ocells, mamífers, peixos, amfibis, rèptils, flora... 2) Compliment de les peticions de dades efectuades des de l'observatori 3) Percentatge de seguiments efectuats seguint les directrius del sistema de seguiment de la UIC 4) Percentatge dels estudis realitzats en els que s'ha aplicat el protocol de compartir informació per el seguiment flobal d'indicadors | T67: 1) 1 2) 100 3) 80 4) 50 | U67: 1) 3 2) 100 3) 100 4) 75 | V67: =30*4 -> 120 | W67: Patrimoni natural | X67: Anna Planella
F68: 06.3.3 | G68: Mantenir una base de dades de seguiment de patrimoni natural de l'ENP actualitzada i ordenada | H68: Comú | I68: Obligatori | J68: Mantenir una base de dades de seguiment de patrimoni natural de l'ENP actualitzada i ordenada i lligada al SINATCAT | L68: Si | M68: ALTA | N68: Manteniment i actualització anual de la base de dades corresponent al Pla de Seguiment de l'ENP | S68: 1) Base de dades corresponent al pla de seguiment de l'ENP, actualitzada anualment 2) Percentatge de seguiments anuals entrats durant la mateixa anualitat a la base de dades de l'ENP | T68: 1) 1 2) 100% | U68: 1) 1 2) 100% | V68: =50*4 -> 200 | W68: Patrimoni natural | X68: Anna Planella
F69: 06.3.4 | G69: Participar en el grups de treball per a la definició i organització del SINATCAT | H69: Comú | I69: Obligatori | J69: Participar en la definició, organització i bolcatge de dades del SINATCAT | K69: CANVI DE REDACTAT OP DE LA DG | L69: Si | M69: ALTA | N69: Participació en el desplegament del SINATCAT | R69: UIC/SENP: Crear i coordinar una metodologia participativa per a la definició del SINATCAT | S69: Percentatge d'assistència als grups de treball i jornades de formació que es convoquin per el desplegament del SINATCAT | T69: 1 | U69: 1 | V69: 180 | W69: Patrimoni natural | X69: Anna Planella
D70: 06.4 | E70: Incrementar el coneixement de qualitat mitjançant l’establiment de marcs de col·laboració, assessorament i suport amb centres de recerca, museus i entitats naturalistes per al desenvolupament de part de la seva activitat en l’ENP | F70: 06.4.1 | G70: Crear sinèrgies i col·laborar amb museus i equipaments de referència per definir línies d'actuació conjunta entre patrimoni cultural i natural | H70: Comú | I70: Optatiu | J70: =G70 -> Crear sinèrgies i col·laborar amb museus i equipaments de referència per definir línies d'actuació conjunta entre patrimoni cultural i natural | L70: Si | M70: MITJANA | N70: *Signatura d'un conveni de col·laboració entre el Museu Etnogràfic de Ripoll i el PNCTF *Detecció d'altres organismes amb qui traçar línies de col·laboració per definir línies d'actuació conjunta entre patrimoni natural i cultural | R70: SENP: Elaborar un mapa d'agents de referència | S70: Nombre d'organismes implicats amb el PNCTF per a la definició de línies d'actuació conjunta entre patrimoni cultural i natural | T70: 1 | U70: 8 | V70: =10*4 -> 40 | W70: Ús públic | X70: Xavier Grivé i Rai
F71: 06.4.2 | G71: Establir acords amb les institucions de recerca i naturalistes per al desenvolupament d'estudis i inventaris dins l'ENP en el marc de les seves línies de recerca | H71: Comú | I71: Optatiu | J71: =G71 -> Establir acords amb les institucions de recerca i naturalistes per al desenvolupament d'estudis i inventaris dins l'ENP en el marc de les seves línies de recerca | L71: Si | M71: MITJANA | N71: Manteniment i estabilment de nous acords amb institucions de recerca per el desenvolupament d'estudis dins de l'ENP | R71: SENP: Elaborar un mapa d'agents de referècia | S71: Nombre d'acords (col·laboracions, contractes, etc.) actius amb institucions de recerca: UdG, UB, CREAF... | T71: 3 | U71: 6 | V71: =15*4 -> 60 | W71: Patrimoni natural | X71: Anna Planella
F72: 06.4.3 | G72: Potenciar la ciència ciutadana en l’ENP com a eina per generar coneixement | H72: Comú | I72: Optatiu | J72: =G72 -> Potenciar la ciència ciutadana en l’ENP com a eina per generar coneixement | K72: Proposta sector conservacionista | L72: Si | M72: ALTA | N72: 1) Realització de projectes de ciència ciutadana dins de l'ENP per tal de generar dades. 2) Suport i estabilització de la xarxa de voluntariat per a determinats seguiments de biodiversitat 3) Potenciar que, en cas de manca de voluntariat es facin els seguiments igualment (contractes menorsconvenis, etc.) | S72: Nombre d'estacions de seguiments estandaritzats duts a terme mitjançant programes de ciencia ciutadana: 1) SOCC 2) CBMS 3) SEMICE 4) Quirohàbitats 5) Projecte Rius 6) SACC 7) Percentatge d'aquests programes de seguiments que es du a terme a través de la xarxa de voluntariat | T72: 1) 7 2) 1 3) 1 4) 5 5) 2 6) 10 7) 50 | U72: 1) 10 2) 2 3) 2 4) 10 5) 4 6) 15 7) 75 | V72: 150 | W72: Patrimoni natural | X72: Anna Planella
F73: 06.4.4 | G73: Crear i desenvolupar jornades de recerca de l'ENP de forma anual on els diferents centres mostrin els estudis realizats en l'ENP | H73: Comú | I73: Optatiu | J73: =G73 -> Crear i desenvolupar jornades de recerca de l'ENP de forma anual on els diferents centres mostrin els estudis realizats en l'ENP | L73: Si | M73: ALTA | N73: Realització de les jornades d'estudiosos del Parc Natural. | R73: SENP: Suport en l'organització de les jornades | S73: Nombre de jornades dutes a terme | T73: 2 | U73: 4 | V73: =40*4 -> 160 | W73: Patrimoni natural | X73: Anna Planella
F74: 06.4.5 | G74: Posar a disposició de la recerca, equipaments i serveis de l'ENP | H74: Comú | I74: Optatiu | J74: =G74 -> Posar a disposició de la recerca, equipaments i serveis de l'ENP | L74: Si | M74: MITJANA | N74: 1) Adaptació d'espais per acollir investigadors i estudiants en pràctiques 2) Suport i col·laboració del personal tècnic i de la brigada en els estudis que es desenvolupin a l'espai | Q74: ESNATURA | S74: 1) Nombre d'espais adaptats, a disposició d'estudiants o investigadors 2) Percentatge d'estudis que es desenvolupen a l'espai en els que es col·labora mitjançant personal tècnic o de la brigada | T74: 1) 1 2) 30% | U74: 1) 1 2) 60% | V74: =40*4 -> 160 | W74: Patrimoni natural | X74: Anna Planella
F75: 06.4.6 | G75: Crear l'Observatori de recerca de l'ENP vinculat a l'Observatori del Patrimoni natural i la biodiversitat | H75: Comú | I75: Optatiu | J75: =G75 -> Crear l'Observatori de recerca de l'ENP vinculat a l'Observatori del Patrimoni natural i la biodiversitat | L75: Si | M75: MITJANA | N75: Creació de l'Observatori de recerca de l'ENP en col·laboració amb la UIC | R75: UIC: Suport en la creació de l'Observatori de reserca | S75: 1) Existència de l'Observatori de la Recerca al Parc 2) Projectes de recerca als quals s'ha donat suport des de l'Observatori de la Recerca (buscar sinèrgies entre ENPE) | T75: 1) 1 2) 5 | U75: 1) 1 2) 10 | V75: =40*4 -> 160 | W75: Patrimoni natural | X75: Anna Planella
D76: 06.5 | E76: Millorar el coneixement global de les dinàmiques d'usos antròpics de l’ENP | F76: 06.5.1 | G76: Participar en la definició del sistema estándard de seguiment de l'ús públic amb el SENP | H76: Comú | I76: Obligatori | J76: =G76 -> Participar en la definició del sistema estándard de seguiment de l'ús públic amb el SENP | L76: Si | M76: MITJANA | N76: *Col·laborar amb el SENP en la definició del Sistema Estàndard de Seguiment de l'Ús Públic | R76: SENP: Crear espais de participació. Definició del sistema estándard de seguiment de l'ús públic | S76: Nombre de reunions amb el SENP en què s'ha participat en la definició del Sistema Estàndard de Seguiment de l'Ús Públic | T76: 1 | U76: 12 | V76: =10*4 -> 40 | W76: Ús públic | X76: Xavier Grivé i Rai
F77: 06.5.2 | G77: Disposar de dades de freqüentació i perfil d'usuari en l'ENP i en especial en equipaments i en zones d'alta freqüentació segons el model de DG | H77: Comú | I77: Obligatori | J77: =G77 -> Disposar de dades de freqüentació i perfil d'usuari en l'ENP i en especial en equipaments i en zones d'alta freqüentació segons el model de DG | L77: Si | M77: MÀXIMA | N77: 1) Implementació del sistema estandaritzat de presa de dades i seguiment de la freqüentació en ENP del SENP 2) Gestió i seguiment mensual dels eco-comptadors de vehicles i persones d'entrada al PNCTF 3) Anàlisi estadístic anual del perfil de visitants als Centres d'Informació del PNCTF 4) Estudi de Freqüentació i Caracterització de Visitants del PNCTF: revisions periòdiques 5) Estudis de Capacitat de Càrrega del PNCTF: aplicació a diferents punts del Parc 6) Establiment de models de freqüentació que serveixin per gestionar l'ús públic en l'ENP conjuntament amb la UIC | R77: SENP: Disseny i elaboració del sistema estandaritzat de presa de dades i seguiment de la freqüentació en ENP | S77: 1) Disposició d'un sistema homogeni de recollida de dades i seguiment de l'ús públic als ENP liderat pel SENP 2) Quantitat de descàrregues de dades per eco-comptador | T77: 1) 1 2) 24 3) 4 4) 1 5) 1 6) 1 | U77: 1) 1 2) 48 3) 4 4) 2 5) 2 6) 1 | V77: =20*4 -> 80 | W77: Ús públic | X77: Xavier Grivé i Rai
F78: 06.5.3 | G78: Identificar les activitats i actors de l’espai. | H78: Comú | I78: Obligatori | J78: =G78 -> Identificar les activitats i actors de l’espai. | L78: Si | M78: MITJANA | N78: *Inventariar les activitats no organitzades que es desenvolupen al PNCTF *Inventariar les activitats organitzades que s'organitzen al PNCTF sense afany de lucre *Inventariar les activitats organitzades que es comercialitzen al PNCTF, així com les empreses implicades | S78: Nombre d'inventaris desenvolupats per detectar les activitats i actors del PNCTF | T78: 1 | U78: 3 | V78: =20*4 -> 80 | W78: Ús públic | X78: Xavier Grivé i Rai
F79: 06.5.4 | G79: Identificar en cartografia les males praxis i punts de massificació | J79: =G79 -> Identificar en cartografia les males praxis i punts de massificació | L79: Si | M79: ALTA | N79: Queda recollit a l'OP 06.5.6. | W79: Ús públic | X79: Xavier Grivé i Rai
F80: 06.5.5 | G80: Adaptar i mantenir un registre d'activitats, actors i inciències en ús públic (curses, conflictes, queixes, etc) | H80: Comú | I80: Obligatori | J80: =G80 -> Adaptar i mantenir un registre d'activitats, actors i inciències en ús públic (curses, conflictes, queixes, etc) | L80: Si | M80: MITJANA | N80: *Dur a terme un registre d'activitats, actors i incidències en ús públic que s'actualitzi periòdicament | R80: UIC: Disseny d'un model de registre d'activitats, actors i inciències en ús públic | S80: Nombre d'actualitzacions anuals del registre d'activitats, actors i incidències en ús públic | T80: 1 | U80: 4 | V80: =15*4 -> 60 | W80: Ús públic | X80: Xavier Grivé i Rai
F81: 06.5.6 | G81: Identificar els impactes (positius i negatius) que generen les activitats d'ús públic dins l'ENP | H81: Comú | I81: Obligatori | J81: =G81 -> Identificar els impactes (positius i negatius) que generen les activitats d'ús públic dins l'ENP | L81: Si | M81: ALTA | N81: 1) Llistar els impactes (positius i negatius) que generen les activitats d'ús públic al PNCTF 2) Cartografiar els impactes mitjançant l'elaboració d'una cartografia de punts de males praxis i massificació 3) Analitzar anualment les activitats que generin massa impacte negatiu per buscar la manera de reduir-lo 4) Prendre mesures per a reduir els impactes negatius de les activitats | Q81: ESNATURA | S81: 1) Nombre d'impactes (positius i negatius) que generen les activitats d'ús públic al PNCTF. 2) Nombre d'activitats d'ús públic amb un impacte negatiu. 3) Cartografia elaborada. 4) Anàlisi anual de les activitats que generin massa impacte negatiu per buscar la manera de reduir-lo feta. 5) % d'activitats gestionades amb mesures de reducció d'impacte. | T81: 1) 1 2) 1 3) 0 4) 1 5) 25 | U81: 1) 10 2) 10 3) 1 4) 4 5) 100 | V81: =20*4 -> 80 | W81: Ús públic | X81: Xavier Grivé i Rai | AD81: Fusionar 6.5.4 i 6.5.6
A82: DESENVOLUPAMENT LOCAL | B82: 7 | C82: FIXAR LA POBLACIÓ AL TERRITORI d'acord amb les oportunitats que generen els objectius de l'espai. | D82: 07.1 | E82: Fomentar i donar suport tècnic als Plans de desenvolupament socioecòmonic local sostenible dels municipis | F82: 07.1.1 | G82: Promoure i col·laborar en l'aplicació de Plans de Desenvolupament Local Sostenible | H82: Comú | I82: Obligatori | J82: Promoure i/o col·laborar en l'aplicació de Plans de Desenvolupament Local Sostenible | K82: CANVI DE REDACTAT OP DE LA DG | L82: Si | M82: MITJANA | N82: *Participació en l'aplicació dels Plans de Desenvolupament Local Sostenible | S82: Nombre de reunions en què el tècnic del PNCTF assisteix destinades a l'aplicació dels Plans de Desenvolupament Local Sostenible | T82: 1 | U82: 4 | V82: =10*4 -> 40 | W82: Ús públic | X82: Xavier Grivé i Rai
B83: 8 | C83: APROFITAR ELS RECURSOS NATURALS DE FORMA SOSTENIBLE mitjançant desenvolupament dels aprofitaments tradicionals de forma compatible amb la conservació de l'espai | D83: 08.1 | E83: Impulsar models productius agraris i forestals per tal d'afavorir la conservació dels hàbitats i els paisatges modelats per aquestes, i contribuir a la millora socioeconòmica de les persones que la fan possible | F83: 08.1.1 | G83: Acompanyar i assessorar els productors agraris per millorar les tècniques productives agràries i afavorir la conservació dels hàbitats i paisatges | H83: Comú | I83: Obligatori | J83: =G83 -> Acompanyar i assessorar els productors agraris per millorar les tècniques productives agràries i afavorir la conservació dels hàbitats i paisatges | L83: Si | M83: MITJANA | N83: *Manual tècnic de bones pràctiques en ramaderia extensiva *Jornades ramaderia i gestió de pastures | S83: 1) treballs amb recomacions de maneig 2) jornades de divulgació 3) Proves pilot de gestió de pastures | T83: 1) 2 2) 1 3)1 | U83: 1) 4 2) 2 3)2 | V83: =10*4 -> 40 | W83: Sistemes agropastorals | X83: Bernat Perramon
F84: 08.1.2 | G84: Oferir formació als productors agraris per millorar el seu coneixement sobre tècniques eficients i respectuoses amb la conservació del patrimoni natural i cultural | H84: Comú | I84: Obligatori | J84: =G84 -> Oferir formació als productors agraris per millorar el seu coneixement sobre tècniques eficients i respectuoses amb la conservació del patrimoni natural i cultural | L84: Si | M84: MITJANA | N84: Inclòs a l'OP 8.1.1 | S84: Marca fet al Parc lligat amb Porducte del Ripollès | X84: Bernat Perramon | AD84: Fusionar 8.1.1 i 8.1.2
F85: 08.1.3 | G85: Promoure la recuperació i conservació de marges i punts d'aigua associats a la ramaderia i l'agricultura i d'interès per la biodiversitat | H85: Específic | I85: Optatiu | J85: =G85 -> Promoure la recuperació i conservació de marges i punts d'aigua associats a la ramaderia i l'agricultura i d'interès per la biodiversitat | L85: Si | M85: MITJANA | N85: Recuperació de punts d'aigua associats a la ramaderia d'interès per a la biodiversitat (basses de Fontlletera, estanyet de Fontalba, etc.) i instal·lació d'abeuradors alternatius | S85: Nombre de punts d'aigua recuperats | T85: 2 | U85: 4 | V85: 25 | W85: Patrimoni natural i sistemes agropastorals | X85: Anna Planella i Bernat Perramon
D86: 08.2 | E86: Promoure la coordinació amb els agents socioeconòmics del territori pel foment del desenvolupament sostenible de l'espai (sector primari i secundari) | F86: 08.2.1 | G86: Establir una relació contínua amb agents socioeconòmics del territori, i si s'escau, crear una Taula de desenvolupament local | J86: =G86 -> Establir una relació contínua amb agents socioeconòmics del territori, i si s'escau, crear una Taula de desenvolupament local | L86: Si | M86: ALTA | N86: *Consolidar el Grup de Treball de la Carta Europea de Turisme Sostenible del Ripollès *Elaboració i actualització periòdica del mapa d’agents socioeconòmics de l’ENP (sector primari i secundari) *Establiment de canals de comunicació i coordinació amb els agents socioeconòmics clau del territori. *Estudi de la idoneïtat de crear una Taula de desenvolupament local, en els ENP que encara no ho tinguin (per ENP o agrupacions d’ENP). *Convocar les taules de desenvolupament local ja constituïdes de cada ENP (o agrupacions d’ENP). *Promoció i enfortiment de la participació dels agents clau a les taules de desenvolupament local ja constituïdes. *Participació en la definició i desplegament dels plans de treball de la taula de desenvolupament local. | P86: Revisar si algunes de les accions es poden descartar i treure-ho. Si aquestes accions van totalment vinculades a la CETS valorar incorporar-ho dins l'objectiu específic que hi ha de la CETS i mantenir només el que NO quedi inclòs dins la carta dins aquest objectiu. A la columna vincles posar els objectius de la CETS. Revisar indicadors i fites | Q86: ESNATURA | S86: Nombre de reunions de les taules de desenvolupament local del Ripollès liderades pel Parc | T86: 10 | U86: 20 | V86: =40*4 -> 160 | W86: Ús públic | X86: Xavier Grivé i Rai
D87: 08.3 | E87: Millorar la valorització i comercialització dels productes generats a l'ENP que contribueixen al desenvolupament socioeconòmic i la conservació del patrimoni de l'ENP | F87: 08.3.1 | G87: Implantar un distintiu de qualitat i compatibilitat amb la conservació dels productes de la Xarxa d'ENP o criteris de qualitat propis de l'ENP | H87: Comú | I87: Optatiu | J87: =G87 -> Implantar un distintiu de qualitat i compatibilitat amb la conservació dels productes de la Xarxa d'ENP o criteris de qualitat propis de l'ENP | L87: Si | M87: MITJANA | N87: 1) Participació en les reunions amb els Serveis Centrals per la generació d'un segell comú. En quant al segell propi de la comarca: - 2) Assistència a les reunions del segell del Productes del Ripollès - 3) Incidir en la millora del segell de Productes del Ripollès pel què fa al vincle amb el territori: treballar per què tingui un valor afegit el producte que prové d'una matèria prima que es produeix a la mateixa comarca i que, per tant, té una incidència sobre els hàbitats de l'espai. | Q87: ESNATURA | R87: SENP: Crear una marca que identifiqui els productes agroalimentaris generats en els ENP | S87: 1) Nombre de reunions amb els serveis centrals per a la generació d'un segell comú en què s'ha participat 2) Nombre de reunions del segell del Productes del Ripollès en què s'ha participat 3) Nombre de propostes de millora del segell de Productes del Ripollès | T87: 1) 1 2) 1 3) 1 | U87: 1) 4 2) 4 3) 4 | V87: =12*4 -> 48 | W87: Ús públic / Sistemes agropastorals | X87: Xavier Grivé i Rai / Bernat Perramon
F88: 08.3.2 | G88: Integrar els productes i activitats locals de qualitat en l'oferta d'activitats d'informació i turístiques de l'ENP | H88: Comú | I88: Obligatori | J88: =G88 -> Integrar els productes i activitats locals de qualitat en l'oferta d'activitats d'informació i turístiques de l'ENP | L88: Si | M88: MITJANA | N88: *Elaboració d'un catàleg de ramaders amb producte final *Inclusió de visites a productors o artesans en el catàleg d'activitats de l'ENP *Incorporació de l'Associació Productes del Ripollès en la presa de decisions d'aquesta línia de treball | Q88: ESNATURA CETS | S88: Actuacions amb ramaders amb producte final dirigides a donar un valor afegit en el seu producte vinculat a una bona gestió ramadera | T88: 1) 1 | U88: 2) 4 | V88: =10*4 -> 40 | W88: Ús públic | X88: Xavier Grivé i Rai / Bernat Perramon
F89: 08.3.3 | G89: Promoure fires d'artesania i productes locals de l'ENP | H89: Comú | I89: Optatiu | J89: =G89 -> Promoure fires d'artesania i productes locals de l'ENP | L89: Si | M89: BAIXA | N89: *Donar suport a l'Associació de Productes del Ripollès en la tasca promocional dels productes locals | S89: Nombre de tasques de promoció de l'Ass. Productes del Ripollès en què el PNCTF ha donat suport | T89: 1 | U89: 12 | V89: =10*4 -> 40 | W89: Ús públic | X89: Xavier Grivé i Rai
F90: 08.3.4 | G90: Generar aliances entre el sector primari, el turisme, la restauració i altres per fomentar la gastronomia local | H90: Comú | I90: Optatiu | J90: Generar aliances entre el sector primari, el turisme, la restauració i altres per fomentar la gastronomia i el comerç local | K90: Aportació ramaders i propietaris | L90: Si | M90: MITJANA | N90: 1) Analitzar el Pla de treball de l'Associació Productes del Ripollès per valorar a quines actuacions el Parc pot donar suport i impuls. 2) Suport i participació en les iniciatives de la marca Productes del Ripollès i de l'Agència de Desenvolupament del Ripollès per a incentivar la interacció entre sectors primari i terciari: divulgació i comunicació, formació i assessorament tècnic, comercialització, treball en xarxa, suport a la gestió de l’activitat. 3) Suport i participació per tenir infraestructura comuna (obrador comunitari). | Q90: ESNATURA CETS | S90: 1) Nombre d'actuacions del Pla de treball de l'Associació Productes del Ripollès en què el Parc ha donat suport i impuls. 2) Nombre d'iniciatives de la marca Productes del Ripollès i de l'Agència de Desenvolupament del Ripollès per a incentivar la interacció entre sectors primari i terciari en què el Parc s'ha implicat i/o ha participat. 3) Obtenció d'una infraestructura comuna (obrador comunitari). | T90: 1) 4 2) 4 3) 0 | U90: 1) 12 2) 12 3) 1 | V90: =20*4 -> 80 | W90: Ús públic | X90: Xavier Grivé i Rai
F91: 08.3.5 | G91: Elaborar una diagnosi del teixit productiu local i un pla d’acció amb línies de treball i actuacions concretes per donar-li suport | H91: Comú | I91: Optatiu | J91: Participar en una diagnosi del teixit productiu local i un pla d'acció amb línies de treball i actuacions concretes per a donar-li suport | L91: Si | M91: MITJANA | N91: Participar en la diagnosi del teixit productiu local que es dugui a terme des de l'Associació Productes del Ripollès i l'Agència de Desenvolupament del Ripollès. | Q91: ESNATURA | S91: Nombre d'hores dedicades a la diagnosi | T91: 4 | U91: 32 | V91: 32 | W91: Ús públic | X91: Xavier Grivé i Rai
F92: 08.3.6 | G92: Elaborar una guia per promocionar els agents del territori que potencien i difonen els productes alimentaris locals i de qualitat (allotjaments, restaurants, cellers, establiments, elaboradors i productors) | H92: Comú | I92: Optatiu | J92: NA | K92: No aplica actualment. Producte del Ripollès són els que tiren endavant la pròpia marca i ja tenen una guia per promoure els principal productors, per tant aquest objectiu no és competència de l'espai.
D93: 08.4 | E93: Contribuir a una correcta planificació i gestió dels recursos cinegètics i piscícoles de forma compatible amb els valors de l'ENP | F93: 08.4.1 | G93: Treballar amb l'autoritat competent per garantir objectius de conservació d’espècies i hàbitats en la revisió dels Plans de Gestió Cinegètica | H93: Comú | I93: Obligatori | J93: =G93 -> Treballar amb l'autoritat competent per garantir objectius de conservació d’espècies i hàbitats en la revisió dels Plans de Gestió Cinegètica | L93: Si | M93: MITJANA | N93: 1) Foment d'acords amb les Societats de Caçadors per a incorporar objectius de conservació d’espècies i hàbitats en la revisió dels Plans de Gestió Cinegètica 2) Establiment de mecanismes de col·laboració amb la Reserva Nacional de Caça i les APC | Q93: MAP | S93: 1) Nombre d'acords amb Societats de Caçadors 2) Nombre de reunions anuals amb la RNC | T93: 1) 1 2) 2 | U93: 1) 4 2) 4 | V93: =30*4 -> 120 | W93: Patrimoni natural | X93: Anna Planella
F94: 08.4.2 | G94: Col·laborar en la regulació i ordenació de la caça i la pesca en zones sensibles o amb risc d'afectació d'elements clau objecte de conservació | H94: Comú | I94: Obligatori | J94: =G94 -> Col·laborar en la regulació i ordenació de la caça i la pesca en zones sensibles o amb risc d'afectació d'elements clau objecte de conservació | L94: Si | M94: BAIXA | N94: Impuls a la declaració de refugis de caça i pesca | Q94: MAP | S94: 1) Nombre de refugis de caça declarats dins l'espai 2) Nombre de refugis de pesca declarats dins l'espai | T94: 1) 1 2) 1 | U94: 1) 2 2) 2 | V94: 10 | W94: Patrimoni natural | X94: Anna Planella
F95: 08.4.3 | G95: Donar suport en la gestió de poblacions que generen danys a les activitats econòmiques de l'ENP | H95: Comú | I95: Obligatori | J95: NA | K95: No aplica. Gestió de la RNC i poc aplicable dins l'espai (sense conreus, poques carreteres...)
B96: 9 | C96: FOMENTAR UN TURISME SOSTENIBLE compatible amb la conservació de l'espai | D96: 09.1 | E96: Fomentar un model de turisme que promogui els valors dels espais naturals protegits d'acord amb els agents turístics del territori | F96: 09.1.1 | G96: Desplegar la Carta Europea de Turisme Sostenible (CETS) | H96: Comú | I96: Optatiu | J96: =G96 -> Desplegar la Carta Europea de Turisme Sostenible (CETS) | L96: Si | M96: ALTA | N96: 1) Continuar amb el desplegament de la CETS del Ripollès: Fase I: execució del Programa d'Actuacions 2024-2028, meòries anuals i seguiment d'indicadors Fase II: adhesió d'empreses turístiques a la CETS del Ripollès Fase III: adhesió d'agències de viatges 2) Coordinar les tasques i contractació de la secretaria tècnica que acompanya el projecte 3) Promoure el grup motor i el Fòrum permanent com a ijmpulsors de la CETS 4) Coordinació amb el grup CETSCAT de Parcs Naturals de Catalunya que desenvolupen la CETS 5) Fora del que és estrictament CETS, però dins d'aquest objectiu operatiu, desplegar les accions del Pla de Foment del Turisme de Natura al PNCTF *Fora del que és estrictament CETS, però dins d'aquest objectiu operatiu, desplegar les accions del Pla de Foment del Turisme de Natura al PNCTF | Q96: ESNATURA | S96: 1) Nombre de noves empreses turístiques adherides. 2) Disposar de secretaria tècnica de la CETS. 3) Nombre de reunions amb el grup CETSCAT. 4) Nombre d'accions del Pla de Foment del Turisme de Natura desplegades al PNCTF | T96: 1) 10 2) 0 3) 4 4) 0 | U96: 1) 40 2) 1 3) 16 4) 10 | V96: =80*4 -> 320 | W96: Ús públic | X96: Xavier Grivé i Rai
F97: 09.1.2 | G97: Tramitar la certificació Biosphere | H97: Comú | I97: Optatiu | J97: =G97 -> Tramitar la certificació Biosphere | M97: FORA DEL TERMINI DEL PLA | N97: *Iniciar i analitzar el procés de tramitació de la certificació Biosphere | S97: Nombre de certificacions Biosphere del PNCTF | T97: 0 | U97: 1 | V97: =20*4 -> 80 | W97: Ús públic | X97: Xavier Grivé i Rai
D98: 09.2 | E98: Promoure la coordinació amb els agents turístics del territori (empreses, industries, administració). | F98: 09.2.1 | G98: Treballar amb les empreses turístiques per trobar eines de canvi cap a un model de turisme sostenible i de qualitat | H98: Comú | I98: Optatiu | J98: =G98 -> Treballar amb les empreses turístiques per trobar eines de canvi cap a un model de turisme sostenible i de qualitat | L98: Si | M98: MITJANA | N98: 1) Dinamitzar el grup d'empreses adherides a la CETS del Ripollès per a liderar plegats la recerca d'eines de canvi cap a un model de turisme més sostenible. 2) Aconseguir l'adhesió de més empreses compromeses amb la CETS del Ripollès. | Q98: ESNATURA | S98: 1) Existència del Grup d'Empreses de la CETS del PNCTF 2) Nombre d'empreses adherides a la CETS del Ripollès | T98: 1) 0 2) 1 3) 20 | U98: 1) 1 2) 2 3) 50 | V98: =20*4 -> 80 | W98: Ús públic | X98: Xavier Grivé i Rai
F99: 09.2.2 | G99: Crear productes i paquets turístics amb associacions d’empreses turístiques i operadors turístics | H99: Comú | I99: Optatiu | J99: =G99 -> Crear productes i paquets turístics amb associacions d’empreses turístiques i operadors turístics | L99: Si | M99: MITJANA | N99: 1) Entrar a la fase III de la CETS del Ripollès, amb empreses que incentivin i facilitin la comercialització, des de la qual liderar la creació de paquets turístics sostenibles. 2) Adherir AAVV a la CETS. 3) Incentivar la creació de paquets turístics sostenibles al Ripollès. | Q99: ESNATURA | S99: 1) Entrada a la fase III de la CETS del Ripollès 2) Nombre d'AAVV adherides a la CETS. 3) Paquets turístics sostenibles creats al Ripollès. | T99: 1) 0 2) 1 3) 1 | U99: 1) 1 2) 4 3) 16 | V99: 50 | W99: Ús públic | X99: Xavier Grivé i Rai
A100: ÚS PÚBLIC I SOCIAL | B100: 10 | C100: ORDENAR ELS USOS I APROFITAMENTS per garantir l'equilibri de les activitats humanes amb la conservació de la biodiversitat | D100: 10.1 | E100: Estandarditzar de regulació d'usos i aprofitaments en base al model de Pla de protecció | F100: 10.1.1 | G100: Establir un model de construcció a l'ENP en base al model de Pla de protecció | H100: Comú | I100: Obligatori | J100: NA | K100: No aplica, pràcticament no hi ha construccions dins l'espai | R100: SPEN: Elaborar model
...

Sheet VINCLE AMENAÇA_OBJ. OPERATIU
A1: TAULA DE VINCLE ENTRE LES AMENACES I ELS OBJECTIUS OPERATIUS DE L'EIX DEL PATRIMONI NATURAL
A3: Eix 1. Natura
A4: Codi | B4: Objectius operatius | C4: Tipologia amenaça | D4: Amenaça concreta
A5: 01.1.1 | B5: =PLA!J5 -> Implementar i executar plans de gestió específics per a hàbitats i espècies de conservació prioritària dins l'ENP | C5: No especificada
A6: 01.1.2 | B6: =PLA!J6 -> Adaptar i executar plans de gestió específics per a elements geològics de conservació prioritària dins l'ENP | C6: No especificada
A7: 01.2.1 | B7: =PLA!J7 -> Implementar la metodologia de gestió adaptativa (Estàndards Oberts de Gestió Adaptativa a Catalunya) en tots els processos de l'ENP | C7: No especificada
A8: 01.2.2 | B8: =PLA!J8 -> Executar les mesures previstes en els plans de conservació o recuperació d'espècies amenaçades de forma coordinada amb el Servei de Flora i Fauna en l'àmbit de l'ENP | C8: No especificada
A9: 01.2.3 | B9: =PLA!J9 -> Executar les mesures de gestió previstes en els plans de control i erradicació d'espècies exòtiques de forma coordinada amb el Servei de Flora i Fauna en l'àmbit de l'ENP | C9: Espècies invasores i patògens
A10: 01.2.4 | B10: =PLA!J10 -> Desplegar els objectius i tasques recollits en els instruments de referència i compromisos internacionals | C10: No especificada
A11: 01.3.1 | B11: =PLA!J11 -> Identificar espais pel foment de la dinàmica natural i l'aprofitament no extractiu | C11: Gestió i modificació de sistemes naturals
A12: 01.3.2 | B12: =PLA!J12 -> Afavorir la maduresa dels sistemes forestals | C12: Gestió i modificació de sistemes naturals
A13: 01.3.3 | B13: =PLA!J13 -> NA | C13: Gestió i modificació de sistemes naturals
A14: 01.3.4 | B14: =PLA!J14 -> NA | C14: Gestió i modificació de sistemes naturals
A15: 01.3.5 | B15: =PLA!J15 -> Fomentar el paisatge en mosaïc | C15: Gestió i modificació de sistemes naturals
A16: 01.3.6 | B16: =PLA!J16 -> Gestionar i intervenir en la dinàmica de poblacions de fauna que no tenen depredador natural | C16: Gestió i modificació de sistemes naturals
... A36: 03.4.2 | B36: =PLA!J36 -> Identificar espais prioritaris per a la gestió directa | C36: No especificada

Sheet Taxonomia Amenaces
A1: Taxonomia d'Amenaces - Xarxa d'ENP Catalunya
A2: Versió 1_revisada pels equips del PNAT Cap de Creus, PNAT Montgrí-Medes, PNAT els Ports, PNIN Poblet, PNAT Delta de l'Ebre, PNAT Alt Pirineu i PNAT Capçaleres del Ter i Freser
A3: Font de dades 1: List of pressures and threats for reporting 2019-2024 v1.1 (Comissió Europea)
A4: Font de dades 2: Llistat de pressions i amenaces del Pla de Protecció del Cadí-Moixeró, inspirat en el llistat de la Comissió Europea
A5: Font de dades 3: IUCN/CMP Threats Classification v 3.3 (2016) i v4.0 draft (2023)
A8: Codi Amenaça | B8: Tipologia d'amenaça | C8: Codi Amenaça | D8: Nom Amenaça | E8: Exemples i descripció del grup
A9: 1 | B9: Urbanització i edificació | C9: 1.1 | D9: Urbanització residencial | E9: Construccions relacionades amb àrees residencials. Tot i que la normativa no permet noves construccions, existeixen edificacions fóra d'ordenació. També casos de remodelacions, reconstruccions o ampliacions d'edificis rurals per usos agrícoles, forestals, ramaders, recreatius, residencials, etc). Restauracions de cabanes i bordes que no deixen forats per ratpenats. cases forestals. Bordes que es canvien d'ús per hosteleria
C10: 1.2 | D10: Urbanització comercial o industrial
C11: 1.3 | D11: Àrees recretives i turístiques | E11: Refugis de muntanya que es remodelen, impacten etc
A12: 2 | B12: Producció primària | C12: 2.1 | D12: Activitat agrícola | E12: Cultius annuals i perennes. Canvis de tipus de cultiu, secà a regadiu o al revés. Canvi d'usos del sòl com cultius de vinya a muntanya, Inclosos el cultiu de l'arròs amb substàncies biocides. Inclòs el cultiu de marihuana
C13: 2.2 | D13: Plantacions forestals
C14: 2.3 | D14: Ramaderia | E14: Ramaderia tan intensiva com extensiva i semi-intensiva (pastura de dia i nit en corral)
C15: 2.4 | D15: Aqüicultura | E15: Aquicultura marina i d'aigua dolça, a l'interior o als voltants del parc
A16: 3 | B16: Producció d'energia i mineria | C16: 3.1 | D16: Activitats de la mineria | E16: Mineria de qualsevol tipus (a cel obert, marina, al·luvial com extracció d'àrids i còdols, subterrània), a l'interior o als voltants del parc. Extracció de torba i salines. Si aplica, extracció d'hidrocarburs terrestres o marins
C17: 3.2 | D17: Producció d'energia renovable | E17: Centrals de producció d'energia renovable (molins eòlics terrestres o marins, instal·lacions solars, hidroelèctriques, geotèrmia inclosos els impactes de fauna contra les instal·lacions). A dins del parc o afectant connectors entre parcs
A18: 4 | B18: Infrastructures de transport i serveis | C18: 4.1 | D18: Vials de transport | E18: Carreteres, pistes forestals, línies fèrries i cremalleres
C19: 4.2 | D19: Conduccions | E19: Conduccions elèctriques, aqueductes, canals de rec, estacions de bombament, conduccions d'aigua o gas
C20: 4.3 | D20: Infrastructures marines | E20: Rutes marines, canals, impactes de vaixells sobre balenes i infrastructura associada. Ports, pantalans, etc
C21: 4.4 | D21: Tancaments i vallats | E21: Tancaments, valles perimetrals i parets de tota mena, en carreteres, per bestiar, estètiques, etc
A22: 5 | B22: Extracció de recursos naturals | C22: 5.1 | D22: Caça i recol·lecció d'animals | E22: Caça i recolecció d'animals, ous, mel silvestre, etc ja sigui per subsistència, esport, tradició, comerç o de forma accidental
C23: 5.2 | D23: Recol·lecció de vegetals | E23: Recolecció de plantes, bolets, resines, líquens, etc
C24: 5.3 | D24: Treballs forestals | E24: Treball forestals de tota mena (arreu, selectiva, carboneig, aclarides, etc)
C25: 5.4 | D25: Pesca i semblants | E25: Pesca i recollida de recursos aquàtics de tota mena i amb qualsevol tècnica (artesanal, xarxa, marisqueig, recollida de corall, pesca accidental, recreativa, etc)
A26: 6 | B26: Molèsties | C26: 6.1 | D26: Molèsties per activitats recreatives | E26: Per activitats recreatives al medi natural de qualsevol tipus (excursionisme, bicicleta, cavall, vehicles a motor, escalada, esquí de muntanya, acampada temporal, pernoctació, ornitòlegs, fotografs, esports nàutics, pesca turisme, àrees recreatives, drons, globus, parapents, buggy-kite, sobrevol amb helicòpters, amb ultralleugers, motos de neu, etc) i tan sigui esporàdica com recurrent
C27: 6.2 | D27: Molèsties per activitats militars | E27: Activitats militars de qualsevol mena (camps militars, assajos amb artilleria, etc)
C28: 6.3 | D28: Altres tipus de molèsties | E28: Qualsevol altra molèstia (per bany en rius i tolles, passeig de gossos, peregrinatges, aplecs, recerca sobre espècies, extraccions arqueològiques, vandalisme, tràfic de drogues, etc)
C29: 6.4 | D29: Molèsties per activitats multitudinàries | E29: Activitats organitzades i multitudinàries, per exemple curses de muntanya, festivals, esdeveniments, filmacions, fins i tot enterraments
A30: 7 | B30: Gestió i modificació de sistemes naturals | C30: 7.1 | D30: Foc | E30: Foc, grans incendis forestals i supressió del foc, incloses activitats de restauració post-foc
C31: 7.2 | D31: Gestió de l'aigua | E31: Construcció i utilització de preses, canals, captacions, pous, dics, etc de qualsevol mena. Extracció / captacions d'aigua per rec, etc. Construcció de basses per fer neu artificial. Dessaladores, potabilitzadores, depuradores, conduccions, trasvassaments, emissaris de salmorres, alteració de cabals, gestió de cabals en rius
C32: 7.3 | D32: Moviments de terres i sediments | E32: Gestió i estabilització de terrenys i sediments (estabilització de dunes, construccions en litorals, remediació de sòls, restauració de mines, dragatges, moviments de sorres, etc)
C33: 7.4 | D33: Modificació del clima | E33: Activitats per modificar el clima o processos naturals (prevenció de gelades, fertilització amb ferro a l'oceà, captura de carboni, etc)
C34: 7.5 | D34: Gestió d'hàbitats | E34: Gestió d'hàbitats: gestió d'aigua dolça de rec i arrossars (que pot afectar a llacunes, etc), retirada de fustes en rius, desbrossades, creació d'esculls artificials, alimentació d'ocells, tancament de coves, barreres elèctriques
C35: 7.6 | D35: Desaparició d'activitats tradicionals | E35: Desaparició de pràctiques tradicionals com pastura extensiva, canvi en el maneig de la pastura, la tipologia de bestiar, caça per control de predadors, etc
A36: 8 | B36: Espècies invasores i patògens | C36: 8.1 | D36: Espècies invasores | E36: Espècies invasores com rates en illes, animals domèstics assilvestrats, musclo zebra, bambú, peixos introduïts com Phoxinus en estanys d'alta muntanya, etc
C37: 8.2 | D37: Espècies desestabilitzades | E37: Espècies natives desestabilitzades com superpoblació de cèrvids, porcs senglars, manca de carnívors, blooms d'algues, plagues d'insectes, o amb impactes puntuals com predadors sobre espècies sensibles com colònies d'ocells, gall fer, etc
C38: 8.3 | D38: Introducció de genotips aliens | E38: Material genètic introduït com cultius resistents a plagues, creuament de gat domèstic amb gat fer, restauracions d'hàbitats fetes amb varietats alienes, arbres o instectes modificats genèticament, aquicultura amb espècies no natives, etc
C39: 8.4 | D39: Plagues i patògens | E39: Malalties que afecten conills, grip aviar, botulisme, castanyers, oliveres, cítrics, amfibis, etc
A40: 9 | B40: Polució | C40: 9.1 | D40: Polució aquàtica | E40: Polució dissolta en aigua (aigües sèptiques, efluents industrials, pesticides, fertilitzants, efluents de la mineria, excès de nutrients en activitats de l'aquicultura, purins, potasses per desfer la neu en pistes i carreteres, etc
C41: 9.2 | D41: Residus sòlids | E41: Residus sòlids de qualsevol orígen i en medi terrestre o marí, inclosos de la caça, pesca, agricultura, aqüicultura, del turisme, construcció, transport, xarxes fantasma i elements abandonats al medi
C42: 9.3 | D42: Polució aèria | E42: Residus en medi aeri com partícules, gasos, o partícules radioactives
C43: 9.4 | D43: Contaminació acústica, llumínica o per radiació | E43: Contaminació lumínica, tèrmica com efluents de centrals elèctriques en rius, acústica com soroll en aeroports o zones industrials o per escoles de formació de pilots d'helicòpters al Pirineu, camps electromagnètics en cables, sonars submarins, soroll i onades causades per embarcacions recreatives, llums de les maquinàries a pistes d'esquí, il·luminació nocturna en estacions d'esquí, il·luminació de monuments, etc
A44: 10 | B44: Grans pertorbacions naturals | C44: 10.1 | D44: Pertorbacions d'origen geològic | E44: De tipus geològic com terratrèmols, esllavissades, allaus, erupcions volcàniques
C45: 10.2 | D45: Pertorbacions d'origen metereològic | E45: Per fenòmens extrems com inundacions, temporals, pedregades, etc
A46: 11 | B46: Canvi global i/o climàtic | C46: 11.1 | D46: Impactes del canvi climàtic en sistemes físics i químics | E46: Canvis en sistemes físics i químics com acidificació d'oceans, augment del CO2 atmosfèric, pèrdua de sediments, colmatació de basses i llacunes, canvis en corrents marins, regressió de la línia de costa, subsidència del Delta, canvis en la cobertura de núvols, etc
C47: 11.2 | D47: Impactes del canvi climàtic relatius a l'alteració del règim de temperatures | E47: Canvis en règims de temperatures: onades de calor o de fred, canvis en la temperatura del mar, fusió de glaceres, etc
C48: 11.3 | D48: Impactes del canvi climàtic relatius a l'alteració del règim de precipitació i sequera | E48: Canvis en règims de precipitació i règims hidrològics com patrons de pluja, d'innivació, generant sequeres, increment de la severitat d'inundacions, reducció de la superfície de llacs i estanys, etc
C49: 11.4 | D49: Pujada del nivell del mar

Sheet Llistes
A1: Llista d'amenaces OS | D1: Si/No | G1: Codi Amenaça | H1: Nom Amenaça
A2: 0 | B2: No especificada | D2: Si | G2: 0 | H2: No especificada
A3: 2 | B3: Urbanització i edificació | D3: No | G3: 1.1 | H3: Urbanització residencial
A4: 3 | B4: Producció primària | D4: Dubtós | G4: 1.2 | H4: Urbanització comercial o industrial
A5: 4 | B5: Producció d'energia i mineria | G5: 1.3 | H5: Àrees recretives i turístiques
A6: 5 | B6: Infrastructures de transport i serveis | G6: 2.1 | H6: Activitat agrícola
A7: 6 | B7: Extracció de recursos naturals | G7: 2.2 | H7: Plantacions forestals
A8: 7 | B8: Molèsties | G8: 2.3 | H8: Ramaderia
A9: 8 | B9: Gestió i modificació de sistemes naturals | G9: 2.4 | H9: Aqüicultura
A10: 9 | B10: Espècies invasores i patògens | G10: 3.1 | H10: Activitats de la mineria
A11: 10 | B11: Polució | G11: 3.2 | H11: Producció d'energia renovable
A12: 11 | B12: Grans pertorbacions naturals | G12: 4.1 | H12: Vials de transport
B13: Canvi global i/o climàtic | G13: 4.2 | H13: Conduccions
G14: 4.3 | H14: Infrastructures marines
G15: 4.4 | H15: Tancaments i vallats
G16: 5.1 | H16: Caça i recol·lecció d'animals
G17: 5.2 | H17: Recol·lecció de vegetals
G18: 5.3 | H18: Treballs forestals
G19: 5.4 | H19: Pesca i semblants
G20: 6.1 | H20: Molèsties per activitats recreatives
G21: 6.2 | H21: Molèsties per activitats militars
G22: 6.3 | H22: Altres tipus de molèsties
G23: 6.4 | H23: Molèsties per activitats multitudinàries
G24: 7.1 | H24: Foc
G25: 7.2 | H25: Gestió de l'aigua
... G43: 11.4 | H43: Pujada del nivell del mar

Sheet Full1
A1: Comú / Específic | B1: Obligatori / Optatiu | C1: Prioritat | E1: Pel POA
A2: Comú | B2: Obligatori | C2: MÀXIMA | E2: Si
A3: Específic | B3: Optatiu | C3: ALTA | E3: No
C4: MITJANA
C5: BAIXA
C6: FORA DEL TERMINI DEL PLA
