Workbook

Sheet ESTRATÈGIA
C3: ESQUEMA CONCEPTUAL PER A LA ELABORACIÓ DEL PLA ESTRATÈGIC EN EL MARC
C4: DELS ESTÀNDARDS OBERTS PER A LA GESTIÓ ADAPTATIVA A CATALUNYA

Sheet INSTRUCCIONS
A1: PESTANYA DE PRIORITZACIÓ
A2: Llistat elements: | B2: Tasca 1: Revisar el llistat d'elements prioritzats per tal d'avaluar si cal afegir-ne algun o treure'n algun. A la columna comentaris cal argumentar, breument, el perquè de la decisió.
A4: Llistat amenaces: | B4: Tasca 2: A partir de la taxonomia d'amenaces que es troba a la pestanya final, cal omplir les tres columnes (E, F i G) amb les tres principals amenaces per a la conservació de l'element. S'afegeixi una darrera columna per si hi ha amenaces que no es troben incloses a la taxonomia.
A6: PESTANYA DEL PLA
A7: Explicacions:
B8: 7 Eixos temàtics
B9: Els objectius generals estan directament associats als objectius generals dels Plans de Protecció del medi naatural i del paisatge. NO ES PODEN RETOCAR
B10: Objectius estratègics: definits en un grup de treball intern de serveis Centrals i dels Parcs durant l'any 2023. NO ES PODEN RETOCAR
B11: Objectius operacionals: definits en un grup de treball intern de serveis Centrals i dels Parcs durant l'any 2023
A14: Tasques a realitzar:
A15: Objectius operacionals: | B15: El llistat d'objectius operacionals té una columna al costa (columna I) on s'indica si l'objectiu és obligatori de mantenir al Pla estratègic o no.
B16: Tasca 1: Columna I. Revisar els que es posa com a obligatoris per veure si són realment aplicables a l'espai o no.
B17: Tasca 2: Columna I. Revisar els que posa "Opcional" per identificar els que són aplicables o no a l'espai. O, també, determinar si algun d'ells seria aplicable o es pot concretar millor el redactat de l'objectiu.
B18: Tasca 3: Columna J. En ambdós casos, cal posar a la columna J, el redactat final de l'objectiu concretat a l'espai. En el cas de que l'objectiu s'elimina, posar "NA". Ara es reprodueix el redactat dels objectius operacionals derivats del grup de treball esmentat
B19: Tasca 4: Columna K. Per tots els casos en que hi ha modificació respecte al redactat original de l'objectiu operatiu -i, també, en el cas que es consideri que s'ha d'eliminar-, a la columna K cal redactar molt breument el motiu pel qual es prèn la decisió.
B20: Tasca 5: Columna L. Incloure un Si/No avaluant si l'objectiu operatiu podria tenir mesures a incorporar a la programació d'actuacions de l'espai (Si) o, per altra banda, el seu assoliment depèn d'altres òrgans, com l'ACA o altres serveis dins la DGPAMN (No).
B21: Tasca 6: Columna M. Definir la prioritat que hauria de tenir l'assoliment de l'objectiu (màxima, si cal assolir en els propers 4 anys, o altrament alta, mitja o baixa). També hi ha l'opció de prioritat a assolir a més llarg termini.
A22: Propostes genèriques d'accions: | B22: Tasca 7: Columna N. En aquest columna cal introduir les accions, de manera genèrica, que caldria aplicar a l'espai per tal d'assolir l'objectiu operatiu. No es tracta d'un llistat d'accions concretes si no, més aviat, accions generals que acabarien concretant-se en la programació anual. PER A INICIAR AMB LA TAULA US PODEU BASAR MOLT EN LA FEINA JA FETA DE PRIORITZACIÓ DE MESURES PEL MAP
B23: En el cas dels objectius operatius que s'ha considerat que no són aplicables a l'espai, cal avaluar si podrien tenir alguna acció que sí tindria sentit d'incloure al Pla estratègic tot i que l'objectiu de manera global no hi ´seria d'aplicació.
A24: Indicadors: | B24: Tasca 8: Columna Q. Posar un indicar SMART per avaluar el compliment de la mesura proposada a la columna N
A25: Fites a assolir en 4 anys: | B25: Tasca 9: Posar un valor de l'indicador a asolir: valor mínim necessari (columna R) o valor desitjable (columna S).
A26: Hores de dedicació: | B26: Tasca 10: Columna T. Realitzar una aproximació el més acurada que es pugui de les hores del personal de gestió de l'espai que cal destinar per a la realització de l'acció.
A27: Àrea responsable: | B27: Tasca 11: Columna U. Indicar quina àrea de l'equip de gestió és responsable de coordinar l'execució de l'acció.
A28: Persona responsable: | B28: Tasca 12: Columna V. Indicar quina persona dins l'àrea seria l'encarregada.
A30: PESTANYA DEL VINCLE
A31: Definir vincle amenaça vs. Obj. Operatiu | B31: Tasca 1: Establir / Revisar el vincle entre les amenaces identificades a la pestanya de priorització i els objectius operatius definits a la columna J de la pestanya Pla. La columna B conté el llistat dels objectius operatius tal i com quedaran definits després de la vostra revisió.
B32: Tasca 2: En cas que es pugui, definir l'amenaça / factor / causa concret a la que atén l'objectiu definit al Pla. Poden ser més d'una.
B33: És important que es visualitzi a quina amenaça es dirigeix l'objectiu operatiu que es proposa al Pla, tot i que, no sempre hi ha d'haver un vincle clar. Pot haver algun objectiu sense amenaça vinculada.

Sheet PRIORITZACIÓ
A2: Llistats corresponent a l'espai de Natura 2000 ES5120004 "Zona volcànica de la Garrotxa"
A3: LLISTAT D'ELEMENTS PRESENT A L'ESPAI | H3: AMENACES PER A CADA ELEMENT
A4: Hàbitats d'interès comunitari | B4: PE | C4: MAP | D4: 25% IdR | E4: Puntuació IdR | F4: PRIORITARI PE | G4: Comentaris en cas de canvi en la priorització | H4: Amenaça 1 segons taxonomia | I4: Amenaça 2 segons taxonomia | J4: Amenaça 3 segons taxonomia | K4: Altres amenaces | L4: Comentari
A5: 3150 - Estanys naturals eutròfics amb vegetació natant (Hydrocharition) o poblaments submersos d'espigues d'aigua (Potamion) | C5: Si | F5: Sí | H5: Gestió de l'aigua | I5: Desaparició d'activitats tradicionals | J5: Impactes del canvi climàtic relatius a l'alteració del règim de precipitació i sequera | K5: Impactes del canvi climàtic relatius a l'alteració del règim de temperatures | L5: Activitat ramadera
A6: 3240 - Rius de tipus alpí amb bosquines de muntanya | C6: Si | F6: Sí | H6: Gestió de l'aigua | I6: Activitat agrícola | J6: Polució aquàtica | K6: Reducció de l'espai fluvial
A7: 3250 - Rius mediterranis amb vegetació del Glaucion flavi | B7: Si | F7: Sí | H7: Gestió de l'aigua | I7: Activitat agrícola | J7: Polució aquàtica | K7: Reducció de l'espai fluvial
A8: 3270 - Rius amb vores llotoses colonitzades per herbassars nitròfils del Chenopodion rubri (p.p.) i del Bidention (p.p.) | B8: Si | C8: Si | D8: Si | E8: 4 | F8: Sí | H8: Gestió de l'aigua | I8: Activitat agrícola | J8: Polució aquàtica | K8: Reducció de l'espai fluvial
A9: 6210 - Prats -i fàcies emmatades- medioeuropeus, seminaturals, sobre substrat calcari (Festuco-Brometea) | B9: Si | C9: Si | F9: Sí | H9: Ramaderia | I9: Espècies desestabilitzades | J9: Espècies invasores | K9: Deute d'extinció | L9: Sobrepastura i abandonament o falta de manteniment d'aquests prats / Entenem per espècie desestabilitzades el porc senglar / deute d'extinció
A10: 6510 - Prats de dall de terra baixa i de la muntanya mitjana (Arrhenatherion) | B10: Si | C10: Si | D10: Si | E10: 3.625 | F10: Sí | H10: Desaparició d'activitats tradicionals | I10: Activitat agrícola | J10: Espècies desestabilitzades | K10: Espècies invasores | L10: Parcel·les petites marginals abandonades / Parcel·les amb millor sòls canvi d'ús /Entenem per espècie desestabilitzades el porc senglar / deute d'extinció
A11: 8210 - Costers rocosos calcaris amb vegetació rupícola | B11: Si | C11: Si | F11: No | G11: No s'observa una amenaça greu.
A12: 8220 - Costers rocosos silicis amb vegetació rupícola | C12: Si | F12: No | G12: No s'observa una amenaça greu.
A13: 8230 - Terraprims silicis amb vegetació pionera (Sedo-Scleranthion) | C13: Si | D13: Si | E13: 4.75 | F13: No | G13: Hàbitat sense presència al Parc Natural | L13: Xavier oliver mirarà si aquest hàbitat està prsent al Parc
A14: 9120 - Fagedes acidòfiles | B14: Si | C14: Si | D14: Si | E14: 3.625 | F14: Sí | H14: Treballs forestals | I14: Impactes del canvi climàtic relatius a l'alteració del règim de precipitació i sequera | L14: Treballs forestals que sobrexploten el bosc
A15: 9130 - Fagedes neutròfiles | C15: Si | D15: Si | E15: 3.625 | F15: Sí | H15: Treballs forestals | I15: Impactes del canvi climàtic relatius a l'alteració del règim de precipitació i sequera | L15: Treballs forestals que sobrexploten el bosc
A16: 9150 - Fagedes calcícoles xerotermòfiles | B16: Si | C16: Si | D16: Si | E16: 3.875 | F16: Sí | H16: Treballs forestals | I16: Impactes del canvi climàtic relatius a l'alteració del règim de precipitació i sequera | L16: Treballs forestals que sobrexploten el bosc
A17: 9160 - Rouredes de roure pènol i boscos mixtos del Carpinion betuli | B17: Si | C17: Si | F17: Sí | H17: Treballs forestals | I17: Impactes del canvi climàtic relatius a l'alteració del règim de precipitació i sequera
A18: 9180p - Boscos de vessants rostos, tarteres o barrancs, del Tilio-Acerion | C18: Si | D18: Si | F18: No | G18: Hàbitat sense presència al Parc Natural. | L18: comprovar si existeix
A19: 91E0p - Vernedes i altres boscos de ribera afins (Alno-Padion) | B19: Si | C19: Si | D19: Si | E19: 3.625 | F19: Sí | H19: Gestió de l'aigua | I19: Activitat agrícola | J19: Polució aquàtica | K19: Reducció de l'espai fluvial / invasores
A20: 9260 - Castanyedes | B20: Si | C20: Si | F20: No | G20: Són plantacions.
A21: 92A0 - Alberedes, salzedes i altres boscos de ribera | B21: Si | C21: Si | F21: Sí | H21: Treballs forestals | I21: Impactes del canvi climàtic relatius a l'alteració del règim de precipitació i sequera
A22: 9340 - Alzinars i carrascars | B22: Si | C22: Si | D22: Si | E22: 4.25 | F22: Sí | H22: Treballs forestals | I22: Impactes del canvi climàtic relatius a l'alteració del règim de precipitació i sequera
A23: 9540 - Pinedes mediterrànies | B23: Si | C23: Si | D23: Si | F23: No | G23: No s'observa una amenaça greu.
A24: 34n Joncedes | B24: Si | F24: Sí | H24: Ramaderia | L24: Abandonament i canvi d'activitat ramadera
A25: 34g Fenassars | F25: Sí | H25: Ramaderia | L25: Abandonament i canvi d'activitat ramadera
A26: 35h Prats silicícoles i xeròfils | F26: Sí | H26: Ramaderia | I26: Espècies invasores
A27: 41.b332+ Altres bedollars, sovint secundaris, pirinencs (i del territori catalanidic septentrional) | B27: Si | F27: Sí | H27: Treballs forestals | I27: Impactes del canvi climàtic relatius a l'alteració del règim de precipitació i sequera
A28: 44.128+ Gatelledes (boscos, generalment baixos, de Salix atrocinerea), amb Equisetum telmateia, Carex pendula..., de fons de barrancs i depressions, amb sòl xop, al territori catalanídic | F28: Sí | H28: Gestió de l'aigua | I28: Activitat agrícola | J28: Polució aquàtica | K28: Reducció de l'espai fluvial
A30: Espècies presents a l'espai | B30: PE | C30: MAP | D30: 25% IdR | E30: Puntuació IdR | F30: PRIORITARI PE | G30: Comentaris en cas de canvi en la priorització | H30: Amenaça 1 segons taxonomia | I30: Amenaça 2 segons taxonomia | J30: Amenaça 3 segons taxonomia | K30: Altres amenaces
A31: Abida secale | B31: Si | F31: Sí | H31: Gestió de l'aigua | I31: Impactes del canvi climàtic relatius a l'alteració del règim de precipitació i sequera
A32: Accipiter gentilis gentilis | C32: Si | F32: No | G32: Espècie forestal rapinyaire amb la massa forestal no pateix
A33: Aconithum pyrenaicum | B33: Si | F33: Sí | H33: Treballs forestals | I33: Activitat agrícola | J33: Impactes del canvi climàtic relatius a l'alteració del règim de precipitació i sequera
A34: Actitis hypoleucos | C34: Si | F34: No | G34: No s'observa una amenaça greu
A35: Alcedo atthis | C35: Si | D35: Si | E35: 1.833 | F35: No | G35: No s'observa una amenaça greu
A36: Alytes obstetricans | C36: Si | F36: Sí | H36: Gestió de l'aigua | I36: Activitat agrícola | J36: Plagues i patògens
A37: Anas platyrhynchos | C37: Si | F37: No | G37: No s'observa una amenaça greu
A38: Asplenium marinum | B38: Si | F38: No
A39: Austropotamobius pallipes | B39: Si | C39: Si | D39: Si | E39: 2.167 | F39: Sí | H39: Plagues i patògens | I39: Gestió de l'aigua | J39: Espècies invasores
A40: Barbastella barbastellus | C40: Si | D40: Si | E40: 2.389 | F40: Sí | H40: Treballs forestals
A41: Barbus meridionalis | C41: Si | D41: Si | E41: 2.389 | F41: Sí | H41: Gestió de l'aigua | I41: Polució aquàtica | J41: Espècies invasores
A42: Belisarius xambeui | B42: Si | F42: Sí | H42: Treballs forestals
A43: Bofillella subarcuata | B43: Si | F43: Sí | I43: Gestió de l'aigua
A44: Buteo buteo | C44: Si | F44: No | G44: No s'observa una amenaça greu
A45: Calotriton asper | D45: Si | E45: 1.833 | F45: Sí | H45: Gestió de l'aigua | I45: Activitat agrícola | J45: Plagues i patògens
A46: Caprimulgus europaeus | C46: Si | F46: No | G46: Es desconeix el seu estatus en el Parc
A47: Carabus granulatus | B47: Si | D47: Si | F47: No | G47: Es desconeix el seu estatus en el Parc
A48: Carex grioletii | B48: Si | F48: Sí | H48: Treballs forestals
A49: Cerambyx cerdo | C49: Si | F49: No | G49: No s'observa una amenaça greu
A50: Certhia brachydactyla all others | C50: Si | F50: No | G50: No s'observa una amenaça greu
A51: Cinclus cinclus | C51: Si | F51: Sí | H51: Gestió de l'aigua | I51: Polució aquàtica
A52: Circaetus gallicus | C52: Si | F52: No | G52: No s'observa una amenaça greu
A53: Circus cyaneus | C53: Si | F53: No | G53: No tenim hàbitat potencial ni població
A54: Coenagrion mercuriale | C54: Si | F54: Sí | H54: Gestió de l'aigua | I54: Polució aquàtica | L54: Fer superfícies innundables previ a l'eliminació de preses
A55: Columba palumbus palumbus | C55: Si | F55: No | G55: No s'observa una amenaça greu
A56: Coturnix coturnix | C56: Si | F56: Sí | H56: Activitat agrícola | I56: Caça i recol·lecció d'animals
A57: Cuculia argentea | B57: Si | F57: No | G57: Es desconeix el seu estatus en el Parc
A58: Eriogaster catax | C58: Si | D58: Si | E58: 1.833 | F58: No | G58: Es desconeix el seu estatus en el Parc
A59: Euphydryas aurinia | C59: Si | F59: Sí | H59: Activitat agrícola | I59: Ramaderia
A60: Euplagia quadripunctaria | C60: Si | F60: No | G60: No s'observa una amenaça greu
A61: Falco tinnunculus | C61: Si | F61: No | G61: No s'observa una amenaça greu
A62: Felis sylvestris | D62: Si | E62: 1.833 | F62: Sí | H62: Introducció de genotips aliens
A63: Fringilla coelebs all others | C63: Si | F63: No | G63: No s'observa una amenaça greu
A64: Galanthus nivalis | B64: Si | F64: Sí | H64: Treballs forestals | I64: Gestió d'hàbitats | J64: Àrees recretives i turístiques
A65: Galerida cristata | C65: Si | F65: No | G65: No s'observa una amenaça greu
A66: Gallinula chloropus | C66: Si | F66: Sí | H66: Gestió de l'aigua | I66: Espècies invasores | J66: Treballs forestals
A67: Graellsia isabellae | B67: Si | C67: Si | D67: Si | E67: 1.917 | F67: Sí | H67: Treballs forestals
A68: Hieraaetus pennatus | C68: Si | F68: No | G68: No s'observa una amenaça greu
A69: Hierophis viridiflavus | D69: Si | E69: 1.667 | F69: No | G69: No tenim cites dins el Parc
A70: Ilex aquifolium | B70: Si | F70: Sí | H70: Treballs forestals | I70: Recol·lecció de vegetals
A71: Isopyrum thalictroides | B71: Si | F71: Sí | H71: Treballs forestals | I71: Ramaderia
A72: Jynx torquilla | C72: Si | F72: No | G72: No s'observa una amenaça greu
A73: Lacerta bilineata | D73: Si | E73: 1.833 | F73: Sí | H73: Treballs forestals | I73: Activitat agrícola
A74: Lanius collurio | C74: Si | F74: Sí | H74: Activitat agrícola | I74: Ramaderia
A75: Lanius excubitor meridionalis | C75: Si | F75: Sí | H75: Desaparició d'activitats tradicionals
A76: Larus michahellis | C76: Si | F76: No | G76: No s'observa una amenaça greu
A77: Larus ridibundus | C77: Si | F77: No | G77: No s'observa una amenaça greu
A78: Lucanus cervus | C78: Si | F78: Sí | H78: Gestió d'hàbitats
A79: Lutra lutra | C79: Si | F79: Sí | H79: Gestió de l'aigua | I79: Molèsties per activitats recreatives
A80: Mannia fragans | B80: Si | D80: Si | F80: Sí | H80: Espècies desestabilitzades | L80: Població reduïda
A81: Mauremys leprosa | B81: Si | C81: Si | F81: Sí | H81: Gestió de l'aigua | I81: Polució aquàtica | J81: Gestió d'hàbitats
A82: Merops apiaster | C82: Si | F82: No | G82: No s'observa una amenaça greu
A83: Miniopterus schreibersii | C83: Si | D83: Si | E83: 1.833 | F83: Sí | H83: Molèsties per activitats recreatives
A84: Molopidius spinicollis | B84: Si | F84: No | G84: Es desconeix el seu estatus en el Parc
A85: Montserratina martorelli | B85: Si | F85: Sí | G85: Es desconeix el seu estatus en el Parc | H85: Gestió d'hàbitats
A86: Muscicapa striata | C86: Si | F86: No | G86: No s'observa una amenaça greu
A87: Myotis bechsteinii | C87: Si | D87: Si | E87: 2.167 | F87: Sí | H87: Treballs forestals | I87: Gestió d'hàbitats | J87: Molèsties per activitats recreatives
A88: Myotis blythii | C88: Si | D88: Si | E88: 2.167 | F88: Sí | H88: Gestió d'hàbitats | I88: Treballs forestals | J88: Molèsties per activitats recreatives
A89: Myotis capaccinii | C89: Si | D89: Si | E89: 1.833 | F89: Sí | H89: Gestió de l'aigua | I89: Molèsties per activitats recreatives | J89: Gestió d'hàbitats
A90: Myotis daubentonii | D90: Si | E90: 2.167 | F90: Sí | H90: Gestió de l'aigua | I90: Treballs forestals | J90: Urbanització residencial
A91: Myotis emarginatus | C91: Si | D91: Si | E91: 2.167 | F91: Sí | H91: Treballs forestals | I91: Urbanització residencial | J91: Molèsties per activitats recreatives
A92: Myotis myotis | D92: Si | E92: 1.667 | F92: Sí | H92: Treballs forestals | I92: Urbanització residencial | J92: Molèsties per activitats recreatives
A93: Neophron percnopterus | C93: Si | F93: Sí | H93: Desaparició d'activitats tradicionals | I93: Molèsties per activitats recreatives
A94: Nyctalus lasiopterus | D94: Si | E94: 2.167 | F94: Sí | H94: Treballs forestals
A95: Nyctalus leisleri | D95: Si | E95: 1.833 | F95: Sí | H95: Treballs forestals
A96: Oplismenus undulatifolius | B96: Si | F96: No | G96: No s'observa una amenaça greu
A97: Otus scops | C97: Si | D97: Si | E97: 2 | F97: No | G97: No s'observa una amenaça greu
A98: Oxygastra curtisii | C98: Si | D98: Si | E98: 2.333 | F98: Sí | H98: Gestió de l'aigua | I98: Treballs forestals
A99: Passer montanus | D99: Si | E99: 2 | F99: No | G99: No s'observa una amenaça greu
A100: Periparus ater all others | C100: Si | F100: No | G100: No s'observa una amenaça greu
A101: Phalacrocorax carbo sinensis | C101: Si | F101: No | G101: No s'observa una amenaça greu
A102: Pisidium subtruncatum | B102: Si | F102: No | G102: Es desconeix el seu estatus en el Parc
...

Sheet PLA_v2025
A1: MODEL DE PLA ESTRATÈGIC PELS ENP
B2: Espai natural protegit: | C2: Zona Volcànica de la Garrotxa
P3: Exemples d'accions | U3: Fita a assolir en 4 anys | X3: Gestió interna | AA3: Gestió externa (AG) | AD3: Calendarització interna (AG)
A4: EIXOS | C4: Objectius generals (PP) | E4: Objectius estratègics | F4: Codi | G4: Objectius operatius | H4: Codi | I4: Comú / Específic | J4: Obligatori / Optatiu | K4: Objectius operatius PNZVG | L4: Justificació del canvi o no inclusió d'un OP | M4: Objectiu aplicable amb accions que depenen directament del PNZVG | N4: Objectiu aplicable amb accions que depenen directament de la Direcció General de PAMN | O4: Prioritat | P4: Propostes genèriques d'accions | Q4: Marc de referència | R4: Resultats derivats | S4: Proposta d'accions | T4: Indicadors | U4: Valor mínim | V4: Valor objectiu | W4: COMENTARIS LAVOLA | X4: Hores de dedicació | Y4: Àrea responsable | Z4: Persona responsable | AA4: Pressupost (€) | AB4: Contractació externa | AC4: Competència DG | AD4: Executat | AE4: 2025 | AF4: 2026 | AG4: 2027 | AH4: 2028
A5: NATURA | B5: 1 | C5: CONSERVAR LA NATURA i restaurar els ecosistemes, els processos naturals i seminaturals, la biodiversitat i la geodiversitat associada. | D5: 01.1 | E5: Adequar i fer eficient la conservació dels elements objecte de gestió prioritària marcats per la DG a l'ENP | F5: 01.1.1 | G5: Implementar i executar plans de gestió específics per a hàbitats i espècies de conservació prioritària dins l'ENP | H5: 01.1.1 | I5: Comú | J5: Obligatori | K5: Implementar i executar plans i mesures de gestió específiques per a hàbitats i espècies de conservació prioritària dins l'ENP | L5: Canvi de redactat OP. Implementació d'accions no emmarcades en un Pla de gestió específic | M5: Sí | N5: Sí | O5: MÀXIMA | P5: *Realització d'accions per a la millora dels elements prioritzats a l'espai *Elaboració de plans de gestió per elements prioritzats a l'espai | Q5: MAP | R5: SFF: Elaboració de plans de gestió específics per a espècies de conservació prioritària i directrius de gestió d'hàbitats. SFF/SENP: Definir a nivell de cluster quins son els que es poden elaborar conjuntament. | S5: 1) Elaboració o actualització de plans, protocols o estratègies de conservació per hàbitats i espècies d'interès (cranc de riu autòcton, nàiade i espècies qualificades de vulnerables al Catàleg de fauna). 2) Actuacions de restauració i millora d'hàbitats i d'espècies d'interès. 3) Treballs de millora i gestió específics pel cranc de riu. | T5: 1) Nombre de plans de gestió específics per a elements prioritaris redactats i implementats. 2) Nombre d'actuacions de restauració 3) Nombre d'exemplars reintroduits | U5: 1) 1 2) 1 3) 100 | V5: 1) 10 2) 4 3) 1000 | X5: 420 420 420 | Y5: Patrimoni Natural | Z5: Emili Bassols Joan Montserrat Bernat Perramon
F6: 01.1.2 | G6: Adaptar i executar plans de gestió específics per a elements geològics de conservació prioritària dins l'ENP | H6: 01.1.2 | I6: Comú | J6: Obligatori | K6: Actualitzar i executar programes de gestió específics per a elements geològics de conservació prioritària dins l'ENP. | L6: Atès que ja es disposa d'una Estratègia de gestió del vulcanisme que cal actualitzar (és del 2000). | M6: Sí | N6: Sí | O6: MÀXIMA | P6: * Elaboració de l'inventari d'elements geològics a l'espai *Aplicació de les directrius de gestió de l'inventari de patrimoni geològic (ICGC) | S6: 1) Asistencia tècnica a la gestió i conservació del patrimoni geològic i la geodiversitat. 2) Actualització de l'Estratègia de conservació del vulcanisme del PNZVG 3) Actuacions de manteniment i conservació d'afloraments d'interès geològic (AIG), per exemple, la cinglera de Castellfollit de la Roca. 4) Restauració d'afloraments d'interès geològic (AIG). Per exemple, tossol del Bosc de Tosca o gredera del volcà del Racó. | T6: 1) Nombre d'hores dedicades a l'assessorament tècnic. 2) Nombre d'actuacions de millora d'elements geològics prioritaris executades. 3) Nombre d'actuacions de manteniment i conservació d'elements geològics prioritaris executades. 4) Nombre d'afloraments restaurats | U6: 1) 50 2) 15 3) 1 4)1 | V6: 1) 150 2) 25 3) 7 4)4 | X6: 150 | Y6: Patrimoni Natural | Z6: Emili Bassols
D7: 01.2 | E7: Executar les mesures de gestió directa previstes en els intruments de planificació per la conservació i la gestió adaptativa dels elements clau de l'ENP | F7: 01.2.1 | G7: Implementar la metodologia de gestió adaptativa (Estàndards Oberts de Gestió Adaptativa a Catalunya) en tots els processos de l'ENP | H7: 01.2.1 | I7: Comú | J7: Obligatori | K7: =G7 -> Implementar la metodologia de gestió adaptativa (Estàndards Oberts de Gestió Adaptativa a Catalunya) en tots els processos de l'ENP | M7: Sí | N7: Sí | O7: ALTA | P7: *Definició d'un protocol per tal d'incorporar la metodologia dels Estàndards Oberts pels processos més rellevants per a la conservació a l'espai | Q7: ESNATURA | R7: SENP: Elaboració d'un manual per la implementació dels OSAM | S7: 1) Definició d'un protocol per incorporar la metodologia dels estandards oberts en els processos més rellevants de conservació de l'espai. 2) Creació d'un sistema de seguiment de les accions de gestió de l'espai. | T7: 1) Percentatge de projectes transversals que incorporen aquesta metodologia. 2) Creació del protocol | U7: 1) 25 2) 1 | V7: 1) 75 2)1 | X7: 100 | Y7: Direcció | Z7: Joan Pijoan
F8: 01.2.2 | G8: Executar les mesures previstes en els plans de conservació o recuperació d'espècies amenaçades de forma coordinada amb el Servei de Flora i Fauna en l'àmbit de l'ENP | H8: 01.2.2 | I8: Comú | J8: Obligatori | K8: =G8 -> Executar les mesures previstes en els plans de conservació o recuperació d'espècies amenaçades de forma coordinada amb el Servei de Flora i Fauna en l'àmbit de l'ENP | M8: Sí | N8: Sí | O8: MÀXIMA | P8: * Implicació i participació en la redacció dels plans de conservació /recuperació d'espècies amenaçades * Execució de les accions dins els plans que pertoquin a cada espai (incorporar totes les mesures que surten als plans ja aprovats que tenen incidència a l'espai) * Col.laboració en l'obtenció de la informació necessària dins els espais per al desenvolupament dels Plans | Q8: MAP Catàlegs | R8: SFF: Elaboració de plans de conservació o recuperació d'espècies protegides | S8: 1) Assistència tècnica en la gestió i conservació de la flora i la vegetació. 2) Col·laboració amb el SFF en l'elaboració de plans de conservació o recuperació d'espècies de fauna i flora. 3) Proporcionar la informació disponible en l'espai en relació a les espècies de les quals s'estigui redactant el pla de conservació o recuperació. 4) Execució de les mesures previstes en els plans de conservació o recuperació aplicables al nostre espai. 5) Obtenció d'informació sobre l'estatus de conservació d'espècies que, en funció de l'evolució de les seves poblacions, podrien ser susceptibles disposar d'un pla de conservació o recuperació en un futur. 6) Treballs de conservació "ex-situ" de flora protegida /amenaçada. 7) Adaptació d'un parell de canals de rescloses Fluvià com a hàbitats aptes a la reproducció de nàiades. 8) Assistència tècnica en la gestió de la fauna | T8: 1) Nombre de plans de conservació o recuperació amb els quals s'ha col·laborat des de l'espai. 2) Nombre de projectes treballats conjutament 3) Informació proporcionada 4) Nombre de mesures 5) Nombre de tàxons els quals obtens informació del seu estat de conservació 6) Nombre de tàxons els quals fas treballs de conservació 7) Nombre de canals o rescloses adaptades 8) Nombre de consultes realitzades | U8: 1) 2 2) 1 3) 1 4) 1 5) 1 6) 1 7) 1 8) 1 | V8: 1) 4 2) 4 3) 10 4) 5 5) 10 6) 10 7) 2 8) 50 | X8: 320 | Y8: Patrimoni Natural | Z8: Emili Bassols
F9: 01.2.3 | G9: Executar les mesures de gestió previstes en els plans de control i erradicació d'espècies exòtiques de forma coordinada amb el Servei de Flora i Fauna en l'àmbit de l'ENP | H9: 01.2.3 | I9: Comú | J9: Obligatori | K9: Rebaixar l'impacte de les espècies exòtiques invasores mitjançant l'execució de les mesures de gestió previstes en els plans de control i erradicació d'espècies exòtiques de forma coordinada amb el Servei de Flora i Fauna en l'àmbit de l'ENP i elaborant documents informatius sobre maneig d'espais d'interès. | L9: Es considera que l'actuació sobre les EEI requereix d'un esforç de gestió més ampli que el simple compliment d'allò que puguin proposar els plans de control i eradicació del SFF. | M9: Sí | N9: Sí | O9: MÀXIMA | P9: * Implicació i participació en la redacció (cal identificar els plans que estan ja en marxa o previstos i posar les mesures concretes) * Execució de les accions dins els plans que pertoquin a cada espai * Col.laboració en l'obtenció de la informació necessària dins els espais per al desenvolupament dels Plans | Q9: ESNATURA MAP | R9: SFF: Elaboració de plans de control i erradicació d'espècies exòtiques | S9: 1) Obtenció d'informació sobre l'evolució de les poblacions d'espècies exòtiques presents a l'espai que podrien ser susceptibles de disposar d'un pla de control i eradicació. 2) Executar accions preventives de control i eradicació d'espècies exòtiques invasores. 3) Elaborar manuals de gestió per evitar la proliferació d'espècies exòtiques invasores en hàbitats d'interès. 4) Col·laboració amb el SFF en l'elaboració de plans de control i eradicació d'espècies exòtiques de fauna i flora. 5) Proporcionar la informació disponible en l'espai en relació a les espècies exòtiques de les quals s'estigui redactant un pla de control i eradicació. 6) Execució de les mesures previstes en els plans de control i eradiació aplicables al nostre espai. | T9: 1) Nombre d'espècies exòtiques invasores de les quals es recull informació de les seves poblacions. 2) Nombre d'accions preventives de control i eradicació. 3) Nombre d'espècies que disposen d'un manual de gestió. 4) Nombre de plans en els quals es col·labora. 5) Nombre d'espècies de les quals es proporciona informació. 6) Nombre d'accions executades. | U9: 1) 1 2) 1 3) 2 4) 1 5) 1 6) 1 | V9: 1) 10 2) 4 3) 5 4) 4 5) 4 6) 4 | X9: 160 | Y9: Patrimoni Natural | Z9: Emili Bassols
F10: 01.2.4 | G10: Desplegar els objectius i tasques recollits en els instruments de referència i compromisos internacionals | H10: 01.2.4 | I10: Específic | J10: Optatiu | K10: =G10 -> Desplegar els objectius i tasques recollits en els instruments de referència i compromisos internacionals | M10: Sí | N10: Sí | O10: MITJANA | P10: * Desplegament dels objectius recollits en l'Estratègia de la Xarxa d'àrees marines protegides del Mediterrani (MedPAN network) * Col·laboració en el compliment dels objectius i tasques derivats de la Mediterranean Climate Action Partnership en matèria de biodiversitat i canvi climàtic i els seus impactes sobre la sequera, calor i incendis * Col·laboració en la implementació pràctica de projectes de l'àrea internacional i dels compromisos amb les entitats membres UICN, Euroregió Pirineus Mediterrània | S10: 1) Participació en projectes d'abast internacional. Per exemple, live ECOAdapt50, FloraLab + POCTEFA. | T10: 1) Nombre de projectes en els que es participa. | U10: 1) 1 | V10: 2) 4 | W10: A columna M marcar que "Si" que té mesures aplicables que depenen del PN. Com a criteri general, encara que sigui participació, si s'incorporen accions/mesures posar que sí a la columna | X10: 160 | Y10: Patrimoni Natural | Z10: Bernat Perramon
D11: 01.3 | E11: Crear ecosistemes complexes, resilients, i d'alta biodiversitat per garantir la recuperació dels processos ecosistèmics | F11: 01.3.1 | G11: Identificar espais pel foment de la dinàmica natural i l'aprofitament no extractiu | H11: 01.3.1 | I11: Comú | J11: Obligatori | K11: =G11 -> Identificar espais pel foment de la dinàmica natural i l'aprofitament no extractiu | M11: Sí | N11: No | O11: MÀXIMA | P11: *Participar en la identificació d'espais pel foment de la dinàmica natural i l'aprofitament no extractiu dins l'ENP en base a uns criteris metodològics predefinits *Afavorir la creació d'hàbitats per a la conservació d'espècies | Q11: ESNATURA | R11: SENP/SFF: Definir criteris metodològics | S11: 1) Elaborar un catàleg d'espais potencials per a ser gestionats en dinàmica natural. | T11: 1) Increment de superfície d'espais gestionats en dinàmica natural. | U11: 1) 1 | V11: 1) 100 | X11: 145 | Y11: Patrimoni Natural | Z11: Joan Montserrat
F12: 01.3.2 | G12: Afavorir la maduresa dels sistemes forestals | H12: 01.3.2 | I12: Específic | J12: Optatiu | K12: =G12 -> Afavorir la maduresa dels sistemes forestals | M12: Sí | N12: Sí | O12: MÀXIMA | P12: *Participar i impulsar la planificació i execució d'accions d'acceleració de la maduresa forestal en zones boscoses dins l'ENP en base als criteris metodològics predefinits | Q12: MAP | R12: SENP/SFF: Definir criteris metodològics | S12: 1) Participar i impulsar la planificació i execució d'accions d'accelaració de la maduresa forestal en zones boscoses dins l'espai natural protegit prioritzant reserves naturals en base a criteris metodològics definits (prioritzar reserves naturals, zones definides pel PEZVG com a protecció de vesants. 2)Diagnosi i pla de custódia i preservació dels boscos d'alt valor ecològic anb prioritat als bosos mdurs del PNZVG | T12: 1) Nombre d'execucions destinades a millorar el grau de maduresa de la massa forestal. 2) Percentatge d'hectàrees potencials a projectes de custòdia. | U12: 1) 1 2) 0 | V12: 1) 5 2)33 | X12: 120 | Y12: Patrimoni Natural Direcció | Z12: Joan Montserrat Joan Pijoan
F13: 01.3.3 | G13: Generar pertorbacions controlades | H13: 01.3.3 | I13: Específic | J13: Optatiu | K13: No aplica | P13: *Elaboració d'una planificació d'actuacions de simulació d'incendis forestals naturals (cremes controlades) dins l'espai en base als criteris metodològics predefinits. *Realització dels estudis necessaris i participació en la reintroducció de grans herbívors, carnívors o carronyaires dins l'ENP en base als criteris metodològics predefinits. | Q13: MAP | R13: SENP/SFF: Definir criteris metodològics | S13: JOAN MONTSERRAT | T13: 1) Informe de les modificacions forestals executades | W13: Pendent definir mesures i valor indicadors. | Y13: Patrimoni Natural | Z13: Joan Montserrat
F14: 01.3.4 | G14: Restaurar la dinàmica natural dels rius | H14: 01.3.4 | I14: Específic | J14: Optatiu | K14: Restaurar i conservar la dinàmica i estructura natural dels rius, les zones humides, i altres hàbitats d'aigua dolça | L14: Canvi de redactat OP. Adaptar el redactat per a tot tipus de masses d'aigua | M14: Sí | P14: *Realització i impuls de la renaturalització de lleres i creació de zones de laminació dins l'ENP en base als criteris metodològics predefinits | Q14: MAP | R14: SENP/SFF: Definir criteris metodològics | S14: 1) Eliminació de rescloses en desús i permeabilitzar les altres per recuperar la qualitat dels sistemes fluvials. 2) Elaboració d'un catàleg de punts d'aigua en l'àmbit del Parc Natural. 3) Execució de les actuacions de recuperació de punts d'aigua per afavorir la biodiversitat previstes en el catàleg. 4) Elaborar un document de proposta per a promoure la incorporació de les zones humides d'interès del Parc Natural en l'Inventari de Zones Humides de Catalunya. Mulladius de Verlets. 5) Elaborar un document de proposta per a Incloure les fonts, les basses i les zones humides del Parc Natural com a elements naturals a protegir en els documents de planificació municipal (POUM i altres). | T14: 1) Nombre de rescloses eliminades 2) Redacció del catàleg 3) Nombre d'actuacions executades 4) Redacció del document 5) Elaborar un document de proposta | U14: 1) 1 2) 1 3) 1 4) 1 5) 1 | V14: 1) 2 2) 1 3) 5 4) 1 5) 1 | W14: Mancaria marcar que "SI" que té mesures aplicables que depenen del PN a columna M. Si volguessiu afegir un indicador més relacionat amb 1) i lligat al compliment de l'objectiu, es podria incorporar "km de riu en dinàmica natural o seminatural" | X14: 380 | Y14: Patrimoni Natural | Z14: Emili Bassols
F15: 01.3.5 | G15: Fomentar el paisatge en mosaïc | H15: 01.3.5 | I15: Específic | J15: Optatiu | K15: =G15 -> Fomentar el paisatge en mosaïc | M15: Sí | O15: MÀXIMA | P15: *Realització d'accions per gestionar l'herbivoria domèstica associada a la ramaderia extensiva *Aplicació dels criteris metodològics predefinits en un manual tècnic de bones pràctiques en ramaderia extensiva i recuperació i manteniment de pastures aplicat a l'ENP. *Coordinació i gestió dels ramats locals en actuacions de restauració de pastures i desembosc. | Q15: ESNATURA | R15: SENP/SFF: Definir criteris metodològics | S15: 1) Identificació cartogràfica dels espais oberts prioritaris. 2) Recuperació d'espais oberts. 3) Mantenir espais d'interès prioritaris i els prats d'interès biológic acord amb el PEZVG 4) Seguiment prats 5) Foment de la ramederia extensiva per a mantenir espais oberts | T15: 1) Nombre d'actuacions executades 2) Relació entre espais oberts i espais forestals / matollars / marges recuperats. Nombre Ha. 3) Nombre d'hectàres 4) Percentatge de prats en bon estat de conservació / Evolució de l'estat de conservació dels prats. 5) Nombre d'accions | U15: 1) 1 2) 5 3) 5 4) 10 5) 1 | V15: 1) 6 2)15 3) 10 4) 25 5) 10 | W15: Mancaria marcar que "SI" que té mesures aplicables que depenen del PN a columna M | X15: 280 | Y15: Patrimoni Natural | Z15: Bernat Perramon
F16: 01.3.6 | G16: Gestionar i intervenir en la dinàmica de poblacions de fauna que no tenen depredador natural | H16: 01.3.6 | I16: Específic | J16: Optatiu | K16: =G16 -> Gestionar i intervenir en la dinàmica de poblacions de fauna que no tenen depredador natural | M16: Sí | N16: Sí | O16: ALTA | P16: *Realització d'acords amb societats de caçadors. *Participació i impuls del control directe de poblacions de fauna en base als criteris metodològics predefinits. | R16: SENP/SFF: Definir criteris metodològics | S16: 1) Participació en el Programa de seguiment de les poblacions de senglar a Catalunya. 2) Coordinació del grup de treball amb les societats de caçadors 3) Participar a la taula entre caçadors, fessolaires i PNZVG | T16: 1) Nombre de colles participants. 2) Nombre de reunions 3) Nombre de reunions | U16: 1) 4 2) 1 3) 1 | V16: 2) 8 2) 4 3) 4 | X16: 225 | Y16: Patrimoni Natural | Z16: Emili Bassols
F17: 01.3.7 | G17: Afavorir la connectivitat ecològica del territori | H17: 01.3.7 | I17: Comú | J17: Obligatori | K17: =G17 -> Afavorir la connectivitat ecològica del territori | M17: Sí | O17: MÀXIMA | S17: 1) Adaptació d'infraestructures viàries per afavorir la connectivitat. 2) Aplicar mesures per minimitzar l'impacte d'ocupació del sòl, concretades en informes preceptius emesos pel Parc Natural, en l'àrea d'influència per a connectivitat definida en el Pla Especial. 3) Connectar hàbitats naturals de superfície reduïda. 4) Millorar la connectivitat en ambients fluvials i zones humides. 5) Adquirir o establir convenis de custòdia en espais naturals rellevants per a la connectivitat ecològica, i impulsar-hi actuacions que l’afavoreixin | T17: 1) Nombre de mesures executades de millora de la connectivitat. 2) Nombre d'informes preceptius emesos en els quals s'incorporen mesures de millora de la connectivitat. 3,4 i 5) Superfície (ha) recuperada per a la connectivitat. | U17: 1) 1 2) 1 3,4) 2 | V17: 1) 4 2) 8 3,4) 10 | W17: Mancaria marcar que "SI" que té mesures aplicables que depenen del PN a columna M | X17: 225 150 150 225 | Y17: Patrimoni Natural | Z17: Emili Bassols Joan Montserrat Bernat Perramon Joan Pijoan
D18: 01.4 | E18: Alinear l'activitat de propietaris i gestors del territori amb la conservació, millora i restauració dels valors de l'ENP | F18: 01.4.1 | G18: Fomentar acords de custòdia en espais d'alt valor dins l'ENP per a la gestió dels elements prioritaris | H18: 01.4.1 | I18: Comú | J18: Optatiu | K18: Fomentar formules de gestió (autoritzacions, convenis, acords de custòdia,...) en espais d'alt valor dins l'ENP per a la gestió dels elements prioritaris. | L18: Per ampliar les possibilitats d'incidir en la gestió de finques privades des del Parc Natural. | M18: Sí | O18: MÀXIMA | P18: *Realització d'acords de custòdia aplicant el model d'acord elaborat per Serveis Centrals | Q18: MAP | R18: SENP/SENP: Dissenyar el protocol i elaborar un model d'acord | S18: 1) Identificació de les finques d'interès que convindria disposar d'algun conveni/autorització/acord amb la propietat. 2) Establiment de convenis/autoritzacions/acords amb propietaris de finques públiques o privades. | T18: 1) Redacció d'un document de porposta de convenis/autoritzacions/acords de custòdia aconseguits. 2) Nombre d'hectàrees conveniades/autoritzades/acordades | U18: 1) 1 2) 50 | V18: 1) 1 2) 200 | X18: 120 120 120 120 | Y18: Patrimoni Natural | Z18: Emili Bassols Joan Montserrat Bernat Perramon Joan Pijoan
F19: 01.4.2 | G19: Fomentar bones pràctiques entre els col·lectius de propietaris i gestors del territori | H19: 01.4.2 | I19: Comú | J19: Optatiu | K19: Fomentar bones pràctiques entre els col·lectius de propietaris i gestors del territori | M19: Sí | O19: MÀXIMA | P19: *Realització d'actuacions demostratives en finques pròpies per al foment de bones pràctiques | S19: 1) Identificar les línies de gestió prioritàries i els sectors implicats per a la promoció de bones pràctiques. 2) Creació d'un model tipus de material informatiu i de comunicació (tipus infografia) de les bones pràctiques. 3) Establiment de camps experimentals i seguiment de prats i divulgació. 4) Millora de la biodiversitat de prats de dall a partir de la sembra amb llavor recollida en prats amb elevada biodiversitat d'espècies. 5) Potenciar millores per a la integració paisatgística de les explotacions. 6) Elaboració de material divulgatiu de bones pràctiques per a la conservació de la biodiversitat en jardins i espais verds. 7) Col·laboració amb les finques col·laboradores del Centre de Conservació de Plantes Cultivades de Can Jordà. 8) Demostració de pràctiques forestals sostenibles (desembosc amb canaletes i altres). | T19: 1) Nombre de línies de gestió en les quals s'incideix. 2) Nombre d'actuacions realitzades (jornades, tríptics, manuals, càpsules,...). 3) Nombre d'accions 4) Superfície 5) Nombre d'explltacions que s'ha actuat 6) Productes elaborats 7) Nombre de finques col·laboradores 8) Nombre de demostracions | U19: 1) 1 2) 1 3) 5 4) 5 5) 4 6) 2 7) 5 8) 2 | V19: 1) 8 2) 4 3) 10 4) 15 5) 10 6) 8 79 8) 6 | W19: Mancaria marcar que "SI" que té mesures aplicables que depenen del PN a columna M | X19: 135 135 135 135 | Y19: Patrimoni Natural | Z19: Emili Bassols Joan Montserrat Bernat Perramon Joan Pijoan
F20: 01.4.3 | G20: Impulsar la coordinació amb els ens locals en la gestió finques públiques situades dins d’ENP | H20: 01.4.3 | I20: Específic | J20: Optatiu | K20: =G20 -> Impulsar la coordinació amb els ens locals en la gestió finques públiques situades dins d’ENP | M20: Sí | O20: MÀXIMA | P20: *Boscos comunals *Medi marí *Lleres i boscos de ribera | Q20: ESNATURA | S20: 1) Coordinació amb ens locals per a la compra de finques d'interès per la conservació. 2) Col·laboració amb els ens locals per a la gestió de les finques públiques. 3) Establir / renovar els convenis de Can Jordà i el volcà de Santa Margarida amb al Diputació de Girona 4) Singar acords de col·laboració amb els ens locals 5) Instar a l’Agència Catalana de l’Aigua l’atermenament del domini públic hidràulic en l’àmbit del Parc natural i de la seva zona d’influència hidràulica del riu Fluvià, el riu Brugent, el riu Ser, la riera de Ridaura, la riera de Bianya i el torrent de Sant Martí (com a mínim) | T20: 1) Nombre de finques adquirides. 2) Nombre de finques en les quals es col·labora. 3) Nombre convenis acordats 4) Nombre acords 5) Nombre d'atermanament | U20: 1) 1 2) 1 3) 1 4) 1 5) 1 | V20: 1) 2 2) 2 3) 4 4) 2 5) 4 | W20: Mancaria marcar que "SI" que té mesures aplicables que depenen del PN a columna M | X20: 262 | Y20: Direcció | Z20: Joan PIjoan
B21: 2 | C21: ADAPTAR ELS ECOSISTEMES AL CANVI CLIMÀTIC i millorar-ne la resiliència en front dels riscos associats. | D21: 02.1 | E21: Planificar l'adaptació dels sistemes naturals al canvi climàtic | F21: 02.1.1 | G21: Adaptar i implementar el Pla d'adaptació de l'ENP al canvi climàtic | H21: 02.1.1 | I21: Comú | J21: Obligatori | K21: =G21 -> Adaptar i implementar el Pla d'adaptació de l'ENP al canvi climàtic | M21: Sí | O21: ALTA | P21: *Planificació del sistema d'espais oberts *Creació de zones de laminació per defensa de inundacions *Creació i manteniment d'espais dunars de protecció de temporals | R21: OCCC/SENP: Elaboració del model de Pla d'adaptació dels ENP al canvi climàtic | S21: 1) Foment dels prats permanents com a sistemes d'adaptació al canvi climàtic en el sector ramader extensiu. 2) Foment del maneig regeneratiu en la ramaderia extensiva. 3) Implementació d'accions de mitigació i adaptació al canvi climàtic previst per les empreses i equipaments acreditades per la CETS. | T21: 1,2,3) Nombre d'actuacions | U21: 1) 1 2) 1 3) 1 | V21: 1) 5 2) 1 3) 10 | W21: Mancaria marcar que "SI" que té mesures aplicables que depenen del PN a columna M | X21: 105 75 | Y21: Patrimoni Natural Ús públic i turisme | Z21: Bernat Perramon Arnau Dorca
F22: 02.1.2 | G22: Gestionar i planificar els recursos hídrics de l'ENP | H22: 02.1.2 | I22: Comú | J22: Obligatori | K22: =G22 -> Gestionar i planificar els recursos hídrics de l'ENP | M22: Sí | O22: MÀXIMA | S22: 1) Assistència tècnica a la gestió de les aigües. 2) Establiment i/o ampliació d'una xarxa de punts de control (aqüífer, aigües superficials i surgències naturals). 3) Fomentar el càlcul de la petjada hídrica de les empreses del Parc Natural altament consumidores d'aigua. | T22: 1) Nombre d'hores d'assessorament tècnic. 2) Nombre de punts de control 2) Nombre d'empreses contactades pel càlcul de la petjada hídrica. | U22: 1) 25 2) 2 3) 5 | V22: 1) 75 2) 5 3)15 | W22: Mancaria marcar que "SI" que té mesures aplicables que depenen del PN a columna M | X22: 150 145 | Y22: Patrimoni Natural Ús públic i turisme | Z22: Emili Bassols Arnau Dorca
F23: 02.1.3 | G23: Participar en la redacció i execució dels instruments d'ordenació forestal sostenible i per la conservació en finques públiques | H23: 02.1.3 | I23: Específic | J23: Optatiu | K23: Promoure la redacció d'instruments d'ordenació forestal sostenible i l'execució d'accions per la conservació i millora dels boscos i els elements d'interès | L23: Canvi de redactat OP. Inclusió d'accions forestals per a la millora de la biodiversitat sense detallar la propietat de la finca | M23: Sí | N23: Sí | O23: ALTA | P23: *Participació en la redacció d'IOF de finques públiques *Realització d'accions demostratives en finca pública o amb acord de custòdia *Realització de tractaments silvícoles i tallades selectives *Promoció de boscos mixtes i de la biodiversitat | R23: DGEFMN: Redacció d'IOF en finques públiques | S23: 1) Treballar en la gestió forestal de les finques públiques del Catàleg d'utilitat pública. 2) Promoure els PTGMF de totes les finques públiques | T23: 1) Percentatge de finques 2) Percentatge de PTGMF | U23: 1) 10% 2) 10% | V23: 1) 80% 2)80% | X23: 680 | Y23: Patrimoni Natural | Z23: Joan Montserrat
F24: 02.1.4 | G24: Promoure la redacció d'instruments d'ordenació forestal per reduir la sensibilitat i vulnerabilitat dels boscos al canvi climàtic en finques privades | H24: 02.1.4 | I24: Específic | J24: Optatiu | K24: =G24 -> Promoure la redacció d'instruments d'ordenació forestal per reduir la sensibilitat i vulnerabilitat dels boscos al canvi climàtic en finques privades | M24: Sí | N24: Sí | P24: * Realització d'accions per donar a conèixer subvencions entre propietaris | S24: 1) Incrementar el nombre de Plans de Gestió i Ordenació Forestal. 2) Elaborar un catàleg de possibles finques protectores (PEZVG) | T24: 1) Percentatge de superfície forestal amb IOF redactat actualment 60% 2) Elaboració catàleg | U24: 1) 60% 2) 1 | V24: 1) 70% 2) 1 | X24: 595 | Y24: Patrimoni Natural | Z24: Joan Montserrat
D25: 02.2 | E25: Planificar la prevenció i extinció d’incendis forestals i la gestió del foc de forma coordinada amb els diferents agents del territori | F25: 02.2.1 | G25: Redactar i implementar el Pla de Prevenció d'Incendis Forestals | H25: 02.2.1 | I25: Comú | J25: Obligatori | K25: Implementar el Pla de Prevenció d'Incendis Forestals | L25: Es treu la paraula redactar perquè el Parc ja disposa de PPI | M25: Sí | N25: Sí | O25: ALTA | P25: *Elaboració del Pla de Prevenció d'Incendis *Definició de: xarxa estratègica i complementària de vials forestals, xarxa estratègica i complementària de punts d’aigua, tractaments de vegetació, punts estratègics de gestió | Q25: ESNATURA | R25: Equip de PPI: Disseny del protocol de treball | S25: 1) Participar i implementar les mesures del PPI | T25: 1) Nombre de mesures que s'ha participat o implementat | U25: 1) 1 | V25: 1) 5 | Y25: Patrimoni Natural | Z25: Joan Montserrat
F26: 02.2.2 | G26: Definir i planificar la gestió del foc per a la millora de l'ENP | H26: 02.2.2 | I26: Específic | J26: Optatiu | K26: =G26 -> Definir i planificar la gestió del foc per a la millora de l'ENP | L26: No aplicable | M26: No | N26: No | P26: *Pla de gestió de foc *Pla de gestió de cremes | R26: SPEN: Elaboració d'un model de pla de gestió
F27: 02.2.3 | G27: Treballar per a la prevenció d'incendis juntament amb els propietaris, ajuntaments, protecció civil, ADF i bombers. | H27: 02.2.3 | I27: Comú | J27: Obligatori | K27: =G27 -> Treballar per a la prevenció d'incendis juntament amb els propietaris, ajuntaments, protecció civil, ADF i bombers. | M27: Sí | N27: No | O27: ALTA | S27: 1) Seguiment de tots els informes forestals 2) Comptar amb un suport pel seguiment dels informes forestals | T27: 1) Percentatge d'informes forestals emesos 2) Hores destinades al seguiment | U27: 1) 1 2) 20 | V27: 1) 100% 2) 50 | X27: 690 | Y27: Patrimoni Natural | Z27: Joan Montserrat
B28: 3 | C28: PROTEGIR LA BIODIVERSITAT, i especialment els elements fràgils i amenaçats, d’interès comunitari o de major interès natural. | D28: 03.1 | E28: Prevenir, minimitzar i compensar els impactes ambientals dels usos i activitats que es desenvolupin en l'àmbit de l'ENP | F28: 03.1.1 | G28: Participar en les consultes dels procesos d'Avaluació Ambiental que afectin directament o indirectament l’espai del ENP | H28: 03.1.1 | I28: Comú | J28: Obligatori | K28: =G28 -> Participar en les consultes dels procesos d'Avaluació Ambiental que afectin directament o indirectament l’espai del ENP | M28: Sí | S28: 1) Redacció d'informes preceptius. 2) Redacció d'informes sol·licitats pels SSTT dins el tràmit d'avaluació ambiental | T28: 1) Percentatge d'informes emesos 2) Percentatge d'informes emesos | U28: 1) 100% 2) 100% | V28: 1) 100% 2) 100% | W28: Mancaria marcar que "SI" que té mesures aplicables que depenen del PN a columna M. Motiu pel qual està en vermell? | X28: 480 125 90 300 | Y28: Patrimoni Natural | Z28: Emili Bassols Joan Montserrat Bernat Perramon Joan Pijoan
F29: 03.1.2 | G29: Exercir un seguiment efectiu de les obres al Parc juntament amb les Oficines Territorials d'Acció i Avaluació Ambiental als efectes d'assegurar la correcta translació de la tutela administrativa. | H29: 03.1.2 | I29: Comú | J29: Obligatori | K29: =G29 -> Exercir un seguiment efectiu de les obres al Parc juntament amb les Oficines Territorials d'Acció i Avaluació Ambiental als efectes d'assegurar la correcta translació de la tutela administrativa. | M29: Sí | S29: 1) Seguiment de les obres amb més impacte sobre el paisatge i el medi natural | T29: 1) Percentatge de seguiments | U29: 1) 80 % | V29: 1) 100% | W29: Mancaria marcar que "SI" que té mesures aplicables que depenen del PN a columna M. Motiu pel qual està en vermell? | X29: 300 | Y29: Direccio | Z29: Joan PIjoan
F30: 03.1.3 | G30: Participar en la compensació d'impactes residuals durant els processos d'avaluació ambiental mitjançant la identificació de necessitats d'actuació prioritària dins i fora dels límits de l’ENP | H30: 03.1.3 | I30: Comú | J30: Optatiu | K30: Correcció i compensació d'impactes residuals mitjançant la identificació de necessitats d'actuació prioritària dins i fora dels límits de l’ENP | L30: Canvi de redactat OP. Correcció i compensació també fora de processos d'avaluació ambiental | M30: Sí | P30: *Catàleg de possibles actuacions compensatories *Catàleg de sectors amb necessitats d'intervenció (incloent també zones fora dels límits de l'ENP que es considerin importants per al manteniment de la connectivitat ecològica dels espais) | S30: 1) Establiment de mesures compensatòries en aquells projectes, plans o programes que ho requereixin, orientades a restaurar impactes o reduir amenaces | T30: 1) Nombre de mesures compensatòries. | U30: !) 1 | V30: 1) 10 | W30: Mancaria marcar que "SI" que té mesures aplicables que depenen del PN a columna M. Motiu pel qual està en vermell? | X30: 50 | Y30: Direccio | Z30: Joan PIjoan
D31: 03.2 | E31: Garantir el compliment dels objectius de conservació dotant l'ENP de la planificació adequada segons estableix la normativa vigent (Pla de Protecció, PRUG, plans específics...) | F31: 03.2.1 | G31: Participar en l'elaboració dels instruments de planificació de l'ENP | H31: 03.2.1 | I31: Comú | J31: Obligatori | K31: Impulsar i participar en l'elaboració dels instruments de planificació de l'ENP | L31: Hi ha plans que són específics i d'interès del propi parc. | M31: Sí | O31: MÀXIMA | P31: *Participació en l'elaboració del Pla de Protecció (PP) juntament amb l'SPEN. *Participació en l'elaboració del Pla Rector d'usos i Gestió (PRUG) juntament amb l'SPEN. *Participació en l'elaboració d'altres instruments de planificació juntament amb l'SPEN. | R31: SPEN: Elaboració del Pla rector d'usos i gestió. SPEN: Elaboració del Pla rector d'usos i gestió | S31: 1) Treballar per la redacció del PRUG. 2) Redacció del Pla Especial del Bosc de Tosca. 3) Participació en la redacció del Pla d'Ús Públic de la comarca de la Garrotxa. 4) Redacció del Pla Estratègic d'Educació Ambiental. 5) Redacció del Pla per a la millora de la fertilització agraria. | T31: 1) Nombre de plans. | U31: 1) 3 | V31: 1) 6 | W31: Mancaria marcar que "SI" que té mesures aplicables que depenen del PN a columna M. Falta indicar la prioritat. | X31: 800 | Y31: Direccio | Z31: Joan PIjoan
D32: 03.3 | E32: Vetllar pel manteniment dels cabals ecològics i la bona qualitat dels cursos fluvials de l'ENP de forma coordinada amb l'administració competent | F32: 03.3.1 | G32: Vetllar pel manteniment del cabal ecològic dels rius definit al Pla sectorial corresponent | H32: 03.3.1 | I32: Específic | J32: Optatiu | K32: =G32 -> Vetllar pel manteniment del cabal ecològic dels rius definit al Pla sectorial corresponent | M32: Sí | O32: MÀXIMA | P32: *Participació en el seguiment del cabal en els trams dins ENP *Impuls del control per incompliment de la normativa i el seu trasllat cap a l'administració competent *Participació en les negociacions sectorials amb incidència a l'espai *Participació en les comissions de desembassament | Q32: ESNATURA | R32: ACA/CHE: Determinar els cabals ecològics en espais naturals protegits | S32: 1) Incidir en l'organisme competent (ACA) per poder disposar de major nombre de punts de control del cabal. 2) Establir un programa de vigilància dels punts de captació d'aigües superficials. | T32: 1) Nombre d'estacions d'aforament construides. 2) Percentatge d'expedients tramitats. 3) Redacció d'un programa | U32: 1) 1 2) 100% 3) 1 | V32: 1) 4 2) 100% 3) 1 | W32: Mancaria marcar que "SI" que té mesures aplicables que depenen del PN a columna M. | X32: 250 | Y32: Patrimoni Natural | Z32: Emili Basols
F33: 03.3.2 | G33: Vetllar per la regulació dels dragatges, canalitzacions o implantació d'activitats extractives que puguin modificar la llera i el cabal dels rius | H33: 03.3.2 | I33: Específic | J33: Optatiu | K33: =G33 -> Vetllar per la regulació dels dragatges, canalitzacions o implantació d'activitats extractives que puguin modificar la llera i el cabal dels rius | M33: Sí | O33: ALTA | S33: 1) Coordinació amb l'organisme competent (ACA). | T33: 1) Nombre de casos gestionats. | U33: 1) 1 | V33: 1) 10 | W33: Mancaria marcar que "SI" que té mesures aplicables que depenen del PN a columna M. Falta indicar la prioritat. | X33: 100 | Y33: Patrimoni Natural | Z33: Emili Basols
F34: 03.3.3 | G34: Avaluar i controlar les actuacions que produeixin drenatges, captacions o que puguin impedir l’arribada d’aigua tant superficial com freàtica | H34: 03.3.3 | I34: Específic | J34: Optatiu | K34: Avaluar i controlar les actuacions que produeixin drenatges, captacions o que puguin impedir l’arribada d’aigua, tant superficial com freàtica, i incidir en la millora de la qualitat de les aigües, subterrànies i superficials. | L34: S'ha modificat l'objectiu per encabir aspectes de qualitat. | M34: Sí | O34: MÀXIMA | P34: *Participació, de forma coordinada amb l'administració competent, en l'avaluació i control d'actuacions dins els límits de l'ENP. *Impuls del control per incompliment de la normativa i el seu trasllat cap a l'administració competent *Participació en les comunitats d'usuaris de les conques | S34: 1) Elaboració d'un estudi de caracterització hidrogeològica i hidrogràfica dels paratges de la Moixina, les Tries-Noc d’en Cols i els Verlets 2) Aplicació de les mesures específiques de conservació de la Reserva Natural Subterrània de la Deu Grossa i els estanys d'en Broc. 3) Seguiment de la qualitat de les aigües subterrànies i superficials de la conca dels Arcs (Santa Pau). | T34: 1) Redacció d'un estudi 2) Nombre d'actuacions identificades / avaluades. 3) Mitjana de concentració de nitrats dels punts seguits (subterranis i superficials). | U34: 1) 1 2) 2 3) X | V34: 1)1 2) 10 3) x | W34: Mancaria marcar que "SI" que té mesures aplicables que depenen del PN a columna M. | X34: 180 | Y34: Patrimoni Natural | Z34: Emili Basols
F35: 03.3.4 | G35: Vetllar pel compliment de la normativa de depuració dels efluents agroramaders, urbans i industrials que s'aboquen als cursos fluvials | H35: 03.3.4 | I35: Específic | J35: Optatiu | K35: =G35 -> Vetllar pel compliment de la normativa de depuració dels efluents agroramaders, urbans i industrials que s'aboquen als cursos fluvials | M35: Sí | O35: MÀXIMA | P35: *Impuls del control per incompliment de la normativa i el seu trasllat cap a l'administració competent | S35: 1) Establir un programa de vigilància d'efluents i punts d'abocament a llera. 2) Analítiques d'autocontrol del punt d'abocament de can Jordà. | T35: 1) Nombre de mesures executades destinades al compliment de la normativa 2) Nombre d'analítiques | U35: 1) 4 1) 10 | V35: 1) 10 2) 30 | W35: Mancaria marcar que "SI" que té mesures aplicables que depenen del PN a columna M. | X35: 225 | Y35: Patrimoni Natural | Z35: Emili Basols
F36: 03.3.5 | G36: Colaborar amb l'òrgan competent per la conservació del domini públic d'acord amb les delimitacions i la normativa d'usos vigent | H36: 03.3.5 | I36: Comú | J36: Optatiu | K36: Col·laborar amb l'òrgan competent per la conservació del domini públic hidràulic d'acord amb les delimitacions i la normativa d'usos vigent | L36: Es concreta en el DPH. | M36: Sí | O36: ALTA | S36: 1) Fer un seguiment periòdic en el marc del programa de vigilància del Parc Natural i coordinació amb els inspectors de l'ACA | T36: 1) Nombre d'expedients oberts. | U36: 1) 0 | V36: 1) 10 | W36: Mancaria marcar que "SI" que té mesures aplicables que depenen del PN a columna M. | X36: 75 | Y36: Patrimoni Natural | Z36: Emili Basols
D37: 03.4 | E37: Incrementar el patrimoni públic destinat a la conservació i millora del patrimoni natural | F37: 03.4.1 | G37: Identificar espais prioritaris per a la compra de terrenys de més valor dins l'ENP | H37: 03.4.1 | J37: Optatiu | K37: =G37 -> Identificar espais prioritaris per a la compra de terrenys de més valor dins l'ENP | M37: Sí | O37: MÀXIMA | P37: *Participació en la identificació de finques prioritàries en base als criteris indicats | R37: SENP/SPEN: Facilitar els criteris a seguir | S37: 1) Elaboració d'un catàleg de finques d'interès prioritari per la seva compra. 2) Suport a les diferents administrcions per l'adquisició de finques ( ajuts, etc) 3) Compra de la reserva natural del volcà de la Garrinada (DTER) i posterior cessió ús i gestió al PNZVG | T37: 1) Superfície de finques prioritaries adquirides 2) Nombre de reunions 3) Acord cessió ús i gestió volcà de la Garrinada | U37: 1) 10 ha. 2) 4 3) 1 | V37: 1) 200 ha 2) 8 3) 1 | W37: Mancaria marcar que "SI" que té mesures aplicables que depenen del PN a columna M. | X37: 200 | Y37: Direcció | Z37: Joan PIjoan
F38: 03.4.2 | G38: Identificar espais prioritaris per a la gestió directa | H38: 03.4.2 | I38: Comú | J38: Optatiu | K38: =G38 -> Identificar espais prioritaris per a la gestió directa | M38: Sí | P38: *Participació en la identificació de finques prioritàries en base als criteris indicats *Participació i foment de la compra o adquisició de drets d’aprofitament | R38: SENP/SPEN: Facilitar els criteris a seguir | S38: 1) Elaboració d'un catàleg de finques d'interès de gestió directa. 2) Establir acords / autortizacions amb propietaris | T38: 1) Superfície identificada per la gestió directa 2) Nombre acords / autoirtzacions | U38: 1) 10 2)1 | V38: 1)100 2) 4 | W38: Mancaria marcar que "SI" que té mesures aplicables que depenen del PN a columna M. Falta indicar la prioritat. | X38: 200 | Y38: Direcció | Z38: Joan Pijoan
A39: CULTURA | B39: 4 | C39: CONSERVAR ELS ELEMENTS CULTURALS materials i immaterials vinculats a la natura | D39: 04.1 | E39: Millorar el coneixement disponible sobre el patrimoni arquitectònic i cultural (material i immaterial) vinculat al patrimoni natural, el seu estat de conservació i els estils propis dels territoris de l'ENP | F39: 04.1.1 | G39: Elaborar l'inventari i cartografia de patrimoni cultural de l'ENP, que també inclogui el patrimoni etnològic i immaterial | H39: 04.1.1 | I39: Comú | J39: Optatiu | K39: Elaborar l'inventari i cartografia de patrimoni cultural de la Garrotxa, que també inclogui el patrimoni etnològic i immaterial | L39: Es treballarà en l'àmbit comarcal més enllà dels límits de l'ENP | M39: Sí | O39: MITJANA | P39: *Recopilació de la informació dels catàlegs dels ajuntaments de l'ENP i fer diagnosi *Inventari de patrimoni cultural material *Inventari de patrimoni cultural immaterial (metodologia de l'inventari de la unesco) *Elaboració d'un mapa de tranquil·litat. | S39: 1) Identificació i priorització dels elements principals que conformen el patrimoni cultural de la Garrotxa. 2) Recull d'informació del patrimoni etnològic i immaterial present de la Garrotxa. 3) Identificació de mancances en el resultat de la recollida d'informació. 4) Elaboració de l'inventari del patrimoni etnològic i immaterial de la Garrotxa 5) Difusió i dinamització de l'inventari 6) Redactar un catàleg de barraques de pedra seca | T39: 1) Nombre d'entitats, associacions i agents locals diversos implicats en el recull d'informació. 2) Nombre d'elements que conformen el patrimoni cultural vinculat a la natura de la Garrotxa. 3) Nombre de persones receptores dels resultats de l'inventari 4) Cataleg de barraques de pedra seca | U39: 1) 15 2) 1000 3) 500 4) 1 | V39: 1) 40 2) 2000 2) 1500 4) 1 | W39: Indiqueu "impuls". Mancaria marcar que "SI" que té mesures aplicables que depenen del PN a columna M. | X39: 280 | Y39: Turisme / SIG | Z39: Arnau Dorca
F40: 04.1.2 | G40: Elaborar el catàleg lingüístic (localismes) de patrimoni natural, geografia popular, festes i activitats tradicionals de l'ENP | H40: 04.1.2 | I40: Comú | J40: Optatiu | K40: NA | L40: Alguns dels elements que es plantegen ja estan recollits en publicacions i alguns dels altres quedaran recollits en l'inventari de patrimoni cultural de l'OP04.1.1 | M40: Sí | O40: FORA DE TERMINI DEL PLA | W40: Més que indicar "Fora de termini del pla" en aquest cas es podria considerar directament l'objetiu com a No aplicable a la columna K (canviat per NA) i deixar la columna de priorització buida.
F41: 04.1.3 | G41: Elaborar la cartografia de la xarxa de camins ramaders i senders tradicionals de l'ENP | H41: 04.1.3 | I41: Comú | J41: Optatiu | O41: FORA DE TERMINI DEL PLA | W41: Mancaria justificar a la columna L el motiu pel que no s'incorpora al pla, i deixar clar si es considera NA o fora de termini
D42: 04.2 | E42: Conservar i gestionar el patrimoni cultural de l'ENP de forma coordinada amb els agents responsables i entitats de referència | F42: 04.2.1 | G42: Identificar els ens de referència en patrimoni cultural (entitats, associacions, museus i ecomuseus, etc.) en l'àmbit de l'ENP | H42: 04.2.1 | I42: Comú | J42: Obligatori | K42: Identificar els ens de referència en patrimoni cultural (entitats, associacions, museus i ecomuseus, etc.) en l'àmbit de la Garrotxa | L42: Es treballarà en l'àmbit comarcal més enllà dels límits de l'ENP | M42: Sí | O42: ALTA | P42: *Elaboració d'un mapa d'entitats, associacions, museus, ecomuseus, OPEI (Observatori del Patrimoni Etnològic i Immaterial), etc. | S42: 1) Identificació d'ens de referència en patrimoni cultural i posterior creació d'un llistat que els reculli. 2) Participació a les jornades Parcs i museus organitzats per la DG. 3) Renovar conveni amb l'Espai Cràter | T42: 1) Nombre d'ens de referència identificats 2) Diversitat d'àmbits 3) Nº de jornades a les que s'ha participat 4) Nombre de convenis | U42: 1) 30 2) 6 3) 1 4)1 | V42: 1) 50 2) 10 3) 4 4) 2 | X42: 150 40 | Y42: Turisme / SIG Direcció | Z42: Arnau Dorca Joan Pijoan
F43: 04.2.2 | G43: Articular treballs conjunts entre l'ENP i representants, gestors o custodis del patrimoni cultural per a la seva protecció i millora | H43: 04.2.2 | I43: Comú | J43: Optatiu | K43: Articular treballs conjunts entre l'ENP i representants, gestors o custodis del patrimoni cultural per a la seva protecció i millora | M43: Sí | O43: BAIXA | P43: *Projecte parcs i museus *Impulsa dels convenis de col·laboració aamb la xarxa de museus i altres equipaments i entitats de referència *Foment de la cooperació tècnica dels gestors de l'ENP amb els representants o custodis del patrimoni cultural, i coordinar-ne l'ús compartit dels recursos | S43: 1) Donar suport a propostes de treballs centrats en la conservació i gestió del patrimoni cultural. 2) Establir vincles amb projectes culturals comarcals ( Sismògraf, espai cràter....) | T43: 1) Nombre de propostes de treballs que han rebut ajuts 2) Nombre de projectes | U43: 1) 2 2) 2 | V43: 1) 4 2) 4 | X43: 85 85 | Y43: Turisme / SIG Ús Públic | Z43: Arnau Dorca Xavier Oliver
F44: 04.2.3 | G44: Impulsar i/o participar dels treballs de restauració arquitectònica, arqueològica i del patrimoni cultural | H44: 04.2.3 | I44: Comú | J44: Optatiu | K44: =G44 -> Impulsar i/o participar dels treballs de restauració arquitectònica, arqueològica i del patrimoni cultural | L44: Està vinculat amb l'OP 04.2.2 | M44: Sí | O44: ALTA | P44: *Coordinació de l'equip tècnic (propi) amb els responsables dels treballs de restauració arquitectònica i del patrimoni cultural Participació quan els treballs estan vinculats a l’àrea d’ús públic de l’ENP | S44: 1) Promoure i donar suport als treballs de restauració arquitectònica, arqueològica i del patrimoni cultural Art. 34 PEZVG 2) Col·laboració en la divulgació del coneixement arqueologic lligat al vulcanisme conjuntament amb altres entitats. | T44: 1) Nombre de propostes | U44: 1) 2 | V44: 1) 4 | X44: 450 | Y44: Direccio Millora Rural | Z44: Joan Pijoan
F45: 04.2.4 | G45: Disposar de personal especialitzat en patrimoni cultural | H45: 04.2.4 | I45: Comú | J45: Obligatori | K45: Disposar d'assessorament especialitzat en patrimoni cultural | L45: Aclariment OP | M45: Sí | N45: Sí | O45: BAIXA | P45: *Formació del personal tècnic de l'ENP en la gestió i conservació dels valors culturals de l'ENP | S45: 1) Disposar d'un servei d'assessorament especialitzat en patrimoni cultural | T45: 1) Nombre de persones especialitzades en patrimoni cultural | U45: 1) 1 | V45: 1)1 | W45: Mancaria marcar que "SI" que té mesures aplicables que depenen del PN a columna M? motiu pel qual heu marcat "NO"? | X45: 40 | Y45: Direcció | Z45: Joan Pijoan
D46: 04.3 | E46: Potenciar la conservació i recuperació del patrimoni cultural material i immaterial de l'ENP | F46: 04.3.1 | G46: Recuperar i conservar el patrimoni cultural immaterial (associat a les activitats i aprofitaments rurals tradicionals) i els valors espirituals | H46: 04.3.1 | I46: Comú | J46: Obligatori | K46: =G46 -> Recuperar i conservar el patrimoni cultural immaterial (associat a les activitats i aprofitaments rurals tradicionals) i els valors espirituals | M46: Sí | O46: MITJANA | Q46: MAP | S46: 1) Celebració d'una jornada d'activitats tradicionals del Parc 2) Elaborar el catàleg de patrimoni immaterial del Parc | T46: 1) Nombre d'activitats presents 2) Nombre de participants a la jornada | U46: 1) 2 2) 16 | V46: 1) 4 2) 32 | X46: 140 140 | Y46: Ús Públic i Turisme Patrimoni Forestal | Z46: Arnau Dorca Joan Montserrat
F47: 04.3.2 | G47: Recuperar i conservar el patrimoni cultural rural vinculat específicament a construccions de pedra en sec | H47: 04.3.2 | I47: Específic | J47: Obligatori | K47: =G47 -> Recuperar i conservar el patrimoni cultural rural vinculat específicament a construccions de pedra en sec | M47: Sí | O47: ALTA | Q47: MAP | S47: 1) Suport i formació a la restauració de murs de pedra seca 2) Suport a la Setmana de la Pedra Seca 3) Catàleg de barraques de pedra seca el PNZVG 4) Restauració de murs de pedra seca en finques pròpies , conveniades o amb autorització. 5) Elaborar un manual de bones pràctiques i caracterització en la construcció de murs de pedra seca. Promoure la capacitat profesional dels pretsacaires. | T47: 1) Nombre d'elements recuperats 2) Nombre d'actuacions de restauració executades 3) Nombre d'activitats programades durant la Setmana de la Pedra Seca 4) Nombre de persones assistents les activitats programades en el marc de la Setmana de la Pedra Seca 5) Metres de murs de pedra seca restaurats | U47: 1) 2 2) 2 3) 1 4) 15 5) 2 | V47: 1) 4 2) 4 3) 3 4) 25 5) 4 | X47: 320 498 | Y47: Patrimoni Natural Patrimoni Forestal | Z47: Emili Bassols Joan Montserrat
F48: 04.3.3 | G48: Fomentar la recuperació i conservació de l'arquitectura tradicional d'intrès de les edificacions i construccions | H48: 04.3.3 | I48: Comú | J48: Optatiu | K48: =G48 -> Fomentar la recuperació i conservació de l'arquitectura tradicional d'intrès de les edificacions i construccions | M48: Sí | O48: ALTA | S48: 1) Assessorament arquitectònic en edificacions i construccions 2) Seguiment dels informes emesos | T48: 1) Nombre d'informes emesos 1,2) Percentatge del compliment dels informes emesos | U48: 1) 0 2) 100% | V48: 1) 100 2) 100% | W48: Mancaria marcar que "SI" que té mesures aplicables que depenen del PN a columna M. | X48: 320 | Y48: Direcció Millora Rural | Z48: Joan Pijoan ?
F49: 04.3.4 | G49: Identificar i conservar la diversitat domesticada de varietats agrícoles i ramaderes locals | H49: 04.3.4 | I49: Comú | J49: Obligatori | K49: =G49 -> Identificar i conservar la diversitat domesticada de varietats agrícoles i ramaderes locals | M49: Sí | O49: ALTA | P49: *Banc de llavors *Convenis ramaders per la cria de races locals | Q49: ESNATURA | S49: 1) Elaboració del catàleg de varietats del CCPC de can Jordà (amb incorporació d'imatges) 2) Identificació de varietats agrícoles i ramaderes locals 3) Recerca i actualització del llistat d'explotacions que treballen amb varietats agrícoles i ramaderes locals 4) Suport a activitats que es centren en impulsar l'activitat agrícola i ramadera local | T49: 1) Elaboració del catàleg 2) Nombre de varietats identificades 3) Nombre d'explotacions identificades i/o actualitzades 4) Activitats realitzades amb el suport del Parc. | U49: 1) 1 2) 5 3) 18 4) 2 | V49: 1) 1 2) 15 3) 30 4) 4 | X49: 680 150 | Y49: Patrimoni Agro Patrimoni Natural | Z49: Bernat Perramon Emili Bassols
D50: 04.4 | E50: Donar a conèixer els elements culturals com a valors del paisatge de l'ENP en les activitats d'ús públic | F50: 04.4.1 | G50: Integrar el patrimoni cultural als itineraris i cartelleria de l'ENP. | H50: 04.4.1 | I50: Comú | J50: Obligatori | K50: =G50 -> Integrar el patrimoni cultural als itineraris i cartelleria de l'ENP. | M50: Sí | O50: MITJANA | S50: 1) Definició d'uns criteris per determinar quins elements del patrimoni cultural s'incorpora als itineraris i a la cartelleria 2) Incorporació d'elements del patrimoni cultural als itineraris i a la cartelleria | T50: 1) Definició dels elements a incorporar 2) Nombre d'elements incorporats als itineraris i a la cartelleria | U50: 1) 5 2) 10 | V50: 1) 10 2) 30 | X50: 152 | Y50: Ús Públic | Z50: Xavier Oliver
F51: 04.4.2 | G51: Incorporar el patrimoni cultural en els plans d’ús públic i educació ambiental per fomentar-ne la seva conservació i divulgació. | H51: 04.4.2 | I51: Comú | J51: Obligatori | K51: =G51 -> Incorporar el patrimoni cultural en els plans d’ús públic i educació ambiental per fomentar-ne la seva conservació i divulgació. | M51: Sí | O51: ALTA | S51: 1) Incoroporar personatges de l'imaginari popular per la creació de recursos educatius 2) Creació de material divulgatiu que relacioni el paisatge amb els trets identitaris del territori 3)Integració del patrimoni cultural en el PUP comarcal. | T51: 1) Proporció d'elements culturals incorporats en l'oferta divulgativa 2) Creació de materials divulgatius 3) Proporció d'elements culturals integrats en el PUP | U51: 1) 2 2) 1 3) 1 | V51: 1) 5 2) 2 3) 10 | X51: 250 250 | Y51: Ús Públic Turisme / SIG | Z51: Xavier Oliver Arnau Dorca
F52: 04.4.3 | G52: Formar el personal dels punts d’informació en els valors culturals de l'ENP | H52: 04.4.3 | I52: Comú | J52: Obligatori | K52: =G52 -> Formar el personal dels punts d’informació en els valors culturals de l'ENP | M52: Sí | O52: ALTA | S52: 1) Revisar els continguts vinculats al patrimoni cultural en el Curs de Bon Coneixement de la Garrotxa. 2) Incorporar el patrimoni cultural a la formació específica de l'equip del servei d'informació | T52: 1) Hores dedicades a continguts revisats/incorporats en el Curs de Bon Coneixement de la Garrotxa. 2) Hores dedicades a creació d'un bloc formatiu dedicat al patrimoni cultural a la formació específica | U52: 1) 2 hores 2) 0,5hores | V52: 1) 5 hores 2) 1,5 hores | X52: 300 | Y52: Ús Públic | Z52: Xavier Oliver
B53: 5 | C53: PROTEGIR EL PAISATGE i la qualitat de l'ambient visual, sonor i lumínic. | D53: 05.1 | E53: Identificar els elements d'interès paisatgístic de l'espai | F53: 05.1.1 | G53: Elaborar un inventari d'elements d'interès paisatgístic de l'ENP d'acord amb el Catàleg de paisatge de la zona | H53: 05.1.1 | I53: Comú | J53: Optatiu | K53: No aplica | L53: Es disposa de la Carta de Paisatge. El Parc disposa també d'un treball sobre l'estudi del paisatge al PNZVG elaborat per Minuartia (2002) | W53: Més que indicar "Fora de termini del pla" en aquest cas es podria considerar directament l'objetiu com a No aplicable a la columna K (canviat per NA) i deixar la columna de priorització buida.
D54: 05.2 | E54: Millorar la qualitat paisatgística | F54: 05.2.1 | G54: Desplegar actuacions de restauració dels elements d'interès paisatgístic degradats | H54: 05.2.1 | I54: Comú | J54: Optatiu | K54: =G54 -> Desplegar actuacions de restauració dels elements d'interès paisatgístic degradats | L54: L'OP està vinculat amb patrimoni natural i ús públic i es pot treballar des d'aquells àmbits | M54: Sí | O54: ALTA | S54: 1) Elaborar un catàleg d'espais degradats a restaurar. 2)Treballar per la restauració d'espais paisatgístics degradats: Tossol del bosc de Tosca, gredera del volcà del Racó, àmbit del Triangle, gredera del Montsacopa, gredera est volcà del Monsacopa,... | T54: 1) Nombre d'espais restaurats | U54: 1) 1 | V54: 1) 4 | W54: Mancaria marcar que "SI" que té mesures aplicables que depenen del PN a columna M. Com a indicador es podria afegir també "Elaboració del catàleg" | X54: 400 177 | Y54: Direcció Patrimoni Natural | Z54: Joan Pijoan Emili Bassols
F55: 05.2.2 | G55: Gestionar l'abandonament d'infraestructures i instal·lacions amb impactes sobre els valors de l'espai | H55: 05.2.2 | K55: =G55 -> Gestionar l'abandonament d'infraestructures i instal·lacions amb impactes sobre els valors de l'espai | M55: Sí | O55: MITJANA | S55: 1) Millora de la passera del riu Fluvià al pas entre Castellfollit de la Roca i Montagut i Oix 2) Redacció del Pla Especial del Bosc de Tosca (barraques, tancaments,.... | T55: 1) Millora de la passera 2) Redacció del Pla | U55: 1) 1 2) 1 | V55: 1) 1 2) 1 | W55: Mancaria marcar que "SI" que té mesures aplicables que depenen del PN a columna M. | X55: 180 | Y55: Direcció | Z55: Joan Pijoan
F56: 05.2.3 | G56: Minimitzar la brutícia, deixalles, vandalisme i males praxis dins l'ENP | H56: 05.2.3 | I56: Comú | J56: Obligatori | K56: =G56 -> Minimitzar la brutícia, deixalles, vandalisme i males praxis dins l'ENP | M56: Sí | O56: ALTA | S56: 1) Gestió i seguiment de requeriments relacionats del Parc 2) Difusió de bones pràctiques a través de difernets mitjans ( educació ambiental | T56: 1) Hores dedicades a la gestió de requeriments 2) Nombre d'accions | U56: 1) 250 2) 5 | V56: 1) 300 2) 10 | X56: 190 | Y56: Ús públic | Z56: Xavier Oliver
D57: 05.3 | E57: Protegir la qualitat acústica i lumínica de l'ENP | F57: 05.3.1 | G57: Promoure la certificació de qualitat del cel nocturn | H57: 05.3.1 | I57: Específic | J57: Optatiu | K57: No aplica | L57: El PNZVG es troba en una zona humanitzada, envoltat de nuclis urbans que generen contaminació lumínica | Q57: ESNATURA | W57: Més que indicar "Fora de termini del pla" en aquest cas es podria considerar directament l'objetiu com a No aplicable a la columna K (canviat per NA) i deixar la columna de priorització buida.
F58: 05.3.2 | G58: Promoure la certificació de zones d'especial protecció de la qualitat acústica | H58: 05.3.2 | I58: Específic | J58: Optatiu | K58: Promoure la certificació de zones d'especial protecció de la qualitat acústica (àmbit de la Moixina i Fageda d'en Jordà) | M58: Sí | N58: No | O58: MITJANA | Q58: ESNATURA | S58: 1) Promoure la certificació de Zona d'Especial Protecció de la Qualitat Acústica àmbit Moixina i Fageda d'en Jordà. | T58: 1) Certificació | U58: 1) 1 | V58: 1) 1 | X58: 60 | Y58: Direcció | Z58: Joan Pijoan
A59: CONEIXEMENT | B59: 6 | C59: MILLORAR EL CONEIXEMENT DE L'ENTORN, del patrimoni natural, cultural i social. | D59: 06.1 | E59: Identificar els objectes de gestió prioritària de l'ENP en el marc dels objectius de govern | F59: 06.1.1 | G59: Identificar i prioritzar els elements clau i d'interès per la gestió de la biodiversitat i geodiversitat de Catalunya que es troben dins l'ENP (especies amenaçades, espècies exòtiques invasores,.. ) | H59: 06.1.1 | I59: Comú | J59: Obligatori | K59: =G59 -> Identificar i prioritzar els elements clau i d'interès per la gestió de la biodiversitat i geodiversitat de Catalunya que es troben dins l'ENP (especies amenaçades, espècies exòtiques invasores,.. ) | O59: ALTA | P59: *Participació en la definició dels objectes de conservació clau (hàbitats, espècies, processos i elements d’interès geològic) comuns a nivell de Xarxa d'ENP o clúster territorial | Q59: Directriva Habitats Carta emplaçament ESNATURA Catàlegs | R59: UIC/SFF/SPEN: Definir criteris d'identificació d'elements interès. UIC/SFF/SPEN: Definició dels objectes de conservació clau comuns a nivell de Xarxa d'ENP o clúster territorial | S59: 1) Crear una base de dades que identifiqui els elements d'interès. 2) Prioritzar els elements d'interès (hàbitats i espècies) en base a la informació recollida. 3) Recollir informació sobre els elements d'interès per la geodiversitat i prioritzar mesures de conservació. 4) Identificar i prioritzar mesures d'intervenció sobre espècies exòtiques en funció de la seva capacitat invasora. 5) Fer catàlegs i inventaris (biodiversitat, forestals, varietats CCPC,...). | T59: 1) Nombre de documents d'elements clau i d'interès per la gestió elaborats 2) Nombre de documents actualitzats. 3) Nombre de documents nous establerts. 4) Nombre mesures 5) Nombe catàlegs | U59: 1) 1 2) 2 3) 1 4) 2 5) 1 | V59: 1) 10 2) 5 3) 5 4) 10 5) 5 | W59: Mancaria marcar que "SI" que té mesures aplicables que depenen del PN a columna M. | X59: 300 | Y59: Patrimoni Natural | Z59: Emili Bassols
F60: 06.1.2 | G60: Definir espais fràgils i zones d'especial atenció | H60: 06.1.2 | I60: Comú | J60: Obligatori | K60: =G60 -> Definir espais fràgils i zones d'especial atenció | M60: Sí | O60: MÀXIMA | P60: *Generació d'informació per a l'inventari i cartografia d'espais fràgils *Realització o actualització de l'inventari de ZH, espais interès geològic, etc. | R60: SPEN: Inventari i cartografia d'espais fràgils i zones d'especial atenció | S60: 1) A partir de la cartografia de sòls singulars disponible i d'ampliar la recerca, identificar les zones de major interès edafològic del Parc. 2) Millora i actualització tècnica de la cartografia edafològica del Parc i de zones properes. 3) Actualitzar l'informe de l'estat de conservació de les Reserves Naturals del Parc i establir un protocol de seguiment. | T60: 1) Nombre d'espais i zones identificats 2) Superfície identificada com espais fràgils o ZEAs 3) Redacció informe | U60: 1) 1 2) 0 3) 1 | V60: 1) 20 2) 100 3) 1 | X60: 280 150 | Y60: Patrimoni Agro Patrimoni Natural | Z60: Bernat Perramon Emili Bassols
D61: 06.2 | E61: Conèixer l'estat de conservació i la seva tendència dels hàbitats, les espècies els elements de la gea i els processos ecològics com a eina per avaluar i optimitzar la gestió | F61: 06.2.1 | G61: Participar en l'elaboració de la cartografia que elabora la UIC | H61: 06.2.1 | I61: Comú | J61: Obligatori | K61: =G61 -> Participar en l'elaboració de la cartografia que elabora la UIC | M61: Sí | O61: MÀXIMA | P61: *Participació en la programació de la realització de la cartografia d'hàbitats en el contracte plurienal que existeix amb GeoVeg-UB | Q61: ESNATURA | R61: UIC: Coordinar i contractar l'elaboració de la cartografia | S61: 1) Transferir a la UIC la informació cartogràfica temàtica elaborada des del Parc Natural. | T61: 1) Nombre de cartografies generades transferides a la UIC. | U61: 1) 1 | V61: 1) 10 | X61: 200 | Y61: Turisme / SIG | Z61: Arnau Dorca
F62: 06.2.2 | G62: Conèixer i estudiar els processos naturals propis de l’espai, la seva funcionalitat, i ecologia en referència als ecosistemes | H62: 06.2.2 | I62: Comú | J62: Obligatori | K62: Conèixer i estudiar els elements i processos naturals propis de l’espai, la seva funcionalitat, i ecologia en referència als ecosistemes | L62: Canvi redactat OP. Incloure elements | M62: Sí | O62: ALTA | P62: *Foment i coordinació dels estudis d'ecologia del foc, el règim hidrològic, la pol·linització, la tipificació i funcionament de les cadenes tròfiques pròpies de l’espai, la dinàmica de la neu i les allaus, dinàmica litoral, dinàmica geomorfològica i morfodinàmica de les roques, etc. *Millora del coneixement de la geoconservació (escala més detallada de 1:50.000) *Implementació del protocol de fluxos d'informació i coneixement de biodiversitat | S62: 1) Foment i coordinació dels estudis sobre el règim hidrològic, la pol·linització, la tipificació i funcionament de les cadenes tròfiques pròpies de l'espai, la maduresa forestal i dinàmica geomorfològica, etc. 2) reedició publicació sobre prats de dall 3) Anàlisi mostres ( paleomagnetisme) 4) Anàlisi de riscos (arbrat) 5) Seguiment espècies (CBMS: Can Jordà, Croscat, Sant Iscle, Sallent) 6) recerca agrària pròpia a partir de l'establiment de camps experimentals i seguiments dirigits a la millora de la pràctiques agràries i ramaderes (àmbit sòls, planta i aigua) 7) seguiments d'hàbitats de prats per determinar l'estat actual i proposar possibles millores (àmbit sòls i espècies) 8) conèixer evolució d'espais oberts des dels anys 80 fins a l'actualitat a partir de fotointerpretació 9) adquisició lupa per a laboratori (vinculat a recerca i seguiments diversos que es porten a terme des del Parc Natural) 10) Seguiment de l'estat de conservació dels boscos (boixedes, boscos madurs, afectació sequera...) | T62: 1) Nombre d'estudis/seguiments realitzats 2) Nombre d'elements/grups clau estudiats | U62: 1) 1 2) 1 | V62: 1) 10 2)10 | W62: Mancaria marcar que "SI" que té mesures aplicables que depenen del PN a columna M. | X62: 450 450 | Y62: Patrimoni Natural Patrimoni Agro | Z62: Emili Bassols Bernat Perramon
F63: 06.2.3 | G63: Conèixer els usos i factors de canvi rellevants en l'evolució dels elements de conservació, i avaluar els efectes que generen en l’espai (pressions i amenaces) | H63: 06.2.3 | I63: Comú | J63: Obligatori | K63: =G63 -> Conèixer els usos i factors de canvi rellevants en l'evolució dels elements de conservació, i avaluar els efectes que generen en l’espai (pressions i amenaces) | M63: Sí | O63: MÀXIMA | P63: *Foment de l'estudi de l'afectació de determinats processos naturals o activitats antròpiques (contaminació, fragmentació d'hàbitats, atropellaments, noves arts de pesca o pràctiques agrícoles de muntanya, etc.) en l’ENP (amenaces i impacte ambiental). *Avaluació de l'impacte del canvi climàtic en l'ENP i la seva capacitat d'adaptació i resiliència. *Avaluació dels resultats de les estratègies de gestió aplicades en l'ENP *Col.laboració amb l?Observatori per aportar els coneixements generats a l'ENP. | Q63: ESNATURA | R63: SENP/UIC: Elaborar la classificació i cartografia de les pressions o factors de canvi sobre el medi natural | S63: 1) Seguiment fotogramètric de l'evolució dels afloraments d'interès geològic (AIG) del Parc Natural. 2) Estudi de l'evolució dels espais oberts del Parc Natural des de 1987. 3) Evolució de l'estat ecològic dels prats seminaturals del Parc Natural (1995 -->) 4) Diagnosi de l'evolució del grau d'ocupació urbana del sòl protegit. 5) Evolució de la implantació de infraestructures de serveis urbans dins l'espai natural protegit. 6) Estudi dels efectes del canvi climàtic sobre les comunitats vegetals d'interès. 7) Diagnosi de l'evolució dels hàbitats al Parc Natural. 8) Estudi d'avaluació d'amenaces al PNZVG | T63: 1) Nombre d'afloraments amb seguiment. 2) Evolució de la superfície d'espais oberts. 3,4,5,6,7) Nombre d'estudis i diagnosis realitzats 8) Nombre de noves amenacesi nombre de amenaces reduides | U63: 1)1 2) 10 3) 1 | V63: 1) 9 2) 50 3) 5 | W63: Mancaria marcar que "SI" que té mesures aplicables que depenen del PN a columna M. | X63: 450 450 400 250 | Y63: Patrimoni natural Direcció | Z63: Emili Basols Bernat Perraamon Joan Montserrat Joan Pijoan
F64: 06.2.4 | G64: Conèixer l'impacte de les gestió de l'aigua, sobre la biodiversitat. | H64: 06.2.4 | I64: Comú | J64: Optatiu | K64: Conèixer l'impacte de l'ús i consum de l'aigua sobre la biodiversitat. | L64: La gestió de l'aigua no hauria de ser un impacte "per se", en canvi sí que ho seria el seu aprofitament, sobretot si és excessiu. | M64: Sí | O64: MÀXIMA | P64: *Programa de seguiment de l’estat hidrològic de les masses d’aigua *Establiment d’una xarxa automatitzada de control (sensors, inventaris, models hidrològics, etc.). | S64: 1) Actualització del nombre de captacions existents en el Parc Natural i la seva àrea d'influència i volum extret. 2) Adquisició de material per fer seguiment de la gestió de l'aigua (sondes, escales limnimètriques, piezòmetres, arquetes protecció) 3) Col·locació de dos sensors per a calcular l'impacte de les derivacións d'aigues superficials 4) Instal·lació de punts de control. | T64: 1) Nombre de captacions localitzades. 2) Adquisició 3) Col·locació 4) Punts controlats | U64: 1) 5 2) 0 3) 0 4) 2 | V64: 1) 20 2) 5 3) 2 4) 5 | W64: Mancaria marcar que "SI" que té mesures aplicables que depenen del PN a columna M. | X64: 200 | Y64: Patrimoni Natural | Z64: Emili Bassols
F65: 06.2.5 | G65: Participar en el coneixement de la tendència d'espècies plaga amb afectacions sobre ecosistemes o activitats econòmiques dins l'ENP | H65: 06.2.5 | I65: Comú | J65: Optatiu | K65: =G65 -> Participar en el coneixement de la tendència d'espècies plaga amb afectacions sobre ecosistemes o activitats econòmiques dins l'ENP | M65: Sí | O65: ALTA | P65: *Participació en dels estudis de les autoritats competents | S65: 1) Identificar les espècies plaga al Parc Natural 2) Participació en el programa de seguiment i actuacions de minimització d'impactes d'espècies plaga com ara el senglar, el fals creixens,etc | T65: 1) Informe investigació realitzada 2) Nombre d'actuacions | U65: 1) 1 2) 1 | V65: 1) 1 2) 10 | W65: Mancaria marcar que "SI" que té mesures aplicables que depenen del PN a columna M. | X65: 50 50 | Y65: Patrimoni Natural Patrimoni Agro | Z65: Emili Bassols Bernat Perramon
F66: 06.2.6 | G66: Conèixer la tendència d'espècies exòtiques invasores amb afectacions sobre ecosistemes o activitats econòmiques dins l'ENP | H66: 06.2.6 | I66: Comú | J66: Obligatori | K66: =G66 -> Conèixer la tendència d'espècies exòtiques invasores amb afectacions sobre ecosistemes o activitats econòmiques dins l'ENP | M66: Sí | N66: Sí | O66: ALTA | P66: *Realització i foment d'estudis de forma coordinada amb el SFF | Q66: ESNATURA | S66: 1) Identificar les espècies plaga al Parc Natural 2) Participació en el programa de seguiment i minimització d'impactes d'espècies exòtiques invasores (papallona del boix, vespa asiàtica, etc.). 3) Realitzar informes botànics per a la millora de la biodiversiat a les empreses CETS | T66: 1) Informe investigació realitzada 2) Nombre d'actuacions 3) Nombre d'informes | U66: 1) 1 2) 2 3) 4 | V66: 1) 1 2) 8 3) 20 | X66: 75 | Y66: Patrimoni Natural | Z66: Emili Bassols
F67: 06.2.7 | G67: Coneixer com millorar la connectivitat de forma coordinada amb altres ENP | H67: 06.2.7 | I67: Comú | J67: Optatiu | K67: NA | L67: El PN ja disposa de zones connectores, internes i externes. | P67: * Elaboració d'una cartografia detallada i actualitzada de connectors ecològics | Q67: ESNATURA | W67: Més que indicar "Fora de termini del pla" en aquest cas es podria considerar directament l'objetiu com a No aplicable a la columna K (canviat per NA) i deixar la columna de priorització buida.
D68: 06.3 | E68: Estandaritzar els seguiments periòdics dels grups clau | F68: 06.3.1 | G68: Participar en la definició del sistema estàndard de seguiment de flora, fauna i hàbitats de la DG | H68: 06.3.1 | I68: Comú | J68: Obligatori | K68: =G68 -> Participar en la definició del sistema estàndard de seguiment de flora, fauna i hàbitats de la DG | M68: Sí | N68: Sí | P68: *Suport a la UIC en la definició dels sistemes de seguiment | Q68: ESNATURA | R68: UIC/SFF/SENP: Crear espais de participació UIC/SFF: Definir el sistema estàndard de seguiment i el protocol d'aplicació | S68: 1) Oferir suport a la DG i a la UIC en aquests estándards. | T68: 1) Nombre d'accions | U68: 1) 1 | V68: 1) 5 | X68: 20 | Y68: Patrimoni Natural | Z68: Emili Bassols
F69: 06.3.2 | G69: Adequar i executar el sistema de seguiment periòdic dels grups clau de l'ENP al sistema estàndard de seguiment | H69: 06.3.2 | I69: Comú | J69: Obligatori | K69: =G69 -> Adequar i executar el sistema de seguiment periòdic dels grups clau de l'ENP al sistema estàndard de seguiment | M69: Sí | P69: * Seguiment de les directrius del sistema de seguiment establerts segons la versió més recent aportada per la UIC *Reforç i estabilització de la xarxa de voluntariat per a determinats seguiments de biodiversitat. *Contractació plurianual d’especialistes *Aplicació del protocol establert de compartir informació per al seguiment global d’indicadors de l’estat de la natura, el seguiment dels pol·linitzadors silvestres, o el seguiment dels pol·linitzadors silvestres | Q69: ESNATURA | R69: UIC/SFF: Definir el sistema estàndard de seguiment i el protocol d'aplicació UIC: Elaborar el protocol d'informació i coneixement | S69: 1) Seguiment d'afloraments efímers. 2) Seguiment d'espècies de flora amenaçada. 3) Seguiment d'espècies o grups de fauna (CBMS: Can Jordà, Croscat, Sant Iscle, Sallent) 4) Seguiments fotogramètric afloraments d'interès geològic (AIG) | T69: 1) Nombre d'espècies clau en seguiment 2) Nombre de seguiments afloraments | U69: 1) 1 2) 1 | V69: 1) 10 2) 5 | W69: Mancaria marcar que "SI" que té mesures aplicables que depenen del PN a columna M. | X69: 150 | Y69: Patrimoni Natural | Z69: Emili Bassols
F70: 06.3.3 | G70: Mantenir una base de dades de seguiment de patrimoni natural de l'ENP actualitzada i ordenada | H70: 06.3.3 | I70: Comú | J70: Obligatori | K70: =G70 -> Mantenir una base de dades de seguiment de patrimoni natural de l'ENP actualitzada i ordenada | M70: Sí | N70: Sí | O70: MÀXIMA | S70: 1) Mantenir les bases de dades de seguiments 2) Elaborar un programa de les espècies de seguiment del Parc 3) Fer operativa la base de dades de flora i vegetació | T70: 1) Mateniment base de dades 2) Progama 3) Actualitzar base de dades | U70: 1) 1 2) 1 3) 1 | V70: 1) 1 2) 1 3) 1 | X70: 20 350 | Y70: Patrimoni Natural Turisme / SIG | Z70: Emili Bassols Arnau Dorca
F71: 06.3.4 | G71: Participar en la definició, organització i bolcatge de dades del SINATCAT | H71: 06.3.4 | I71: Comú | J71: Obligatori | K71: =G71 -> Participar en la definició, organització i bolcatge de dades del SINATCAT | N71: Sí | O71: MÀXIMA | R71: UIC/SENP: Crear i coordinar una metodologia participativa per a la definició del SINATCAT | S71: 1) Recollir, ordenar i transferir de forma contínua les dades relacionades amb la gestió de l'espai al SINATCAT | T71: 1) Nombre accions SINATCAT | U71: 1) 1 | V71: 1) 10 | X71: 300 | Y71: Turisme / SIG | Z71: Arnau Dorca
D72: 06.4 | E72: Incrementar el coneixement de qualitat mitjançant l’establiment de marcs de col·laboració, assessorament i suport amb centres de recerca, museus i entitats naturalistes per al desenvolupament de part de la seva activitat en l’ENP | F72: 06.4.1 | G72: Crear sinèrgies i col·laborar amb museus i equipaments de referència per definir línies d'actuació conjunta entre patrimoni cultural i natural | H72: 06.4.1 | I72: Comú | J72: Optatiu | K72: Crear sinèrgies i col·laborar amb la comunitat museus, equipaments de referència i xarxs de biblioteques per definir línies d'actuació conjunta entre patrimoni cultural i natural | L72: Ampliar la col·laboració més enllà dels museus i equipaments de referència. | M72: Sí | O72: ALTA | R72: SENP: Elaborar un mapa d'agents de referència | S72: 1) Col·laboració amb els equipaments locals proposant accions conjuntes (Espai Cràter, Can Trona, etc.) 2) Col·laboració als premis Jordi Pujiula de treballs de recerca de batxillerat 3) Col·laboració als premis Arnau Bartrina Luque 4) Col·laboració amb FAVER LLULL. 5) Col·laboració amb l'Escola d'Art d'Olot 6) Col·laborar amb iniciatives de xarxes com DocAmbCat o RECIDA | T72: 1) Nombre de col·laboracions amb museus. 2,3,4,5,6) Nombre de col·labora. | U72: 1) 1 2) 1 | V72: 1) 2 2) 4 | W72: Adequar nom OP al que comenteu: - Crear sinèrgies i col·laborar amb la comunitat museus, equipaments de referència i xarxs de biblioteques per definir línies d'actuació conjunta entre patrimoni cultural i natural | X72: 980 40 50 | Y72: Centre de Documentació Direcció Patrimoni Natural | Z72: Montse Grabolosa Joan Pijoan Emili Bassols
F73: 06.4.2 | G73: Establir acords amb les institucions de recerca i naturalistes per al desenvolupament d'estudis i inventaris dins l'ENP en el marc de les seves línies de recerca | H73: 06.4.2 | I73: Comú | J73: Optatiu | K73: Establir acords amb les institucions de recerca i naturalistes per al desenvolupament d'estudis i inventaris dins l'ENP en el marc de les seves línies de recerca | M73: Sí | O73: ALTA | R73: SENP: Elaborar un mapa d'agents de referècia | S73: 1) Col·laboració amb centres de recerca per la realització d'estudis, seguiments, assajos i per transferir el resultats de la mateixa. | T73: 1) Nombre de col·laboracions amb institucions de recerca. 2) Nombre d'entitats amb les que es col·labora. | U73: 1) 1 2) 1 | V73: 1) 5 2) 5 | X73: 45 45 | Y73: Patrimoni Natural Direcció | Z73: Emili Bassols Joan Pijoan
F74: 06.4.3 | G74: Potenciar la ciència ciutadana en l’ENP com a eina per generar coneixement | H74: 06.4.3 | I74: Comú | J74: Optatiu | K74: =G74 -> Potenciar la ciència ciutadana en l’ENP com a eina per generar coneixement | M74: Sí | O74: MITJANA | P74: *Vinculació amb projectes de ciència ciutana existents per generar dades en l'ENP | S74: 1) Realització de projectes de ciència ciutadana dins l'ENP per tal de generar dades. 2) Suport i estabilització de la xarxa de voluntariat per a determinats seguiments de biodiversitat. | T74: 1) Nombre de projectes treballats amb ciència ciutadana i voluntariat | U74: 1,2) 1 | V74: 1,2) 4 | X74: 40 40 40 40 | Y74: Direcció Patrimoni Natural Ús Públic Turisme / SIG | Z74: Joan Pijoan Emili Bassols Xavier Oliver Arnau Dorca
F75: 06.4.4 | G75: Crear i desenvolupar jornades de recerca de l'ENP de forma anual on els diferents centres mostrin els estudis realizats en l'ENP | H75: 06.4.4 | I75: Comú | J75: Optatiu | K75: =G75 -> Crear i desenvolupar jornades de recerca de l'ENP de forma anual on els diferents centres mostrin els estudis realizats en l'ENP | M75: Sí | O75: ALTA | R75: SENP: Suport en l'organització de les jornades | S75: 1) Organització d'una jornada de recerca anual PNZVG en la que es presenten els principals estudis realitzats dins l'ENP. | T75: 1) Jornades realitzades | U75: 1) 1 | V75: 1) 4 | X75: 50 | Y75: Direcció | Z75: Joan Pijoan
F76: 06.4.5 | G76: Posar a disposició de la recerca, equipaments i serveis de l'ENP | H76: 06.4.5 | I76: Comú | J76: Optatiu | K76: =G76 -> Posar a disposició de la recerca, equipaments i serveis de l'ENP | M76: Sí | O76: MITJANA | Q76: ESNATURA | S76: 1) Posar a disposició els equipaments del PN (seu del Parc, cabana,...) 2) Posar a disposició la consulta i servei del Centre de Documentació i la cabana d'allotjament. | T76: 1) Nombre de cessions 2) Nombre consultes CD | U76: 1) 1 1) 20 | V76: 1) 5 2) 50 | X76: 20 150 880 | Y76: Direcció Centre de Documentaicó Administració | Z76: Joan Pijoan Montse Grabolosa
F77: 06.4.6 | G77: Crear l'Observatori de recerca de l'ENP vinculat a l'Observatori del Patrimoni natural i la biodiversitat | H77: 06.4.6 | I77: Comú | J77: Optatiu | K77: No aplica | L77: No es considera una actuació prioritària | M77: No | P77: *Impuls de la creació de l'Observatori de recerca de l'ENP en col·laboració amb la UIC | R77: UIC: Suport en la creació de l'Observatori de reserca | W77: Més que indicar "Fora de termini del pla" en aquest cas es podria considerar directament l'objetiu com a No aplicable a la columna K (canviat per NA) i deixar la columna de priorització buida.
D78: 06.5 | E78: Millorar el coneixement global de les dinàmiques d'usos antròpics de l’ENP | F78: 06.5.1 | G78: Participar en la definició del sistema estándard de seguiment de l'ús públic amb el SENP | H78: 06.5.1 | I78: Comú | J78: Obligatori | K78: =G78 -> Participar en la definició del sistema estándard de seguiment de l'ús públic amb el SENP | M78: Sí | R78: SENP: Crear espais de participació. Definició del sistema estándard de seguiment de l'ús públic | S78: 1) Assistència reunions d'ús públic del SENP | T78: 1) Nombre de reunions | U78: 1) 1 | V78: 1) 8 | W78: Mancaria marcar que "SI" que té mesures aplicables que depenen del PN a columna M. | X78: 60 | Y78: Ús públic | Z78: Xavier Oliver
F79: 06.5.2 | G79: Disposar de dades de freqüentació i perfil d'usuari en l'ENP i en especial en equipaments i en zones d'alta freqüentació segons el model de DG | H79: 06.5.2 | I79: Comú | J79: Obligatori | K79: =G79 -> Disposar de dades de freqüentació i perfil d'usuari en l'ENP i en especial en equipaments i en zones d'alta freqüentació segons el model de DG | M79: Sí | O79: ALTA | P79: *Implementació del sistema estandaritzat de presa de dades i seguiment de la freqüentació en ENP del SENP *Establiment de models de freqüentació que serveixin per gestionar l'ús públic en l'ENP conjuntament amb la UIC | R79: SENP: Disseny i elaboració del sistema estandaritzat de presa de dades i seguiment de la freqüentació en ENP | S79: 1) Seguiment del contracte d'Educació ambiental i servei informació 2) Posar sensors de recompte de visitants a les zones més freqüentades del Parc Natural ( Can Serra, Santa Margarida,...). 3) Instal·lació de ecocomptadors a punts estratègics 4) Participació com a agent clau al projecte smart county promogut pel Consell Comarcal de la Garrotxa 5) Elaboració d'enquestes coneixement perfil visitant 6) Treball conjunt amb la plataforma Smart Garrotxa | T79: 1) Nombre de reunions amb l'empresa adjudicatària del contracte. 2) Nombre de sensors instal·lats 3) Nombre de ecocomptadors instal·lats 4) Nombre de reunions 5) Nombre d'equestes realitzades | U79: 1)12 2) 2 3)2 4)2 5) 50 | V79: 1) 48 2) 4 3) 4 4) 4 5) 100.000 | X79: 300 500 | Y79: Ús públic Turisme / SIG | Z79: Xavier Oliver Arnau Dorca
F80: 06.5.3 | G80: Identificar les activitats i actors de l’espai. | H80: 06.5.3 | I80: Comú | J80: Obligatori | K80: =G80 -> Identificar les activitats i actors de l’espai. | M80: Sí | O80: MITJANA | S80: 1) Actualitzar l'estudi de l'impacte d'activiats turístiques sobre el medi natural (2019) 2) Inventariar les activitats no organitzades que s'organitzen dins el Parc | T80: 1) Actualització de l'estudi 2) Nombre d'activitats detectades | U80: 1) 1 2) 1 | V80: 1) 1 2) ? | X80: 300 | Y80: Turisme / SIG | Z80: Arnau Dorca
F81: 06.5.4 | G81: Identificar en cartografia les males praxis i punts de massificació | H81: 06.5.4 | K81: =G81 -> Identificar en cartografia les males praxis i punts de massificació | M81: Sí | S81: 1) Traspassar la informació de la base de dades d'incidencies a una base cartogràfica 2) Actualització de l'estudi de l'impacte turístic sobre zones freqüentades | T81: 1) Crear mapes temàtics 2) Estudi actaulitzat | U81: 1) 1 2) 1 | V81: 1) 1 2) 1 | X81: 200 | Y81: Turisme / SIG | Z81: Arnau Dorca
F82: 06.5.5 | G82: Adaptar i mantenir un registre d'activitats, actors i inciències en ús públic (curses, conflictes, queixes, etc) | H82: 06.5.5 | I82: Comú | J82: Obligatori | K82: =G82 -> Adaptar i mantenir un registre d'activitats, actors i inciències en ús públic (curses, conflictes, queixes, etc) | M82: Sí | R82: UIC: Disseny d'un model de registre d'activitats, actors i inciències en ús públic | S82: 1) Millorar la base de dades d'incidències on hi participin com a mínim: agents de camp, educadors de reserva, informadors i tècnics del Parc 2) Recollir els suggeriements i les reclamacions dels uusaris per tal d'adreçar-los a la persona coordinaroa del servei. | T82: 1) Percentatge d'incidencies respostes 2) Nombre de suggeriments rebut | U82: 1) 10 2) 1 | V82: 1) 90% 2) 20 | W82: Mancaria marcar que "SI" que té mesures aplicables que depenen del PN a columna M. | X82: 250 | Y82: Turisme / SIG | Z82: Arnau Dorca
F83: 06.5.6 | G83: Identificar els impactes (positius i negatius) que generen les activitats d'ús públic dins l'ENP | H83: 06.5.6 | I83: Comú | J83: Obligatori | K83: =G83 -> Identificar els impactes (positius i negatius) que generen les activitats d'ús públic dins l'ENP | M83: Sí | Q83: ESNATURA | S83: 1) Redacció d'un Pla d'ús públic del Parc dins el context Comarcal | T83: 1) Realització del Pla 2) Treballar amb l'eina d'avaluaciò d'impactes i iiformes junts CAG i SIGMA | U83: 1) 1 2) 1 | V83: 1) 1 2) 1 | W83: Mancaria marcar que "SI" que té mesures aplicables que depenen del PN a columna M. | X83: 217 380 | Y83: Turisme / SIG Ús Públic | Z83: Arnau Dorca Xavier Oliver
A84: DESENVOLUPAMENT LOCAL | B84: 7 | C84: FIXAR LA POBLACIÓ AL TERRITORI d'acord amb les oportunitats que generen els objectius de l'espai. | D84: 07.1 | E84: Fomentar i donar suport tècnic als Plans de desenvolupament socioecòmonic local sostenible dels municipis | F84: 07.1.1 | G84: Promoure i/o col·laborar en l'aplicació de Plans de Desenvolupament Local Sostenible | H84: 07.1.1 | I84: Comú | J84: Obligatori | K84: =G84 -> Promoure i/o col·laborar en l'aplicació de Plans de Desenvolupament Local Sostenible | M84: Sí | O84: ALTA | S84: 1) Participació en l'elaboració i aplicació de plans de desenvolupament local portats a terme per agents locals (ajuntaments, Adrinoc...) | T84: 1) Nombre de projectes amb els quals es participa i/o col·labora | U84: 1) 1 | V84: 1) 4 | W84: Mancaria marcar que "SI" que té mesures aplicables que depenen del PN a columna M. | X84: 150 | Y84: Direcció | Z84: Joan Pijoan
B85: 8 | C85: APROFITAR ELS RECURSOS NATURALS DE FORMA SOSTENIBLE mitjançant desenvolupament dels aprofitaments tradicionals de forma compatible amb la conservació de l'espai | D85: 08.1 | E85: Impulsar models productius agraris i forestals per tal d'afavorir la conservació dels hàbitats i els paisatges modelats per aquestes, i contribuir a la millora socioeconòmica de les persones que la fan possible | F85: 08.1.1 | G85: Acompanyar i assessorar els productors agraris per millorar les tècniques productives agràries i afavorir la conservació dels hàbitats i paisatges | H85: 08.1.1 | I85: Comú | J85: Obligatori | K85: Assessorar i donar suport als agricultors i ramaders en l'aplicació de bones pràctiques per a la obtenció de bones produccions i qualitats i la conservació dels hàbitats i les espècies presents | L85: Canvi de redactat OP. Dirigit a agricultors i ramaders i s'afegeixen aspectes agronòmics | M85: Sí | O85: MÀXIMA | P85: *Manual tècnic de bones pràctiques en ramaderia extensiva i recuperació i manteniment de pastures en espais naturals protegits *Programa de suport tècnic a sector agrari *Promoció i assessorament sobre l'adhesió als distintius de qualitat ambiental existents | S85: 1) Fer recomanacions de maneig en els cultius extensius i les pastures per a la millora d'aspectes agronòmics i de conservació (àmbits de fertilització, sòl, qualitat farratgera, espècies vegetals, adaptació a CC, PAE...) | T85: 1) Nombre de recomanacions directes 2) Nombre de documents elaborats que incorporin recomanacions | U85: 1) 12 2) 8 | V85: 1) 24 2) 16 | W85: Mancaria marcar que "SI" que té mesures aplicables que depenen del PN a columna M. | X85: 995 | Y85: Patrimoni Agro | Z85: Bernat Perramon
F86: 08.1.2 | G86: Oferir formació als productors agraris per millorar el seu coneixement sobre tècniques eficients i respectuoses amb la conservació del patrimoni natural i cultural | H86: 08.1.2 | I86: Comú | J86: Obligatori | K86: Oferir formació a agricultors i ramaders per millorar el seu coneixement sobre tècniques eficients agronòmicament i respectuoses amb la conservació del patrimoni natural i cultural | L86: Canvi de redactat OP. Dirigit a agricultors i ramaders i s'afegeixen aspectes agronòmics | M86: Sí | O86: MÀXIMA | P86: *Programa de formació a sector primari | S86: 1) Organització i participació de jornades dirigides al sector primari per divulgar informació útil per al maneig i conservació de cultius i pastures | T86: 1) Nombre de jornades de formació que s'organitzen directament des del Parc Natural 2) nombre de jornades amb les que es participa des del Parc Natural però que s'organitzen per altres entitats 3) Nombre d'assistents. | U86: 1) 2 2) 2 3) 10 | V86: 1) 4 2) 4 2) 60 | W86: Mancaria marcar que "SI" que té mesures aplicables que depenen del PN a columna M. | Y86: Patrimoni Agro | Z86: Bernat Perramon
F87: 08.1.3 | G87: Promoure la recuperació i conservació de marges i punts d'aigua associats a la ramaderia i l'agricultura i d'interès per la biodiversitat | H87: 08.1.3 | I87: Específic | J87: Optatiu | K87: Promoure l'adequació d'edificacions, la recuperació de marges i la conservació de punts d'aigua associats a la ramaderia i l'agricultura d'interès per la biodiversitat | L87: Canvi de redactat OP. Inclusió d'edificacions rurals | M87: Sí | O87: ALTA | S87: 1) Fomentar que a través de la línia d'ajuts en espais protegits es recuperin punts d'aigua i marges de pedra seca i desenvolupar actuacions directes per aquest objectiu des del Parc Natural | T87: 1) Nombre d'actuacions que es porten a terme a partir de la línia d'ajuts 2) Nombre d'actuacions que es porten a terme directament des del Parc Natural | U87: 1) 4 2) 4 | V87: 1) 8 2) 8 | W87: Mancaria marcar que "SI" que té mesures aplicables que depenen del PN a columna M. | X87: 40 120 | Y87: Patrimoni Natural Patrimoni Forestal | Z87: Emili Bassols Joan Montserrat
D88: 08.2 | E88: Promoure la coordinació amb els agents socioeconòmics del territori pel foment del desenvolupament sostenible de l'espai (sector primari i secundari) | F88: 08.2.1 | G88: Establir una relació contínua amb agents socioeconòmics del territori, i si s'escau, crear una Taula de desenvolupament local | H88: 08.2.1 | K88: =G88 -> Establir una relació contínua amb agents socioeconòmics del territori, i si s'escau, crear una Taula de desenvolupament local | M88: Sí | O88: ALTA | P88: *Elaboració i actualització periòdica del mapa d’agents socioeconòmics de l’ENP (sector primari i secundari) *Establiment de canals de comunicació i coordinació amb els agents socioeconòmics clau del territori. *Estudi de la idoneïtat de crear una Taula de desenvolupament local, en els ENP que encara no ho tinguin (per ENP o agrupacions d’ENP). *Convocar les taules de desenvolupament local ja constituïdes de cada ENP (o agrupacions d’ENP). *Promoció i enfortiment de la participació dels agents clau a les taules de desenvolupament local ja constituïdes. *Participació en la definició i desplegament dels plans de treball de la taula de desenvolupament local. | Q88: ESNATURA | S88: 1) Col·laborar amb diferents agents del territori a través de col·laboracions i actuacions conjuntes 2) Pormoure una associació FET el Parc | T88: 1) Número de sectors amb els quals es col·labora (sector primari, sector turístic, sector forestal, caçadors...) 2) Número d'actuacions que es porten a terme amb diferents agents del territori | U88: 1) 4 2) 20 | V88: 2) 8 2) 40 | W88: Mancaria marcar que "SI" que té mesures aplicables que depenen del PN a columna M. | X88: 40 80 100 10 | Y88: Direcció Patrimoni Agro Turisme Patrimoni Natural | Z88: Joan Pijoan Bernat Perramon Arnau Dorca Emili Bassols
D89: 08.3 | E89: Millorar la valorització i comercialització dels productes generats a l'ENP que contribueixen al desenvolupament socioeconòmic i la conservació del patrimoni de l'ENP | F89: 08.3.1 | G89: Implantar un distintiu de qualitat i compatibilitat amb la conservació dels productes de la Xarxa d'ENP o criteris de qualitat propis de l'ENP | H89: 08.3.1 | I89: Comú | J89: Optatiu | K89: Implantar el distintiu Fet al Parc en els productes que provenen directament del sector primari i s'obtenen amb una activitat agrícola i ramadera beneficiosa pel territori | L89: Canvi de redactat OP. S'adapta al plantejament de Fet al Parc, un marc de col·laboració amb el sector agrari iniciat l'any 2019 | M89: Sí | O89: ALTA | P89: *Generació d'un segell comú per a tota la xarxa de Parcs (responsabilitat de SENP) *Establiment de criteris propis de l'ENP per poder facilitar identificació de productes de qualitat i respectuosos | Q89: ESNATURA | R89: SENP: Crear una marca que identifiqui els productes agroalimentaris generats en els ENP | S89: 1) Establir acords de col·laboració amb explotacions agràries i ramaderes en què s'estableixin una sèrie de requisits que incideixin en el manteniment dels hàbitats agraris en bones condicions agronòmiques i mediamenbientals 2)Incrementar el número d'explotacions que tenen un acord de col·laboració Fet al Parc amb el Parc Natural i identificar-lo amb una marca regulada normativament 3) Establir actuacions de difusió de l'activitat que porten a terme les explotacions que formen part de Fet al Parc (publicacions, rètols, vídeos, xarxes socials...) | T89: 1,2) Increment del nombre d'explotacions que formen part de Fet al Parc, que actualment és de 25, i establir acords de col·laboració amb les noves explotacions 3) Nombre d'accions a difondre | U89: 1,2)2 3)1 | V89: 1,2)5 3) 4 | W89: Mancaria marcar que "SI" que té mesures aplicables que depenen del PN a columna M. | X89: 600 | Y89: Patrimoni Agro | Z89: Bernat Perramon
F90: 08.3.2 | G90: Integrar els productes i activitats locals de qualitat en l'oferta d'activitats d'informació i turístiques de l'ENP | H90: 08.3.2 | I90: Comú | J90: Obligatori | K90: =G90 -> Integrar els productes i activitats locals de qualitat en l'oferta d'activitats d'informació i turístiques de l'ENP | M90: Sí | O90: MITJANA | P90: *Elaboració d'un catàleg de productors i artesans de l'ENP *Inclusió de visites a productors o artesans en el catàleg d'activitats de l'ENP | Q90: ESNATURA CETS | S90: 1) Incentivar que es portin a terme activitats per donar a conèixer les explotacions agràries i ramaderes, els productes que elaboren i el sistema productiu de la zona que es puguin integrar en l'oferta d'activitats d'informació i turisme 2) Incentivar que agricultors i ramaders que realitzin activitats s'acreditin amb la CETS | T90: 1) Nombre d'actuacions que es porten a terme per donar a conèixer el sector primari en activitats d'informació i turisme 2) Nombre d'actuacions que es porten a terme per donar a conìxer el projecte de Fet al Parc | U90: 1) 2 1) 2 | V90: 1) 8 2) 8 | W90: Mancaria marcar que "SI" que té mesures aplicables que depenen del PN a columna M. | X90: 50 50 | Y90: Patrimoni Agro Turisme / SIG | Z90: Bernat Perramon Arnau Dorca
F91: 08.3.3 | G91: Promoure fires d'artesania i productes locals de l'ENP | H91: 08.3.3 | I91: Comú | J91: Optatiu | K91: Col·laborar amb fires d'artesania i productes locals de l'ENP | L91: Canvi de redactat de l'OP. S'organitzen diverses fires a la zona amb l'opció de col·laborar-hi des del Parc Natural | M91: Sí | O91: MITJANA | S91: 1)Col·laborar amb les fires de la zona més significatives vetllant perquè es prioritzin els productes locals que provenen de les explotacions agràries i ramaderes de la zona i es doni a conèixer el projecte de Fet al Parc | T91: 1) Nombre de fires amb les quals es col·la bora 2) Nombre de fires amb què s'hi participa amb el projecte de Fet al Parc | U91: 1) 1 2) 1 | V91: 1) 3 2) 3 | W91: Mancaria marcar que "SI" que té mesures aplicables que depenen del PN a columna M. | X91: 45 | Y91: Patrimoni Agro | Z91: Bernat Perramon
F92: 08.3.4 | G92: Generar aliances entre el sector primari, el turisme, la restauració i altres per fomentar la gastronomia local | H92: 08.3.4 | I92: Comú | J92: Optatiu | K92: =G92 -> Generar aliances entre el sector primari, el turisme, la restauració i altres per fomentar la gastronomia local | M92: Sí | O92: ALTA | P92: *Creació i coordinació de jornades d'intercanvi *Creació d'espais de treball comú *Foment del treball per tenir infraestructura comuna (obrador comunitari) | Q92: ESNATURA CETS | S92: 1) Col·laborar amb Turisme Garrotxa i Garrotxa Hostalatge per desenvolupar actuacions conjuntes que permetin que el sector primari tingui una presència destacada en la gastronomia local i establir sinèrgies entre Fet al Parc i la CETS | T92: 1) Nombre d'actuacions que es desenvolupen en l'àmbit de Fet al Parc per promoure els productes locals en l'àmbit de la restauració 2) Nombre d'actuacions que es desenvolupen en col·laboració entre Fet al Parc i la CETS | U92: 1) 4 2) 4 | V92: 1) 8 2) 8 | W92: Mancaria marcar que "SI" que té mesures aplicables que depenen del PN a columna M. | X92: 40 200 | Y92: Turisme / SIG Patrimoni Agro | Z92: Arnau Dorca Bernat Perramon
F93: 08.3.5 | G93: Elaborar una diagnòsi del teixit productiu local i un pla d’acció amb línies de treball i actuacions concretes per donar-li suport | H93: 08.3.5 | I93: Comú | J93: Optatiu | K93: No aplica | L93: No es porta a terme perquè ja s'han fet moltes diagnosi i ara el que cal són actuacions per executar les línies de treball que es considerin més adients | P93: *Divulgació i comunicació, formació i assessorament tècnic, comercialització, treball en xarxa, suport a la gestió de l’activitat | Q93: ESNATURA | W93: Més que indicar "Fora de termini del pla" en aquest cas es podria considerar directament l'objetiu com a No aplicable a la columna K (canviat per NA) i deixar la columna de priorització buida.
F94: 08.3.6 | G94: Promoure els agents del territori que potencien i difonen els productes locals i de qualitat (artesanies, allotjaments, restaurants, cellers, establiments, elaboradors i productors) que afavoreixin la conservació | H94: 08.3.6 | I94: Comú | J94: Optatiu | K94: =G94 -> Promoure els agents del territori que potencien i difonen els productes locals i de qualitat (artesanies, allotjaments, restaurants, cellers, establiments, elaboradors i productors) que afavoreixin la conservació | M94: Sí | O94: ALTA | P94: *Projecte Parcs a taula | S94: 1) Donar a conèixer i acostar Fet al Parc als agents locals perquè aquests puguin donar a conèixer el projecte de Fet al Parc | T94: 1) Nombre d'actuacions en què els agents locals difonen Fet al Parc entre el sector turístic o la població local 2) Nombre d'actuacions en què els establiments de la CETS difonen Fet al Parc entre el sector turístic o la població local | U94: 1) 2 2) 2 | V94: 1) 4 2) 4 | W94: Mancaria marcar que "SI" que té mesures aplicables que depenen del PN a columna M. | X94: 125 | Y94: Patrimoni Agro | Z94: Bernat Perramon
D95: 08.4 | E95: Contribuir a una correcta planificació i gestió dels recursos cinegètics i piscícoles de forma compatible amb els valors de l'ENP | F95: 08.4.1 | G95: Treballar amb l'autoritat competent per garantir objectius de conservació d’espècies i hàbitats en la revisió dels Plans de Gestió Cinegètica | H95: 08.4.1 | I95: Comú | J95: Obligatori | K95: =G95 -> Treballar amb l'autoritat competent per garantir objectius de conservació d’espècies i hàbitats en la revisió dels Plans de Gestió Cinegètica | M95: Sí | O95: ALTA | P95: *Foment d'acords amb les Societats de Caçadors per a incorporar objectius de conservació d’espècies i hàbitats en la revisió dels Plans de Gestió Cinegètica | Q95: MAP | S95: 1) Elaboració d'informes preceptius previs a l'aprovació dels Plans Tècnics de Millora Cinegètica. 2) Establiment de contactes periòdics amb les societats de caçadors locals. | T95: 1) Percentatge de Plans de Gestió Cinegètica revisats 2) Nombre de reunions | U95: 1) 100% 2) 1 | V95: 1) 100% 2) 4 | W95: Mancaria marcar que "SI" que té mesures aplicables que depenen del PN a columna M. | X95: 80 | Y95: Patrimoni Natural | Z95: Emili Bassols
F96: 08.4.2 | G96: Col·laborar en la regulació i ordenació de la caça i la pesca en zones sensibles o amb risc d'afectació d'elements clau objecte de conservació | H96: 08.4.2 | I96: Comú | J96: Obligatori | K96: =G96 -> Col·laborar en la regulació i ordenació de la caça i la pesca en zones sensibles o amb risc d'afectació d'elements clau objecte de conservació | M96: Sí | O96: ALTA | P96: *Impuls a la declaració de refugis de caça i pesca *Foment de la implicació dels caçadors i pescadors del territori en la conservació dels valors de l'espai | Q96: MAP | S96: 1) Coordinació tècnica amb l'Àrea d'Activitats Cinegètiques dels Serveis Territorials de Girona. 2) Elaboració d'informes preceptius previs a l'autorització d'actuacions excepcionals. | T96: 1) Nombre d'actuacions i regulacions executades. 2) Percentatge d'informes realitzats | U96: 1) 1 2) 100% | V96: 1) 4 2) 100% | W96: Mancaria marcar que "SI" que té mesures aplicables que depenen del PN a columna M. | Y96: Patrimoni Natural | Z96: Emili Bassols
F97: 08.4.3 | G97: Donar suport en la gestió de poblacions que generen danys a les activitats econòmiques de l'ENP | H97: 08.4.3 | I97: Comú | J97: Obligatori | K97: =G97 -> Donar suport en la gestió de poblacions que generen danys a les activitats econòmiques de l'ENP | M97: Sí | P97: *Gestió directa d'ungulats (protecció de conreus, cooperació amb carreteres, etc.) a partir d'un procediment d’aplicació del control d'ungulats *Acords amb caçadors de la APC *Foment d’actuacions per prevenció de col·lisions amb vehicles d'acord amb titulars de les carreteres | S97: 1) Seguiment d'espècies de caça major que provoquen danys i col·laboració en l'assaig de proves per minimitzar el seu impacte sobre l'agricultura. | T97: 1) Nombre de seguiments | U97: 1) 1 | V97: 1) 4 | W97: Mancaria marcar que "SI" que té mesures aplicables que depenen del PN a columna M. Falta indicar la prioritat | X97: 40
B98: 9 | C98: FOMENTAR UN TURISME SOSTENIBLE compatible amb la conservació de l'espai | D98: 09.1 | E98: Fomentar un model de turisme que promogui els valors dels espais naturals protegits d'acord amb els agents turístics del territori | F98: 09.1.1 | G98: Desplegar la Carta Europea de Turisme Sostenible (CETS) | H98: 09.1.1 | I98: Comú | J98: Optatiu | K98: =G98 -> Desplegar la Carta Europea de Turisme Sostenible (CETS) | M98: Sí | O98: MÀXIMA | Q98: ESNATURA | S98: 1) Redacció del nou dossier CETS pel període 2026-2030 2) Participació i gestió de la metodologia de treball Agility (OKR) 3) Participació com a vocal al Fòrum permanent de la CETS (Junta i Assamblea de Turisme Garrotxa) 4) Coordinació i gestió de la CETS a nivell comarcal 5) Difondre i presentar la CETS PN Garrotxa a nivell nacional i internacional. 6) Participar com a membre del grup "Evaluación Fase III CETS" 7) Contractació d'un assessorament tècnic 8) Participació com a representant dels ENPE de comarques gironines dins el Consell assessor del Patronat de Turisme Costa Brava Pirineus de Girona 9) Treballar de forma conjunta amb projectes comuns entre Parc Natural i Turisme Garrotxa 10) Participació com a membre de la Taula d'ecoturisme de Catalunya | T98: 1) Dossier presentat (memòria, estratègia i programa d'actuació) 2) Nombre d'equips OKR implementats i nombre de reunions assistides 3) Nombre de reunions assistides 4) Nombre de reunions realitzades 5) Nombre de presentacions a jornades / congresos 6) Nombre d'informes realitzats 7) Contractes realitzats 8) Nombre de sessions del Consell assistides 9) Nombre de projectes realitzats 10) Percentatge de sessions assistides | U98: 1) 1 2) 4/15 3) 7 4)20 5) 2 6) 1 7) 1 8) 1 9) 2 10) 50 | V98: 1) 1 2) 7/20 3) 12 4) 35 5) 5 6) 3 7) 1 8) 4 9) 5 10) 100 | X98: 950 | Y98: Turisme / SIG | Z98: Arnau Dorca
F99: 09.1.2 | G99: Tramitar la certificació Biosphere | H99: 09.1.2 | I99: Comú | J99: Optatiu | K99: No aplica | L99: Acord amb els diferents agents de la comarca a dia d'avui no es creu convenient apostar per aquesta certifiació. L'aposta de la Garrotxa des de l'any 2001 és per la CETS. | W99: Més que indicar "Fora de termini del pla" en aquest cas es podria considerar directament l'objetiu com a No aplicable a la columna K (canviat per NA) i deixar la columna de priorització buida.
F100: 09.1.3 | G100: Fomentar la creació d'allotjaments i altres recursos turístics d'acord amb les necessitats i els agents turístics del territori que es vinculin als valors naturals de l'espai | H100: 09.1.3 | I100: Comú | J100: Optatiu | K100: Fomentar la creació de recursos turístics d'acord amb les necessitats i els agents turístics del territori que es vinculin als valors naturals de l'espai | M100: Sí | N100: No | O100: ALTA | S100: 1) Crear recursos d'acord amb els criteris d'accessibilitat universal. 2) Informar / autoritzar nous recursos turístics presentats per empreses. | T100: 1) Nombre de recursos creats 2) Nombre de recursos informats | U100: 1) 1 1) 1 | V100: 1) 1 1) 2 | X100: 100 | Y100: Turisme / SIG | Z100: Arnau Dorca
...

Sheet Hores
B1: Gerard | C1: Manteniment | D1: Montse | E1: Emili | F1: Bernat | G1: Joan Montserrat | H1: Xavier Oliver | I1: Arnau Dorca | J1: Joan Pijoan | K1: Eva Calm | L1: Josep Riera | M1: Hores | N1: 1688x4= 6752
D2: 980 | E2: 420 | F2: 220 | G2: 420 | H2: 85 | I2: 75 | J2: 100 | K2: 880 | L2: 50
D3: 150 | E3: 150 | F3: 160 | G3: 120 | H3: 152 | I3: 145 | J3: 225 | K3: 50 | L3: 300
D4: 300 | E4: 320 | F4: 280 | G4: 145 | H4: 250 | I4: 280 | J4: 120 | K4: 300 | L4: 400
D5: 800 | E5: 160 | F5: 150 | G5: 150 | H5: 300 | I5: 150 | J5: 135 | K5: 400 | L5: 350
D6: 750 | E6: 380 | F6: 120 | G6: 120 | H6: 190 | I6: 85 | J6: 320 | K6: 350 | L6: 200
D7: 850 | E7: 225 | F7: 135 | G7: 135 | H7: 40 | I7: 140 | J7: 300 | K7: 200 | L7: 450
D8: 300 | E8: 225 | F8: 105 | G8: 680 | H8: 60 | I8: 250 | J8: 400 | K8: 450 | L8: 400
D9: 1072 | E9: 120 | F9: 90 | G9: 595 | H9: 300 | I9: 300 | J9: 50 | K9: 400 | L9: 250
D10: 350 | E10: 135 | F10: 680 | G10: 400 | H10: 380 | I10: 350 | J10: 800 | K10: 250 | L10: 300
D11: 400 | E11: 150 | F11: 280 | G11: 690 | H11: 80 | I11: 300 | J11: 200 | K11: 300
D12: 800 | E12: 480 | F12: 450 | G12: 125 | H12: 80 | I12: 40 | J12: 200
E13: 250 | F13: 450 | G13: 140 | H13: 80 | I13: 500 | J13: 40
E14: 100 | F14: 50 | G14: 498 | H14: 150 | I14: 200 | J14: 450
E15: 180 | F15: 995 | G15: 400 | H15: 150 | I15: 200 | J15: 40
E16: 225 | F16: 80 | G16: 120 | H16: 150 | I16: 250 | J16: 262
E17: 75 | F17: 600 | G17: 40 | H17: 150 | I17: 217 | J17: 300
E18: 320 | F18: 50 | G18: 100 | H18: 150 | I18: 100 | J18: 180
E19: 150 | F19: 45 | G19: 100 | H19: 50 | I19: 50 | J19: 60
E20: 177 | F20: 125 | H20: 80 | I20: 950 | J20: 250
E21: 300 | F21: 200 | H21: 200 | I21: 100 | J21: 40
E22: 150 | F22: 40 | H22: 100 | I22: 120 | J22: 45
E23: 450 | F23: 150 | H23: 450 | I23: 400 | J23: 40
E24: 450 | H24: 400 | I24: 80 | J24: 50
E25: 200 | H25: 40 | I25: 50 | J25: 20
E26: 50 | H26: 50 | J26: 150
E27: 75 | H27: 150 | I27: 10 | J27: 40
E28: 20 | H28: 40 | I28: 40 | J28: 80
E29: 150 | H29: 20 | I29: 100 | J29: 80
E30: 20 | H30: 20 | I30: 300 | J30: 125
E31: 50 | H31: 25 | I31: 20 | J31: 20
E32: 45 | H32: 80 | I32: 40 | J32: 50
E33: 40 | H33: 40 | I33: 80 | J33: 10
E34: 40 | H34: 20 | I34: 20 | J34: 100
E35: 10 | H35: 40 | I35: 40 | J35: 40
E36: 80 | H36: 575 | I36: 60 | J36: 100
E37: 40 | H37: 80 | I37: 40 | J37: 60
E38: 200 | H38: 100 | I38: 90 | J38: 200
... E41: 60 | H41: 40 | I41: 40 | J41: 300
H42: 100 | I42: 150 | J42: 200
H43: 40 | I43: 100 | J43: 80
H44: 300 | I44: 50 | J44: 200
H45: 80 | I45: 80 | J45: 100
H46: 30 | J46: 40
H47: 50 | J47: 50
H48: 70
H49: 40
H50: 40
H51: 40
H52: 65
H53: 80
H54: 10
H55: 40
H56: 60
H57: 30
H58: 50
H59: 80 | P59: =H63-6752 -> -685
B63: =SUM(B2:B40) -> 0 | C63: =SUM(C2:C40) -> 0 | D63: =SUM(D2:D45) -> 6752 | E63: =SUM(E2:E45) -> 6752 | F63: =SUM(F2:F45) -> 5455 | G63: =SUM(G2:G45) -> 4978 | H63: =SUM(H2:H45) -> 6067 | I63: =SUM(I2:I45) -> 6752 | J63: =SUM(J2:J45) -> 6752 | K63: =SUM(K2:K45) -> 3580 | L63: =SUM(L2:L45) -> 2700
O64: 6752
G66: =D63-O64 -> 0
G70: =E63-O64 -> 0 | J70: =400-223 -> 177

Sheet PLA
A1: MODEL DE PLA ESTRATÈGIC PELS ENP
B2: Espai natural protegit: | C2: Zona Volcànica de la Garrotxa
Q3: Exemples d'accions | V3: Fita a assolir en 4 anys | X3: Calendarització interna | AC3: Gestió interna | AF3: Gestió externa
A4: EIXOS | C4: Objectius generals (PP) | E4: Objectius estratègics | G4: Objectius operatius | H4: Comú / Específic | I4: Obligatori / Optatiu | J4: Marc de referència | K4: Resultats derivats | L4: Objectius operatius PNZVG | M4: Justificació del canvi o no inclusió d'un OP | N4: Objectiu aplicable amb accions que depenen directament del PNZVG | O4: Objectiu aplicable amb accions que depenen directament de la Direcció General de PAMN | P4: Prioritat | Q4: Propostes genèriques d'accions | R4: Mesures MAP | S4: Mesures Pla Especial ZVG | T4: Mesures d'altres plans | U4: Indicadors | V4: Mínima | W4: Màxim (Desitjable) | X4: Executat | Y4: 2025 | Z4: 2026 | AA4: 2027 | AB4: 2028 | AC4: Hores de dedicació | AD4: Àrea responsable | AE4: Persona responsable | AF4: Pressupost (€) | AG4: Contractació externa | AH4: Competència DG
A5: NATURA | B5: 1 | C5: CONSERVAR LA NATURA i restaurar els ecosistemes, els processos naturals i seminaturals, la biodiversitat i la geodiversitat associada. | D5: 01.1 | E5: Adequar i fer eficient la conservació dels elements objecte de gestió prioritària marcats per la DG a l'ENP | F5: 01.1.1 | G5: Implementar i executar plans de gestió específics per a hàbitats i espècies de conservació prioritària dins l'ENP | H5: Comú | I5: Obligatori | J5: MAP | K5: SFF: Elaboració de plans de gestió específics per a espècies de conservació prioritària i directrius de gestió d'hàbitats. SFF/SENP: Definir a nivell de cluster quins son els que es poden elaborar conjuntament. | L5: =G5 -> Implementar i executar plans de gestió específics per a hàbitats i espècies de conservació prioritària dins l'ENP | Q5: *Realització d'accions per a la millora dels elements prioritzats a l'espai *Elaboració de plans de gestió per elements prioritzats a l'espai
F6: 01.1.2 | G6: Adaptar i executar plans de gestió específics per a elements geològics de conservació prioritària dins l'ENP | H6: Comú | I6: Obligatori | L6: =G6 -> Adaptar i executar plans de gestió específics per a elements geològics de conservació prioritària dins l'ENP | Q6: * Elaboració de l'inventari d'elements geològics a l'espai *Aplicació de les directrius de gestió de l'inventari de patrimoni geològic (ICGC)
D7: 01.2 | E7: Executar les mesures de gestió directa previstes en els intruments de planificació per la conservació i la gestió adaptativa dels elements clau de l'ENP | F7: 01.2.1 | G7: Implementar la metodologia de gestió adaptativa (Estàndards Oberts de Gestió Adaptativa a Catalunya) en tots els processos de l'ENP | H7: Comú | I7: Obligatori | J7: ESNATURA | K7: SENP: Elaboració d'un manual per la implementació dels OSAM | L7: =G7 -> Implementar la metodologia de gestió adaptativa (Estàndards Oberts de Gestió Adaptativa a Catalunya) en tots els processos de l'ENP | Q7: *Definició d'un protocol per tal d'incorporar la metodologia dels Estàndards Oberts pels processos més rellevants per a la conservació a l'espai
F8: 01.2.2 | G8: Executar les mesures previstes en els plans de conservació o recuperació d'espècies amenaçades de forma coordinada amb el Servei de Flora i Fauna en l'àmbit de l'ENP | H8: Comú | I8: Obligatori | J8: MAP Catàlegs | K8: SFF: Elaboració de plans de conservació o recuperació d'espècies protegides | L8: =G8 -> Executar les mesures previstes en els plans de conservació o recuperació d'espècies amenaçades de forma coordinada amb el Servei de Flora i Fauna en l'àmbit de l'ENP | Q8: * Implicació i participació en la redacció dels plans de conservació /recuperació d'espècies amenaçades * Execució de les accions dins els plans que pertoquin a cada espai (incorporar totes les mesures que surten als plans ja aprovats que tenen incidència a l'espai) * Col.laboració en l'obtenció de la informació necessària dins els espais per al desenvolupament dels Plans
F9: 01.2.3 | G9: Executar les mesures de gestió previstes en els plans de control i erradicació d'espècies exòtiques de forma coordinada amb el Servei de Flora i Fauna en l'àmbit de l'ENP | H9: Comú | I9: Obligatori | J9: ESNATURA MAP | K9: SFF: Elaboració de plans de control i erradicació d'espècies exòtiques | L9: =G9 -> Executar les mesures de gestió previstes en els plans de control i erradicació d'espècies exòtiques de forma coordinada amb el Servei de Flora i Fauna en l'àmbit de l'ENP | Q9: * Implicació i participació en la redacció (cal identificar els plans que estan ja en marxa o previstos i posar les mesures concretes) * Execució de les accions dins els plans que pertoquin a cada espai * Col.laboració en l'obtenció de la informació necessària dins els espais per al desenvolupament dels Plans
F10: 01.2.4 | G10: Desplegar els objectius i tasques recollits en els instruments de referència i compromisos internacionals | H10: Específic | I10: Optatiu | L10: =G10 -> Desplegar els objectius i tasques recollits en els instruments de referència i compromisos internacionals | Q10: * Desplegament dels objectius recollits en l'Estratègia de la Xarxa d'àrees marines protegides del Mediterrani (MedPAN network) * Col·laboració en el compliment dels objectius i tasques derivats de la Mediterranean Climate Action Partnership en matèria de biodiversitat i canvi climàtic i els seus impactes sobre la sequera, calor i incendis * Col·laboració en la implementació pràctica de projectes de l'àrea internacional i dels compromisos amb les entitats membres UICN, Euroregió Pirineus Mediterrània
D11: 01.3 | E11: Crear ecosistemes complexes, resilients, i d'alta biodiversitat per garantir la recuperació dels processos ecosistèmics | F11: 01.3.1 | G11: Identificar espais pel foment de la dinàmica natural i l'aprofitament no extractiu | H11: Comú | I11: Obligatori | J11: ESNATURA | K11: SENP/SFF: Definir criteris metodològics | L11: =G11 -> Identificar espais pel foment de la dinàmica natural i l'aprofitament no extractiu | Q11: *Participar en la identificació d'espais pel foment de la dinàmica natural i l'aprofitament no extractiu dins l'ENP en base a uns criteris metodològics predefinits *Afavorir la creació d'hàbitats per a la conservació d'espècies
F12: 01.3.2 | G12: Afavorir la maduresa dels sistemes forestals | H12: Específic | I12: Optatiu | J12: MAP | K12: SENP/SFF: Definir criteris metodològics | L12: =G12 -> Afavorir la maduresa dels sistemes forestals | Q12: *Participar i impulsar la planificació i execució d'accions d'acceleració de la maduresa forestal en zones boscoses dins l'ENP en base als criteris metodològics predefinits
F13: 01.3.3 | G13: Generar pertorbacions controlades | H13: Específic | I13: Optatiu | J13: MAP | K13: SENP/SFF: Definir criteris metodològics | L13: =G13 -> Generar pertorbacions controlades | Q13: *Elaboració d'una planificació d'actuacions de simulació d'incendis forestals naturals (cremes controlades) dins l'espai en base als criteris metodològics predefinits. *Realització dels estudis necessaris i participació en la reintroducció de grans herbívors, carnívors o carronyaires dins l'ENP en base als criteris metodològics predefinits.
F14: 01.3.4 | G14: Restaurar la dinàmica natural dels rius | H14: Específic | I14: Optatiu | J14: MAP | K14: SENP/SFF: Definir criteris metodològics | L14: =G14 -> Restaurar la dinàmica natural dels rius | Q14: *Realització i impuls de la renaturalització de lleres i creació de zones de laminació dins l'ENP en base als criteris metodològics predefinits
F15: 01.3.5 | G15: Fomentar el paisatge en mosaïc | H15: Específic | I15: Optatiu | J15: ESNATURA | K15: SENP/SFF: Definir criteris metodològics | L15: =G15 -> Fomentar el paisatge en mosaïc | Q15: *Realització d'accions per gestionar l'herbivoria domèstica associada a la ramaderia extensiva *Aplicació dels criteris metodològics predefinits en un manual tècnic de bones pràctiques en ramaderia extensiva i recuperació i manteniment de pastures aplicat a l'ENP. *Coordinació i gestió dels ramats locals en actuacions de restauració de pastures i desembosc.
F16: 01.3.6 | G16: Gestionar i intervenir en la dinàmica de poblacions de fauna que no tenen depredador natural | H16: Específic | I16: Optatiu | K16: SENP/SFF: Definir criteris metodològics | L16: =G16 -> Gestionar i intervenir en la dinàmica de poblacions de fauna que no tenen depredador natural | Q16: *Realització d'acords amb societats de caçadors. *Participació i impuls del control directe de poblacions de fauna en base als criteris metodològics predefinits.
D18: 01.4 | E18: Alinear l'activitat de propietaris i gestors del territori amb la conservació, millora i restauració dels valors de l'ENP | F18: 01.4.1 | G18: Fomentar acords de custòdia en espais d'alt valor dins l'ENP per a la gestió dels elements prioritaris | H18: Comú | I18: Optatiu | J18: MAP | K18: SENP/SENP: Dissenyar el protocol i elaborar un model d'acord | L18: =G18 -> Fomentar acords de custòdia en espais d'alt valor dins l'ENP per a la gestió dels elements prioritaris | Q18: *Realització d'acords de custòdia aplicant el model d'acord elaborat per Serveis Centrals
F19: 01.4.2 | G19: Fomentar bones pràctiques entre els col·lectius de propietaris i gestors del territori | H19: Comú | I19: Optatiu | L19: =G19 -> Fomentar bones pràctiques entre els col·lectius de propietaris i gestors del territori | Q19: *Realització d'actuacions demostratives en finques pròpies per al foment de bones pràctiques
F20: 01.4.3 | G20: Impulsar la coordinació amb els ens locals en la gestió finques públiques situades dins d’ENP | H20: Específic | I20: Optatiu | J20: ESNATURA | L20: =G20 -> Impulsar la coordinació amb els ens locals en la gestió finques públiques situades dins d’ENP | Q20: *Boscos comunals *Medi marí *Lleres i boscos de ribera
B21: 2 | C21: ADAPTAR ELS ECOSISTEMES AL CANVI CLIMÀTIC i millorar-ne la resiliència en front dels riscos associats. | D21: 02.1 | E21: Planificar l'adaptació dels sistemes naturals al canvi climàtic | F21: 02.1.1 | G21: Adaptar i implementar el Pla d'adaptació de l'ENP al canvi climàtic | H21: Comú | I21: Obligatori | K21: OCCC/SENP: Elaboració del model de Pla d'adaptació dels ENP al canvi climàtic | L21: =G21 -> Adaptar i implementar el Pla d'adaptació de l'ENP al canvi climàtic | Q21: *Planificació del sistema d'espais oberts *Creació de zones de laminació per defensa de inundacions *Creació i manteniment d'espais dunars de protecció de temporals
F22: 02.1.2 | G22: Gestionar i planificar els recursos hídrics de l'ENP | H22: Comú | I22: Obligatori | L22: =G22 -> Gestionar i planificar els recursos hídrics de l'ENP
F23: 02.1.3 | G23: Participar en la redacció i execució dels instruments d'ordenació forestal sostenible i per la conservació en finques públiques | H23: Específic | I23: Optatiu | K23: DGEFMN: Redacció d'IOF en finques públiques | L23: =G23 -> Participar en la redacció i execució dels instruments d'ordenació forestal sostenible i per la conservació en finques públiques | Q23: *Participació en la redacció d'IOF de finques públiques *Realització d'accions demostratives en finca pública o amb acord de custòdia *Realització de tractaments silvícoles i tallades selectives *Promoció de boscos mixtes i de la biodiversitat
F24: 02.1.4 | G24: Promoure la redacció d'instruments d'ordenació forestal per reduir la sensibilitat i vulnerabilitat dels boscos al canvi climàtic en finques privades | H24: Específic | I24: Optatiu | L24: =G24 -> Promoure la redacció d'instruments d'ordenació forestal per reduir la sensibilitat i vulnerabilitat dels boscos al canvi climàtic en finques privades | Q24: * Realització d'accions per donar a conèixer subvencions entre propietaris
D25: 02.2 | E25: Planificar la prevenció i extinció d’incendis forestals i la gestió del foc de forma coordinada amb els diferents agents del territori | F25: 02.2.1 | G25: Redactar i implementar el Pla de Prevenció d'Incendis | H25: Comú | I25: Obligatori | J25: ESNATURA | K25: Equip de PPI: Disseny del protocol de treball | L25: =G25 -> Redactar i implementar el Pla de Prevenció d'Incendis | Q25: *Elaboració del Pla de Prevenció d'Incendis *Definició de: xarxa estratègica i complementària de vials forestals, xarxa estratègica i complementària de punts d’aigua, tractaments de vegetació, punts estratègics de gestió
F26: 02.2.2 | G26: Definir i planificar la gestió del foc per a la millora de l'ENP | H26: Específic | I26: Optatiu | K26: SPEN: Elaboració d'un model de pla de gestió | L26: =G26 -> Definir i planificar la gestió del foc per a la millora de l'ENP | Q26: *Pla de gestió de foc *Pla de gestió de cremes
F27: 02.2.3 | G27: Treballar per a la prevenció d'incendis juntament amb els propietaris, ajuntaments, protecció civil, ADF i bombers. | H27: Comú | I27: Obligatori | L27: =G27 -> Treballar per a la prevenció d'incendis juntament amb els propietaris, ajuntaments, protecció civil, ADF i bombers.
B28: 3 | C28: PROTEGIR LA BIODIVERSITAT, i especialment els elements fràgils i amenaçats, d’interès comunitari o de major interès natural. | D28: 03.1 | E28: Prevenir, minimitzar i compensar els impactes ambientals dels usos i activitats que es desenvolupin en l'àmbit de l'ENP | F28: 03.1.1 | G28: Participar en les consultes dels procesos d'Avaluació Ambiental que afectin directament o indirectament l’espai del ENP | H28: Comú | I28: Obligatori | L28: =G28 -> Participar en les consultes dels procesos d'Avaluació Ambiental que afectin directament o indirectament l’espai del ENP
F29: 03.1.2 | G29: Exercir un seguiment efectiu de les obres al Parc juntament amb les Oficines Territorials d'Acció i Avaluació Ambiental als efectes d'assegurar la correcta translació de la tutela administrativa. | H29: Comú | I29: Obligatori | L29: =G29 -> Exercir un seguiment efectiu de les obres al Parc juntament amb les Oficines Territorials d'Acció i Avaluació Ambiental als efectes d'assegurar la correcta translació de la tutela administrativa.
F30: 03.1.3 | G30: Participar en la compensació d'impactes residuals durant els processos d'avaluació ambiental mitjançant la identificació de necessitats d'actuació prioritària dins i fora dels límits de l’ENP | H30: Comú | I30: Optatiu | L30: =G30 -> Participar en la compensació d'impactes residuals durant els processos d'avaluació ambiental mitjançant la identificació de necessitats d'actuació prioritària dins i fora dels límits de l’ENP | Q30: *Catàleg de possibles actuacions compensatories *Catàleg de sectors amb necessitats d'intervenció (incloent també zones fora dels límits de l'ENP que es considerin importants per al manteniment de la connectivitat ecològica dels espais)
D31: 03.2 | E31: Garantir el compliment dels objectius de conservació dotant l'ENP de la planificació adequada segons estableix la normativa vigent (Pla de Protecció, PRUG, plans específics...) | F31: 03.2.1 | G31: Participar en l'elaboració dels instruments de planificació de l'ENP | H31: Comú | I31: Obligatori | K31: SPEN: Elaboració del Pla rector d'usos i gestió. SPEN: Elaboració del Pla rector d'usos i gestió | L31: =G31 -> Participar en l'elaboració dels instruments de planificació de l'ENP | Q31: *Participació en l'elaboració del Pla de Protecció (PP) juntament amb l'SPEN. *Participació en l'elaboració del Pla Rector d'usos i Gestió (PRUG) juntament amb l'SPEN. *Participació en l'elaboració d'altres instruments de planificació juntament amb l'SPEN.
D32: 03.3 | E32: Vetllar pel manteniment dels cabals ecològics i la bona qualitat dels cursos fluvials de l'ENP de forma coordinada amb l'administració competent | F32: 03.3.1 | G32: Vetllar pel manteniment del cabal ecològic dels rius definit al Pla sectorial corresponent | H32: Específic | I32: Optatiu | J32: ESNATURA | K32: ACA/CHE: Determinar els cabals ecològics en espais naturals protegits | L32: =G32 -> Vetllar pel manteniment del cabal ecològic dels rius definit al Pla sectorial corresponent | Q32: *Participació en el seguiment del cabal en els trams dins ENP *Impuls del control per incompliment de la normativa i el seu trasllat cap a l'administració competent *Participació en les negociacions sectorials amb incidència a l'espai *Participació en les comissions de desembassament
F33: 03.3.2 | G33: Vetllar per la regulació dels dragatges, canalitzacions o implantació d'activitats extractives que puguin modificar la llera i el cabal dels rius | H33: Específic | I33: Optatiu | L33: =G33 -> Vetllar per la regulació dels dragatges, canalitzacions o implantació d'activitats extractives que puguin modificar la llera i el cabal dels rius
F34: 03.3.3 | G34: Avaluar i controlar les actuacions que produeixin drenatges, captacions o que puguin impedir l’arribada d’aigua tant superficial com freàtica | H34: Específic | I34: Optatiu | L34: =G34 -> Avaluar i controlar les actuacions que produeixin drenatges, captacions o que puguin impedir l’arribada d’aigua tant superficial com freàtica | Q34: *Participació, de forma coordinada amb l'administració competent, en l'avaluació i control d'actuacions dins els límits de l'ENP. *Impuls del control per incompliment de la normativa i el seu trasllat cap a l'administració competent *Participació en les comunitats d'usuaris de les conques
F35: 03.3.4 | G35: Vetllar pel compliment de la normativa de depuració dels efluents agroramaders, urbans i industrials que s'aboquen als cursos fluvials | H35: Específic | I35: Optatiu | L35: =G35 -> Vetllar pel compliment de la normativa de depuració dels efluents agroramaders, urbans i industrials que s'aboquen als cursos fluvials | Q35: *Impuls del control per incompliment de la normativa i el seu trasllat cap a l'administració competent
D36: 03.4 | E36: Incrementar el patrimoni públic destinat a la conservació i millora del patrimoni natural | F36: 03.4.1 | G36: Identificar espais prioritaris per a la compra de terrenys de més valor dins l'ENP | H36: Comú | I36: Optatiu | K36: SENP/SPEN: Facilitar els criteris a seguir | L36: =G36 -> Identificar espais prioritaris per a la compra de terrenys de més valor dins l'ENP | Q36: *Participació en la identificació de finques prioritàries en base als criteris indicats
F37: 03.4.2 | G37: Identificar espais prioritaris per a la gestió directa | H37: Comú | I37: Optatiu | K37: SENP/SPEN: Facilitar els criteris a seguir | L37: =G37 -> Identificar espais prioritaris per a la gestió directa | Q37: *Participació en la identificació de finques prioritàries en base als criteris indicats *Participació i foment de la compra o adquisició de drets d’aprofitament
A38: CULTURA | B38: 4 | C38: CONSERVAR ELS ELEMENTS CULTURALS materials i immaterials vinculats a la natura | D38: 04.1 | E38: Millorar el coneixement disponible sobre el patrimoni arquitectònic i cultural (material i immaterial) vinculat al patrimoni natural, el seu estat de conservació i els estils propis dels territoris de l'ENP | F38: 04.1.1 | G38: Elaborar l'inventari i cartografia de patrimoni cultural de l'ENP, que també inclogui el patrimoni etnològic i immaterial | H38: Comú | I38: Optatiu | L38: =G38 -> Elaborar l'inventari i cartografia de patrimoni cultural de l'ENP, que també inclogui el patrimoni etnològic i immaterial | Q38: *Recopilació de la informació dels catàlegs dels ajuntaments de l'ENP i fer diagnosi *Inventari de patrimoni cultural material *Inventari de patrimoni cultural immaterial (metodologia de l'inventari de la unesco) *Elaboració d'un mapa de tranquil·litat.
F39: 04.1.2 | G39: Elaborar el catàleg lingüístic (localismes) de patrimoni natural, geografia popular, festes i activitats tradicionals de l'ENP | H39: Comú | I39: Optatiu | L39: =G39 -> Elaborar el catàleg lingüístic (localismes) de patrimoni natural, geografia popular, festes i activitats tradicionals de l'ENP
F40: 04.1.3 | G40: Elaborar la cartografia de la xarxa de camins ramaders i senders tradicionals de l'ENP | H40: Comú | I40: Optatiu | L40: =G40 -> Elaborar la cartografia de la xarxa de camins ramaders i senders tradicionals de l'ENP
D41: 04.2 | E41: Conservar i gestionar el patrimoni cultural de l'ENP de forma coordinada amb els agents responsables i entitats de referència | F41: 04.2.1 | G41: Identificar els ens de referència en patrimoni cultural (entitats, associacions, museus i ecomuseus, etc.) en l'àmbit de l'ENP | H41: Comú | I41: Obligatori | L41: =G41 -> Identificar els ens de referència en patrimoni cultural (entitats, associacions, museus i ecomuseus, etc.) en l'àmbit de l'ENP | Q41: *Elaboració d'un mapa d'entitats, associacions, museus, ecomuseus, OPEI (Observatori del Patrimoni Etnològic i Immaterial), etc.
F42: 04.2.2 | G42: Articular treballs conjunts entre l'ENP i representants, gestors o custodis del patrimoni cultural per a la seva protecció i millora | H42: Comú | I42: Optatiu | L42: =G42 -> Articular treballs conjunts entre l'ENP i representants, gestors o custodis del patrimoni cultural per a la seva protecció i millora | Q42: *Projecte parcs i museus *Impulsa dels convenis de col·laboració aamb la xarxa de museus i altres equipaments i entitats de referència *Foment de la cooperació tècnica dels gestors de l'ENP amb els representants o custodis del patrimoni cultural, i coordinar-ne l'ús compartit dels recursos
F43: 04.2.3 | G43: Coordinar i participar dels treballs de restauració arquitectònica i del patrimoni cultural | H43: Comú | I43: Optatiu | L43: =G43 -> Coordinar i participar dels treballs de restauració arquitectònica i del patrimoni cultural | Q43: *Coordinació de l'equip tècnic (propi) amb els responsables dels treballs de restauració arquitectònica i del patrimoni cultural Participació quan els treballs estan vinculats a l’àrea d’ús públic de l’ENP
F44: 04.2.4 | G44: Disposar de personal especialitzat en patrimoni cultural | H44: Comú | I44: Obligatori | L44: =G44 -> Disposar de personal especialitzat en patrimoni cultural | Q44: *Formació del personal tècnic de l'ENP en la gestió i conservació dels valors culturals de l'ENP
D45: 04.3 | E45: Potenciar la conservació i recuperació del patrimoni cultural material i immaterial de l'ENP | F45: 04.3.1 | G45: Recuperar i conservar el patrimoni cultural rural immaterial associat a les activitats i aprofitaments tradicionals | H45: Comú | I45: Obligatori | J45: MAP | L45: =G45 -> Recuperar i conservar el patrimoni cultural rural immaterial associat a les activitats i aprofitaments tradicionals
F46: 04.3.2 | G46: Recuperar i conservar el patrimoni cultural rural vinculat específicament a construccions de pedra en sec | H46: Específic | I46: Obligatori | J46: MAP | L46: =G46 -> Recuperar i conservar el patrimoni cultural rural vinculat específicament a construccions de pedra en sec
F47: 04.3.3 | G47: Fomentar la recuperació i conservació de l'arquitectura tradicional d'intrès de les edificacions i construccions | H47: Comú | I47: Optatiu | L47: =G47 -> Fomentar la recuperació i conservació de l'arquitectura tradicional d'intrès de les edificacions i construccions
F48: 04.3.4 | G48: Identificar i conservar la diversitat domesticada de varietats agrícoles i ramaderes locals | H48: Comú | I48: Obligatori | J48: ESNATURA | L48: =G48 -> Identificar i conservar la diversitat domesticada de varietats agrícoles i ramaderes locals | Q48: *Banc de llavors *Convenis ramaders per la cria de races locals
D49: 04.4 | E49: Donar a conèixer els elements culturals com a valors del paisatge de l'ENP en les activitats d'ús públic | F49: 04.4.1 | G49: Integrar el patrimoni cultural als itineraris i cartelleria de l'ENP. | H49: Comú | I49: Obligatori | L49: =G49 -> Integrar el patrimoni cultural als itineraris i cartelleria de l'ENP.
F50: 04.4.2 | G50: Incorporar el patrimoni cultural en els plans d’ús públic i educació ambiental per fomentar-ne la seva conservació i divulgació. | H50: Comú | I50: Obligatori | L50: =G50 -> Incorporar el patrimoni cultural en els plans d’ús públic i educació ambiental per fomentar-ne la seva conservació i divulgació.
F51: 04.4.3 | G51: Formar el personal dels punts d’informació en els valors culturals de l'ENP | H51: Comú | I51: Obligatori | L51: =G51 -> Formar el personal dels punts d’informació en els valors culturals de l'ENP
B52: 5 | C52: PROTEGIR EL PAISATGE i la qualitat de l'ambient visual, sonor i lumínic. | D52: 05.1 | E52: Identificar els elements d'interès paisatgístic de l'espai | F52: 05.1.1 | G52: Elaborar un inventari d'elements d'interès paisatgístic de l'ENP d'acord amb el Catàleg de paisatge de la zona | H52: Comú | I52: Optatiu | L52: =G52 -> Elaborar un inventari d'elements d'interès paisatgístic de l'ENP d'acord amb el Catàleg de paisatge de la zona
D53: 05.2 | E53: Millorar la qualitat paisatgística | F53: 05.2.1 | G53: Desplegar actuacions de restauració dels elements d'interès paisatgístic degradats | H53: Comú | I53: Optatiu | L53: =G53 -> Desplegar actuacions de restauració dels elements d'interès paisatgístic degradats
F54: 05.2.2 | G54: Gestionar l'abandonament d'infraestructures i instal·lacions amb inpactes sobre els valors de l'espai | L54: =G54 -> Gestionar l'abandonament d'infraestructures i instal·lacions amb inpactes sobre els valors de l'espai
F55: 05.2.3 | G55: Minimitzar la brutícia, deixalles, vandalisme i males praxis dins l'ENP | H55: Comú | I55: Obligatori | L55: =G55 -> Minimitzar la brutícia, deixalles, vandalisme i males praxis dins l'ENP
D56: 05.3 | E56: Protegir la qualitat acústica i lumínica de l'ENP | F56: 05.3.1 | G56: Promoure la certificació de qualitat del cel nocturn | H56: Específic | I56: Optatiu | J56: ESNATURA | L56: =G56 -> Promoure la certificació de qualitat del cel nocturn
F57: 05.3.2 | G57: Promoure la certificació de zones d'especial protecció de la qualitat acústica | H57: Específic | I57: Optatiu | J57: ESNATURA | L57: =G57 -> Promoure la certificació de zones d'especial protecció de la qualitat acústica
A58: CONEIXEMENT | B58: 6 | C58: MILLORAR EL CONEIXEMENT DE L'ENTORN, del patrimoni natural, cultural i social. | D58: 06.1 | E58: Identificar els objectes de gestió prioritària de l'ENP en el marc dels objectius de govern | F58: 06.1.1 | G58: Identificar i prioritzar els elements clau i d'interès per la gestió de la biodiversitat i geodiversitat de Catalunya es troben dins l'ENP (especies amenaçades, espècies exòtiques invasores,.. ) | H58: Comú | I58: Obligatori | J58: Directriva Habitats Carta emplaçament ESNATURA Catàlegs | K58: UIC/SFF/SPEN: Definir criteris d'identificació d'elements interès. UIC/SFF/SPEN: Definició dels objectes de conservació clau comuns a nivell de Xarxa d'ENP o clúster territorial | L58: =G58 -> Identificar i prioritzar els elements clau i d'interès per la gestió de la biodiversitat i geodiversitat de Catalunya es troben dins l'ENP (especies amenaçades, espècies exòtiques invasores,.. ) | Q58: *Participació en la definició dels objectes de conservació clau (hàbitats, espècies, processos i elements d’interès geològic) comuns a nivell de Xarxa d'ENP o clúster territorial
F59: 06.1.2 | G59: Definir espais fràgils i zones d'especial atenció | H59: Comú | I59: Obligatori | K59: SPEN: Inventari i cartografia d'espais fràgils i zones d'especial atenció | L59: =G59 -> Definir espais fràgils i zones d'especial atenció | Q59: *Generació d'informació per a l'inventari i cartografia d'espais fràgils *Realització o actualització de l'inventari de ZH, espais interès geològic, etc.
D60: 06.2 | E60: Conèixer l'estat de conservació i la seva tendència dels hàbitats, les espècies els elements de la gea i els processos ecològics com a eina per avaluar i optimitzar la gestió | F60: 06.2.1 | G60: Participar en l'elaboració de la cartografia que elabora la UIC | H60: Comú | I60: Obligatori | J60: ESNATURA | K60: UIC: Coordinar i contractar l'elaboració de la cartografia | L60: =G60 -> Participar en l'elaboració de la cartografia que elabora la UIC | Q60: *Participació en la programació de la realització de la cartografia d'hàbitats en el contracte plurienal que existeix amb GeoVeg-UB
F61: 06.2.2 | G61: Conèixer i estudiar els processos naturals propis de l’espai, la seva funcionalitat, i ecologia en referència als ecosistemes | H61: Comú | I61: Obligatori | L61: =G61 -> Conèixer i estudiar els processos naturals propis de l’espai, la seva funcionalitat, i ecologia en referència als ecosistemes | Q61: *Foment i coordinació dels estudis d'ecologia del foc, el règim hidrològic, la pol·linització, la tipificació i funcionament de les cadenes tròfiques pròpies de l’espai, la dinàmica de la neu i les allaus, dinàmica litoral, dinàmica geomorfològica i morfodinàmica de les roques, etc. *Millora del coneixement de la geoconservació (escala més detallada de 1:50.000) *Implementació del protocol de fluxos d'informació i coneixement de biodiversitat
F62: 06.2.3 | G62: Conèixer els usos i factors de canvi rellevants en l'evolució dels elements de conservació, i avaluar els efectes que generen en l’espai (pressions i amenaces) | H62: Comú | I62: Obligatori | J62: ESNATURA | K62: SENP/UIC: Elaborar la classificació i cartografia de les pressions o factors de canvi sobre el medi natural | L62: =G62 -> Conèixer els usos i factors de canvi rellevants en l'evolució dels elements de conservació, i avaluar els efectes que generen en l’espai (pressions i amenaces) | Q62: *Foment de l'estudi de l'afectació de determinats processos naturals o activitats antròpiques (contaminació, fragmentació d'hàbitats, atropellaments, noves arts de pesca o pràctiques agrícoles de muntanya, etc.) en l’ENP (amenaces i impacte ambiental). *Avaluació de l'impacte del canvi climàtic en l'ENP i la seva capacitat d'adaptació i resiliència. *Avaluació dels resultats de les estratègies de gestió aplicades en l'ENP *Col.laboració amb l?Observatori per aportar els coneixements generats a l'ENP.
F63: 06.2.4 | G63: Conèixer l'impacte de les gestió de l'aigua, sobre la biodiversitat. | H63: Comú | I63: Optatiu | L63: =G63 -> Conèixer l'impacte de les gestió de l'aigua, sobre la biodiversitat. | Q63: *Programa de seguiment de l’estat hidrològic de les masses d’aigua *Establiment d’una xarxa automatitzada de control (sensors, inventaris, models hidrològics, etc.).
F64: 06.2.5 | G64: Participar en el coneixement de la tendència d'espècies plaga amb afectacions sobre ecosistemes o activitats econòmiques dins l'ENP | H64: Comú | I64: Optatiu | L64: =G64 -> Participar en el coneixement de la tendència d'espècies plaga amb afectacions sobre ecosistemes o activitats econòmiques dins l'ENP | Q64: *Participació en dels estudis de les autoritats competents
F65: 06.2.6 | G65: Conèixer la tendència d'espècies exòtiques invasores amb afectacions sobre ecosistemes o activitats econòmiques dins l'ENP | H65: Comú | I65: Obligatori | J65: ESNATURA | L65: =G65 -> Conèixer la tendència d'espècies exòtiques invasores amb afectacions sobre ecosistemes o activitats econòmiques dins l'ENP | Q65: *Realització i foment d'estudis de forma coordinada amb el SFF
F66: 06.2.7 | G66: Coneixer com millorar la connectivitat de forma coordinada amb altres ENP | H66: Comú | I66: Optatiu | J66: ESNATURA | L66: =G66 -> Coneixer com millorar la connectivitat de forma coordinada amb altres ENP | Q66: * Elaboració d'una cartografia detallada i actualitzada de connectors ecològics
D67: 06.3 | E67: Estandaritzar els seguiments periòdics dels grups clau | F67: 06.3.1 | G67: Participar en la definició del sistema estàndard de seguiment de flora, fauna i hàbitats de la DG | H67: Comú | I67: Obligatori | J67: ESNATURA | K67: UIC/SFF/SENP: Crear espais de participació UIC/SFF: Definir el sistema estàndard de seguiment i el protocol d'aplicació | L67: =G67 -> Participar en la definició del sistema estàndard de seguiment de flora, fauna i hàbitats de la DG | Q67: *Suport a la UIC en la definició dels sistemes de seguiment
F68: 06.3.2 | G68: Adequar i executar el sistema de seguiment periòdic dels grups clau de l'ENP al sistema estàndard de seguiment | H68: Comú | I68: Obligatori | J68: ESNATURA | K68: UIC/SFF: Definir el sistema estàndard de seguiment i el protocol d'aplicació UIC: Elaborar el protocol d'informació i coneixement | L68: =G68 -> Adequar i executar el sistema de seguiment periòdic dels grups clau de l'ENP al sistema estàndard de seguiment | Q68: * Seguiment de les directrius del sistema de seguiment establerts segons la versió més recent aportada per la UIC *Reforç i estabilització de la xarxa de voluntariat per a determinats seguiments de biodiversitat. *Contractació plurianual d’especialistes *Aplicació del protocol establert de compartir informació per al seguiment global d’indicadors de l’estat de la natura, el seguiment dels pol·linitzadors silvestres, o el seguiment dels pol·linitzadors silvestres
F69: 06.3.3 | G69: Mantenir una base de dades de seguiment de patrimoni natural de l'ENP actualitzada i ordenada | H69: Comú | I69: Obligatori | L69: =G69 -> Mantenir una base de dades de seguiment de patrimoni natural de l'ENP actualitzada i ordenada
F70: 06.3.4 | G70: Participar en el grups de treball per a la definició i organització del SINATCAT | H70: Comú | I70: Obligatori | K70: UIC/SENP: Crear i coordinar una metodologia participativa per a la definició del SINATCAT | L70: =G70 -> Participar en el grups de treball per a la definició i organització del SINATCAT
D71: 06.4 | E71: Incrementar el coneixement de qualitat mitjançant l’establiment de marcs de col·laboració, assessorament i suport amb centres de recerca, museus i entitats naturalistes per al desenvolupament de part de la seva activitat en l’ENP | F71: 06.4.1 | G71: Crear sinèrgies i col·laborar amb museus i equipaments de referència per definir línies d'actuació conjunta entre patrimoni cultural i natural | H71: Comú | I71: Optatiu | K71: SENP: Elaborar un mapa d'agents de referència | L71: =G71 -> Crear sinèrgies i col·laborar amb museus i equipaments de referència per definir línies d'actuació conjunta entre patrimoni cultural i natural
F72: 06.4.2 | G72: Establir acords amb les institucions de recerca i naturalistes per al desenvolupament d'estudis i inventaris dins l'ENP en el marc de les seves línies de recerca | H72: Comú | I72: Optatiu | K72: SENP: Elaborar un mapa d'agents de referècia | L72: =G72 -> Establir acords amb les institucions de recerca i naturalistes per al desenvolupament d'estudis i inventaris dins l'ENP en el marc de les seves línies de recerca
F73: 06.4.3 | G73: Potenciar la ciència ciutadana en l’ENP com a eina per generar coneixement | H73: Comú | I73: Optatiu | L73: =G73 -> Potenciar la ciència ciutadana en l’ENP com a eina per generar coneixement | Q73: *Vinculació amb projectes de ciència ciutana existents per generar dades en l'ENP
F74: 06.4.4 | G74: Crear i desenvolupar jornades de recerca de l'ENP de forma anual on els diferents centres mostrin els estudis realizats en l'ENP | H74: Comú | I74: Optatiu | K74: SENP: Suport en l'organització de les jornades | L74: =G74 -> Crear i desenvolupar jornades de recerca de l'ENP de forma anual on els diferents centres mostrin els estudis realizats en l'ENP
F75: 06.4.5 | G75: Posar a disposició de la recerca, equipaments i serveis de l'ENP | H75: Comú | I75: Optatiu | J75: ESNATURA | L75: =G75 -> Posar a disposició de la recerca, equipaments i serveis de l'ENP
F76: 06.4.6 | G76: Crear l'Observatori de recerca de l'ENP vinculat a l'Observatori del Patrimoni natural i la biodiversitat | H76: Comú | I76: Optatiu | K76: UIC: Suport en la creació de l'Observatori de reserca | L76: =G76 -> Crear l'Observatori de recerca de l'ENP vinculat a l'Observatori del Patrimoni natural i la biodiversitat | Q76: *Impuls de la creació de l'Observatori de recerca de l'ENP en col·laboració amb la UIC
D77: 06.5 | E77: Millorar el coneixement global de les dinàmiques d'usos antròpics de l’ENP | F77: 06.5.1 | G77: Participar en la definició del sistema estándard de seguiment de l'ús públic amb el SENP | H77: Comú | I77: Obligatori | K77: SENP: Crear espais de participació. Definició del sistema estándard de seguiment de l'ús públic | L77: =G77 -> Participar en la definició del sistema estándard de seguiment de l'ús públic amb el SENP
F78: 06.5.2 | G78: Disposar de dades de freqüentació i perfil d'usuari en l'ENP i en especial en equipaments i en zones d'alta freqüentació segons el model de DG | H78: Comú | I78: Obligatori | K78: SENP: Disseny i elaboració del sistema estandaritzat de presa de dades i seguiment de la freqüentació en ENP | L78: =G78 -> Disposar de dades de freqüentació i perfil d'usuari en l'ENP i en especial en equipaments i en zones d'alta freqüentació segons el model de DG | Q78: *Implementació del sistema estandaritzat de presa de dades i seguiment de la freqüentació en ENP del SENP *Establiment de models de freqüentació que serveixin per gestionar l'ús públic en l'ENP conjuntament amb la UIC
F79: 06.5.3 | G79: Identificar les activitats i actors de l’espai. | H79: Comú | I79: Obligatori | L79: =G79 -> Identificar les activitats i actors de l’espai.
F80: 06.5.4 | G80: Identificar en cartografia les males praxis i punts de massificació | L80: =G80 -> Identificar en cartografia les males praxis i punts de massificació
F81: 06.5.5 | G81: Adaptar i mantenir un registre d'activitats, actors i inciències en ús públic (curses, conflictes, queixes, etc) | H81: Comú | I81: Obligatori | K81: UIC: Disseny d'un model de registre d'activitats, actors i inciències en ús públic | L81: =G81 -> Adaptar i mantenir un registre d'activitats, actors i inciències en ús públic (curses, conflictes, queixes, etc)
F82: 06.5.6 | G82: Identificar els impactes (positius i negatius) que generen les activitats d'ús públic dins l'ENP | H82: Comú | I82: Obligatori | J82: ESNATURA | L82: =G82 -> Identificar els impactes (positius i negatius) que generen les activitats d'ús públic dins l'ENP
A83: DESENVOLUPAMENT LOCAL | B83: 7 | C83: FIXAR LA POBLACIÓ AL TERRITORI d'acord amb les oportunitats que generen els objectius de l'espai. | D83: 07.1 | E83: Fomentar i donar suport tècnic als Plans de desenvolupament socioecòmonic local sostenible dels municipis | F83: 07.1.1 | G83: Promoure i col·laborar en l'aplicació de Plans de Desenvolupament Local Sostenible | H83: Comú | I83: Obligatori | L83: =G83 -> Promoure i col·laborar en l'aplicació de Plans de Desenvolupament Local Sostenible
B84: 8 | C84: APROFITAR ELS RECURSOS NATURALS DE FORMA SOSTENIBLE mitjançant desenvolupament dels aprofitaments tradicionals de forma compatible amb la conservació de l'espai | D84: 08.1 | E84: Impulsar models productius agraris i forestals per tal d'afavorir la conservació dels hàbitats i els paisatges modelats per aquestes, i contribuir a la millora socioeconòmica de les persones que la fan possible | F84: 08.1.1 | G84: Acompanyar i assessorar els productors agraris per millorar les tècniques productives agràries i afavorir la conservació dels hàbitats i paisatges | H84: Comú | I84: Obligatori | L84: =G84 -> Acompanyar i assessorar els productors agraris per millorar les tècniques productives agràries i afavorir la conservació dels hàbitats i paisatges | Q84: *Manual tècnic de bones pràctiques en ramaderia extensiva i recuperació i manteniment de pastures en espais naturals protegits *Programa de suport tècnic a sector agrari *Promoció i assessorament sobre l'adhesió als distintius de qualitat ambiental existents
F85: 08.1.2 | G85: Oferir formació als productors agraris per millorar el seu coneixement sobre tècniques eficients i respectuoses amb la conservació del patrimoni natural i cultural | H85: Comú | I85: Obligatori | L85: =G85 -> Oferir formació als productors agraris per millorar el seu coneixement sobre tècniques eficients i respectuoses amb la conservació del patrimoni natural i cultural | Q85: *Programa de formació a sector primari
F86: 08.1.3 | G86: Promoure la recuperació i conservació de marges i punts d'aigua associats a la ramaderia i l'agricultura i d'interès per la biodiversitat | H86: Específic | I86: Optatiu | L86: =G86 -> Promoure la recuperació i conservació de marges i punts d'aigua associats a la ramaderia i l'agricultura i d'interès per la biodiversitat
D87: 08.2 | E87: Promoure la coordinació amb els agents socioeconòmics del territori pel foment del desenvolupament sostenible de l'espai (sector primari i secundari) | F87: 08.2.1 | G87: Establir una relació contínua amb agents socioeconòmics del territori, i si s'escau, crear una Taula de desenvolupament local | J87: ESNATURA | L87: =G87 -> Establir una relació contínua amb agents socioeconòmics del territori, i si s'escau, crear una Taula de desenvolupament local | Q87: *Elaboració i actualització periòdica del mapa d’agents socioeconòmics de l’ENP (sector primari i secundari) *Establiment de canals de comunicació i coordinació amb els agents socioeconòmics clau del territori. *Estudi de la idoneïtat de crear una Taula de desenvolupament local, en els ENP que encara no ho tinguin (per ENP o agrupacions d’ENP). *Convocar les taules de desenvolupament local ja constituïdes de cada ENP (o agrupacions d’ENP). *Promoció i enfortiment de la participació dels agents clau a les taules de desenvolupament local ja constituïdes. *Participació en la definició i desplegament dels plans de treball de la taula de desenvolupament local.
D88: 08.3 | E88: Millorar la valorització i comercialització dels productes generats a l'ENP que contribueixen al desenvolupament socioeconòmic i la conservació del patrimoni de l'ENP | F88: 08.3.1 | G88: Implantar un distintiu de qualitat i compatibilitat amb la conservació dels productes de la Xarxa d'ENP o criteris de qualitat propis de l'ENP | H88: Comú | I88: Optatiu | J88: ESNATURA | K88: SENP: Crear una marca que identifiqui els productes agroalimentaris generats en els ENP | L88: =G88 -> Implantar un distintiu de qualitat i compatibilitat amb la conservació dels productes de la Xarxa d'ENP o criteris de qualitat propis de l'ENP | Q88: *Generació d'un segell comú per a tota la xarxa de Parcs (responsabilitat de SENP) *Establiment de criteris propis de l'ENP per poder facilitar identificació de productes de qualitat i respectuosos
F89: 08.3.2 | G89: Integrar els productes i activitats locals de qualitat en l'oferta d'activitats d'informació i turístiques de l'ENP | H89: Comú | I89: Obligatori | J89: ESNATURA CETS | L89: =G89 -> Integrar els productes i activitats locals de qualitat en l'oferta d'activitats d'informació i turístiques de l'ENP | Q89: *Elaboració d'un catàleg de productors i artesans de l'ENP *Inclusió de visites a productors o artesans en el catàleg d'activitats de l'ENP
F90: 08.3.3 | G90: Promoure fires d'artesania i productes locals de l'ENP | H90: Comú | I90: Optatiu | L90: =G90 -> Promoure fires d'artesania i productes locals de l'ENP
F91: 08.3.4 | G91: Generar aliances entre el sector primari, el turisme, la restauració i altres per fomentar la gastronomia local | H91: Comú | I91: Optatiu | J91: ESNATURA CETS | L91: =G91 -> Generar aliances entre el sector primari, el turisme, la restauració i altres per fomentar la gastronomia local | Q91: *Creació i coordinació de jornades d'intercanvi *Creació d'espais de treball comú *Foment del treball per tenir infraestructura comuna (obrador comunitari)
F92: 08.3.5 | G92: Elaborar una diagnòsi del teixit productiu local i un pla d’acció amb línies de treball i actuacions concretes per donar-li suport | H92: Comú | I92: Optatiu | J92: ESNATURA | L92: =G92 -> Elaborar una diagnòsi del teixit productiu local i un pla d’acció amb línies de treball i actuacions concretes per donar-li suport | Q92: *Divulgació i comunicació, formació i assessorament tècnic, comercialització, treball en xarxa, suport a la gestió de l’activitat
F93: 08.3.6 | G93: Elaborar una guia per promocionar els agents del territori que potencien i difonen els productes alimentaris locals i de qualitat (allotjaments, restaurants, cellers, establiments, elaboradors i productors) | H93: Comú | I93: Optatiu | L93: =G93 -> Elaborar una guia per promocionar els agents del territori que potencien i difonen els productes alimentaris locals i de qualitat (allotjaments, restaurants, cellers, establiments, elaboradors i productors) | Q93: *Projecte Parcs a taula
D94: 08.4 | E94: Contribuir a una correcta planificació i gestió dels recursos cinegètics i piscícoles de forma compatible amb els valors de l'ENP | F94: 08.4.1 | G94: Treballar amb l'autoritat competent per garantir objectius de conservació d’espècies i hàbitats en la revisió dels Plans de Gestió Cinegètica | H94: Comú | I94: Obligatori | J94: MAP | L94: =G94 -> Treballar amb l'autoritat competent per garantir objectius de conservació d’espècies i hàbitats en la revisió dels Plans de Gestió Cinegètica | Q94: *Foment d'acords amb les Societats de Caçadors per a incorporar objectius de conservació d’espècies i hàbitats en la revisió dels Plans de Gestió Cinegètica
F95: 08.4.2 | G95: Col·laborar en la regulació i ordenació de la caça i la pesca en zones sensibles o amb risc d'afectació d'elements clau objecte de conservació | H95: Comú | I95: Obligatori | J95: MAP | L95: =G95 -> Col·laborar en la regulació i ordenació de la caça i la pesca en zones sensibles o amb risc d'afectació d'elements clau objecte de conservació | Q95: *Impuls a la declaració de refugis de caça i pesca *Foment de la implicació dels caçadors i pescadors del territori en la conservació dels valors de l'espai
F96: 08.4.3 | G96: Donar suport en la gestió de poblacions que generen danys a les activitats econòmiques de l'ENP | H96: Comú | I96: Obligatori | L96: =G96 -> Donar suport en la gestió de poblacions que generen danys a les activitats econòmiques de l'ENP | Q96: *Gestió directa d'ungulats (protecció de conreus, cooperació amb carreteres, etc.) a partir d'un procediment d’aplicació del control d'ungulats *Acords amb caçadors de la APC *Foment d’actuacions per prevenció de col·lisions amb vehicles d'acord amb titulars de les carreteres
B97: 9 | C97: FOMENTAR UN TURISME SOSTENIBLE compatible amb la conservació de l'espai | D97: 09.1 | E97: Fomentar un model de turisme que promogui els valors dels espais naturals protegits d'acord amb els agents turístics del territori | F97: 09.1.1 | G97: Desplegar la Carta Europea de Turisme Sostenible (CETS) | H97: Comú | I97: Optatiu | J97: ESNATURA | L97: =G97 -> Desplegar la Carta Europea de Turisme Sostenible (CETS)
F98: 09.1.2 | G98: Tramitar la certificació Biosphere | H98: Comú | I98: Optatiu | L98: =G98 -> Tramitar la certificació Biosphere
D99: 09.2 | E99: Promoure la coordinació amb els agents turístics del territori (empreses, industries, administració). | F99: 09.2.1 | G99: Treballar amb les empreses turístiques per trobar eines de canvi cap a un model de turisme sostenible i de qualitat | H99: Comú | I99: Optatiu | J99: ESNATURA | L99: =G99 -> Treballar amb les empreses turístiques per trobar eines de canvi cap a un model de turisme sostenible i de qualitat
F100: 09.2.2 | G100: Crear productes i paquets turístics amb associacions d’empreses turístiques i operadors turístics | H100: Comú | I100: Optatiu | J100: ESNATURA | L100: =G100 -> Crear productes i paquets turístics amb associacions d’empreses turístiques i operadors turístics
A101: ÚS PÚBLIC I SOCIAL | B101: 10 | C101: ORDENAR ELS USOS I APROFITAMENTS per garantir l'equilibri de les activitats humanes amb la conservació de la biodiversitat | D101: 10.1 | E101: Estandarditzar de regulació d'usos i aprofitaments en base al model de Pla de protecció | F101: 10.1.1 | G101: Establir un model de construcció a l'ENP en base al model de Pla de protecció | H101: Comú | I101: Obligatori | K101: SPEN: Elaborar model | L101: =G101 -> Establir un model de construcció a l'ENP en base al model de Pla de protecció | Q101: *Regulació de tancats
...

Sheet Taxonomia Amenaces
A1: Taxonomia d'Amenaces - Xarxa d'ENP Catalunya
A2: Versió 1_revisada pels equips del PNAT Cap de Creus, PNAT Montgrí-Medes, PNAT els Ports, PNIN Poblet, PNAT Delta de l'Ebre, PNAT Alt Pirineu i PNAT Capçaleres del Ter i Freser
A3: Font de dades 1: List of pressures and threats for reporting 2019-2024 v1.1 (Comissió Europea)
A4: Font de dades 2: Llistat de pressions i amenaces del Pla de Protecció del Cadí-Moixeró, inspirat en el llistat de la Comissió Europea
A5: Font de dades 3: IUCN/CMP Threats Classification v 3.3 (2016) i v4.0 draft (2023)
A8: Codi Amenaça | B8: Tipologia d'amenaça | C8: Codi Amenaça | D8: Nom Amenaça | E8: Exemples i descripció del grup
A9: 1 | B9: Urbanització i edificació | C9: 1.1 | D9: Urbanització residencial | E9: Construccions relacionades amb àrees residencials. Tot i que la normativa no permet noves construccions, existeixen edificacions fóra d'ordenació. També casos de remodelacions, reconstruccions o ampliacions d'edificis rurals per usos agrícoles, forestals, ramaders, recreatius, residencials, etc). Restauracions de cabanes i bordes que no deixen forats per ratpenats. cases forestals. Bordes que es canvien d'ús per hosteleria
C10: 1.2 | D10: Urbanització comercial o industrial
C11: 1.3 | D11: Àrees recretives i turístiques | E11: Refugis de muntanya que es remodelen, impacten etc
A12: 2 | B12: Producció primària | C12: 2.1 | D12: Activitat agrícola | E12: Cultius annuals i perennes. Canvis de tipus de cultiu, secà a regadiu o al revés. Canvi d'usos del sòl com cultius de vinya a muntanya, Inclosos el cultiu de l'arròs amb substàncies biocides. Inclòs el cultiu de marihuana
C13: 2.2 | D13: Plantacions forestals
C14: 2.3 | D14: Ramaderia | E14: Ramaderia tan intensiva com extensiva i semi-intensiva (pastura de dia i nit en corral)
C15: 2.4 | D15: Aqüicultura | E15: Aquicultura marina i d'aigua dolça, a l'interior o als voltants del parc
A16: 3 | B16: Producció d'energia i mineria | C16: 3.1 | D16: Activitats de la mineria | E16: Mineria de qualsevol tipus (a cel obert, marina, al·luvial com extracció d'àrids i còdols, subterrània), a l'interior o als voltants del parc. Extracció de torba i salines. Si aplica, extracció d'hidrocarburs terrestres o marins
C17: 3.2 | D17: Producció d'energia renovable | E17: Centrals de producció d'energia renovable (molins eòlics terrestres o marins, instal·lacions solars, hidroelèctriques, geotèrmia inclosos els impactes de fauna contra les instal·lacions). A dins del parc o afectant connectors entre parcs
A18: 4 | B18: Infrastructures de transport i serveis | C18: 4.1 | D18: Vials de transport | E18: Carreteres, pistes forestals, línies fèrries i cremalleres
C19: 4.2 | D19: Conduccions | E19: Conduccions elèctriques, aqueductes, canals de rec, estacions de bombament, conduccions d'aigua o gas
C20: 4.3 | D20: Infrastructures marines | E20: Rutes marines, canals, impactes de vaixells sobre balenes i infrastructura associada. Ports, pantalans, etc
C21: 4.4 | D21: Tancaments i vallats | E21: Tancaments, valles perimetrals i parets de tota mena, en carreteres, per bestiar, estètiques, etc
A22: 5 | B22: Extracció de recursos naturals | C22: 5.1 | D22: Caça i recol·lecció d'animals | E22: Caça i recolecció d'animals, ous, mel silvestre, etc ja sigui per subsistència, esport, tradició, comerç o de forma accidental
C23: 5.2 | D23: Recol·lecció de vegetals | E23: Recolecció de plantes, bolets, resines, líquens, etc
C24: 5.3 | D24: Treballs forestals | E24: Treball forestals de tota mena (arreu, selectiva, carboneig, aclarides, etc)
C25: 5.4 | D25: Pesca i semblants | E25: Pesca i recollida de recursos aquàtics de tota mena i amb qualsevol tècnica (artesanal, xarxa, marisqueig, recollida de corall, pesca accidental, recreativa, etc)
A26: 6 | B26: Molèsties | C26: 6.1 | D26: Molèsties per activitats recreatives | E26: Per activitats recreatives al medi natural de qualsevol tipus (excursionisme, bicicleta, cavall, vehicles a motor, escalada, esquí de muntanya, acampada temporal, pernoctació, ornitòlegs, fotografs, esports nàutics, pesca turisme, àrees recreatives, drons, globus, parapents, buggy-kite, sobrevol amb helicòpters, amb ultralleugers, motos de neu, etc) i tan sigui esporàdica com recurrent.
C27: 6.2 | D27: Molèsties per activitats militars | E27: Activitats militars de qualsevol mena (camps militars, assajos amb artilleria, etc)
C28: 6.3 | D28: Altres tipus de molèsties | E28: Qualsevol altra molèstia (per bany en rius i tolles, passeig de gossos, peregrinatges, aplecs, recerca sobre espècies, extraccions arqueològiques, vandalisme, tràfic de drogues, etc)
C29: 6.4 | D29: Molèsties per activitats multitudinàries | E29: Activitats organitzades i multitudinàries, per exemple curses de muntanya, festivals, esdeveniments, filmacions, fins i tot enterraments
A30: 7 | B30: Gestió i modificació de sistemes naturals | C30: 7.1 | D30: Foc | E30: Foc, grans incendis forestals i supressió del foc, incloses activitats de restauració post-foc
C31: 7.2 | D31: Gestió de l'aigua | E31: Construcció i utilització de preses, canals, captacions, pous, dics, etc de qualsevol mena. Extracció / captacions d'aigua per rec, etc. Construcció de basses per fer neu artificial. Dessaladores, potabilitzadores, depuradores, conduccions, trasvassaments, emissaris de salmorres, alteració de cabals, gestió de cabals en rius
C32: 7.3 | D32: Moviments de terres i sediments | E32: Gestió i estabilització de terrenys i sediments (estabilització de dunes, construccions en litorals, remediació de sòls, restauració de mines, dragatges, moviments de sorres, etc)
C33: 7.4 | D33: Modificació del clima | E33: Activitats per modificar el clima o processos naturals (prevenció de gelades, fertilització amb ferro a l'oceà, captura de carboni, etc)
C34: 7.5 | D34: Gestió d'hàbitats | E34: Gestió d'hàbitats: gestió d'aigua dolça de rec i arrossars (que pot afectar a llacunes, etc), retirada de fustes en rius, desbrossades, creació d'esculls artificials, alimentació d'ocells, tancament de coves, barreres elèctriques
C35: 7.6 | D35: Desaparició d'activitats tradicionals | E35: Desaparició de pràctiques tradicionals com pastura extensiva, canvi en el maneig de la pastura, la tipologia de bestiar, caça per control de predadors, etc
A36: 8 | B36: Espècies invasores i patògens | C36: 8.1 | D36: Espècies invasores | E36: Espècies invasores com rates en illes, animals domèstics assilvestrats, musclo zebra, bambú, peixos introduïts com Phoxinus en estanys d'alta muntanya, etc
C37: 8.2 | D37: Espècies desestabilitzades | E37: Espècies natives desestabilitzades com superpoblació de cèrvids, porcs senglars, manca de carnívors, blooms d'algues, plagues d'insectes, o amb impactes puntuals com predadors sobre espècies sensibles com colònies d'ocells, gall fer, etc
C38: 8.3 | D38: Introducció de genotips aliens | E38: Material genètic introduït com cultius resistents a plagues, creuament de gat domèstic amb gat fer, restauracions d'hàbitats fetes amb varietats alienes, arbres o instectes modificats genèticament, aquicultura amb espècies no natives, etc
C39: 8.4 | D39: Plagues i patògens | E39: Malalties que afecten conills, grip aviar, botulisme, castanyers, oliveres, cítrics, amfibis, etc
A40: 9 | B40: Polució | C40: 9.1 | D40: Polució aquàtica | E40: Polució dissolta en aigua (aigües sèptiques, efluents industrials, pesticides, fertilitzants, efluents de la mineria, excès de nutrients en activitats de l'aquicultura, purins, potasses per desfer la neu en pistes i carreteres, etc
C41: 9.2 | D41: Residus sòlids | E41: Residus sòlids de qualsevol orígen i en medi terrestre o marí, inclosos de la caça, pesca, agricultura, aqüicultura, del turisme, construcció, transport, xarxes fantasma i elements abandonats al medi
C42: 9.3 | D42: Polució aèria | E42: Residus en medi aeri com partícules, gasos, o partícules radioactives
C43: 9.4 | D43: Contaminació acústica, llumínica o per radiació | E43: Contaminació lumínica, tèrmica com efluents de centrals elèctriques en rius, acústica com soroll en aeroports o zones industrials o per escoles de formació de pilots d'helicòpters al Pirineu, camps electromagnètics en cables, sonars submarins, soroll i onades causades per embarcacions recreatives, llums de les maquinàries a pistes d'esquí, il·luminació nocturna en estacions d'esquí, il·luminació de monuments, etc
A44: 10 | B44: Grans pertorbacions naturals | C44: 10.1 | D44: Pertorbacions d'origen geològic | E44: De tipus geològic com terratrèmols, esllavissades, allaus, erupcions volcàniques
C45: 10.2 | D45: Pertorbacions d'origen metereològic | E45: Per fenòmens extrems com inundacions, temporals, pedregades, etc
A46: 11 | B46: Canvi global i/o climàtic | C46: 11.1 | D46: Impactes del canvi climàtic en sistemes físics i químics | E46: Canvis en sistemes físics i químics com acidificació d'oceans, augment del CO2 atmosfèric, pèrdua de sediments, colmatació de basses i llacunes, canvis en corrents marins, regressió de la línia de costa, subsidència del Delta, canvis en la cobertura de núvols, etc
C47: 11.2 | D47: Impactes del canvi climàtic relatius a l'alteració del règim de temperatures | E47: Canvis en règims de temperatures: onades de calor o de fred, canvis en la temperatura del mar, fusió de glaceres, etc
C48: 11.3 | D48: Impactes del canvi climàtic relatius a l'alteració del règim de precipitació i sequera | E48: Canvis en règims de precipitació i règims hidrològics com patrons de pluja, d'innivació, generant sequeres, increment de la severitat d'inundacions, reducció de la superfície de llacs i estanys, etc
C49: 11.4 | D49: Pujada del nivell del mar

Sheet Llistes
A1: Llista d'amenaces OS | D1: Si/No | F1: Codi Amenaça | G1: Nom Amenaça
A2: 0 | B2: No especificada | D2: Si | G2: No especificada
A3: 1 | B3: Urbanització i edificació | D3: No | F3: 1.1 | G3: Urbanització residencial
A4: 2 | B4: Producció primària | D4: Dubtós | F4: 1.2 | G4: Urbanització comercial o industrial
A5: 3 | B5: Producció d'energia i mineria | F5: 1.3 | G5: Àrees recretives i turístiques
A6: 4 | B6: Infrastructures de transport i serveis | F6: 2.1 | G6: Activitat agrícola
A7: 5 | B7: Extracció de recursos naturals | F7: 2.2 | G7: Plantacions forestals
A8: 6 | B8: Molèsties | F8: 2.3 | G8: Ramaderia
A9: 7 | B9: Gestió i modificació de sistemes naturals | F9: 2.4 | G9: Aqüicultura
A10: 8 | B10: Espècies invasores i patògens | F10: 3.1 | G10: Activitats de la mineria
A11: 9 | B11: Polució | F11: 3.2 | G11: Producció d'energia renovable
A12: 10 | B12: Grans pertorbacions naturals | F12: 4.1 | G12: Vials de transport
A13: 11 | B13: Canvi global i/o climàtic | F13: 4.2 | G13: Conduccions
F14: 4.3 | G14: Infrastructures marines
F15: 4.4 | G15: Tancaments i vallats
F16: 5.1 | G16: Caça i recol·lecció d'animals
F17: 5.2 | G17: Recol·lecció de vegetals
F18: 5.3 | G18: Treballs forestals
F19: 5.4 | G19: Pesca i semblants
F20: 6.1 | G20: Molèsties per activitats recreatives
F21: 6.2 | G21: Molèsties per activitats militars
F22: 6.3 | G22: Altres tipus de molèsties
F23: 6.4 | G23: Molèsties per activitats multitudinàries
F24: 7.1 | G24: Foc
F25: 7.2 | G25: Gestió de l'aigua
... F43: 11.4 | G43: Pujada del nivell del mar

Sheet Full1
A1: Comú / Específic | B1: Obligatori / Optatiu | C1: Prioritat | E1: Pel POA
A2: Comú | B2: Obligatori | C2: MÀXIMA | E2: Si
A3: Específic | B3: Optatiu | C3: ALTA | E3: No
C4: MITJANA
C5: BAIXA
C6: FORA DEL TERMINI DEL PLA

Sheet VINCLE AMENAÇA_OBJ. OPERATIU
A1: TAULA DE VINCLE ENTRE LES AMENACES I ELS OBJECTIUS OPERATIUS DE L'EIX DEL PATRIMONI NATURAL
A3: Eix 1. Natura
A4: Codi | B4: Objectius operatius | C4: Tipologia amenaça | D4: Amenaça concreta
A5: 01.1.1 | B5: =PLA!L5 -> Implementar i executar plans de gestió específics per a hàbitats i espècies de conservació prioritària dins l'ENP | C5: No especificada
A6: 01.1.2 | B6: =PLA!L6 -> Adaptar i executar plans de gestió específics per a elements geològics de conservació prioritària dins l'ENP | C6: No especificada
A7: 01.2.1 | B7: =PLA!L7 -> Implementar la metodologia de gestió adaptativa (Estàndards Oberts de Gestió Adaptativa a Catalunya) en tots els processos de l'ENP | C7: Activitat agrícola
A8: 01.2.2 | B8: =PLA!L8 -> Executar les mesures previstes en els plans de conservació o recuperació d'espècies amenaçades de forma coordinada amb el Servei de Flora i Fauna en l'àmbit de l'ENP | C8: No especificada
A9: 01.2.3 | B9: =PLA!L9 -> Executar les mesures de gestió previstes en els plans de control i erradicació d'espècies exòtiques de forma coordinada amb el Servei de Flora i Fauna en l'àmbit de l'ENP | C9: Espècies invasores i patògens
A10: 01.2.4 | B10: =PLA!L10 -> Desplegar els objectius i tasques recollits en els instruments de referència i compromisos internacionals | C10: No especificada
A11: 01.3.1 | B11: =PLA!L11 -> Identificar espais pel foment de la dinàmica natural i l'aprofitament no extractiu | C11: Gestió i modificació de sistemes naturals
A12: 01.3.2 | B12: =PLA!L12 -> Afavorir la maduresa dels sistemes forestals | C12: Gestió i modificació de sistemes naturals
A13: 01.3.3 | B13: =PLA!L13 -> Generar pertorbacions controlades | C13: Gestió i modificació de sistemes naturals
A14: 01.3.4 | B14: =PLA!L14 -> Restaurar la dinàmica natural dels rius | C14: Gestió i modificació de sistemes naturals
A15: 01.3.5 | B15: =PLA!L15 -> Fomentar el paisatge en mosaïc | C15: Gestió i modificació de sistemes naturals
A16: 01.3.6 | B16: =PLA!L16 -> Gestionar i intervenir en la dinàmica de poblacions de fauna que no tenen depredador natural | C16: Gestió i modificació de sistemes naturals
A17: 01.4.1 | B17: =PLA!L18 -> Fomentar acords de custòdia en espais d'alt valor dins l'ENP per a la gestió dels elements prioritaris | C17: No especificada
A18: 01.4.2 | B18: =PLA!L19 -> Fomentar bones pràctiques entre els col·lectius de propietaris i gestors del territori | C18: No especificada
A19: 01.4.3 | B19: =PLA!L20 -> Impulsar la coordinació amb els ens locals en la gestió finques públiques situades dins d’ENP | C19: No especificada
A20: 02.1.1 | B20: =PLA!L21 -> Adaptar i implementar el Pla d'adaptació de l'ENP al canvi climàtic | C20: Canvi global i/o climàtic
A21: 02.1.2 | B21: =PLA!L22 -> Gestionar i planificar els recursos hídrics de l'ENP | C21: Extracció de recursos naturals
A22: 02.1.3 | B22: =PLA!L23 -> Participar en la redacció i execució dels instruments d'ordenació forestal sostenible i per la conservació en finques públiques | C22: Producció primària
A23: 02.1.4 | B23: =PLA!L24 -> Promoure la redacció d'instruments d'ordenació forestal per reduir la sensibilitat i vulnerabilitat dels boscos al canvi climàtic en finques privades | C23: Producció primària
A24: 02.2.1 | B24: =PLA!L25 -> Redactar i implementar el Pla de Prevenció d'Incendis | C24: Grans pertorbacions naturals
A25: 02.2.2 | B25: =PLA!L26 -> Definir i planificar la gestió del foc per a la millora de l'ENP | C25: Grans pertorbacions naturals
A26: 02.2.3 | B26: =PLA!L27 -> Treballar per a la prevenció d'incendis juntament amb els propietaris, ajuntaments, protecció civil, ADF i bombers. | C26: Grans pertorbacions naturals
A27: 03.1.1 | B27: =PLA!L28 -> Participar en les consultes dels procesos d'Avaluació Ambiental que afectin directament o indirectament l’espai del ENP | C27: Infrastructures de transport i serveis
A28: 03.1.2 | B28: =PLA!L29 -> Exercir un seguiment efectiu de les obres al Parc juntament amb les Oficines Territorials d'Acció i Avaluació Ambiental als efectes d'assegurar la correcta translació de la tutela administrativa. | C28: No especificada
... A36: 03.4.2 | B36: =PLA!L37 -> Identificar espais prioritaris per a la gestió directa | C36: No especificada
B37: AFEGIR LES FILES QUE S'HAGIN INCORPORAT A LA TAULA DEL PLA

Sheet BUIDAT_ACCIONS_vDec
A1: ORDRE | B1: DOCUMENT | C1: CODI OBJECTIU | D1: OBJECTIU | E1: CODI ACCIÓ | F1: ACCIÓ | G1: EXECUTAT / PLANIFICAT | H1: NO APLICA | I1: COMENTARIS PNZVG | J1: CODI OP | K1: OP | L1: OP MODIFICAT | M1: CODI NOU | N1: OP PROPOSTA
A2: 1 | B2: Estratègia de Turisme Sostenible de la Garrotxa | C2: 1 | D2: Arribar a un model de governança de la CETS integrador i vertebrador | E2: 1.1 | F2: Realitzar un treball de benchmark nacional i internacional de models de governança | G2: En curs indefinidament | J2: 09.1.1 | K2: Desplegar la Carta Europea de Turisme Sostenible (CETS)
A3: 2 | B3: Estratègia de Turisme Sostenible de la Garrotxa | C3: 1 | D3: Arribar a un model de governança de la CETS integrador i vertebrador | E3: 1.2 | F3: Organitzar sessions de participació amb experts per analitzar diferents models de governança | G3: Executat | J3: 09.1.1 | K3: Desplegar la Carta Europea de Turisme Sostenible (CETS)
A4: 3 | B4: Estratègia de Turisme Sostenible de la Garrotxa | C4: 1 | D4: Arribar a un model de governança de la CETS integrador i vertebrador | E4: 1.3 | F4: Organitzar activitats participatives amb els agents implicats per a la co-creació del model | G4: Executat | J4: 09.1.1 | K4: Desplegar la Carta Europea de Turisme Sostenible (CETS)
A5: 4 | B5: Estratègia de Turisme Sostenible de la Garrotxa | C5: 1 | D5: Arribar a un model de governança de la CETS integrador i vertebrador | E5: 1.4 | F5: Dissenyar un model sostenible de governança integrador i vertebrador | G5: En curs indefinidament | J5: 09.1.1 | K5: Desplegar la Carta Europea de Turisme Sostenible (CETS)
A6: 5 | B6: Estratègia de Turisme Sostenible de la Garrotxa | C6: 1 | D6: Arribar a un model de governança de la CETS integrador i vertebrador | E6: 1.5 | F6: Testejar el prototip del model de governança | G6: Executat en part/en curs | J6: 09.1.1 | K6: Desplegar la Carta Europea de Turisme Sostenible (CETS)
A7: 6 | B7: Estratègia de Turisme Sostenible de la Garrotxa | C7: 1 | D7: Arribar a un model de governança de la CETS integrador i vertebrador | E7: 1.6 | F7: Concretar i implementar el model de governança | G7: Executat en part/en curs | J7: 09.1.1 | K7: Desplegar la Carta Europea de Turisme Sostenible (CETS)
A8: 7 | B8: Estratègia de Turisme Sostenible de la Garrotxa | C8: 1 | D8: Arribar a un model de governança de la CETS integrador i vertebrador | E8: 1.7 | F8: Avaluar i millorar contínuament el model de governança | G8: En curs indefinidament | J8: 09.1.1 | K8: Desplegar la Carta Europea de Turisme Sostenible (CETS)
A9: 8 | B9: Estratègia de Turisme Sostenible de la Garrotxa | C9: 1 | D9: Arribar a un model de governança de la CETS integrador i vertebrador | E9: 1.8 | F9: *Coexistència temporal dels models de governança A | G9: Descartat | H9: NA
A10: 9 | B10: Estratègia de Turisme Sostenible de la Garrotxa | C10: 1 | D10: Arribar a un model de governança de la CETS integrador i vertebrador | E10: 1.9 | F10: *Coexistència temporal dels models de governança B | G10: Descartat | H10: NA
A11: 10 | B11: Estratègia de Turisme Sostenible de la Garrotxa | C11: 1 | D11: Arribar a un model de governança de la CETS integrador i vertebrador | E11: 1.10 | F11: *Aprofitar les sinergies generades amb altres actors de la CETS | G11: En curs indefinidament | J11: 09.2.1 | K11: Treballar amb les empreses turístiques per trobar eines de canvi cap a un model de turisme sostenible i de qualitat
A12: 11 | B12: Estratègia de Turisme Sostenible de la Garrotxa | C12: 2 | D12: Posicionar la CETS com un element aglutinador i identitari del turisme sostenible | E12: 2.1 | F12: Coordinar els plans de comunicació de les entitats implicades a la CETS | G12: En curs indefinidament | J12: 14.3.2 | K12: Garantir l'harmonització de la comunicació com a Parc, Xarxa i Generalitat.
A13: 12 | B13: Estratègia de Turisme Sostenible de la Garrotxa | C13: 2 | D13: Posicionar la CETS com un element aglutinador i identitari del turisme sostenible | E13: 2.1 | F13: Compartir l'estratègia de comunicació CETS | G13: En curs indefinidament | J13: 14.2.1 | K13: Sensibilitzar als diferents agents sobre els valors de l'ENP
A14: 13 | B14: Estratègia de Turisme Sostenible de la Garrotxa | C14: 2 | D14: Posicionar la CETS com un element aglutinador i identitari del turisme sostenible | E14: 2.2 | F14: Impulsar la creació de materials i continguts comunicatius | G14: En curs indefinidament | J14: 14.2.1 | K14: Sensibilitzar als diferents agents sobre els valors de l'ENP
A15: 14 | B15: Estratègia de Turisme Sostenible de la Garrotxa | C15: 2 | D15: Posicionar la CETS com un element aglutinador i identitari del turisme sostenible | E15: 2.3 | F15: *Promoure una oferta turística sostenible de qualitat | G15: En curs indefinidament | J15: 09.2.1 | K15: Treballar amb les empreses turístiques per trobar eines de canvi cap a un model de turisme sostenible i de qualitat
A16: 15 | B16: Estratègia de Turisme Sostenible de la Garrotxa | C16: 2 | D16: Posicionar la CETS com un element aglutinador i identitari del turisme sostenible | E16: 2.4 | F16: *Incrementar el nombre d'empreses i paquets turístics a partir de la Fase II i III de la CETS | G16: En curs indefinidament | J16: 09.2.1 | K16: Treballar amb les empreses turístiques per trobar eines de canvi cap a un model de turisme sostenible i de qualitat
A17: 16 | B17: Estratègia de Turisme Sostenible de la Garrotxa | C17: 3 | D17: Integrar la mobilitat com a part de l'experiència de la visita | E17: 3.1 | F17: Redactar un Pla de mobilitat sostenible i eco mobilitat turística | G17: En curs indefinidament | J17: 09.2.1 | K17: Treballar amb les empreses turístiques per trobar eines de canvi cap a un model de turisme sostenible i de qualitat
A18: 17 | B18: Estratègia de Turisme Sostenible de la Garrotxa | C18: 3 | D18: Integrar la mobilitat com a part de l'experiència de la visita | E18: 3.2 | F18: Desplegar el Pla de mobilitat sostenible i eco mobilitat turística | G18: En curs indefinidament | J18: 09.2.1 | K18: Treballar amb les empreses turístiques per trobar eines de canvi cap a un model de turisme sostenible i de qualitat
A19: 18 | B19: Estratègia de Turisme Sostenible de la Garrotxa | C19: 3 | D19: Integrar la mobilitat com a part de l'experiència de la visita | E19: 3.3 | F19: Sensibilitzar a través de prescriptors | G19: En curs indefinidament | J19: 13.3.2 | K19: Cercar i establir col·laboracions i projectes conjunts amb agents clau del territori
A20: 19 | B20: Estratègia de Turisme Sostenible de la Garrotxa | C20: 3 | D20: Integrar la mobilitat com a part de l'experiència de la visita | E20: 3.4 | F20: Establir complicitats amb agents clau del territori nacional i internacional | G20: En curs indefinidament | J20: 13.3.2 | K20: Cercar i establir col·laboracions i projectes conjunts amb agents clau del territori
A21: 20 | B21: Estratègia de Turisme Sostenible de la Garrotxa | C21: 3 | D21: Integrar la mobilitat com a part de l'experiència de la visita | E21: 3.5 | F21: Contribuir a la implementació del Pla a través d'inversions | G21: Descartat | H21: NA
A22: 21 | B22: Estratègia de Turisme Sostenible de la Garrotxa | C22: 3 | D22: Integrar la mobilitat com a part de l'experiència de la visita | E22: 3.6 | F22: Crear una oferta que inclogui la mobilitat com a experiència turística per al visitant | G22: En curs indefinidament | J22: 09.2.2 | K22: Crear productes i paquets turístics amb associacions d’empreses turístiques i operadors turístics
A23: 22 | B23: Estratègia de Turisme Sostenible de la Garrotxa | C23: 3 | D23: Integrar la mobilitat com a part de l'experiència de la visita | E23: 3.7 | F23: *Mantenir i millorar les infraestructures del Parc Natural i dinamitzar itineraris i camins | G23: En curs indefinidament | J23: 11.7.2 | K23: Disposar i mantenir els serveis, equipaments i infraestructures necessàries i accessibles per acollir, informar, facilitar la visita i garantir la seguretat dels visitants i la protecció de l'entorn
A24: 23 | B24: Estratègia de Turisme Sostenible de la Garrotxa | C24: 3 | D24: Integrar la mobilitat com a part de l'experiència de la visita | E24: 3.8 | F24: *Gestionar de forma integral les àrees d'acollida de visitants | G24: En curs indefinidament | J24: 11.7.2 | K24: Disposar i mantenir els serveis, equipaments i infraestructures necessàries i accessibles per acollir, informar, facilitar la visita i garantir la seguretat dels visitants i la protecció de l'entorn
A25: 24 | B25: Estratègia de Turisme Sostenible de la Garrotxa | C25: 4 | D25: Potenciar el valor de l'experiència al territori (respecte la natura) | E25: 4.1 | F25: Potenciar els valors naturals i culturals de la comarca i de l'espai com a oferta per als visitants | G25: En curs indefinidament | J25: 04.4.2 | K25: Incorporar el patrimoni cultural en els plans d’ús públic i educació ambiental per fomentar-ne la seva conservació i divulgació.
A26: 25 | B26: Estratègia de Turisme Sostenible de la Garrotxa | C26: 4 | D26: Potenciar el valor de l'experiència al territori (respecte la natura) | E26: 4.2 | F26: Incrementar la sensibilització i el compromís de les persones en la conservació dels valors de la comarca | G26: En curs indefinidament | J26: 14.2.1 | K26: Sensibilitzar als diferents agents sobre els valors de l'ENP
A27: 26 | B27: Estratègia de Turisme Sostenible de la Garrotxa | C27: 4 | D27: Potenciar el valor de l'experiència al territori (respecte la natura) | E27: 4.3 | F27: *Potenciar la conservació a partir de les capacitats de càrrega | G27: En curs indefinidament | J27: 10.1.2 | K27: Ordenar els aprofitaments i extraccions dins l'espai
A28: 27 | B28: Estratègia de Turisme Sostenible de la Garrotxa | C28: 4 | D28: Potenciar el valor de l'experiència al territori (respecte la natura) | E28: 4.4 | F28: *Continuar treballant amb el "Pla d'Espais Museístics, d'espais d'interès natural i cultural" iniciat pel Parc Natural de la Zona Volcànica de la Garrotxa per a una millor interpretació del patrimoni. | G28: En curs indefinidament | J28: 06.4.1 | K28: Crear sinèrgies i col·laborar amb museus i equipaments de referència per definir línies d'actuació conjunta entre patrimoni cultural i natural
A29: 28 | B29: Estratègia de Turisme Sostenible de la Garrotxa | C29: 5 | D29: Implicar directament a l'usuari en la conservació del territori | E29: 5.1 | F29: Proporcionar pautes per a una visita més responsable | G29: En curs indefinidament | J29: 13.4.1 | K29: Desplegar en el territori les campanyes de sensibilització i bones pràctiques que s'impulsin des de la DG
A30: 29 | B30: Estratègia de Turisme Sostenible de la Garrotxa | C30: 5 | D30: Implicar directament a l'usuari en la conservació del territori | E30: 5.2 | F30: Vincular projectes de conservació amb la població local i visitants | G30: En curs indefinidament | J30: 13.6.1 | K30: Identificar els programes, projectes i accions en marxa o previstos a l’ENP que poden rebre el suport del voluntariat
