Workbook

Sheet Instruccions
A1: Programa d'actuacions 2027 — Parc Natural de l'Alt Pirineu
A2: Versió del model: | B2: 1.0
A3: Codi de la unitat al Motor: | B3: PNAP
A4: Pla estratègic de referència: | B4: Alt Pirineu_Pla Estrategic_final.xlsx
A6: COM OMPLIR-LO
A7: 1. Mireu el Pla | B7: La pestanya PLA ESTRATÈGIC porta el pla aprovat del vostre espai (objectius, accions, indicadors i fites). No s'ha de modificar. La pestanya PA 2026 (consulta) porta les actuacions del 2026, per si en voleu repetir o adaptar alguna.
A8: 2. Ompliu PROGRAMA ANUAL 2027 | B8: Una actuació per fila. Les columnes blanques són per omplir i les grises es calculen soles. Gairebé tot són desplegables: no cal escriure codis a mà.
A9: 3. Mireu la columna «Revisió» | B9: Cada fila mostra ✔ si està completa o diu què hi falta (import, partida RAE, gestor, codi RAE repetit…). Abans d'enviar el fitxer, no hauria de quedar cap avís.
A10: 4. Envieu el fitxer | B10: El fitxer s'ha de poder convertir al JSON del Motor. No canvieu els noms de les pestanyes ni les columnes.
A12: COLUMNES DE PROGRAMA ANUAL 2027
A13: Codi (automàtic) | B13: Es genera sol: any 27, eix i número correlatiu (27_NA_01). Depèn de l'ordre de les files; no les reordeneu ni n'esborreu cap un cop enviat el fitxer. Per anul·lar una actuació, buideu-ne les cel·les.
A14: Codi RAE | B14: Només si l'actuació té codi RAE. Ha de ser únic.
A15: Actuació | B15: Què farà el parc el 2027. Ha de derivar d'una acció del Pla estratègic.
A16: Objectiu operatiu principal | B16: Desplegable amb els objectius del vostre Pla. El nom de l'objectiu i l'eix s'omplen sols.
A17: Altres objectius relacionats | B17: Fins a tres, amb desplegable. Opcional.
A18: Tipus de despesa | B18: Desplegable. «Mitjans propis» és per a les actuacions sense contractació externa.
A19: Partida RAE | B19: Només per a «Contracte menor a càrrec del RAE». Obligatòria en aquest cas.
A20: Tipus dactuació segons MAP | B20: Desplegable amb les tipologies del Marc d'Acció Prioritària. Si cap no hi encaixa, «Altres».
A21: Import (€) | B21: Import previst. Si no té cost directe, poseu 0. No s'admeten valors negatius.
A22: Acció i indicador del Pla | B22: Desplegable amb les accions del Pla per a l'objectiu triat. La fita mínima i la màxima s'omplen soles.
A23: Grau de compliment | B23: Percentatge (0–100%) de la fita màxima que aconseguirà l'actuació. Si és qualitatiu, expliqueu-ho a Observacions.
A24: Gestor responsable | B24: Desplegable amb l'equip del parc. Si hi falta algú, es pot escriure el nom.
... A26: Naturalesa del contracte | B26: Opcional: Obra, Servei o Subministrament. Ajuda el Motor a proposar el procediment.
A28: QUÈ HA CANVIAT RESPECTE AL MODEL ANTERIOR
B29: Es porta el Pla estratègic de l'espai amb indicadors i fites; l'objectiu i l'eix es trien i es calculen sols; el codi és automàtic; hi ha validacions i una columna de revisió; s'hi han afegit el gestor, l'actuació recurrent i el tipus de despesa «Mitjans propis».

Sheet PROGRAMA ANUAL 2027
A1: PROGRAMA D'ACTUACIONS 2027 — Parc Natural de l'Alt Pirineu
A2: Unitat: | B2: PNAP | D2: Blanc = per omplir · Gris = automàtic · Reviseu la columna «Revisió» abans d'enviar el fitxer.
A3: Model: | B3: v1.0
A5: Codi (automàtic) | B5: Codi RAE | C5: Actuació | D5: Objectiu operatiu principal | E5: Objectiu concret a l'espai (automàtic) | F5: Altre objectiu relacionat 1 | G5: Altre objectiu relacionat 2 | H5: Altre objectiu relacionat 3 | I5: Eix (automàtic) | J5: Tipus de despesa | K5: Partida RAE | L5: Tipus d'actuació segons MAP | M5: Import (€) | N5: Acció i indicador del Pla | O5: Fita mínima (automàtic) | P5: Fita màxima (automàtic) | Q5: Grau de compliment (% de la fita) | R5: Gestor responsable | S5: Actuació recurrent | T5: Naturalesa del contracte | U5: Observacions | V5: Revisió
A6: =IF($D6="","","27_"&IFERROR(INDEX(Objectius!$E$2:$E$183,MATCH($D6,Objectius!$A$2:$A$183,0)),"??")&"_"&TEXT(COUNTIF($I$6:$I6,$I6),"00")) | E6: =IF($D6="","",IFERROR(INDEX(Objectius!$C$2:$C$183,MATCH($D6,Objectius!$A$2:$A$183,0)),"Objectiu no trobat al Pla")) | I6: =IF($D6="","",IFERROR(INDEX(Objectius!$D$2:$D$183,MATCH($D6,Objectius!$A$2:$A$183,0)),"")) | O6: =IF($N6="","",IFERROR(INDEX('PLA ESTRATÈGIC'!$G$4:$G$452,MATCH($N6,'PLA ESTRATÈGIC'!$Q$4:$Q$452,0)),"")) | P6: =IF($N6="","",IFERROR(INDEX('PLA ESTRATÈGIC'!$H$4:$H$452,MATCH($N6,'PLA ESTRATÈGIC'!$Q$4:$Q$452,0)),"")) | V6: =IF(COUNTA($C6,$D6,$J6,$M6)=0,"",IF(TRIM(IF($C6="","Falta l'actuació. ","")&IF($D6="","Falta l'objectiu. ","")&IF($J6="","Falta el tipus de despesa. ","")&IF(AND($J6<>"",$J6<>"Mitjans propis",$J6<>"Altres",$M6=""),"Falta l'import. ","")&IF(AND($J6="Contracte menor a càrrec del RAE",$K6=""),"Falta la partida RAE. ","")&IF(AND($B6<>"",COUNTIF($B$6:$B$705,$B6)>1),"Codi RAE repetit. ","")&IF(AND($B6<>"",$J6<>"",$J6<>"Contracte menor a càrrec del RAE"),"Té codi RAE però no és de tipus RAE. ","")&IF($N6="","Falta l'indicador del Pla. ","")&IF($R6="","Falta el gestor. ","")&IF($S6="","Falta indicar si és recurrent. ",""))="","✔",TRIM(IF($C6="","Falta l'actuació. ","")&IF($D6="","Falta l'objectiu. ","")&IF($J6="","Falta el tipus de despesa. ","")&IF(AND($J6<>"",$J6<>"Mitjans propis",$J6<>"Altres",$M6=""),"Falta l'import. ","")&IF(AND($J6="Contracte menor a càrrec del RAE",$K6=""),"Falta la partida RAE. ","")&IF(AND($B6<>"",COUNTIF($B$6:$B$705,$B6)>1),"Codi RAE repetit. ","")&IF(AND($B6<>"",$J6<>"",$J6<>"Contracte menor a càrrec del RAE"),"Té codi RAE però no és de tipus RAE. ","")&IF($N6="","Falta l'indicador del Pla. ","")&IF($R6="","Falta el gestor. ","")&IF($S6="","Falta indicar si és recurrent. ",""))))
A7: =IF($D7="","","27_"&IFERROR(INDEX(Objectius!$E$2:$E$183,MATCH($D7,Objectius!$A$2:$A$183,0)),"??")&"_"&TEXT(COUNTIF($I$6:$I7,$I7),"00")) | E7: =IF($D7="","",IFERROR(INDEX(Objectius!$C$2:$C$183,MATCH($D7,Objectius!$A$2:$A$183,0)),"Objectiu no trobat al Pla")) | I7: =IF($D7="","",IFERROR(INDEX(Objectius!$D$2:$D$183,MATCH($D7,Objectius!$A$2:$A$183,0)),"")) | O7: =IF($N7="","",IFERROR(INDEX('PLA ESTRATÈGIC'!$G$4:$G$452,MATCH($N7,'PLA ESTRATÈGIC'!$Q$4:$Q$452,0)),"")) | P7: =IF($N7="","",IFERROR(INDEX('PLA ESTRATÈGIC'!$H$4:$H$452,MATCH($N7,'PLA ESTRATÈGIC'!$Q$4:$Q$452,0)),"")) | V7: =IF(COUNTA($C7,$D7,$J7,$M7)=0,"",IF(TRIM(IF($C7="","Falta l'actuació. ","")&IF($D7="","Falta l'objectiu. ","")&IF($J7="","Falta el tipus de despesa. ","")&IF(AND($J7<>"",$J7<>"Mitjans propis",$J7<>"Altres",$M7=""),"Falta l'import. ","")&IF(AND($J7="Contracte menor a càrrec del RAE",$K7=""),"Falta la partida RAE. ","")&IF(AND($B7<>"",COUNTIF($B$6:$B$705,$B7)>1),"Codi RAE repetit. ","")&IF(AND($B7<>"",$J7<>"",$J7<>"Contracte menor a càrrec del RAE"),"Té codi RAE però no és de tipus RAE. ","")&IF($N7="","Falta l'indicador del Pla. ","")&IF($R7="","Falta el gestor. ","")&IF($S7="","Falta indicar si és recurrent. ",""))="","✔",TRIM(IF($C7="","Falta l'actuació. ","")&IF($D7="","Falta l'objectiu. ","")&IF($J7="","Falta el tipus de despesa. ","")&IF(AND($J7<>"",$J7<>"Mitjans propis",$J7<>"Altres",$M7=""),"Falta l'import. ","")&IF(AND($J7="Contracte menor a càrrec del RAE",$K7=""),"Falta la partida RAE. ","")&IF(AND($B7<>"",COUNTIF($B$6:$B$705,$B7)>1),"Codi RAE repetit. ","")&IF(AND($B7<>"",$J7<>"",$J7<>"Contracte menor a càrrec del RAE"),"Té codi RAE però no és de tipus RAE. ","")&IF($N7="","Falta l'indicador del Pla. ","")&IF($R7="","Falta el gestor. ","")&IF($S7="","Falta indicar si és recurrent. ",""))))
A8: =IF($D8="","","27_"&IFERROR(INDEX(Objectius!$E$2:$E$183,MATCH($D8,Objectius!$A$2:$A$183,0)),"??")&"_"&TEXT(COUNTIF($I$6:$I8,$I8),"00")) | E8: =IF($D8="","",IFERROR(INDEX(Objectius!$C$2:$C$183,MATCH($D8,Objectius!$A$2:$A$183,0)),"Objectiu no trobat al Pla")) | I8: =IF($D8="","",IFERROR(INDEX(Objectius!$D$2:$D$183,MATCH($D8,Objectius!$A$2:$A$183,0)),"")) | O8: =IF($N8="","",IFERROR(INDEX('PLA ESTRATÈGIC'!$G$4:$G$452,MATCH($N8,'PLA ESTRATÈGIC'!$Q$4:$Q$452,0)),"")) | P8: =IF($N8="","",IFERROR(INDEX('PLA ESTRATÈGIC'!$H$4:$H$452,MATCH($N8,'PLA ESTRATÈGIC'!$Q$4:$Q$452,0)),"")) | V8: =IF(COUNTA($C8,$D8,$J8,$M8)=0,"",IF(TRIM(IF($C8="","Falta l'actuació. ","")&IF($D8="","Falta l'objectiu. ","")&IF($J8="","Falta el tipus de despesa. ","")&IF(AND($J8<>"",$J8<>"Mitjans propis",$J8<>"Altres",$M8=""),"Falta l'import. ","")&IF(AND($J8="Contracte menor a càrrec del RAE",$K8=""),"Falta la partida RAE. ","")&IF(AND($B8<>"",COUNTIF($B$6:$B$705,$B8)>1),"Codi RAE repetit. ","")&IF(AND($B8<>"",$J8<>"",$J8<>"Contracte menor a càrrec del RAE"),"Té codi RAE però no és de tipus RAE. ","")&IF($N8="","Falta l'indicador del Pla. ","")&IF($R8="","Falta el gestor. ","")&IF($S8="","Falta indicar si és recurrent. ",""))="","✔",TRIM(IF($C8="","Falta l'actuació. ","")&IF($D8="","Falta l'objectiu. ","")&IF($J8="","Falta el tipus de despesa. ","")&IF(AND($J8<>"",$J8<>"Mitjans propis",$J8<>"Altres",$M8=""),"Falta l'import. ","")&IF(AND($J8="Contracte menor a càrrec del RAE",$K8=""),"Falta la partida RAE. ","")&IF(AND($B8<>"",COUNTIF($B$6:$B$705,$B8)>1),"Codi RAE repetit. ","")&IF(AND($B8<>"",$J8<>"",$J8<>"Contracte menor a càrrec del RAE"),"Té codi RAE però no és de tipus RAE. ","")&IF($N8="","Falta l'indicador del Pla. ","")&IF($R8="","Falta el gestor. ","")&IF($S8="","Falta indicar si és recurrent. ",""))))
A9: =IF($D9="","","27_"&IFERROR(INDEX(Objectius!$E$2:$E$183,MATCH($D9,Objectius!$A$2:$A$183,0)),"??")&"_"&TEXT(COUNTIF($I$6:$I9,$I9),"00")) | E9: =IF($D9="","",IFERROR(INDEX(Objectius!$C$2:$C$183,MATCH($D9,Objectius!$A$2:$A$183,0)),"Objectiu no trobat al Pla")) | I9: =IF($D9="","",IFERROR(INDEX(Objectius!$D$2:$D$183,MATCH($D9,Objectius!$A$2:$A$183,0)),"")) | O9: =IF($N9="","",IFERROR(INDEX('PLA ESTRATÈGIC'!$G$4:$G$452,MATCH($N9,'PLA ESTRATÈGIC'!$Q$4:$Q$452,0)),"")) | P9: =IF($N9="","",IFERROR(INDEX('PLA ESTRATÈGIC'!$H$4:$H$452,MATCH($N9,'PLA ESTRATÈGIC'!$Q$4:$Q$452,0)),"")) | V9: =IF(COUNTA($C9,$D9,$J9,$M9)=0,"",IF(TRIM(IF($C9="","Falta l'actuació. ","")&IF($D9="","Falta l'objectiu. ","")&IF($J9="","Falta el tipus de despesa. ","")&IF(AND($J9<>"",$J9<>"Mitjans propis",$J9<>"Altres",$M9=""),"Falta l'import. ","")&IF(AND($J9="Contracte menor a càrrec del RAE",$K9=""),"Falta la partida RAE. ","")&IF(AND($B9<>"",COUNTIF($B$6:$B$705,$B9)>1),"Codi RAE repetit. ","")&IF(AND($B9<>"",$J9<>"",$J9<>"Contracte menor a càrrec del RAE"),"Té codi RAE però no és de tipus RAE. ","")&IF($N9="","Falta l'indicador del Pla. ","")&IF($R9="","Falta el gestor. ","")&IF($S9="","Falta indicar si és recurrent. ",""))="","✔",TRIM(IF($C9="","Falta l'actuació. ","")&IF($D9="","Falta l'objectiu. ","")&IF($J9="","Falta el tipus de despesa. ","")&IF(AND($J9<>"",$J9<>"Mitjans propis",$J9<>"Altres",$M9=""),"Falta l'import. ","")&IF(AND($J9="Contracte menor a càrrec del RAE",$K9=""),"Falta la partida RAE. ","")&IF(AND($B9<>"",COUNTIF($B$6:$B$705,$B9)>1),"Codi RAE repetit. ","")&IF(AND($B9<>"",$J9<>"",$J9<>"Contracte menor a càrrec del RAE"),"Té codi RAE però no és de tipus RAE. ","")&IF($N9="","Falta l'indicador del Pla. ","")&IF($R9="","Falta el gestor. ","")&IF($S9="","Falta indicar si és recurrent. ",""))))
A10: =IF($D10="","","27_"&IFERROR(INDEX(Objectius!$E$2:$E$183,MATCH($D10,Objectius!$A$2:$A$183,0)),"??")&"_"&TEXT(COUNTIF($I$6:$I10,$I10),"00")) | E10: =IF($D10="","",IFERROR(INDEX(Objectius!$C$2:$C$183,MATCH($D10,Objectius!$A$2:$A$183,0)),"Objectiu no trobat al Pla")) | I10: =IF($D10="","",IFERROR(INDEX(Objectius!$D$2:$D$183,MATCH($D10,Objectius!$A$2:$A$183,0)),"")) | O10: =IF($N10="","",IFERROR(INDEX('PLA ESTRATÈGIC'!$G$4:$G$452,MATCH($N10,'PLA ESTRATÈGIC'!$Q$4:$Q$452,0)),"")) | P10: =IF($N10="","",IFERROR(INDEX('PLA ESTRATÈGIC'!$H$4:$H$452,MATCH($N10,'PLA ESTRATÈGIC'!$Q$4:$Q$452,0)),"")) | V10: =IF(COUNTA($C10,$D10,$J10,$M10)=0,"",IF(TRIM(IF($C10="","Falta l'actuació. ","")&IF($D10="","Falta l'objectiu. ","")&IF($J10="","Falta el tipus de despesa. ","")&IF(AND($J10<>"",$J10<>"Mitjans propis",$J10<>"Altres",$M10=""),"Falta l'import. ","")&IF(AND($J10="Contracte menor a càrrec del RAE",$K10=""),"Falta la partida RAE. ","")&IF(AND($B10<>"",COUNTIF($B$6:$B$705,$B10)>1),"Codi RAE repetit. ","")&IF(AND($B10<>"",$J10<>"",$J10<>"Contracte menor a càrrec del RAE"),"Té codi RAE però no és de tipus RAE. ","")&IF($N10="","Falta l'indicador del Pla. ","")&IF($R10="","Falta el gestor. ","")&IF($S10="","Falta indicar si és recurrent. ",""))="","✔",TRIM(IF($C10="","Falta l'actuació. ","")&IF($D10="","Falta l'objectiu. ","")&IF($J10="","Falta el tipus de despesa. ","")&IF(AND($J10<>"",$J10<>"Mitjans propis",$J10<>"Altres",$M10=""),"Falta l'import. ","")&IF(AND($J10="Contracte menor a càrrec del RAE",$K10=""),"Falta la partida RAE. ","")&IF(AND($B10<>"",COUNTIF($B$6:$B$705,$B10)>1),"Codi RAE repetit. ","")&IF(AND($B10<>"",$J10<>"",$J10<>"Contracte menor a càrrec del RAE"),"Té codi RAE però no és de tipus RAE. ","")&IF($N10="","Falta l'indicador del Pla. ","")&IF($R10="","Falta el gestor. ","")&IF($S10="","Falta indicar si és recurrent. ",""))))
A11: =IF($D11="","","27_"&IFERROR(INDEX(Objectius!$E$2:$E$183,MATCH($D11,Objectius!$A$2:$A$183,0)),"??")&"_"&TEXT(COUNTIF($I$6:$I11,$I11),"00")) | E11: =IF($D11="","",IFERROR(INDEX(Objectius!$C$2:$C$183,MATCH($D11,Objectius!$A$2:$A$183,0)),"Objectiu no trobat al Pla")) | I11: =IF($D11="","",IFERROR(INDEX(Objectius!$D$2:$D$183,MATCH($D11,Objectius!$A$2:$A$183,0)),"")) | O11: =IF($N11="","",IFERROR(INDEX('PLA ESTRATÈGIC'!$G$4:$G$452,MATCH($N11,'PLA ESTRATÈGIC'!$Q$4:$Q$452,0)),"")) | P11: =IF($N11="","",IFERROR(INDEX('PLA ESTRATÈGIC'!$H$4:$H$452,MATCH($N11,'PLA ESTRATÈGIC'!$Q$4:$Q$452,0)),"")) | V11: =IF(COUNTA($C11,$D11,$J11,$M11)=0,"",IF(TRIM(IF($C11="","Falta l'actuació. ","")&IF($D11="","Falta l'objectiu. ","")&IF($J11="","Falta el tipus de despesa. ","")&IF(AND($J11<>"",$J11<>"Mitjans propis",$J11<>"Altres",$M11=""),"Falta l'import. ","")&IF(AND($J11="Contracte menor a càrrec del RAE",$K11=""),"Falta la partida RAE. ","")&IF(AND($B11<>"",COUNTIF($B$6:$B$705,$B11)>1),"Codi RAE repetit. ","")&IF(AND($B11<>"",$J11<>"",$J11<>"Contracte menor a càrrec del RAE"),"Té codi RAE però no és de tipus RAE. ","")&IF($N11="","Falta l'indicador del Pla. ","")&IF($R11="","Falta el gestor. ","")&IF($S11="","Falta indicar si és recurrent. ",""))="","✔",TRIM(IF($C11="","Falta l'actuació. ","")&IF($D11="","Falta l'objectiu. ","")&IF($J11="","Falta el tipus de despesa. ","")&IF(AND($J11<>"",$J11<>"Mitjans propis",$J11<>"Altres",$M11=""),"Falta l'import. ","")&IF(AND($J11="Contracte menor a càrrec del RAE",$K11=""),"Falta la partida RAE. ","")&IF(AND($B11<>"",COUNTIF($B$6:$B$705,$B11)>1),"Codi RAE repetit. ","")&IF(AND($B11<>"",$J11<>"",$J11<>"Contracte menor a càrrec del RAE"),"Té codi RAE però no és de tipus RAE. ","")&IF($N11="","Falta l'indicador del Pla. ","")&IF($R11="","Falta el gestor. ","")&IF($S11="","Falta indicar si és recurrent. ",""))))
A12: =IF($D12="","","27_"&IFERROR(INDEX(Objectius!$E$2:$E$183,MATCH($D12,Objectius!$A$2:$A$183,0)),"??")&"_"&TEXT(COUNTIF($I$6:$I12,$I12),"00")) | E12: =IF($D12="","",IFERROR(INDEX(Objectius!$C$2:$C$183,MATCH($D12,Objectius!$A$2:$A$183,0)),"Objectiu no trobat al Pla")) | I12: =IF($D12="","",IFERROR(INDEX(Objectius!$D$2:$D$183,MATCH($D12,Objectius!$A$2:$A$183,0)),"")) | O12: =IF($N12="","",IFERROR(INDEX('PLA ESTRATÈGIC'!$G$4:$G$452,MATCH($N12,'PLA ESTRATÈGIC'!$Q$4:$Q$452,0)),"")) | P12: =IF($N12="","",IFERROR(INDEX('PLA ESTRATÈGIC'!$H$4:$H$452,MATCH($N12,'PLA ESTRATÈGIC'!$Q$4:$Q$452,0)),"")) | V12: =IF(COUNTA($C12,$D12,$J12,$M12)=0,"",IF(TRIM(IF($C12="","Falta l'actuació. ","")&IF($D12="","Falta l'objectiu. ","")&IF($J12="","Falta el tipus de despesa. ","")&IF(AND($J12<>"",$J12<>"Mitjans propis",$J12<>"Altres",$M12=""),"Falta l'import. ","")&IF(AND($J12="Contracte menor a càrrec del RAE",$K12=""),"Falta la partida RAE. ","")&IF(AND($B12<>"",COUNTIF($B$6:$B$705,$B12)>1),"Codi RAE repetit. ","")&IF(AND($B12<>"",$J12<>"",$J12<>"Contracte menor a càrrec del RAE"),"Té codi RAE però no és de tipus RAE. ","")&IF($N12="","Falta l'indicador del Pla. ","")&IF($R12="","Falta el gestor. ","")&IF($S12="","Falta indicar si és recurrent. ",""))="","✔",TRIM(IF($C12="","Falta l'actuació. ","")&IF($D12="","Falta l'objectiu. ","")&IF($J12="","Falta el tipus de despesa. ","")&IF(AND($J12<>"",$J12<>"Mitjans propis",$J12<>"Altres",$M12=""),"Falta l'import. ","")&IF(AND($J12="Contracte menor a càrrec del RAE",$K12=""),"Falta la partida RAE. ","")&IF(AND($B12<>"",COUNTIF($B$6:$B$705,$B12)>1),"Codi RAE repetit. ","")&IF(AND($B12<>"",$J12<>"",$J12<>"Contracte menor a càrrec del RAE"),"Té codi RAE però no és de tipus RAE. ","")&IF($N12="","Falta l'indicador del Pla. ","")&IF($R12="","Falta el gestor. ","")&IF($S12="","Falta indicar si és recurrent. ",""))))
A13: =IF($D13="","","27_"&IFERROR(INDEX(Objectius!$E$2:$E$183,MATCH($D13,Objectius!$A$2:$A$183,0)),"??")&"_"&TEXT(COUNTIF($I$6:$I13,$I13),"00")) | E13: =IF($D13="","",IFERROR(INDEX(Objectius!$C$2:$C$183,MATCH($D13,Objectius!$A$2:$A$183,0)),"Objectiu no trobat al Pla")) | I13: =IF($D13="","",IFERROR(INDEX(Objectius!$D$2:$D$183,MATCH($D13,Objectius!$A$2:$A$183,0)),"")) | O13: =IF($N13="","",IFERROR(INDEX('PLA ESTRATÈGIC'!$G$4:$G$452,MATCH($N13,'PLA ESTRATÈGIC'!$Q$4:$Q$452,0)),"")) | P13: =IF($N13="","",IFERROR(INDEX('PLA ESTRATÈGIC'!$H$4:$H$452,MATCH($N13,'PLA ESTRATÈGIC'!$Q$4:$Q$452,0)),"")) | V13: =IF(COUNTA($C13,$D13,$J13,$M13)=0,"",IF(TRIM(IF($C13="","Falta l'actuació. ","")&IF($D13="","Falta l'objectiu. ","")&IF($J13="","Falta el tipus de despesa. ","")&IF(AND($J13<>"",$J13<>"Mitjans propis",$J13<>"Altres",$M13=""),"Falta l'import. ","")&IF(AND($J13="Contracte menor a càrrec del RAE",$K13=""),"Falta la partida RAE. ","")&IF(AND($B13<>"",COUNTIF($B$6:$B$705,$B13)>1),"Codi RAE repetit. ","")&IF(AND($B13<>"",$J13<>"",$J13<>"Contracte menor a càrrec del RAE"),"Té codi RAE però no és de tipus RAE. ","")&IF($N13="","Falta l'indicador del Pla. ","")&IF($R13="","Falta el gestor. ","")&IF($S13="","Falta indicar si és recurrent. ",""))="","✔",TRIM(IF($C13="","Falta l'actuació. ","")&IF($D13="","Falta l'objectiu. ","")&IF($J13="","Falta el tipus de despesa. ","")&IF(AND($J13<>"",$J13<>"Mitjans propis",$J13<>"Altres",$M13=""),"Falta l'import. ","")&IF(AND($J13="Contracte menor a càrrec del RAE",$K13=""),"Falta la partida RAE. ","")&IF(AND($B13<>"",COUNTIF($B$6:$B$705,$B13)>1),"Codi RAE repetit. ","")&IF(AND($B13<>"",$J13<>"",$J13<>"Contracte menor a càrrec del RAE"),"Té codi RAE però no és de tipus RAE. ","")&IF($N13="","Falta l'indicador del Pla. ","")&IF($R13="","Falta el gestor. ","")&IF($S13="","Falta indicar si és recurrent. ",""))))
A14: =IF($D14="","","27_"&IFERROR(INDEX(Objectius!$E$2:$E$183,MATCH($D14,Objectius!$A$2:$A$183,0)),"??")&"_"&TEXT(COUNTIF($I$6:$I14,$I14),"00")) | E14: =IF($D14="","",IFERROR(INDEX(Objectius!$C$2:$C$183,MATCH($D14,Objectius!$A$2:$A$183,0)),"Objectiu no trobat al Pla")) | I14: =IF($D14="","",IFERROR(INDEX(Objectius!$D$2:$D$183,MATCH($D14,Objectius!$A$2:$A$183,0)),"")) | O14: =IF($N14="","",IFERROR(INDEX('PLA ESTRATÈGIC'!$G$4:$G$452,MATCH($N14,'PLA ESTRATÈGIC'!$Q$4:$Q$452,0)),"")) | P14: =IF($N14="","",IFERROR(INDEX('PLA ESTRATÈGIC'!$H$4:$H$452,MATCH($N14,'PLA ESTRATÈGIC'!$Q$4:$Q$452,0)),"")) | V14: =IF(COUNTA($C14,$D14,$J14,$M14)=0,"",IF(TRIM(IF($C14="","Falta l'actuació. ","")&IF($D14="","Falta l'objectiu. ","")&IF($J14="","Falta el tipus de despesa. ","")&IF(AND($J14<>"",$J14<>"Mitjans propis",$J14<>"Altres",$M14=""),"Falta l'import. ","")&IF(AND($J14="Contracte menor a càrrec del RAE",$K14=""),"Falta la partida RAE. ","")&IF(AND($B14<>"",COUNTIF($B$6:$B$705,$B14)>1),"Codi RAE repetit. ","")&IF(AND($B14<>"",$J14<>"",$J14<>"Contracte menor a càrrec del RAE"),"Té codi RAE però no és de tipus RAE. ","")&IF($N14="","Falta l'indicador del Pla. ","")&IF($R14="","Falta el gestor. ","")&IF($S14="","Falta indicar si és recurrent. ",""))="","✔",TRIM(IF($C14="","Falta l'actuació. ","")&IF($D14="","Falta l'objectiu. ","")&IF($J14="","Falta el tipus de despesa. ","")&IF(AND($J14<>"",$J14<>"Mitjans propis",$J14<>"Altres",$M14=""),"Falta l'import. ","")&IF(AND($J14="Contracte menor a càrrec del RAE",$K14=""),"Falta la partida RAE. ","")&IF(AND($B14<>"",COUNTIF($B$6:$B$705,$B14)>1),"Codi RAE repetit. ","")&IF(AND($B14<>"",$J14<>"",$J14<>"Contracte menor a càrrec del RAE"),"Té codi RAE però no és de tipus RAE. ","")&IF($N14="","Falta l'indicador del Pla. ","")&IF($R14="","Falta el gestor. ","")&IF($S14="","Falta indicar si és recurrent. ",""))))
A15: =IF($D15="","","27_"&IFERROR(INDEX(Objectius!$E$2:$E$183,MATCH($D15,Objectius!$A$2:$A$183,0)),"??")&"_"&TEXT(COUNTIF($I$6:$I15,$I15),"00")) | E15: =IF($D15="","",IFERROR(INDEX(Objectius!$C$2:$C$183,MATCH($D15,Objectius!$A$2:$A$183,0)),"Objectiu no trobat al Pla")) | I15: =IF($D15="","",IFERROR(INDEX(Objectius!$D$2:$D$183,MATCH($D15,Objectius!$A$2:$A$183,0)),"")) | O15: =IF($N15="","",IFERROR(INDEX('PLA ESTRATÈGIC'!$G$4:$G$452,MATCH($N15,'PLA ESTRATÈGIC'!$Q$4:$Q$452,0)),"")) | P15: =IF($N15="","",IFERROR(INDEX('PLA ESTRATÈGIC'!$H$4:$H$452,MATCH($N15,'PLA ESTRATÈGIC'!$Q$4:$Q$452,0)),"")) | V15: =IF(COUNTA($C15,$D15,$J15,$M15)=0,"",IF(TRIM(IF($C15="","Falta l'actuació. ","")&IF($D15="","Falta l'objectiu. ","")&IF($J15="","Falta el tipus de despesa. ","")&IF(AND($J15<>"",$J15<>"Mitjans propis",$J15<>"Altres",$M15=""),"Falta l'import. ","")&IF(AND($J15="Contracte menor a càrrec del RAE",$K15=""),"Falta la partida RAE. ","")&IF(AND($B15<>"",COUNTIF($B$6:$B$705,$B15)>1),"Codi RAE repetit. ","")&IF(AND($B15<>"",$J15<>"",$J15<>"Contracte menor a càrrec del RAE"),"Té codi RAE però no és de tipus RAE. ","")&IF($N15="","Falta l'indicador del Pla. ","")&IF($R15="","Falta el gestor. ","")&IF($S15="","Falta indicar si és recurrent. ",""))="","✔",TRIM(IF($C15="","Falta l'actuació. ","")&IF($D15="","Falta l'objectiu. ","")&IF($J15="","Falta el tipus de despesa. ","")&IF(AND($J15<>"",$J15<>"Mitjans propis",$J15<>"Altres",$M15=""),"Falta l'import. ","")&IF(AND($J15="Contracte menor a càrrec del RAE",$K15=""),"Falta la partida RAE. ","")&IF(AND($B15<>"",COUNTIF($B$6:$B$705,$B15)>1),"Codi RAE repetit. ","")&IF(AND($B15<>"",$J15<>"",$J15<>"Contracte menor a càrrec del RAE"),"Té codi RAE però no és de tipus RAE. ","")&IF($N15="","Falta l'indicador del Pla. ","")&IF($R15="","Falta el gestor. ","")&IF($S15="","Falta indicar si és recurrent. ",""))))
A16: =IF($D16="","","27_"&IFERROR(INDEX(Objectius!$E$2:$E$183,MATCH($D16,Objectius!$A$2:$A$183,0)),"??")&"_"&TEXT(COUNTIF($I$6:$I16,$I16),"00")) | E16: =IF($D16="","",IFERROR(INDEX(Objectius!$C$2:$C$183,MATCH($D16,Objectius!$A$2:$A$183,0)),"Objectiu no trobat al Pla")) | I16: =IF($D16="","",IFERROR(INDEX(Objectius!$D$2:$D$183,MATCH($D16,Objectius!$A$2:$A$183,0)),"")) | O16: =IF($N16="","",IFERROR(INDEX('PLA ESTRATÈGIC'!$G$4:$G$452,MATCH($N16,'PLA ESTRATÈGIC'!$Q$4:$Q$452,0)),"")) | P16: =IF($N16="","",IFERROR(INDEX('PLA ESTRATÈGIC'!$H$4:$H$452,MATCH($N16,'PLA ESTRATÈGIC'!$Q$4:$Q$452,0)),"")) | V16: =IF(COUNTA($C16,$D16,$J16,$M16)=0,"",IF(TRIM(IF($C16="","Falta l'actuació. ","")&IF($D16="","Falta l'objectiu. ","")&IF($J16="","Falta el tipus de despesa. ","")&IF(AND($J16<>"",$J16<>"Mitjans propis",$J16<>"Altres",$M16=""),"Falta l'import. ","")&IF(AND($J16="Contracte menor a càrrec del RAE",$K16=""),"Falta la partida RAE. ","")&IF(AND($B16<>"",COUNTIF($B$6:$B$705,$B16)>1),"Codi RAE repetit. ","")&IF(AND($B16<>"",$J16<>"",$J16<>"Contracte menor a càrrec del RAE"),"Té codi RAE però no és de tipus RAE. ","")&IF($N16="","Falta l'indicador del Pla. ","")&IF($R16="","Falta el gestor. ","")&IF($S16="","Falta indicar si és recurrent. ",""))="","✔",TRIM(IF($C16="","Falta l'actuació. ","")&IF($D16="","Falta l'objectiu. ","")&IF($J16="","Falta el tipus de despesa. ","")&IF(AND($J16<>"",$J16<>"Mitjans propis",$J16<>"Altres",$M16=""),"Falta l'import. ","")&IF(AND($J16="Contracte menor a càrrec del RAE",$K16=""),"Falta la partida RAE. ","")&IF(AND($B16<>"",COUNTIF($B$6:$B$705,$B16)>1),"Codi RAE repetit. ","")&IF(AND($B16<>"",$J16<>"",$J16<>"Contracte menor a càrrec del RAE"),"Té codi RAE però no és de tipus RAE. ","")&IF($N16="","Falta l'indicador del Pla. ","")&IF($R16="","Falta el gestor. ","")&IF($S16="","Falta indicar si és recurrent. ",""))))
A17: =IF($D17="","","27_"&IFERROR(INDEX(Objectius!$E$2:$E$183,MATCH($D17,Objectius!$A$2:$A$183,0)),"??")&"_"&TEXT(COUNTIF($I$6:$I17,$I17),"00")) | E17: =IF($D17="","",IFERROR(INDEX(Objectius!$C$2:$C$183,MATCH($D17,Objectius!$A$2:$A$183,0)),"Objectiu no trobat al Pla")) | I17: =IF($D17="","",IFERROR(INDEX(Objectius!$D$2:$D$183,MATCH($D17,Objectius!$A$2:$A$183,0)),"")) | O17: =IF($N17="","",IFERROR(INDEX('PLA ESTRATÈGIC'!$G$4:$G$452,MATCH($N17,'PLA ESTRATÈGIC'!$Q$4:$Q$452,0)),"")) | P17: =IF($N17="","",IFERROR(INDEX('PLA ESTRATÈGIC'!$H$4:$H$452,MATCH($N17,'PLA ESTRATÈGIC'!$Q$4:$Q$452,0)),"")) | V17: =IF(COUNTA($C17,$D17,$J17,$M17)=0,"",IF(TRIM(IF($C17="","Falta l'actuació. ","")&IF($D17="","Falta l'objectiu. ","")&IF($J17="","Falta el tipus de despesa. ","")&IF(AND($J17<>"",$J17<>"Mitjans propis",$J17<>"Altres",$M17=""),"Falta l'import. ","")&IF(AND($J17="Contracte menor a càrrec del RAE",$K17=""),"Falta la partida RAE. ","")&IF(AND($B17<>"",COUNTIF($B$6:$B$705,$B17)>1),"Codi RAE repetit. ","")&IF(AND($B17<>"",$J17<>"",$J17<>"Contracte menor a càrrec del RAE"),"Té codi RAE però no és de tipus RAE. ","")&IF($N17="","Falta l'indicador del Pla. ","")&IF($R17="","Falta el gestor. ","")&IF($S17="","Falta indicar si és recurrent. ",""))="","✔",TRIM(IF($C17="","Falta l'actuació. ","")&IF($D17="","Falta l'objectiu. ","")&IF($J17="","Falta el tipus de despesa. ","")&IF(AND($J17<>"",$J17<>"Mitjans propis",$J17<>"Altres",$M17=""),"Falta l'import. ","")&IF(AND($J17="Contracte menor a càrrec del RAE",$K17=""),"Falta la partida RAE. ","")&IF(AND($B17<>"",COUNTIF($B$6:$B$705,$B17)>1),"Codi RAE repetit. ","")&IF(AND($B17<>"",$J17<>"",$J17<>"Contracte menor a càrrec del RAE"),"Té codi RAE però no és de tipus RAE. ","")&IF($N17="","Falta l'indicador del Pla. ","")&IF($R17="","Falta el gestor. ","")&IF($S17="","Falta indicar si és recurrent. ",""))))
... A705: =IF($D705="","","27_"&IFERROR(INDEX(Objectius!$E$2:$E$183,MATCH($D705,Objectius!$A$2:$A$183,0)),"??")&"_"&TEXT(COUNTIF($I$6:$I705,$I705),"00")) | E705: =IF($D705="","",IFERROR(INDEX(Objectius!$C$2:$C$183,MATCH($D705,Objectius!$A$2:$A$183,0)),"Objectiu no trobat al Pla")) | I705: =IF($D705="","",IFERROR(INDEX(Objectius!$D$2:$D$183,MATCH($D705,Objectius!$A$2:$A$183,0)),"")) | O705: =IF($N705="","",IFERROR(INDEX('PLA ESTRATÈGIC'!$G$4:$G$452,MATCH($N705,'PLA ESTRATÈGIC'!$Q$4:$Q$452,0)),"")) | P705: =IF($N705="","",IFERROR(INDEX('PLA ESTRATÈGIC'!$H$4:$H$452,MATCH($N705,'PLA ESTRATÈGIC'!$Q$4:$Q$452,0)),"")) | V705: =IF(COUNTA($C705,$D705,$J705,$M705)=0,"",IF(TRIM(IF($C705="","Falta l'actuació. ","")&IF($D705="","Falta l'objectiu. ","")&IF($J705="","Falta el tipus de despesa. ","")&IF(AND($J705<>"",$J705<>"Mitjans propis",$J705<>"Altres",$M705=""),"Falta l'import. ","")&IF(AND($J705="Contracte menor a càrrec del RAE",$K705=""),"Falta la partida RAE. ","")&IF(AND($B705<>"",COUNTIF($B$6:$B$705,$B705)>1),"Codi RAE repetit. ","")&IF(AND($B705<>"",$J705<>"",$J705<>"Contracte menor a càrrec del RAE"),"Té codi RAE però no és de tipus RAE. ","")&IF($N705="","Falta l'indicador del Pla. ","")&IF($R705="","Falta el gestor. ","")&IF($S705="","Falta indicar si és recurrent. ",""))="","✔",TRIM(IF($C705="","Falta l'actuació. ","")&IF($D705="","Falta l'objectiu. ","")&IF($J705="","Falta el tipus de despesa. ","")&IF(AND($J705<>"",$J705<>"Mitjans propis",$J705<>"Altres",$M705=""),"Falta l'import. ","")&IF(AND($J705="Contracte menor a càrrec del RAE",$K705=""),"Falta la partida RAE. ","")&IF(AND($B705<>"",COUNTIF($B$6:$B$705,$B705)>1),"Codi RAE repetit. ","")&IF(AND($B705<>"",$J705<>"",$J705<>"Contracte menor a càrrec del RAE"),"Té codi RAE però no és de tipus RAE. ","")&IF($N705="","Falta l'indicador del Pla. ","")&IF($R705="","Falta el gestor. ","")&IF($S705="","Falta indicar si és recurrent. ",""))))

Sheet PLA ESTRATÈGIC
A1: PLA ESTRATÈGIC — Parc Natural de l'Alt Pirineu (només consulta: no modificar)
A3: Eix | B3: Codi objectiu operatiu | C3: Objectiu operatiu (estàndard) | D3: Objectiu concret a l'espai | E3: Acció del Pla | F3: Indicador | G3: Fita mínima | H3: Fita màxima | I3: Prioritat | J3: Àrea responsable | K3: Persona responsable | L3: Objectiu general | M3: Objectiu estratègic | N3: Comú / Específic | O3: Obligatori / Optatiu | P3: Incorporable a la planificació anual | Q3: Clau (per als desplegables)
A4: 1. Natura | B4: 01.1.1 | C4: Implementar i executar plans de gestió específics per a hàbitats i espècies de conservació prioritària dins l'ENP | D4: Implementar i executar plans de gestió específics per a hàbitats i espècies de conservació prioritària dins l'ENP | E4: Realització d'accions per a la millora dels elements prioritzats a l'espai, incloent les accions previstes de conservació al Marc d’Acció Prioritària dels espais Xarxa Natura 2000 “Alt Pallars” i “la Torrassa” | F4: Número d'accions | G4: 20 | H4: 60 | I4: MÀXIMA | J4: Patrimoni | K4: Eli | L4: CONSERVAR LA NATURA i restaurar els ecosistemes, els processos naturals i seminaturals, la biodiversitat i la geodiversitat associada. | M4: Adequar i fer eficient la conservació dels elements objecte de gestió prioritària marcats per la DG a l'ENP | N4: Comú | O4: Obligatori | P4: Si | Q4: 01.1.1 · Realització d'accions per a la millora dels elements prioritzats a l'espai, incloent les accions previstes de conservació al Marc d’Acció Prioritària — Número d'accions
A5: 1. Natura | B5: 01.1.1 | C5: Implementar i executar plans de gestió específics per a hàbitats i espècies de conservació prioritària dins l'ENP | D5: Implementar i executar plans de gestió específics per a hàbitats i espècies de conservació prioritària dins l'ENP | E5: Realització d’actuacions de control i eradicació d’espècies invasores (exòtiques o no) que afecten a l’estat de conservació d’hàbitats i espècies | F5: Número d'accions | G5: 4 | H5: 20 | I5: MÀXIMA | L5: CONSERVAR LA NATURA i restaurar els ecosistemes, els processos naturals i seminaturals, la biodiversitat i la geodiversitat associada. | M5: Adequar i fer eficient la conservació dels elements objecte de gestió prioritària marcats per la DG a l'ENP | N5: Comú | O5: Obligatori | P5: Si | Q5: 01.1.1 · Realització d’actuacions de control i eradicació d’espècies invasores (exòtiques o no) que afecten a l’estat de conservació d’hàbitats i espècies — Número d'accions
A6: 1. Natura | B6: 01.1.1 | C6: Implementar i executar plans de gestió específics per a hàbitats i espècies de conservació prioritària dins l'ENP | D6: Implementar i executar plans de gestió específics per a hàbitats i espècies de conservació prioritària dins l'ENP | E6: Realització de les actuacions de conservació d’hàbitats i espècies aquàtiques d’alta muntanya previstes al projecte LIFE RESQUE ALPYR i projectes Next Generation (Pla de Salito, Estanys dels Rosari i Garrabea) | F6: Número d’accions de conservació executades | G6: 4 | H6: 8 | I6: MÀXIMA | L6: CONSERVAR LA NATURA i restaurar els ecosistemes, els processos naturals i seminaturals, la biodiversitat i la geodiversitat associada. | M6: Adequar i fer eficient la conservació dels elements objecte de gestió prioritària marcats per la DG a l'ENP | N6: Comú | O6: Obligatori | P6: Si | Q6: 01.1.1 · Realització de les actuacions de conservació d’hàbitats i espècies aquàtiques d’alta muntanya previstes al projecte LIFE RESQUE ALPYR i projectes Next — Número d’accions de conservació executades
A7: 1. Natura | B7: 01.1.1 | C7: Implementar i executar plans de gestió específics per a hàbitats i espècies de conservació prioritària dins l'ENP | D7: Implementar i executar plans de gestió específics per a hàbitats i espècies de conservació prioritària dins l'ENP | E7: Elaboració de plans de gestió per elements prioritzats a l'espai | F7: Número de plans | G7: 2 | H7: (tots perill extincio + habitats prioritaris) | I7: ALTA | J7: Patrimoni | K7: Eli | L7: CONSERVAR LA NATURA i restaurar els ecosistemes, els processos naturals i seminaturals, la biodiversitat i la geodiversitat associada. | M7: Adequar i fer eficient la conservació dels elements objecte de gestió prioritària marcats per la DG a l'ENP | N7: Comú | O7: Obligatori | P7: Si | Q7: 01.1.1 · Elaboració de plans de gestió per elements prioritzats a l'espai — Número de plans
A8: 1. Natura | B8: 01.1.1 | C8: Implementar i executar plans de gestió específics per a hàbitats i espècies de conservació prioritària dins l'ENP | D8: Implementar i executar plans de gestió específics per a hàbitats i espècies de conservació prioritària dins l'ENP | E8: Afavorir la custòdia del territori amb entitats i potenciar projectes de conservació de forma col·laborativa entre el parc, els ens locals i les entitats de custòdia | F8: Número d’acords de custòdia implementats | G8: 1 | H8: 3 | I8: MITJANA | L8: CONSERVAR LA NATURA i restaurar els ecosistemes, els processos naturals i seminaturals, la biodiversitat i la geodiversitat associada. | M8: Adequar i fer eficient la conservació dels elements objecte de gestió prioritària marcats per la DG a l'ENP | N8: Comú | O8: Obligatori | P8: Si | Q8: 01.1.1 · Afavorir la custòdia del territori amb entitats i potenciar projectes de conservació de forma col·laborativa entre el parc, els ens locals i les entit — Número d’acords de custòdia implementats
A9: 1. Natura | B9: 01.1.2 | C9: Adaptar i executar plans de gestió específics per a elements geològics de conservació prioritària dins l'ENP | D9: Adaptar i executar plans de gestió específics per a elements geològics de conservació prioritària dins l'ENP | E9: Actualitzar i digitalitzar l'inventari d'elements geològics a l'espai | F9: Fitxes noves/actualitzades | G9: 10 | H9: 37 | I9: BAIXA | J9: Direcció | K9: Marc | L9: CONSERVAR LA NATURA i restaurar els ecosistemes, els processos naturals i seminaturals, la biodiversitat i la geodiversitat associada. | M9: Executar les mesures de gestió directa previstes en els intruments de planificació per la conservació i la gestió adaptativa dels elements clau de l'ENP | N9: Comú | O9: Obligatori | P9: Si | Q9: 01.1.2 · Actualitzar i digitalitzar l'inventari d'elements geològics a l'espai — Fitxes noves/actualitzades
A10: 1. Natura | B10: 01.1.2 | C10: Adaptar i executar plans de gestió específics per a elements geològics de conservació prioritària dins l'ENP | D10: Adaptar i executar plans de gestió específics per a elements geològics de conservació prioritària dins l'ENP | E10: Actualitzar i digitalitzat l'inventari d'elements geomorfologic a l'espai | F10: Fitxes noves/actualitzades | G10: 24 | H10: 89 | I10: BAIXA | J10: Patrimoni | K10: Oriol | L10: CONSERVAR LA NATURA i restaurar els ecosistemes, els processos naturals i seminaturals, la biodiversitat i la geodiversitat associada. | M10: Executar les mesures de gestió directa previstes en els intruments de planificació per la conservació i la gestió adaptativa dels elements clau de l'ENP | N10: Comú | O10: Obligatori | P10: Si | Q10: 01.1.2 · Actualitzar i digitalitzat l'inventari d'elements geomorfologic a l'espai — Fitxes noves/actualitzades
A11: 1. Natura | B11: 01.1.2 | C11: Adaptar i executar plans de gestió específics per a elements geològics de conservació prioritària dins l'ENP | D11: Adaptar i executar plans de gestió específics per a elements geològics de conservació prioritària dins l'ENP | E11: Aplicació de les directrius de gestió de l'inventari de patrimoni geològic (ICGC) i els inventaris gologics i geomorfologics de l'espai | F11: Número accions conservació | G11: 2 | H11: 10 | I11: MITJANA | J11: Direcció | K11: Marc | L11: CONSERVAR LA NATURA i restaurar els ecosistemes, els processos naturals i seminaturals, la biodiversitat i la geodiversitat associada. | M11: Executar les mesures de gestió directa previstes en els intruments de planificació per la conservació i la gestió adaptativa dels elements clau de l'ENP | N11: Comú | O11: Obligatori | P11: Si | Q11: 01.1.2 · Aplicació de les directrius de gestió de l'inventari de patrimoni geològic (ICGC) i els inventaris gologics i geomorfologics de l'espai — Número accions conservació
A12: 1. Natura | B12: 01.2.1 | C12: Implementar la metodologia de gestió adaptativa (Estàndards Oberts de Gestió Adaptativa a Catalunya) en tots els processos de l'ENP | D12: Implementar la metodologia de gestió adaptativa (Estàndards Oberts de Gestió Adaptativa a Catalunya) en tots els processos de l'ENP | E12: Implentar metodologia Open Standards als processos més rellevants de l'espai | F12: Número OP | G12: 1 | H12: 10 | I12: MÀXIMA | J12: Direcció | K12: Marc | L12: CONSERVAR LA NATURA i restaurar els ecosistemes, els processos naturals i seminaturals, la biodiversitat i la geodiversitat associada. | M12: Executar les mesures de gestió directa previstes en els intruments de planificació per la conservació i la gestió adaptativa dels elements clau de l'ENP | N12: Comú | O12: Obligatori | P12: No | Q12: 01.2.1 · Implentar metodologia Open Standards als processos més rellevants de l'espai — Número OP
A13: 1. Natura | B13: 01.2.2 | C13: Executar les mesures previstes en els plans de conservació o recuperació d'espècies amenaçades de forma coordinada amb el Servei de Flora i Fauna en l'àmbit de l'ENP | D13: Executar les mesures previstes en els plans de conservació o recuperació d'espècies amenaçades de forma coordinada amb el Servei de Flora i Fauna en l'àmbit de l'ENP | E13: Implicació i participació en la redacció dels plans de conservació /recuperació d'espècies amenaçades. Reforç poblacional quan s'escaigui | F13: Número plans implicats | G13: 1 | H13: 4 | I13: MÀXIMA | J13: Patrimoni | K13: Eli | L13: CONSERVAR LA NATURA i restaurar els ecosistemes, els processos naturals i seminaturals, la biodiversitat i la geodiversitat associada. | M13: Executar les mesures de gestió directa previstes en els intruments de planificació per la conservació i la gestió adaptativa dels elements clau de l'ENP | N13: Comú | O13: Obligatori | P13: Si | Q13: 01.2.2 · Implicació i participació en la redacció dels plans de conservació /recuperació d'espècies amenaçades. Reforç poblacional quan s'escaigui — Número plans implicats
A14: 1. Natura | B14: 01.2.2 | C14: Executar les mesures previstes en els plans de conservació o recuperació d'espècies amenaçades de forma coordinada amb el Servei de Flora i Fauna en l'àmbit de l'ENP | D14: Executar les mesures previstes en els plans de conservació o recuperació d'espècies amenaçades de forma coordinada amb el Servei de Flora i Fauna en l'àmbit de l'ENP | E14: Execució de les accions dins els plans que pertoquin a cada espai (incorporar totes les mesures que surten als plans ja aprovats que tenen incidència a l'espai) | F14: Número accions | G14: 10 | H14: 40 | I14: MÀXIMA | J14: Patrimoni | K14: Eli | L14: CONSERVAR LA NATURA i restaurar els ecosistemes, els processos naturals i seminaturals, la biodiversitat i la geodiversitat associada. | M14: Executar les mesures de gestió directa previstes en els intruments de planificació per la conservació i la gestió adaptativa dels elements clau de l'ENP | N14: Comú | O14: Obligatori | P14: Si | Q14: 01.2.2 · Execució de les accions dins els plans que pertoquin a cada espai (incorporar totes les mesures que surten als plans ja aprovats que tenen incidència — Número accions
A15: 1. Natura | B15: 01.2.2 | C15: Executar les mesures previstes en els plans de conservació o recuperació d'espècies amenaçades de forma coordinada amb el Servei de Flora i Fauna en l'àmbit de l'ENP | D15: Executar les mesures previstes en els plans de conservació o recuperació d'espècies amenaçades de forma coordinada amb el Servei de Flora i Fauna en l'àmbit de l'ENP | E15: Col.laboració en l'obtenció de la informació necessària dins els espais per al desenvolupament dels Plans | F15: Número plans s'ha obtingut informació | G15: 1 | H15: 4 | I15: MÀXIMA | J15: Patrimoni | K15: Eli | L15: CONSERVAR LA NATURA i restaurar els ecosistemes, els processos naturals i seminaturals, la biodiversitat i la geodiversitat associada. | M15: Executar les mesures de gestió directa previstes en els intruments de planificació per la conservació i la gestió adaptativa dels elements clau de l'ENP | N15: Comú | O15: Obligatori | P15: Si | Q15: 01.2.2 · Col.laboració en l'obtenció de la informació necessària dins els espais per al desenvolupament dels Plans — Número plans s'ha obtingut informació
A16: 1. Natura | B16: 01.2.2 | C16: Executar les mesures previstes en els plans de conservació o recuperació d'espècies amenaçades de forma coordinada amb el Servei de Flora i Fauna en l'àmbit de l'ENP | D16: Executar les mesures previstes en els plans de conservació o recuperació d'espècies amenaçades de forma coordinada amb el Servei de Flora i Fauna en l'àmbit de l'ENP | E16: Acompanyament de la Comissió Ramadera amb l’òrgan competent per abordar de forma específica la millora de la convivència entre la ramaderia i la presència de grans depredadors, i l’ús de gossos de protecció | F16: Número de reunions realitzades | G16: 4 | H16: 8 | I16: ALTA | L16: CONSERVAR LA NATURA i restaurar els ecosistemes, els processos naturals i seminaturals, la biodiversitat i la geodiversitat associada. | M16: Executar les mesures de gestió directa previstes en els intruments de planificació per la conservació i la gestió adaptativa dels elements clau de l'ENP | N16: Comú | O16: Obligatori | P16: Si | Q16: 01.2.2 · Acompanyament de la Comissió Ramadera amb l’òrgan competent per abordar de forma específica la millora de la convivència entre la ramaderia i la presè — Número de reunions realitzades
A17: 1. Natura | B17: 01.2.3 | C17: Executar les mesures de gestió previstes en els plans de control i erradicació d'espècies exòtiques de forma coordinada amb el Servei de Flora i Fauna en l'àmbit de l'ENP | D17: Executar les mesures de gestió previstes en els plans de control i erradicació d'espècies exòtiques de forma coordinada amb el Servei de Flora i Fauna en l'àmbit de l'ENP | E17: Implicació i participació en la redacció (cal identificar els plans que estan ja en marxa o previstos i posar les mesures concretes) | F17: Número plans implicats | G17: 1 | H17: 2 | I17: MÀXIMA | J17: Patrimoni | K17: Eli | L17: CONSERVAR LA NATURA i restaurar els ecosistemes, els processos naturals i seminaturals, la biodiversitat i la geodiversitat associada. | M17: Executar les mesures de gestió directa previstes en els intruments de planificació per la conservació i la gestió adaptativa dels elements clau de l'ENP | N17: Comú | O17: Obligatori | P17: Si | Q17: 01.2.3 · Implicació i participació en la redacció (cal identificar els plans que estan ja en marxa o previstos i posar les mesures concretes) — Número plans implicats
A18: 1. Natura | B18: 01.2.3 | C18: Executar les mesures de gestió previstes en els plans de control i erradicació d'espècies exòtiques de forma coordinada amb el Servei de Flora i Fauna en l'àmbit de l'ENP | D18: Executar les mesures de gestió previstes en els plans de control i erradicació d'espècies exòtiques de forma coordinada amb el Servei de Flora i Fauna en l'àmbit de l'ENP | E18: Execució de les accions dins els plans que pertoquin a cada espai | F18: Número accions | G18: 4 | H18: 10 | I18: MÀXIMA | J18: Patrimoni | K18: Eli | L18: CONSERVAR LA NATURA i restaurar els ecosistemes, els processos naturals i seminaturals, la biodiversitat i la geodiversitat associada. | M18: Executar les mesures de gestió directa previstes en els intruments de planificació per la conservació i la gestió adaptativa dels elements clau de l'ENP | N18: Comú | O18: Obligatori | P18: Si | Q18: 01.2.3 · Execució de les accions dins els plans que pertoquin a cada espai — Número accions
A19: 1. Natura | B19: 01.2.3 | C19: Executar les mesures de gestió previstes en els plans de control i erradicació d'espècies exòtiques de forma coordinada amb el Servei de Flora i Fauna en l'àmbit de l'ENP | D19: Executar les mesures de gestió previstes en els plans de control i erradicació d'espècies exòtiques de forma coordinada amb el Servei de Flora i Fauna en l'àmbit de l'ENP | E19: Col.laboració en l'obtenció de la informació necessària dins els espais per al desenvolupament dels Plans | F19: Número plans s'ha obtingut informació | G19: 1 | H19: 2 | I19: ALTA | J19: Patrimoni | K19: Eli | L19: CONSERVAR LA NATURA i restaurar els ecosistemes, els processos naturals i seminaturals, la biodiversitat i la geodiversitat associada. | M19: Executar les mesures de gestió directa previstes en els intruments de planificació per la conservació i la gestió adaptativa dels elements clau de l'ENP | N19: Comú | O19: Obligatori | P19: Si | Q19: 01.2.3 · Col.laboració en l'obtenció de la informació necessària dins els espais per al desenvolupament dels Plans — Número plans s'ha obtingut informació
A20: 1. Natura | B20: 01.2.4 | C20: Desplegar els objectius i tasques recollits en els instruments de referència i compromisos internacionals | D20: Desplegar els objectius i tasques recollits en els instruments de referència i compromisos internacionals | E20: Presentar candidatura a la GREEN List UICN | F20: Execució | G20: no | H20: si | I20: MITJANA | J20: Direcció | K20: Marc | L20: CONSERVAR LA NATURA i restaurar els ecosistemes, els processos naturals i seminaturals, la biodiversitat i la geodiversitat associada. | M20: Executar les mesures de gestió directa previstes en els intruments de planificació per la conservació i la gestió adaptativa dels elements clau de l'ENP | N20: Específic | O20: Optatiu | P20: Si | Q20: 01.2.4 · Presentar candidatura a la GREEN List UICN — Execució
A21: 1. Natura | B21: 01.2.4 | C21: Desplegar els objectius i tasques recollits en els instruments de referència i compromisos internacionals | D21: Desplegar els objectius i tasques recollits en els instruments de referència i compromisos internacionals | E21: Presentar candidatura Wild Rivers Noguera Pallaresa | F21: Execució | G21: no | H21: si | I21: ALTA | J21: Direcció | K21: Marc | L21: CONSERVAR LA NATURA i restaurar els ecosistemes, els processos naturals i seminaturals, la biodiversitat i la geodiversitat associada. | M21: Executar les mesures de gestió directa previstes en els intruments de planificació per la conservació i la gestió adaptativa dels elements clau de l'ENP | N21: Específic | O21: Optatiu | P21: Si | Q21: 01.2.4 · Presentar candidatura Wild Rivers Noguera Pallaresa — Execució
A22: 1. Natura | B22: 01.2.4 | C22: Desplegar els objectius i tasques recollits en els instruments de referència i compromisos internacionals | D22: Desplegar els objectius i tasques recollits en els instruments de referència i compromisos internacionals | E22: Preparar candidatura a Reserva Biosfera Transfronterera o Transboundary Park Europarc PP3N | F22: Execució | G22: no | H22: si | I22: MITJANA | J22: Direcció | K22: Marc | L22: CONSERVAR LA NATURA i restaurar els ecosistemes, els processos naturals i seminaturals, la biodiversitat i la geodiversitat associada. | M22: Executar les mesures de gestió directa previstes en els intruments de planificació per la conservació i la gestió adaptativa dels elements clau de l'ENP | N22: Específic | O22: Optatiu | P22: Si | Q22: 01.2.4 · Preparar candidatura a Reserva Biosfera Transfronterera o Transboundary Park Europarc PP3N — Execució
A23: 1. Natura | B23: 01.3.1 | C23: Identificar espais pel foment de la dinàmica natural i l'aprofitament no extractiu | D23: Identificar espais pel foment de la dinàmica natural i l'aprofitament no extractiu | E23: Participar en la identificació de boscos madurs pel foment de la dinàmica natural i l'aprofitament no extractiu dins l'ENP en base a uns criteris metodològics predefinits (DG Boscos i boscos BAVE POCTEFA RedBio) | F23: Número participacions | G23: 1 | H23: 2 | I23: ALTA | J23: Patrimoni | K23: Eli | L23: CONSERVAR LA NATURA i restaurar els ecosistemes, els processos naturals i seminaturals, la biodiversitat i la geodiversitat associada. | M23: Afavorir ecosistemes complexes, resilients, i d'alta biodiversitat per garantir la recuperació dels processos ecosistèmics | N23: Comú | O23: Obligatori | P23: Si | Q23: 01.3.1 · Participar en la identificació de boscos madurs pel foment de la dinàmica natural i l'aprofitament no extractiu dins l'ENP en base a uns criteris meto — Número participacions
A24: 1. Natura | B24: 01.3.1 | C24: Identificar espais pel foment de la dinàmica natural i l'aprofitament no extractiu | D24: Identificar espais pel foment de la dinàmica natural i l'aprofitament no extractiu | E24: Afavorir la creació o recuperació d'hàbitats per a la conservació d'espècies (Pla de Salito, cua embassament de Boren, llacuna de Llagunes, basses aigua) i ordenació de l’ús públic del seu entorn | F24: Número habitats creats | G24: 1 | H24: 4 | I24: ALTA | J24: Patrimoni | K24: Eli | L24: CONSERVAR LA NATURA i restaurar els ecosistemes, els processos naturals i seminaturals, la biodiversitat i la geodiversitat associada. | M24: Afavorir ecosistemes complexes, resilients, i d'alta biodiversitat per garantir la recuperació dels processos ecosistèmics | N24: Comú | O24: Obligatori | P24: Si | Q24: 01.3.1 · Afavorir la creació o recuperació d'hàbitats per a la conservació d'espècies (Pla de Salito, cua embassament de Boren, llacuna de Llagunes, basses aig — Número habitats creats
A25: 1. Natura | B25: 01.3.2 | C25: Afavorir la maduresa dels sistemes forestals | D25: Afavorir la maduresa dels sistemes forestals | E25: Participar i impulsar la planificació i execució d'accions d'acceleració de la maduresa forestal en zones boscoses dins l'ENP en base als criteris metodològics predefinits | F25: Superficie amb accelaració maduresa | G25: 30 | H25: 100 | I25: ALTA | J25: Patrimoni | K25: Eli | L25: CONSERVAR LA NATURA i restaurar els ecosistemes, els processos naturals i seminaturals, la biodiversitat i la geodiversitat associada. | M25: Afavorir ecosistemes complexes, resilients, i d'alta biodiversitat per garantir la recuperació dels processos ecosistèmics | N25: Específic | O25: Optatiu | P25: Si | Q25: 01.3.2 · Participar i impulsar la planificació i execució d'accions d'acceleració de la maduresa forestal en zones boscoses dins l'ENP en base als criteris met — Superficie amb accelaració maduresa
A26: 1. Natura | B26: 01.3.3 | C26: Procurar un règim de pertorbacions que afavoreixi l'ús sostenible dels recursos, la biodiversitat i el funcionament del ecosistemes | D26: Procurar un règim de pertorbacions que afavoreixi l'ús sostenible dels recursos, la biodiversitat i el funcionament del ecosistemes | E26: Elaboració d'una planificació d'actuacions de simulació d'incendis forestals naturals (cremes controlades i criteris d'actuació en cas d'incendi) dins l'espai en base als criteris metodològics predefinits (POCTEFA Desbosiguem) a través de la figura de Pla de Prevenció d'Incendis Forestals | F26: Redacció i aprovació del Pla | G26: Redacció | H26: Redacció i aprovació | I26: ALTA | J26: Patrimoni | K26: Oriol | L26: CONSERVAR LA NATURA i restaurar els ecosistemes, els processos naturals i seminaturals, la biodiversitat i la geodiversitat associada. | M26: Afavorir ecosistemes complexes, resilients, i d'alta biodiversitat per garantir la recuperació dels processos ecosistèmics | N26: Específic | O26: Optatiu | P26: Si | Q26: 01.3.3 · Elaboració d'una planificació d'actuacions de simulació d'incendis forestals naturals (cremes controlades i criteris d'actuació en cas d'incendi) dins — Redacció i aprovació del Pla
A27: 1. Natura | B27: 01.3.3 | C27: Procurar un règim de pertorbacions que afavoreixi l'ús sostenible dels recursos, la biodiversitat i el funcionament del ecosistemes | D27: Procurar un règim de pertorbacions que afavoreixi l'ús sostenible dels recursos, la biodiversitat i el funcionament del ecosistemes | E27: Realització de cremes controlades impulsades des del Parc | F27: Número de cremes sol·licitades formalment | G27: 1 | H27: 4 | I27: ALTA | J27: Patrimoni | K27: Oriol | L27: CONSERVAR LA NATURA i restaurar els ecosistemes, els processos naturals i seminaturals, la biodiversitat i la geodiversitat associada. | M27: Afavorir ecosistemes complexes, resilients, i d'alta biodiversitat per garantir la recuperació dels processos ecosistèmics | N27: Específic | O27: Optatiu | P27: Si | Q27: 01.3.3 · Realització de cremes controlades impulsades des del Parc — Número de cremes sol·licitades formalment
A28: 1. Natura | B28: 01.3.4 | C28: Restaurar la dinàmica natural dels rius i altres ecosistemes aquàtics que estiguin dregradats | D28: Restaurar la dinàmica natural dels rius i altres ecosistemes aquàtics que estiguin dregradats | E28: Càlcul i sol·licitud implementació de cabals ecològics en aprofitaments hidroelèctrics dels rius del Parc o bé per desviament d'aigua per rec de prats | F28: Número d'aforaments de cabal ecològic calculats i tramitats | G28: 1 | H28: 6 | I28: MITJANA | J28: Patrimoni | K28: Oriol | L28: CONSERVAR LA NATURA i restaurar els ecosistemes, els processos naturals i seminaturals, la biodiversitat i la geodiversitat associada. | M28: Afavorir ecosistemes complexes, resilients, i d'alta biodiversitat per garantir la recuperació dels processos ecosistèmics | N28: Específic | O28: Optatiu | P28: Si | Q28: 01.3.4 · Càlcul i sol·licitud implementació de cabals ecològics en aprofitaments hidroelèctrics dels rius del Parc o bé per desviament d'aigua per rec de prats — Número d'aforaments de cabal ecològic calculats i tramitats
A29: 1. Natura | B29: 01.3.5 | C29: Fomentar mosaics de paisatges resilients i diversos | D29: Fomentar mosaics de paisatges resilients i diversos | E29: Establir taules de treball entre l’equip del Parc i Comissió Ramadera per desenvolupar una proposta de línies d’ajut que respongui de forma més efectiva a les necessitats del sector i a la preservació dels hàbitats i la cultura associada, incloent la possibilitat de subvencionar pastors, vaquers i eugassers | F29: Número de sessions de treball realitzades | G29: 3 | H29: 10 | I29: ALTA | L29: CONSERVAR LA NATURA i restaurar els ecosistemes, els processos naturals i seminaturals, la biodiversitat i la geodiversitat associada. | M29: Afavorir ecosistemes complexes, resilients, i d'alta biodiversitat per garantir la recuperació dels processos ecosistèmics | N29: Específic | O29: Optatiu | P29: Si | Q29: 01.3.5 · Establir taules de treball entre l’equip del Parc i Comissió Ramadera per desenvolupar una proposta de línies d’ajut que respongui de forma més efecti — Número de sessions de treball realitzades
A30: 1. Natura | B30: 01.3.5 | C30: Fomentar mosaics de paisatges resilients i diversos | D30: Fomentar mosaics de paisatges resilients i diversos | E30: Tramitació d'ajuts per explotacions ramaderes per gestionar l'herbivoria domèstica associada a la ramaderia extensiva | F30: Número expedients d'ajut de maneig de pastures | G30: Tots els sol·licitats | H30: Tots els sol·licitats dins del termini establert | I30: ALTA | J30: Patrimoni | K30: Josep | L30: CONSERVAR LA NATURA i restaurar els ecosistemes, els processos naturals i seminaturals, la biodiversitat i la geodiversitat associada. | M30: Afavorir ecosistemes complexes, resilients, i d'alta biodiversitat per garantir la recuperació dels processos ecosistèmics | N30: Específic | O30: Optatiu | P30: Si | Q30: 01.3.5 · Tramitació d'ajuts per explotacions ramaderes per gestionar l'herbivoria domèstica associada a la ramaderia extensiva — Número expedients d'ajut de maneig de pastures
A31: 1. Natura | B31: 01.3.5 | C31: Fomentar mosaics de paisatges resilients i diversos | D31: Fomentar mosaics de paisatges resilients i diversos | E31: Realització d'un manual tècnic de bones pràctiques en ramaderia extensiva i recuperació i manteniment de pastures aplicat a l'ENP (Projecte REPICA) | F31: Progrés del manual tècnic | G31: Redacció | H31: Redacció, aprovació i divulgació | I31: ALTA | J31: Patrimoni | K31: Oriol | L31: CONSERVAR LA NATURA i restaurar els ecosistemes, els processos naturals i seminaturals, la biodiversitat i la geodiversitat associada. | M31: Afavorir ecosistemes complexes, resilients, i d'alta biodiversitat per garantir la recuperació dels processos ecosistèmics | N31: Específic | O31: Optatiu | P31: Si | Q31: 01.3.5 · Realització d'un manual tècnic de bones pràctiques en ramaderia extensiva i recuperació i manteniment de pastures aplicat a l'ENP (Projecte REPICA) — Progrés del manual tècnic
A32: 1. Natura | B32: 01.3.5 | C32: Fomentar mosaics de paisatges resilients i diversos | D32: Fomentar mosaics de paisatges resilients i diversos | E32: Acords amb ramaders locals per actuacions de restauració i manteniment de pastures al voltant de pobles (POCTEFA Desbosiguem) | F32: Número acords implementats | G32: 1 | H32: 3 | I32: MITJANA | J32: Patrimoni | K32: Josep | L32: CONSERVAR LA NATURA i restaurar els ecosistemes, els processos naturals i seminaturals, la biodiversitat i la geodiversitat associada. | M32: Afavorir ecosistemes complexes, resilients, i d'alta biodiversitat per garantir la recuperació dels processos ecosistèmics | N32: Específic | O32: Optatiu | P32: Si | Q32: 01.3.5 · Acords amb ramaders locals per actuacions de restauració i manteniment de pastures al voltant de pobles (POCTEFA Desbosiguem) — Número acords implementats
A33: 1. Natura | B33: 01.3.5 | C33: Fomentar mosaics de paisatges resilients i diversos | D33: Fomentar mosaics de paisatges resilients i diversos | E33: Afavorir la custòdia del territori amb entitats, per tal d’aconseguir fomentar el paisatge en mosaic i potenciar projectes de forma col·laborativa entre el parc, els ens locals i les entitats de custòdia | F33: Número d’acords de custòdia implementats | G33: 1 | H33: 3 | I33: MITJANA | L33: CONSERVAR LA NATURA i restaurar els ecosistemes, els processos naturals i seminaturals, la biodiversitat i la geodiversitat associada. | M33: Afavorir ecosistemes complexes, resilients, i d'alta biodiversitat per garantir la recuperació dels processos ecosistèmics | N33: Específic | O33: Optatiu | P33: Si | Q33: 01.3.5 · Afavorir la custòdia del territori amb entitats, per tal d’aconseguir fomentar el paisatge en mosaic i potenciar projectes de forma col·laborativa ent — Número d’acords de custòdia implementats
A34: 1. Natura | B34: 01.3.6 | C34: Gestionar i intervenir en la dinàmica de poblacions de fauna que no tenen depredador natural | D34: Gestionar i intervenir en la dinàmica de poblacions de fauna que no tenen depredador natural | E34: Realització d'acords amb societats de caçadors mitjançant informes en els PTGMC | F34: Número informes preceptius de PTGMC | G34: Tots els sol·licitats | H34: Tots els sol·licitats dins de termini | I34: MITJANA | J34: Patrimoni | K34: Eli | L34: CONSERVAR LA NATURA i restaurar els ecosistemes, els processos naturals i seminaturals, la biodiversitat i la geodiversitat associada. | M34: Afavorir ecosistemes complexes, resilients, i d'alta biodiversitat per garantir la recuperació dels processos ecosistèmics | N34: Específic | O34: Optatiu | P34: Si | Q34: 01.3.6 · Realització d'acords amb societats de caçadors mitjançant informes en els PTGMC — Número informes preceptius de PTGMC
A35: 1. Natura | B35: 01.4.1 | C35: Fomentar acords de custòdia en espais d'alt valor dins l'ENP per a la gestió dels elements prioritaris | D35: Fomentar acords de custòdia en espais d'alt valor dins l'ENP per a la gestió dels elements prioritaris | E35: Realització d'acords de custòdia aplicant el model d'acord elaborat per Serveis Centrals | F35: Número d'acords de custòdia duts a terme | G35: 1 | H35: 2 | I35: MÀXIMA | J35: Direccio | K35: Marc | L35: CONSERVAR LA NATURA i restaurar els ecosistemes, els processos naturals i seminaturals, la biodiversitat i la geodiversitat associada. | M35: Planificar l'adaptació dels sistemes naturals al canvi climàtic | N35: Comú | O35: Optatiu | P35: Si | Q35: 01.4.1 · Realització d'acords de custòdia aplicant el model d'acord elaborat per Serveis Centrals — Número d'acords de custòdia duts a terme
A36: 1. Natura | B36: 01.4.2 | C36: Fomentar bones pràctiques entre els col·lectius de propietaris i gestors del territori | D36: Fomentar bones pràctiques entre els col·lectius de propietaris i gestors del territori | E36: Realització d'actuacions demostratives en finques pròpies per al foment de bones pràctiques | F36: Número d'actuacions demostratives en forests i finques patrimonials | G36: 1 | H36: 6 | I36: ALTA | J36: Direccio | K36: Marc | L36: CONSERVAR LA NATURA i restaurar els ecosistemes, els processos naturals i seminaturals, la biodiversitat i la geodiversitat associada. | M36: Planificar l'adaptació dels sistemes naturals al canvi climàtic | N36: Comú | O36: Optatiu | P36: Si | Q36: 01.4.2 · Realització d'actuacions demostratives en finques pròpies per al foment de bones pràctiques — Número d'actuacions demostratives en forests i finques patrimonials
A37: 1. Natura | B37: 01.4.3 | C37: Impulsar la coordinació amb els ens locals i entitats del tercer sector en la gestió finques públiques situades dins d’ENP | D37: Impulsar la coordinació amb els ens locals i entitats del tercer sector en la gestió finques públiques situades dins d’ENP | E37: Realització de projectes de forma col·laborativa amb els ens locals i entitats del tercer sector per a la gestió de les forests comunals | F37: Nombre de projectes col·laboratius | G37: 3 | H37: 6 | I37: MÀXIMA | J37: Direccio | K37: Marc | L37: CONSERVAR LA NATURA i restaurar els ecosistemes, els processos naturals i seminaturals, la biodiversitat i la geodiversitat associada. | M37: Planificar l'adaptació dels sistemes naturals al canvi climàtic | N37: Específic | O37: Optatiu | P37: Si | Q37: 01.4.3 · Realització de projectes de forma col·laborativa amb els ens locals i entitats del tercer sector per a la gestió de les forests comunals — Nombre de projectes col·laboratius
A38: 1. Natura | B38: 02.1.1 | C38: Adaptar i implementar el Pla d'adaptació de l'ENP al canvi climàtic | D38: Adaptar i implementar el Pla d'adaptació de l'ENP al canvi climàtic | E38: Implementació d'accions des del Parc previstes als plans d'adaptació al canvi climàtic municipals aprovats | F38: Nombre d'accions d'adaptació al canvi climàtic municipal implementades | G38: 3 | H38: 6 | I38: ALTA | J38: Direccio | K38: Marc | L38: ADAPTAR ELS ECOSISTEMES AL CANVI CLIMÀTIC i millorar-ne la resiliència en front dels riscos associats. | M38: Alinear l'activitat de propietaris i gestors del territori amb la conservació, millora i restauració dels valors de l'ENP | N38: Comú | O38: Obligatori | P38: Si | Q38: 02.1.1 · Implementació d'accions des del Parc previstes als plans d'adaptació al canvi climàtic municipals aprovats — Nombre d'accions d'adaptació al canvi climàtic municipal implementades
A39: 1. Natura | B39: 02.1.1 | C39: Adaptar i implementar el Pla d'adaptació de l'ENP al canvi climàtic | D39: Adaptar i implementar el Pla d'adaptació de l'ENP al canvi climàtic | E39: Implementació d'accions de mitigació i adaptació al canvi climàtic previst per les empreses i equipaments acreditades per la CETS | F39: Nombre d'accions implementades | G39: 15 | H39: 40 | I39: ALTA | J39: Us Public | K39: Nuria | L39: ADAPTAR ELS ECOSISTEMES AL CANVI CLIMÀTIC i millorar-ne la resiliència en front dels riscos associats. | M39: Alinear l'activitat de propietaris i gestors del territori amb la conservació, millora i restauració dels valors de l'ENP | N39: Comú | O39: Obligatori | P39: Si | Q39: 02.1.1 · Implementació d'accions de mitigació i adaptació al canvi climàtic previst per les empreses i equipaments acreditades per la CETS — Nombre d'accions implementades
A40: 1. Natura | B40: 02.1.2 | C40: Gestionar i planificar els recursos hídrics de l'ENP | D40: Gestionar i planificar els recursos hídrics de l'ENP | E40: Diagnosi dels cabals dels rius del Parc i establiment dels cabals ecològics | F40: Redacció de l'informe | G40: no | H40: si | I40: ALTA | J40: Patrimoni | K40: Oriol | L40: ADAPTAR ELS ECOSISTEMES AL CANVI CLIMÀTIC i millorar-ne la resiliència en front dels riscos associats. | M40: Alinear l'activitat de propietaris i gestors del territori amb la conservació, millora i restauració dels valors de l'ENP | N40: Comú | O40: Obligatori | P40: Si | Q40: 02.1.2 · Diagnosi dels cabals dels rius del Parc i establiment dels cabals ecològics — Redacció de l'informe
A41: 1. Natura | B41: 02.1.3 | C41: Participar en la redacció i execució dels instruments d'ordenació forestal sostenible i per la conservació en finques públiques | D41: Participar en la redacció i execució dels instruments d'ordenació forestal sostenible i per la conservació en finques públiques | E41: Participació en la redacció d'IOF de finques públiques en la fase de zonificació i planificació | F41: Nombre de IOF amb participació activa | G41: 1 | H41: tots els que es redactin | I41: MÀXIMA | J41: Patrimoni | K41: Eli | L41: ADAPTAR ELS ECOSISTEMES AL CANVI CLIMÀTIC i millorar-ne la resiliència en front dels riscos associats. | M41: Alinear l'activitat de propietaris i gestors del territori amb la conservació, millora i restauració dels valors de l'ENP | N41: Específic | O41: Optatiu | P41: Si | Q41: 02.1.3 · Participació en la redacció d'IOF de finques públiques en la fase de zonificació i planificació — Nombre de IOF amb participació activa
A42: 1. Natura | B42: 02.1.3 | C42: Participar en la redacció i execució dels instruments d'ordenació forestal sostenible i per la conservació en finques públiques | D42: Participar en la redacció i execució dels instruments d'ordenació forestal sostenible i per la conservació en finques públiques | E42: Realització d'accions demostratives en finques públiques o amb acord de custòdia de mutu acord amb el DARP i la propietat | F42: Nombre accions demostratives | G42: 5 | H42: 20 | I42: MITJANA | J42: Direccio | K42: Marc | L42: ADAPTAR ELS ECOSISTEMES AL CANVI CLIMÀTIC i millorar-ne la resiliència en front dels riscos associats. | M42: Alinear l'activitat de propietaris i gestors del territori amb la conservació, millora i restauració dels valors de l'ENP | N42: Específic | O42: Optatiu | P42: Si | Q42: 02.1.3 · Realització d'accions demostratives en finques públiques o amb acord de custòdia de mutu acord amb el DARP i la propietat — Nombre accions demostratives
A43: 1. Natura | B43: 02.1.3 | C43: Participar en la redacció i execució dels instruments d'ordenació forestal sostenible i per la conservació en finques públiques | D43: Participar en la redacció i execució dels instruments d'ordenació forestal sostenible i per la conservació en finques públiques | E43: Realització de tractaments silvícoles per afavorir la biodiversitat de mutu acord amb el DARP i la propietat | F43: Ha intervingudes | G43: 20 | H43: 200 | I43: ALTA | J43: Patrimoni | K43: Eli | L43: ADAPTAR ELS ECOSISTEMES AL CANVI CLIMÀTIC i millorar-ne la resiliència en front dels riscos associats. | M43: Alinear l'activitat de propietaris i gestors del territori amb la conservació, millora i restauració dels valors de l'ENP | N43: Específic | O43: Optatiu | P43: Si | Q43: 02.1.3 · Realització de tractaments silvícoles per afavorir la biodiversitat de mutu acord amb el DARP i la propietat — Ha intervingudes
A44: 1. Natura | B44: 02.1.3 | C44: Participar en la redacció i execució dels instruments d'ordenació forestal sostenible i per la conservació en finques públiques | D44: Participar en la redacció i execució dels instruments d'ordenació forestal sostenible i per la conservació en finques públiques | E44: Promoure als ens locals la sol·licitud d'ajuts disponibles per incentivar els serveis ecosistèmics per a la gestió forestal sostenible en finques publiques, incloent les finques patrimonials de la Generalitat amb drets comunals | F44: Número expedients d'ajut sol·licitats promoguts | G44: 2 | H44: 10 | I44: ALTA | J44: Patrimoni | K44: Eli | L44: ADAPTAR ELS ECOSISTEMES AL CANVI CLIMÀTIC i millorar-ne la resiliència en front dels riscos associats. | M44: Alinear l'activitat de propietaris i gestors del territori amb la conservació, millora i restauració dels valors de l'ENP | N44: Específic | O44: Optatiu | P44: Si | Q44: 02.1.3 · Promoure als ens locals la sol·licitud d'ajuts disponibles per incentivar els serveis ecosistèmics per a la gestió forestal sostenible en finques publ — Número expedients d'ajut sol·licitats promoguts
A45: 1. Natura | B45: 02.1.3 | C45: Participar en la redacció i execució dels instruments d'ordenació forestal sostenible i per la conservació en finques públiques | D45: Participar en la redacció i execució dels instruments d'ordenació forestal sostenible i per la conservació en finques públiques | E45: Divulgar i implementar les instruccions acordades entre el DTER i el DARP per compatibilitzar la gestió forestal i la conservació del gall fer, els rapinyaires forestals i altres elements de conservació que s’acordin | F45: Número d’implementacions de les directrius | G45: 10 | H45: Tots els aprofitaments sol·licitats | I45: ALTA | L45: ADAPTAR ELS ECOSISTEMES AL CANVI CLIMÀTIC i millorar-ne la resiliència en front dels riscos associats. | M45: Alinear l'activitat de propietaris i gestors del territori amb la conservació, millora i restauració dels valors de l'ENP | N45: Específic | O45: Optatiu | P45: Si | Q45: 02.1.3 · Divulgar i implementar les instruccions acordades entre el DTER i el DARP per compatibilitzar la gestió forestal i la conservació del gall fer, els ra — Número d’implementacions de les directrius
A46: 1. Natura | B46: 02.1.4 | C46: Promoure la redacció d'instruments d'ordenació forestal per reduir la sensibilitat i vulnerabilitat dels boscos al canvi climàtic en finques privades | D46: Promoure la redacció d'instruments d'ordenació forestal per reduir la sensibilitat i vulnerabilitat dels boscos al canvi climàtic en finques privades | E46: Promoció i participació en la redacció d'IOF de finques privades en la fase de zonificació i planificació | F46: Nombre de IOF amb participació activa | G46: 1 | H46: tots els que es redactin | I46: ALTA | J46: Patrimoni | K46: Eli | L46: ADAPTAR ELS ECOSISTEMES AL CANVI CLIMÀTIC i millorar-ne la resiliència en front dels riscos associats. | M46: Alinear l'activitat de propietaris i gestors del territori amb la conservació, millora i restauració dels valors de l'ENP | N46: Específic | O46: Optatiu | P46: No | Q46: 02.1.4 · Promoció i participació en la redacció d'IOF de finques privades en la fase de zonificació i planificació — Nombre de IOF amb participació activa
A47: 1. Natura | B47: 02.1.4 | C47: Promoure la redacció d'instruments d'ordenació forestal per reduir la sensibilitat i vulnerabilitat dels boscos al canvi climàtic en finques privades | D47: Promoure la redacció d'instruments d'ordenació forestal per reduir la sensibilitat i vulnerabilitat dels boscos al canvi climàtic en finques privades | E47: Promoure als propietaris privats la solicitud d'ajuts disponibles per incentivar els serveis ecosistèmics per a la gestió forestal sostenible en finques privades | F47: Número expedients d'ajut sol·licitats promoguts | G47: 1 | H47: 5 | I47: ALTA | J47: Patrimoni | K47: Eli | L47: ADAPTAR ELS ECOSISTEMES AL CANVI CLIMÀTIC i millorar-ne la resiliència en front dels riscos associats. | M47: Alinear l'activitat de propietaris i gestors del territori amb la conservació, millora i restauració dels valors de l'ENP | N47: Específic | O47: Optatiu | P47: No | Q47: 02.1.4 · Promoure als propietaris privats la solicitud d'ajuts disponibles per incentivar els serveis ecosistèmics per a la gestió forestal sostenible en finqu — Número expedients d'ajut sol·licitats promoguts
A48: 1. Natura | B48: 02.2.1 | C48: Redactar i implementar el Pla de Prevenció d'Incendis | D48: Redactar i implementar el Pla de Prevenció d'Incendis | E48: Elaboració i aprovació del Pla de Prevenció d'Incendis i gestió del foc (POCTEFA Desbosiguem) de mutu acord amb el DARP i ens locals | F48: Redacció i aprovació del Pla | G48: Redacció | H48: Redaccio i aprovació | I48: ALTA | J48: Direcció | K48: Marc | L48: ADAPTAR ELS ECOSISTEMES AL CANVI CLIMÀTIC i millorar-ne la resiliència en front dels riscos associats. | M48: Planificar la prevenció i extinció d’incendis forestals i la gestió del foc de forma coordinada amb els diferents agents del territori | N48: Comú | O48: Obligatori | P48: Si | Q48: 02.2.1 · Elaboració i aprovació del Pla de Prevenció d'Incendis i gestió del foc (POCTEFA Desbosiguem) de mutu acord amb el DARP i ens locals — Redacció i aprovació del Pla
A49: 1. Natura | B49: 02.2.1 | C49: Redactar i implementar el Pla de Prevenció d'Incendis | D49: Redactar i implementar el Pla de Prevenció d'Incendis | E49: Realització d'accions de prevenció d'incendis forestals planificades: linies de defensa en vials forestals, punts d’aigua i actuacions en punts estratègics de gestió | F49: Número accions de prevenció d'incendis forestals | G49: 3 | H49: 8 | I49: MITJANA | J49: Millora rural | K49: Natalia | L49: ADAPTAR ELS ECOSISTEMES AL CANVI CLIMÀTIC i millorar-ne la resiliència en front dels riscos associats. | M49: Planificar la prevenció i extinció d’incendis forestals i la gestió del foc de forma coordinada amb els diferents agents del territori | N49: Comú | O49: Obligatori | P49: Si | Q49: 02.2.1 · Realització d'accions de prevenció d'incendis forestals planificades: linies de defensa en vials forestals, punts d’aigua i actuacions en punts estrat — Número accions de prevenció d'incendis forestals
A50: 1. Natura | B50: 02.2.2 | C50: Definir i planificar la gestió del foc per a la millora de l'ENP | D50: Definir i planificar la gestió del foc per a la millora de l'ENP | E50: Elaboració i aprovació del Pla de Prevenció d'Incendis i gestió del foc (POCTEFA Desbosiguem) | F50: Redacció i aprovació del Pla | G50: Redacció | H50: Redacció i aprovació | I50: ALTA | J50: Direcció | K50: Marc | L50: ADAPTAR ELS ECOSISTEMES AL CANVI CLIMÀTIC i millorar-ne la resiliència en front dels riscos associats. | M50: Planificar la prevenció i extinció d’incendis forestals i la gestió del foc de forma coordinada amb els diferents agents del territori | N50: Específic | O50: Optatiu | P50: Si | Q50: 02.2.2 · Elaboració i aprovació del Pla de Prevenció d'Incendis i gestió del foc (POCTEFA Desbosiguem) — Redacció i aprovació del Pla
A51: 1. Natura | B51: 02.2.2 | C51: Definir i planificar la gestió del foc per a la millora de l'ENP | D51: Definir i planificar la gestió del foc per a la millora de l'ENP | E51: Realització de cremes controlades impulsades des del Parc | F51: Número de cremes controlades | G51: 1 | H51: 4 | I51: ALTA | J51: Patrimoni | K51: Oriol | L51: ADAPTAR ELS ECOSISTEMES AL CANVI CLIMÀTIC i millorar-ne la resiliència en front dels riscos associats. | M51: Planificar la prevenció i extinció d’incendis forestals i la gestió del foc de forma coordinada amb els diferents agents del territori | N51: Específic | O51: Optatiu | P51: Si | Q51: 02.2.2 · Realització de cremes controlades impulsades des del Parc — Número de cremes controlades
A52: 1. Natura | B52: 02.2.3 | C52: Treballar per a la prevenció d'incendis juntament amb els propietaris, ajuntaments, protecció civil, ADF i bombers. | D52: Treballar per a la prevenció d'incendis juntament amb els propietaris, ajuntaments, protecció civil, ADF i bombers. | E52: Execució d'altres actuacions de prevenció d'incendis forestals no recollides al Pla | F52: Número accions de prevenció d'incendis forestals | G52: 2 | H52: 10 | I52: MITJANA | J52: Millora rural | K52: Natalia | L52: ADAPTAR ELS ECOSISTEMES AL CANVI CLIMÀTIC i millorar-ne la resiliència en front dels riscos associats. | M52: Planificar la prevenció i extinció d’incendis forestals i la gestió del foc de forma coordinada amb els diferents agents del territori | N52: Comú | O52: Obligatori | P52: Si | Q52: 02.2.3 · Execució d'altres actuacions de prevenció d'incendis forestals no recollides al Pla — Número accions de prevenció d'incendis forestals
A53: 1. Natura | B53: 03.1.1 | C53: Participar en les consultes dels procesos d'Avaluació Ambiental que afectin directament o indirectament l’espai del ENP | D53: Participar en les consultes dels procesos d'Avaluació Ambiental que afectin directament o indirectament l’espai del ENP | E53: Participació a les taules d'avaluació via informe preceptiu | F53: Número d'informes preceptius d'AIA | G53: 15 | H53: 40 | I53: MITJANA | J53: Patrimoni | K53: Eli | L53: PROTEGIR LA BIODIVERSITAT, i especialment els elements fràgils i amenaçats, d’interès comunitari o de major interès natural. | M53: Prevenir, minimitzar i compensar els impactes ambientals dels usos i activitats que es desenvolupin en l'àmbit de l'ENP | N53: Comú | O53: Obligatori | P53: No | Q53: 03.1.1 · Participació a les taules d'avaluació via informe preceptiu — Número d'informes preceptius d'AIA
A54: 1. Natura | B54: 03.1.2 | C54: Exercir un seguiment efectiu de les obres al Parc juntament amb les Oficines Territorials d'Acció i Avaluació Ambiental als efectes d'assegurar la correcta translació de la tutela administrativa. | D54: Exercir un seguiment efectiu de les obres al Parc juntament amb les Oficines Territorials d'Acció i Avaluació Ambiental als efectes d'assegurar la correcta translació de la tutela administrativa. | E54: Seguiment de les obres i altres actuacions informades que afecten i es realitzen dins dels límits del PNAP+XN2000 Alt Pallars | F54: Número d'actes de visites | G54: 10% dels que requereixin visita | H54: 100% dels que requereixin visita | I54: MITJANA | J54: Patrimoni | K54: Josep | L54: PROTEGIR LA BIODIVERSITAT, i especialment els elements fràgils i amenaçats, d’interès comunitari o de major interès natural. | M54: Prevenir, minimitzar i compensar els impactes ambientals dels usos i activitats que es desenvolupin en l'àmbit de l'ENP | N54: Comú | O54: Obligatori | P54: Si | Q54: 03.1.2 · Seguiment de les obres i altres actuacions informades que afecten i es realitzen dins dels límits del PNAP+XN2000 Alt Pallars — Número d'actes de visites
A55: 1. Natura | B55: 03.1.3 | C55: Participar en la compensació d'impactes residuals durant els processos d'avaluació ambiental mitjançant la identificació de necessitats d'actuació prioritària dins i fora dels límits de l’ENP | D55: Participar en la compensació d'impactes residuals durant els processos d'avaluació ambiental mitjançant la identificació de necessitats d'actuació prioritària dins i fora dels límits de l’ENP | E55: Establiment de mesures compensatories en cas de projectes que ho requereixin | F55: Número de mesures compensatories informades | G55: 0 | H55: 4 | I55: MITJANA | J55: Patrimoni | K55: Eli | L55: PROTEGIR LA BIODIVERSITAT, i especialment els elements fràgils i amenaçats, d’interès comunitari o de major interès natural. | M55: Prevenir, minimitzar i compensar els impactes ambientals dels usos i activitats que es desenvolupin en l'àmbit de l'ENP | N55: Comú | O55: Optatiu | P55: No | Q55: 03.1.3 · Establiment de mesures compensatories en cas de projectes que ho requereixin — Número de mesures compensatories informades
A56: 1. Natura | B56: 03.2.1 | C56: Participar en l'elaboració dels instruments de planificació de l'ENP | D56: Participar en l'elaboració dels instruments de planificació de l'ENP | E56: Participació en l'elaboració del Pla de Protecció (PP) i Pla Rector d'usos i Gestió (PRUG) juntament amb l'SPEN | F56: Participació realitzada | G56: no | H56: si | I56: MÀXIMA | J56: Direcció | K56: Marc | L56: PROTEGIR LA BIODIVERSITAT, i especialment els elements fràgils i amenaçats, d’interès comunitari o de major interès natural. | M56: Garantir el compliment dels objectius de conservació dotant l'ENP de la planificació adequada segons estableix la normativa vigent (Pla de Protecció, PRUG, plans específics...) | N56: Comú | O56: Obligatori | P56: Si | Q56: 03.2.1 · Participació en l'elaboració del Pla de Protecció (PP) i Pla Rector d'usos i Gestió (PRUG) juntament amb l'SPEN — Participació realitzada
A57: 1. Natura | B57: 03.3.1 | C57: Vetllar pel manteniment del cabal ecològic dels rius definit al Pla sectorial corresponent | D57: Vetllar pel manteniment del cabal ecològic dels rius definit al Pla sectorial corresponent | E57: Participació en el seguiment del cabal en els trams dins ENP | F57: Número estacions de seguiment del Parc | G57: 5 | H57: 10 | I57: ALTA | J57: Patrimoni | K57: Oriol | L57: PROTEGIR LA BIODIVERSITAT, i especialment els elements fràgils i amenaçats, d’interès comunitari o de major interès natural. | M57: Vetllar pel manteniment dels cabals ecològics i la bona qualitat dels cursos fluvials de l'ENP de forma coordinada amb l'administració competent | N57: Específic | O57: Optatiu | P57: Si | Q57: 03.3.1 · Participació en el seguiment del cabal en els trams dins ENP — Número estacions de seguiment del Parc
A58: 1. Natura | B58: 03.3.1 | C58: Vetllar pel manteniment del cabal ecològic dels rius definit al Pla sectorial corresponent | D58: Vetllar pel manteniment del cabal ecològic dels rius definit al Pla sectorial corresponent | E58: Impuls del control per incompliment de la normativa i el seu trasllat cap a l'administració competent | F58: Número d'informes per incompliment tramesos al CAR i/o ACA i/o CHE | G58: 0 | H58: Tots els que es detectin | I58: MITJANA | J58: Direccio | K58: Marc | L58: PROTEGIR LA BIODIVERSITAT, i especialment els elements fràgils i amenaçats, d’interès comunitari o de major interès natural. | M58: Vetllar pel manteniment dels cabals ecològics i la bona qualitat dels cursos fluvials de l'ENP de forma coordinada amb l'administració competent | N58: Específic | O58: Optatiu | P58: Si | Q58: 03.3.1 · Impuls del control per incompliment de la normativa i el seu trasllat cap a l'administració competent — Número d'informes per incompliment tramesos al CAR i/o ACA i/o CHE
A59: 1. Natura | B59: 03.3.1 | C59: Vetllar pel manteniment del cabal ecològic dels rius definit al Pla sectorial corresponent | D59: Vetllar pel manteniment del cabal ecològic dels rius definit al Pla sectorial corresponent | E59: Participació en el Pla Hidrològic de la Conca de l'Ebre | F59: Redacció informe preceptiu vers el Pla | G59: 0 | H59: 1 | I59: ALTA | J59: Patrimoni | K59: Eli | L59: PROTEGIR LA BIODIVERSITAT, i especialment els elements fràgils i amenaçats, d’interès comunitari o de major interès natural. | M59: Vetllar pel manteniment dels cabals ecològics i la bona qualitat dels cursos fluvials de l'ENP de forma coordinada amb l'administració competent | N59: Específic | O59: Optatiu | P59: Si | Q59: 03.3.1 · Participació en el Pla Hidrològic de la Conca de l'Ebre — Redacció informe preceptiu vers el Pla
A60: 1. Natura | B60: 03.3.1 | C60: Vetllar pel manteniment del cabal ecològic dels rius definit al Pla sectorial corresponent | D60: Vetllar pel manteniment del cabal ecològic dels rius definit al Pla sectorial corresponent | E60: Integració i participació en les comissions de desembassament prevegi la CHE | F60: Número de participacions | G60: 0 | H60: Totes les comissions es facin | I60: MITJANA | J60: Patrimoni | K60: Eli | L60: PROTEGIR LA BIODIVERSITAT, i especialment els elements fràgils i amenaçats, d’interès comunitari o de major interès natural. | M60: Vetllar pel manteniment dels cabals ecològics i la bona qualitat dels cursos fluvials de l'ENP de forma coordinada amb l'administració competent | N60: Específic | O60: Optatiu | P60: Si | Q60: 03.3.1 · Integració i participació en les comissions de desembassament prevegi la CHE — Número de participacions
A61: 1. Natura | B61: 03.3.2 | C61: Vetllar per la regulació dels dragatges, canalitzacions o implantació d'activitats extractives que puguin modificar la llera i el cabal dels rius | D61: Vetllar per la regulació dels dragatges, canalitzacions o implantació d'activitats extractives que puguin modificar la llera i el cabal dels rius | E61: Informes preceptius i requeriments emesos d'aquest àmbit | F61: Número informes preceptius i requeriments | G61: 0 | H61: Tots els que es demanin | I61: ALTA | J61: Patrimoni | K61: Eli | L61: PROTEGIR LA BIODIVERSITAT, i especialment els elements fràgils i amenaçats, d’interès comunitari o de major interès natural. | M61: Vetllar pel manteniment dels cabals ecològics i la bona qualitat dels cursos fluvials de l'ENP de forma coordinada amb l'administració competent | N61: Específic | O61: Optatiu | P61: No | Q61: 03.3.2 · Informes preceptius i requeriments emesos d'aquest àmbit — Número informes preceptius i requeriments
A62: 1. Natura | B62: 03.3.3 | C62: Avaluar i controlar les actuacions que produeixin drenatges, captacions o que puguin impedir l’arribada d’aigua tant superficial com freàtica | D62: Avaluar i controlar les actuacions que produeixin drenatges, captacions o que puguin impedir l’arribada d’aigua tant superficial com freàtica | E62: Participació, de forma coordinada amb l'administració competent, en l'avaluació i control d'actuacions dins els límits de l'ENP. | F62: Número informes precepetius | G62: 0 | H62: Tots els que es demanin | I62: ALTA | J62: Patrimoni | K62: Eli | L62: PROTEGIR LA BIODIVERSITAT, i especialment els elements fràgils i amenaçats, d’interès comunitari o de major interès natural. | M62: Vetllar pel manteniment dels cabals ecològics i la bona qualitat dels cursos fluvials de l'ENP de forma coordinada amb l'administració competent | N62: Específic | O62: Optatiu | P62: No | Q62: 03.3.3 · Participació, de forma coordinada amb l'administració competent, en l'avaluació i control d'actuacions dins els límits de l'ENP. — Número informes precepetius
A63: 1. Natura | B63: 03.3.3 | C63: Avaluar i controlar les actuacions que produeixin drenatges, captacions o que puguin impedir l’arribada d’aigua tant superficial com freàtica | D63: Avaluar i controlar les actuacions que produeixin drenatges, captacions o que puguin impedir l’arribada d’aigua tant superficial com freàtica | E63: Impuls del control per incompliment de la normativa i el seu trasllat cap a l'administració competent | F63: Número d'informes per incompliment tramesos al CAR i/o ACA i/o CHE | G63: 0 | H63: Tots els que es detectin | I63: ALTA | J63: Direccio | K63: Marc | L63: PROTEGIR LA BIODIVERSITAT, i especialment els elements fràgils i amenaçats, d’interès comunitari o de major interès natural. | M63: Vetllar pel manteniment dels cabals ecològics i la bona qualitat dels cursos fluvials de l'ENP de forma coordinada amb l'administració competent | N63: Específic | O63: Optatiu | P63: No | Q63: 03.3.3 · Impuls del control per incompliment de la normativa i el seu trasllat cap a l'administració competent — Número d'informes per incompliment tramesos al CAR i/o ACA i/o CHE
A64: 1. Natura | B64: 03.3.4 | C64: Vetllar pel compliment de la normativa de depuració dels efluents agroramaders, urbans i industrials que s'aboquen als cursos fluvials | D64: Vetllar pel compliment de la normativa de depuració dels efluents agroramaders, urbans i industrials que s'aboquen als cursos fluvials | E64: Impuls del control per incompliment de la normativa i el seu trasllat cap a l'administració competent | F64: Número d'informes per incompliment tramesos al CAR i/o ACA i/o CHE | G64: 0 | H64: Tots els que es detectin | I64: ALTA | J64: Direccio | K64: Marc | L64: PROTEGIR LA BIODIVERSITAT, i especialment els elements fràgils i amenaçats, d’interès comunitari o de major interès natural. | M64: Vetllar pel manteniment dels cabals ecològics i la bona qualitat dels cursos fluvials de l'ENP de forma coordinada amb l'administració competent | N64: Específic | O64: Optatiu | P64: No | Q64: 03.3.4 · Impuls del control per incompliment de la normativa i el seu trasllat cap a l'administració competent — Número d'informes per incompliment tramesos al CAR i/o ACA i/o CHE
A65: 1. Natura | B65: 03.4.1 | C65: Identificar espais prioritaris per a la compra de terrenys de més valor dins l'ENP | D65: Identificar espais prioritaris per a la compra de terrenys de més valor dins l'ENP | E65: Participació en la identificació de finques prioritàries en base als criteris indicats | F65: Número de finques identificades | G65: 1 | H65: 5 | I65: ALTA | J65: Direccio | K65: Marc | L65: PROTEGIR LA BIODIVERSITAT, i especialment els elements fràgils i amenaçats, d’interès comunitari o de major interès natural. | M65: Incrementar el patrimoni públic destinat a la conservació i millora del patrimoni natural | N65: Comú | O65: Optatiu | P65: Si | Q65: 03.4.1 · Participació en la identificació de finques prioritàries en base als criteris indicats — Número de finques identificades
A66: 1. Natura | B66: 03.4.2 | C66: Identificar espais prioritaris per a la gestió directa | D66: Identificar espais prioritaris per a la gestió directa | E66: Participació en la identificació de finques prioritàries en base als criteris indicats | F66: Número de finques identificades | G66: 5 | H66: 8 | I66: ALTA | J66: Direccio | K66: Marc | L66: PROTEGIR LA BIODIVERSITAT, i especialment els elements fràgils i amenaçats, d’interès comunitari o de major interès natural. | M66: Incrementar el patrimoni públic destinat a la conservació i millora del patrimoni natural | N66: Comú | O66: Optatiu | P66: Si | Q66: 03.4.2 · Participació en la identificació de finques prioritàries en base als criteris indicats — Número de finques identificades
A67: 1. Natura | B67: 03.4.2 | C67: Identificar espais prioritaris per a la gestió directa | D67: Identificar espais prioritaris per a la gestió directa | E67: Participació i foment de la compra o adquisició de drets d’aprofitament | F67: Número d'expedients de compra o adquisició de drets tramesos | G67: 1 | H67: 5 | I67: ALTA | J67: Direccio | K67: Marc | L67: PROTEGIR LA BIODIVERSITAT, i especialment els elements fràgils i amenaçats, d’interès comunitari o de major interès natural. | M67: Incrementar el patrimoni públic destinat a la conservació i millora del patrimoni natural | N67: Comú | O67: Optatiu | P67: Si | Q67: 03.4.2 · Participació i foment de la compra o adquisició de drets d’aprofitament — Número d'expedients de compra o adquisició de drets tramesos
A68: 2. Cultura | B68: 04.1.1 | C68: Elaborar l'inventari i cartografia de patrimoni cultural de l'ENP, que també inclogui el patrimoni etnològic i immaterial | D68: Elaborar l'inventari i cartografia de patrimoni cultural de l'ENP, que també inclogui el patrimoni etnològic i immaterial | E68: Actualització i georeferenciació dels inventaris del patrimoni arquitectònic i arqueològic existents del Parc | F68: Número d'elements actualitzats | G68: 10 | H68: 50 | I68: MITJANA | J68: Direccio | K68: Marc | L68: CONSERVAR ELS ELEMENTS CULTURALS materials i immaterials vinculats a la natura | M68: Millorar el coneixement disponible sobre el patrimoni arquitectònic i cultural (material i immaterial) vinculat al patrimoni natural, el seu estat de conservació i els estils propis dels territoris de l'ENP | N68: Comú | O68: Optatiu | P68: Si | Q68: 04.1.1 · Actualització i georeferenciació dels inventaris del patrimoni arquitectònic i arqueològic existents del Parc — Número d'elements actualitzats
A69: 2. Cultura | B69: 04.1.1 | C69: Elaborar l'inventari i cartografia de patrimoni cultural de l'ENP, que també inclogui el patrimoni etnològic i immaterial | D69: Elaborar l'inventari i cartografia de patrimoni cultural de l'ENP, que també inclogui el patrimoni etnològic i immaterial | E69: Prospecció arqueològica de zones alpines del Parc: massís Marimanha, Vall d'Unarre, Vall de Tavascan i capçalera de la Vall Ferrera | F69: Número d'elements prospectats | G69: 20 | H69: 100 | I69: MITJANA | J69: Direccio | K69: Marc | L69: CONSERVAR ELS ELEMENTS CULTURALS materials i immaterials vinculats a la natura | M69: Millorar el coneixement disponible sobre el patrimoni arquitectònic i cultural (material i immaterial) vinculat al patrimoni natural, el seu estat de conservació i els estils propis dels territoris de l'ENP | N69: Comú | O69: Optatiu | P69: Si | Q69: 04.1.1 · Prospecció arqueològica de zones alpines del Parc: massís Marimanha, Vall d'Unarre, Vall de Tavascan i capçalera de la Vall Ferrera — Número d'elements prospectats
A70: 2. Cultura | B70: 04.1.1 | C70: Elaborar l'inventari i cartografia de patrimoni cultural de l'ENP, que també inclogui el patrimoni etnològic i immaterial | D70: Elaborar l'inventari i cartografia de patrimoni cultural de l'ENP, que també inclogui el patrimoni etnològic i immaterial | E70: Continuar les excavacions arqueològiques de l'explotació siderúrgica de Virós, Cova de l'Home Mort, Santa Creu de Llagunes, i iniciar l'excavació de Sant Martí del Pui i Sant Joan de l’Erm vell, i accions de conservació i divulgació d’aquests jaciments | F70: Número de campanyes d'excavació realitzades | G70: 3 | H70: 10 | I70: ALTA | J70: Direccio | K70: Marc | L70: CONSERVAR ELS ELEMENTS CULTURALS materials i immaterials vinculats a la natura | M70: Millorar el coneixement disponible sobre el patrimoni arquitectònic i cultural (material i immaterial) vinculat al patrimoni natural, el seu estat de conservació i els estils propis dels territoris de l'ENP | N70: Comú | O70: Optatiu | P70: Si | Q70: 04.1.1 · Continuar les excavacions arqueològiques de l'explotació siderúrgica de Virós, Cova de l'Home Mort, Santa Creu de Llagunes, i iniciar l'excavació de S — Número de campanyes d'excavació realitzades
A71: 2. Cultura | B71: 04.1.1 | C71: Elaborar l'inventari i cartografia de patrimoni cultural de l'ENP, que també inclogui el patrimoni etnològic i immaterial | D71: Elaborar l'inventari i cartografia de patrimoni cultural de l'ENP, que també inclogui el patrimoni etnològic i immaterial | E71: Actualització de l'inventari de les infraestructures agroramaderes històriques del Parc | F71: Número d'infraestructures inventariades i/o actualitzades | G71: 10 | H71: 50 | I71: BAIXA | J71: Direccio | K71: Marc | L71: CONSERVAR ELS ELEMENTS CULTURALS materials i immaterials vinculats a la natura | M71: Millorar el coneixement disponible sobre el patrimoni arquitectònic i cultural (material i immaterial) vinculat al patrimoni natural, el seu estat de conservació i els estils propis dels territoris de l'ENP | N71: Comú | O71: Optatiu | P71: Si | Q71: 04.1.1 · Actualització de l'inventari de les infraestructures agroramaderes històriques del Parc — Número d'infraestructures inventariades i/o actualitzades
A72: 2. Cultura | B72: 04.1.1 | C72: Elaborar l'inventari i cartografia de patrimoni cultural de l'ENP, que també inclogui el patrimoni etnològic i immaterial | D72: Elaborar l'inventari i cartografia de patrimoni cultural de l'ENP, que també inclogui el patrimoni etnològic i immaterial | E72: Inventari del llegat cultural de la zona "Wild Rivers" del curs alt del Noguera Pallaresa | F72: Número d'elements inventariats | G72: 5 | H72: 20 | I72: MITJANA | J72: Direccio | K72: Febrer | L72: CONSERVAR ELS ELEMENTS CULTURALS materials i immaterials vinculats a la natura | M72: Millorar el coneixement disponible sobre el patrimoni arquitectònic i cultural (material i immaterial) vinculat al patrimoni natural, el seu estat de conservació i els estils propis dels territoris de l'ENP | N72: Comú | O72: Optatiu | P72: Si | Q72: 04.1.1 · Inventari del llegat cultural de la zona "Wild Rivers" del curs alt del Noguera Pallaresa — Número d'elements inventariats
A73: 2. Cultura | B73: 04.1.1 | C73: Elaborar l'inventari i cartografia de patrimoni cultural de l'ENP, que també inclogui el patrimoni etnològic i immaterial | D73: Elaborar l'inventari i cartografia de patrimoni cultural de l'ENP, que també inclogui el patrimoni etnològic i immaterial | E73: Elaborar un registre del patrimoni etnogràfic i immaterial no georeferenciable | F73: Número d'elements registrats | G73: 5 | H73: 30 | I73: MITJANA | L73: CONSERVAR ELS ELEMENTS CULTURALS materials i immaterials vinculats a la natura | M73: Millorar el coneixement disponible sobre el patrimoni arquitectònic i cultural (material i immaterial) vinculat al patrimoni natural, el seu estat de conservació i els estils propis dels territoris de l'ENP | N73: Comú | O73: Optatiu | P73: Si | Q73: 04.1.1 · Elaborar un registre del patrimoni etnogràfic i immaterial no georeferenciable — Número d'elements registrats
A74: 2. Cultura | B74: 04.1.2 | C74: Elaborar el catàleg lingüístic (localismes) de patrimoni natural, geografia popular, festes i activitats tradicionals de l'ENP | D74: Elaborar el catàleg lingüístic (localismes) de patrimoni natural, geografia popular, festes i activitats tradicionals de l'ENP | E74: Recopilació i georeferenciació de toponimia popular del Parc no present o errònia de la cartografia ICGC en base a la memòria oral amb col·laboració amb les entitats locals | F74: Número de topònims recopilats | G74: 25 | H74: 200 | I74: MÀXIMA | J74: Direccio | K74: Marc | L74: CONSERVAR ELS ELEMENTS CULTURALS materials i immaterials vinculats a la natura | M74: Millorar el coneixement disponible sobre el patrimoni arquitectònic i cultural (material i immaterial) vinculat al patrimoni natural, el seu estat de conservació i els estils propis dels territoris de l'ENP | N74: Comú | O74: Optatiu | P74: Si | Q74: 04.1.2 · Recopilació i georeferenciació de toponimia popular del Parc no present o errònia de la cartografia ICGC en base a la memòria oral amb col·laboració a — Número de topònims recopilats
A75: 2. Cultura | B75: 04.1.2 | C75: Elaborar el catàleg lingüístic (localismes) de patrimoni natural, geografia popular, festes i activitats tradicionals de l'ENP | D75: Elaborar el catàleg lingüístic (localismes) de patrimoni natural, geografia popular, festes i activitats tradicionals de l'ENP | E75: Donar suport a les iniciatives i publicacions dedicades a recuperar la parla pallaresa | F75: Número d’accions de suport | G75: 1 | H75: 5 | I75: MITJANA | L75: CONSERVAR ELS ELEMENTS CULTURALS materials i immaterials vinculats a la natura | M75: Millorar el coneixement disponible sobre el patrimoni arquitectònic i cultural (material i immaterial) vinculat al patrimoni natural, el seu estat de conservació i els estils propis dels territoris de l'ENP | N75: Comú | O75: Optatiu | P75: Si | Q75: 04.1.2 · Donar suport a les iniciatives i publicacions dedicades a recuperar la parla pallaresa — Número d’accions de suport
A76: 2. Cultura | B76: 04.1.3 | C76: Elaborar la cartografia de la xarxa de camins ramaders i senders tradicionals de l'ENP | D76: Elaborar la cartografia de la xarxa de camins ramaders i senders tradicionals de l'ENP | E76: Actualització i millora de la precisió del traçat de l'inventari de camins ramaders i històrics del Parc (en base a l'inventari del 1999 del CCPS) junt amb els ens locals | F76: Número de camins actualitzats | G76: 20 | H76: 150 | I76: ALTA | J76: Direccio | K76: Marc | L76: CONSERVAR ELS ELEMENTS CULTURALS materials i immaterials vinculats a la natura | M76: Millorar el coneixement disponible sobre el patrimoni arquitectònic i cultural (material i immaterial) vinculat al patrimoni natural, el seu estat de conservació i els estils propis dels territoris de l'ENP | N76: Comú | O76: Optatiu | P76: Si | Q76: 04.1.3 · Actualització i millora de la precisió del traçat de l'inventari de camins ramaders i històrics del Parc (en base a l'inventari del 1999 del CCPS) jun — Número de camins actualitzats
A77: 2. Cultura | B77: 04.2.1 | C77: Identificar els ens de referència en patrimoni cultural (entitats, associacions, museus i ecomuseus, etc.) en l'àmbit de l'ENP | D77: Identificar els ens de referència en patrimoni cultural (entitats, associacions, museus i ecomuseus, etc.) en l'àmbit de l'ENP | E77: Actualització del mapa d'entitats, associacions, museus, ecomuseus, OPEI (Observatori del Patrimoni Etnològic i Immaterial), etc. | F77: Número d'ens actualitzats | G77: 5 | H77: 20 | I77: MITJANA | J77: Direccio | K77: Marc | L77: CONSERVAR ELS ELEMENTS CULTURALS materials i immaterials vinculats a la natura | M77: Conservar i gestionar el patrimoni cultural de l'ENP de forma coordinada amb els agents responsables i entitats de referència | N77: Comú | O77: Obligatori | P77: No | Q77: 04.2.1 · Actualització del mapa d'entitats, associacions, museus, ecomuseus, OPEI (Observatori del Patrimoni Etnològic i Immaterial), etc. — Número d'ens actualitzats
A78: 2. Cultura | B78: 04.2.2 | C78: Articular treballs conjunts entre l'ENP i representants, gestors o custodis del patrimoni cultural per a la seva protecció i millora | D78: Articular treballs conjunts entre l'ENP i representants, gestors o custodis del patrimoni cultural per a la seva protecció i millora | E78: Continuar impulsant el projecte de parcs i museus junt amb l'Ecomuseu de les Vals d'Àneu | F78: Número d'accions realitzades vinculades al projecte | G78: 4 | H78: 8 | I78: ALTA | J78: Direccio | K78: Marc | L78: CONSERVAR ELS ELEMENTS CULTURALS materials i immaterials vinculats a la natura | M78: Conservar i gestionar el patrimoni cultural de l'ENP de forma coordinada amb els agents responsables i entitats de referència | N78: Comú | O78: Optatiu | P78: Si | Q78: 04.2.2 · Continuar impulsant el projecte de parcs i museus junt amb l'Ecomuseu de les Vals d'Àneu — Número d'accions realitzades vinculades al projecte
A79: 2. Cultura | B79: 04.2.2 | C79: Articular treballs conjunts entre l'ENP i representants, gestors o custodis del patrimoni cultural per a la seva protecció i millora | D79: Articular treballs conjunts entre l'ENP i representants, gestors o custodis del patrimoni cultural per a la seva protecció i millora | E79: Impulsar la bona cooperació, i si s'escau, establir convenis de col·laboració amb els equipaments culturals de l'àmbit del Parc, conjuntament amb el grup de treball de cultura de la CETS (acció 32): Ecomuseu de les Valls d'Àneu (principal), Espai Ermengol de la Seu, Museu Diocesà de la Seu, Centre d'Interpretació de l'Aigua de Tavascan, Molí de Casa Bellera de Rialp, Museu de les Papalllones, Museu de la Fusta d'Àreu (MNAC), Era d'Ortega de Peramea, Museu del Despoblat de Sta Creu de Llagunes, Museu de Camins, Presó Museu del Camí de la llibertat, Museu de la Sal (MNAC), Ecomuseu de Casa Sintet, Casa Cerdà d'Àreu, Casa de l'Os Bru dels Pirineus, Cente d'Interpretació de les Viles Closes d'Escaló, el Centre de Descoberta de les Ciències de la Terra, l’espai Puiolo de Pujalt, el Romànic visitable a través del Bisbat d’Urgell i altres entitats, ruta de les esglésies barroques de la Vall de Cardós i altres es puguin afegir o inaugurar properament. Alguns d’aquests convenis s’estudiarà la possible integració com equipament propi del Parc, com seria la Casa de l’Os Bru, el Centre de Descoberta de ciències de la Terra o ús compartit com l’espai Puiolo de Pujalt | F79: Número d'acords o convenis realitzats | G79: 1 | H79: 17 | I79: ALTA | J79: Direccio | K79: Marc | L79: CONSERVAR ELS ELEMENTS CULTURALS materials i immaterials vinculats a la natura | M79: Conservar i gestionar el patrimoni cultural de l'ENP de forma coordinada amb els agents responsables i entitats de referència | N79: Comú | O79: Optatiu | P79: Si | Q79: 04.2.2 · Impulsar la bona cooperació, i si s'escau, establir convenis de col·laboració amb els equipaments culturals de l'àmbit del Parc, conjuntament amb el g — Número d'acords o convenis realitzats
A80: 2. Cultura | B80: 04.2.2 | C80: Articular treballs conjunts entre l'ENP i representants, gestors o custodis del patrimoni cultural per a la seva protecció i millora | D80: Articular treballs conjunts entre l'ENP i representants, gestors o custodis del patrimoni cultural per a la seva protecció i millora | E80: Fomentar la cooperació tècnica del gestors del PNAP amb els gestors de l'Ecomuseu de les Valls d'Àneu com a centre estructrual de gestió del Parc en l'àmbit cultural | F80: Número d'accions realitzades conjuntament | G80: 4 | H80: 12 | I80: MÀXIMA | J80: Direccio | K80: Marc | L80: CONSERVAR ELS ELEMENTS CULTURALS materials i immaterials vinculats a la natura | M80: Conservar i gestionar el patrimoni cultural de l'ENP de forma coordinada amb els agents responsables i entitats de referència | N80: Comú | O80: Optatiu | P80: Si | Q80: 04.2.2 · Fomentar la cooperació tècnica del gestors del PNAP amb els gestors de l'Ecomuseu de les Valls d'Àneu com a centre estructrual de gestió del Parc en l — Número d'accions realitzades conjuntament
A81: 2. Cultura | B81: 04.2.3 | C81: Coordinar i participar dels treballs de restauració arquitectònica i del patrimoni cultural | D81: Coordinar i participar dels treballs de restauració arquitectònica i del patrimoni cultural | E81: Coordinació i participació de l'equip tècnic (propi) i servei de manteniment amb els responsables pertinents en els treballs de restauració arquitectònica i del patrimoni cultural | F81: Número d'accions realitzades | G81: 2 | H81: 8 | I81: MITJANA | J81: Direccio | K81: Marc | L81: CONSERVAR ELS ELEMENTS CULTURALS materials i immaterials vinculats a la natura | M81: Conservar i gestionar el patrimoni cultural de l'ENP de forma coordinada amb els agents responsables i entitats de referència | N81: Comú | O81: Optatiu | P81: Si | Q81: 04.2.3 · Coordinació i participació de l'equip tècnic (propi) i servei de manteniment amb els responsables pertinents en els treballs de restauració arquitectò — Número d'accions realitzades
A82: 2. Cultura | B82: 04.2.4 | C82: Disposar de personal especialitzat en patrimoni cultural | D82: Disposar de personal especialitzat en patrimoni cultural | E82: Formació del personal tècnic de l'ENP i entitats col·laboradores en la gestió i conservació dels valors culturals de l'ENP | F82: Número d'activitats formatives realitzades | G82: 2 | H82: 6 | I82: BAIXA | J82: Direccio | K82: Marc | L82: CONSERVAR ELS ELEMENTS CULTURALS materials i immaterials vinculats a la natura | M82: Conservar i gestionar el patrimoni cultural de l'ENP de forma coordinada amb els agents responsables i entitats de referència | N82: Comú | O82: Obligatori | P82: Si | Q82: 04.2.4 · Formació del personal tècnic de l'ENP i entitats col·laboradores en la gestió i conservació dels valors culturals de l'ENP — Número d'activitats formatives realitzades
A83: 2. Cultura | B83: 04.3.1 | C83: Recuperar i conservar el patrimoni cultural rural immaterial associat a les activitats i aprofitaments tradicionals | D83: Recuperar i conservar el patrimoni cultural rural immaterial associat a les activitats i aprofitaments tradicionals | E83: Donar suport material i logístic a les activitats vinculades al patrimoni immaterial de l'àmbit del Parc per ajudar a conservar-les i visibilitzar-les: baixada de falles, aplecs, fira del ferro pirinenc, fires ramaderes, activitats agrícoles tradicionals, fer comú, raiers, musica popular pirinenca, bitlles pallareses, la parla pallaresa, art local, ... | F83: Número d'activitats del patrimoni immaterial del Parc a que se'ls dona suport | G83: 6 | H83: 18 | I83: MITJANA | J83: Direccio | K83: Marc | L83: CONSERVAR ELS ELEMENTS CULTURALS materials i immaterials vinculats a la natura | M83: Potenciar la conservació i recuperació del patrimoni cultural material i immaterial de l'ENP | N83: Comú | O83: Obligatori | P83: Si | Q83: 04.3.1 · Donar suport material i logístic a les activitats vinculades al patrimoni immaterial de l'àmbit del Parc per ajudar a conservar-les i visibilitzar-les — Número d'activitats del patrimoni immaterial del Parc a que se'ls dona suport
A84: 2. Cultura | B84: 04.3.1 | C84: Recuperar i conservar el patrimoni cultural rural immaterial associat a les activitats i aprofitaments tradicionals | D84: Recuperar i conservar el patrimoni cultural rural immaterial associat a les activitats i aprofitaments tradicionals | E84: Iniciar noves recerques sobre l’àmbit etnològic i immaterial del Parc. Incorporant elements vinculats amb el món de les creences, mitologia, espiritualitat, rondallística, etc... | F84: Número de recerques efectuades | G84: 1 | H84: 4 | I84: BAIXA | J84: Direccio | K84: Marc | L84: CONSERVAR ELS ELEMENTS CULTURALS materials i immaterials vinculats a la natura | M84: Potenciar la conservació i recuperació del patrimoni cultural material i immaterial de l'ENP | N84: Comú | O84: Obligatori | P84: Si | Q84: 04.3.1 · Iniciar noves recerques sobre l’àmbit etnològic i immaterial del Parc. Incorporant elements vinculats amb el món de les creences, mitologia, espiritua — Número de recerques efectuades
A85: 2. Cultura | B85: 04.3.1 | C85: Recuperar i conservar el patrimoni cultural rural immaterial associat a les activitats i aprofitaments tradicionals | D85: Recuperar i conservar el patrimoni cultural rural immaterial associat a les activitats i aprofitaments tradicionals | E85: Donar suport a activitats i accions que divulguen la mitologia popular Pirinenca (festivals, rutes,...) | F85: Número d'accions realitzades | G85: 4 | H85: 10 | I85: MITJANA | J85: Direccio | K85: Marc | L85: CONSERVAR ELS ELEMENTS CULTURALS materials i immaterials vinculats a la natura | M85: Potenciar la conservació i recuperació del patrimoni cultural material i immaterial de l'ENP | N85: Comú | O85: Obligatori | P85: Si | Q85: 04.3.1 · Donar suport a activitats i accions que divulguen la mitologia popular Pirinenca (festivals, rutes,...) — Número d'accions realitzades
A86: 2. Cultura | B86: 04.3.1 | C86: Recuperar i conservar el patrimoni cultural rural immaterial associat a les activitats i aprofitaments tradicionals | D86: Recuperar i conservar el patrimoni cultural rural immaterial associat a les activitats i aprofitaments tradicionals | E86: Fomentar la recerca en l'àmbit del patrimoni artesà de l'Alt Pirineu (fusta, ferro, tèxtil, terrissa, pintura, etc.), la seva relació amb la natura i la seva divulgació a través del Festival Terra Roia i altres activitats | F86: Número de recerques efectuades | G86: 1 | H86: 4 | I86: MITJANA | J86: Direccio | K86: Marc | L86: CONSERVAR ELS ELEMENTS CULTURALS materials i immaterials vinculats a la natura | M86: Potenciar la conservació i recuperació del patrimoni cultural material i immaterial de l'ENP | N86: Comú | O86: Obligatori | P86: Si | Q86: 04.3.1 · Fomentar la recerca en l'àmbit del patrimoni artesà de l'Alt Pirineu (fusta, ferro, tèxtil, terrissa, pintura, etc.), la seva relació amb la natura i — Número de recerques efectuades
A87: 2. Cultura | B87: 04.3.1 | C87: Recuperar i conservar el patrimoni cultural rural immaterial associat a les activitats i aprofitaments tradicionals | D87: Recuperar i conservar el patrimoni cultural rural immaterial associat a les activitats i aprofitaments tradicionals | E87: Tramitar un conveni de col·laboració estable per l’organització del Festival Terra Roia de Vilamur i els intercanvis amb festivals d’art agermanats del Parc Pirinenc de les Tres Nacions de divulgació del patrimoni artesà i artístic de l’Alt Pirineu | F87: Conveni | G87: Tramitat | H87: Aprovat i executat | I87: MITJANA | J87: Direccio | K87: Marc | L87: CONSERVAR ELS ELEMENTS CULTURALS materials i immaterials vinculats a la natura | M87: Potenciar la conservació i recuperació del patrimoni cultural material i immaterial de l'ENP | N87: Comú | O87: Obligatori | P87: Si | Q87: 04.3.1 · Tramitar un conveni de col·laboració estable per l’organització del Festival Terra Roia de Vilamur i els intercanvis amb festivals d’art agermanats de — Conveni
A88: 2. Cultura | B88: 04.3.1 | C88: Recuperar i conservar el patrimoni cultural rural immaterial associat a les activitats i aprofitaments tradicionals | D88: Recuperar i conservar el patrimoni cultural rural immaterial associat a les activitats i aprofitaments tradicionals | E88: Fomentar la recerca en memòria oral de les activitats tradicionals de l'àmbit del Parc i la seva divulgació | F88: Número de recerques efectuades | G88: 2 | H88: 8 | I88: ALTA | J88: Direccio | K88: Marc | L88: CONSERVAR ELS ELEMENTS CULTURALS materials i immaterials vinculats a la natura | M88: Potenciar la conservació i recuperació del patrimoni cultural material i immaterial de l'ENP | N88: Comú | O88: Obligatori | P88: Si | Q88: 04.3.1 · Fomentar la recerca en memòria oral de les activitats tradicionals de l'àmbit del Parc i la seva divulgació — Número de recerques efectuades
A89: 2. Cultura | B89: 04.3.2 | C89: Recuperar i conservar el patrimoni cultural rural vinculat específicament a construccions de pedra en sec | D89: Recuperar i conservar el patrimoni cultural rural vinculat específicament a construccions de pedra en sec | E89: Continuar realitzant activitats formatives de la tècnica de pedra en sec (murs, empedrats, cabanes, ..) | F89: Número d'activitats formatives de pedra seca realitzades | G89: 6 | H89: 12 | I89: ALTA | J89: Millora rural | K89: Natàlia | L89: CONSERVAR ELS ELEMENTS CULTURALS materials i immaterials vinculats a la natura | M89: Potenciar la conservació i recuperació del patrimoni cultural material i immaterial de l'ENP | N89: Específic | O89: Obligatori | P89: Si | Q89: 04.3.2 · Continuar realitzant activitats formatives de la tècnica de pedra en sec (murs, empedrats, cabanes, ..) — Número d'activitats formatives de pedra seca realitzades
A90: 2. Cultura | B90: 04.3.2 | C90: Recuperar i conservar el patrimoni cultural rural vinculat específicament a construccions de pedra en sec | D90: Recuperar i conservar el patrimoni cultural rural vinculat específicament a construccions de pedra en sec | E90: Creació d'un Parc Arqueològic d'Alta Muntanya de la pedra seca (possiblement el Pla de Sartari) | F90: Creació del Parc Arqueològic | G90: no | H90: si | I90: MITJANA | J90: Direccio | K90: Marc | L90: CONSERVAR ELS ELEMENTS CULTURALS materials i immaterials vinculats a la natura | M90: Potenciar la conservació i recuperació del patrimoni cultural material i immaterial de l'ENP | N90: Específic | O90: Obligatori | P90: Si | Q90: 04.3.2 · Creació d'un Parc Arqueològic d'Alta Muntanya de la pedra seca (possiblement el Pla de Sartari) — Creació del Parc Arqueològic
A91: 2. Cultura | B91: 04.3.3 | C91: Fomentar la recuperació i conservació de l'arquitectura tradicional d'intrès de les edificacions i construccions | D91: Fomentar la recuperació i conservació de l'arquitectura tradicional d'intrès de les edificacions i construccions | E91: Divulgació i foment de l'aplicació del nou manual de bones pràctiques per la rehabilitació de construccions rurals aïllades del Parc | F91: Número de construccions en que s'ha aplicat el manual | G91: 3 | H91: 10 | I91: ALTA | J91: Direccio | K91: Marc | L91: CONSERVAR ELS ELEMENTS CULTURALS materials i immaterials vinculats a la natura | M91: Potenciar la conservació i recuperació del patrimoni cultural material i immaterial de l'ENP | N91: Comú | O91: Optatiu | P91: Si | Q91: 04.3.3 · Divulgació i foment de l'aplicació del nou manual de bones pràctiques per la rehabilitació de construccions rurals aïllades del Parc — Número de construccions en que s'ha aplicat el manual
A92: 2. Cultura | B92: 04.3.3 | C92: Fomentar la recuperació i conservació de l'arquitectura tradicional d'intrès de les edificacions i construccions | D92: Fomentar la recuperació i conservació de l'arquitectura tradicional d'intrès de les edificacions i construccions | E92: Continuar les recerques i investigacions iniciades sobre arquitectura tradicional, tant d’interior com d’exterior, vinculada amb agricultura i ramaderia, patrimoni preindustrial (molins, serradores, batans, etc...), esglésies, capelles i ermites, en tot l’àmbit del Parc. Cal fer una menció específica a l’interès que desperta l’antiga explotació fustera La Matussiere a Bonabé, a partir de la qual es poden desenvolupar interessants relats patrimonials com la frontera, la gestió del bosc, etc... | F92: Número d'accions realitzades | G92: 2 | H92: 8 | I92: ALTA | J92: Direccio | K92: Marc | L92: CONSERVAR ELS ELEMENTS CULTURALS materials i immaterials vinculats a la natura | M92: Potenciar la conservació i recuperació del patrimoni cultural material i immaterial de l'ENP | N92: Comú | O92: Optatiu | P92: Si | Q92: 04.3.3 · Continuar les recerques i investigacions iniciades sobre arquitectura tradicional, tant d’interior com d’exterior, vinculada amb agricultura i ramader — Número d'accions realitzades
A93: 2. Cultura | B93: 04.3.3 | C93: Fomentar la recuperació i conservació de l'arquitectura tradicional d'intrès de les edificacions i construccions | D93: Fomentar la recuperació i conservació de l'arquitectura tradicional d'intrès de les edificacions i construccions | E93: Continuar donant ajuts, i realitzar campanyes de difusió i informació, per a la rehabilitació de bordes, cabanes i altres construccions rurals aïllades del Parc d'ús agroramader o patrimonial (moles, serradores,..), valorant incloure la redacció dels projectes tècnics i estudis ambientals | F93: Número d'ajuts concedits i campanyes d’informació realitzades | G93: 4 | H93: 12 | I93: ALTA | J93: Direccio | K93: Marc | L93: CONSERVAR ELS ELEMENTS CULTURALS materials i immaterials vinculats a la natura | M93: Potenciar la conservació i recuperació del patrimoni cultural material i immaterial de l'ENP | N93: Comú | O93: Optatiu | P93: Si | Q93: 04.3.3 · Continuar donant ajuts, i realitzar campanyes de difusió i informació, per a la rehabilitació de bordes, cabanes i altres construccions rurals aïllade — Número d'ajuts concedits i campanyes d’informació realitzades
A94: 2. Cultura | B94: 04.3.3 | C94: Fomentar la recuperació i conservació de l'arquitectura tradicional d'intrès de les edificacions i construccions | D94: Fomentar la recuperació i conservació de l'arquitectura tradicional d'intrès de les edificacions i construccions | E94: Continuar en la restauració del patrimoni moble de Casa Bringué de Ginestarre | F94: Número de mobles restaurats | G94: 4 | H94: 10 | I94: MITJANA | J94: Direccio | K94: Marc | L94: CONSERVAR ELS ELEMENTS CULTURALS materials i immaterials vinculats a la natura | M94: Potenciar la conservació i recuperació del patrimoni cultural material i immaterial de l'ENP | N94: Comú | O94: Optatiu | P94: Si | Q94: 04.3.3 · Continuar en la restauració del patrimoni moble de Casa Bringué de Ginestarre — Número de mobles restaurats
A95: 2. Cultura | B95: 04.3.3 | C95: Fomentar la recuperació i conservació de l'arquitectura tradicional d'intrès de les edificacions i construccions | D95: Fomentar la recuperació i conservació de l'arquitectura tradicional d'intrès de les edificacions i construccions | E95: Executar el projecte de rehabilització de Casa Bringué de Ginestarre com espai museistic, formatiu i alberg de joventut | F95: Execució del projecte | G95: no | H95: si | I95: MÀXIMA | J95: Direccio | K95: Marc | L95: CONSERVAR ELS ELEMENTS CULTURALS materials i immaterials vinculats a la natura | M95: Potenciar la conservació i recuperació del patrimoni cultural material i immaterial de l'ENP | N95: Comú | O95: Optatiu | P95: Si | Q95: 04.3.3 · Executar el projecte de rehabilització de Casa Bringué de Ginestarre com espai museistic, formatiu i alberg de joventut — Execució del projecte
A96: 2. Cultura | B96: 04.3.3 | C96: Fomentar la recuperació i conservació de l'arquitectura tradicional d'intrès de les edificacions i construccions | D96: Fomentar la recuperació i conservació de l'arquitectura tradicional d'intrès de les edificacions i construccions | E96: Mantenir la coberta vegetal de la Borda de Llosaus | F96: Número d'acions de manteniment | G96: 1 | H96: 4 | I96: MITJANA | J96: Millora rural | K96: Natàlia | L96: CONSERVAR ELS ELEMENTS CULTURALS materials i immaterials vinculats a la natura | M96: Potenciar la conservació i recuperació del patrimoni cultural material i immaterial de l'ENP | N96: Comú | O96: Optatiu | P96: Si | Q96: 04.3.3 · Mantenir la coberta vegetal de la Borda de Llosaus — Número d'acions de manteniment
A97: 2. Cultura | B97: 04.3.3 | C97: Fomentar la recuperació i conservació de l'arquitectura tradicional d'intrès de les edificacions i construccions | D97: Fomentar la recuperació i conservació de l'arquitectura tradicional d'intrès de les edificacions i construccions | E97: Redacció projecte i rehabilitació de les cases forestals patrimonials de Mas Llavaners, Borda de l’Orient i el Soi destinats a l’educació ambiental i conservació de la biodiversitat | F97: Acció realitzada | G97: Redacció del projecte | H97: Redacció i rehabilitació | I97: MITJANA | L97: CONSERVAR ELS ELEMENTS CULTURALS materials i immaterials vinculats a la natura | M97: Potenciar la conservació i recuperació del patrimoni cultural material i immaterial de l'ENP | N97: Comú | O97: Optatiu | P97: Si | Q97: 04.3.3 · Redacció projecte i rehabilitació de les cases forestals patrimonials de Mas Llavaners, Borda de l’Orient i el Soi destinats a l’educació ambiental i — Acció realitzada
A98: 2. Cultura | B98: 04.3.3 | C98: Fomentar la recuperació i conservació de l'arquitectura tradicional d'intrès de les edificacions i construccions | D98: Fomentar la recuperació i conservació de l'arquitectura tradicional d'intrès de les edificacions i construccions | E98: Realització d'accions de conservació del patrimoni arquitectònic públic del Parc a través del servei de manteniment, obres o ajuts | F98: Número d'accions de conservació | G98: 5 | H98: 25 | I98: MITJANA | J98: Millora rural | K98: Natàlia | L98: CONSERVAR ELS ELEMENTS CULTURALS materials i immaterials vinculats a la natura | M98: Potenciar la conservació i recuperació del patrimoni cultural material i immaterial de l'ENP | N98: Comú | O98: Optatiu | P98: Si | Q98: 04.3.3 · Realització d'accions de conservació del patrimoni arquitectònic públic del Parc a través del servei de manteniment, obres o ajuts — Número d'accions de conservació
A99: 2. Cultura | B99: 04.3.4 | C99: Identificar i conservar la diversitat domesticada de varietats agrícoles i ramaderes locals | D99: Identificar i conservar la diversitat domesticada de varietats agrícoles i ramaderes locals | E99: Donar suport a les entitats que ajuden a identificar, conservar, multiplicar i fomentar l'ús del banc de llavors de les varietats agrícoles i ornamentals de l'Alt Pirineu, incloent les seves activitats formatives | F99: Número d'accions de suport realitzades | G99: 4 | H99: 10 | I99: MITJANA | J99: Direccio | K99: Marc | L99: CONSERVAR ELS ELEMENTS CULTURALS materials i immaterials vinculats a la natura | M99: Donar a conèixer els elements culturals com a valors del paisatge de l'ENP en les activitats d'ús públic | N99: Comú | O99: Obligatori | P99: Si | Q99: 04.3.4 · Donar suport a les entitats que ajuden a identificar, conservar, multiplicar i fomentar l'ús del banc de llavors de les varietats agrícoles i ornament — Número d'accions de suport realitzades
A100: 2. Cultura | B100: 04.3.4 | C100: Identificar i conservar la diversitat domesticada de varietats agrícoles i ramaderes locals | D100: Identificar i conservar la diversitat domesticada de varietats agrícoles i ramaderes locals | E100: Manteniment i millora dels espais de conservació i multiplicació de les varietats agrícoles i ornamentals locals: planter de Gerri, fruiterar de salvaguarda de la Deixalleria de Sort, banc de llavors del Paller d’Antonet | F100: Número d'accions realitzades | G100: 8 | H100: 16 | I100: ALTA | J100: Millora rural | K100: Natàlia | L100: CONSERVAR ELS ELEMENTS CULTURALS materials i immaterials vinculats a la natura | M100: Donar a conèixer els elements culturals com a valors del paisatge de l'ENP en les activitats d'ús públic | N100: Comú | O100: Obligatori | P100: Si | Q100: 04.3.4 · Manteniment i millora dels espais de conservació i multiplicació de les varietats agrícoles i ornamentals locals: planter de Gerri, fruiterar de salva — Número d'accions realitzades
A101: 2. Cultura | B101: 04.3.4 | C101: Identificar i conservar la diversitat domesticada de varietats agrícoles i ramaderes locals | D101: Identificar i conservar la diversitat domesticada de varietats agrícoles i ramaderes locals | E101: Difondre el coneixement de les varietats locals, incentivar la producció de planter i fomentar el seu ús en fires, cultius, tastos, visites a horts, activitats inclusives i de salut, etc. | F101: Número d’activitats realitzades | G101: 5 | H101: 20 | I101: MITJANA | L101: CONSERVAR ELS ELEMENTS CULTURALS materials i immaterials vinculats a la natura | M101: Donar a conèixer els elements culturals com a valors del paisatge de l'ENP en les activitats d'ús públic | N101: Comú | O101: Obligatori | P101: Si | Q101: 04.3.4 · Difondre el coneixement de les varietats locals, incentivar la producció de planter i fomentar el seu ús en fires, cultius, tastos, visites a horts, a — Número d’activitats realitzades
...

Sheet PA 2026 (consulta)
A1: PROGRAMA D'ACTUACIONS 2026 — Parc Natural de l'Alt Pirineu (només consulta)
A2: Codis amb prefix 26_, objectius i eixos normalitzats. Si no hi ha actuacions, el parc no tenia programa 2026 al Motor.
A4: Codi 2026 | B4: Codi RAE | C4: Actuació | D4: Objectiu operatiu | E4: Altres objectius | F4: Eix | G4: Tipus de despesa | H4: Partida RAE | I4: Tipus MAP | J4: Import (€) | K4: Grau de compliment | L4: Observacions | M4: Gestor | N4: Recurrent | O4: L'objectiu és al Pla 2027?
A5: 26_NA_01 | C5: Realització d'accions per a la millora dels elements prioritzats a l'espai, incloent les accions previstes de conservació al Marc d’Acció Prioritària dels espais Xarxa Natura 2000 “Alt Pallars” i “la Torrassa”: Canalització del camí d'accés a la Pica d'estats al seu pas per la tartera de Sotllo. Redacció del projecte | D5: 01.1.1 | F5: 1. Natura | G5: PEA Infraestructures | I5: 2.7 Mesures de conservació i restauració d'hàbitats rocosos, dunes i terres de vegetació esparsa | J5: 30000 | K5: 0.2 | L5: Import aproximat, en funció del previst finalment al projecte executiu | M5: Marc Garriga Lujan | N5: No | O5: =IF(COUNTIF(Objectius!$A$2:$A$183,D5)>0,"Sí","No")
A6: 26_NA_02 | C6: Realització d'accions per a la millora dels elements prioritzats a l'espai, incloent les accions previstes de conservació al Marc d’Acció Prioritària dels espais Xarxa Natura 2000 “Alt Pallars” i “la Torrassa”: Restauració de la cua de l'embassament de Boren. Redacció del proejcte | D6: 01.1.1 | F6: 1. Natura | G6: PEA Infraestructures | I6: 2.8 Mesures de manteniment i restauració d'hàbitats d'aigua dolça (rius, llacs i zones humides no litorals) | J6: 30000 | K6: 0.2 | L6: Xifra final pendent d'adjudicació del contracte | M6: Marc Garriga Lujan | N6: No | O6: =IF(COUNTIF(Objectius!$A$2:$A$183,D6)>0,"Sí","No")
A7: 26_NA_03 | C7: Realització d'accions per a la millora dels elements prioritzats a l'espai, incloent les accions previstes de conservació al Marc d’Acció Prioritària dels espais Xarxa Natura 2000 “Alt Pallars” i “la Torrassa”: Realització d'accions de millora d'habitat de gall ger en boscos patrimonials. Redacció del projecte. | D7: 01.1.1 | E7: 01.3.2, 01.4.2, 02.1.3 | F7: 1. Natura | G7: PEA Infraestructures | I7: 2.6 Mesures de manteniment i restauració de boscos i superfícies forestals | J7: 30000 | K7: 0.2 | L7: Xifra final pendent d'adjudicació del contracte | M7: Josep Pique Palacin | N7: No | O7: =IF(COUNTIF(Objectius!$A$2:$A$183,D7)>0,"Sí","No")
A8: 26_NA_04 | C8: Realització d'accions per a la millora dels elements prioritzats a l'espai, incloent les accions previstes de conservació al Marc d’Acció Prioritària dels espais Xarxa Natura 2000 “Alt Pallars” i “la Torrassa”: Revisió, modificació i/o visibilització de filats perillosos per a fauna amenaçada, en especial gall fer. | D8: 01.1.1 | F8: 1. Natura | G8: Encomana Forestal Catalana | I8: 2.6 Mesures de manteniment i restauració de boscos i superfícies forestals | J8: 36222.283 | L8: 5% de l'encomana de manteniment. Import 2026 calculat amb la fórmula =724445.66*0.05 | M8: Josep Pique Palacin | N8: No | O8: =IF(COUNTIF(Objectius!$A$2:$A$183,D8)>0,"Sí","No")
A9: 26_NA_05 | B9: 6 | C9: Realització d'accions per a la millora dels elements prioritzats a l'espai, incloent les accions previstes de conservació al Marc d’Acció Prioritària dels espais Xarxa Natura 2000 “Alt Pallars” i “la Torrassa”: Millora de les poblacions d'Hippuris a la Torrassa | D9: 01.1.1 | F9: 1. Natura | G9: Contracte menor a càrrec del RAE | H9: 210.0001 - Conservació, reparació i manteniment de terrenys | I9: 2.8 Mesures de manteniment i restauració d'hàbitats d'aigua dolça (rius, llacs i zones humides no litorals) | J9: 4560 | K9: 0.1 | M9: Mariona Martinez Salvador | N9: No | O9: =IF(COUNTIF(Objectius!$A$2:$A$183,D9)>0,"Sí","No")
A10: 26_NA_06 | C10: Realització d'accions per a la millora dels elements prioritzats a l'espai, incloent les accions previstes de conservació al Marc d’Acció Prioritària dels espais Xarxa Natura 2000 “Alt Pallars” i “la Torrassa”: Realització d'accions d'exclusió d'herbivors en molleres | D10: 01.1.1 | F10: 1. Natura | G10: Encomana Forestal Catalana | I10: 2.3 Mesures de manteniment i restauració de torberes | J10: 36222.283 | K10: 0.2 | L10: 5% de l'encomana de manteniment. Import 2026 calculat amb la fórmula =724445.66*0.05 | M10: Nil Bacardit Tudela | N10: No | O10: =IF(COUNTIF(Objectius!$A$2:$A$183,D10)>0,"Sí","No")
A11: 26_NA_07 | C11: Realització d'accions per a la millora dels elements prioritzats a l'espai, incloent les accions previstes de conservació al Marc d’Acció Prioritària dels espais Xarxa Natura 2000 “Alt Pallars” i “la Torrassa”: seguiment d'actuacions de conservació en molleres | D11: 01.1.1 | F11: 1. Natura | G11: Contracte menor des de la DG | I11: 2.3 Mesures de manteniment i restauració de torberes | J11: 18128.58 | M11: Mariona Martinez Salvador | N11: No | O11: =IF(COUNTIF(Objectius!$A$2:$A$183,D11)>0,"Sí","No")
A12: 26_NA_08 | C12: Realització d’actuacions de control i eradicació d’espècies invasores (exòtiques o no) que afecten a l’estat de conservació d’hàbitats i espècies: actuacions de control de flora invasora | D12: 01.1.1 | F12: 1. Natura | G12: Encomana Forestal Catalana | I12: 2.8 Mesures de manteniment i restauració d'hàbitats d'aigua dolça (rius, llacs i zones humides no litorals) | J12: 100000 | K12: 0.25 | L12: Xifra aproximada dins un contracte més global | M12: Mariona Martinez Salvador | N12: No | O12: =IF(COUNTIF(Objectius!$A$2:$A$183,D12)>0,"Sí","No")
A13: 26_NA_09 | C13: Realització de les actuacions de conservació d’hàbitats i espècies aquàtiques d’alta muntanya previstes al projecte LIFE RESQUE ALPYR: restauració estanys Muntanyó d'Arreu i Naorte, molleres de Comes de Rubió, Sartari i Pallerols | D13: 01.1.1 | F13: 1. Natura | G13: Encomana Forestal Catalana | I13: 2.8 Mesures de manteniment i restauració d'hàbitats d'aigua dolça (rius, llacs i zones humides no litorals) | J13: 100000 | K13: 0.25 | L13: Brigades extra que s'aporten al Projecte | M13: Marc Garriga Lujan | N13: No | O13: =IF(COUNTIF(Objectius!$A$2:$A$183,D13)>0,"Sí","No")
A14: 26_NA_10 | C14: Realització de les actuacions de conservació d’hàbitats i espècies aquàtiques d’alta muntanya previstes al projecte LIFE RESQUE ALPYR:programa d'educació ambiental | D14: 01.1.1 | F14: 1. Natura | G14: Contracte menor des de la DG | I14: 1.5 Mesures de comunicació i sensibilització, educació i accés de visitants relacionades amb Natura 2000 | J14: 6824.4 | K14: 0.25 | M14: Moises Villanueva Coello | N14: No | O14: =IF(COUNTIF(Objectius!$A$2:$A$183,D14)>0,"Sí","No")
A15: 26_NA_11 | C15: Realització de les actuacions de conservació d’hàbitats i espècies aquàtiques d’alta muntanya previstes al projecte LIFE RESQUE ALPYR: Treballs de disseny i maquetació de plafons i cartelleres per Muntanyó, Sartari, Comes de Rubió, mirador de la Font de la Tosca i Tavascan | D15: 01.1.1 | F15: 1. Natura | G15: Contracte menor des de la DG | I15: 1.5 Mesures de comunicació i sensibilització, educació i accés de visitants relacionades amb Natura 2000 | J15: 17859.6 | K15: 0.25 | M15: Nil Bacardit Tudela | N15: No | O15: =IF(COUNTIF(Objectius!$A$2:$A$183,D15)>0,"Sí","No")
A16: 26_NA_12 | C16: Realització de les actuacions de conservació d’hàbitats i espècies aquàtiques d’alta muntanya previstes al projecte LIFE RESQUE ALPYR: impressió i instalació senyalització | D16: 01.1.1 | F16: 1. Natura | G16: Contracte menor des de la DG | I16: 1.5 Mesures de comunicació i sensibilització, educació i accés de visitants relacionades amb Natura 2000 | J16: 12021.68 | K16: 0.25 | M16: Nil Bacardit Tudela | N16: No | O16: =IF(COUNTIF(Objectius!$A$2:$A$183,D16)>0,"Sí","No")
A17: 26_NA_13 | C17: Elaboració de plans de gestió per elements prioritzats a l'espai: Document d'avaluació d'eficàcia de la gestió del Parc (LIFE PAME) | D17: 01.1.1 | F17: 1. Natura | G17: Altres | I17: 1.1 Planificació de la gestió i designació del lloc | J17: 0 | K17: 0.25 | L17: A realitzar amb mitjans propis en el marc LIFE PAME | M17: Marc Garriga Lujan | N17: No | O17: =IF(COUNTIF(Objectius!$A$2:$A$183,D17)>0,"Sí","No")
A18: 26_NA_14 | B18: 68 | C18: Afavorir la custòdia del territori amb entitats i potenciar projectes de conservació de forma col·laborativa entre el parc, els ens locals i les entitats de custòdia: Fomentar les compensacions del carboni generat pels visitants a través de Gratitud Pallars - Coordinació del projecte | D18: 01.1.1 | E18: 02.1.1 | F18: 1. Natura | G18: Contracte menor a càrrec del RAE | H18: 227.0013 - Treballs tècnics | I18: 1.1 Planificació de la gestió i designació del lloc | J18: 18150 | K18: 0.25 | M18: Moises Villanueva Coello | N18: Si | O18: =IF(COUNTIF(Objectius!$A$2:$A$183,D18)>0,"Sí","No")
A19: 26_NA_15 | C19: Acompanyament de la Comissió Ramadera amb l’òrgan competent per abordar de forma específica la millora de la convivència entre la ramaderia i la presència de grans depredadors, i l’ús de gossos de protecció | D19: 01.2.2 | F19: 1. Natura | G19: Altres | I19: 3.2 Prevenció, mitigació o compensació dels danys ocasionats per les espècies protegides | J19: 0 | K19: 0.25 | M19: Neus Artigas Piñero | N19: Si | O19: =IF(COUNTIF(Objectius!$A$2:$A$183,D19)>0,"Sí","No")
A20: 26_NA_16 | C20: Col.laboració en l'obtenció de la informació necessària dins els espais per al desenvolupament dels Plans | D20: 01.2.2 | F20: 1. Natura | G20: Altres | I20: 3.1 Mesures i programes específics de conservació d'espècies no incloses en altres apartats | J20: 0 | K20: 0.25 | L20: Participació en eles reunions que el SFF ens convoqui | M20: Marc Garriga Lujan | N20: Si | O20: =IF(COUNTIF(Objectius!$A$2:$A$183,D20)>0,"Sí","No")
A21: 26_NA_17 | C21: Implicació i participació en la redacció dels plans de conservació /recuperació d'espècies amenaçades. Reforç poblacional quan s'escaigui. | D21: 01.2.2 | F21: 1. Natura | G21: Altres | I21: 1.1 Planificació de la gestió i designació del lloc | J21: 0 | K21: 0.25 | L21: Participació en eles reunions que el SFF ens convoqui | M21: Mariona Martinez Salvador | N21: Si | O21: =IF(COUNTIF(Objectius!$A$2:$A$183,D21)>0,"Sí","No")
A22: 26_NA_18 | C22: Execució de les accions dins els plans que pertoquin a cada espai. Accions d'erradicació de flora exòtica invasora realitzades a través del servei de manteniment (Falsa acàcia) | D22: 01.2.3 | F22: 1. Natura | G22: Encomana Forestal Catalana | I22: 2.8 Mesures de manteniment i restauració d'hàbitats d'aigua dolça (rius, llacs i zones humides no litorals) | J22: 0 | K22: 0.25 | L22: A través de les brigades d'exotiques de FC | M22: Nil Bacardit Tudela | N22: No | O22: =IF(COUNTIF(Objectius!$A$2:$A$183,D22)>0,"Sí","No")
A23: 26_NA_19 | C23: Execució de les accions dins els plans que pertoquin a cada espai. Col·laboració amb SFF en l'erradicació de flora exòtica invasora al PNAP a través de la brigada d'exòtiques (Buddleja i falsa acàcia) | D23: 01.2.3 | F23: 1. Natura | G23: Encomana Forestal Catalana | I23: 2.8 Mesures de manteniment i restauració d'hàbitats d'aigua dolça (rius, llacs i zones humides no litorals) | J23: 0 | K23: 0.25 | L23: A través de les brigades d'exotiques de FC | M23: Nil Bacardit Tudela | N23: No | O23: =IF(COUNTIF(Objectius!$A$2:$A$183,D23)>0,"Sí","No")
A24: 26_NA_20 | C24: Execució de les accions dins els plans que pertoquin a cada espai. Col·laboració amb SFF en l'execució del projecte d'erradicació de flora exòtica invasora al PNAP (Seneci del cap i ailant) | D24: 01.2.3 | F24: 1. Natura | G24: Encomana Forestal Catalana | I24: 2.6 Mesures de manteniment i restauració de boscos i superfícies forestals | J24: 0 | K24: 0.25 | L24: A través de les brigades d'exotiques de FC | M24: Nil Bacardit Tudela | N24: No | O24: =IF(COUNTIF(Objectius!$A$2:$A$183,D24)>0,"Sí","No")
A25: 26_NA_21 | C25: Execució de les accions dins els plans que pertoquin a cada espai. Col·laboració amb SFF en l'execució del projecte de control i d'erradicació de flora exòtica invasora al PNAP (Elodea) | D25: 01.2.3 | F25: 1. Natura | G25: Encomana Forestal Catalana | I25: 2.8 Mesures de manteniment i restauració d'hàbitats d'aigua dolça (rius, llacs i zones humides no litorals) | J25: 18000 | K25: 0.25 | L25: Contracte menor a través de l'encomana de control de flora exotica de FC | M25: Nil Bacardit Tudela | N25: No | O25: =IF(COUNTIF(Objectius!$A$2:$A$183,D25)>0,"Sí","No")
A26: 26_NA_22 | B26: 89 | C26: Preparar candidatura a Transboundary Park Europarc PP3N. Assessorament | D26: 01.2.4 | F26: 1. Natura | G26: Contracte menor a càrrec del RAE | H26: 227.0089 - Altres treballs realitzats per persones físiques o jurídiques | I26: 1.1 Planificació de la gestió i designació del lloc | J26: 3000 | K26: 0.5 | L26: Vinculat al POCTEFA PP3N | M26: Marc Garriga Lujan | N26: No | O26: =IF(COUNTIF(Objectius!$A$2:$A$183,D26)>0,"Sí","No")
A27: 26_NA_23 | B27: 123 | C27: Afavorir la creació d'hàbitats per a la conservació d'espècies i ordenació de l'ús públic del seu entorn. Introducció i seguiment de cavalls camarguesos a la Mollera d’Escalarre | D27: 01.3.1 | F27: 1. Natura | G27: Contracte menor a càrrec del RAE | H27: 227.0089 - Altres treballs realitzats per persones físiques o jurídiques | I27: 2.8 Mesures de manteniment i restauració d'hàbitats d'aigua dolça (rius, llacs i zones humides no litorals) | J27: 5500 | K27: 0.25 | M27: Neus Artigas Piñero | N27: No | O27: =IF(COUNTIF(Objectius!$A$2:$A$183,D27)>0,"Sí","No")
A28: 26_NA_24 | C28: Participar en la identificació de boscos madurs pel foment de la dinàmica natural i l'aprofitament no extractiu dins l'ENP en base a uns criteris metodològics predefinits (DG Boscos i boscos BAVE POCTEFA RedBio) | D28: 01.3.1 | F28: 1. Natura | G28: Encàrrec directe CREAF | I28: 2.6 Mesures de manteniment i restauració de boscos i superfícies forestals | J28: 0 | K28: 0.5 | L28: mitjans propis col·laboració | M28: Josep Pique Palacin | N28: No | O28: =IF(COUNTIF(Objectius!$A$2:$A$183,D28)>0,"Sí","No")
A29: 26_NA_25 | C29: Elaboració d'una planificació d'actuacions de simulació d'incendis forestals naturals (cremes controlades i criteris d'actuació en cas d'incendi) dins l'espai en base als criteris metodològics predefinits (POCTEFA Desbosiguem) a través de la figura de Pla de Prevenció d'Incendis Forestals | D29: 01.3.3 | F29: 1. Natura | G29: Altres | I29: 1.1 Planificació de la gestió i designació del lloc | J29: 0 | L29: Les simulacions seran realitzades pel la UPC i el pla prev incendis per FPC, socis del projecte POCTEFA Desbosiguem en que hi participem | M29: Marc Garriga Lujan | N29: No | O29: =IF(COUNTIF(Objectius!$A$2:$A$183,D29)>0,"Sí","No")
A30: 26_NA_26 | C30: Realització de cremes controlades impulsades des del Parc. Cremes de solanes de Gavas i Burg | D30: 01.3.3 | E30: 02.2.2 | F30: 1. Natura | G30: Encomana Forestal Catalana | I30: 1.1 Planificació de la gestió i designació del lloc | J30: 0 | L30: Accions demanades pel Parc que executa les brigades GEPIF | M30: Oriol Grau Fernandez | N30: No | O30: =IF(COUNTIF(Objectius!$A$2:$A$183,D30)>0,"Sí","No")
A31: 26_NA_27 | B31: 147 | C31: Calcul i solicitud implementació de cabals ecològics en aprofitaments hidroelèctics dels rius del Parc. Seguiment cabals ecològics | D31: 01.3.4 | E31: 02.1.2, 03.3.1 | F31: 1. Natura | G31: Contracte menor a càrrec del RAE | H31: 227.0013 - Treballs tècnics | I31: 1.4 Buits de coneixement i necessitats de recerca | J31: 1500 | K31: 0.25 | L31: Queda asssessorament i que nosaltres realitzem el seguiment, poso una mica mes perque hi ha un equip malmes | M31: Oriol Grau Fernandez | N31: Si | O31: =IF(COUNTIF(Objectius!$A$2:$A$183,D31)>0,"Sí","No")
A32: 26_NA_28 | C32: Establir taules de treball entre l’equip del Parc i Comissió Ramadera per desenvolupar una proposta de línies d’ajut que respongui de forma més efectiva a les necessitats del sector i a la preservació dels hàbitats i la cultura associada, incloent la possibilitat de subvencionar pastors, vaquers i eugassers | D32: 01.3.5 | F32: 1. Natura | G32: Altres | I32: 2.4 Mesures de manteniment i restauració de prats i pastures | J32: 0 | L32: Amb mitjans propis | M32: Neus Artigas Piñero | N32: Si | O32: =IF(COUNTIF(Objectius!$A$2:$A$183,D32)>0,"Sí","No")
A33: 26_NA_29 | C33: Acords amb ramaders locals per actuacions de restauració i manteniment de pastures al voltant de pobles (POCTEFA Desbosiguem). Adquisició de tancaments per pasturatge | D33: 01.3.5 | F33: 1. Natura | G33: Contracte menor des de la DG | I33: 2.4 Mesures de manteniment i restauració de prats i pastures | J33: 9000 | K33: 0.33 | L33: Correspon als tancaments per bestiar | M33: Nil Bacardit Tudela | N33: No | O33: =IF(COUNTIF(Objectius!$A$2:$A$183,D33)>0,"Sí","No")
A34: 26_NA_30 | C34: Realització d'un manual tècnic de bones pràctiques en ramaderia extensiva i recuperació i manteniment de pastures aplicat a l'ENP (Projecte REPICA) | D34: 01.3.5 | F34: 1. Natura | G34: Altres | I34: 2.4 Mesures de manteniment i restauració de prats i pastures | J34: 0 | K34: 1 | L34: Producte resultat del projecte REPICA | M34: Oriol Grau Fernandez | N34: No | O34: =IF(COUNTIF(Objectius!$A$2:$A$183,D34)>0,"Sí","No")
A35: 26_NA_31 | C35: Tramitació d'ajuts per explotacions ramaderes per gestionar l'herbivoria domèstica associada a la ramaderia extensiva | D35: 01.3.5 | F35: 1. Natura | G35: Altres | I35: 2.4 Mesures de manteniment i restauració de prats i pastures | J35: 0 | K35: 0.5 | L35: Qua surti la nova convocatoria el 2026 | M35: Neus Artigas Piñero | N35: Si | O35: =IF(COUNTIF(Objectius!$A$2:$A$183,D35)>0,"Sí","No")
A36: 26_NA_32 | C36: Realització d'acords amb societats de caçadors mitjançant informes en els PTGMC | D36: 01.3.6 | F36: 1. Natura | G36: Altres | I36: 1.1 Planificació de la gestió i designació del lloc | J36: 0 | K36: 0.25 | L36: Mitjans propis | M36: Josep Pique Palacin | N36: Si | O36: =IF(COUNTIF(Objectius!$A$2:$A$183,D36)>0,"Sí","No")
A37: 26_NA_33 | C37: Participació en la redacció d'IOF de finques públiques en la fase de zonificació i planificació | D37: 02.1.3 | F37: 1. Natura | G37: Altres | I37: 2.6 Mesures de manteniment i restauració de boscos i superfícies forestals | J37: 0 | K37: 0.25 | L37: Mitjans propis a través d'informes previs | M37: Marc Garriga Lujan | N37: Si | O37: =IF(COUNTIF(Objectius!$A$2:$A$183,D37)>0,"Sí","No")
A38: 26_NA_34 | C38: Promoure als ens locals la solicitud d'ajuts disponibles per incentivar els serveis ecosistèmics per a la gestió forestal sostenible en finques publiques | D38: 02.1.3 | F38: 1. Natura | G38: Altres | I38: 2.6 Mesures de manteniment i restauració de boscos i superfícies forestals | J38: 0 | K38: 0.25 | L38: Mitjans propis | M38: Nil Bacardit Tudela | N38: Si | O38: =IF(COUNTIF(Objectius!$A$2:$A$183,D38)>0,"Sí","No")
A39: 26_NA_35 | C39: Promoure als propietaris privats la solicitud d'ajuts disponibles per incentivar els serveis ecosistèmics per a la gestió forestal sostenible en finques privades | D39: 02.1.4 | F39: 1. Natura | G39: Altres | I39: 2.6 Mesures de manteniment i restauració de boscos i superfícies forestals | J39: 0 | K39: 0.25 | L39: Mitjans propis | M39: Nil Bacardit Tudela | N39: Si | O39: =IF(COUNTIF(Objectius!$A$2:$A$183,D39)>0,"Sí","No")
A40: 26_NA_36 | C40: Elaboració i aprovació del Pla de Prevenció d'Incendis i gestió del foc (POCTEFA Desbosiguem). Redacció del pla i procés participatiu | D40: 02.2.1 | E40: 12.1.2, 02.2.2 | F40: 1. Natura | G40: Altres | I40: 1.1 Planificació de la gestió i designació del lloc | J40: 0 | K40: 0.4 | L40: A realitzar per la Fundació Pau Costa dins del projecte POCTEFA Desbosiguem | M40: Marc Garriga Lujan | N40: No | O40: =IF(COUNTIF(Objectius!$A$2:$A$183,D40)>0,"Sí","No")
A41: 26_NA_37 | C41: Execució d'altres actuacions de prevenció d'incendis forestals no recollides al Pla. Accions de prevenció d'incendis realitzades a través del servei de manteniment | D41: 02.2.3 | E41: 12.1.2 | F41: 1. Natura | G41: Encomana Forestal Catalana | I41: 2.6 Mesures de manteniment i restauració de boscos i superfícies forestals | J41: 0 | K41: 0.25 | L41: SI ens demanen desbrossar pistes a través de la brigada (Montsclado,..) | M41: Nil Bacardit Tudela | N41: Si | O41: =IF(COUNTIF(Objectius!$A$2:$A$183,D41)>0,"Sí","No")
A42: 26_NA_38 | C42: Execució d'altres actuacions de prevenció d'incendis forestals no recollides al Pla. Creació de franges de protecció contra incendis forestals al voltant dels pobles de Vilamur (Soriguera) i Roní (Rialp). Projecte POCTEFA Desbosiguem! | D42: 02.2.3 | E42: 12.1.2 | F42: 1. Natura | G42: Contracte menor des de la DG | I42: 2.4 Mesures de manteniment i restauració de prats i pastures | J42: 39359.02 | K42: 0.4 | L42: Acció del POCTEFA Desbosiguem | M42: Nil Bacardit Tudela | N42: No | O42: =IF(COUNTIF(Objectius!$A$2:$A$183,D42)>0,"Sí","No")
A43: 26_NA_39 | B43: 108 | C43: Execució d'altres actuacions de prevenció d'incendis forestals no recollides al Pla. Redacció projecte i direcció tècnica franja perimetral de protecció de Roní (POCTEFA Desbosiguem!) | D43: 02.2.3 | F43: 1. Natura | G43: Contracte menor a càrrec del RAE | H43: 600.0000 - Inversions en terrenys i bens naturals | I43: 2.4 Mesures de manteniment i restauració de prats i pastures | J43: 2500 | K43: 0.25 | M43: Nil Bacardit Tudela | N43: No | O43: =IF(COUNTIF(Objectius!$A$2:$A$183,D43)>0,"Sí","No")
A44: 26_NA_40 | C44: Participació a les taules d'avaluació ambiental via informe preceptiu | D44: 03.1.1 | F44: 1. Natura | G44: Altres | I44: 1.1 Planificació de la gestió i designació del lloc | J44: 0 | K44: 0.25 | L44: A realitzar amb mitjans propis | M44: Marc Garriga Lujan | N44: Si | O44: =IF(COUNTIF(Objectius!$A$2:$A$183,D44)>0,"Sí","No")
A45: 26_NA_41 | C45: Seguiment de les obres i altres actuacions informades que afecten i es realitzen dins dels límits del PNAP+XN2000 Alt Pallars | D45: 03.1.2 | F45: 1. Natura | G45: Altres | I45: 1.3 Seguiment, vigilància i notificació | J45: 0 | K45: 0.25 | L45: A realitzar amb mitjans propis | M45: Josep Pique Palacin | N45: Si | O45: =IF(COUNTIF(Objectius!$A$2:$A$183,D45)>0,"Sí","No")
A46: 26_NA_42 | C46: Impuls del control per incompliment de la normativa i el seu trasllat cap a l'administració competent | D46: 03.3.1 | F46: 1. Natura | G46: Altres | I46: 1.3 Seguiment, vigilància i notificació | J46: 0 | K46: 0.25 | L46: A realitzar amb mitjans propis | M46: Marc Garriga Lujan | N46: Si | O46: =IF(COUNTIF(Objectius!$A$2:$A$183,D46)>0,"Sí","No")
A47: 26_NA_43 | C47: Participació en el Pla Hidrològic de la Conca de l'Ebre | D47: 03.3.1 | F47: 1. Natura | G47: Altres | I47: 1.3 Seguiment, vigilància i notificació | J47: 0 | K47: 0.25 | L47: A realitzar amb mitjans propis | M47: Marc Garriga Lujan | N47: Si | O47: =IF(COUNTIF(Objectius!$A$2:$A$183,D47)>0,"Sí","No")
A48: 26_NA_44 | C48: Participació en el seguiment del cabal en els trams dins ENP | D48: 03.3.1 | F48: 1. Natura | G48: Altres | I48: 1.3 Seguiment, vigilància i notificació | J48: 0 | K48: 0.25 | L48: A realitzar amb mitjans propis | M48: Oriol Grau Fernandez | N48: Si | O48: =IF(COUNTIF(Objectius!$A$2:$A$183,D48)>0,"Sí","No")
A49: 26_NA_45 | C49: Participació, de forma coordinada amb l'administració competent, en l'avaluació i control d'actuacions de captacions dins els límits de l'ENP. | D49: 03.3.3 | F49: 1. Natura | G49: Altres | I49: 1.3 Seguiment, vigilància i notificació | J49: 0 | K49: 0.25 | L49: A realitzar amb mitjans propis | M49: Marc Garriga Lujan | N49: Si | O49: =IF(COUNTIF(Objectius!$A$2:$A$183,D49)>0,"Sí","No")
A50: 26_NA_46 | B50: 62 | C50: Participació en la identificació de finques prioritàries per comprar en base als criteris indicats | D50: 03.4.1 | F50: 1. Natura | G50: Altres | H50: 227.0013 - Treballs tècnics | I50: 1.4 Buits de coneixement i necessitats de recerca | J50: 2300 | K50: 1 | M50: Marc Garriga Lujan | N50: Si | O50: =IF(COUNTIF(Objectius!$A$2:$A$183,D50)>0,"Sí","No")
A51: 26_CU_01 | B51: 63 | C51: Prospecció arqueològica de zones alpines del Parc: massís Marimanha, Vall d'Unarre, Vall de Tavascan i capçalera de la Vall Ferrera | D51: 04.1.1 | F51: 2. Cultura | G51: Contracte menor a càrrec del RAE | H51: 227.0013 - Treballs tècnics | I51: 1.4 Buits de coneixement i necessitats de recerca | J51: 8000 | K51: 0.25 | M51: Marc Garriga Lujan | N51: Si | O51: =IF(COUNTIF(Objectius!$A$2:$A$183,D51)>0,"Sí","No")
A52: 26_CU_02 | B52: 150 | C52: Continuar les excavacions arqueològiques; Santa Creu de Llagunes, i accions de conservació i divulgació d’aquests jaciments | D52: 04.1.1 | F52: 2. Cultura | G52: Contracte menor a càrrec del RAE | H52: 227.0013 - Treballs tècnics | I52: 1.4 Buits de coneixement i necessitats de recerca | J52: 18500 | K52: 0.25 | M52: Marc Garriga Lujan | N52: No | O52: =IF(COUNTIF(Objectius!$A$2:$A$183,D52)>0,"Sí","No")
A53: 26_CU_03 | C53: iniciar l'excavació de Sant Martí del Pui | D53: 04.1.1 | F53: 2. Cultura | G53: Altres | I53: 1.4 Buits de coneixement i necessitats de recerca | J53: 18111.142 | K53: 0.1 | L53: 2,5% de l'encomana de manteniment. Import 2026 calculat amb la fórmula =724445.66*0.025 | M53: Marc Garriga Lujan | N53: No | O53: =IF(COUNTIF(Objectius!$A$2:$A$183,D53)>0,"Sí","No")
A54: 26_CU_04 | C54: Recopilació i georeferenciació de toponimia popular del Parc no present o errònia de la cartografia ICGC en base a la memòria oral amb col·laboració amb les entitats locals | D54: 04.1.2 | F54: 2. Cultura | G54: Altres | I54: 1.4 Buits de coneixement i necessitats de recerca | J54: 0 | L54: Mitjans propis | M54: Marc Garriga Lujan | N54: Si | O54: =IF(COUNTIF(Objectius!$A$2:$A$183,D54)>0,"Sí","No")
A55: 26_CU_05 | C55: Donar suport a les iniciatives i publicacions dedicades a recuperar la parla pallaresa | D55: 04.1.2 | F55: 2. Cultura | G55: Altres | I55: 1.5 Mesures de comunicació i sensibilització, educació i accés de visitants relacionades amb Natura 2000 | J55: 7244.4566 | K55: 0.1 | L55: 1% de l'encomana de manteniment. Import 2026 calculat amb la fórmula =724445.66*0.01 | M55: Marc Garriga Lujan | N55: Si | O55: =IF(COUNTIF(Objectius!$A$2:$A$183,D55)>0,"Sí","No")
A56: 26_CU_06 | C56: Continuar impulsant el projecte de parcs i museus junt amb l'Ecomuseu de les Vals d'Àneu | D56: 04.2.2 | F56: 2. Cultura | G56: Altres | I56: 1.1 Planificació de la gestió i designació del lloc | J56: 0 | K56: 0.25 | L56: A realitzar amb mtjans propis i altres actuacions vinculades | M56: Moises Villanueva Coello | N56: Si | O56: =IF(COUNTIF(Objectius!$A$2:$A$183,D56)>0,"Sí","No")
A57: 26_CU_07 | C57: Impulsar la bona cooperació, i si s'escau, establir convenis de col·laboració amb els equipaments culturals de l'àmbit del Parc, conjuntament amb el grup de treball de cultura de la CETS | D57: 04.2.2 | F57: 2. Cultura | G57: Altres | I57: 1.2 Administració del lloc i comunicació amb les parts interessades | J57: 0 | L57: A realitzar amb mitjans propis | M57: Moises Villanueva Coello | N57: Si | O57: =IF(COUNTIF(Objectius!$A$2:$A$183,D57)>0,"Sí","No")
A58: 26_CU_08 | B58: 19 | C58: Donar suport material i logístic a les activitats vinculades al patrimoni immaterial de l'àmbit del Parc per ajudar a conservar-les i visibilitzar-les: queviures per tastos de productes locals de les activiats | D58: 04.3.1 | F58: 2. Cultura | G58: Contracte menor a càrrec del RAE | H58: 221.0007 - Queviures | I58: 1.5 Mesures de comunicació i sensibilització, educació i accés de visitants relacionades amb Natura 2000 | J58: 8500 | K58: 0.25 | M58: Marc Garriga Lujan | N58: Si | O58: =IF(COUNTIF(Objectius!$A$2:$A$183,D58)>0,"Sí","No")
A59: 26_CU_09 | B59: 22 | C59: Donar suport material i logístic a les activitats vinculades al patrimoni immaterial de l'àmbit del Parc per ajudar a conservar-les i visibilitzar-les: subministrament de material promocional i de merxandatge | D59: 04.3.1 | F59: 2. Cultura | G59: Contracte menor a càrrec del RAE | H59: 221.0089 - Altres subministraments | I59: 1.5 Mesures de comunicació i sensibilització, educació i accés de visitants relacionades amb Natura 2000 | J59: 1000 | K59: 0.25 | M59: Marc Garriga Lujan | N59: Si | O59: =IF(COUNTIF(Objectius!$A$2:$A$183,D59)>0,"Sí","No")
A60: 26_CU_10 | B60: 156 | C60: Donar suport a activitats i accions que divulguen la mitologia popular Pirinenca (festivals, rutes,...): organització i realització de tallers | D60: 04.3.1 | F60: 2. Cultura | G60: Contracte menor a càrrec del RAE | H60: 227.0089 - Altres treballs realitzats per persones físiques o jurídiques | I60: 1.5 Mesures de comunicació i sensibilització, educació i accés de visitants relacionades amb Natura 2000 | J60: 1600 | K60: 0.25 | M60: Pol Alcalde Floriach | N60: Si | O60: =IF(COUNTIF(Objectius!$A$2:$A$183,D60)>0,"Sí","No")
A61: 26_CU_11 | C61: Donar suport a activitats i accions que divulguen la mitologia popular Pirinenca (festivals, rutes,...): itinerari mitologic Ainet de Cardós | D61: 04.3.1 | F61: 2. Cultura | G61: Contracte menor des de la DG | I61: 1.5 Mesures de comunicació i sensibilització, educació i accés de visitants relacionades amb Natura 2000 | J61: 18000 | K61: 0.25 | M61: Nil Bacardit Tudela | N61: No | O61: =IF(COUNTIF(Objectius!$A$2:$A$183,D61)>0,"Sí","No")
A62: 26_CU_12 | C62: Tramitar un conveni de col·laboració estable per l’organització del Festival Terra Roia de Vilamur i els intercanvis amb festivals d’art agermanats del Parc Pirinenc de les Tres Nacions de divulgació del patrimoni artesà i artístic de l’Alt Pirineu | D62: 04.3.1 | F62: 2. Cultura | G62: Altres | I62: 1.1 Planificació de la gestió i designació del lloc | J62: 0 | L62: A realitzar amb mitjans propis | M62: Marc Garriga Lujan | N62: No | O62: =IF(COUNTIF(Objectius!$A$2:$A$183,D62)>0,"Sí","No")
A63: 26_CU_13 | B63: 167 | C63: Fomentar la recerca en memòria oral de les activitats tradicionals de l'àmbit del Parc i la seva divulgació | D63: 04.3.1 | F63: 2. Cultura | G63: Contracte menor a càrrec del RAE | H63: 227.0013 - Treballs tècnics | I63: 1.4 Buits de coneixement i necessitats de recerca | J63: 1500 | K63: 0.25 | M63: Marc Garriga Lujan | N63: No | O63: =IF(COUNTIF(Objectius!$A$2:$A$183,D63)>0,"Sí","No")
A64: 26_CU_14 | C64: Coordinar i implementar les accions previstes pel PNAP del projecte POCTEFA Pyrfer + de posada en valor i dinamització de la Vall Ferrera entorn el ferro i la forja: aasitencia tècnica llançament projecte | D64: 04.3.1 | F64: 2. Cultura | G64: Contracte menor des de la DG | I64: 1.1 Planificació de la gestió i designació del lloc | J64: 6000 | K64: 0.1 | M64: Pol Alcalde Floriach | N64: No | O64: =IF(COUNTIF(Objectius!$A$2:$A$183,D64)>0,"Sí","No")
A65: 26_CU_15 | B65: 170 | C65: Coordinar i implementar les accions previstes pel PNAP del projecte POCTEFA Pyrfer + de posada en valor i dinamització de la Vall Ferrera entorn el ferro i la forja: organització fira del ferro | D65: 04.3.1 | E65: 07.1.1 | F65: 2. Cultura | G65: Contracte menor a càrrec del RAE | H65: 226.0001 - Exposicions, certàmens i altres activitats de promoció | I65: 1.5 Mesures de comunicació i sensibilització, educació i accés de visitants relacionades amb Natura 2000 | J65: 16000 | K65: 0.1 | M65: Pol Alcalde Floriach | N65: No | O65: =IF(COUNTIF(Objectius!$A$2:$A$183,D65)>0,"Sí","No")
A66: 26_CU_16 | C66: Coordinar i implementar les accions previstes pel PNAP del projecte POCTEFA Pyrfer + de posada en valor i dinamització de la Vall Ferrera entorn el ferro i la forja: excavació arqueològica | D66: 04.3.1 | E66: 07.1.1 | F66: 2. Cultura | G66: Contracte menor des de la DG | I66: Altres | J66: 16900 | K66: 0.1 | M66: Marc Garriga Lujan | N66: No | O66: =IF(COUNTIF(Objectius!$A$2:$A$183,D66)>0,"Sí","No")
A67: 26_CU_17 | C67: Coordinar i implementar les accions previstes pel PNAP del projecte POCTEFA Pyrfer + de posada en valor i dinamització de la Vall Ferrera entorn el ferro i la forja: formació en forja | D67: 04.3.1 | F67: 2. Cultura | G67: Contracte menor des de la DG | I67: Altres | J67: 5800 | K67: 0.1 | M67: Pol Alcalde Floriach | N67: No | O67: =IF(COUNTIF(Objectius!$A$2:$A$183,D67)>0,"Sí","No")
A68: 26_CU_18 | C68: Coordinar i implementar les accions previstes pel PNAP del projecte POCTEFA Pyrfer + de posada en valor i dinamització de la Vall Ferrera entorn el ferro i la forja: exposició itinerant | D68: 04.3.1 | E68: 07.1.1 | F68: 2. Cultura | G68: Contracte menor des de la DG | I68: Altres | J68: 5000 | K68: 0.1 | M68: Marc Garriga Lujan | N68: No | O68: =IF(COUNTIF(Objectius!$A$2:$A$183,D68)>0,"Sí","No")
A69: 26_CU_19 | C69: Coordinar i implementar les accions previstes pel PNAP del projecte POCTEFA Pyrfer + de posada en valor i dinamització de la Vall Ferrera entorn el ferro i la forja: material pedagogic escolar | D69: 04.3.1 | F69: 2. Cultura | G69: Contracte menor des de la DG | I69: 1.5 Mesures de comunicació i sensibilització, educació i accés de visitants relacionades amb Natura 2000 | J69: 3000 | K69: 0.1 | M69: Pol Alcalde Floriach | N69: No | O69: =IF(COUNTIF(Objectius!$A$2:$A$183,D69)>0,"Sí","No")
A70: 26_CU_20 | B70: 135 | C70: Coordinar i implementar les accions previstes pel PNAP del projecte POCTEFA Pyrfer + de posada en valor i dinamització de la Vall Ferrera entorn el ferro i la forja: compra de carbó i ferro | D70: 04.3.1 | E70: 07.1.1 | F70: 2. Cultura | G70: Contracte menor a càrrec del RAE | H70: 221.0089 - Altres subministraments | I70: Altres | J70: 3000 | K70: 0.1 | M70: Marc Garriga Lujan | N70: No | O70: =IF(COUNTIF(Objectius!$A$2:$A$183,D70)>0,"Sí","No")
A71: 26_CU_21 | B71: 164 | C71: Coordinar i implementar les accions previstes pel PNAP del projecte POCTEFA Pyrfer + de posada en valor i dinamització de la Vall Ferrera entorn el ferro i la forja: Treballs previs de forja de la Fira del Ferro Pirinenc | D71: 04.3.1 | F71: 2. Cultura | G71: Contracte menor a càrrec del RAE | H71: 227.0089 - Altres treballs realitzats per persones físiques o jurídiques | I71: Altres | J71: 8000 | K71: 0.25 | M71: Marc Garriga Lujan | N71: No | O71: =IF(COUNTIF(Objectius!$A$2:$A$183,D71)>0,"Sí","No")
A72: 26_CU_22 | B72: 76 | C72: Continuar realitzant activitats formatives de la tècnica de pedra en sec (murs, empedrats, cabanes, ..): Cursos vinculats a la pedra seca | D72: 04.3.2 | F72: 2. Cultura | G72: Contracte menor a càrrec del RAE | H72: 227.014 Serveis de formació | I72: 2.5 Mesures de manteniment i restauració d'altres agroecosistemes (inclosos els conreus) | J72: 4000 | K72: 0.25 | M72: Nil Bacardit Tudela | N72: Si | O72: =IF(COUNTIF(Objectius!$A$2:$A$183,D72)>0,"Sí","No")
A73: 26_CU_23 | B73: 98 | C73: Divulgació i foment de l'aplicació del nou manual de bones pràctiques per la rehabilitació de construccions rurals aïllades del Parc: impressió nova edició | D73: 04.3.3 | E73: 10.1.1 | F73: 2. Cultura | G73: Contracte menor a càrrec del RAE | H73: 240.0001 - Despeses de publicacions | I73: 2.5 Mesures de manteniment i restauració d'altres agroecosistemes (inclosos els conreus) | J73: 1500 | K73: 0.5 | L73: 1a edició esgotada | M73: Moises Villanueva Coello | N73: No | O73: =IF(COUNTIF(Objectius!$A$2:$A$183,D73)>0,"Sí","No")
A74: 26_CU_24 | B74: 81 | C74: Divulgació i foment de l'aplicació del nou manual de bones pràctiques per la rehabilitació de construccions rurals aïllades del Parc:xerrada de presentació a l'Alt Urgell i a les jornades de parcs i museus | D74: 04.3.3 | E74: 10.1.1 | F74: 2. Cultura | G74: Contracte menor a càrrec del RAE | H74: 227.0089 - Altres treballs realitzats per persones físiques o jurídiques | I74: 2.5 Mesures de manteniment i restauració d'altres agroecosistemes (inclosos els conreus) | J74: 600 | K74: 0.25 | M74: Marc Garriga Lujan | N74: No | O74: =IF(COUNTIF(Objectius!$A$2:$A$183,D74)>0,"Sí","No")
A75: 26_CU_25 | B75: 133 | C75: Restauració del patrimoni moble de Casa Bringué: Ventadora, bauls i fresquera | D75: 04.3.3 | F75: 2. Cultura | G75: Contracte menor a càrrec del RAE | H75: 213.0001 - Conservació, reparació i manteniment d'altre immobilitzat material | I75: Altres | J75: 2420 | K75: 0.25 | M75: Marc Garriga Lujan | N75: No | O75: =IF(COUNTIF(Objectius!$A$2:$A$183,D75)>0,"Sí","No")
A76: 26_CU_26 | C76: Executar el projecte de rehabilització de Casa Bringué de Ginestarre com espai museistic, formatiu i alberg de joventut - Licitació de l'obra | D76: 04.3.3 | E76: 06.4.5 | F76: 2. Cultura | G76: PEA Infraestructures | I76: 2.5 Mesures de manteniment i restauració d'altres agroecosistemes (inclosos els conreus) | J76: 0 | K76: 0.1 | L76: Es licita el 2026, pero com l'obra s'iniciarà el 2027, s'imputarà el cost pel 2027 | M76: Marc Garriga Lujan | N76: No | O76: =IF(COUNTIF(Objectius!$A$2:$A$183,D76)>0,"Sí","No")
A77: 26_CU_27 | C77: Mantenir la coberta vegetal de la Borda de Llosaus | D77: 04.3.3 | F77: 2. Cultura | G77: Encomana Forestal Catalana | I77: 2.5 Mesures de manteniment i restauració d'altres agroecosistemes (inclosos els conreus) | J77: 0 | K77: 0.25 | L77: Actuació a realitzar amb servei de manteniment FC | M77: Nil Bacardit Tudela | N77: No | O77: =IF(COUNTIF(Objectius!$A$2:$A$183,D77)>0,"Sí","No")
A78: 26_CU_28 | C78: Realització d'accions de conservació del patrimoni arquitectònic públic del Parc a través del servei de manteniment, obres o ajuts | D78: 04.3.3 | F78: 2. Cultura | G78: Encomana Forestal Catalana | I78: 2.5 Mesures de manteniment i restauració d'altres agroecosistemes (inclosos els conreus) | J78: 0 | K78: 0.25 | L78: Actuació a realitzar amb servei de manteniment FC | M78: Nil Bacardit Tudela | N78: Si | O78: =IF(COUNTIF(Objectius!$A$2:$A$183,D78)>0,"Sí","No")
A79: 26_CU_29 | B79: 82 | C79: Promoció i conservació de la biodiversitat cultivada del Parc | D79: 04.3.4 | F79: 2. Cultura | G79: Contracte menor a càrrec del RAE | H79: 227.0089 - Altres treballs realitzats per persones físiques o jurídiques | I79: 2.5 Mesures de manteniment i restauració d'altres agroecosistemes (inclosos els conreus) | J79: 0 | K79: 0.25 | M79: Moises Villanueva Coello | N79: No | O79: =IF(COUNTIF(Objectius!$A$2:$A$183,D79)>0,"Sí","No")
A80: 26_CU_30 | B80: 137 | C80: Donar suport a la conservació de les races locals de bestiar del Parc a través de les fires i concursos de raça - Transport dels animals de les fires ramaderes de cavall pirinenc | D80: 04.3.4 | F80: 2. Cultura | G80: Contracte menor a càrrec del RAE | H80: 223.0001 - Transports | I80: 2.4 Mesures de manteniment i restauració de prats i pastures | J80: 2400 | K80: 0.25 | M80: Nil Bacardit Tudela | N80: Si | O80: =IF(COUNTIF(Objectius!$A$2:$A$183,D80)>0,"Sí","No")
A81: 26_CU_31 | B81: 20 | C81: Donar suport a la conservació de les races locals de bestiar del Parc a través de les fires i concursos de raça - Farratge pels animals de les fires ramaderes | D81: 04.3.4 | F81: 2. Cultura | G81: Contracte menor a càrrec del RAE | H81: 221.0007 - Queviures | I81: 2.4 Mesures de manteniment i restauració de prats i pastures | J81: 2500 | K81: 0.25 | M81: Nil Bacardit Tudela | N81: Si | O81: =IF(COUNTIF(Objectius!$A$2:$A$183,D81)>0,"Sí","No")
A82: 26_CU_32 | B82: 54 | C82: Donar suport a la conservació de les races locals de bestiar del Parc a través de les fires i concursos de raça - Organització i premis pels participants de les fires ramaderes. Lots de productes locals | D82: 04.3.4 | F82: 2. Cultura | G82: Contracte menor a càrrec del RAE | H82: 226.0010 - Premis | I82: 2.4 Mesures de manteniment i restauració de prats i pastures | J82: 7500 | K82: 0.25 | M82: Marc Garriga Lujan | N82: No | O82: =IF(COUNTIF(Objectius!$A$2:$A$183,D82)>0,"Sí","No")
A83: 26_CU_33 | C83: Donar suport a la conservació de les races locals de bestiar del Parc a través de les fires i concursos de raça - Muntatge i desmuntatge dels tancats i carpes de les fires ramaderes | D83: 04.3.4 | F83: 2. Cultura | G83: Encomana Forestal Catalana | I83: 2.4 Mesures de manteniment i restauració de prats i pastures | J83: 0 | K83: 0.25 | L83: Actuació a realitzar amb servei de manteniment FC | M83: Nil Bacardit Tudela | N83: Si | O83: =IF(COUNTIF(Objectius!$A$2:$A$183,D83)>0,"Sí","No")
A84: 26_CU_34 | B84: 104.2 | C84: Divulgar i donar a conèixer les races locals de bestiar del Parc a través de diferents mitjans - Disseny, maquetació i impressió d’un plafó divulgatiu i d’un díptic informatiu sobre la mostra d’ovella xisqueta i el concurs nacional morfològic de la fira de tardor de Sort. | D84: 04.3.4 | F84: 2. Cultura | G84: Contracte menor a càrrec del RAE | H84: 240.0001 - Despeses de publicacions | I84: 2.4 Mesures de manteniment i restauració de prats i pastures | J84: 1911.8 | K84: 0.5 | M84: Pol Alcalde Floriach | N84: No | O84: =IF(COUNTIF(Objectius!$A$2:$A$183,D84)>0,"Sí","No")
A85: 26_CU_35 | B85: 83 | C85: Fomentar i divulgar les activitats de guiatge interpretatiu i educatives i xerrades que incorporen el patrimoni cultural, especialment el reconegut per la UNESCO: Realització d'activitats culturals escenificades en esdeveniments al Parc Natural de l'Alt pirineu per l'any 2026 | D85: 04.4.2 | F85: 2. Cultura | G85: Contracte menor a càrrec del RAE | H85: 227.0089 - Altres treballs realitzats per persones físiques o jurídiques | I85: 1.5 Mesures de comunicació i sensibilització, educació i accés de visitants relacionades amb Natura 2000 | J85: 4730 | K85: 0.25 | M85: Moises Villanueva Coello | N85: No | O85: =IF(COUNTIF(Objectius!$A$2:$A$183,D85)>0,"Sí","No")
A86: 26_CU_36 | B86: 162 | C86: Fomentar i divulgar les activitats de guiatge interpretatiu i educatives i xerrades que incorporen el patrimoni cultural, especialment el reconegut per la UNESCO - revisió hotel d'insectes | D86: 04.4.2 | F86: 2. Cultura | G86: Contracte menor a càrrec del RAE | H86: 227.0089 - Altres treballs realitzats per persones físiques o jurídiques | I86: 1.5 Mesures de comunicació i sensibilització, educació i accés de visitants relacionades amb Natura 2000 | J86: 790.5 | K86: 0.25 | M86: Moises Villanueva Coello | N86: No | O86: =IF(COUNTIF(Objectius!$A$2:$A$183,D86)>0,"Sí","No")
A87: 26_CU_37 | B87: 84 | C87: Realització de murals de divulgació dels valors naturals i culturals del Parc en parets d’elements paisatgístics degradats - mural de Rialp | D87: 05.2.1 | F87: 2. Cultura | G87: Contracte menor a càrrec del RAE | H87: 227.0089 - Altres treballs realitzats per persones físiques o jurídiques | I87: Altres | J87: 5500 | K87: 0.25 | M87: Marc Garriga Lujan | N87: No | O87: =IF(COUNTIF(Objectius!$A$2:$A$183,D87)>0,"Sí","No")
A88: 26_CU_38 | C88: Restauració del paisatge a través de l'eliminació d'infrasstructures obsoletes via servei de manteniment, voluntariat o ajuts | D88: 05.2.2 | F88: 2. Cultura | G88: Encomana Forestal Catalana | I88: Altres | J88: 0 | K88: 0.25 | L88: Actuació a realitzar amb servei de manteniment FC | M88: Nil Bacardit Tudela | N88: Si | O88: =IF(COUNTIF(Objectius!$A$2:$A$183,D88)>0,"Sí","No")
A89: 26_CU_39 | C89: Tramitar i retirar vehicles abandonats a l'interior del Parc | D89: 05.2.2 | F89: 2. Cultura | G89: Encomana Forestal Catalana | I89: Altres | J89: 0 | K89: 0.25 | L89: Actuació a realitzar amb servei de manteniment FC | M89: Nil Bacardit Tudela | N89: Si | O89: =IF(COUNTIF(Objectius!$A$2:$A$183,D89)>0,"Sí","No")
A90: 26_CU_40 | C90: Retirar deixalles acumulades a l'interior del Parc a través del servei de manteniment, prioritzant els espais més freqüentats i integrar-ho als plans periòdics de manteniment de la brigada | D90: 05.2.3 | F90: 2. Cultura | G90: Encomana Forestal Catalana | I90: Altres | J90: 0 | K90: 0.25 | L90: Actuació a realitzar amb servei de manteniment FC | M90: Nil Bacardit Tudela | N90: Si | O90: =IF(COUNTIF(Objectius!$A$2:$A$183,D90)>0,"Sí","No")
A91: 26_CU_41 | B91: 160 | C91: Donar suport a activitats de voluntariat de retirada de deialles - Organització del projecte Mountain Calling | D91: 05.2.3 | F91: 2. Cultura | G91: Contracte menor a càrrec del RAE | H91: 227.0089 - Altres treballs realitzats per persones físiques o jurídiques | I91: 2.4 Mesures de manteniment i restauració de prats i pastures | J91: 2500 | K91: 0.25 | M91: Moises Villanueva Coello | N91: Si | O91: =IF(COUNTIF(Objectius!$A$2:$A$183,D91)>0,"Sí","No")
A92: 26_CU_42 | B92: 159 | C92: Donar suport a activitats de voluntariat de retirada de deialles - Organització del projecte Iniciativa Rius | D92: 05.2.3 | F92: 2. Cultura | G92: Contracte menor a càrrec del RAE | H92: 227.0089 - Altres treballs realitzats per persones físiques o jurídiques | I92: 2.8 Mesures de manteniment i restauració d'hàbitats d'aigua dolça (rius, llacs i zones humides no litorals) | J92: 14500 | K92: 0.25 | M92: Moises Villanueva Coello | N92: Si | O92: =IF(COUNTIF(Objectius!$A$2:$A$183,D92)>0,"Sí","No")
A93: 26_CU_43 | C93: Fomentar el reciclatge i la minimització de generació de residus a les empreses i equipaments del Parc a través de la seva acreditació per la CETS (Fase 2) | D93: 05.2.3 | F93: 2. Cultura | G93: Altres | I93: Altres | J93: 0 | L93: A realitzar amb mitjans propis i com a aprt secretaria cETS | M93: Nuria Canals Sangra | N93: Si | O93: =IF(COUNTIF(Objectius!$A$2:$A$183,D93)>0,"Sí","No")
A94: 26_CU_44 | C94: Implementar les accions previstes al projecte POCTEFA Pyre neit per l’àmbit del Parc - Diagnosi dels fluxos migratoris d’insectes al Pirineu i els efectes de la contaminació lumínica al Parc | D94: 05.3.1 | F94: 2. Cultura | G94: Contracte menor des de la DG | I94: 1.4 Buits de coneixement i necessitats de recerca | J94: 15013.15 | K94: 0.2 | M94: Mariona Martinez Salvador | N94: No | O94: =IF(COUNTIF(Objectius!$A$2:$A$183,D94)>0,"Sí","No")
A95: 26_CU_45 | C95: Implementar les accions previstes al projecte POCTEFA Pyre neit per l’àmbit del Parc - Accions de coordinació i seguiment | D95: 05.3.1 | F95: 2. Cultura | G95: Altres | I95: 1.1 Planificació de la gestió i designació del lloc | J95: 0 | K95: 0.2 | L95: A realitzar amb mitjans propis i nova plaça contractada per al projecte | M95: Mariona Martinez Salvador | N95: No | O95: =IF(COUNTIF(Objectius!$A$2:$A$183,D95)>0,"Sí","No")
A96: 26_CU_46 | C96: Impulsar i obtenir una certificació de qualitat del cel nocturn internacional (Starlight, Darksky,..) | D96: 05.3.1 | F96: 2. Cultura | G96: Altres | I96: 1.1 Planificació de la gestió i designació del lloc | J96: 0 | K96: 0.2 | L96: A realitzar amb mitjans propis i nova plaça contractada per al projecte | M96: Mariona Martinez Salvador | N96: No | O96: =IF(COUNTIF(Objectius!$A$2:$A$183,D96)>0,"Sí","No")
A97: 26_CU_47 | B97: 85 | C97: Realitzar activitats divulgatives i educatives de la importància de conservar la qualitat del cel nocturn i reduir la contaminació lumínica - activitats d’astronomia en jornades i fires durant l’any 2026. | D97: 05.3.1 | F97: 2. Cultura | G97: Contracte menor a càrrec del RAE | H97: 227.0089 - Altres treballs realitzats per persones físiques o jurídiques | I97: 1.5 Mesures de comunicació i sensibilització, educació i accés de visitants relacionades amb Natura 2000 | J97: 1887.6 | K97: 0.25 | M97: Pol Alcalde Floriach | N97: Si | O97: =IF(COUNTIF(Objectius!$A$2:$A$183,D97)>0,"Sí","No")
A98: 26_CO_01 | C98: Participació en la definició dels objectes de conservació clau (hàbitats, espècies, processos i elements d’interès geològic) comuns a nivell de Xarxa d'ENP o clúster territorial amb el suport de la Comissió Científica | D98: 06.1.1 | F98: 3. Coneixement | G98: Altres | I98: 1.1 Planificació de la gestió i designació del lloc | J98: 0 | K98: 0.25 | L98: A realitzar amb mitjans propis | M98: Marc Garriga Lujan | N98: Si | O98: =IF(COUNTIF(Objectius!$A$2:$A$183,D98)>0,"Sí","No")
A99: 26_CO_02 | C99: Col·laboració amb la UIC per mantenir actualitzada la cartografia dels elements de conservació del Parc | D99: 06.2.1 | F99: 3. Coneixement | G99: Altres | I99: 1.1 Planificació de la gestió i designació del lloc | J99: 0 | K99: 0.25 | L99: A realitzar amb mitjans propis | M99: Mariona Martinez Salvador | N99: Si | O99: =IF(COUNTIF(Objectius!$A$2:$A$183,D99)>0,"Sí","No")
A100: 26_CO_03 | B100: 122 | C100: Foment de l'estudi de l'afectació de determinats processos naturals o activitats antròpiques en l’ENP. Seguiment de l'estat i productivitat de les pastures amb seguiment remot (NDVI) | D100: 06.2.3 | F100: 3. Coneixement | G100: Contracte menor a càrrec del RAE | H100: 227.0013 - Treballs tècnics | I100: 1.4 Buits de coneixement i necessitats de recerca | J100: 18000 | K100: 0.1 | M100: Josep Pique Palacin | N100: No | O100: =IF(COUNTIF(Objectius!$A$2:$A$183,D100)>0,"Sí","No")
A101: 26_CO_04 | B101: 73 | C101: Foment de l'estudi de l'afectació de determinats processos naturals o activitats antròpiques en l’ENP. Diagnosi de l'ús i impacte dels fàrmacs utilitzats en ramaderia extensiva sobre la biodiversitat | D101: 06.2.3 | E101: 06.2.5 | F101: 3. Coneixement | G101: Contracte menor a càrrec del RAE | H101: 227.0013 - Treballs tècnics | I101: 1.4 Buits de coneixement i necessitats de recerca | J101: 18000 | K101: 0.1 | M101: Josep Pique Palacin | N101: No | O101: =IF(COUNTIF(Objectius!$A$2:$A$183,D101)>0,"Sí","No")
...

Sheet Llistes
A1: Tipus de despesa | B1: Tipologia MAP | C1: Eix | D1: Codi eix | E1: Partides RAE | F1: Naturalesa | G1: Sí/No
A2: Contracte menor a càrrec del RAE | B2: 1.1 Planificació de la gestió i designació del lloc | C2: 1. Natura | D2: NA | E2: 201.0001 - Lloguers i cànons de material de transport | F2: Obra | G2: Sí
A3: Contracte menor des de la DG | B3: 1.2 Administració del lloc i comunicació amb les parts interessades | C3: 2. Cultura | D3: CU | E3: 203.0001 - Lloguers i cànons d'altre immobilitzat material | F3: Servei | G3: No
A4: Contracte obert (licitació des de la DG) | B4: 1.3 Seguiment, vigilància i notificació | C4: 3. Coneixement | D4: CO | E4: 210.0001 - Conservació, reparació i manteniment de terrenys | F4: Subministrament
A5: PEA Infraestructures | B5: 1.4 Buits de coneixement i necessitats de recerca | C5: 4. Desenvolupament local | D5: DE | E5: 211.0001 - Conservació, reparació, manteniment de material de transport
A6: PEA Forestal Catalana | B6: 1.5 Mesures de comunicació i sensibilització, educació i accés de visitants relacionades amb Natura 2000 | C6: 5. Ús públic i social | D6: US | E6: 213.0001 - Conservació, reparació i manteniment d'altre immobilitzat material
A7: Encomana Forestal Catalana | B7: 2.1 Mesures de manteniment i restauració d'aigües marines i costeres (inclou llacunes litorals) | C7: 6. Educació, voluntariat i comunicació | D7: ED | E7: 214.0001 - Altres despeses de conservació, reparació i manteniment
A8: Encàrrec directe Infraestructures | B8: 2.2 Mesures de manteniment i restauració de matollars | C8: 7. Gestió i administració | D8: GE | E8: 215.0001 - Farmaciola
A9: Encàrrec directe Forestal Catalana | B9: 2.3 Mesures de manteniment i restauració de torberes | E9: 220.0001 - Material ordinari no inventariable
A10: Encàrrec directe CREAF | B10: 2.4 Mesures de manteniment i restauració de prats i pastures | E10: 220.0002 - Premsa, revistes, llibres i altres publicacions
A11: Encàrrec directe CTFC | B11: 2.5 Mesures de manteniment i restauració d'altres agroecosistemes (inclosos els conreus) | E11: 221.0001 - Aigua i energia
A12: Encàrrec directe TRAGSA | B12: 2.6 Mesures de manteniment i restauració de boscos i superfícies forestals | E12: 221.0002 - Combustible per a mitjans de transport
A13: Contracte programa CTFC | B13: 2.7 Mesures de conservació i restauració d'hàbitats rocosos, dunes i terres de vegetació esparsa | E13: 221.0003 - Vestuari
A14: Contracte programa CREAF | B14: 2.8 Mesures de manteniment i restauració d'hàbitats d'aigua dolça (rius, llacs i zones humides no litorals) | E14: 221.0005 - Farmaciola
A15: Mitjans propis | B15: 2.9 Mesures de conservació i restauració de coves i altres no inclosos als anteriors | E15: 221.0006 - Compres de mercaderies i matèries primes
A16: Altres | B16: 2.B Mesures adicionals d'«infraestructura verda» més enllà de Natura 2000 | E16: 221.0007 - Queviures
B17: 3.1 Mesures i programes específics de conservació d'espècies no incloses en altres apartats | E17: 221.0089 - Altres subministraments
B18: 3.2 Prevenció, mitigació o compensació dels danys ocasionats per les espècies protegides | E18: 222.0001 - Despeses postals, missatgeria i altres similars
B19: Altres | E19: 223.0001 - Transports
E20: 225.0001 - Tributs i taxes
E21: 226.0003 - Publicitat, difusió i campanyes institucionals
E22: 226.0005 - Organització de reunions, conferències i cursos
E23: 226.0010 - Premis
E24: 226.0011 - Formació del personal propi
E25: 226.0039 - Despeses per serveis bancàris
E26: 226.0040 - Inscripció com a soci o altra figura a organismes o a entitats de caràcter associatiu
E27: 226.0089 - Altres despeses diverses
E28: 227.0001 - Neteja i sanejament
E29: 227.0003 - Valoracions i peritatges
E30: 227.0007 - Gestió dels centres i serveis
E31: 227.0013 - Treballs tècnics
... E40: 670.0002 - Inversions en altre immobilitzat material

Sheet Objectius
A1: Codi | B1: Objectiu operatiu (estàndard) | C1: Objectiu concret a l'espai | D1: Eix | E1: Codi eix | F1: Objectiu general | G1: Objectiu estratègic
A2: 01.1.1 | B2: Implementar i executar plans de gestió específics per a hàbitats i espècies de conservació prioritària dins l'ENP | C2: Implementar i executar plans de gestió específics per a hàbitats i espècies de conservació prioritària dins l'ENP | D2: 1. Natura | E2: NA | F2: CONSERVAR LA NATURA i restaurar els ecosistemes, els processos naturals i seminaturals, la biodiversitat i la geodiversitat associada. | G2: Adequar i fer eficient la conservació dels elements objecte de gestió prioritària marcats per la DG a l'ENP
A3: 01.1.2 | B3: Adaptar i executar plans de gestió específics per a elements geològics de conservació prioritària dins l'ENP | C3: Adaptar i executar plans de gestió específics per a elements geològics de conservació prioritària dins l'ENP | D3: 1. Natura | E3: NA | F3: CONSERVAR LA NATURA i restaurar els ecosistemes, els processos naturals i seminaturals, la biodiversitat i la geodiversitat associada. | G3: Executar les mesures de gestió directa previstes en els intruments de planificació per la conservació i la gestió adaptativa dels elements clau de l'ENP
A4: 01.2.1 | B4: Implementar la metodologia de gestió adaptativa (Estàndards Oberts de Gestió Adaptativa a Catalunya) en tots els processos de l'ENP | C4: Implementar la metodologia de gestió adaptativa (Estàndards Oberts de Gestió Adaptativa a Catalunya) en tots els processos de l'ENP | D4: 1. Natura | E4: NA | F4: CONSERVAR LA NATURA i restaurar els ecosistemes, els processos naturals i seminaturals, la biodiversitat i la geodiversitat associada. | G4: Executar les mesures de gestió directa previstes en els intruments de planificació per la conservació i la gestió adaptativa dels elements clau de l'ENP
A5: 01.2.2 | B5: Executar les mesures previstes en els plans de conservació o recuperació d'espècies amenaçades de forma coordinada amb el Servei de Flora i Fauna en l'àmbit de l'ENP | C5: Executar les mesures previstes en els plans de conservació o recuperació d'espècies amenaçades de forma coordinada amb el Servei de Flora i Fauna en l'àmbit de l'ENP | D5: 1. Natura | E5: NA | F5: CONSERVAR LA NATURA i restaurar els ecosistemes, els processos naturals i seminaturals, la biodiversitat i la geodiversitat associada. | G5: Executar les mesures de gestió directa previstes en els intruments de planificació per la conservació i la gestió adaptativa dels elements clau de l'ENP
A6: 01.2.3 | B6: Executar les mesures de gestió previstes en els plans de control i erradicació d'espècies exòtiques de forma coordinada amb el Servei de Flora i Fauna en l'àmbit de l'ENP | C6: Executar les mesures de gestió previstes en els plans de control i erradicació d'espècies exòtiques de forma coordinada amb el Servei de Flora i Fauna en l'àmbit de l'ENP | D6: 1. Natura | E6: NA | F6: CONSERVAR LA NATURA i restaurar els ecosistemes, els processos naturals i seminaturals, la biodiversitat i la geodiversitat associada. | G6: Executar les mesures de gestió directa previstes en els intruments de planificació per la conservació i la gestió adaptativa dels elements clau de l'ENP
A7: 01.2.4 | B7: Desplegar els objectius i tasques recollits en els instruments de referència i compromisos internacionals | C7: Desplegar els objectius i tasques recollits en els instruments de referència i compromisos internacionals | D7: 1. Natura | E7: NA | F7: CONSERVAR LA NATURA i restaurar els ecosistemes, els processos naturals i seminaturals, la biodiversitat i la geodiversitat associada. | G7: Executar les mesures de gestió directa previstes en els intruments de planificació per la conservació i la gestió adaptativa dels elements clau de l'ENP
A8: 01.3.1 | B8: Identificar espais pel foment de la dinàmica natural i l'aprofitament no extractiu | C8: Identificar espais pel foment de la dinàmica natural i l'aprofitament no extractiu | D8: 1. Natura | E8: NA | F8: CONSERVAR LA NATURA i restaurar els ecosistemes, els processos naturals i seminaturals, la biodiversitat i la geodiversitat associada. | G8: Afavorir ecosistemes complexes, resilients, i d'alta biodiversitat per garantir la recuperació dels processos ecosistèmics
A9: 01.3.2 | B9: Afavorir la maduresa dels sistemes forestals | C9: Afavorir la maduresa dels sistemes forestals | D9: 1. Natura | E9: NA | F9: CONSERVAR LA NATURA i restaurar els ecosistemes, els processos naturals i seminaturals, la biodiversitat i la geodiversitat associada. | G9: Afavorir ecosistemes complexes, resilients, i d'alta biodiversitat per garantir la recuperació dels processos ecosistèmics
A10: 01.3.3 | B10: Procurar un règim de pertorbacions que afavoreixi l'ús sostenible dels recursos, la biodiversitat i el funcionament del ecosistemes | C10: Procurar un règim de pertorbacions que afavoreixi l'ús sostenible dels recursos, la biodiversitat i el funcionament del ecosistemes | D10: 1. Natura | E10: NA | F10: CONSERVAR LA NATURA i restaurar els ecosistemes, els processos naturals i seminaturals, la biodiversitat i la geodiversitat associada. | G10: Afavorir ecosistemes complexes, resilients, i d'alta biodiversitat per garantir la recuperació dels processos ecosistèmics
A11: 01.3.4 | B11: Restaurar la dinàmica natural dels rius i altres ecosistemes aquàtics que estiguin dregradats | C11: Restaurar la dinàmica natural dels rius i altres ecosistemes aquàtics que estiguin dregradats | D11: 1. Natura | E11: NA | F11: CONSERVAR LA NATURA i restaurar els ecosistemes, els processos naturals i seminaturals, la biodiversitat i la geodiversitat associada. | G11: Afavorir ecosistemes complexes, resilients, i d'alta biodiversitat per garantir la recuperació dels processos ecosistèmics
A12: 01.3.5 | B12: Fomentar mosaics de paisatges resilients i diversos | C12: Fomentar mosaics de paisatges resilients i diversos | D12: 1. Natura | E12: NA | F12: CONSERVAR LA NATURA i restaurar els ecosistemes, els processos naturals i seminaturals, la biodiversitat i la geodiversitat associada. | G12: Afavorir ecosistemes complexes, resilients, i d'alta biodiversitat per garantir la recuperació dels processos ecosistèmics
... A183: 16.6.2 | B183: Gestió de personal | C183: Dotació de personal estructural del parc | D183: 7. Gestió i administració | E183: GE | F183: MILLORAR L'EFICIÈNCIA de la gestió administrativa | G183: Gestionar recursos humans

Sheet Gestors
A1: Gestors de l'espai
A2: Daniel Maresma Fernandez
A3: Josep Pique Palacin
A4: Marc Garriga Lujan
A5: Maria de las Merce Frade Palau
A6: Mariona Martinez Salvador
A7: Moises Villanueva Coello
A8: Neus Artigas Piñero
A9: Nil Bacardit Tudela
A10: Nuria Canals Sangra
A11: Oriol Grau Fernandez
A12: Oriol Martinez Cañas
A13: Pol Alcalde Floriach
